Workbook

Sheet PMR-Data
A2: MONTH | B2: (Multiple Items)
A3: YEAR | B3: (Multiple Items)
A5: PR# | B5: Purpose | C5: End-User | D5: Modality | E5: Delivery Date | F5: IAR Date | G5: Fund Code | H5: Class | I5: Status | J5: Sum of Estimated Total | K5: Sum of Total
A6: 202-013A | B6: supplies for the repair & maintenance of the building | C6: JERSHON RALPH F. CASTANO | D6: SVP | E6: August 23, 2021 | F6: August 23, 2021 | G6: 101 | H6: MOOE | I6: complete | J6: 85520 | K6: 65665
A7: 2021-001A | B7: snacks for the "Internal Quality Audit" on January 19-21, 2021 | J7: 17850 | K7: 17850
A8: 2021-002 | B8: Supply and installation of CCTV for Academic Building, Dormitory and Agriculture Building | C8: ALETH A. MEORA | D8: SVP | E8: April 27, 2021 | F8: May 26, 2021` | G8: 101 | H8: CO | I8: complete | J8: 435000 | K8: 397860
A9: 2021-002A | B9: to be used in the different activities and internet communication needs of BSC | C9: RANDALL G. CASTILLO | D9: SVP | E9: 5/19 & 7/19/2021 | F9: 5/26 & 7/21/2021 | G9: 101 | H9: (blank) | I9: complete | J9: 25500 | K9: 25480
A10: 2021-003 | B10: Purchase of Academic Equipment | C10: ALETH A. MEORA | D10: SVP | E10: 5/19 & 7/19/2021 | F10: 5/19 & 7/21/2021 | G10: 101 | H10: CO | I10: complete | J10: 947218.62 | K10: 928620
A11: 2021-003A | B11: for PBB compliance specifically transparency seal and BSC publication | C11: RANDALL G. CASTILLO | D11: SVP | E11: February 16, 2021 | F11: March 2, 2021 | G11: 165 | H11: MOOE | I11: complete | J11: 49000 | K11: 45560
A12: 2021-004 | B12: for the purchase of Academic Equipments | C12: ALETH A. MEORA | D12: SVP | E12: January 12, 2021 | F12: April 27, 2021 | G12: 101 | H12: CO | I12: complete | J12: 972105.5 | K12: 791000
A13: 2021-004A | B13: for the purchase of enrollment forms | C13: RHEA ANGELLICA B. ADDATU | D13: SVP | E13: August 23, 2021 | F13: August 23, 2021 | G13: 101 | H13: (blank) | I13: (blank) | J13: 22500 | K13: 22500
A14: 2021-005 | B14: Purchase of Academic Equipment | C14: ALETH A. MEORA | D14: SVP | E14: 44396 | F14: 44403 | G14: 101 | H14: CO | I14: reimbursement | J14: 378961.7 | K14: 359780
A15: 2021-005A | B15: to be used in the different activities and internet communication needs of BSC | C15: RANDALL G. CASTILLO | D15: SVP | E15: May 19, 2021 | F15: May 26, 2021 | G15: 101 | H15: MOOE | I15: complete | J15: 30250 | K15: 29960
A16: 2021-006 | B16: Supply and Delivery of Academic Equipment | C16: ALETH A. MEORA | D16: SVP | E16: January 12, 2021 | F16: January 25, 2021 | G16: 101 | H16: CO | I16: complete | J16: 315813.75 | K16: 195700
E17: January 25, 2021 | F17: January 25, 2021 | G17: 101 | H17: CO | I17: complete | J17: 45000 | K17: 42000
A18: 2021-006A | B18: for the ISO Activity Management Review on Feb. 3, 2021 | C18: ROMINA KATRINA C. BAYARAS | D18: SVP | E18: 44230 | F18: February 16, 2021 | G18: 164 | H18: MOOE | I18: complete | J18: 14000 | K18: 11800
A19: 2021-007A | B19: Internet data/Regular load Allocation of Administrative & Finance staff of the college to support online submission of reports & other related activities for the Fiscal Year 2021 | C19: DJOVI R. DURANTE | D19: SVP | E19: March 29, 2021 | F19: March 31, 2021 | G19: 101 | H19: MOOE | I19: complete | J19: 107880 | K19: 107880
A20: 2021-008A | B20: for the "ISO Documentation" | C20: ROMINA KATRINA C. BAYARAS | D20: SVP | E20: March 15, 2021 | F20: March 15, 2021 | G20: 164 | H20: MOOE | I20: complete | J20: 3960 | K20: 3885
A21: 2021-009 | B21: Purchase of Academic Furniture Fixtures | C21: ALETH A. MEORA | D21: SVP | E21: August 23, 2021 | F21: August 23, 2021 | G21: 101 | H21: MOOE | I21: complete | J21: 200000 | K21: 199680
A22: 2021-009A | B22: stamp use for the filing of ISO documents | C22: ROMINA KATRINA C. BAYARAS | D22: SVP | E22: - | F22: - | G22: 165 | H22: (blank) | I22: FAILED | J22: 28000 | K22: 0
A23: 2021-0100 | B23: for the Implementation of "ADOPT through Varied R & D of Ivatan Endemic Resources" research project | C23: JANE S. CASTILLO | D23: SVP | E23: August 23, 2021 | F23: August 23, 2021 | G23: 165 | H23: MOOE | I23: for delivery | J23: 30950 | K23: 29315
A24: 2021-0101 | B24: office supplies for the Administrative & Finance Services Units | C24: DJOVI R. DURANTE | D24: SVP | E24: August 23, 2021 | F24: August 23, 2021 | G24: 165 | H24: MOOE | I24: for delivery | J24: 30840 | K24: 28941.9
A25: 2021-0102 | B25: supplies for Budget office | C25: BRYAN DAVE P. REVILLA | D25: SVP | E25: August 23, 2021 | F25: August 23, 2021 | G25: 101 | H25: MOOE | I25: for delivery | J25: 3500 | K25: 2990
A26: 2021-0103 | B26: supplies for Budget office | C26: BRYAN DAVE P. REVILLA | D26: SVP | E26: July 1, 2021 | F26: July 1, 2021 | G26: 101 | H26: MOOE | I26: complete | J26: 790 | K26: 600
A27: 2021-0104 | B27: supplies for the Budget office | C27: BRYAN DAVE P. REVILLA | D27: SVP | E27: August 23, 2021 | F27: August 23, 2021 | G27: 101 | H27: MOOE | I27: for delivery | J27: 1000 | K27: 800
A28: 2021-0105 | B28: repair of 2 units floor type airconditioner at Faculty Room | C28: JERSHON RALPH F. CASTANO | D28: SVP | E28: August 23, 2021 | F28: August 23, 2021 | G28: (blank) | H28: (blank) | I28: FAILED | J28: 13000
A29: 2021-0106 | B29: GSO Supplies | C29: JERSHON RALPH F. CASTANO | D29: SVP | E29: July 19 & 26, 2021 | F29: July 21 & 26, 2021 | G29: 101 | H29: MOOE | I29: complete | J29: 10950 | K29: 8314
A30: 2021-0107 | B30: GSO Supplies | C30: JERSHON RALPH F. CASTANO | D30: SVP | E30: 44399 | F30: 44411 | G30: 101 | H30: MOOE | I30: reimbursement | J30: 18500 | K30: 15780
A31: 2021-0108 | B31: Snack for the Preparatory Board Meeting on June 25, 2021 at 10:00 a.m | C31: GERZON R. ABAD | D31: SVP | E31: August 23, 2021 | F31: August 23, 2021 | G31: (blank) | H31: (blank) | I31: FAILED | J31: 3000 | K31: 0
A32: 2021-0109 | B32: PM snack and dinner for the 52nd Board of Trustees Meeting on June 25, 2021 | C32: GERZON R. ABAD | D32: SVP | E32: June 25, 2021 | F32: 44377 | G32: 101 | H32: MOOE | I32: reimbursement | J32: 13000 | K32: 9000
A33: 2021-010A | B33: ink use for enrollment | C33: RHEA ANGELLICA B. ADDATU | D33: SVP | E33: August 23, 2021 | F33: August 23, 2021 | G33: 101 | H33: (blank) | I33: FAILED | J33: 1500
A34: 2021-0110 | B34: Lunch, PM Snack and Dinner of Commissioner Lilian A. De Las Llagas and Staff for the 52nd BOT Meeting on 25 June 2021 | C34: GERZON R. ABAD | D34: SVP | E34: August 23, 2021 | F34: August 23, 2021 | G34: (blank) | H34: (blank) | I34: reimbursement | J34: 12597.5 | K34: 12597.5
A35: 2021-0111 | B35: repair & maintenance of A/C units of Registrar's, Cashier's, Accountant's & President's office | C35: JERSHON RALPH F. CASATANO | D35: SVP | E35: August 23, 2021 | F35: August 23, 2021 | G35: 101 | H35: MOOE | I35: on-going | J35: 8000 | K35: 8000
A36: 2021-0112 | B36: supplies for the rewiring of faculty room electrical system | C36: JERSHON RALPH F. CASATANO | D36: SVP | E36: July 21, 2021 | F36: July 26, 2021 | G36: 101 | H36: MOOE | I36: complete | J36: 23700 | K36: 21624
A37: 2021-0113 | B37: for the purchase of Semi-expendable equipments purposes | C37: JERSHON RALPH F. CASATANO | D37: SVP | E37: August 23, 2021 | F37: August 23, 2021 | G37: 101 | H37: MOOE | I37: on-going | J37: 10000 | K37: 10000
A38: 2021-011A | B38: for the Pre Assessment Audit Plan on Feb. 10-11, 2021 | C38: ROMINA KATRINA C. BAYARAS | D38: SVP | E38: February 10-11, 2021 | F38: March 2, 2021 | G38: 164 | H38: MOOE | I38: complete | J38: 7500 | K38: 7125
A39: 2021-012A | B39: supplies for the repair & maintenance of transportation vehicle | C39: JERSHON RALPH F. CASTANO | D39: SVP | E39: March 31, 2021 | F39: April 5, 2021 | G39: 101 | H39: MOOE | I39: on-going | J39: 49399.99 | K39: 42550
A40: 2021-013 | B40: Puchase of drafting tables and chairs for the Academiic Furnitures and Fixtures | C40: ALETH A. MEORA | D40: SVP | E40: January 26, 2021 | F40: January 26, 2021 | G40: 101 | H40: CO | I40: complete | J40: 277500 | K40: 195000
A41: 2021-014A | B41: office machinery & equipment | C41: JERSHON RALPH F. CASTANO | D41: SVP | E41: March 29, 2021 | F41: March 30, 2021 | G41: 101 | H41: MOOE | I41: complete | J41: 47002 | K41: 42500
A42: 2021-015A | B42: supplies for janitorial services | C42: JERSHON RALPH F. CASTANO | D42: SVP | E42: April 15, 2021 | F42: April 15, 2021 | G42: 101 | H42: MOOE | I42: complete | J42: 5000 | K42: 3000
E43: March 30, 2021 | F43: April 15, 2021 | G43: 101 | H43: MOOE | I43: complete | J43: 15000 | K43: 15200
A44: 2021-016A | B44: AM snacks for the meeting on the Assessment of the Conduct of Flexible Learning in the 1st Semester of SY 2020-2021 | C44: ANGELITA H. VARGAS | D44: SVP | E44: February 16, 2021 | F44: March 24, 2021 | G44: 101 | H44: MOOE | I44: complete | J44: 7950 | K44: 7950
A45: 2021-017A | B45: snacks & meals for the Administrative & Finance Conference on the finalization of FY 2021 targets and deliverables | C45: DJOVI R. DURANTE | D45: SVP | E45: February 23, 2021 | F45: March 1, 2021 | G45: 101 | H45: MOOE | I45: complete | J45: 19250 | K45: 16275
A46: 2021-018A | B46: snacks & dinner for the 51st Board meeting on Feb. 24, 2021 | C46: GERZON R. ABAD | D46: SVP | E46: February 24, 2021 | F46: March 9, 2021 | G46: 101 | H46: MOOE | I46: complete | J46: 10200 | K46: 8330
A47: 2021-019A | B47: use for National Women's Month Celebration | C47: JENNY S. ALINA | D47: SVP | E47: March 29, 2021 | F47: March 29, 2021 | G47: 101 | H47: MOOE | I47: complete | J47: 5320 | K47: 5320
A48: 2021-020 | B48: seed propagation for the Production of High Value Crop (HVC) Seess & Seedling in Batanes under the Bayanihan II project | C48: ROMEL A. RATERTA | D48: (blank) | E48: August 23, 2021 | F48: August 23, 2021 | G48: (blank) | H48: (blank) | I48: FAILED | J48: 259100 | K48: 0
A49: 2021-021 | B49: supplies for the National Women's Month Celebration | C49: JENNY S. ALINA | D49: SVP | E49: March 29, 2021 | F49: March 30, 2021 | G49: 101 | H49: MOOE | I49: complete | J49: 1170 | K49: 735
A50: 2021-022 | B50: supplies & materials for the installation of 3 units television | C50: JERSHON RALPH F. CASTANO | D50: (blank) | E50: August 23, 2021 | F50: August 23, 2021 | G50: (blank) | H50: (blank) | I50: FAILED | J50: 4500 | K50: 0
A51: 2021-023 | B51: supplies & materials for the connection of 3 units television | C51: JERSHON RALPH F. CASTANO | D51: (blank) | E51: August 23, 2021 | F51: August 23, 2021 | G51: (blank) | H51: (blank) | I51: FAILED | J51: 5200 | K51: 0
A52: 2021-024 | B52: stamp use for the filing of ISO documents | C52: ROMINA KATRINA C. BAYARAS | D52: SVP | E52: May 7, 2021 | F52: May 19, 2021 | G52: 164 | H52: MOOE | I52: complete | J52: 40000 | K52: 40000
A53: 2021-025 | B53: stamp to be used in the office of the President & Office of the Board Sec | C53: GERZON R. ABAD | D53: SVP | E53: June 2, 2021 | F53: June 10, 2021 | G53: 101 | H53: (blank) | I53: complete | J53: 8000 | K53: 8000
A54: 2021-026 | B54: snacks & lunch for the "Records Management System Echo Seminar on March 23, 2021 | C54: ROMINA KATRINA C. BAYARAS | D54: SVP | E54: April 8, 2021 | F54: April 12, 2021 | G54: 101 | H54: MOOE | I54: complete | J54: 17500 | K54: 14750
A55: 2021-027 | B55: meals & snacks for the FY 2022 Budget Review & Consultation on March 16, 2021 | C55: BRYAN DAVE P. REVILLA | D55: SVP | E55: March 16, 2021 | F55: March 26, 2021 | G55: 101 | H55: MOOE | I55: complete | J55: 7700 | K55: 6930
A56: 2021-028 | B56: for preventive maintenance of BSC ICT Equipment | C56: RANDALL G. CASTILLO | D56: (blank) | E56: August 23, 2021 | F56: August 23, 2021 | G56: (blank) | H56: (blank) | I56: FAILED | J56: 42000 | K56: 0
A57: 2021-029 | B57: for preventive maintenance of BSC ICT Equipment | C57: RANDALL G. CASTILLO | D57: (blank) | E57: August 23, 2021 | F57: August 23, 2021 | G57: (blank) | H57: (blank) | I57: pending | J57: 48250 | K57: 0
A58: 2021-030 | B58: Snacks during the National Women's Month Celebration | C58: JENNY S. ALINA | D58: SVP | E58: March 25, 2021 | F58: May 4, 2021 | G58: 101 | H58: MOOE | I58: complete | J58: 11100 | K58: 10730
A59: 2021-031 | B59: for National Womens Month Celebration activity | C59: JENNY S. ALINA | D59: (blank) | E59: August 23, 2021 | F59: August 23, 2021 | G59: (blank) | H59: (blank) | I59: (blank) | J59: 12750 | K59: 12750
A60: 2021-032 | B60: Snacks and lunch during the Administrative Council meeting on March 31, 2021 | C60: GERZON R. ABAD | D60: SVP | E60: March 31, 2021 | F60: March 31, 2021 | G60: 101 | H60: MOOE | I60: complete | J60: 18200 | K60: 17500
A61: 2021-033 | B61: Snacks and Lunch during the Academic Council meeting on March 30, 2021 | C61: GERZON R. ABAD | D61: SVP | E61: March 30, 2021 | F61: March 30, 2021 | G61: 101 | H61: MOOE | I61: complete | J61: 24700 | K61: 23750
A62: 2021-034 | B62: seed propagation for the Production of High Value Crop (HVC) Seess & Seedling in Batanes under the Bayanihan II project | C62: ROMEL A. RATERTA | D62: SVP | E62: May 31, 2021 | F62: June 10, 2021 | G62: 165 | H62: MOOE | I62: complete | J62: 60000 | K62: 61200
E63: August 23, 2021 | F63: June 10, 2021 | G63: 165 | H63: MOOE | I63: complete | J63: 529100 | K63: 467600
A64: 2021-035 | B64: for the purchase of Semi-Expendable Office Supply purposes | C64: ALETH A. MEORA | D64: (blank) | E64: August 23, 2021 | F64: August 23, 2021 | G64: (blank) | H64: (blank) | I64: FAILED | J64: 55200 | K64: 0
A65: 2021-036 | B65: For the purchase of office equipment | C65: ALETH A. MEORA | D65: (blank) | E65: May 31, 2021 | F65: June 1, 2021 | G65: 101 | H65: (blank) | I65: complete | J65: 85000 | K65: 56025
G66: (blank) | H66: (blank) | I66: complete | J66: 70000 | K66: 43425
A67: 2021-037 | B67: For the purchase of office equipment | C67: ALETH A. MEORA | D67: SVP | E67: June 30, 2021 | F67: July 1, 2021 | G67: 101 | H67: CO | I67: complete | J67: 319140 | K67: 279976.5
A68: 2021-038 | B68: For the purchase of semi-expendable equipment | C68: ALETH A. MEORA | D68: SVP | E68: June 10, 2021 | F68: June 11, 2021 | G68: 101 | H68: MOOE | I68: complete | J68: 637300 | K68: 633015
A69: 2021-039 | B69: for the purchase of Academic furnitures & fixtures purposes | C69: ALETH A. MEORA | D69: Public Bidding | E69: August 23, 2021 | F69: August 23, 2021 | G69: (blank) | H69: (blank) | I69: (blank) | J69: 980000 | K69: 0
A70: 2021-040 | B70: Snacks during the Expanded Finance Committee Meeting on April 13, 2021 | C70: GERZON R. ABAD | D70: SVP | E70: April 13, 2021 | F70: April 22, 2021 | G70: 101 | H70: MOOE | I70: complete | J70: 2550 | K70: 1445
A71: 2021-041 | B71: for back-up and saving documents purposes | C71: ANGELITA H. VARGAS | D71: SVP | E71: 44384 | F71: 44384 | G71: 101 | H71: MOOE | I71: completed | J71: 168000 | K71: 139720
A72: 2021-042 | B72: communication expenses in the implementation of the Learning Continuity Plan | C72: ANGELITA H. VARGAS | D72: SVP | E72: June 9, 2021 | F72: June 29, 2021 | G72: 101 | H72: MOOE | I72: complete | J72: 171680 | K72: 171400
A73: 2021-043 | B73: Supplies and materials for Sports Development | C73: WILLIAM POL M. MAGGAY | D73: SVP | E73: August 23, 2021 | F73: August 23, 2021 | G73: 165 | H73: MOOE | I73: FAILED | J73: 3300 | K73: 0
A74: 2021-044 | B74: supplies/materials use for product development | C74: JANE S. CASTILLO | D74: SVP | E74: May 31 & July 1, 2021 | F74: June 10 & July 1, 2021 | G74: 165 | H74: MOOE | I74: complete | J74: 22625 | K74: 22170
A75: 2021-045 | B75: supplies/materials use for product development | C75: JANE S. CASTILLO | D75: SVP | E75: August 23, 2021 | F75: August 23, 2021 | G75: 165 | H75: MOOE | I75: for delivery | J75: 2000 | K75: 2000
A76: 2021-046 | B76: supplies/materials use for product development | C76: JANE S. CASTILLO | D76: SVP | E76: May 20, 2021 | F76: May 26, 2021 | G76: 165 | H76: MOOE | I76: complete | J76: 4500 | K76: 4500
A77: 2021-047 | B77: supplies/materials use for product development | C77: JANE S. CASTILLO | D77: SVP | E77: May 4, 2021 | F77: May 4, 2021 | G77: 165 | H77: MOOE | I77: complete | J77: 3000 | K77: 2650
A78: 2021-048 | B78: For President's Office use | C78: GERZON R. ABAD | D78: SVP | E78: May 20, 2021 | F78: May 26, 2021 | G78: 101 | H78: MOOE | I78: complete | J78: 3500 | K78: 2900
A79: 2021-049 | B79: Supplies for operational use of the Procurement Office | C79: ANNE MARIELLE V. TEVES | D79: SVP | E79: June 2 & July 7, 2021 | F79: June 10 & July 7, 2021 | G79: 101 | H79: MOOE | I79: partial delivery | J79: 14500 | K79: 14800
E80: August 23, 2021 | F80: August 23, 2021 | G80: 101 | H80: MOOE | I80: for delivery | J80: 22580 | K80: 21860
A81: 2021-050 | B81: replacement of defective HDD of ACER ASPIRE 3 | C81: JERSHON RALPH F. CASTANO | D81: SVP | E81: May 25, 2021 | F81: May 26, 2021 | G81: 101 | H81: MOOE | I81: complete | J81: 4500 | K81: 3800
A82: 2021-051 | B82: for office supplies | C82: WILLIAM JO SE M. BILLOTE | D82: SVP | E82: July 1, 2021 | F82: June 1 & July 1, 2021 | G82: 165 | H82: MOOE | I82: complete | J82: 39000 | K82: 36750
A83: 2021-052 | B83: for office supply | C83: WILLIAM JO SE M. BILLOTE | D83: (blank) | E83: August 23, 2021 | F83: August 23, 2021 | G83: (blank) | H83: (blank) | I83: FAILED | J83: 6000 | K83: 0
A84: 2021-053 | B84: use for office supplies | C84: WILLIAM JO SE M. BILLOTE | D84: SVP | E84: May 26, 2021 | F84: May 26, 2021 | G84: 165 | H84: MOOE | I84: complete | J84: 1450 | K84: 1400
A85: 2021-054 | B85: supplies & equuipment for the installation of split type | C85: JERSHON RALPH F. CASTANO | D85: SVP | E85: August 23, 2021 | F85: August 23, 2021 | G85: 101 | H85: MOOE | I85: on going | J85: 30000 | K85: 28020
A86: 2021-055 | B86: food for the BSC employees during the Tree Planting Activity at "Rakuh A Payaman" in Mahatao, Batanes 7:00am | C86: ANGELITA H. VARGAS | D86: SVP | E86: April 30, 2021 | F86: April 30, 2021 | G86: 101 | H86: MOOE | I86: complete | J86: 25000 | K86: 24900
A87: 2021-056 | B87: communication expenses | C87: XINA V. VINALAY | D87: (blank) | E87: August 23, 2021 | F87: August 23, 2021 | G87: (blank) | H87: (blank) | I87: (blank) | J87: 9880 | K87: 0
A88: 2021-057 | B88: for office supply | C88: ANDREI JOHN S. CORDOVA | D88: SVP | E88: June 2 & July 19, 2021 | F88: June 10 & July 26, 2021 | G88: 165 | H88: MOOE | I88: complete | J88: 13200 | K88: 12390
A89: 2021-058 | B89: snacks & lunch for the 2nd Quarter Performance Review & Regular meeting (May 18, 2021) | C89: DJOVI R. DURANTE | D89: SVP | E89: May 18, 2021 | F89: June 1, 2021 | G89: 101 | H89: MOOE | I89: complete | J89: 15700 | K89: 15400
A90: 2021-059 | B90: to keep update on the development of training/program for sports development | C90: WILLIAM POL M. MAGGAY | D90: SVP | E90: May 25, 2021 | F90: May 26, 2021 | G90: 165 | H90: MOOE | I90: complete | J90: 3300 | K90: 2800
A91: 2021-060 | B91: Use for mailing report of grades to parents, request credentials, Form 137 | C91: MAGDALENA V. BALLES | D91: SVP | E91: July 1, 2021 | F91: July 1, 2021 | G91: 165 | H91: MOOE | I91: for delivery | J91: 3000 | K91: 2950
A92: 2021-061 | B92: lunch & snacks for the Lab-Trip Training on May 6 and 7, 2021 at BSC | C92: FERDINAND BULUSAN | D92: SVP | E92: May 6 & 7, 2021 | F92: 44323 | G92: 165 | H92: MOOE | I92: complete | J92: 10500 | K92: 10425
A93: 2021-062 | B93: for office consumption (office supplies) | C93: WILLIAM JO SE M. BILLOTE | D93: SVP | E93: May 25 & July 5, 2021 | F93: May 26 & July 7, 2021 | G93: 101 | H93: MOOE | I93: complete | J93: 10000 | K93: 6270
A94: 2021-063 | B94: Installation of 2 units grrenhouse (4 x 12 sq. m) | C94: ROMEL A. RATERTA | D94: SVP | E94: August 23, 2021 | F94: August 23, 2021 | G94: (blank) | H94: (blank) | I94: on going | J94: 985000 | K94: 886500
A95: 2021-064 | B95: repair & maintenance of the cables of old 16 channel CCTV located at Supply Office | C95: JERSHON RALPH F. CASTANO | D95: SVP | E95: July 2, 2021 | F95: July 2, 2021 | G95: 101 | H95: MOOE | I95: complete | J95: 29000 | K95: 14860
A96: 2021-065 | B96: materials for the National Higher Education Week Competition (May 17-21, 2021) | C96: ELEIN T. ESPERANZA | D96: SVP | E96: May 17, 2021 | F96: June 1, 2021 | G96: 165 | H96: MOOE | I96: complete | J96: 900 | K96: 318
A97: 2021-066 | B97: materials for the National Higher Education Week Competition (May 17-21, 2021) | C97: ELEIN T. ESPERANZA | D97: SVP | E97: May 14, 2021 | F97: June 7, 2021 | G97: 165 | H97: MOOE | I97: complete | J97: 3420 | K97: 2537
A98: 2021-067 | B98: materials for the National Higher Education Week Competition (May 17-21, 2021) | C98: ELEIN T. ESPERANZA | D98: SVP | E98: August 23, 2021 | F98: August 23, 2021 | G98: (blank) | H98: (blank) | I98: FAILED | J98: 1500 | K98: 0
A99: 2021-068 | B99: materials for the National Higher Education Week Competition (May 17-21, 2021) | C99: ELEIN T. ESPERANZA | D99: SVP | E99: August 23, 2021 | F99: August 23, 2021 | G99: (blank) | H99: (blank) | I99: FAILED | J99: 1050 | K99: 0
A100: 2021-069 | B100: provision of WiFi Modems for internet connectivity (Admin. & Finance units) | C100: DJOVI R. DURANTE | D100: SVP | E100: August 23, 2021 | F100: August 23, 2021 | G100: 101 | H100: MOOE | I100: for delivery | J100: 30000 | K100: 27950
A101: 2021-070 | B101: Health Insurance of students | C101: WILLIAM JO SE M. BILLOTE | D101: SVP | E101: July 1, 2021 | F101: July 2, 2021 | G101: 165 | H101: (blank) | I101: complete | J101: 7500 | K101: 7500
A102: 2021-071 | B102: for the Implementation of "ADOPT through varied R & D of Ivatan Endemic Resources" research project | C102: FERDINAND BULUSAN | D102: SVP | E102: August 23, 2021 | F102: August 23, 2021 | G102: (blank) | H102: (blank) | I102: FAILED | J102: 45400 | K102: 0
...

Sheet Suppliers TIN
B1: Business Name | C1: Name/Owner | D1: TIN #
A2: 1 | B2: Apostol General Merchandise | C2: Leo A. Apostol | D2: 183-008-448
A3: 2 | B3: Bartilad's Feeds Trading | C3: Roldan Q. Bartilad | D3: 771-272-422
A4: 3 | B4: Bitstop Network Services Inc. | C4: JC James P. Jihay | D4: 005-931-291
A5: 4 | B5: Casa Del Basco | D5: 107-549-729
A6: 5 | B6: Crisel General Merchandise | C6: Cresencio M. Verana | D6: 135-792-662
A7: 6 | B7: Claire's Drugstore | C7: Claire H. Abad | D7: 264-438-671
A8: 7 | B8: Davocol's General Merchandise | C8: Lilibeth T. Davocol | D8: 116-311-342
A9: 8 | B9: Davocol's Inn | C9: Dan Ardie T. Davocol | D9: 739-884-154
A10: 9 | B10: D' Islands Gasoline Station | C10: Lito Doroteo A. Adarme | D10: 124-072-664
A11: 10 | B11: Doque's Congie Hauz | C11: Glenda L. Gordo | D11: 922-904-311
A12: 11 | B12: D. Michael Co Industrial Supply (DMC) Corp. | C12: Eunelyn O. Ramilla | D12: 007-776-953
A13: 12 | B13: E. A. Amboy General Merchandise | C13: Cesar Edgardo Amboy | D13: 928-655-269
A14: 13 | B14: Enrinar Trading | C14: Narcisa Co Melad | D14: 123-394-221
A15: 14 | B15: FMG Trading & Construction Supply | C15: Frederick Gari | D15: 219-884-940
A16: 15 | B16: GDP Trading | C16: George D. Peralta | D16: 150-214-534
A17: 16 | B17: Hubalde's Drugstore | C17: Marilyn G. Hubalde | D17: 914-979-941
A18: 17 | B18: Hudzan Café & Catering Services | C18: Susan Villegas | D18: 290-315-057 | E18: **
A19: 18 | B19: I.B.S Pharmacy & General Merchadise | C19: Dale Anthony C. Gutierrez | D19: 411-599-160
A20: 19 | B20: IAM'J Graphic Design & Printing | C20: Jaycy S. Alina | D20: 318-666-833
A21: 20 | B21: JPM General Merchandise & Hardware | C21: Emma P. Adarme | D21: 160-183-814
A22: 21 | B22: J-Tech Trading & Services | C22: Cecilia C. De Sagon | D22: 933-429-635
A23: 22 | B23: M.G. Hubalde's General Merchandise | C23: Marilyn G. Hubalde | D23: 914-979-941-001
A24: 23 | B24: MDAC Trading & Compuserve | C24: Florescita A. Cruz | D24: 100-194-776
A25: 24 | B25: NRA Hardware | C25: Neil Bernardo Ordas | D25: 196-062-499
A26: 25 | B26: One-Touch Technology Trading | C26: Janice A. Alasco | D26: 283-009-327
A27: 26 | B27: Pension Ivatan | C27: Teresita D. Valiente | D27: 106-115-883
A28: 27 | B28: Sophia Marie Store | C28: Regina B. Gabaldon | D28: 279-057-542
A29: 28 | B29: Twixbiz General Merchandise | C29: Charles B. Domingo | D29: 118-687-531
A30: 29 | B30: Northern Star General Merchandise | C30: Cesar A. Calma | D30: 151-407-774
... A37: 36 | B37: MKM Hardware | C37: Enrique Abuyo Melad Jr. | D37: 148-780-907
A38: 37 | B38: NSGB Books Trading | C38: Nica Sandra Go Banag
A39: 38 | B39: ONPREM2CLOUD IT SOLUTIONS CO. | C39: Emmanuel B. Mamayson | D39: 101-626-582
A40: 39 | B40: Petonio's Kitchen Food Services | C40: Ramona C. Tabuso | D40: 013-000-080-045-720-21
A41: 40 | B41: Tiger Consulting and Software Devt Inc. | D41: 007-073-548
A42: 41 | B42: MOJR Construction Trading & General Services, Ltd, Co. | C42: Manuel S. Obedoza Jr.
A43: 42 | B43: Batanes Electric Cooperative Inc. | C43: Victoria A. Mata | D43: 005-641-216-000
A44: 43 | B44: Maddies Fashion Design Services | C44: Madeline Palencia Palustre
A45: 44 | B45: CMVILL Trading | C45: Zariffe G. Villanueva | D45: 421-603-862-000
A46: 45 | B46: VL Mini Canteen | C46: Estela N. Lizardo | D46: 930-779-799
A47: 46 | B47: IDB Merida Photo Studio & Artworks | C47: Ignacio Danilo B. Merida | D47: 925-632-231
A48: 47 | B48: SKE Souvenir Trading | C48: Sophia Kate L. Esdicul | D48: 613-655-085-00001
A49: 48 | B49: I.B.S. Travel and Tours | C49: Zharmaine C. Gutierrez | D49: 258-905-353
A50: 49 | B50: FVA Trading | C50: NathaN A. Amboy | D50: 436-695-403
A51: 50 | B51: JC Delatado's Telecommunication Equipment Trading | C51: Jesse A. Delatado | D51: 713-001-589-00001
A52: 51 | B52: AZ Blue Box Café | C52: Zafra Hazel B. Baldovino | D52: 434-947-764-00001
A53: 52 | B53: Kian's Food Product | C53: William Pol M. Maggay | D53: 915-768-533-00000
A54: 53 | B54: ORCA General Merchandise | C54: Engr. La Verne Sarmiento | D54: 614-297-100-00000
A55: 54 | B55: Boulder Bay Residence | C55: Mario Rey Roa Pacana | D55: 943-433-381-002
A56: 55 | B56: Simsiman Arts & Crafts Manufacturing | C56: Catherine De Mata | D56: 187-250-096
... A66: 65 | B66: Katuvang B and B | C66: Miguel Mariano B. Acebes | D66: 155-777-594-000
A67: 66 | B67: Bethel General Insurance and Surety Corporation | C67: Nicasio B. Subteniente Jr.
A68: 67 | B68: D.E. Curtain Shop | C68: Marlon Hernandez Espiritu | D68: 260-562-542-00000
A69: 68 | B69: Biang's Catering Services | C69: Sylvia R. Ugaddan | D69: 944-147-244-00000
A70: 69 | B70: AlliedBankers Insurance Corporation (ABIC)-PNB
A71: 70 | B71: Bunkers Bistro | C71: Jennifer Gabilo | D71: 297-134-097-00000
A72: 71 | B72: CMJ Shop and Snack | C72: Crisan C. Imperial | D72: 182-066-055-00000
A73: 72 | B73: Harbor Café | C73: Kurt Ryan L. Donato | D73: 303-569-039-00000
A74: 73 | B74: REMAR Construction | C74: Remy G. Cadiente
A75: 74 | B75: Artech Printing Services | C75: John Patrick D. Pasio | D75: 477-299-309-00000
A76: 75 | B76: Cielo General Merchandise | C76: Cyprian Crisostomo B. Cielo | D76: 275-653-568-00001
A77: 76 | B77: GMPI Construction OPC | C77: Gilbert N. Imperial | D77: 617-880-746-00000
A78: 77 | B78: Printopia Digital Printing Shop | C78: Marvilyn H. Castro | D78: 378-544-709-00000

Sheet FundCodes
A1: CODE | B1: CATEGORY | C1: OFFICE/UNIT
A2: GAS1 | B2: General Administration Services | C2: Office of the President
A3: GAS2 | B3: General Administration Services | C3: Office of the Board Secretary
A4: GAS3 | B4: General Administration Services | C4: Office of the College Secretary | G4: Fund
A5: GAS4 | B5: General Administration Services | C5: Information & Communications Technology Unit | G5: 01-101
A6: GAS5 | B6: General Administration Services | C6: Information Unit | G6: 05-164
A7: GAS6 | B7: General Administration Services | C7: Internal Audit Unit | G7: 06-162
A8: GAS7 | B8: General Administration Services | C8: Legal Unit | G8: 07-165
A9: GAS8 | B9: General Administration Services | C9: Planning Unit
A10: GAS9 | B10: General Administration Services | C10: Project Management Unit
A11: GAS10 | B11: General Administration Services | C11: Quality Assurance Office
A12: GAS11 | B12: General Administration Services | C12: Administrative Office
A13: GAS12 | B13: General Administration Services | C13: Cash Unit
A14: GAS13 | B14: General Administration Services | C14: General Services Unit
A15: GAS14 | B15: General Administration Services | C15: Human Resource Management Unit
A16: GAS15 | B16: General Administration Services | C16: Procurement Unit
A17: GAS16 | B17: General Administration Services | C17: Records Unit
A18: GAS17 | B18: General Administration Services | C18: Supply & Property Management Unit
A19: GAS18 | B19: General Administration Services | C19: Accounting Unit
A20: GAS19 | B20: General Administration Services | C20: Budget Unit
... A45: Acad9 | B45: Director for Instruction | C45: DI
A46: 1005 | B46: Research & Extension Services | C46: Research & Extension Office
A47: 1006 | B47: Business Affairs Office | C47: CBAO
A48: 1006A | B48: College Assessment Center | C48: CAC
A49: 1006B | B49: College Business Affairs Office | C49: CBAO-IGP
A50: 1006C | B50: College Business Affairs Office | C50: CBAO-Dorm
A51: 1006D | B51: College Business Affairs Office | C51: CBAO-Hostel

Sheet DATA
A1: YEAR | B1: MONTH | C1: End-User | D1: Position/Designation | E1: Fund Code | F1: Class | G1: PR# | H1: Modality | I1: Item | J1: Qty | K1: Unit of Issue | L1: Unit Budget | M1: Estimated Total | N1: Unit LCRB | O1: Total | P1: Purpose | Q1: Office | R1: Date of LON | S1: Date of BAC Award | T1: PO/Contract Date | U1: PO/Contract Date Received | V1: Delivery Date | W1: Supplier | X1: IAR Date | Y1: Section Code/Dept. | Z1: Released Date | AA1: Status | AB1: Remarks | AC1: ObR # | AD1: # of RFQ's printed | AE1: Sales/Charge Invoice/Billing
A2: 2025 | B2: October | C2: ALFRED VINCENT D. BACCAY | D2: SSC President | G2: 2025-347 | I2: Wooden Plaque | J2: 4 | K2: pcs | L2: 1000 | M2: =SUM(J2*L2) -> 4000 | N2: 1000 | O2: =SUM(J2*N2) -> 4000 | P2: "A Tribute to our Teachers: Guiding BSCians, Building a Brighter Tomorrow | Q2: SSC | R2: October 20, 2025 | S2: October 22, 2025 | T2: October 22, 2025 | W2: SKE Souvenir Trading | Y2: SS09 | AD2: 3 RFQ's
A3: 2025 | B3: October | C3: ALFRED VINCENT D. BACCAY | D3: SSC President | E3: 165 | G3: 2025-348 | I3: Specialty Paper, A4 | J3: 20 | K3: ballots | L3: 150 | M3: =SUM(J3*L3) -> 3000 | N3: 65 | O3: =SUM(J3*N3) -> 1300 | P3: "A Tribute to our Teachers: Guiding BSCians, Building a Brighter Tomorrow | Q3: SSC | R3: October 7, 2025 | S3: October 13, 2025 | T3: October 14, 2025 | U3: October 16, 2026 | W3: JPM General Merchandise & Hardware | X3: March 3, 2026 | Y3: SS09 | Z3: March 10, 2026 | AA3: complete | AB3: for payment-Acctg. | AC3: 07-02-2025-10-0363 | AD3: 4 RFQ's | AE3: 13438/3/8/2026
A4: 2025 | B4: October | C4: JENNY S. ALINA | D4: College Nurse | E4: 165 | G4: 2025-349 | I4: Diphenhydramine 50mg/capsule | J4: 3 | K4: boxes | L4: 500 | M4: =SUM(J4*L4) -> 1500 | N4: 110 | O4: =SUM(J4*N4) -> 330 | P4: for the program/activity intended to strengthen the healthcare services of the BSC Clinic through the procurement of medicines and medical supplies | Q4: Medical-Clinic | R4: October 28, 2025 | S4: November 7, 2025 | T4: November 11, 2025 | U4: November 17, 2025 | V4: Oct. 29,Dec. 5,10 & 23, 2025 & Jan. 15, 2026 | W4: Claire's Drugstore | X4: Nov. 20,Dec. 10,& 23, 2025 & Jan. 15, 2026 | Y4: SS02 | Z4: January 27, 2026 | AA4: complete | AB4: for payment-Acctg. | AC4: 07-02-2025-11-0397A | AD4: 5 RFQ's | AE4: 0719-0721/1/13/2026
A5: 2025 | B5: October | C5: JENNY S. ALINA | D5: College Nurse | E5: 165 | G5: 2025-349 | I5: Hydrogen Peroxide 120ml | J5: 30 | K5: bottles | L5: 120 | M5: =SUM(J5*L5) -> 3600 | N5: 45 | O5: =SUM(J5*N5) -> 1350 | P5: for the program/activity intended to strengthen the healthcare services of the BSC Clinic through the procurement of medicines and medical supplies | Q5: Medical-Clinic | R5: October 28, 2025 | S5: November 7, 2025 | T5: November 11, 2025 | U5: November 17, 2025 | V5: Oct. 29,Dec. 5,10 & 23, 2025 & Jan. 15, 2026 | W5: Claire's Drugstore | X5: Nov. 20,Dec. 10,& 23, 2025 & Jan. 15, 2026 | Y5: SS02 | Z5: January 27, 2026 | AA5: complete | AB5: for payment-Acctg. | AC5: 07-02-2025-11-0397A
A6: 2025 | B6: October | C6: JENNY S. ALINA | D6: College Nurse | E6: 165 | G6: 2025-349 | I6: Paracetamol 500mg. | J6: 5 | K6: boxes (100's) | L6: 500 | M6: =SUM(J6*L6) -> 2500 | N6: 70 | O6: =SUM(J6*N6) -> 350 | P6: for the program/activity intended to strengthen the healthcare services of the BSC Clinic through the procurement of medicines and medical supplies | Q6: Medical-Clinic | R6: October 28, 2025 | S6: November 7, 2025 | T6: November 11, 2025 | U6: November 17, 2025 | V6: Oct. 29,Dec. 5,10 & 23, 2025 & Jan. 15, 2026 | W6: Claire's Drugstore | X6: Nov. 20,Dec. 10,& 23, 2025 & Jan. 15, 2026 | Y6: SS02 | Z6: January 27, 2026 | AA6: complete | AB6: for payment-Acctg. | AC6: 07-02-2025-11-0397A
A7: 2025 | B7: October | C7: JENNY S. ALINA | D7: College Nurse | E7: 165 | G7: 2025-349 | I7: Mefenamic Acid 500mg/capsule | J7: 5 | K7: boxes | L7: 1000 | M7: =SUM(J7*L7) -> 5000 | N7: 125 | O7: =SUM(J7*N7) -> 625 | P7: for the program/activity intended to strengthen the healthcare services of the BSC Clinic through the procurement of medicines and medical supplies | Q7: Medical-Clinic | R7: October 28, 2025 | S7: November 7, 2025 | T7: November 11, 2025 | U7: November 17, 2025 | V7: Oct. 29,Dec. 5,10 & 23, 2025 & Jan. 15, 2026 | W7: Claire's Drugstore | X7: Nov. 20,Dec. 10,& 23, 2025 & Jan. 15, 2026 | Y7: SS02 | Z7: January 27, 2026 | AA7: complete | AB7: for payment-Acctg. | AC7: 07-02-2025-11-0397A
A8: 2025 | B8: October | C8: JENNY S. ALINA | D8: College Nurse | E8: 165 | G8: 2025-349 | I8: Salmeterol+Fluticasone Inhaler 25mcg/125mcg metered dose inhaler | J8: 10 | K8: pcs. | L8: 650 | M8: =SUM(J8*L8) -> 6500 | N8: 400 | O8: =SUM(J8*N8) -> 4000 | P8: for the program/activity intended to strengthen the healthcare services of the BSC Clinic through the procurement of medicines and medical supplies | Q8: Medical-Clinic | R8: October 28, 2025 | S8: November 7, 2025 | T8: November 11, 2025 | U8: November 17, 2025 | V8: Oct. 29,Dec. 5,10 & 23, 2025 & Jan. 15, 2026 | W8: Claire's Drugstore | X8: Nov. 20,Dec. 10,& 23, 2025 & Jan. 15, 2026 | Y8: SS02 | Z8: January 27, 2026 | AA8: complete | AB8: for payment-Acctg. | AC8: 07-02-2025-11-0397A
A9: 2025 | B9: October | C9: JENNY S. ALINA | D9: College Nurse | E9: 165 | G9: 2025-349 | I9: Providine Iodine 60ml | J9: 30 | K9: bottles | L9: 200 | M9: =SUM(J9*L9) -> 6000 | N9: 60 | O9: =SUM(J9*N9) -> 1800 | P9: for the program/activity intended to strengthen the healthcare services of the BSC Clinic through the procurement of medicines and medical supplies | Q9: Medical-Clinic | R9: October 28, 2025 | S9: November 7, 2025 | T9: November 11, 2025 | U9: November 17, 2025 | V9: Oct. 29,Dec. 5,10 & 23, 2025 & Jan. 15, 2026 | W9: Claire's Drugstore | X9: Nov. 20,Dec. 10,& 23, 2025 & Jan. 15, 2026 | Y9: SS02 | Z9: January 27, 2026 | AA9: complete | AB9: for payment-Acctg. | AC9: 07-02-2025-11-0397A
A10: 2025 | B10: October | C10: JENNY S. ALINA | D10: College Nurse | E10: 165 | G10: 2025-349 | I10: Loperamide | J10: 10 | K10: boxes | L10: 500 | M10: =SUM(J10*L10) -> 5000 | N10: 80 | O10: =SUM(J10*N10) -> 800 | P10: for the program/activity intended to strengthen the healthcare services of the BSC Clinic through the procurement of medicines and medical supplies | Q10: Medical-Clinic | R10: October 28, 2025 | S10: November 7, 2025 | T10: November 11, 2025 | U10: November 17, 2025 | V10: Oct. 29,Dec. 5,10 & 23, 2025 & Jan. 15, 2026 | W10: Claire's Drugstore | X10: Nov. 20,Dec. 10,& 23, 2025 & Jan. 15, 2026 | Y10: SS02 | Z10: January 27, 2026 | AA10: complete | AB10: for payment-Acctg. | AC10: 07-02-2025-11-0397A
A11: 2025 | B11: October | C11: JENNY S. ALINA | D11: College Nurse | E11: 165 | G11: 2025-349 | I11: Band Aid (Waterproof) | J11: 15 | K11: boxes | L11: 200 | M11: =SUM(J11*L11) -> 3000 | N11: 110 | O11: =SUM(J11*N11) -> 1650 | P11: for the program/activity intended to strengthen the healthcare services of the BSC Clinic through the procurement of medicines and medical supplies | Q11: Medical-Clinic | R11: October 28, 2025 | S11: November 7, 2025 | T11: November 11, 2025 | U11: November 17, 2025 | V11: Oct. 29,Dec. 5,10 & 23, 2025 & Jan. 15, 2026 | W11: Claire's Drugstore | X11: Nov. 20,Dec. 10,& 23, 2025 & Jan. 15, 2026 | Y11: SS02 | Z11: January 27, 2026 | AA11: complete | AB11: for payment-Acctg. | AC11: 07-02-2025-11-0397A
A12: 2025 | B12: October | C12: JENNY S. ALINA | D12: College Nurse | E12: 165 | G12: 2025-349 | I12: Ice Bag (big) 9’’ | J12: 6 | K12: pc | L12: 150 | M12: =SUM(J12*L12) -> 900 | N12: 160 | O12: =SUM(J12*N12) -> 960 | P12: for the program/activity intended to strengthen the healthcare services of the BSC Clinic through the procurement of medicines and medical supplies | Q12: Medical-Clinic | R12: October 28, 2025 | S12: November 7, 2025 | T12: November 11, 2025 | U12: November 17, 2025 | V12: Oct. 29,Dec. 5,10 & 23, 2025 & Jan. 15, 2026 | W12: Claire's Drugstore | X12: Nov. 20,Dec. 10,& 23, 2025 & Jan. 15, 2026 | Y12: SS02 | Z12: January 27, 2026 | AA12: complete | AB12: for payment-Acctg. | AC12: 07-02-2025-11-0397A
A13: 2025 | B13: October | C13: JENNY S. ALINA | D13: College Nurse | E13: 165 | G13: 2025-349 | I13: Mupirocin 2omg/g/ 5g | J13: 10 | K13: pcs. | L13: 200 | M13: =SUM(J13*L13) -> 2000 | N13: 60 | O13: =SUM(J13*N13) -> 600 | P13: for the program/activity intended to strengthen the healthcare services of the BSC Clinic through the procurement of medicines and medical supplies | Q13: Medical-Clinic | R13: October 28, 2025 | S13: November 7, 2025 | T13: November 11, 2025 | U13: November 17, 2025 | V13: Oct. 29,Dec. 5,10 & 23, 2025 & Jan. 15, 2026 | W13: Claire's Drugstore | X13: Nov. 20,Dec. 10,& 23, 2025 & Jan. 15, 2026 | Y13: SS02 | Z13: January 27, 2026 | AA13: complete | AB13: for payment-Acctg. | AC13: 07-02-2025-11-0397A
A14: 2025 | B14: October | C14: JENNY S. ALINA | D14: College Nurse | E14: 165 | G14: 2025-349 | I14: Clean gloves(large) | J14: 10 | K14: boxes | L14: 400 | M14: =SUM(J14*L14) -> 4000 | N14: 330 | O14: =SUM(J14*N14) -> 3300 | P14: for the program/activity intended to strengthen the healthcare services of the BSC Clinic through the procurement of medicines and medical supplies | Q14: Medical-Clinic | R14: October 28, 2025 | S14: November 7, 2025 | T14: November 11, 2025 | U14: November 17, 2025 | V14: Oct. 29,Dec. 5,10 & 23, 2025 & Jan. 15, 2026 | W14: Claire's Drugstore | X14: Nov. 20,Dec. 10,& 23, 2025 & Jan. 15, 2026 | Y14: SS02 | Z14: January 27, 2026 | AA14: complete | AB14: for payment-Acctg. | AC14: 07-02-2025-11-0397A
A15: 2025 | B15: October | C15: JENNY S. ALINA | D15: College Nurse | E15: 165 | G15: 2025-349 | I15: Naproxen Sodium 550mg(blue) | J15: 200 | K15: tablet | L15: 33 | M15: =SUM(J15*L15) -> 6600 | N15: 33 | O15: =SUM(J15*N15) -> 6600 | P15: for the program/activity intended to strengthen the healthcare services of the BSC Clinic through the procurement of medicines and medical supplies | Q15: Medical-Clinic | R15: October 28, 2025 | S15: November 7, 2025 | T15: November 11, 2025 | U15: November 17, 2025 | V15: Oct. 29,Dec. 5,10 & 23, 2025 & Jan. 15, 2026 | W15: Claire's Drugstore | X15: Nov. 20,Dec. 10,& 23, 2025 & Jan. 15, 2026 | Y15: SS02 | Z15: January 27, 2026 | AA15: complete | AB15: for payment-Acctg. | AC15: 07-02-2025-11-0397A
A16: 2025 | B16: October | C16: JENNY S. ALINA | D16: College Nurse | E16: 165 | G16: 2025-349 | I16: Multi Insect Killer 700ml (Odorless/Lemon) | J16: 3 | K16: Cannister | L16: 700 | M16: =SUM(J16*L16) -> 2100 | N16: 780 | O16: =SUM(J16*N16) -> 2340 | P16: for the program/activity intended to strengthen the healthcare services of the BSC Clinic through the procurement of medicines and medical supplies | Q16: Medical-Clinic | R16: October 28, 2025 | S16: November 7, 2025 | T16: November 11, 2025 | U16: November 17, 2025 | V16: Oct. 29,Dec. 5,10 & 23, 2025 & Jan. 15, 2026 | W16: Claire's Drugstore | X16: Nov. 20,Dec. 10,& 23, 2025 & Jan. 15, 2026 | Y16: SS02 | Z16: January 27, 2026 | AA16: complete | AB16: for payment-Acctg. | AC16: 07-02-2025-11-0397A
... A45: 2025 | B45: October | C45: JENNY S. ALINA | D45: College Nurse | E45: 165 | G45: 2025-349 | I45: Bleach lemon 1 Liter | J45: 3 | K45: boxes | L45: 500 | M45: =SUM(J45*L45) -> 1500 | N45: 2300 | O45: =SUM(J45*N45) -> 6900 | P45: for the program/activity intended to strengthen the healthcare services of the BSC Clinic through the procurement of medicines and medical supplies | Q45: Medical-Clinic | R45: October 28, 2025 | S45: November 7, 2025 | T45: November 11, 2025 | U45: November 17, 2025 | V45: Oct. 29,Dec. 5,10 & 23, 2025 & Jan. 15, 2026 | W45: Claire's Drugstore | X45: Nov. 20,Dec. 10,& 23, 2025 & Jan. 15, 2026 | Y45: SS02 | Z45: January 27, 2026 | AA45: complete | AB45: for payment-Acctg. | AC45: 07-02-2025-11-0397A
A46: 2025 | B46: October | C46: DOREEN C. CASTILLO | D46: Director for CBAO | G46: 2025-350 | I46: Spicy Seafood Cup Noodles 48's | J46: 2 | K46: box | L46: 1480 | M46: =SUM(J46*L46) -> 2960 | O46: =SUM(J46*N46) -> 0 | P46: for canteen operation | Q46: CBAO | Y46: 1006 | AA46: FAILED | AB46: quotation exceeded the budget | AD46: 3 RFQ's
A47: 2025 | B47: October | C47: DOREEN C. CASTILLO | D47: Director for CBAO | G47: 2025-350 | I47: Spicy Beef Cup Noodles 48's | J47: 2 | K47: box | L47: 1480 | M47: =SUM(J47*L47) -> 2960 | O47: =SUM(J47*N47) -> 0 | P47: for canteen operation | Q47: CBAO | Y47: 1006
A48: 2025 | B48: October | C48: DOREEN C. CASTILLO | D48: Director for CBAO | G48: 2025-350 | I48: Beef Flavor Cup Noodles 48's | J48: 2 | K48: box | L48: 1480 | M48: =SUM(J48*L48) -> 2960 | O48: =SUM(J48*N48) -> 0 | P48: for canteen operation | Q48: CBAO | Y48: 1006
A49: 2025 | B49: October | C49: DOREEN C. CASTILLO | D49: Director for CBAO | G49: 2025-350 | I49: Batchoy Flavor Cup Noodles 48's | J49: 2 | K49: box | L49: 1480 | M49: =SUM(J49*L49) -> 2960 | O49: =SUM(J49*N49) -> 0 | P49: for canteen operation | Q49: CBAO | Y49: 1006
A50: 2025 | B50: October | C50: DOREEN C. CASTILLO | D50: Director for CBAO | G50: 2025-350 | I50: Creamy Seafood Flavor Cup Noodles 48's | J50: 2 | K50: box | L50: 1480 | M50: =SUM(J50*L50) -> 2960 | O50: =SUM(J50*N50) -> 0 | P50: for canteen operation | Q50: CBAO | Y50: 1006
A51: 2025 | B51: October | C51: DOREEN C. CASTILLO | D51: Director for CBAO | G51: 2025-350 | I51: Seafood Flavor Cup Noodles 48's | J51: 2 | K51: box | L51: 1480 | M51: =SUM(J51*L51) -> 2960 | O51: =SUM(J51*N51) -> 0 | P51: for canteen operation | Q51: CBAO | Y51: 1006
A52: 2025 | B52: October | C52: DOREEN C. CASTILLO | D52: Director for CBAO | G52: 2025-350 | I52: Bulalo Flavor Cup Noodles 48's | J52: 2 | K52: box | L52: 1480 | M52: =SUM(J52*L52) -> 2960 | O52: =SUM(J52*N52) -> 0 | P52: for canteen operation | Q52: CBAO | Y52: 1006
A53: 2025 | B53: October | C53: DOREEN C. CASTILLO | D53: Director for CBAO | G53: 2025-350 | I53: Coke in Can | J53: 5 | K53: case | L53: 1260 | M53: =SUM(J53*L53) -> 6300 | O53: =SUM(J53*N53) -> 0 | P53: for canteen operation | Q53: CBAO | Y53: 1006
A54: 2025 | B54: October | C54: DOREEN C. CASTILLO | D54: Director for CBAO | G54: 2025-350 | I54: Royal in can | J54: 5 | K54: case | L54: 1260 | M54: =SUM(J54*L54) -> 6300 | O54: =SUM(J54*N54) -> 0 | P54: for canteen operation | Q54: CBAO | Y54: 1006
A55: 2025 | B55: October | C55: DOREEN C. CASTILLO | D55: Director for CBAO | G55: 2025-350 | I55: Sprite in can | J55: 5 | K55: case | L55: 1260 | M55: =SUM(J55*L55) -> 6300 | O55: =SUM(J55*N55) -> 0 | P55: for canteen operation | Q55: CBAO | Y55: 1006
A56: 2025 | B56: October | C56: DOREEN C. CASTILLO | D56: Director for CBAO | G56: 2025-350 | I56: Mountain Dew 500ml | J56: 5 | K56: case | L56: 1095 | M56: =SUM(J56*L56) -> 5475 | O56: =SUM(J56*N56) -> 0 | P56: for canteen operation | Q56: CBAO | Y56: 1006
A57: 2025 | B57: October | C57: DOREEN C. CASTILLO | D57: Director for CBAO | G57: 2025-350 | I57: Bottled Water 500ml | J57: 10 | K57: case | L57: 580 | M57: =SUM(J57*L57) -> 5800 | O57: =SUM(J57*N57) -> 0 | P57: for canteen operation | Q57: CBAO | Y57: 1006
A58: 2025 | B58: October | C58: DOREEN C. CASTILLO | D58: Director for CBAO | G58: 2025-350 | I58: Tetra Pack Juice | J58: 15 | K58: box | L58: 245 | M58: =SUM(J58*L58) -> 3675 | O58: =SUM(J58*N58) -> 0 | P58: for canteen operation | Q58: CBAO | Y58: 1006
... A85: 2025 | B85: October | C85: DOREEN C. CASTILLO | D85: Director for CBAO | G85: 2025-350 | I85: Cling Wrap | J85: 2 | K85: roll | L85: 500 | M85: =SUM(J85*L85) -> 1000 | O85: =SUM(J85*N85) -> 0 | P85: for canteen operation | Q85: CBAO | Y85: 1006
A86: 2025 | B86: October | C86: MARIE FE E. PABLEO | D86: Board Secretary I | E86: 101 | F86: Toss Coin | G86: 2025-351 | I86: Tarpaulin Printing (4ft x 6ft) | J86: 1 | K86: pc | L86: 1500 | M86: =SUM(J86*L86) -> 1500 | N86: 720 | O86: =SUM(J86*N86) -> 720 | P86: announcement for the opening of search for private sector representatives to the BSC Board of Trustees | Q86: OBS | R86: October 22, 2025 | S86: October 24, 2025 | T86: October 28, 2025 | U86: November 13, 2025 | V86: November 26, 2025 | W86: YCA Printing Services | X86: November 26, 2025 | Y86: GAS2 | Z86: December 4, 2025 | AA86: complete | AB86: for payment-Acctg. | AC86: 02-101101-2025-10-00881 | AD86: 3 RFQ's | AE86: 379/11/26/2025
A87: 2025 | B87: October | C87: ZOE DYMPNA H. CARTAŇO | D87: AO V/GAD Focal Person | E87: 101 | F87: Dir. Acq. | G87: 2025-352 | I87: Rice (25kgs) | J87: 13 | K87: sack | L87: 1800 | M87: =SUM(J87*L87) -> 23400 | N87: 1800 | O87: =SUM(J87*N87) -> 23400 | P87: for the distribution of food packs for the elderly and person with special needs of the BSC employees | Q87: GAD | T87: October 8, 2025 | U87: October 14, 2025 | V87: October 3, 2025 | W87: CMJ Shop & Snack | X87: October 6, 2025 | Y87: GAS21 | Z87: October 28, 2025 | AA87: complete | AB87: for payment-Acctg. | AC87: 02-101101-2025-10-00814 | AE87: 0008157/10/06/2025
A88: 2025 | B88: October | C88: ZOE DYMPNA H. CARTAŇO | D88: AO V/GAD Focal Person | E88: 101 | G88: 2025-352 | I88: Assorted Biscuits | J88: 100 | K88: pack | L88: 95 | M88: =SUM(J88*L88) -> 9500 | N88: 95 | O88: =SUM(J88*N88) -> 9500 | P88: for the distribution of food packs for the elderly and person with special needs of the BSC employees | Q88: GAD | T88: October 8, 2025 | U88: October 14, 2025 | V88: October 3, 2025 | W88: CMJ Shop & Snack | X88: October 6, 2025 | Y88: GAS21 | Z88: October 28, 2025 | AA88: complete | AB88: for payment-Acctg. | AC88: 02-101101-2025-10-00814
A89: 2025 | B89: October | C89: ZOE DYMPNA H. CARTAŇO | D89: AO V/GAD Focal Person | E89: 101 | G89: 2025-352 | I89: Washed Sugar | J89: 100 | K89: kg | L89: 115 | M89: =SUM(J89*L89) -> 11500 | N89: 115 | O89: =SUM(J89*N89) -> 11500 | P89: for the distribution of food packs for the elderly and person with special needs of the BSC employees | Q89: GAD | T89: October 8, 2025 | U89: October 14, 2025 | V89: October 3, 2025 | W89: CMJ Shop & Snack | X89: October 6, 2025 | Y89: GAS21 | Z89: October 28, 2025 | AA89: complete | AB89: for payment-Acctg. | AC89: 02-101101-2025-10-00814
A90: 2025 | B90: October | C90: ZOE DYMPNA H. CARTAŇO | D90: AO V/GAD Focal Person | E90: 101 | G90: 2025-352 | I90: Eco Bag 25pc/pack (large) | J90: 4 | K90: pack | L90: 1400 | M90: =SUM(J90*L90) -> 5600 | N90: 1400 | O90: =SUM(J90*N90) -> 5600 | P90: for the distribution of food packs for the elderly and person with special needs of the BSC employees | Q90: GAD | T90: October 8, 2025 | U90: October 14, 2025 | V90: October 3, 2025 | W90: CMJ Shop & Snack | X90: October 6, 2025 | Y90: GAS21 | Z90: October 28, 2025 | AA90: complete | AB90: for payment-Acctg. | AC90: 02-101101-2025-10-00814
A91: 2025 | B91: October | C91: ZOE DYMPNA H. CARTAŇO | D91: AO V/GAD Focal Person | E91: 101 | G91: 2025-352 | I91: Sando Bag | J91: 1 | K91: pack | L91: 200 | M91: =SUM(J91*L91) -> 200 | N91: 200 | O91: =SUM(J91*N91) -> 200 | P91: for the distribution of food packs for the elderly and person with special needs of the BSC employees | Q91: GAD | T91: October 8, 2025 | U91: October 14, 2025 | V91: October 3, 2025 | W91: CMJ Shop & Snack | X91: October 6, 2025 | Y91: GAS21 | Z91: October 28, 2025 | AA91: complete | AB91: for payment-Acctg. | AC91: 02-101101-2025-10-00814
A92: 2025 | B92: October | C92: ZOE DYMPNA H. CARTAŇO | D92: AO V/GAD Focal Person | E92: 101 | G92: 2025-352 | I92: Instant Oats | J92: 100 | K92: pack | L92: 125 | M92: =SUM(J92*L92) -> 12500 | N92: 125 | O92: =SUM(J92*N92) -> 12500 | P92: for the distribution of food packs for the elderly and person with special needs of the BSC employees | Q92: GAD | T92: October 8, 2025 | U92: October 14, 2025 | V92: October 3, 2025 | W92: CMJ Shop & Snack | X92: October 6, 2025 | Y92: GAS21 | Z92: October 28, 2025 | AA92: complete | AB92: for payment-Acctg. | AC92: 02-101101-2025-10-00814
A93: 2025 | B93: October | C93: ZOE DYMPNA H. CARTAŇO | D93: AO V/GAD Focal Person | E93: 101 | G93: 2025-352 | I93: Powdered Milk (600grams) | J93: 69 | K93: pack | L93: 450 | M93: =SUM(J93*L93) -> 31050 | N93: 450 | O93: =SUM(J93*N93) -> 31050 | P93: for the distribution of food packs for the elderly and person with special needs of the BSC employees | Q93: GAD | T93: October 8, 2025 | U93: October 14, 2025 | V93: October 3, 2025 | W93: CMJ Shop & Snack | X93: October 6, 2025 | Y93: GAS21 | Z93: October 28, 2025 | AA93: complete | AB93: for payment-Acctg. | AC93: 02-101101-2025-10-00814
A94: 2025 | B94: October | C94: ZOE DYMPNA H. CARTAŇO | D94: AO V/GAD Focal Person | E94: 101 | G94: 2025-352 | I94: Powdered Milk (680grams) | J94: 31 | K94: pack | L94: 415 | M94: =SUM(J94*L94) -> 12865 | N94: 415 | O94: =SUM(J94*N94) -> 12865 | P94: for the distribution of food packs for the elderly and person with special needs of the BSC employees | Q94: GAD | T94: October 8, 2025 | U94: October 14, 2025 | V94: October 3, 2025 | W94: CMJ Shop & Snack | X94: October 6, 2025 | Y94: GAS21 | Z94: October 28, 2025 | AA94: complete | AB94: for payment-Acctg. | AC94: 02-101101-2025-10-00814
A95: 2025 | B95: October | C95: ZOE DYMPNA H. CARTAŇO | D95: AO V/GAD Focal Person | E95: 101 | F95: Dir. Acq. | G95: 2025-353 | I95: AM Snack (pasta) | J95: 360 | K95: pax | L95: 200 | M95: =SUM(J95*L95) -> 72000 | N95: 200 | O95: =SUM(J95*N95) -> 72000 | P95: for the provision of snacks for the activity "Strong Minds,Safe Roads, Smart Choices" | Q95: GAD | T95: October 8, 2025 | U95: October 14, 2025 | V95: October 9, 2025 | W95: Harbor Café | X95: October 9, 2025 | Y95: GAS21 | Z95: October 28, 2025 | AA95: complete | AB95: for payment-Acctg. | AC95: 02-101101-2025-10-00815 | AE95: 0229/10/9/2025
A96: 2025 | B96: October | C96: ZOE DYMPNA H. CARTAŇO | D96: AO V/GAD Focal Person | E96: 101 | F96: Dir. Acq. | G96: 2025-354 | I96: AM Snack (pasta with garlic bread and soda) | J96: 29 | K96: pax | L96: 250 | M96: =SUM(J96*L96) -> 7250 | N96: 250 | O96: =SUM(J96*N96) -> 7250 | P96: for the provision of snacks for the special GAD meeting | Q96: GAD | T96: October 9, 2025 | U96: October 14, 2025 | V96: October 7, 2025 | W96: Biang's Catering Services | X96: October 7, 2025 | Y96: GAS21 | Z96: October 28, 2025 | AA96: complete | AB96: for payment-Acctg. | AC96: 02-101101-2025-10-00825 | AE96: 0109/10/07/2025
A97: 2025 | B97: October | C97: ZOE DYMPNA H. CARTAŇO | D97: AO V/GAD Focal Person | E97: 101 | G97: 2025-354 | I97: AM Snack (vegetarian) | J97: 1 | K97: pax | L97: 250 | M97: =SUM(J97*L97) -> 250 | N97: 250 | O97: =SUM(J97*N97) -> 250 | P97: for the provision of snacks for the special GAD meeting | Q97: GAD | T97: October 9, 2025 | U97: October 14, 2025 | V97: October 7, 2025 | W97: Biang's Catering Services | X97: October 7, 2025 | Y97: GAS21 | Z97: October 28, 2025 | AA97: complete | AB97: for payment-Acctg. | AC97: 02-101101-2025-10-00825
A98: 2025 | B98: October | C98: ELEIN T. ESPERANZA | D98: Acting Guidance Counselor | E98: 165 | F98: Del. Oct. 10 | G98: 2025-355 | I98: Assorted Biscuits | J98: 34 | K98: ballots | L98: 150 | M98: =SUM(J98*L98) -> 5100 | N98: 150 | O98: =SUM(J98*N98) -> 5100 | P98: snacks for students, faculty, and staff for SSO activities | Q98: Guidance | T98: November 26, 2025 | U98: December 3, 2025 | V98: December 3, 2025 | W98: Sophia Marie Store | X98: December 3, 2025 | Y98: SS01 | Z98: January 20, 2026 | AA98: complete | AB98: for payment-Acctg. | AC98: 07-02-2025-11-0437 | AE98: 1
A99: 2025 | B99: October | C99: ELEIN T. ESPERANZA | D99: Acting Guidance Counselor | E99: 165 | F99: Dir. Acq. | G99: 2025-355 | I99: Assorted Tetrapack Juice | J99: 35 | K99: boxes | L99: 200 | M99: =SUM(J99*L99) -> 7000 | N99: 200 | O99: =SUM(J99*N99) -> 7000 | P99: snacks for students, faculty, and staff for SSO activities | Q99: Guidance | T99: November 26, 2025 | U99: December 3, 2025 | V99: December 3, 2025 | W99: Sophia Marie Store | X99: December 3, 2025 | Y99: SS01 | Z99: January 20, 2026 | AA99: complete | AB99: for payment-Acctg. | AC99: 07-02-2025-11-0437 | AE99: 1355/12/03/2025
A100: 2025 | B100: October | C100: WARLITO M. TOMAS JR. | D100: Project Leader | E100: 165 | G100: 2025-356 | I100: Vitamin B Complex (100ml) | J100: 2 | K100: bottles | L100: 600 | M100: =SUM(J100*L100) -> 1200 | N100: 600 | O100: =SUM(J100*N100) -> 1200 | P100: for research project "Developing Feed Formulation for Bagu Ivatan Using Locally -Available Feeds and Forages" | Q100: Agriculture | R100: November 11, 2025 | S100: November 17, 2025 | T100: November 18, 2025 | U100: November 27, 2025 | V100: November 28, 2025 | W100: Bartilad Feeds Trading | X100: November 28, 2025 | Y100: Acad7 | Z100: January 7, 2026 | AA100: complete | AB100: for payment-Acctg. | AC100: 07-02-2025-11-0428 | AD100: 4 RFQ's | AE100: 046/11/28/2025
A101: 2025 | B101: October | C101: WARLITO M. TOMAS JR. | D101: Project Leader | E101: 165 | G101: 2025-356 | I101: Antibiotic (100ml) | J101: 2 | K101: bottles | L101: 600 | M101: =SUM(J101*L101) -> 1200 | N101: 650 | O101: =SUM(J101*N101) -> 1300 | P101: for research project "Developing Feed Formulation for Bagu Ivatan Using Locally -Available Feeds and Forages" | Q101: Agriculture | R101: November 11, 2025 | S101: November 17, 2025 | T101: November 18, 2025 | U101: November 27, 2025 | V101: November 28, 2025 | W101: Bartilad Feeds Trading | X101: November 28, 2025 | Y101: Acad7 | Z101: January 7, 2026 | AA101: complete | AB101: for payment-Acctg. | AC101: 07-02-2025-11-0428
A102: 2025 | B102: October | C102: WARLITO M. TOMAS JR. | D102: Project Leader | E102: 165 | G102: 2025-356 | I102: Anthelmintic (100ml) | J102: 2 | K102: bottles | L102: 600 | M102: =SUM(J102*L102) -> 1200 | N102: 600 | O102: =SUM(J102*N102) -> 1200 | P102: for research project "Developing Feed Formulation for Bagu Ivatan Using Locally -Available Feeds and Forages" | Q102: Agriculture | R102: November 11, 2025 | S102: November 17, 2025 | T102: November 18, 2025 | U102: November 27, 2025 | V102: November 28, 2025 | W102: Bartilad Feeds Trading | X102: November 28, 2025 | Y102: Acad7 | Z102: January 7, 2026 | AA102: complete | AB102: for payment-Acctg. | AC102: 07-02-2025-11-0428
A103: 2025 | B103: October | C103: WARLITO M. TOMAS JR. | D103: Project Leader | E103: 165 | G103: 2025-356 | I103: Syringe (5cc) | J103: 1 | K103: box | L103: 1500 | M103: =SUM(J103*L103) -> 1500 | N103: 500 | O103: =SUM(J103*N103) -> 500 | P103: for research project "Developing Feed Formulation for Bagu Ivatan Using Locally -Available Feeds and Forages" | Q103: Agriculture | R103: November 11, 2025 | S103: November 17, 2025 | T103: November 18, 2025 | U103: November 27, 2025 | V103: November 28, 2025 | W103: Bartilad Feeds Trading | X103: November 28, 2025 | Y103: Acad7 | Z103: January 7, 2026 | AA103: complete | AB103: for payment-Acctg. | AC103: 07-02-2025-11-0428
A104: 2025 | B104: October | C104: WARLITO M. TOMAS JR. | D104: Project Leader | E104: 165 | G104: 2025-356 | I104: Combinex (150ml) | J104: 2 | K104: bottles | L104: 500 | M104: =SUM(J104*L104) -> 1000 | N104: 700 | O104: =SUM(J104*N104) -> 1400 | P104: for research project "Developing Feed Formulation for Bagu Ivatan Using Locally -Available Feeds and Forages" | Q104: Agriculture | R104: November 11, 2025 | S104: November 17, 2025 | T104: November 18, 2025 | U104: November 27, 2025 | V104: November 28, 2025 | W104: Bartilad Feeds Trading | X104: November 28, 2025 | Y104: Acad7 | Z104: January 7, 2026 | AA104: complete | AB104: for payment-Acctg. | AC104: 07-02-2025-11-0428
A105: 2025 | B105: October | C105: WARLITO M. TOMAS JR. | D105: Project Leader | G105: 2025-357 | I105: Science & Technology Consultant (3 pax) 1. Services to be rendered. The S & T Consultant shall: a. Lead the development & implementation of survey instruments & training programs; b. Assist in the analysis of qualitative data; c. Facilitate the development of training needs analysis; d. Assist in the training programs of the programs of the project; e. Design,edit,& lay-out of the manual in developing feed formulations; and f. Assist in the preparation & submission of the projects accomplishment which shall be packaged by the Project Leader as a project output. 2. Services to be rendered. The S & T Consultatnt shall; a. review existing feed formulations & recommend enhancements for improved efficiency & efficacy; b. Provide Technical guidance in the development of nutritionally balanced feed formulations; and c. Assist in ensuing compliance with quality control standards & best practices in feed formulation processes 3. Servicesto be rendered. The S & T Consultant shall; a. Lead the improvement of record-keeping systems & quantitative data analysis; b. Support the encoding & management of performance data in the Philippine Native Pig Breed Information System; c. Provide technical assistance in data analysis and animal performance evaluation, and d. Assist in the preparation & submission of the projects accomplishment, which shall be packaged by the Project Leader as a project output. | J105: 12 | K105: months | L105: 3000 | M105: =SUM(J105*L105) -> 36000 | O105: =SUM(J105*N105) -> 0 | P105: for research project "Developing Feed Formulation for Bagu Ivatan Using Locally -Available Feeds and Forages" | Q105: Agriculture | Y105: Acad7 | AB105: there is changes in payment for consultant
A106: 2025 | B106: October | C106: SYRA KARLA C. GORDO | D106: PTS I | E106: 165 | G106: 2025-358 | I106: HDPE Pipe 1/2" 100m/roll | J106: 2 | K106: rolls | L106: 3300 | M106: =SUM(J106*L106) -> 6600 | N106: 2550 | O106: =SUM(J106*N106) -> 5100 | P106: for the implementation of the project-charged to S & T based interventions for sustainable tourism in Batanes | Q106: RDET-S & T | R106: October 28, 2025 | S106: November 7, 2025 | T106: November 3, 2025 | U106: November 27, 2025 | V106: November 27, 2025 | W106: FVA Trading | X106: November 27, 2025 | Y106: 1005 | Z106: December 5, 2025 | AA106: complete | AB106: for payment-Acctg. | AC106: 07-02-2025-11-0402 | AD106: 4 RFQ's | AE106: 3220/11/28/2025
A107: 2025 | B107: October | C107: SYRA KARLA C. GORDO | D107: PTS I | E107: 165 | G107: 2025-358 | I107: Water Meter | J107: 1 | K107: pc | L107: 1600 | M107: =SUM(J107*L107) -> 1600 | N107: 1300 | O107: =SUM(J107*N107) -> 1300 | P107: for the implementation of the project-charged to S & T based interventions for sustainable tourism in Batanes | Q107: RDET-S & T | R107: October 28, 2025 | S107: November 7, 2025 | T107: November 3, 2025 | U107: November 27, 2025 | V107: November 27, 2025 | W107: FVA Trading | X107: November 27, 2025 | Y107: 1005 | Z107: December 5, 2025 | AA107: complete | AB107: for payment-Acctg. | AC107: 07-02-2025-11-0402
A108: 2025 | B108: October | C108: SYRA KARLA C. GORDO | D108: PTS I | E108: 165 | G108: 2025-358 | I108: Gate Valve | J108: 1 | K108: pc | L108: 450 | M108: =SUM(J108*L108) -> 450 | N108: 320 | O108: =SUM(J108*N108) -> 320 | P108: for the implementation of the project-charged to S & T based interventions for sustainable tourism in Batanes | Q108: RDET-S & T | R108: October 28, 2025 | S108: November 7, 2025 | T108: November 3, 2025 | U108: November 27, 2025 | V108: November 27, 2025 | W108: FVA Trading | X108: November 27, 2025 | Y108: 1005 | Z108: December 5, 2025 | AA108: complete | AB108: for payment-Acctg. | AC108: 07-02-2025-11-0402
A109: 2025 | B109: October | C109: SYRA KARLA C. GORDO | D109: PTS I | E109: 165 | G109: 2025-358 | I109: HDPE Male Adaptor 1/2" | J109: 4 | K109: pcs | L109: 180 | M109: =SUM(J109*L109) -> 720 | N109: 120 | O109: =SUM(J109*N109) -> 480 | P109: for the implementation of the project-charged to S & T based interventions for sustainable tourism in Batanes | Q109: RDET-S & T | R109: October 28, 2025 | S109: November 7, 2025 | T109: November 3, 2025 | U109: November 27, 2025 | V109: November 27, 2025 | W109: FVA Trading | X109: November 27, 2025 | Y109: 1005 | Z109: December 5, 2025 | AA109: complete | AB109: for payment-Acctg. | AC109: 07-02-2025-11-0402
A110: 2025 | B110: October | C110: SYRA KARLA C. GORDO | D110: PTS I | E110: 165 | G110: 2025-358 | I110: HDPE Coupling 1/2" | J110: 4 | K110: pcs | L110: 120 | M110: =SUM(J110*L110) -> 480 | N110: 50 | O110: =SUM(J110*N110) -> 200 | P110: for the implementation of the project-charged to S & T based interventions for sustainable tourism in Batanes | Q110: RDET-S & T | R110: October 28, 2025 | S110: November 7, 2025 | T110: November 3, 2025 | U110: November 27, 2025 | V110: November 27, 2025 | W110: FVA Trading | X110: November 27, 2025 | Y110: 1005 | Z110: December 5, 2025 | AA110: complete | AB110: for payment-Acctg. | AC110: 07-02-2025-11-0402
A111: 2025 | B111: October | C111: SYRA KARLA C. GORDO | D111: PTS I | E111: 165 | G111: 2025-358 | I111: Saddle Clamp 75mm 1/2" | J111: 1 | K111: pc | L111: 600 | M111: =SUM(J111*L111) -> 600 | N111: 400 | O111: =SUM(J111*N111) -> 400 | P111: for the implementation of the project-charged to S & T based interventions for sustainable tourism in Batanes | Q111: RDET-S & T | R111: October 28, 2025 | S111: November 7, 2025 | T111: November 3, 2025 | U111: November 27, 2025 | V111: November 27, 2025 | W111: FVA Trading | X111: November 27, 2025 | Y111: 1005 | Z111: December 5, 2025 | AA111: complete | AB111: for payment-Acctg. | AC111: 07-02-2025-11-0402
A112: 2025 | B112: October | C112: ROMINA KATRINA B. BERNARDO | D112: DAFS | E112: 101 | F112: Dir. Acqui. | G112: 2025-359 | I112: Rellenong Bangus | J112: 4 | K112: trays | L112: 1700 | M112: =SUM(J112*L112) -> 6800 | N112: 1700 | O112: =SUM(J112*N112) -> 6800 | P112: food in celebration of World Teacher's Month | Q112: DAFS | T112: October 9, 2025 | U112: October 14, 2025 | V112: October 7, 2025 | W112: Biang's Catering Services | X112: October 3, 2025 | Y112: GAS23 | Z112: October 28, 2025 | AA112: complete | AB112: for payment-Acctg. | AC112: 02-101101-2025-10-00826 | AE112: 0108/10/03/2025
A113: 2025 | B113: October | C113: ROMINA KATRINA B. BERNARDO | D113: DAFS | E113: 101 | G113: 2025-359 | I113: Fish Lumpia | J113: 5 | K113: trays | L113: 1300 | M113: =SUM(J113*L113) -> 6500 | N113: 1300 | O113: =SUM(J113*N113) -> 6500 | P113: food in celebration of World Teacher's Month | Q113: DAFS | T113: October 9, 2025 | U113: October 14, 2025 | V113: October 7, 2025 | W113: Biang's Catering Services | X113: October 3, 2025 | Y113: GAS23 | Z113: October 28, 2025 | AA113: complete | AB113: for payment-Acctg. | AC113: 02-101101-2025-10-00826
A114: 2025 | B114: October | C114: ROMINA KATRINA B. BERNARDO | D114: DAFS | E114: 101 | G114: 2025-359 | I114: Pork Sisig | J114: 5 | K114: trays | L114: 1600 | M114: =SUM(J114*L114) -> 8000 | N114: 1600 | O114: =SUM(J114*N114) -> 8000 | P114: food in celebration of World Teacher's Month | Q114: DAFS | T114: October 9, 2025 | U114: October 14, 2025 | V114: October 7, 2025 | W114: Biang's Catering Services | X114: October 3, 2025 | Y114: GAS23 | Z114: October 28, 2025 | AA114: complete | AB114: for payment-Acctg. | AC114: 02-101101-2025-10-00826
A115: 2025 | B115: October | C115: JANE S. CASTILLO | D115: Futures Thinking & Strategic Foresight Coordinator | E115: 101 | G115: 2025-360 | I115: Medium Roast Soluble Coffee intensify 5 Instatnt Coffee (bottled 200g) 1 year | J115: 3 | K115: bottle | L115: 1050 | M115: =SUM(J115*L115) -> 3150 | N115: 1318 | O115: =SUM(J115*N115) -> 3954 | P115: office supplies for Futures Thinking office | Q115: RDET-Futures Thinking | R115: November 7, 2025 | S115: November 14, 2025 | T115: November 17, 2025 | U115: November 25, 2025 | V115: December 17, 2025 | W115: Apostol General Merchandise | X115: December 23, 2025 | Y115: 1005 | Z115: January 20, 2026 | AA115: complete | AB115: for payment-Acctg. | AC115: 02-102101-2025-11-00936 | AD115: 3 RFQ's | AE115: 3264/
A116: 2025 | B116: October | C116: JANE S. CASTILLO | D116: Futures Thinking & Strategic Foresight Coordinator | E116: 101 | G116: 2025-360 | I116: Refined Washed Sugar ( 1 year expiration) | J116: 3 | K116: kg | L116: 105 | M116: =SUM(J116*L116) -> 315 | N116: 120 | O116: =SUM(J116*N116) -> 360 | P116: office supplies for Futures Thinking office | Q116: RDET-Futures Thinking | R116: November 7, 2025 | S116: November 14, 2025 | T116: November 17, 2025 | U116: November 25, 2025 | V116: December 17, 2025 | W116: Apostol General Merchandise | X116: December 23, 2025 | Y116: 1005 | Z116: January 20, 2026 | AA116: complete | AB116: for payment-Acctg. | AC116: 02-102101-2025-11-00936
A117: 2025 | B117: October | C117: JANE S. CASTILLO | D117: Futures Thinking & Strategic Foresight Coordinator | E117: 101 | G117: 2025-360 | I117: Assorted Biscuit in plastic pail (1.5kg)- 1 year expiration | J117: 5 | K117: pail | L117: 550 | M117: =SUM(J117*L117) -> 2750 | N117: 380 | O117: =SUM(J117*N117) -> 1900 | P117: office supplies for Futures Thinking office | Q117: RDET-Futures Thinking | R117: November 7, 2025 | S117: November 14, 2025 | T117: November 17, 2025 | U117: November 25, 2025 | V117: December 17, 2025 | W117: Apostol General Merchandise | X117: December 23, 2025 | Y117: 1005 | Z117: January 20, 2026 | AA117: complete | AB117: for payment-Acctg. | AC117: 02-102101-2025-11-00936
A118: 2025 | B118: October | C118: ROMINA KATRINA B. BERNARDO | D118: DAFS | E118: 101 | F118: Dir. Acqui. | G118: 2025-361 | I118: Totebag with printed design (size: 12" x 14") | J118: 105 | K118: pcs | L118: 180 | M118: =SUM(J118*L118) -> 18900 | N118: 180 | O118: =SUM(J118*N118) -> 18900 | P118: supplies & materials in celebration of World Teacher's Month | Q118: DAFS | T118: December 1, 2025 | U118: December 1, 2025 | V118: December 8, 2025 | W118: Printopia Digital Printing Shop | X118: December 8, 2025 | Y118: GAS23 | Z118: February 3, 2026 | AA118: complete | AB118: for payment-Acctg. | AC118: 02-101101-2025-12-00987 | AD118: 3 RFQ's | AE118: 0007/12/8/2025
A119: 2025 | B119: October | C119: MARVIN KEITH C. ALAVADO | D119: Project Staff I | E119: 165 | G119: 2025-362 | I119: SendGrid API Service Subscription (Essential Package) | J119: 24 | K119: months | L119: 2000 | M119: =SUM(J119*L119) -> 48000 | N119: 1880 | O119: =SUM(J119*N119) -> 45120 | P119: S & T Sustainable Tourism-Component 4, Tourism Web Portal-API services integration | Q119: RDET-S & T | R119: October 30, 2025 | S119: October 30, 2025 | T119: November 3, 2025 | U119: December 15, 2025 | V119: February 17, 2026 | W119: M.G.Hubalde's General Merchandise | X119: March 12, 2026 | Y119: 1005 | Z119: March 17, 2026 | AA119: complete | AB119: for payment-Acctg. | AC119: 07-02-2025-11-0423 | AD119: 4 RFQ's | AE119: 13581-13582/312/2026
A120: 2025 | B120: October | C120: MARVIN KEITH C. ALAVADO | D120: Project Staff I | E120: 165 | G120: 2025-362 | I120: Supabase Database & Storage Platform (Pro Package) | J120: 24 | K120: months | L120: 2300 | M120: =SUM(J120*L120) -> 55200 | N120: 2300 | O120: =SUM(J120*N120) -> 55200 | P120: S & T Sustainable Tourism-Component 4, Tourism Web Portal-API services integration | Q120: RDET-S & T | R120: October 30, 2025 | S120: October 30, 2025 | T120: November 3, 2025 | U120: December 15, 2025 | V120: February 17, 2026 | W120: M.G.Hubalde's General Merchandise | X120: March 12, 2026 | Y120: 1005 | Z120: March 17, 2026 | AA120: complete | AB120: for payment-Acctg. | AC120: 07-02-2025-11-0423
A121: 2025 | B121: October | C121: MARVIN KEITH C. ALAVADO | D121: Project Staff I | E121: 165 | G121: 2025-362 | I121: Vercel Online Hosting Platform (Pro Package) | J121: 24 | K121: months | L121: 2000 | M121: =SUM(J121*L121) -> 48000 | N121: 1950 | O121: =SUM(J121*N121) -> 46800 | P121: S & T Sustainable Tourism-Component 4, Tourism Web Portal-API services integration | Q121: RDET-S & T | R121: October 30, 2025 | S121: October 30, 2025 | T121: November 3, 2025 | U121: December 15, 2025 | V121: February 17, 2026 | W121: M.G.Hubalde's General Merchandise | X121: March 12, 2026 | Y121: 1005 | Z121: March 17, 2026 | AA121: complete | AB121: for payment-Acctg. | AC121: 07-02-2025-11-0423
A122: 2025 | B122: October | C122: MARVIN KEITH C. ALAVADO | D122: Project Staff I | E122: 165 | G122: 2025-362 | I122: Domain Name Registration (.com/.com.ph) | J122: 2 | K122: years | L122: 7000 | M122: =SUM(J122*L122) -> 14000 | N122: 6750 | O122: =SUM(J122*N122) -> 13500 | P122: S & T Sustainable Tourism-Component 4, Tourism Web Portal-API services integration | Q122: RDET-S & T | R122: October 30, 2025 | S122: October 30, 2025 | T122: November 3, 2025 | U122: December 15, 2025 | V122: February 17, 2026 | W122: M.G.Hubalde's General Merchandise | X122: March 12, 2026 | Y122: 1005 | Z122: March 17, 2026 | AA122: complete | AB122: for payment-Acctg. | AC122: 07-02-2025-11-0423
A123: 2025 | B123: October | C123: MARVIN KEITH C. ALAVADO | D123: Project Staff I | E123: 165 | G123: 2025-362 | I123: Google Map SDK Gateway API Service (Computed) | J123: 24 | K123: months | L123: 3000 | M123: =SUM(J123*L123) -> 72000 | N123: 3000 | O123: =SUM(J123*N123) -> 72000 | P123: S & T Sustainable Tourism-Component 4, Tourism Web Portal-API services integration | Q123: RDET-S & T | R123: October 30, 2025 | S123: October 30, 2025 | T123: November 3, 2025 | U123: December 15, 2025 | V123: February 17, 2026 | W123: M.G.Hubalde's General Merchandise | X123: March 12, 2026 | Y123: 1005 | Z123: March 17, 2026 | AA123: complete | AB123: for payment-Acctg. | AC123: 07-02-2025-11-0423
A124: 2025 | B124: October | C124: CECILIA S. NIPES | D124: Administrative Assistant II | G124: 2025-363 | I124: Expansion Portable Drive (HDD, 2 TB) | J124: 2 | K124: pc | L124: 6000 | M124: =SUM(J124*L124) -> 12000 | O124: =SUM(J124*N124) -> 0 | P124: office repository/for back up storage of office files | Q124: HRMO | Y124: GAS14 | AA124: FAILED | AB124: quotation exceeded the budget | AD124: 5 RFQ's
A125: 2025 | B125: October | C125: ANGELITA H. VARGAS | D125: College Vice President | E125: 101 | G125: 2025-364 | I125: 001-Black | J125: 2 | K125: bottles | L125: 600 | M125: =SUM(J125*L125) -> 1200 | N125: 800 | O125: =SUM(J125*N125) -> 1600 | P125: vice president office supplies | Q125: OVP | R125: October 28, 2025 | S125: Noveber 12, 2025 | T125: November 13, 2025 | U125: November 26, 2025 | V125: November 26, 2025 | W125: YCA Office Supplies & Equipment Trading | X125: November 27, 2025 | Y125: Acad8 | Z125: Dcember 16, 2025 | AA125: complete | AB125: for payment-Acctg. | AC125: 02-101101-2025-11-00918 | AD125: 5 RFQ's | AE125: 317/11/26/2025
A126: 2025 | B126: October | C126: ANGELITA H. VARGAS | D126: College Vice President | E126: 101 | G126: 2025-364 | I126: BTD100BK-black | J126: 2 | K126: bottles | L126: 650 | M126: =SUM(J126*L126) -> 1300 | N126: 460 | O126: =SUM(J126*N126) -> 920 | P126: vice president office supplies | Q126: OVP | R126: October 28, 2025 | S126: Noveber 12, 2025 | T126: November 13, 2025 | U126: November 26, 2025 | V126: November 26, 2025 | W126: YCA Office Supplies & Equipment Trading | X126: November 27, 2025 | Y126: Acad8 | Z126: Dcember 16, 2025 | AA126: complete | AB126: for payment-Acctg. | AC126: 02-101101-2025-11-00918
A127: 2025 | B127: October | C127: ANGELITA H. VARGAS | D127: College Vice President | E127: 101 | G127: 2025-364 | I127: BTD100C-cyan | J127: 2 | K127: bottles | L127: 650 | M127: =SUM(J127*L127) -> 1300 | N127: 460 | O127: =SUM(J127*N127) -> 920 | P127: vice president office supplies | Q127: OVP | R127: October 28, 2025 | S127: Noveber 12, 2025 | T127: November 13, 2025 | U127: November 26, 2025 | V127: November 26, 2025 | W127: YCA Office Supplies & Equipment Trading | X127: November 27, 2025 | Y127: Acad8 | Z127: Dcember 16, 2025 | AA127: complete | AB127: for payment-Acctg. | AC127: 02-101101-2025-11-00918
A128: 2025 | B128: October | C128: ANGELITA H. VARGAS | D128: College Vice President | E128: 101 | G128: 2025-364 | I128: BTD100M-magenta | J128: 2 | K128: bottles | L128: 650 | M128: =SUM(J128*L128) -> 1300 | N128: 460 | O128: =SUM(J128*N128) -> 920 | P128: vice president office supplies | Q128: OVP | R128: October 28, 2025 | S128: Noveber 12, 2025 | T128: November 13, 2025 | U128: November 26, 2025 | V128: November 26, 2025 | W128: YCA Office Supplies & Equipment Trading | X128: November 27, 2025 | Y128: Acad8 | Z128: Dcember 16, 2025 | AA128: complete | AB128: for payment-Acctg. | AC128: 02-101101-2025-11-00918
A129: 2025 | B129: October | C129: ANGELITA H. VARGAS | D129: College Vice President | E129: 101 | G129: 2025-364 | I129: BTD100Y-yellow | J129: 2 | K129: bottles | L129: 650 | M129: =SUM(J129*L129) -> 1300 | N129: 460 | O129: =SUM(J129*N129) -> 920 | P129: vice president office supplies | Q129: OVP | R129: October 28, 2025 | S129: Noveber 12, 2025 | T129: November 13, 2025 | U129: November 26, 2025 | V129: November 26, 2025 | W129: YCA Office Supplies & Equipment Trading | X129: November 27, 2025 | Y129: Acad8 | Z129: Dcember 16, 2025 | AA129: complete | AB129: for payment-Acctg. | AC129: 02-101101-2025-11-00918
A130: 2025 | B130: October | C130: FORTUNATO PHILLIP A. CABUGAO | D130: Director for Student Services | G130: 2025-365 | I130: KD Lumber 2"x 3" x12' | J130: 5 | K130: pcs | L130: 600 | M130: =SUM(J130*L130) -> 3000 | O130: =SUM(J130*N130) -> 0 | P130: framework of Tarpaulin for Student Services | Q130: SSO | Y130: SS09 | AB130: quotation exceeded the budget | AD130: 4 RFQ's
A131: 2025 | B131: October | C131: FORTUNATO PHILLIP A. CABUGAO | D131: Director for Student Services | G131: 2025-365 | I131: CWN 2 1/2" | J131: 1 | K131: kg | L131: 100 | M131: =SUM(J131*L131) -> 100 | O131: =SUM(J131*N131) -> 0 | P131: framework of Tarpaulin for Student Services | Q131: SSO | Y131: SS09
A132: 2025 | B132: October | C132: FORTUNATO PHILLIP A. CABUGAO | D132: Director for Student Services | G132: 2025-365 | I132: Marine plywood 1/2" | J132: 2 | K132: pcs | L132: 1000 | M132: =SUM(J132*L132) -> 2000 | O132: =SUM(J132*N132) -> 0 | P132: framework of Tarpaulin for Student Services | Q132: SSO | Y132: SS09
A133: 2025 | B133: October | C133: FORTUNATO PHILLIP A. CABUGAO | D133: Director for Student Services | E133: 165 | G133: 2025-366 | I133: Tarpaulin (5' x 10') | J133: 1 | K133: pc | L133: 2500 | M133: =SUM(J133*L133) -> 2500 | N133: 1500 | O133: =SUM(J133*N133) -> 1500 | P133: for signages of property wardrobe for student | Q133: SSO | R133: October 28, 2025 | S133: November 7, 2025 | T133: November 11, 2025 | U133: November 17, 2025 | V133: December 17, 2025 | W133: YCA Printing Services | X133: December 17, 2025 | Y133: SS09 | Z133: January 28, 2026 | AA133: complete | AB133: for payment-Acctg. | AC133: 07-02-2025-11-0398 | AD133: 3 RFQ's | AE133: 408/1/28/2026
A134: 2025 | B134: October | C134: MARIE FE E. PABLEO | D134: Board Secretary I | G134: 2025-367 | I134: Snacks & Drinks | J134: 6 | K134: packs | L134: 300 | M134: =SUM(J134*L134) -> 1800 | O134: =SUM(J134*N134) -> 0 | P134: snacks & drinks for the Search Committee for Private Sector Representative (SCPSR) for the preliminary meeting | Q134: OBS | Y134: GAS2
A135: 2025 | B135: October | C135: ANGELITA H. VARGAS | D135: Vice President | E135: 101 | G135: 2025-368 | I135: Tarpaulin (8 x 5ft) | J135: 1 | K135: pc | L135: 1400 | M135: =SUM(J135*L135) -> 1400 | N135: 1200 | O135: =SUM(J135*N135) -> 1200 | P135: to commemorate the 28th anniversary of the Indigenous Peoples Right Act (IPCRA) of 1997 | Q135: OVP | R135: October 28, 2025 | S135: November 12, 2025 | T135: November 13, 2025 | U135: November 26, 2025 | V135: November 26, 2025 | W135: YCA Printing Services | X135: November 26, 2025 | Y135: Acad8 | Z135: January 20, 2026 | AA135: complete | AB135: for payment-Acctg. | AC135: 02-101101-2025-11-00917 | AD135: 3 RFQ's | AE135: 396/11/26/2025
A136: 2025 | B136: October | C136: ALFRED VINCENT BACCAY | D136: SSC President | G136: 2025-369 | I136: Ink (001-Magenta, Cyan, Yellow & Black) | J136: 5 | K136: sets | L136: 1075 | M136: =SUM(J136*L136) -> 5375 | O136: =SUM(J136*N136) -> 0 | P136: SSC supplies | Q136: SSC | Y136: SS09 | AB136: quotation exceeded the budget | AD136: 5 RFQ's
A137: 2025 | B137: October | C137: ALFRED VINCENT BACCAY | D137: SSC President | G137: 2025-369 | I137: 8.1/4 inch Ergonomic Stainless Office Scissors | J137: 3 | K137: pcs | L137: 60 | M137: =SUM(J137*L137) -> 180 | O137: =SUM(J137*N137) -> 0 | P137: SSC supplies | Q137: SSC | Y137: SS09
A138: 2025 | B138: October | C138: ALFRED VINCENT BACCAY | D138: SSC President | G138: 2025-369 | I138: 12 HB2 Pencil with Eraser Tip | J138: 5 | K138: box | L138: 250 | M138: =SUM(J138*L138) -> 1250 | O138: =SUM(J138*N138) -> 0 | P138: SSC supplies | Q138: SSC | Y138: SS09
A139: 2025 | B139: October | C139: JANE S. CASTILLO | D139: Project Leader | E139: 165 | F139: Del. Oct. 17 | G139: 2025-370 | I139: Dukay Rootcrops (fresh,cleaned, high-quality produce) | J139: 50 | K139: kg | L139: 150 | M139: =SUM(J139*L139) -> 7500 | N139: 135 | O139: =SUM(J139*N139) -> 6750 | P139: supplies & materials for the Tugi Cereal Research Project | Q139: RDET | R139: November 7, 2025 | S139: November 14, 2025 | T139: November 17, 2025 | U139: November 18, 2025 | V139: November 18, 2025 | W139: Sophia Marie Store | X139: November 18, 2025 | Y139: 1005 | Z139: December 16, 2025 | AA139: complete | AB139: for payment-Acctg. | AC139: 07-02-2025-11-0421 | AD139: 3 RFQ's | AE139: 1356/11/18/2025
A140: 2025 | B140: October | C140: JENNY S. ALINA | D140: Socio-Cultural Coordinator | E140: 165 | F140: Intrams | G140: 2025-371 | I140: Water Based Paint Red (Acrylic 20ml) | J140: 15 | K140: pcs | L140: 30 | M140: =SUM(J140*L140) -> 450 | N140: 25 | O140: =SUM(J140*N140) -> 375 | P140: for the conduct of 2025 College Intramurals & Socio- Cultural Competition | Q140: Socio-cultural | R140: October 28, 2025 | S140: November 7, 2025 | T140: November 11, 2025 | U140: November 17, 2025 | V140: November 18, 2025 | W140: JPM General Merchandise & Hardware | X140: November 18, 2025 | Y140: SS07 | Z140: November 28, 2025 | AA140: complete | AB140: for payment-Acctg. | AC140: 07-02-2025-11-0399 | AD140: 6 RFQ's | AE140: 13267/11/20/25
A141: 2025 | B141: October | C141: JENNY S. ALINA | D141: Socio-Cultural Coordinator | E141: 165 | G141: 2025-371 | I141: Water Based Paint Blue (Acrylic 20ml) | J141: 15 | K141: pcs | L141: 30 | M141: =SUM(J141*L141) -> 450 | N141: 25 | O141: =SUM(J141*N141) -> 375 | P141: for the conduct of 2025 College Intramurals & Socio- Cultural Competition | Q141: Socio-cultural | R141: October 28, 2025 | S141: November 7, 2025 | T141: November 11, 2025 | U141: November 17, 2025 | V141: November 18, 2025 | W141: JPM General Merchandise & Hardware | X141: November 18, 2025 | Y141: SS07 | Z141: November 28, 2025 | AA141: complete | AB141: for payment-Acctg. | AC141: 07-02-2025-11-0399
A142: 2025 | B142: October | C142: JENNY S. ALINA | D142: Socio-Cultural Coordinator | E142: 165 | G142: 2025-371 | I142: Water Based Paint Yellow (Acrylic 20ml) | J142: 15 | K142: pcs | L142: 30 | M142: =SUM(J142*L142) -> 450 | N142: 25 | O142: =SUM(J142*N142) -> 375 | P142: for the conduct of 2025 College Intramurals & Socio- Cultural Competition | Q142: Socio-cultural | R142: October 28, 2025 | S142: November 7, 2025 | T142: November 11, 2025 | U142: November 17, 2025 | V142: November 18, 2025 | W142: JPM General Merchandise & Hardware | X142: November 18, 2025 | Y142: SS07 | Z142: November 28, 2025 | AA142: complete | AB142: for payment-Acctg. | AC142: 07-02-2025-11-0399
A143: 2025 | B143: October | C143: JENNY S. ALINA | D143: Socio-Cultural Coordinator | E143: 165 | G143: 2025-371 | I143: Water Based Paint White (Acrylic 20ml) | J143: 15 | K143: pcs | L143: 30 | M143: =SUM(J143*L143) -> 450 | N143: 25 | O143: =SUM(J143*N143) -> 375 | P143: for the conduct of 2025 College Intramurals & Socio- Cultural Competition | Q143: Socio-cultural | R143: October 28, 2025 | S143: November 7, 2025 | T143: November 11, 2025 | U143: November 17, 2025 | V143: November 18, 2025 | W143: JPM General Merchandise & Hardware | X143: November 18, 2025 | Y143: SS07 | Z143: November 28, 2025 | AA143: complete | AB143: for payment-Acctg. | AC143: 07-02-2025-11-0399
A144: 2025 | B144: October | C144: JENNY S. ALINA | D144: Socio-Cultural Coordinator | E144: 165 | G144: 2025-371 | I144: 12" x 18" canvass | J144: 10 | K144: pcs | L144: 185 | M144: =SUM(J144*L144) -> 1850 | N144: 165 | O144: =SUM(J144*N144) -> 1650 | P144: for the conduct of 2025 College Intramurals & Socio- Cultural Competition | Q144: Socio-cultural | R144: October 28, 2025 | S144: November 7, 2025 | T144: November 11, 2025 | U144: November 17, 2025 | V144: November 18, 2025 | W144: JPM General Merchandise & Hardware | X144: November 18, 2025 | Y144: SS07 | Z144: November 28, 2025 | AA144: complete | AB144: for payment-Acctg. | AC144: 07-02-2025-11-0399
A145: 2025 | B145: October | C145: JENNY S. ALINA | D145: Socio-Cultural Coordinator | E145: 165 | G145: 2025-371 | I145: Lumograph Pencil 2H/3H | J145: 5 | K145: pcs | L145: 60 | M145: =SUM(J145*L145) -> 300 | N145: 50 | O145: =SUM(J145*N145) -> 250 | P145: for the conduct of 2025 College Intramurals & Socio- Cultural Competition | Q145: Socio-cultural | R145: October 28, 2025 | S145: November 7, 2025 | T145: November 11, 2025 | U145: November 17, 2025 | V145: November 18, 2025 | W145: JPM General Merchandise & Hardware | X145: November 18, 2025 | Y145: SS07 | Z145: November 28, 2025 | AA145: complete | AB145: for payment-Acctg. | AC145: 07-02-2025-11-0399
A146: 2025 | B146: October | C146: JENNY S. ALINA | D146: Socio-Cultural Coordinator | E146: 165 | G146: 2025-371 | I146: Lumograph Pencil B/2B | J146: 5 | K146: pcs | L146: 60 | M146: =SUM(J146*L146) -> 300 | N146: 50 | O146: =SUM(J146*N146) -> 250 | P146: for the conduct of 2025 College Intramurals & Socio- Cultural Competition | Q146: Socio-cultural | R146: October 28, 2025 | S146: November 7, 2025 | T146: November 11, 2025 | U146: November 17, 2025 | V146: November 18, 2025 | W146: JPM General Merchandise & Hardware | X146: November 18, 2025 | Y146: SS07 | Z146: November 28, 2025 | AA146: complete | AB146: for payment-Acctg. | AC146: 07-02-2025-11-0399
A147: 2025 | B147: October | C147: JENNY S. ALINA | D147: Socio-Cultural Coordinator | E147: 165 | G147: 2025-371 | I147: Lumograph Pencil 5B/6B | J147: 5 | K147: pcs | L147: 60 | M147: =SUM(J147*L147) -> 300 | N147: 50 | O147: =SUM(J147*N147) -> 250 | P147: for the conduct of 2025 College Intramurals & Socio- Cultural Competition | Q147: Socio-cultural | R147: October 28, 2025 | S147: November 7, 2025 | T147: November 11, 2025 | U147: November 17, 2025 | V147: November 18, 2025 | W147: JPM General Merchandise & Hardware | X147: November 18, 2025 | Y147: SS07 | Z147: November 28, 2025 | AA147: complete | AB147: for payment-Acctg. | AC147: 07-02-2025-11-0399
A148: 2025 | B148: October | C148: JENNY S. ALINA | D148: Socio-Cultural Coordinator | E148: 165 | G148: 2025-371 | I148: Charcoal Pencil Dark | J148: 5 | K148: pcs | L148: 85 | M148: =SUM(J148*L148) -> 425 | N148: 80 | O148: =SUM(J148*N148) -> 400 | P148: for the conduct of 2025 College Intramurals & Socio- Cultural Competition | Q148: Socio-cultural | R148: October 28, 2025 | S148: November 7, 2025 | T148: November 11, 2025 | U148: November 17, 2025 | V148: November 18, 2025 | W148: JPM General Merchandise & Hardware | X148: November 18, 2025 | Y148: SS07 | Z148: November 28, 2025 | AA148: complete | AB148: for payment-Acctg. | AC148: 07-02-2025-11-0399
A149: 2025 | B149: October | C149: JENNY S. ALINA | D149: Socio-Cultural Coordinator | E149: 165 | G149: 2025-371 | I149: Charcoal Pencil Medium | J149: 5 | K149: pcs | L149: 85 | M149: =SUM(J149*L149) -> 425 | N149: 80 | O149: =SUM(J149*N149) -> 400 | P149: for the conduct of 2025 College Intramurals & Socio- Cultural Competition | Q149: Socio-cultural | R149: October 28, 2025 | S149: November 7, 2025 | T149: November 11, 2025 | U149: November 17, 2025 | V149: November 18, 2025 | W149: JPM General Merchandise & Hardware | X149: November 18, 2025 | Y149: SS07 | Z149: November 28, 2025 | AA149: complete | AB149: for payment-Acctg. | AC149: 07-02-2025-11-0399
A150: 2025 | B150: October | C150: JENNY S. ALINA | D150: Socio-Cultural Coordinator | E150: 165 | G150: 2025-371 | I150: Charcoal Pencil Light | J150: 5 | K150: pcs | L150: 85 | M150: =SUM(J150*L150) -> 425 | N150: 80 | O150: =SUM(J150*N150) -> 400 | P150: for the conduct of 2025 College Intramurals & Socio- Cultural Competition | Q150: Socio-cultural | R150: October 28, 2025 | S150: November 7, 2025 | T150: November 11, 2025 | U150: November 17, 2025 | V150: November 18, 2025 | W150: JPM General Merchandise & Hardware | X150: November 18, 2025 | Y150: SS07 | Z150: November 28, 2025 | AA150: complete | AB150: for payment-Acctg. | AC150: 07-02-2025-11-0399
A151: 2025 | B151: October | C151: JENNY S. ALINA | D151: Socio-Cultural Coordinator | E151: 165 | G151: 2025-371 | I151: Cartolina White | J151: 20 | K151: pcs | L151: 15 | M151: =SUM(J151*L151) -> 300 | N151: 15 | O151: =SUM(J151*N151) -> 300 | P151: for the conduct of 2025 College Intramurals & Socio- Cultural Competition | Q151: Socio-cultural | R151: October 28, 2025 | S151: November 7, 2025 | T151: November 11, 2025 | U151: November 17, 2025 | V151: November 18, 2025 | W151: JPM General Merchandise & Hardware | X151: November 18, 2025 | Y151: SS07 | Z151: November 28, 2025 | AA151: complete | AB151: for payment-Acctg. | AC151: 07-02-2025-11-0399
A152: 2025 | B152: October | C152: JENNY S. ALINA | D152: Socio-Cultural Coordinator | E152: 165 | G152: 2025-371 | I152: Professional Paint Brush Set 6's (sizes: 2,4,6,8,10,12/per set) | J152: 8 | K152: sets | L152: 230 | M152: =SUM(J152*L152) -> 1840 | N152: 200 | O152: =SUM(J152*N152) -> 1600 | P152: for the conduct of 2025 College Intramurals & Socio- Cultural Competition | Q152: Socio-cultural | R152: October 28, 2025 | S152: November 7, 2025 | T152: November 11, 2025 | U152: November 17, 2025 | V152: November 18, 2025 | W152: JPM General Merchandise & Hardware | X152: November 18, 2025 | Y152: SS07 | Z152: November 28, 2025 | AA152: complete | AB152: for payment-Acctg. | AC152: 07-02-2025-11-0399
... A155: 2025 | B155: October | C155: JENNY S. ALINA | D155: Socio-Cultural Coordinator | E155: 165 | G155: 2025-371 | I155: Specialty Paper A4 (white) | J155: 40 | K155: sets | L155: 80 | M155: =SUM(J155*L155) -> 3200 | N155: 65 | O155: =SUM(J155*N155) -> 2600 | P155: for the conduct of 2025 College Intramurals & Socio- Cultural Competition | Q155: Socio-cultural | R155: October 28, 2025 | S155: November 7, 2025 | T155: November 11, 2025 | U155: November 17, 2025 | V155: November 18, 2025 | W155: JPM General Merchandise & Hardware | X155: November 18, 2025 | Y155: SS07 | Z155: November 28, 2025 | AA155: complete | AB155: for payment-Acctg. | AC155: 07-02-2025-11-0399
A156: 2025 | B156: October | C156: FORTUNATO PHILIP A. CABUGAO | D156: Study Leader (Study 2) | E156: 165 | G156: 2025-372 | I156: Celphone - Display;6.67" amoled display, Internal; 128GB 8GB RAM, 256GB 8Gb RAM,256GB 12GB RAM, 512GB 12Gb RAM UFS 2.2, Dimensions; Height; 162.33mm, width; 74.42mm, thickness; Coral green & midnight black 8.4mm l Lavender Purple 8.55mm weight; 190g 511 Omah battery capacity | J156: 1 | K156: unit | L156: 25000 | M156: =SUM(J156*L156) -> 25000 | N156: 25000 | O156: =SUM(J156*N156) -> 25000 | P156: for the implementation of the project 2- charge to S & T sustainable tourism in Batanes | Q156: RDET-S & T | R156: October 25, 2025 | S156: October 27, 2025 | T156: November 3, 2025 | U156: December 23, 2025 | V156: January 23, 2026 | W156: YCA Office Supplies & Equipment | X156: January 27, 2026 | Y156: 1005 | Z156: January 30, 2026 | AA156: complete | AB156: for payment-Acctg. | AC156: 07-02-2025-12-0443A | AD156: 6 RFQ's | AE156: 364/1/23/2026
...

Sheet PR
A3: Republic of the Philippines
A4: BATANES STATE COLLEGE
A5: Basco, Batanes
A7: PURCHASE REQUEST
D9: PR No. | E9: =DATA!G200 -> 2025-380 | F9: Date
A10: Department: | D10: SAI No.:
A11: Section: | B11: =DATA!Y200 -> 1005 | D11: OBR#
A12: Ref. No.: | B12: 2510-1005-380
A14: Qty | B14: Unit of Issue | D14: Item Description | F14: Stock No. | G14: Estimated
G15: Unit Cost | H15: Total Cost
A16: =DATA!J200 -> 60 | B16: =DATA!K200 -> copies | D16: =DATA!I200 -> Printing of Training Manual (Hardbound cover, laminated, colored,15.5 x 23 cm, 70 pages, 80gsm, colored, glossy with ISSN/ISBN number) | G16: =DATA!L200 -> 1350 | H16: =SUM(A16*G16) -> 81000
H17: =SUM(A17*G17) -> 0
H18: =SUM(A18*G18) -> 0
H19: =SUM(A19*G19) -> 0
H20: =SUM(A20*G20) -> 0
H21: =SUM(A21*G21) -> 0
H22: =SUM(A22*G22) -> 0
H23: =SUM(A23*G23) -> 0
H24: =SUM(A24*G24) -> 0
H25: =SUM(A25*G25) -> 0
H26: =SUM(A26*G26) -> 0
H27: =SUM(A27*G27) -> 0
H28: =SUM(A28*G28) -> 0
... H34: =SUM(A34*G34) -> 0
A35: =DATA!J398 -> 5 | B35: =DATA!K398 -> set | D35: =DATA!I398 -> Laddle with wooden handle with hole | G35: =DATA!L398 -> 88.5 | H35: =SUM(A35*G35) -> 442.5
A36: =DATA!J399 -> 5 | B36: =DATA!K399 -> set | D36: =DATA!I399 -> Laddle with wooden handle without hole | G36: =DATA!L399 -> 88.5 | H36: =SUM(A36*G36) -> 442.5
A37: =DATA!J400 -> 5 | B37: =DATA!K400 -> pc | D37: =DATA!I400 -> Measuring Cup Glass | G37: =DATA!L400 -> 349.5 | H37: =SUM(A37*G37) -> 1747.5
A38: =DATA!J401 -> 5 | B38: =DATA!K401 -> set | D38: =DATA!I401 -> Measuring Cup Set Set Includes: 1/4 cup,1/3 cup, 1/2 cup,1 cup | G38: =DATA!L401 -> 198 | H38: =SUM(A38*G38) -> 990
A39: =DATA!J402 -> 5 | B39: =DATA!K402 -> set | D39: =DATA!I402 -> Measuring Spoon Set sets include: 1/8 teaspoon, 1/4 teaspoon, 1/2 teaspoon, 1 teaspoon, 1/ 2 tbsp, 1 tbsp | G39: =DATA!L402 -> 429 | H39: =SUM(A39*G39) -> 2145
A40: =DATA!J403 -> 3 | B40: =DATA!K403 -> set | D40: =DATA!I403 -> Mixing Bowl with Cover 5pcs | G40: =DATA!L403 -> 6547.23 | H40: =SUM(A40*G40) -> 19641.69
A41: =DATA!J404 -> 5 | B41: =DATA!K404 -> set | D41: =DATA!I404 -> Fruit and Vegetable Peeler Stainless Steel 13 cm (5 ") | G41: =DATA!L404 -> 240 | H41: =SUM(A41*G41) -> 1200
A42: =DATA!J405 -> 5 | B42: =DATA!K405 -> set | D42: =DATA!I405 -> Pot Holder Cloth 3pcs/set | G42: =DATA!L405 -> 45 | H42: =SUM(A42*G42) -> 225
A43: =DATA!J406 -> 10 | B43: =DATA!K406 -> pc | D43: =DATA!I406 -> Pot Holder Heat Insulated Gloves Specifications: Color: Grey Material: silicone Size: 20.5x16.5cm | G43: =DATA!L406 -> 118.5 | H43: =SUM(A43*G43) -> 1185
A44: =DATA!J407 -> 2 | B44: =DATA!K407 -> pc | D44: =DATA!I407 -> Knife Sharpener | G44: =DATA!L407 -> 523.5 | H44: =SUM(A44*G44) -> 1047
A45: =DATA!J408 -> 5 | B45: =DATA!K408 -> pc | D45: =DATA!I408 -> Sifter Stainless Steel 270 x 70mm Mesh: #30 (0.595mm) | G45: =DATA!L408 -> 450 | H45: =SUM(A45*G45) -> 2250
A46: =DATA!J409 -> 5 | B46: =DATA!K409 -> pc | D46: =DATA!I409 -> Pitcher Stainless Steel 2000 ml | G46: =DATA!L409 -> 898.5 | H46: =SUM(A46*G46) -> 4492.5
... A73: =DATA!J436 -> 3 | B73: =DATA!K436 -> pc | D73: =DATA!I436 -> Wok Pan 2mm (thickness) 60cm diameter | G73: =DATA!L436 -> 4125 | H73: =SUM(A73*G73) -> 12375
A74: =DATA!J210 -> 1 | B74: =DATA!K437 -> pcs | D74: =DATA!I437 -> Office Desk/Table Material: MDF Color: Walnut Dimensions of Table: 47.24" W x 30.31" H x 23.63" D Drawer Dimensions: 11" W x 23" H x 18.75" D | G74: =DATA!L62 -> 60 | H74: =SUM(A74*G74) -> 60
A75: =DATA!J211 -> 1 | B75: =DATA!K438 -> pcs | D75: =DATA!I438 -> Office Chair - Junior Executive Chair Black Leatherette Ergonomic with padded armrests Chrome base with smooth-rolling caster wheels Seat Dimensions: 21" L x 21" W Backrest Dimensions: 26.5" L x 21" W Full Dimensions: 25" W x 42" - 45" H | G75: =DATA!L63 -> 125 | H75: =SUM(A75*G75) -> 125
A76: =DATA!J212 -> 2 | B76: =DATA!K439 -> pcs | D76: =DATA!I439 -> Portable Projector with bag and stand Product Details: Android 11,500 ANSI DRM L1 Certification nnovative 120°rotating projection ASA 3.0(AF+KS+ScrnFit+Avoid) Dual-bass diaphragms ≤30 dB/m Ultra-low decibel Specifications: Product Color: White Product Weight: 1.5Kg Product Size: 145*142*219 mm Display Technology: LCD Brightness: 500 ANSI Lumens Physical Resolution: 1920 * 1080 FHD Lens： 3 Pcs aspherical pure glass lens Projection Features Zoom Function：50%-100% Projection Ratio: 1.2: 1 Projection Size: 45-140 Inch Projection Distance: 1.2-3.8m Intelligent Adjustment Keystone Correction： Auto Focus Adjustment： Auto Obstacle Avoidance： Auto Screen Alignment： Auto Audio & Connectivity Speaker: 5W * 2 Noise: ≤30dB/m Cavity Volume：370CC Bluetooth: 5.0 WiFi: Dual Band 2.4/5G Hz Interface HDMI：*1 USB：*1 AUX3.5mm：*1 | G76: =DATA!L64 -> 150 | H76: =SUM(A76*G76) -> 300
A77: =DATA!J213 -> 5 | B77: =DATA!K440 -> 0 | D77: =DATA!I440 -> 0 | G77: =DATA!L65 -> 130 | H77: =SUM(A77*G77) -> 650
A78: =DATA!J214 -> 2 | B78: =DATA!K441 -> pcs | D78: =DATA!I66 -> Assorted Coffee 3 in 1 | G78: =DATA!L66 -> 225 | H78: =SUM(A78*G78) -> 450
A79: =DATA!J215 -> 1 | B79: =DATA!K442 -> 0 | D79: =DATA!I67 -> Coke 1.7L | G79: =DATA!L67 -> 1180 | H79: =SUM(A79*G79) -> 1180
A80: =DATA!J216 -> 5 | B80: =DATA!K443 -> pcs | D80: =DATA!I68 -> Bottled Water 1L | G80: =DATA!L68 -> 485 | H80: =SUM(A80*G80) -> 2425
A81: =DATA!J217 -> 1 | B81: =DATA!K444 -> pcs | D81: =DATA!I69 -> Dutchmill 90ml 4's | G81: =DATA!L69 -> 130 | H81: =SUM(A81*G81) -> 130
A82: =DATA!J218 -> 1 | B82: =DATA!K445 -> 0 | D82: =DATA!I70 -> Dutchmill 180ml 4's | G82: =DATA!L70 -> 140 | H82: =SUM(A82*G82) -> 140
A83: =DATA!J219 -> 1 | B83: =DATA!K446 -> pcs | D83: =DATA!I71 -> Chuckie 180ml 6's | G83: =DATA!L71 -> 210 | H83: =SUM(A83*G83) -> 210
A84: =DATA!J220 -> 16 | B84: =DATA!K447 -> pcs | D84: =DATA!I72 -> Cupkeyk | G84: =DATA!L72 -> 98 | H84: =SUM(A84*G84) -> 1568
A85: =DATA!J221 -> 10 | B85: =DATA!K448 -> pcs | D85: =DATA!I73 -> Fudgee Bar | G85: =DATA!L73 -> 125 | H85: =SUM(A85*G85) -> 1250
A86: =DATA!J222 -> 10 | B86: =DATA!K449 -> pack | D86: =DATA!I74 -> Mamon 12's | G86: =DATA!L74 -> 255 | H86: =SUM(A86*G86) -> 2550
A87: =DATA!J223 -> 5 | B87: =DATA!K450 -> pack | D87: =DATA!I75 -> Smart-C Assorted | G87: =DATA!L75 -> 210 | H87: =SUM(A87*G87) -> 1050
A88: =DATA!J224 -> 2 | B88: =DATA!K451 -> pack | D88: =DATA!I76 -> Chuckie 110ml 6's | G88: =DATA!L76 -> 195 | H88: =SUM(A88*G88) -> 390
A89: =DATA!J225 -> 1 | B89: =DATA!K452 -> pack | D89: =DATA!I77 -> Nestea Drink 500ml | G89: =DATA!L77 -> 1000 | H89: =SUM(A89*G89) -> 1000
... A107: =DATA!J243 -> 1 | B107: =DATA!K470 -> pcs | D107: =DATA!I95 -> AM Snack (pasta) | G107: =DATA!L95 -> 200 | H107: =SUM(A107*G107) -> 200
A108: =DATA!J244 -> 0 | B108: =DATA!K471 -> pcs | D108: =DATA!I96 -> AM Snack (pasta with garlic bread and soda) | G108: =DATA!L96 -> 250
A109: =DATA!J245 -> 1 | B109: =DATA!K472 -> pcs | D109: =DATA!I97 -> AM Snack (vegetarian) | G109: =DATA!L97 -> 250
H110: =SUM(H16:H31) -> 81000
A111: Purpose: | B111: =DATA!P200 -> printing of the Production Guide on Native pig raising, titled " Bagu Ivatan; Gabay s pagaalaga ng Native na baboy" (charged to Futures Thinking Fund)
F112: Approved By:
A114: Signature:
A115: Printed Name: | B115: =DATA!C200 -> JANE S. CASTILLO | F115: DJOVI REGALA DURANTE,DPA
A116: Designation: | B116: =DATA!D200 -> Futures Thinking & Strategic Foresight Coordinator | F116: SUC President I
A117: Date:

Sheet ResoSVP (2)
A6: BAC Resolution Recommending Alternative Mode of Procurement under Small Value Procurement
B7: BAC Resolution No. | D7: =PR!B12 -> 2510-1005-380
A9: WHEREAS, Section 48 Rule XVI of the Revised Implementing Rules and Regulations of RA 9184 allows Alternative Mode of Procurement subject to prior approval of the HOPE thru Annual Procurement Plan (APP) and only to promote economy and efficiency;
A10: WHEREAS, Section 53.9 allows Small Value Procurement provided that the procurement does not fall under shopping in Section 52 of this IRR and the amount involved does not exceed the thresholds prescribed in Annex "H" of this IRR;
A11: WHEREAS, Appendix 18, Section 3.e on the Guidelines for Shopping and Small Value Procurement provides an Abstract of Quotations shall be prepared setting forth the names of those who responded to the RFQ's right after the deadline for submission except for shopping under Section 52.1(b), where at least three (3) price quotations (RFQ) must be obtained;
A12: WHEREAS, Annex "H" of the Consolidated Guidelines for the Alternative Methods of Procurement prescribed under Section V, Paragraph D.8.b.ii that the BAC shall prepare and send the RFQs/RFPs to at least three (3) suppliers, contractors or consultants of known qualifications where receipt of at least one (1) quotations is sufficient to proceed with the evaluation thererof;
A13: WHEREAS, Purchase Request No. | D13: =PR!E9 -> 2025-380 | E13: involves the procurement of
A14: AM and PM Snack and Lunch --snacks & lunch for the Joint Academic & Admin meeting
A15: with the approved budget of | D15: =PR!H110 -> 81000
A16: WHEREAS, the default mode of evaluation shall be on a lot basis which means that the determination of the single/lowest calculated and responsive bid (S/LCRB) is the total amount of offered unit price multiply by the required quantity;
A18: NOW THEREFORE, we, the members of the Bids and Awards Committee hereby RESOLVE as it is hereby RESOLVED to recommend to the College President to adopt Alternative Mode of Procurement under Small Value Procurement for the said transaction;
A20: RESOLVED FINALLY, at the Batanes State College, this
A21: Recommending Approval:
A24: RHOUPHELINE AYA A. CADIZ | C24: RANDALL G. CASTILLO | E24: EMILYN D. ALUETA
A25: BAC Member | C25: BAC Member | E25: BAC Member
A28: =PR!B115 -> JANE S. CASTILLO | C28: FORTUNATO PHILIP A. CABUGAO | E28: DOREEN C. CASTILLO
A29: End-User/Provisional Member | C29: BAC Vice Chairperson | E29: BAC Chairperson
A30: BRYAN H. CIELO
A31: DELMA G. MALUPA-ABAD
A32: EDWIN F.MACABALLUG, Ph.D.
A33: LIEZL P. DELA CRUZ
A34: RODERICK Y. ABAD
A35: VILMA D. BACCAY
A36: ESTEBAN C. BADAJOS
A37: LEOBERT L. BANZALI
A38: MIAH DAPHNIE B. BUENAFE
A39: GLORIA N. CABIZON
A40: FORTUNATO PHILIP A. CABUGAO
A41: RICARDO Q. CABUGAO, JR.
... A83: LEONARDO CABRERA

Sheet AResoSVP (2)
A6: Approval of BAC Resolution Recommending Alternative Mode of Procurement under Small Value Procurement
B7: BAC Resolution No. | D7: =PR!B12 -> 2510-1005-380
A9: WHEREAS, Section 48 Rule XVI of the Revised Implementing Rules and Regulations of RA 9184 allows Alternative Mode of Procurement subject to prior approval of the HOPE thru Annual Procurement Plan (APP) and only to promote economy and efficiency;
A10: WHEREAS, Section 53.9 allows Small Value Procurement provided that the procurement does not fall under shopping in Section 52 of this IRR and the amount involved does not exceed the thresholds prescribed in Annex "H" of this IRR;
A11: WHEREAS, Appendix 18, Section 3.e on the Guidelines for Shopping and Small Value Procurement provides an Abstract of Quotations shall be prepared setting forth the names of those who responded to the RFQ's right after the deadline for submission except for shopping under Section 52.1(b), where at least three (3) price quotations (RFQ) must be obtained;
A12: WHEREAS, Annex "H" of the Consolidated Guidelines for the Alternative Methods of Procurement prescribed under Section V, Paragraph D.8.b.ii that the BAC shall prepare and send the RFQs/RFPs to at least three (3) suppliers, contractors or consultants of known qualifications where receipt of at least one (1) quotations is sufficient to proceed with the evaluation thererof;
A13: WHEREAS, Purchase Request No. | D13: =PR!E9 -> 2025-380 | E13: involves the procurement of
A14: AM and PM Snack and Lunch --snacks & lunch for the Joint Academic & Admin meeting | H14: Items:
A15: with the approved budget of | D15: =PR!H110 -> 81000
A16: WHEREAS, the default mode of evaluation shall be on a lot basis which means that the determination of the single/lowest calculated and responsive bid (S/LCRB) is the total amount of offered unit price multiply by the required quantity;
A17: NOW THEREFORE, I,DR.DJOVI R. DURANTE, Head of the Procuring Entity (HOPE) by virtue of the authority vested in me by the Board of Trustees of this Institution and after taking into consideration the merits and legal bases of the recommendation of the members of the Bids and Awards Committee (BAC) do hereby APPROVE the foregoing recommendation and adoption of Alternative Mode of Procurement under Small Value Procurement;
A19: APPROVED FINALLY, at the Batanes State College, this | F19: ___________________
B25: DJOVI REGALA DURANTE,DPA
B26: SUC President I
A31: BRYAN H. CIELO
A32: DELMA G. MALUPA-ABAD
A33: EDWIN F.MACABALLUG, Ph.D.
A34: LIEZL P. DELA CRUZ
A35: RODERICK Y. ABAD
A36: VILMA D. BACCAY
A37: ESTEBAN C. BADAJOS
A38: LEOBERT L. BANZALI
A39: MIAH DAPHNIE B. BUENAFE
A40: GLORIA N. CABIZON
A41: FORTUNATO PHILIP A. CABUGAO
A42: RICARDO Q. CABUGAO, JR.
... A87: EMILYN D. ALUETA

Sheet RFQ_ (2)
E6: Date: | F6: 10/20/25
A7: REQUEST FOR PRICE QUOTATION
A8: YCA Printing Services
A9: Please give us your best and final price offer for the item/s listed below, have this signed and submit this by you or by your duly authorized representative WITHIN SEVEN (7) CALENDAR DAYS upon receipt to Procurement Section, Batanes State College.
A11: NOTE: | B11: 1. THE DEFAULT MODE OF PRICE EVALUATION SHALL BE ON A LOT BASIS, OTHERWISE PER ITEMS EVALUATION SHALL BE USED IF THERE WILL BE LACKING ITEMS IN ALL RFQ's AND SUBJECT TO END-USER APPROVAL., (Clause 15.2, Section I, Instruction to Bidders of the Philippine Bidding Documents for goods and infrastructure projects)
B12: 2. DELIVERY PERIOD: Thirty (30) calendar days.
B13: 3. Submission of price quotation shall be in sealed envelope.
B14: 4. THE APPROVED BUDGET FOR THIS PROCUREMENT IS
B15: =PR!H110 -> 81000 | D15: (GPPB Resolution No. 09-2009)
B16: 5. PURSUANT TO ANNEX "H", APPENDIX A, SECTION II, SUBMISSION OF APPLICABLE DOCUMENTS (e.g.MAYORS/BUSINESS PERMIT, PROFESSIONAL LICENSE/CURRICULUM VITAE (CONSULTING SEERVICES),PHILGEPS CERT. NO., PCAB LICENSE (INFRA), INCOME/BUSINESS TAX RETURN,OMNIBUS SWORN STATEMENT SHALL BE REQUIRED BEFORE THE ISSUANCE OF NOA OR PRIOR TO PAYMENT.
B17: 6. In case the item is not availble, please write "None".
A18: Item # | B18: Qty. | C18: Unit | D18: PARTICULAR | E18: Unit Price | F18: Total
A19: 001 | B19: =PR!A16 -> 60 | C19: =PR!B16 -> copies | D19: =PR!D16 -> Printing of Training Manual (Hardbound cover, laminated, colored,15.5 x 23 cm, 70 pages, 80gsm, colored, glossy with ISSN/ISBN number)
A20: 002
A21: 003
A22: 004
A23: 005
A24: 006
A25: 007
A26: 008
A27: 009
A28: 010
A29: 011 | B29: =PR!A26 -> 0 | C29: =PR!B26 -> 0 | D29: =PR!D26 -> 0
A30: 012 | B30: =PR!A27 -> 0 | C30: =PR!B27 -> 0 | D30: =PR!D27 -> 0
A31: 013 | B31: =PR!A28 -> 0 | C31: =PR!B28 -> 0 | D31: =PR!D28 -> 0
A32: 014 | B32: =PR!A29 -> 0 | D32: =PR!D29 -> 0
A33: 015 | B33: =PR!A30 -> 0 | D33: =PR!D30 -> 0
A34: 016 | B34: =PR!A31 -> 0 | D34: =PR!D31 -> 0
A35: 017 | B35: =PR!A32 -> 0 | C35: =PR!B32 -> 0 | D35: =PR!D32 -> 0
A36: 018 | B36: =PR!A33 -> 0 | C36: =PR!B33 -> 0 | D36: =PR!D33 -> 0
A37: 019 | B37: =PR!A34 -> 0 | C37: =PR!B34 -> 0 | D37: =PR!D34 -> 0
A38: 020 | B38: =PR!A35 -> 5 | C38: =PR!B35 -> set | D38: =PR!D35 -> Laddle with wooden handle with hole
A39: 021 | B39: =PR!A36 -> 5 | C39: =PR!B36 -> set | D39: =PR!D36 -> Laddle with wooden handle without hole
A40: 022 | B40: =PR!A37 -> 5 | C40: =PR!B37 -> pc | D40: =PR!D37 -> Measuring Cup Glass
A41: 023 | B41: =PR!A38 -> 5 | C41: =PR!B38 -> set | D41: =PR!D38 -> Measuring Cup Set Set Includes: 1/4 cup,1/3 cup, 1/2 cup,1 cup
A42: 024 | B42: =PR!A39 -> 5 | C42: =PR!B39 -> set | D42: =PR!D39 -> Measuring Spoon Set sets include: 1/8 teaspoon, 1/4 teaspoon, 1/2 teaspoon, 1 teaspoon, 1/ 2 tbsp, 1 tbsp
A43: 025 | B43: =PR!A40 -> 3 | C43: =PR!B40 -> set | D43: =PR!D40 -> Mixing Bowl with Cover 5pcs
A44: 026 | B44: =PR!A41 -> 5 | C44: =PR!B41 -> set | D44: =PR!D41 -> Fruit and Vegetable Peeler Stainless Steel 13 cm (5 ")
A45: 027 | B45: =PR!A42 -> 5 | C45: =PR!B42 -> set | D45: =PR!D42 -> Pot Holder Cloth 3pcs/set
A46: 028 | B46: =PR!A43 -> 10 | C46: =PR!B43 -> pc | D46: =PR!D43 -> Pot Holder Heat Insulated Gloves Specifications: Color: Grey Material: silicone Size: 20.5x16.5cm
... A100: 083 | B100: =PR!A97 -> 1 | C100: =PR!B97 -> pc | D100: =PR!D97 -> Cling Wrap
E102: Total
A104: After having carefully read and accepted your conditions, I/We have place my /our best and final price offer on the item/s listed above.
E105: Very truly yours,
A107: Printed Name/Signature
E108: DOREEN C. CASTILLO
A109: Ref.# | B109: =PR!B12 -> 2510-1005-380 | E109: BAC Chairperson

Sheet RFQ_ (3)
E6: Date: | F6: =NOW() -> 46181.383
A7: REQUEST FOR PRICE QUOTATION
A8: Apostol General Merchandise
A9: Please give us your best and final price offer for the item/s listed below, have this signed and submit this by you or by your duly authorized representative WITHIN SEVEN (7) CALENDAR DAYS upon receipt to Procurement Section, Batanes State College.
A11: NOTE: | B11: 1. THE DEFAULT MODE OF PRICE EVALUATION SHALL BE ON A LOT BASIS, OTHERWISE PER ITEMS EVALUATION SHALL BE USED IF THERE WILL BE LACKING ITEMS IN ALL RFQ's AND SUBJECT TO END-USER APPROVAL., (Clause 15.2, Section I, Instruction to Bidders of the Philippine Bidding Documents for goods and infrastructure projects)
B12: 2. DELIVERY PERIOD: Thirty (30) calendar days.
B13: 3. Submission of price quotation shall be in sealed envelope.
B14: 4. THE APPROVED BUDGET FOR THIS PROCUREMENT IS
B15: =PR!H110 -> 81000 | D15: (GPPB Resolution No. 09-2009)
B16: 5. PURSUANT TO ANNEX "H", APPENDIX A, SECTION II, SUBMISSION OF APPLICABLE DOCUMENTS (e.g.MAYORS/BUSINESS PERMIT, PROFESSIONAL LICENSE/CURRICULUM VITAE (CONSULTING SEERVICES),PHILGEPS CERT. NO., PCAB LICENSE (INFRA), INCOME/BUSINESS TAX RETURN,OMNIBUS SWORN STATEMENT SHALL BE REQUIRED BEFORE THE ISSUANCE OF NOA OR PRIOR TO PAYMENT.
B17: 6. In case the item is not availble, please write "None".
A18: Item # | B18: Qty. | C18: Unit | D18: PARTICULAR | E18: Unit Price | F18: Total
A19: 001 | B19: =PR!A16 -> 60 | C19: =PR!B16 -> copies | D19: =PR!D16 -> Printing of Training Manual (Hardbound cover, laminated, colored,15.5 x 23 cm, 70 pages, 80gsm, colored, glossy with ISSN/ISBN number)
A20: 002 | B20: =PR!A17 -> 0 | C20: =PR!B17 -> 0 | D20: =PR!D17 -> 0
A21: 003 | B21: =PR!A18 -> 0 | C21: =PR!B18 -> 0 | D21: =PR!D18 -> 0
A22: 004 | B22: =PR!A19 -> 0 | C22: =PR!B19 -> 0 | D22: =PR!D19 -> 0
A23: 005 | B23: =PR!A20 -> 0 | C23: =PR!B20 -> 0 | D23: =PR!D20 -> 0
A24: 006 | B24: =PR!A21 -> 0 | C24: =PR!B21 -> 0 | D24: =PR!D21 -> 0
A25: 007 | B25: =PR!A22 -> 0 | C25: =PR!B22 -> 0 | D25: =PR!D22 -> 0
A26: 008 | B26: =PR!A23 -> 0 | C26: =PR!B23 -> 0 | D26: =PR!D23 -> 0
A27: 009 | B27: =PR!A24 -> 0 | C27: =PR!B24 -> 0 | D27: =PR!D24 -> 0
A28: 010 | B28: =PR!A25 -> 0 | C28: =PR!B25 -> 0 | D28: =PR!D25 -> 0
A29: 011 | B29: =PR!A26 -> 0 | C29: =PR!B26 -> 0 | D29: =PR!D26 -> 0
A30: 012 | B30: =PR!A27 -> 0 | C30: =PR!B27 -> 0 | D30: =PR!D27 -> 0
... A76: 058 | B76: =PR!A73 -> 3 | C76: =PR!B73 -> pc | D76: =PR!D73 -> Wok Pan 2mm (thickness) 60cm diameter
A77: 060 | B77: =[1]PR!A74 -> 1 | C77: =PR!B74 -> pcs | D77: =PR!D74 -> Office Desk/Table Material: MDF Color: Walnut Dimensions of Table: 47.24" W x 30.31" H x 23.63" D Drawer Dimensions: 11" W x 23" H x 18.75" D
A78: 061 | B78: =[1]PR!A75 -> 1 | C78: =PR!B75 -> pcs | D78: =PR!D75 -> Office Chair - Junior Executive Chair Black Leatherette Ergonomic with padded armrests Chrome base with smooth-rolling caster wheels Seat Dimensions: 21" L x 21" W Backrest Dimensions: 26.5" L x 21" W Full Dimensions: 25" W x 42" - 45" H
A79: 062 | B79: =[1]PR!A76 -> 1 | C79: =PR!B76 -> pcs | D79: =PR!D76 -> Portable Projector with bag and stand Product Details: Android 11,500 ANSI DRM L1 Certification nnovative 120°rotating projection ASA 3.0(AF+KS+ScrnFit+Avoid) Dual-bass diaphragms ≤30 dB/m Ultra-low decibel Specifications: Product Color: White Product Weight: 1.5Kg Product Size: 145*142*219 mm Display Technology: LCD Brightness: 500 ANSI Lumens Physical Resolution: 1920 * 1080 FHD Lens： 3 Pcs aspherical pure glass lens Projection Features Zoom Function：50%-100% Projection Ratio: 1.2: 1 Projection Size: 45-140 Inch Projection Distance: 1.2-3.8m Intelligent Adjustment Keystone Correction： Auto Focus Adjustment： Auto Obstacle Avoidance： Auto Screen Alignment： Auto Audio & Connectivity Speaker: 5W * 2 Noise: ≤30dB/m Cavity Volume：370CC Bluetooth: 5.0 WiFi: Dual Band 2.4/5G Hz Interface HDMI：*1 USB：*1 AUX3.5mm：*1
A80: 063 | B80: =[1]PR!A77 -> 1 | C80: =PR!B77 -> 0 | D80: =PR!D77 -> 0
A81: 064 | B81: =[1]PR!A78 -> 1 | C81: =PR!B78 -> pcs | D81: =PR!D78 -> Assorted Coffee 3 in 1
A82: 065 | B82: =[1]PR!A79 -> 1 | C82: =PR!B79 -> 0 | D82: =PR!D79 -> Coke 1.7L
A83: 066 | B83: =[1]PR!A80 -> 1 | C83: =PR!B80 -> pcs | D83: =PR!D80 -> Bottled Water 1L
A84: 067 | B84: =[1]PR!A81 -> 1 | C84: =PR!B81 -> pcs | D84: =PR!D81 -> Dutchmill 90ml 4's
A85: 068 | B85: =[1]PR!A82 -> 1 | C85: =PR!B82 -> 0 | D85: =PR!D82 -> Dutchmill 180ml 4's
A86: 069 | B86: =[1]PR!A83 -> 1 | C86: =PR!B83 -> pcs | D86: =PR!D83 -> Chuckie 180ml 6's
A87: 070 | B87: =[1]PR!A84 -> 1 | C87: =PR!B84 -> pcs | D87: =PR!D84 -> Cupkeyk
A88: 071 | B88: =[1]PR!A85 -> 1 | C88: =PR!B85 -> pcs | D88: =PR!D85 -> Fudgee Bar
... A101: 084 | B101: =[1]PR!A98 -> 1 | C101: =PR!B98 -> pc | D101: =PR!D98 -> Tarpaulin Printing (4ft x 6ft)
E102: Total
A103: After having carefully read and accepted your conditions, I/We have place my /our best and final price offer on the item/s listed above.
E104: Very truly yours,
A106: Printed Name/Signature
E107: DOREEN C. CASTILLO
A108: Ref.# | B108: =PR!B12 -> 2510-1005-380 | E108: BAC Chairperson

Sheet AckReceipt (3)
A3: Acknowledgement for Request for Quotation
A4: RIS# | B4: =PR!B12 -> 2510-1005-380
A5: No. | B5: Supplier | F5: Received by: | G5: Date & Time:
B6: JPM Gen. Mdse. & Hardware
B7: Thine-line Trading
B8: J-Tech Trading & Services
B9: MDAC Trading & Compuserve
B10: FVA Gen Mdse & Construction Supply
B12: GDP Trading
B13: EA Amboy Gen Mdse
B14: L & R's Hontomin Gen Mdse
B15: Davocol's Gen. Mdse.
B16: RCJ Hardware & Gen Mdse
B17: Fitero's Gen Mdse & Electronic Supply
B18: Lar & San's Store
... B20: Wilmerson Gen Mdse
B21: FMG Trading & Construction Supply | C21: q
B22: MG Hubalde Gen Mdse
B23: Basco Cable TV Services, Inc.
B24: Berlen's Store
B25: Melad's Gen. Mdse
B26: R. A. Electronics
B27: RJ General Merchandise
B28: Batanes Multi-Purpose Cooperative, Inc.
B29: Romy & Ava's Store
B30: J-nell's Gen Mdse
B31: Impression Digital Printing Solutions
B32: Golden Press
B33: Tawsen's Agri-Venture & Souvenirs
... B62: Sophia Marie Store
A63: 1 | B63: Swift Development & Supplies Corp.
A64: 2 | B64: JF Gabotero, In
A65: 3 | B65: GMPI Construction OPC
A66: 4
A67: 5 | J67: zz
A68: 6
A69: 7
A70: NOTE: | B70: 1. MODE OF PRICE EVALUATION SHALL BE ON A LOT BASIS, OTHERWISE PER ITEMS EVALUATION SHALL BE USED IF THERE WILL BE LACKING ITEMS IN ALL RFQ'S AND THE END-USER AGREED, . (Clause 15.2, Section II, Instructions to Bidders of the Philippine Bidding Documents for goods and infrastructure projects)
B71: 2. DELIVERY PERIOD: Thirty (30) calendar days.
B72: 3. WARRANTY SHALL BE FOR A PERIOD OF SIX (6) MONTHS FOR SUPPLIES AND MATERIALS, ONE (1) YEAR FOR EQUIPMENT, FROM THE DATE OF ACCEPTANCE BY THE PROCURING ENTITY.
B73: 4. THE APPROVED BUDGET CEILING FOR THIS PROCUREMENT IS PHP (GPPB Resolution no. 09-2009)
B74: =PR!H110 -> 81000
B75: 5. PRICE VALIDITY SHALL BE OR THE PERIOD OF 30 CALENDAR DAYS.
B76: 6. BIDDERS SHALL SUBMIT ORIGINAL BROCHURES SHOWING SPECIFICATIONS OF THE PRODUCT BEING OFFERED IF APPLICABLE.
A77: In compliance with GPPB Resolution No. 09-2009
B79: Retrieval of Request for Quotation
A81: No. | B81: Supplier | E81: Released by: | F81: Date & Time: | G81: Remarks | N81: k
A82: 1 | B82: Swift Development & Supplies Corp.
A83: 2 | B83: JF Gabotero, Inc.
A84: 3 | B84: GMPI Construction OPC
A85: 4
A86: 5
A87: 6
A88: 7
A89: 8

Sheet Abstract 
B2: ABSTRACT OF QUOTATIONS
B4: (x) Furnishing/delivery of supplies, and materials or equipment | G4: Bids opened at Basco, Batanes
B5: ( x ) Furnishing Labor, services, etc. | I5: =NOW() -> 46181.383
B6: ( ) Rental or use of transportation facilities equipment, quarters, rooms, lot or space, etc.
B8: To be furnished at the | D8: BATANES STATE COLLEGE
D9: (State place or site of Office or project where articles or services be furnished or returned)
A11: NAME OF ARTICLES OR SERVICES TO BE FURNISHED, RENDERED OR FACILITIES TO BE RENTED
F14: JPM Gen. Mdse. & Hardware
F15: Thine-line Trading
F16: J-Tech Trading & Services
F17: Mulong Ydel
F18: MDAC Trading & Compuserve
F19: FVA Gen Mdse & Construction Supply
F20: MKM Hardware
F21: GDP Trading
F22: EA Amboy Gen Mdse
F23: L & R's Hontomin Gen Mdse
F24: Davocol's Gen. Mdse.
F25: RCJ Hardware & Gen Mdse
... F86: Valiente Food Producer
F87: =DATA!W200 -> YCA Printing Services | G87: Golden Press | H87: CMVILL Trading | I87: One-Touch Technology Trading
A89: =PR!D16 -> Printing of Training Manual (Hardbound cover, laminated, colored,15.5 x 23 cm, 70 pages, 80gsm, colored, glossy with ISSN/ISBN number) | F89: =DATA!O200 -> 81000 | G89: 87500 | H89: 90000 | I89: none
A105: =PR!D32 -> 0 | F105: =DATA!O20 -> 1940 | G105: 3000 | H105: 1900
A106: =PR!D33 -> 0 | F106: =DATA!O21 -> 520 | G106: 590 | H106: 2800
A107: =PR!D34 -> 0 | B107: Bond paper, A4 size | C107: Bond paper, A4 size | D107: Bond paper, A4 size | E107: Bond paper, A4 size | F107: =DATA!O22 -> 1500 | G107: 1200 | H107: 7500
A108: =PR!D35 -> Laddle with wooden handle with hole | B108: Bond paper, A4 size | C108: Bond paper, A4 size | D108: Bond paper, A4 size | E108: Bond paper, A4 size | F108: =DATA!O23 -> 1980 | G108: 2800 | H108: 3500
A109: =PR!D36 -> Laddle with wooden handle without hole | B109: Bond paper, A4 size | C109: Bond paper, A4 size | D109: Bond paper, A4 size | E109: Bond paper, A4 size | F109: =DATA!O24 -> 900 | G109: 1500 | H109: 1200
A110: =PR!D37 -> Measuring Cup Glass | B110: Bond paper, A4 size | C110: Bond paper, A4 size | D110: Bond paper, A4 size | E110: Bond paper, A4 size | F110: =DATA!O25 -> 800 | G110: 1800 | H110: 1100
A111: =PR!D38 -> Measuring Cup Set Set Includes: 1/4 cup,1/3 cup, 1/2 cup,1 cup | B111: Bond paper, A4 size | C111: Bond paper, A4 size | D111: Bond paper, A4 size | E111: Bond paper, A4 size | F111: =DATA!O26 -> 550 | G111: 800 | H111: 1200
A112: =PR!D39 -> Measuring Spoon Set sets include: 1/8 teaspoon, 1/4 teaspoon, 1/2 teaspoon, 1 teaspoon, 1/ 2 tbsp, 1 tbsp | B112: Bond paper, A4 size | C112: Bond paper, A4 size | D112: Bond paper, A4 size | E112: Bond paper, A4 size | F112: =DATA!O27 -> 4500 | G112: 4500 | H112: 4600
A113: =PR!D40 -> Mixing Bowl with Cover 5pcs | B113: Bond paper, A4 size | C113: Bond paper, A4 size | D113: Bond paper, A4 size | E113: Bond paper, A4 size | F113: =DATA!O28 -> 8600 | G113: 16000 | H113: 11000
A114: =PR!D41 -> Fruit and Vegetable Peeler Stainless Steel 13 cm (5 ") | B114: Bond paper, A4 size | C114: Bond paper, A4 size | D114: Bond paper, A4 size | E114: Bond paper, A4 size | F114: =DATA!O29 -> 1400 | G114: 1600 | H114: 3600
A115: =PR!D42 -> Pot Holder Cloth 3pcs/set | B115: Bond paper, A4 size | C115: Bond paper, A4 size | D115: Bond paper, A4 size | E115: Bond paper, A4 size | F115: =DATA!O30 -> 1900 | G115: 1800 | H115: 2000
A116: =PR!D43 -> Pot Holder Heat Insulated Gloves Specifications: Color: Grey Material: silicone Size: 20.5x16.5cm | B116: Bond paper, A4 size | C116: Bond paper, A4 size | D116: Bond paper, A4 size | E116: Bond paper, A4 size | F116: =DATA!O31 -> 2800 | G116: 800 | H116: 5200
A117: =PR!D44 -> Knife Sharpener | B117: Bond paper, A4 size | C117: Bond paper, A4 size | D117: Bond paper, A4 size | E117: Bond paper, A4 size | F117: =DATA!O32 -> 2240 | G117: 2000 | H117: 5200
A118: =PR!D45 -> Sifter Stainless Steel 270 x 70mm Mesh: #30 (0.595mm) | B118: Bond paper, A4 size | C118: Bond paper, A4 size | D118: Bond paper, A4 size | E118: Bond paper, A4 size | F118: =DATA!O33 -> 2580 | G118: 1620 | H118: 4500
... A130: =PR!D57 -> Fire Extinguisher ABC Dry Chemical 10LBS | B130: Bond paper, A4 size | C130: Bond paper, A4 size | D130: Bond paper, A4 size | E130: Bond paper, A4 size | F130: =DATA!O45 -> 6900 | G130: 6840 | H130: 5760
A131: =PR!D58 -> Fruit and Vegetables Brush Soft Bristle | B131: Bond paper, A4 size | C131: Bond paper, A4 size | D131: Bond paper, A4 size | E131: Bond paper, A4 size
A132: =DATA!I317 -> Heavy Duty Nylon Rope (Dia;12mm ,200meters) | B132: Bond paper, A4 size | C132: Bond paper, A4 size | D132: Bond paper, A4 size | E132: Bond paper, A4 size
A133: =DATA!I318 -> Garden shade Net (70% shading rate) black length;100meters | B133: Bond paper, A4 size | C133: Bond paper, A4 size | D133: Bond paper, A4 size | E133: Bond paper, A4 size
A134: =DATA!I319 -> Trapal rubberized (9x12) color; yellow/grey | B134: Bond paper, A4 size | C134: Bond paper, A4 size | D134: Bond paper, A4 size | E134: Bond paper, A4 size
A135: =DATA!I320 -> Fishin line 200 pounds | B135: Bond paper, A4 size | C135: Bond paper, A4 size | D135: Bond paper, A4 size | E135: Bond paper, A4 size | H135: none
A136: =DATA!I321 -> PLAIN ROUND BAR.Size 12mm | B136: Bond paper, A4 size | C136: Bond paper, A4 size | D136: Bond paper, A4 size | E136: Bond paper, A4 size | H136: none
A137: =DATA!I322 -> Volleyball Ball (FIVB Approved) | B137: Bond paper, A4 size | C137: Bond paper, A4 size | D137: Bond paper, A4 size | E137: Bond paper, A4 size | H137: none
A138: =DATA!I323 -> Basketball Ball CG7 (FIBA Approved) | B138: Bond paper, A4 size | C138: Bond paper, A4 size | D138: Bond paper, A4 size | E138: Bond paper, A4 size | H138: none
A139: =DATA!I324 -> Table Tennis Ball (ITTF Approved) | B139: Bond paper, A4 size | C139: Bond paper, A4 size | D139: Bond paper, A4 size | E139: Bond paper, A4 size | H139: none
A140: =DATA!I325 -> Badminto Feather Shuttlecock | B140: Bond paper, A4 size | C140: Bond paper, A4 size | D140: Bond paper, A4 size | E140: Bond paper, A4 size | H140: none
A141: =DATA!I326 -> Doubled Battery | B141: Bond paper, A4 size | C141: Bond paper, A4 size | D141: Bond paper, A4 size | E141: Bond paper, A4 size | H141: none
A142: =DATA!I327 -> Beach Volleyball Ball (FIVB Approved) | B142: Bond paper, A4 size | C142: Bond paper, A4 size | D142: Bond paper, A4 size | E142: Bond paper, A4 size | H142: none
A143: =DATA!I328 -> Paper Velum Board,A4 (10pcs/pack) | B143: Bond paper, A4 size | C143: Bond paper, A4 size | D143: Bond paper, A4 size | E143: Bond paper, A4 size | H143: none
A144: =DATA!I329 -> CCTV - Dual DH-IPC-WPT1539DD-PV 5MP + 5MP Wi-Fi Dual Lens PT Outdoor Camera with Mic and Speaker AI Human Detection Deterrence Function Smart Dual Light Specs: 5 MP + 5 MP Full HD Video AI Human and Vehicle Detection Auto Tracking Two Way Audio Built-in Microphone and Speaker Built-in Siren and Strobe Light Smart Dual Light Alarm Notification Micro SD Card Slot Supports up to 256GB | B144: Bond paper, A4 size | C144: Bond paper, A4 size | D144: Bond paper, A4 size | E144: Bond paper, A4 size | H144: none
A145: =DATA!I330 -> Ultra microSDXC UHS-I Card Specs: Capacity : 256GB Form Factor : microSDXC™ Sequential Read Performance : Up to 100MB/s Dimensions (L x W x H) : 1.02mm x 14.99mm x 10.92mm Weight : 4.54gms Class: Class 10 Waterproof Shockproof Compatible with Smartphones and Cameras OS Compatibility: Windows 2000 or later, Mac OS 10.4 or later | B145: Bond paper, A4 size | C145: Bond paper, A4 size | D145: Bond paper, A4 size | E145: Bond paper, A4 size | H145: none
A146: =DATA!I331 -> Cable reel extension wheel outlet AWG 16 25 meters SPECIFICATIONS: ►Cord Length: 25M ►Cord Size: #16 ►4 Sockets ►Power Switch ►Thermal Cut-out Protection ►Winding Knob | B146: Bond paper, A4 size | C146: Bond paper, A4 size | D146: Bond paper, A4 size | E146: Bond paper, A4 size | H146: none
A147: =DATA!I332 -> Multi-purpose Universal Adapter with Safety Switch Product Details: Input Voltage 125 Vac Max Current: 10 Amperes Load Capacity: Up to 1200 watts With on/off switch for safety Can accomodate multiple plug types | B147: Bond paper, A4 size | C147: Bond paper, A4 size | D147: Bond paper, A4 size | E147: Bond paper, A4 size | H147: none
A148: =DATA!I125 -> 001-Black | B148: Bond paper, A4 size | C148: Bond paper, A4 size | D148: Bond paper, A4 size | E148: Bond paper, A4 size | H148: none
A149: =DATA!I126 -> BTD100BK-black | B149: Bond paper, A4 size | C149: Bond paper, A4 size | D149: Bond paper, A4 size | E149: Bond paper, A4 size | H149: none
A150: =DATA!I127 -> BTD100C-cyan | B150: Bond paper, A4 size | C150: Bond paper, A4 size | D150: Bond paper, A4 size | E150: Bond paper, A4 size | H150: none
A151: =DATA!I128 -> BTD100M-magenta | B151: Bond paper, A4 size | C151: Bond paper, A4 size | D151: Bond paper, A4 size | E151: Bond paper, A4 size | H151: none
A152: =DATA!I129 -> BTD100Y-yellow | B152: Bond paper, A4 size | C152: Bond paper, A4 size | D152: Bond paper, A4 size | E152: Bond paper, A4 size | H152: none
A153: =DATA!I130 -> KD Lumber 2"x 3" x12' | B153: Bond paper, A4 size | C153: Bond paper, A4 size | D153: Bond paper, A4 size | E153: Bond paper, A4 size | H153: none
A154: =DATA!I131 -> CWN 2 1/2" | B154: Bond paper, A4 size | C154: Bond paper, A4 size | D154: Bond paper, A4 size | E154: Bond paper, A4 size | H154: none
A155: =DATA!I132 -> Marine plywood 1/2" | B155: Bond paper, A4 size | C155: Bond paper, A4 size | D155: Bond paper, A4 size | E155: Bond paper, A4 size | H155: none
A156: =DATA!I133 -> Tarpaulin (5' x 10') | B156: Bond paper, A4 size | C156: Bond paper, A4 size | D156: Bond paper, A4 size | E156: Bond paper, A4 size | H156: none
A157: =DATA!I134 -> Snacks & Drinks | B157: Bond paper, A4 size | C157: Bond paper, A4 size | D157: Bond paper, A4 size | E157: Bond paper, A4 size | H157: none
A158: =DATA!I136 -> Ink (001-Magenta, Cyan, Yellow & Black) | B158: Bond paper, A4 size | C158: Bond paper, A4 size | D158: Bond paper, A4 size | E158: Bond paper, A4 size | H158: none
A159: =DATA!I137 -> 8.1/4 inch Ergonomic Stainless Office Scissors | B159: Bond paper, A4 size | C159: Bond paper, A4 size | D159: Bond paper, A4 size | E159: Bond paper, A4 size | F159: =DATA!O1277 -> 0 | G159: 900 | H159: none
A160: =DATA!I138 -> 12 HB2 Pencil with Eraser Tip | B160: Bond paper, A4 size | C160: Bond paper, A4 size | D160: Bond paper, A4 size | E160: Bond paper, A4 size | F160: =DATA!O1278 -> 0 | G160: 900 | H160: none
A161: =DATA!I139 -> Dukay Rootcrops (fresh,cleaned, high-quality produce) | B161: Bond paper, A4 size | C161: Bond paper, A4 size | D161: Bond paper, A4 size | E161: Bond paper, A4 size | F161: =DATA!O1279 -> 0 | G161: 925 | H161: none
A162: =DATA!I140 -> Water Based Paint Red (Acrylic 20ml) | B162: Bond paper, A4 size | C162: Bond paper, A4 size | D162: Bond paper, A4 size | E162: Bond paper, A4 size | F162: =DATA!O1280 -> 0 | G162: 9300 | H162: none
A163: =DATA!I141 -> Water Based Paint Blue (Acrylic 20ml) | B163: Bond paper, A4 size | C163: Bond paper, A4 size | D163: Bond paper, A4 size | E163: Bond paper, A4 size | F163: =DATA!O1281 -> 0 | G163: 32000 | H163: none
A164: =DATA!I142 -> Water Based Paint Yellow (Acrylic 20ml) | B164: Bond paper, A4 size | C164: Bond paper, A4 size | D164: Bond paper, A4 size | E164: Bond paper, A4 size | F164: =DATA!O1282 -> 0 | G164: 9900 | H164: none
A165: =DATA!I143 -> Water Based Paint White (Acrylic 20ml) | B165: Bond paper, A4 size | C165: Bond paper, A4 size | D165: Bond paper, A4 size | E165: Bond paper, A4 size | F165: =DATA!O1283 -> 0 | G165: 400 | H165: none
A166: =DATA!I144 -> 12" x 18" canvass | B166: Bond paper, A4 size | C166: Bond paper, A4 size | D166: Bond paper, A4 size | E166: Bond paper, A4 size | F166: =DATA!O1284 -> 0 | G166: 1500 | H166: none
A167: =DATA!I145 -> Lumograph Pencil 2H/3H | B167: Bond paper, A4 size | C167: Bond paper, A4 size | D167: Bond paper, A4 size | E167: Bond paper, A4 size | F167: =DATA!O1285 -> 0 | G167: 9950 | H167: none
A168: =DATA!I146 -> Lumograph Pencil B/2B | B168: Bond paper, A4 size | C168: Bond paper, A4 size | D168: Bond paper, A4 size | E168: Bond paper, A4 size | F168: =DATA!O1286 -> 0 | G168: 1440 | H168: none
A169: =DATA!I147 -> Lumograph Pencil 5B/6B | B169: Bond paper, A4 size | C169: Bond paper, A4 size | D169: Bond paper, A4 size | E169: Bond paper, A4 size | F169: =DATA!O1287 -> 0 | H169: none
A170: =DATA!I148 -> Charcoal Pencil Dark | B170: Bond paper, A4 size | C170: Bond paper, A4 size | D170: Bond paper, A4 size | E170: Bond paper, A4 size | F170: =DATA!O1288 -> 0 | H170: none
A171: =DATA!I149 -> Charcoal Pencil Medium | B171: Bond paper, A4 size | C171: Bond paper, A4 size | D171: Bond paper, A4 size | E171: Bond paper, A4 size | F171: =DATA!O1289 -> 0 | H171: none
A172: =DATA!I150 -> Charcoal Pencil Light | B172: Bond paper, A4 size | C172: Bond paper, A4 size | D172: Bond paper, A4 size | E172: Bond paper, A4 size | F172: =DATA!O1290 -> 0 | H172: none
A173: =DATA!I151 -> Cartolina White | B173: Bond paper, A4 size | C173: Bond paper, A4 size | D173: Bond paper, A4 size | E173: Bond paper, A4 size | F173: =DATA!O1291 -> 0 | H173: none
A174: =DATA!I152 -> Professional Paint Brush Set 6's (sizes: 2,4,6,8,10,12/per set) | B174: Bond paper, A4 size | C174: Bond paper, A4 size | D174: Bond paper, A4 size | E174: Bond paper, A4 size | F174: =DATA!O1292 -> 0 | H174: none
A175: =DATA!I153 -> Certificate Holder 9" x 12" | B175: Bond paper, A4 size | C175: Bond paper, A4 size | D175: Bond paper, A4 size | E175: Bond paper, A4 size | F175: =DATA!O1293 -> 0 | H175: none
A176: =DATA!I154 -> Pallete Knives 5's | B176: Bond paper, A4 size | C176: Bond paper, A4 size | D176: Bond paper, A4 size | E176: Bond paper, A4 size | F176: =DATA!O1294 -> 0 | H176: none
A177: =DATA!I155 -> Specialty Paper A4 (white) | B177: Bond paper, A4 size | C177: Bond paper, A4 size | D177: Bond paper, A4 size | E177: Bond paper, A4 size | F177: =DATA!O1295 -> 0 | H177: none
A178: =DATA!I156 -> Celphone - Display;6.67" amoled display, Internal; 128GB 8GB RAM, 256GB 8Gb RAM,256GB 12GB RAM, 512GB 12Gb RAM UFS 2.2, Dimensions; Height; 162.33mm, width; 74.42mm, thickness; Coral green & midnight black 8.4mm l Lavender Purple 8.55mm weight; 190g 511 Omah battery capacity | B178: Bond paper, A4 size | C178: Bond paper, A4 size | D178: Bond paper, A4 size | E178: Bond paper, A4 size | F178: =DATA!O1296 -> 0 | H178: none
A179: =DATA!I157 -> Realtim GPS Tracker for Car/Motorcycle Anti-theft GSM Alarm Tracking Device built-in battery | B179: Bond paper, A4 size | C179: Bond paper, A4 size | D179: Bond paper, A4 size | E179: Bond paper, A4 size | F179: =DATA!O1297 -> 0 | H179: none
A180: =DATA!I158 -> Drill Bit (set) | B180: Bond paper, A4 size | C180: Bond paper, A4 size | D180: Bond paper, A4 size | E180: Bond paper, A4 size | F180: =DATA!O1298 -> 0 | H180: none
... A208: =DATA!I186 -> Beach Volleyball Ball (FIVB Approved) | B208: Bond paper, A4 size | C208: Bond paper, A4 size | D208: Bond paper, A4 size | E208: Bond paper, A4 size | F208: =DATA!O1326 -> 0 | H208: none
A209: =DATA!I192 -> Embroidered Patches BSC Logo 5.4cm diameter (see sample) | B209: Bond paper, A4 size | C209: Bond paper, A4 size | D209: Bond paper, A4 size | E209: Bond paper, A4 size | F209: =DATA!#REF! -> #REF! | H209: none
A210: =DATA!I193 -> Abaca Tote Bag/Eco handbag (size; 22cm x 12cm x 16cm) with thick handle | B210: Bond paper, A4 size | C210: Bond paper, A4 size | D210: Bond paper, A4 size | E210: Bond paper, A4 size | F210: =DATA!O1328 -> 0 | H210: none
A211: =DATA!I194 -> Sublimation Coated White Mugs, 11oz, sublimation printable mugs,glossy,plain (24pcs/box) | B211: Bond paper, A4 size | C211: Bond paper, A4 size | D211: Bond paper, A4 size | E211: Bond paper, A4 size | F211: =DATA!O1329 -> 0 | H211: none
A212: =DATA!I195 -> Sublimation Coated White Mugs, 11oz, sublimation printable mugs,glossy,plain (24pcs/box)assorted colors | B212: Bond paper, A4 size | C212: Bond paper, A4 size | D212: Bond paper, A4 size | E212: Bond paper, A4 size | F212: =DATA!O1330 -> 0 | H212: none
A213: =DATA!I196 -> Rough Satin Photo Paper, Waterproof, 4R, 20's/pack | B213: Bond paper, A4 size | C213: Bond paper, A4 size | D213: Bond paper, A4 size | E213: Bond paper, A4 size | F213: =DATA!O1331 -> 0 | H213: none
A214: =DATA!I197 -> Card Hole Corner Puncher for PVC ID | B214: Bond paper, A4 size | C214: Bond paper, A4 size | D214: Bond paper, A4 size | E214: Bond paper, A4 size | F214: =DATA!O1332 -> 0 | H214: none
A215: =DATA!I198 -> Laminating Film Roll | B215: Bond paper, A4 size | C215: Bond paper, A4 size | D215: Bond paper, A4 size | E215: Bond paper, A4 size | F215: =DATA!O1333 -> 0 | H215: none
A216: =DATA!I199 -> Transfer Tape, 60cm x 2meters | B216: Bond paper, A4 size | C216: Bond paper, A4 size | D216: Bond paper, A4 size | E216: Bond paper, A4 size | F216: =DATA!O1334 -> 0 | H216: none
A217: =DATA!I200 -> Printing of Training Manual (Hardbound cover, laminated, colored,15.5 x 23 cm, 70 pages, 80gsm, colored, glossy with ISSN/ISBN number) | B217: Bond paper, A4 size | C217: Bond paper, A4 size | D217: Bond paper, A4 size | E217: Bond paper, A4 size | F217: =DATA!O1335 -> 0 | H217: none
A218: =DATA!I201 -> Air Freshener (scented) | B218: Bond paper, A4 size | C218: Bond paper, A4 size | D218: Bond paper, A4 size | E218: Bond paper, A4 size | F218: =DATA!O1336 -> 0 | H218: none
A219: =DATA!I202 -> Whisk Broom | B219: Bond paper, A4 size | C219: Bond paper, A4 size | D219: Bond paper, A4 size | E219: Bond paper, A4 size | F219: =DATA!O1337 -> 0 | H219: none
A220: =DATA!I203 -> Linoleum (brown) | B220: Bond paper, A4 size | C220: Bond paper, A4 size | D220: Bond paper, A4 size | E220: Bond paper, A4 size | F220: =DATA!O1338 -> 0 | H220: none
...

Sheet Abstract (Failed)
B3: ABSTRACT OF QUOTATIONS
B5: (x) Furnishing/delivery of supplies, and materials or equipment | G5: Bids opened at Basco, Batanes
B6: ( x ) Furnishing Labor, services, etc. | I6: =NOW() -> 46181.383
B7: ( ) Rental or use of transportation facilities equipment, quarters, rooms, lot or space, etc.
B9: To be furnished at the | D9: BATANES STATE COLLEGE
D10: (State place or site of Office or project where articles or services be furnished or returned)
A12: NAME OF ARTICLES OR SERVICES TO BE FURNISHED, RENDERED OR FACILITIES TO BE RENTED
F15: JPM Gen. Mdse. & Hardware | K15: JPM Gen. Mdse. & Hardware | M15: JPM Gen. Mdse. & Hardware
F16: Thine-line Trading | K16: Thine-line Trading | M16: Thine-line Trading
F17: J-Tech Trading & Services | K17: J-Tech Trading & Services | M17: J-Tech Trading & Services
F18: Mulong Ydel | K18: Mulong Ydel | M18: Mulong Ydel
F19: MDAC Trading & Compuserve | K19: MDAC Trading & Compuserve | M19: MDAC Trading & Compuserve
F20: FVA Gen Mdse & Construction Supply | K20: FVA Gen Mdse & Construction Supply | M20: FVA Gen Mdse & Construction Supply
F21: MKM Hardware | K21: MKM Hardware | M21: MKM Hardware
F22: GDP Trading | K22: GDP Trading | M22: GDP Trading
F23: EA Amboy Gen Mdse | K23: EA Amboy Gen Mdse | M23: EA Amboy Gen Mdse
F24: L & R's Hontomin Gen Mdse | K24: L & R's Hontomin Gen Mdse | M24: L & R's Hontomin Gen Mdse
F25: Davocol's Gen. Mdse. | K25: Davocol's Gen. Mdse. | M25: Davocol's Gen. Mdse.
F26: RCJ Hardware & Gen Mdse | K26: RCJ Hardware & Gen Mdse | M26: RCJ Hardware & Gen Mdse
... F87: Valiente Food Producer | K87: Valiente Food Producer | M87: Valiente Food Producer
F88: M.G. Hubalde's General Merchandise | G88: E.A.Amboy General Merchandise | H88: JPM General Merchandise & Hardware | I88: Apostol General Merchandise | L88: MDAC Trading & Compuserve | M88: J-Tech Trading & Services
A90: =PR!D16 -> Printing of Training Manual (Hardbound cover, laminated, colored,15.5 x 23 cm, 70 pages, 80gsm, colored, glossy with ISSN/ISBN number) | B90: Pineapple Chunks | C90: Pineapple Chunks | D90: Pineapple Chunks | E90: Pineapple Chunks | F90: 2500 | G90: none | H90: none | I90: none | L90: 200000 | M90: none
A91: =PR!D17 -> 0 | B91: Pineapple Chunks | C91: Pineapple Chunks | D91: Pineapple Chunks | E91: Pineapple Chunks | F91: 3200 | G91: none | H91: none | I91: none
A92: =PR!D18 -> 0 | B92: Pineapple Chunks | C92: Pineapple Chunks | D92: Pineapple Chunks | E92: Pineapple Chunks | F92: 2500 | G92: none | H92: none | I92: none
A93: =PR!D19 -> 0 | B93: Pineapple Chunks | C93: Pineapple Chunks | D93: Pineapple Chunks | E93: Pineapple Chunks | F93: 6720 | G93: none | H93: none | I93: none
A94: =PR!D20 -> 0 | B94: Pineapple Chunks | C94: Pineapple Chunks | D94: Pineapple Chunks | E94: Pineapple Chunks | F94: 6720 | G94: none | H94: none | I94: none
A95: =PR!D21 -> 0 | B95: Pineapple Chunks | C95: Pineapple Chunks | D95: Pineapple Chunks | E95: Pineapple Chunks | F95: 6720 | G95: none | H95: none | I95: none
A96: =PR!D22 -> 0 | B96: Pineapple Chunks | C96: Pineapple Chunks | D96: Pineapple Chunks | E96: Pineapple Chunks | F96: 6720 | G96: none | H96: none | I96: none
A97: =PR!D23 -> 0 | B97: Pineapple Chunks | C97: Pineapple Chunks | D97: Pineapple Chunks | E97: Pineapple Chunks | F97: 6720 | G97: none | H97: none | I97: none
A98: =PR!D24 -> 0 | B98: Pineapple Chunks | C98: Pineapple Chunks | D98: Pineapple Chunks | E98: Pineapple Chunks | F98: 6720 | G98: none | H98: none | I98: none
A99: =PR!D25 -> 0 | B99: Pineapple Chunks | C99: Pineapple Chunks | D99: Pineapple Chunks | E99: Pineapple Chunks | F99: 2800 | G99: none | H99: none | I99: none
A100: =PR!D26 -> 0 | B100: Pineapple Chunks | C100: Pineapple Chunks | D100: Pineapple Chunks | E100: Pineapple Chunks | F100: 2800 | G100: none | H100: none | I100: none
A101: =PR!D27 -> 0 | B101: Pineapple Chunks | C101: Pineapple Chunks | D101: Pineapple Chunks | E101: Pineapple Chunks | F101: 1750 | G101: none | H101: none | I101: none
A102: =PR!D28 -> 0 | B102: Pineapple Chunks | C102: Pineapple Chunks | D102: Pineapple Chunks | E102: Pineapple Chunks | F102: none | G102: none | H102: none | I102: none
A103: =PR!D29 -> 0 | B103: Pineapple Chunks | C103: Pineapple Chunks | D103: Pineapple Chunks | E103: Pineapple Chunks | F103: 1100 | G103: none | H103: none | I103: none
A104: =PR!D30 -> 0 | B104: Pineapple Chunks | C104: Pineapple Chunks | D104: Pineapple Chunks | E104: Pineapple Chunks | F104: 10400 | G104: none | H104: none | I104: none
A105: =PR!D31 -> 0 | B105: Pineapple Chunks | C105: Pineapple Chunks | D105: Pineapple Chunks | E105: Pineapple Chunks | F105: none | G105: none | H105: none | I105: none
A106: =PR!D32 -> 0 | B106: Pineapple Chunks | C106: Pineapple Chunks | D106: Pineapple Chunks | E106: Pineapple Chunks | F106: none | G106: none | H106: none | I106: none
A107: =PR!D33 -> 0 | B107: Pineapple Chunks | C107: Pineapple Chunks | D107: Pineapple Chunks | E107: Pineapple Chunks | F107: none | G107: none | H107: none | I107: none
A108: =PR!D34 -> 0 | B108: Pineapple Chunks | C108: Pineapple Chunks | D108: Pineapple Chunks | E108: Pineapple Chunks | F108: 3600 | G108: none | H108: none | I108: none
A109: =PR!D35 -> Laddle with wooden handle with hole | B109: Pineapple Chunks | C109: Pineapple Chunks | D109: Pineapple Chunks | E109: Pineapple Chunks | F109: none | G109: none | H109: none | I109: none
A110: =PR!D36 -> Laddle with wooden handle without hole | B110: Pineapple Chunks | C110: Pineapple Chunks | D110: Pineapple Chunks | E110: Pineapple Chunks | F110: 4750 | G110: none | H110: none | I110: none
A111: =PR!D37 -> Measuring Cup Glass | B111: Pineapple Chunks | C111: Pineapple Chunks | D111: Pineapple Chunks | E111: Pineapple Chunks | F111: 3750 | G111: none | H111: none | I111: none
A112: =PR!D38 -> Measuring Cup Set Set Includes: 1/4 cup,1/3 cup, 1/2 cup,1 cup | B112: Pineapple Chunks | C112: Pineapple Chunks | D112: Pineapple Chunks | E112: Pineapple Chunks | F112: 575 | G112: none | H112: none | I112: none
A113: =PR!D39 -> Measuring Spoon Set sets include: 1/8 teaspoon, 1/4 teaspoon, 1/2 teaspoon, 1 teaspoon, 1/ 2 tbsp, 1 tbsp | B113: Pineapple Chunks | C113: Pineapple Chunks | D113: Pineapple Chunks | E113: Pineapple Chunks | F113: 500 | G113: none | H113: none | I113: none
A114: =PR!D40 -> Mixing Bowl with Cover 5pcs | B114: Pineapple Chunks | C114: Pineapple Chunks | D114: Pineapple Chunks | E114: Pineapple Chunks | F114: none | G114: none | H114: none | I114: none
A115: =PR!D41 -> Fruit and Vegetable Peeler Stainless Steel 13 cm (5 ") | B115: Pineapple Chunks | C115: Pineapple Chunks | D115: Pineapple Chunks | E115: Pineapple Chunks | F115: none | G115: none | H115: none | I115: none
A116: =PR!D42 -> Pot Holder Cloth 3pcs/set | B116: Pineapple Chunks | C116: Pineapple Chunks | D116: Pineapple Chunks | E116: Pineapple Chunks | F116: 2500 | G116: none | H116: none | I116: none
A117: =PR!D43 -> Pot Holder Heat Insulated Gloves Specifications: Color: Grey Material: silicone Size: 20.5x16.5cm | B117: Pineapple Chunks | C117: Pineapple Chunks | D117: Pineapple Chunks | E117: Pineapple Chunks | F117: none | G117: none | H117: none | I117: none
A118: =PR!D44 -> Knife Sharpener | B118: Pineapple Chunks | C118: Pineapple Chunks | D118: Pineapple Chunks | E118: Pineapple Chunks | F118: 800 | G118: none | H118: none | I118: none
A119: =PR!D45 -> Sifter Stainless Steel 270 x 70mm Mesh: #30 (0.595mm) | B119: Pineapple Chunks | C119: Pineapple Chunks | D119: Pineapple Chunks | E119: Pineapple Chunks | F119: none | G119: none | H119: none | I119: none
A120: =PR!D46 -> Pitcher Stainless Steel 2000 ml | B120: Pineapple Chunks | C120: Pineapple Chunks | D120: Pineapple Chunks | E120: Pineapple Chunks | F120: 4125 | G120: none | H120: none | I120: none
A121: =PR!D47 -> Basin 3.0 thick 76cm diameter Stainless | B121: Pineapple Chunks | C121: Pineapple Chunks | D121: Pineapple Chunks | E121: Pineapple Chunks | F121: 2400 | G121: none | H121: none | I121: none
A122: =PR!D48 -> Basin 3.0 thick 52cm diameter Stainless | B122: Pineapple Chunks | C122: Pineapple Chunks | D122: Pineapple Chunks | E122: Pineapple Chunks | F122: 2160 | G122: none | H122: none | I122: none
A123: =PR!D49 -> Basin 3.0 thick 40cm diameter Stainless | B123: Pineapple Chunks | C123: Pineapple Chunks | D123: Pineapple Chunks | E123: Pineapple Chunks | F123: 1680 | G123: none | H123: 720 | I123: none
A124: =PR!D50 -> Portioning Bowl Stainless Steel with Capacity Markings Indicator 2.5L (22cm) | B124: Pineapple Chunks | C124: Pineapple Chunks | D124: Pineapple Chunks | E124: Pineapple Chunks | F124: none | G124: none | H124: 3250 | I124: none
A125: =PR!D51 -> Sponge Scrap Pad | B125: Pineapple Chunks | C125: Pineapple Chunks | D125: Pineapple Chunks | E125: Pineapple Chunks | F125: none | G125: none | H125: 4750 | I125: none
A126: =PR!D52 -> Scrub Pad | B126: Pineapple Chunks | C126: Pineapple Chunks | D126: Pineapple Chunks | E126: Pineapple Chunks | F126: none | G126: none | H126: 3250 | I126: none
A127: =PR!D53 -> Dish Cloth Cotton Quick Drying Towel Size: 70x50cm | B127: Pineapple Chunks | C127: Pineapple Chunks | D127: Pineapple Chunks | E127: Pineapple Chunks | F127: none | G127: none | H127: none | I127: none
A128: =PR!D54 -> Cleaning Gloves Long Size,Rubber, Large | B128: Pineapple Chunks | C128: Pineapple Chunks | D128: Pineapple Chunks | E128: Pineapple Chunks | F128: 2200 | G128: none | H128: none | I128: none
A129: =PR!D55 -> Cleaning Gloves Long Size,Rubber, Medium | B129: Pineapple Chunks | C129: Pineapple Chunks | D129: Pineapple Chunks | E129: Pineapple Chunks | F129: 2000 | G129: none | H129: none | I129: none
A130: =PR!D56 -> Cleaning Gloves Long Size,Rubber, Small | B130: Pineapple Chunks | C130: Pineapple Chunks | D130: Pineapple Chunks | E130: Pineapple Chunks | F130: 1800 | G130: none | H130: none | I130: none
A131: =PR!D57 -> Fire Extinguisher ABC Dry Chemical 10LBS | B131: Pineapple Chunks | C131: Pineapple Chunks | D131: Pineapple Chunks | E131: Pineapple Chunks | F131: none | G131: none | H131: none | I131: none
A132: =PR!D58 -> Fruit and Vegetables Brush Soft Bristle | B132: Pineapple Chunks | C132: Pineapple Chunks | D132: Pineapple Chunks | E132: Pineapple Chunks | F132: 1200 | G132: none | H132: none | I132: none
A133: =PR!D59 -> Cleaning Bottle Brush 5 in 1 Multifunctional | B133: Pineapple Chunks | C133: Pineapple Chunks | D133: Pineapple Chunks | E133: Pineapple Chunks | F133: none | G133: none | H133: none | I133: none
A134: =PR!D60 -> Wooden Handle Ladle Length 88 CM Diameter 14 CM | B134: Pineapple Chunks | C134: Pineapple Chunks | D134: Pineapple Chunks | E134: Pineapple Chunks | F134: none | G134: none | H134: none | I134: none
A135: =PR!D61 -> Silicone Gloves | B135: Pineapple Chunks | C135: Pineapple Chunks | D135: Pineapple Chunks | E135: Pineapple Chunks | F135: 2450 | G135: none | H135: none | I135: none
A136: =PR!D62 -> Plastic Crate 52cmX36cmX25cm without Hole Green | B136: Pineapple Chunks | C136: Pineapple Chunks | D136: Pineapple Chunks | E136: Pineapple Chunks | F136: 5000 | G136: none | H136: none | I136: none
A137: =PR!D63 -> Plastic Crate 52cmX36cmX25cm with Hole Green | B137: Pineapple Chunks | C137: Pineapple Chunks | D137: Pineapple Chunks | E137: Pineapple Chunks | F137: 4950 | G137: none | H137: none | I137: none
A138: =PR!D64 -> Plastic Crate 52cmX36cmX25cm without Hole Blue | B138: Pineapple Chunks | C138: Pineapple Chunks | D138: Pineapple Chunks | E138: Pineapple Chunks | F138: 4950 | G138: none | H138: none | I138: none
A139: =PR!D65 -> Plastic Crate 52cmX36cmX25cm with Hole Blue | B139: Pineapple Chunks | C139: Pineapple Chunks | D139: Pineapple Chunks | E139: Pineapple Chunks | F139: 5000 | G139: none | H139: none | I139: none
A140: =PR!D66 -> Plastic Bucket 12L with Cover and handle Food Grade (Storage Containers) white | B140: Pineapple Chunks | C140: Pineapple Chunks | D140: Pineapple Chunks | E140: Pineapple Chunks | F140: 24000 | G140: none | H140: none | I140: none
A141: =PR!D67 -> Plastic Bucket 6L with Cover and handle Food Grade (Storage Containers) white | B141: Pineapple Chunks | C141: Pineapple Chunks | D141: Pineapple Chunks | E141: Pineapple Chunks | F141: 6800 | G141: none | H141: none | I141: none
A142: =PR!D68 -> Plastic Bucket 4L with Cover and handle Food Grade (Storage Containers)white | B142: Pineapple Chunks | C142: Pineapple Chunks | D142: Pineapple Chunks | E142: Pineapple Chunks | F142: 5600 | G142: none | H142: none | I142: none
A143: =PR!D69 -> Plastic Bucket 2L with Cover and handle Food Grade (Storage Containers) white | B143: Pineapple Chunks | C143: Pineapple Chunks | D143: Pineapple Chunks | E143: Pineapple Chunks | F143: none | G143: none | H143: none | I143: none
A144: =PR!D70 -> Storage box 155 liters | B144: Pineapple Chunks | C144: Pineapple Chunks | D144: Pineapple Chunks | E144: Pineapple Chunks | F144: none | G144: none | H144: none | I144: none
A145: =PR!D71 -> Steamer Cooker 20 Quart Induction-ready Stainless Steel Cover included Stainless steel Tri-ply bottom | B145: Pineapple Chunks | C145: Pineapple Chunks | D145: Pineapple Chunks | E145: Pineapple Chunks | F145: none | G145: none | H145: none | I145: none
A146: =PR!D72 -> Stock Pot with Cover, 45CM*45CM Stainless Steel | B146: Pineapple Chunks | C146: Pineapple Chunks | D146: Pineapple Chunks | E146: Pineapple Chunks | F146: none | G146: none | H146: none | I146: none
A147: =PR!D73 -> Wok Pan 2mm (thickness) 60cm diameter | B147: Pineapple Chunks | C147: Pineapple Chunks | D147: Pineapple Chunks | E147: Pineapple Chunks | F147: none | G147: none | H147: none | I147: none
A148: =PR!D74 -> Office Desk/Table Material: MDF Color: Walnut Dimensions of Table: 47.24" W x 30.31" H x 23.63" D Drawer Dimensions: 11" W x 23" H x 18.75" D | B148: Pineapple Chunks | C148: Pineapple Chunks | D148: Pineapple Chunks | E148: Pineapple Chunks | F148: =DATA!O1265 -> 0 | G148: none | H148: none | I148: none | K148: none
A149: =PR!D75 -> Office Chair - Junior Executive Chair Black Leatherette Ergonomic with padded armrests Chrome base with smooth-rolling caster wheels Seat Dimensions: 21" L x 21" W Backrest Dimensions: 26.5" L x 21" W Full Dimensions: 25" W x 42" - 45" H | B149: Pineapple Chunks | C149: Pineapple Chunks | D149: Pineapple Chunks | E149: Pineapple Chunks | F149: =DATA!O1266 -> 0 | G149: none | H149: none | I149: none | K149: none
A150: =PR!D76 -> Portable Projector with bag and stand Product Details: Android 11,500 ANSI DRM L1 Certification nnovative 120°rotating projection ASA 3.0(AF+KS+ScrnFit+Avoid) Dual-bass diaphragms ≤30 dB/m Ultra-low decibel Specifications: Product Color: White Product Weight: 1.5Kg Product Size: 145*142*219 mm Display Technology: LCD Brightness: 500 ANSI Lumens Physical Resolution: 1920 * 1080 FHD Lens： 3 Pcs aspherical pure glass lens Projection Features Zoom Function：50%-100% Projection Ratio: 1.2: 1 Projection Size: 45-140 Inch Projection Distance: 1.2-3.8m Intelligent Adjustment Keystone Correction： Auto Focus Adjustment： Auto Obstacle Avoidance： Auto Screen Alignment： Auto Audio & Connectivity Speaker: 5W * 2 Noise: ≤30dB/m Cavity Volume：370CC Bluetooth: 5.0 WiFi: Dual Band 2.4/5G Hz Interface HDMI：*1 USB：*1 AUX3.5mm：*1 | B150: Pineapple Chunks | C150: Pineapple Chunks | D150: Pineapple Chunks | E150: Pineapple Chunks | F150: =DATA!O1267 -> 0 | G150: none | H150: none | I150: none | K150: none
A151: =PR!D77 -> 0 | B151: Pineapple Chunks | C151: Pineapple Chunks | D151: Pineapple Chunks | E151: Pineapple Chunks | F151: =DATA!O1268 -> 0
A152: =PR!D78 -> Assorted Coffee 3 in 1 | B152: Pineapple Chunks | C152: Pineapple Chunks | D152: Pineapple Chunks | E152: Pineapple Chunks | F152: =DATA!O1269 -> 0
A153: =PR!D79 -> Coke 1.7L | B153: Pineapple Chunks | C153: Pineapple Chunks | D153: Pineapple Chunks | E153: Pineapple Chunks | F153: =DATA!O1270 -> 0
A154: =PR!D80 -> Bottled Water 1L | B154: Pineapple Chunks | C154: Pineapple Chunks | D154: Pineapple Chunks | E154: Pineapple Chunks | F154: =DATA!O1271 -> 0
A155: =PR!D81 -> Dutchmill 90ml 4's | B155: Pineapple Chunks | C155: Pineapple Chunks | D155: Pineapple Chunks | E155: Pineapple Chunks | F155: =DATA!O1272 -> 0 | G155: 17000 | H155: 17000 | I155: 17000
A156: =PR!D82 -> Dutchmill 180ml 4's | B156: Pineapple Chunks | C156: Pineapple Chunks | D156: Pineapple Chunks | E156: Pineapple Chunks | F156: =DATA!O1273 -> 0 | G156: 1500 | H156: 1500 | I156: 1500
A157: =PR!D83 -> Chuckie 180ml 6's | B157: Pineapple Chunks | C157: Pineapple Chunks | D157: Pineapple Chunks | E157: Pineapple Chunks | F157: =DATA!O1274 -> 0 | G157: 880 | H157: 880 | I157: 880
A158: =PR!D84 -> Cupkeyk | B158: Pineapple Chunks | C158: Pineapple Chunks | D158: Pineapple Chunks | E158: Pineapple Chunks | F158: =DATA!O1275 -> 0 | G158: 180 | H158: 180 | I158: 180
A159: =PR!D85 -> Fudgee Bar | B159: Pineapple Chunks | C159: Pineapple Chunks | D159: Pineapple Chunks | E159: Pineapple Chunks | F159: =DATA!O1276 -> 0 | G159: 360 | H159: 360 | I159: 360
A160: =PR!D86 -> Mamon 12's | B160: Pineapple Chunks | C160: Pineapple Chunks | D160: Pineapple Chunks | E160: Pineapple Chunks | F160: =DATA!O1277 -> 0 | G160: 900 | H160: 900 | I160: 900
A161: =PR!D87 -> Smart-C Assorted | B161: Pineapple Chunks | C161: Pineapple Chunks | D161: Pineapple Chunks | E161: Pineapple Chunks | F161: =DATA!O1278 -> 0 | G161: 900 | H161: 900 | I161: 900
A162: =PR!D88 -> Chuckie 110ml 6's | B162: Pineapple Chunks | C162: Pineapple Chunks | D162: Pineapple Chunks | E162: Pineapple Chunks | F162: =DATA!O1279 -> 0 | G162: 925 | H162: 925 | I162: 925
A163: =PR!D89 -> Nestea Drink 500ml | B163: Pineapple Chunks | C163: Pineapple Chunks | D163: Pineapple Chunks | E163: Pineapple Chunks | F163: =DATA!O1280 -> 0 | G163: 9300 | H163: 9300 | I163: 9300
A164: =PR!D90 -> Meal Box 2 Compartment | B164: Pineapple Chunks | C164: Pineapple Chunks | D164: Pineapple Chunks | E164: Pineapple Chunks | F164: =DATA!O1281 -> 0 | G164: 32000 | H164: 32000 | I164: 32000
A165: =PR!D91 -> Disposable Fork | B165: Pineapple Chunks | C165: Pineapple Chunks | D165: Pineapple Chunks | E165: Pineapple Chunks | F165: =DATA!O1282 -> 0 | G165: 9900 | H165: 9900 | I165: 9900
A166: =PR!D92 -> Disposable Spoon | B166: Pineapple Chunks | C166: Pineapple Chunks | D166: Pineapple Chunks | E166: Pineapple Chunks | F166: =DATA!O1283 -> 0 | G166: 400 | H166: 400 | I166: 400
... A169: =PR!D95 -> Disposable Bowl 390cc | B169: Pineapple Chunks | C169: Pineapple Chunks | D169: Pineapple Chunks | E169: Pineapple Chunks | F169: =DATA!O1286 -> 0 | G169: 1440 | H169: 1440 | I169: 1440
A170: =PR!D96 -> Disposable Cup 8oz | B170: Pineapple Chunks | C170: Pineapple Chunks | D170: Pineapple Chunks | E170: Pineapple Chunks | F170: =DATA!O1287 -> 0
...

Sheet LON (2)
A6: BIDS AND AWARDS COMMITTEE
A8: LETTER OF NOTICE
A11: NATHAN A. AMBOY
A12: Owner
A13: FVA Trading
A14: Brgy. Kaychanarianan, Batanes
A17: Madam/Sir:
A18: We are happy to notify you that your quotation dated September 8, 2025 for the 4ft x 8ft Galvanized Plain Sheet, 25 Gauge,2inch x 3inch x 12ft Palochina Wood,3inch Log Screw with Anchor, etc,. with PR # 2509-GAS20-305 contract price equivalent to SEVENTY SIX THOUSAND FIVE HUNDRED FORTY FOUR PESOS ONLY (Php 76,544.00) is hereby accepted.
A19: You are hereby required to provide within Ten (10) days a certified photocopy of the following requirements:
A20: .
B21: 1. Updated Mayor's Permit/Business Permit
B22: 2. PhilGEPS Registration no.
B23: 3. Latest Income/Business Tax Return (ITR)
B24: 4. Duly Notarized Omnibus Sworn Statement
B25: 5. BIR 2302 Certificate of Registration (COR)
B26: 6. Updated DTI Registration
B27: 7. Landbank Account details of the business (for payment purposes)
A29: However, If you already have a maintaining and updated file of the above-mentioned requirements in the BAC Office you may no longer require its re-submission (Annex "H", Appendix "A" Section III)
A31: *For individuals engaged under Sec. 53.6, 53.7, and 53.9 of the IRR of RA 9184, only the BIR Certificate of Registration shall be submitted in lieu of DTI Registration and Mayor’s Permit.
A32: Thank you
A34: Very truly yours,
A37: DOREEN C. CASTILLO
A38: BAC Chairperson
A40: Received by:
A43: (Signature over printed name)
A44: Date: ___________________
A45: Ref. No.: | B45: =PR!B12 -> 2510-1005-380

Sheet BAC  Award 2025
E6: OFFICE OF THE BIDS AND AWARDS COMMITTEE | N6: OFFICE OF THE BIDS AND AWARDS COMMITTEE
D7: BAC Resolution No: | M7: =D7 -> BAC Resolution No:
D8: =PR!B12 -> 2510-1005-380 | M8: =D8 -> 2510-1005-380
E10: BAC RESOLUTION RECOMMENDING FOR AWARD | N10: APPROVAL OF THE BAC RECOMMENDATION FOR AWARD
A12: WHEREAS, the BATANES STATE COLLEGE advertised the Request for Price Quotation (RFQ) of the Printing of Training Manual (Hardbound cover, laminated, colored,15.5 x 23 cm, 70 pages, 80gsm, colored, glossy with ISSN/ISBN number) with PR # 2510-1005-380 dated October 20, 2025. | J12: WHEREAS, the BATANES STATE COLLEGE advertised the Request for Price Quotation (RFQ) of the Printing of Training Manual (Hardbound cover, laminated, colored,15.5 x 23 cm, 70 pages, 80gsm, colored, glossy with ISSN/ISBN number) with PR # 2510-1005-380 dated October 20, 2025.
A15: WHEREAS, from the period the Request for Price Quotation (RFQ) has started up to the time of bid submission and opening,Four (4) prospective bidder were able to submit the RFQ; | J15: WHEREAS, from the period the Request for Price Quotation (RFQ) has started up to the time of bid submission and opening,Four (4) prospective bidder were able to submit the RFQ;
A18: WHEREAS, the Price Quotation based on the Lowest Calculated & Responsive Bid (LCRB) format of the bidders were opened and its bid price was read as follows: | J18: WHEREAS, the Price Quotation based on the Lowest Calculated & Responsive Bid (LCRB) format of the bidders were opened and its bid price was read as follows:
A21: ITEM NO. | B21: BIDDER WITH CALCULATED BID | G21: ABC | I21: BID AMOUNT | J21: ITEM NO. | K21: BIDDER WITH CALCULATED BID | P21: ABC | R21: BID AMOUNT
A22: 1 | B22: =DATA!W200 -> YCA Printing Services | G22: =PR!H110 -> 81000 | I22: 81000 | J22: 1 | K22: =B22 -> YCA Printing Services | P22: =G22 -> 81000 | R22: =I22 -> 81000
A23: 2 | B23: Golden Press | G23: =PR!H110 -> 81000 | I23: 87500 | J23: 2 | K23: =B23 -> Golden Press | P23: =G23 -> 81000 | R23: =I23 -> 87500
A24: 3 | B24: CMVILL Trading | G24: =PR!H110 -> 81000 | I24: 90000 | J24: 3 | K24: =B24 -> CMVILL Trading | P24: =G24 -> 81000 | R24: =I24 -> 90000
A25: 4 | B25: One-Touch Technology Trading | G25: =PR!H110 -> 81000 | I25: none | J25: 4 | K25: =B25 -> One-Touch Technology Trading | P25: =G25 -> 81000 | R25: =I25 -> none
A26: 5 | G26: =PR!H110 -> 81000 | I26: none | J26: 5 | K26: =B26 -> 0 | P26: =G26 -> 81000 | R26: =I26 -> none
A27: 6 | B27: JPM General Merchandise & hardware | G27: =PR!H110 -> 81000 | I27: none | J27: 6 | K27: =B27 -> JPM General Merchandise & hardware | P27: =G27 -> 81000 | R27: =I27 -> none
A28: 7 | J28: 7 | K28: =B28 -> 0 | P28: =G28 -> 0 | R28: =I28 -> 0
B29: JPM General Merchandise & hardware | J29: 8 | K29: =B29 -> JPM General Merchandise & hardware | P29: =G29 -> 0 | R29: =I29 -> 0
J30: NOW THEREFORE, I DJOVI R. DURANTE,DPA by virtue of the authority vested in me of this institution and after taking into consideration the merits and legal bases of the recommendation of the members of the Bids and Awards Committee (BAC) do hereby APPROVE the following;
B32: 1. To declare YCA Printing Services as supplier with the Lowest Calculated & Responsive Bid of Printing of Training Manual (Hardbound cover, laminated, colored,15.5 x 23 cm, 70 pages, 80gsm, colored, glossy with ISSN/ISBN number) with PR # 2510-1005-380 dated October 20, 2025.
B35: 2. To recommend for approval by the Head of Procuring Entity of the Batanes State College the foregoing findings.
A36: RESOLVED FINALLY, at the BAC Office, Batanes State College, this _______day of . | J36: To declare YCA Printing Services as supplier with the Lowest Calculated & Responsive Bid of Printing of Training Manual (Hardbound cover, laminated, colored,15.5 x 23 cm, 70 pages, 80gsm, colored, glossy with ISSN/ISBN number) with PR # 2510-1005-380.
A37: Recommending Approval:
A40: RHOUPHELINE AYA A. CADIZ | D40: EMILYN D. ALUETA | G40: FORTUNATO PHILIP A. CABUGAO | J40: Done this ______ day of _________ 2026.
A41: BAC Member | D41: BAC Member | G41: BAC Member
L44: DJOVI REGALA DURANTE,DPA
A45: =PR!B115 -> JANE S. CASTILLO | F45: PHILIP ULYSSES T. CASTILLO | L45: SUC President I
A46: End-user/Provisional Member | F46: Vice BAC Chairperson
D48: DOREEN C. CASTILLO
D49: BAC Chairperson

Sheet BAC RESO 2022 (Toss Coin)
E6: OFFICE OF THE BIDS AND AWARDS COMMITTEE | N6: OFFICE OF THE BIDS AND AWARDS COMMITTEE
E7: bac resolution No: | M7: =E7 -> bac resolution No:
D8: =PR!B12 -> 2510-1005-380 | M8: =D8 -> 2510-1005-380
E10: BAC RESOLUTION RECOMMENDING FOR AWARD | N10: APPROVAL OF THE BAC RECOMMENDATION FOR AWARD
A12: WHEREAS, the BATANES STATE COLLEGE advertised the Request for Price Quotation (RFQ)of the Tarpaulin 8 x 5ft with PR # 2510-SS09-368 dated October 15, 2025. | J12: WHEREAS, the BATANES STATE COLLEGE advertised the Request for Price Quotation (RFQ)of the Tarpaulin 8 x 5ft with PR # 2510-SS09-368 dated October 15, 2025.
A15: WHEREAS, from the period the Request for Price Quotation (RFQ) has started up to the time of bid submission and opening, Three (3) prospective bidders were able to submit the RFQ; | J15: WHEREAS, from the period the Request for Price Quotation (RFQ) has started up to the time of bid submission and opening, Three (3) prospective bidders were able to submit the RFQ;
A18: WHEREAS, the Price Quotation based on the Lowest Calculated & Responsive Bid (LCRB) format of the bidders were opened and its bid price was read as follows: | J18: WHEREAS, the Price Quotation based on the Lowest Calculated & Responsive Bid (LCRB) format of the bidders were opened and its bid price was read as follows:
A21: ITEM NO. | B21: BIDDER WITH CALCULATED BID | G21: ABC | I21: BID AMOUNT | J21: ITEM NO. | K21: BIDDER WITH CALCULATED BID | P21: ABC | R21: BID AMOUNT
A22: 1 | B22: =DATA!W135 -> YCA Printing Services | G22: =PR!H110 -> 81000 | I22: 1200 | J22: 1 | K22: =B22 -> YCA Printing Services | P22: =G22 -> 81000 | R22: =I22 -> 1200
A23: 2 | B23: IAM'J Graphic Design & Printing | G23: =PR!H110 -> 81000 | I23: 1200 | J23: 2 | K23: =B23 -> IAM'J Graphic Design & Printing | P23: =G23 -> 81000 | R23: =I23 -> 1200
A24: 3 | B24: CMVILL Trading | G24: =PR!H110 -> 81000 | I24: 2500 | J24: 3 | K24: =B24 -> CMVILL Trading | P24: =G24 -> 81000 | R24: =I24 -> 2500
A25: 4 | J25: 4 | K25: =B25 -> 0 | P25: =G25 -> 0 | R25: =I25 -> 0
A26: 5 | J26: 5 | K26: =B26 -> 0 | P26: =G26 -> 0 | R26: =I26 -> 0
A27: 6 | J27: 6 | K27: =B27 -> 0 | P27: =G27 -> 0 | R27: =I27 -> 0
A28: 7 | J28: 7 | K28: =B28 -> 0 | P28: =G28 -> 0 | R28: =I28 -> 0
A29: 8 | J29: 8 | K29: =B29 -> 0 | P29: =G29 -> 0 | R29: =I29 -> 0
A30: WHEREAS,two (2) of the suppliers have the same total price quotation; | J30: WHEREAS,two (2) of the suppliers have the same total price quotation;
A32: WHEREAS, to resolve cases involving a tie, the procuring entity may determine a measure to be used by which it shall be non-discretionary and non-discriminatory such that the same shall be based on sheer luck or chance. The method used was "toss coin"; | J32: WHEREAS, to resolve cases involving a tie, the procuring entity may determine a measure to be used by which it shall be non-discretionary and non-discriminatory such that the same shall be based on sheer luck or chance. The method used was "toss coin";
A34: However, IAM'J Graphic Design & Printing was not able to attend the said Toss Coin, | J34: However, IAM'J Graphic Design & Printing was not able to attend the said Toss Coin,
A35: WHEREAS, as per result of the toss coin conducted, YCA Printing Services was announced as the winner: | J35: WHEREAS, as per result of the toss coin conducted, YCA Printing Services was announced as the winner:
B36: 1. To declare YCA Printing Services as supplier of Tarpaulin 8 x 5ft with PR # 2510-SS09-368 dated October 15, 2025. | J36: NOW THEREFORE, I DJOVI R. DURANTE,DPA by virtue of the authority vested in me of this institution and after taking into consideration the merits and legal bases of the recommendation of the members of the Bids and Awards Committee (BAC) do hereby APPROVE the following;
B39: 2. To recommend for approval by the Head of Procuring Entity of the Batanes State College the foregoing findings.
A40: RESOLVED FINALLY, at the BAC Office, Batanes State College, this _______day of . | J40: To declare YCA Printing Services as supplier of Tarpaulin 8 x 5ft with PR # 2510-SS09-368.
A41: Recommending Approval:
A44: RHOUPHELINE AYA A. CADIZ | D44: EMILYN D. ALUETA | G44: FORTUNATO PHILIP A. CABUGAO | J44: Done this _______ day of ___________ 2022 | N44: 2025
A45: BAC Member | D45: BAC Member | G45: BAC Member
L47: DJOVI REGALA DURANTE,DPA
A48: =PR!B115 -> JANE S. CASTILLO | D48: PHILIP ULYSSES T. CASTILLO | H48: DOREEN C. CASTILLO | L48: SUC President I
A49: End-user/Provisional Member | D49: BAC Vice Chairperson | H49: BAC Chairperson

Sheet PO (2)
E2: Appendix 61
A3: PURCHASE ORDER
A4: BATANES STATE COLLEGE
A5: Entity Name
A6: Supplier : | B6: =DATA!W200 -> YCA Printing Services | D6: P.O. No. : | E6: 2025-10-380
A7: Address : | B7: Basco, Batanes | D7: Date : | E7: December 23, 2025
A8: TIN : | B8: 206-113-292-00000 | C8: 206-113-292-00000 | D8: Mode of Procurement : Small Value Procurement
A9: Gentlemen:
A10: Please furnish this Office the following articles subject to the terms and conditions contained herein:
A12: Place of Delivery : ___________________________________ | B12: Batanes Stae College | D12: Delivery Term : FOB Destination
A13: Date of Delivery : ____________________________________ | B13: 30 days upon receipt of PO | D13: Payment Term : 15 days upon complete delivery
A14: Stock/ Property No. | B14: Unit | C14: Description | D14: Quantity | E14: Unit Cost | F14: Amount
A15: 1 | B15: =PR!B16 -> copies | C15: =PR!D16 -> Printing of Training Manual (Hardbound cover, laminated, colored,15.5 x 23 cm, 70 pages, 80gsm, colored, glossy with ISSN/ISBN number) | D15: =PR!A16 -> 60 | E15: =DATA!N200 -> 1350 | F15: =SUM(D15*E15) -> 81000
A16: 2 | F16: =SUM(D16*E16) -> 0
A17: 3 | F17: =SUM(D17*E17) -> 0
A18: 4 | F18: =SUM(D18*E18) -> 0
A19: 5 | F19: =SUM(D19*E19) -> 0
A20: 6 | F20: =SUM(D20*E20) -> 0
A21: 7 | F21: =SUM(D21*E21) -> 0
A22: 8 | F22: =SUM(D22*E22) -> 0
A23: 9 | F23: =SUM(D23*E23) -> 0
A24: 10 | F24: =SUM(D24*E24) -> 0
A25: 11 | B25: =PR!B26 -> 0 | C25: =PR!D26 -> 0 | D25: =PR!A26 -> 0 | E25: =DATA!N356 -> 3385 | F25: =SUM(D25*E25) -> 0
A26: 12 | B26: =PR!B27 -> 0 | C26: =PR!D27 -> 0 | D26: =PR!A27 -> 0 | E26: =DATA!N357 -> 2280 | F26: =SUM(D26*E26) -> 0
A27: 13 | B27: =PR!B28 -> 0 | C27: =PR!D28 -> 0 | D27: =PR!A28 -> 0 | E27: =DATA!N358 -> 0 | F27: =SUM(D27*E27) -> 0
A28: 14 | B28: =PR!B29 -> 0 | C28: =PR!D29 -> 0 | D28: =PR!A29 -> 0 | E28: =DATA!N359 -> 0 | F28: =SUM(D28*E28) -> 0
A29: 15 | B29: =PR!B30 -> 0 | C29: =PR!D30 -> 0 | D29: =PR!A30 -> 0 | E29: =DATA!N360 -> 0 | F29: =SUM(D29*E29) -> 0
A30: 16 | B30: =PR!B31 -> 0 | C30: =PR!D31 -> 0 | D30: =PR!A31 -> 0 | E30: =DATA!N361 -> 0 | F30: =SUM(D30*E30) -> 0
A31: 17 | E31: =DATA!N362 -> 0 | F31: =SUM(D31*E31) -> 0
A32: 18 | E32: =DATA!N363 -> 0 | F32: =SUM(D32*E32) -> 0
A33: 19 | E33: =DATA!N364 -> 0 | F33: =SUM(D33*E33) -> 0
A34: 20 | E34: =DATA!N365 -> 0 | F34: =SUM(D34*E34) -> 0
A35: 21 | E35: =DATA!N366 -> 0 | F35: =SUM(D35*E35) -> 0
A36: 22 | E36: =DATA!N367 -> 0 | F36: =SUM(D36*E36) -> 0
A37: 23 | E37: =DATA!N368 -> 0 | F37: =SUM(D37*E37) -> 0
A38: 24 | E38: =DATA!N369 -> 0 | F38: =SUM(D38*E38) -> 0
A39: 25 | E39: =DATA!N370 -> 225 | F39: =SUM(D39*E39) -> 0
A40: 26 | E40: =DATA!N371 -> 225 | F40: =SUM(D40*E40) -> 0
A41: 27 | E41: =DATA!N372 -> 225 | F41: =SUM(D41*E41) -> 0
A42: 28 | E42: =DATA!N373 -> 185 | F42: =SUM(D42*E42) -> 0
... A56: 42 | E56: =DATA!N387 -> 0 | F56: =SUM(D56*E56) -> 0
E57: =DATA!N388 -> 0
E58: =DATA!N389 -> 0
E59: =DATA!N390 -> 0
E60: =DATA!N391 -> 0
E61: =DATA!N392 -> 0
E62: =DATA!N393 -> 0
E63: =DATA!N394 -> 0
E64: =DATA!N395 -> 0
E65: =DATA!N396 -> 0
E66: =DATA!N397 -> 0
E67: =DATA!N398 -> 0
E68: =DATA!N399 -> 0
... E81: =DATA!N412 -> 0
A82: Total | E82: =DATA!N413 -> 0 | F82: =SUM(F15:F22) -> 81000
A83: (Total Amount in Words) | C83: EIGHTY ONE THOUSAND PESOS ONLY | F83: =SUM(F15:F30) -> 81000
A85: In case of failure to make the full delivery within the time specified above, a penalty of one-tenth (1/10) of one percent for every day of delay shall be imposed on the undelivered item/s.
A88: Conforme: | D88: Very truly yours,
A90: __________________________ | D90: DJOVI REGALA DURANTE,DPA
A91: Signature over Printed Name of Supplier | D91: Signature over Printed Name of Authorized Official
A92: ___________________________ | D92: SUC President I
A93: Date | D93: Designation
A96: Fund Cluster : ___________________________________ | D96: ORS/BURS No. : ______________________
A97: Funds Available : _________________________________ | D97: Date of the ORS/BURS: _______________
B98: RHEA ANGELLICA B. ADDATU,CPA | D98: Amount : | E98: =F83 -> 81000
B99: Signature over Printed Name of Chief Accountant/Head of Accounting Division/Unit

Sheet POback (2)
A1: INSTRUCTIONS
A3: A. The PO is a form/document used by the agency/entity, addressed to supplier, to deliver specific quantities of supplies/goods/property subject to the terms and conditions contained in the PO.
A4: B. This form shall be accomplished as follows:
B5: 1. Entity Name - name of the agency/entity
B6: 2. Supplier/Address/TIN - name, address and TIN of the supplier
B7: 3. P.O. No. - the number assigned to the PO which shall be as follows:
C8: 0000-00-0000 | E8: Serial number (one series for each year)
E9: Month
E10: Year
B11: 4. Date - date of the preparation of the PO
B12: 5. Mode of Procurement - mode of procurement such as public bidding, through Procurement Service, limited source bidding, direct contracting, repeat order, shopping and negotiated procurement in accordance with RA 9184
B13: 6. Place/Date of Delivery - place of delivery and definite date/s of delivery; if not stated, the date of delivery shall mean seven (7) calendar days after the receipt of PO by the supplier
B14: 7. Delivery Term - delivery term i.e., FOB destination, FOB shipping point
B15: 8. Payment Term - specified period required when the delivered goods shall be paid and discounts, if any, such as 2/10, n/30
B16: 9. Stock/Property No. - stock/property number of the goods to be purchased as provided by the Supply and/or Property Division Unit
B17: 10. Unit - unit of measurement of the supplies/goods/property being procured (i.e. piece, roll, box, reams, etc.)
B18: 11. Description - brief description of the supplies/goods/property being procured
B19: 12. Quantity - quantity of supplies/goods/property being procured
B20: 13. Unit Cost - cost per unit of the supplies/goods/property being procured
B21: 14. Amount - total amount of the supplies/goods/property being procured (Quantity x Unit Cost)
B22: 15. Penalty Clause - penalty to be imposed by the agency/entity in case of non-compliance with the term, that is, one-tenth (1/10) of one percent (1%) for every day of delay on the undelivered item/s
... B27: 20. ORS/BURSNo., Date and Amount - ORS/BURS number assigned by the Budget Division/Unit, date of the ORS/BURS and the amount of obligation supporting the purchase
A28: C. It shall be prepared in four (4) copies distributed as follows:
B29: Original - to the supplier for conforme to the terms of the PO and as attachment to the DV upon request for payment
B30: Copy 2 - retained by the Supply and/or Property Division Unit for file
B31: Copy 3 - to be submitted to COA within five (5) days after conformity by the supplier
B32: Copy 4 - Supplier's copy

Sheet ChkDocs
B1: PR No.: | C1: 22-040 | D1: -------------------cut here-------------------cut here-------------------cut here-------------------cut here-------------------cut here------------------- | E1: PR No.: | F1: =C1 -> 22-040 | G1: -------------------cut here-------------------cut here-------------------cut here-------------------cut here-------------------cut here------------------- | H1: PR No.: | I1: =C1 -> 22-040
B2: Checklist of Documents Submitted: | E2: Checklist of Documents Submitted: | H2: Checklist of Documents Submitted:
C3: Management Monitoring Slip | F3: Management Monitoring Slip | I3: Management Monitoring Slip
B4: X | C4: Purchase Request | E4: X | F4: Purchase Request | H4: X | I4: Purchase Request
C5: Pre and Post Inspection Report | F5: Pre and Post Inspection Report | I5: Pre and Post Inspection Report
B6: X | C6: OBR | E6: X | F6: OBR | H6: X | I6: OBR
B7: X | C7: BAC Resolution | E7: =B7 -> X | F7: BAC Resolution | H7: =B7 -> X | I7: BAC Resolution
B8: X | C8: Approval of BAC Resolution on SVP | E8: =B8 -> X | F8: Approval of BAC Resolution on SVP | H8: =B8 -> X | I8: Approval of BAC Resolution on SVP
B9: X | C9: RFQ1 | E9: =B9 -> X | F9: RFQ1 | H9: =B9 -> X | I9: RFQ1
B10: X | C10: RFQ2 | E10: =B10 -> X | F10: RFQ2 | H10: =B10 -> X | I10: RFQ2
B11: X | C11: RFQ3 | E11: =B11 -> X | F11: RFQ3 | H11: =B11 -> X | I11: RFQ3
B12: X | C12: Acknowledgment for Request for Quotation | E12: =B12 -> X | F12: Acknowledgment for Request for Quotation | H12: =B12 -> X | I12: Acknowledgment for Request for Quotation
C13: Abstract of Bids | E13: =B13 -> 0 | F13: Abstract of Bids | H13: =B13 -> 0 | I13: Abstract of Bids
B14: X | C14: BAC Resolution for Award | E14: =B14 -> X | F14: BAC Resolution for Award | H14: =E14 -> X | I14: BAC Resolution for Award
B15: X | C15: Approval of Reso. for Award | E15: =B15 -> X | F15: Approval of Reso. for Award | H15: =E15 -> X | I15: Approval of Reso. for Award
B16: X | C16: Letter of Notice | E16: =B16 -> X | F16: Letter of Notice | H16: =B16 -> X | I16: Letter of Notice
B17: X | C17: Notice to Proceed | E17: =B17 -> X | F17: Notice to Proceed | I17: Notice to Proceed
B18: X | C18: Certification of BAC | E18: =B18 -> X | F18: Certification of BAC | H18: =B18 -> X | I18: Certification of BAC
C19: Waste Materials Report/Pre & Post Repair Inspection | E19: =B19 -> 0 | F19: Waste Materials Report/Pre & Post Repair Inspection | H19: =B19 -> 0 | I19: Waste Materials Report/Pre & Post Repair Inspection
B20: X | C20: Purchase Order (PO) | E20: =B20 -> X | F20: Purchase Order (PO) | H20: =B20 -> X | I20: Purchase Order (PO)
B21: X | C21: Charge/Sales Invoice | E21: =B21 -> X | F21: Charge/Sales Invoice | H21: =B21 -> X | I21: Charge/Sales Invoice
B22: X | C22: IAR | E22: X | F22: IAR | H22: X | I22: IAR
C23: Inventory Custodian Slip (ICS) | E23: =B23 -> 0 | F23: Inventory Custodian Slip (ICS) | H23: =B23 -> 0 | I23: Inventory Custodian Slip (ICS)
B24: X | C24: RIS | E24: X | F24: RIS | H24: X | I24: RIS
C25: (3)ARE # 221111LLB,DRD,AAM-ARE | F25: =C25 -> (3)ARE # 221111LLB,DRD,AAM-ARE | H25: =B25 -> 0 | I25: =C25 -> (3)ARE # 221111LLB,DRD,AAM-ARE
B26: X | C26: PhilGEPS Bid Notice Abstract ref #8607137 | E26: =B26 -> X | F26: =C26 -> PhilGEPS Bid Notice Abstract ref #8607137 | H26: =B26 -> X | I26: =C26 -> PhilGEPS Bid Notice Abstract ref #8607137
C27: MOA | F27: MOA | I27: MOA
B28: X | C28: PPMP for CY2021 | E28: =B28 -> X | F28: =C28 -> PPMP for CY2021 | H28: =B28 -> X | I28: =C28 -> PPMP for CY2021
C29: Attendance Sheet | E29: =B29 -> 0 | F29: Attendance Sheet | H29: =B29 -> 0 | I29: Attendance Sheet
C30: Recipient of load | E30: =B30 -> 0 | F30: Recipient of load | H30: =B30 -> 0 | I30: Recipient of load
B31: Received by: | E31: Received by: | H31: Received by:
C33: (Signature over Printed Name/Date) | F33: (Signature over Printed Name/Date) | I33: (Signature over Printed Name/Date)
B34: Note: Please return one (1) copy to Supply section for filing purposes. Thank you. | E34: Note: Please return one (1) copy to Supply section for filing purposes. Thank you. | H34: Note: Please return one (1) copy to Supply section for filing purposes. Thank you.
B35: SS Form 14/001 (A) | E35: SS Form 14/001 (B) | H35: SS Form 14/001©
D36: "
B40: +

Sheet AResoSVP -Emergency
A4: Approval of BAC Resolution Recommending Emergency Procurement of the Project: Supply and Installation of 50KVA Transformer
B6: BAC Resolution No. | D6: =PR!B12 -> 2510-1005-380
A8: WHEREAS, Section 53 Rule XVI of the Revised Implementing Rules and Regulations of RA 9184
A9: allows Negotiated Mode of Procurement subject to prior approval of the HOPE thru Annual
A10: Procurement Plan (APP) and only to promote economy and efficiency;
A12: WHEREAS, Section 53.2 allows Emergency Cases in case of imminent danger to life or property
A13: during state of calamity, or when time is of the essence arising from natural or man-made calamities or other
A14: causes where immediate action is necessary to prevent damage to or loss of life or property, or to
A15: restore vital public services, infrastructure facilities and other public utilities;
A17: WHEREAS, "Annex H" of the Consolidated Guidelines for Emergency Cases prescribed under
A18: Section V, Paragraph D.2.b.,upon submission of request and other supporting documents identifying
A19: the emergency sought to be addressed, the BAC shall prepare the appropriate procurement
A20: documents and directly negotiate with a supplier, contractor, or consultant with technical, legal and
A21: financial capability to deliver the goods, execute the works and perform the services to address the emergency;
... A24: the HOPE, upon the recommendation of the BAC, shall immediately award the contract to the Supplier, Contractor or Consultant;
A25: WHEREAS, Purchase Request No. | D25: =PR!E9 -> 2025-380 | E25: involves the procurement of
A26: =PR!B111 -> printing of the Production Guide on Native pig raising, titled " Bagu Ivatan; Gabay s pagaalaga ng Native na baboy" (charged to Futures Thinking Fund)
A27: with the Approved Budget of | D27: =PR!H110 -> 81000
A28: WHEREAS, the default mode of evaluation shall be on a lot basis which means that the
A29: determination of the single/lowest calculated and responsive bid (S/LCRB) is the total amount of offered
A30: unit price multiply by the required quantity;
A32: NOW THEREFORE, I, DR.DJOVI R. DURANTE, Director for Admin & Finance Services by virtue of
A33: the authority vested in me by the Board of Trustees of this Institution and after taking into consideration
A34: the merits and legal bases of the recommendation of the members of the Bids and Awards Committee (BAC)
A35: do hereby APPROVE the foregoing recommendation and adoption of Negotiated Mode of Procurement
A36: under Emergency Case;
A38: APPROVED FINALLY, at the Batanes State College, this | F38: ___________________
B41: DJOVI REGALA DURANTE,DPA
B42: SUC President I
A47: BRYAN H. CIELO
A48: DELMA G. MALUPA-ABAD
A49: EDWIN F.MACABALLUG, Ph.D.
A50: LIEZL P. DELA CRUZ
A51: RODERICK Y. ABAD
A52: VILMA D. BACCAY
A53: ESTEBAN C. BADAJOS
A54: LEOBERT L. BANZALI
A55: MIAH DAPHNIE B. BUENAFE
A56: GLORIA N. CABIZON
A57: FORTUNATO PHILIP A. CABUGAO
A58: RICARDO Q. CABUGAO, JR.
... A103: EMILYN D. ALUETA

Sheet ResoSVP -Emergency
A4: BAC Resolution Recommending Emergency Procurement of the Project: Supply and Installation of 50KVA Transformer
B6: BAC Resolution No. | D6: =PR!B12 -> 2510-1005-380
A8: WHEREAS, Section 53 Rule XVI of the Revised Implementing Rules and Regulations of RA 9184
A9: allows Negotiated Mode of Procurement subject to prior approval of the HOPE thru Annual
A10: Procurement Plan (APP) and only to promote economy and efficiency;
A12: WHEREAS, Section 53.2 allows Emergency Cases in case of imminent danger to life or property
A13: during state of calamity, or when time is of the essence arising from natural or man-made calamities or other
A14: causes where immediate action is necessary to prevent damage to or loss of life or property, or to
A15: restore vital public services, infrastructure facilities and other public utilities;
A17: WHEREAS, "Annex H" of the Consolidated Guidelines for Emergency Cases prescribed under
A18: Section V, Paragraph D.2.b.,upon submission of request and other supporting documents identifying
A19: the emergency sought to be addressed, the BAC shall prepare the appropriate procurement
A20: documents and directly negotiate with a supplier, contractor, or consultant with technical, legal and
A21: financial capability to deliver the goods, execute the works and perform the services to address the emergency;
... A24: the HOPE, upon the recommendation of the BAC, shall immediately award the contract to the Supplier, Contractor or Consultant;
A25: WHEREAS, Purchase Request No. | D25: =PR!E9 -> 2025-380 | E25: involves the procurement of
A26: =PR!B111 -> printing of the Production Guide on Native pig raising, titled " Bagu Ivatan; Gabay s pagaalaga ng Native na baboy" (charged to Futures Thinking Fund)
A27: with the Approved Budget of | D27: =PR!H110 -> 81000
A28: WHEREAS, the default mode of evaluation shall be on a lot basis which means that the
A29: determination of the single/lowest calculated and responsive bid (S/LCRB) is the total amount of offered
A30: unit price multiply by the required quantity;
A32: NOW THEREFORE, we, the members of the Bids and Awards Committee hereby RESOLVE to recommend to the HOPE to adopt Negotiated Mode of Procurement under Emergency Cases for the said transaction;
A33: RESOLVED FINALLY, at the Batanes State College, this
A34: Recommending Approval:
A37: RHOUPHELINE AYA A. CADIZ | C37: RANDALL G. CASTILLO | E37: EMILYN D. ALUETA
A38: BAC Member | C38: BAC Member | E38: BAC Member
A41: =PR!B115 -> JANE S. CASTILLO | C41: FORTUNATO PHILIP A. CABUGAO | E41: DOREEN C. CASTILLO
A42: End-User/Provisional Member | C42: BAC Vice Chairperson | E42: BAC Chairperson
A47: BRYAN H. CIELO
A48: DELMA G. MALUPA-ABAD
A49: EDWIN F.MACABALLUG, Ph.D.
A50: LIEZL P. DELA CRUZ
A51: RODERICK Y. ABAD
A52: VILMA D. BACCAY
A53: ESTEBAN C. BADAJOS
A54: LEOBERT L. BANZALI
A55: MIAH DAPHNIE B. BUENAFE
A56: GLORIA N. CABIZON
A57: FORTUNATO PHILIP A. CABUGAO
A58: RICARDO Q. CABUGAO, JR.
... A103: EMILYN D. ALUETA

Sheet ResoSoSVP(Direct Contracting)
A4: BAC Resolution Recommending Alternative Mode of Procurement under Direct Contracting for the Blank TOR Paper
B6: BAC Resolution No. | D6: =PR!B12 -> 2510-1005-380
A8: WHEREAS, Rule XVI of the Revised Implementing Rules and Regulations of RA 9184
A9: allows Alternative Mode of Procurement subject to prior approval of the HOPE thru Annual
A10: Procurement Plan (APP) and only to promote economy and efficiency;
A12: WHEREAS, Section 50(c) allows Direct Contracting in cases where Procuring Entity intends to procure
A13: goods form an exclusive local manufacturer, supplier, distributor, or dealer for which no suitable
A14: substitute can be obtained at more advantageous terms to the GoP.
A16: WHEREAS, "Annex H" of the Consolidated Guidelines for Direct Contracting prescribed under
A17: Section V, Paragraph A.2.,upon submission of request and other supporting documents
A18: the BAC shall prepare the RFQ or pro-forma invoice together with the term and conditions of sale,
A19: and shall send the same to the identified direct supplier.
A20: WHEREAS, the BAC shall ensure that the supplier is technically, legally and financially capable
A21: to deliver the goods at the most advantageous price and contract for the Government
... A24: contract to the Supplier, Contractor or dealer.
A25: WHEREAS, Purchase Request No. | D25: =PR!E9 -> 2025-380 | E25: involves the procurement of
A26: =PR!B111 -> printing of the Production Guide on Native pig raising, titled " Bagu Ivatan; Gabay s pagaalaga ng Native na baboy" (charged to Futures Thinking Fund)
A27: with the Approved Budget of | D27: =PR!H110 -> 81000
A28: WHEREAS, the default mode of evaluation shall be on a lot basis which means that the
A29: determination of the single/lowest calculated and responsive bid (S/LCRB) is the total amount of offered
A30: unit price multiply by the required quantity;
A32: NOW THEREFORE, we, the members of the Bids and Awards Committee hereby RESOLVE to recommend to the HOPE to adopt Negotiated Mode of Procurement under Direct Contracting for the said transaction;
A33: RESOLVED FINALLY, at the Batanes State College, this
A34: Recommending Approval:
A37: RHOUPHELINE AYA A. CADIZ | C37: RANDALL G. CASTILLO | E37: EMILYN D. ALUETA
A38: BAC Member | C38: BAC Member | E38: BAC Member
A41: =PR!B115 -> JANE S. CASTILLO | C41: FORTUNATO PHILIP A. CABUGAO | E41: DOREEN C. CASTILLO
A42: End-User/Provisional Member | C42: BAC Vice Chairperson | E42: BAC Chairperson
A47: BRYAN H. CIELO
A48: DELMA G. MALUPA-ABAD
A49: EDWIN F.MACABALLUG, Ph.D.
A50: LIEZL P. DELA CRUZ
A51: RODERICK Y. ABAD
A52: VILMA D. BACCAY
A53: ESTEBAN C. BADAJOS
A54: LEOBERT L. BANZALI
A55: MIAH DAPHNIE B. BUENAFE
A56: GLORIA N. CABIZON
A57: FORTUNATO PHILIP A. CABUGAO
A58: RICARDO Q. CABUGAO, JR.
... A103: EMILYN D. ALUETA

Sheet AResoSoSVP(Direct Contractin (2
A4: Approval of BAC Resolution Recommending Alternative Mode of Procurement under Direct Contracting of the Project: Additional 2GB RAM for the College Website
B6: BAC Resolution No. | D6: =PR!B12 -> 2510-1005-380
A8: WHEREAS, Rule XVI of the Revised Implementing Rules and Regulations of RA 9184
A9: allows Alternative Mode of Procurement subject to prior approval of the HOPE thru Annual
A10: Procurement Plan (APP) and only to promote economy and efficiency;
A12: WHEREAS, Section 50(c) allows Direct Contracting in cases where Procuring Entity intends to procure
A13: goods form an exclusive local manufacturer, supplier, distributor, or dealer for which no suitable
A14: substitute can be obtained at more advantageous terms to the GoP.
A16: WHEREAS, "Annex H" of the Consolidated Guidelines for Direct Contracting prescribed under
A17: Section V, Paragraph A.2.,upon submission of request and other supporting documents
A18: the BAC shall prepare the RFQ or pro-forma invoice together with the term and conditions of sale,
A19: and shall send the same to the identified direct supplier.
A20: WHEREAS, the BAC shall ensure that the supplier is technically, legally and financially capable
A21: to deliver the goods at the most advantageous price and contract for the Government
... A24: contract to the Supplier, Contractor or dealer.
A25: WHEREAS, Purchase Request No. | D25: =PR!E9 -> 2025-380 | E25: involves the procurement of
A26: subscription expenses for the Additional 2GB RAM for the College Website (bscbatanes.edu.ph)
A27: with the Approved Budget of | D27: =PR!H110 -> 81000
A28: WHEREAS, the default mode of evaluation shall be on a lot basis which means that the
A29: determination of the single/lowest calculated and responsive bid (S/LCRB) is the total amount of offered
A30: unit price multiply by the required quantity;
A32: NOW THEREFORE, I, DR.DJOVI R. DURANTE, Head of the Procuring Entity (HOPE) by virtue of
A33: the authority vested in me by the Board of Trustees of this Institution and after taking into consideration
A34: the merits and legal bases of the recommendation of the members of the Bids and Awards Committee (BAC)
A35: do hereby APPROVE the foregoing recommendation and adoption of Alternative Mode of Procurement
A36: under Direct Contracting;
A38: APPROVED FINALLY, at the Batanes State College, this | F38: ___________________
B41: DJOVI REGALA DURANTE,DPA
B42: SUC President I
A47: BRYAN H. CIELO
A48: DELMA G. MALUPA-ABAD
A49: EDWIN F.MACABALLUG, Ph.D.
A50: LIEZL P. DELA CRUZ
A51: RODERICK Y. ABAD
A52: VILMA D. BACCAY
A53: ESTEBAN C. BADAJOS
A54: LEOBERT L. BANZALI
A55: MIAH DAPHNIE B. BUENAFE
A56: GLORIA N. CABIZON
A57: FORTUNATO PHILIP A. CABUGAO
A58: RICARDO Q. CABUGAO, JR.
... A103: EMILYN D. ALUETA

Sheet Reso-Repeat Order
A5: BAC Resolution Recommending Alternative Mode of Procurement under Small Value Procurement
B7: BAC Resolution No. | D7: =#REF! -> #REF!
A9: WHEREAS, Section 48 Rule XVI of the Revised Implementing Rules and Regulations of RA 9184 allows Alternative Mode of Procurement subject to prior approval of the HOPE thru Annual Procurement Plan (APP) and only to promote economy and efficiency;
A10: WHEREAS, Section 53.9 allows Small Value Procurement provided that the procurement does not fall under shopping in Section 52 of this IRR and the amount involved does not exceed the thresholds prescribed in Annex "H" of this IRR;
A11: WHEREAS, Rule XVI, Section 51., on Repeat Order states this when provided for in the APP, is a method of procurement of goods from the previous winning bidder, whenever there is a need to replenish goods procured under a contract previously awarded through competitive bidding. | H11: c
A12: WHEREAS, Rule XVI, Section 51.,a) A repeat order provides that unit prices of the repeat order must be the same as or lower than those in the original contract: provided, that such prices are still the most advantegous to the GoP after price verification: b) thet the repeat order will not result in splitting of contracts, requisitions, or purchase orders, as provided for in Section 54.1 of this IRR;
A13: WHEREAS, Purchase Request No. | D13: =#REF! -> #REF! | E13: involves the procurement of
A14: =#REF! -> #REF!
A15: =#REF! -> #REF! | D15: =#REF! -> #REF!
A16: WHEREAS, the default mode of evaluation shall be on a lot basis which means that the determination of the single/lowest calculated and responsive bid (S/LCRB) is the total amount of offered unit price multiply by the required quantity;
A18: NOW THEREFORE, we, the members of the Bids and Awards Committee hereby RESOLVE as it is hereby RESOLVED to recommend to the College President to adopt Alternative Mode of Procurement under Small Value Procurement for the said transaction;
A20: RESOLVED FINALLY, at the Batanes State College, this
A21: Recommending Approval:
A24: RHOUPHELINE AYA A. CADIZ | C24: RANDALL G. CASTILLO | E24: EMILYN D. ALUETA
A25: BAC Member | C25: BAC Member | E25: BAC Member
A28: =PR!B115 -> JANE S. CASTILLO | C28: FORTUNATO PHILIP A. CABUGAO | E28: DOREEN C. CASTILLO
A29: End-User/Provisional Member | C29: BAC Vice Chairperson | E29: BAC Chairperson
A30: BRYAN H. CIELO
A31: DELMA G. MALUPA-ABAD
A32: EDWIN F.MACABALLUG, Ph.D.
A33: LIEZL P. DELA CRUZ
A34: RODERICK Y. ABAD
A35: VILMA D. BACCAY
A36: ESTEBAN C. BADAJOS
A37: LEOBERT L. BANZALI
A38: MIAH DAPHNIE B. BUENAFE
A39: GLORIA N. CABIZON
A40: FORTUNATO PHILIP A. CABUGAO
A41: RICARDO Q. CABUGAO, JR.
... A83: LEONARDO CABRERA

Sheet AReso-Repeat Order
A4: Approval of BAC Resolution Recommending Alternative Mode of Procurement under Small Value Procurement
B6: BAC Resolution No. | D6: =PR!B12 -> 2510-1005-380
A8: WHEREAS, Section 48 Rule XVI of the Revised Implementing Rules and Regulations of RA 9184 allows Alternative Mode of Procurement subject to prior approval of the HOPE thru Annual Procurement Plan (APP) and only to promote economy and efficiency;
A9: WHEREAS, Section 53.9 allows Small Value Procurement provided that the procurement does not fall under shopping in Section 52 of this IRR and the amount involved does not exceed the thresholds prescribed in Annex "H" of this IRR;
A10: WHEREAS, Appendix 18, Section 3.e on the Guidelines for Shopping and Small Value Procurement provides an Abstract of Quotations shall be prepared setting forth the names of those who responded to the RFQ's right after the deadline for submission except for shopping under Section 52.1(b), where at least three (3) price quotations (RFQ) must be obtained;
A11: WHEREAS, Annex "H" of the Consolidated Guidelines for the Alternative Methods of Procurement prescribed under Section V, Paragraph D.8.b.ii that the BAC shall prepare and send the RFQs/RFPs to at least three (3) suppliers, contractors or consultants of known qualifications where receipt of at least one (1) quotations is sufficient to proceed with the evaluation thererof;
A12: WHEREAS, Purchase Request No. | D12: =PR!E9 -> 2025-380 | E12: involves the procurement of
A13: Presidential Medallion | H13: Items:
A14: with the Approved Budget of | D14: =PR!H110 -> 81000
A15: WHEREAS, the default mode of evaluation shall be on a lot basis which means that the determination of the single/lowest calculated and responsive bid (S/LCRB) is the total amount of offered unit price multiply by the required quantity;
A16: NOW THEREFORE, I,DR.DJOVI R. DURANTE, Head of the Procuring Entity (HOPE) by virtue of the authority vested in me by the Board of Trustees of this Institution and after taking into consideration the merits and legal bases of the recommendation of the members of the Bids and Awards Committee (BAC) do hereby APPROVE the foregoing recommendation and adoption of Alternative Mode of Procurement under Small Value Procurement;
A18: APPROVED FINALLY, at the Batanes State College, this | F18: ___________________
B24: DJOVI REGALA DURANTE,DPA
B25: SUC President I
A30: BRYAN H. CIELO
A31: DELMA G. MALUPA-ABAD
A32: EDWIN F.MACABALLUG, Ph.D.
A33: LIEZL P. DELA CRUZ
A34: RODERICK Y. ABAD
A35: VILMA D. BACCAY
A36: ESTEBAN C. BADAJOS
A37: LEOBERT L. BANZALI
A38: MIAH DAPHNIE B. BUENAFE
A39: GLORIA N. CABIZON
A40: FORTUNATO PHILIP A. CABUGAO
A41: RICARDO Q. CABUGAO, JR.
... A86: EMILYN D. ALUETA

Sheet ARE-Direct Contracting
A6: Approval of BAC Resolution Recommending Alternative Mode of Procurement under Direct Contracting of the Project: Additional 2GB RAM for the College Website
B7: BAC Resolution No. | D7: 2024-1004C-0064
A9: WHEREAS, Section 48 Rule XVI of the Revised Implementing Rules and Regulations of RA 9184 allows Alternative Mode of Procurement subject to prior approval of the HOPE thru Annual Procurement Plan (APP) and only to promote economy and efficiency;
A10: WHEREAS, Section 50© allows Direct Contracting in cases where procuring Entity intends to procure goods from an exclusive local manufacturer,supplier,distributor or dealer for which no suitable substitute can be obtain at more advantegeous terms to the GoP.
A11: WHEREAS, "Annex H" of the Consolidated Guidelines for Direct Contracting prescribed under Section V, Paragraph A.2.,upon submission of request and other supporting documents,the BAC shall prepare the RFQ or pro-forma invoice together with the term and conditions of sale,and shall send the same to the identified direct supplier.
A12: WHEREAS, the BAC shall ensure that the supplier is technically, legally and financially capable to deliver th goods at the most advantageous price and contract for the Government
A13: WHEREAS, upon confirmation and ascertainment of such capability of the supplier,the HOPE, upon the recommendation of the BAC, shall immediately award the contract to the supplier,contractor or dealer.
A14: WHEREAS, Purchase Request No. | D14: 2024-0064 | E14: involves the procurement of
A15: subscription expenses for the Additional 2GB RAM for the College Website (bscbatanes.edu.ph) | H15: Items:
A16: with the approved budget of | D16: 5100
A17: WHEREAS, the default mode of evaluation shall be on a lot basis which means that the determination of the single/lowest calculated and responsive bid (S/LCRB) is the total amount of offered unit price multiply by the required quantity;
A18: NOW THEREFORE, I,ENGR. ALFONSO R. SIMON, Head of the Procuring Entity (HOPE) by virtue of the authority vested in me by the Board of Trustees of this Institution and after taking into consideration the merits and legal bases of the recommendation of the members of the Bids and Awards Committee (BAC) do hereby APPROVE the foregoing recommendation and adoption of Alternative Mode of Procurement under Small Value Procurement;
A20: APPROVED FINALLY, at the Batanes State College, this | F20: ___________________
B26: DJOVI REGALA DURANTE
B27: SUC President I
A32: BRYAN H. CIELO
A33: DELMA G. MALUPA-ABAD
A34: EDWIN F.MACABALLUG, Ph.D.
A35: LIEZL P. DELA CRUZ
A36: RODERICK Y. ABAD
A37: VILMA D. BACCAY
A38: ESTEBAN C. BADAJOS
A39: LEOBERT L. BANZALI
A40: MIAH DAPHNIE B. BUENAFE
A41: GLORIA N. CABIZON
A42: FORTUNATO PHILIP A. CABUGAO
A43: RICARDO Q. CABUGAO, JR.
... A88: EMILYN D. ALUETA

Sheet ARE-Reso Direct Contracting (2)
A6: BAC Resolution Recommending Alternative Mode of Procurement under Direct Contracting of the Project: Additional 2GB RAM for the College Website
B7: BAC Resolution No. | D7: =PR!B12 -> 2510-1005-380
A9: WHEREAS, Section 48 Rule XVI of the Revised Implementing Rules and Regulations of RA 9184 allows Alternative Mode of Procurement subject to prior approval of the HOPE thru Annual Procurement Plan (APP) and only to promote economy and efficiency;
A10: WHEREAS, Section 50© allows Direct Contracting in cases where procuring Entity intends to procure goods from an exclusive local manufacturer,supplier,distributor or dealer for which no suitable substitute can be obtain at more advantegeous terms to the GoP.
A11: WHEREAS, "Annex H" of the Consolidated Guidelines for Direct Contracting prescribed under Section V, Paragraph A.2.,upon submission of request and other supporting documents,the BAC shall prepare the RFQ or pro-forma invoice together with the term and conditions of sale,and shall send the same to the identified direct supplier.
A12: WHEREAS, the BAC shall ensure that the supplier is technically, legally and financially capable to deliver th goods at the most advantageous price and contract for the Government
A13: WHEREAS, upon confirmation and ascertainment of such capability of the supplier,the HOPE, upon the recommendation of the BAC, shall immediately award the contract to the supplier,contractor or dealer.
A14: WHEREAS, Purchase Request No. | D14: =PR!E9 -> 2025-380 | E14: involves the procurement of
A15: subscription expenses for the Additional 2GB RAM for the College Website (bscbatanes.edu.ph) | H15: Items:
A16: with the approved budget of | D16: =PR!H110 -> 81000
A17: WHEREAS, the default mode of evaluation shall be on a lot basis which means that the determination of the single/lowest calculated and responsive bid (S/LCRB) is the total amount of offered unit price multiply by the required quantity;
A18: NOW THEREFORE, we the members of the Bids and Awards Committee hereby RESOLVE to recommend to the HOPE to adopt Alternative Mode of Procurement under Direct Contracting:
A20: RESOLVED FINALLY, at the Batanes State College, this | F20: ___________________
A24: Recommending Approval:
A26: RHOUPHELINE AYA A. CADIZ | C26: RANDALL G. CASTILLO | F26: EMILY D. ALUETA
A27: BAC Member | C27: BAC Member | F27: BAC Member
A32: BRYAN H. CIELO
A33: DELMA G. MALUPA-ABAD
A34: EDWIN F.MACABALLUG, Ph.D.
A35: LIEZL P. DELA CRUZ
A36: RODERICK Y. ABAD
A37: VILMA D. BACCAY
A38: ESTEBAN C. BADAJOS
A39: LEOBERT L. BANZALI
A40: MIAH DAPHNIE B. BUENAFE
A41: GLORIA N. CABIZON
A42: FORTUNATO PHILIP A. CABUGAO
A43: RICARDO Q. CABUGAO, JR.
... A87: EMILYN D. ALUETA
A89: MARVIN KEITH C. ALAVADO | C89: FORTUNATO PHILIP A. CABUGAO | F89: DOREEN C. CASTILLO
A90: End-user/Provisional Member | C90: BAC Vice Chairperson | F90: BAC Chairperson

Sheet BAC RESO for Award Direct Contr
M2: Republic of the Philippines
N3: BATANES STATE COLLEGE
N4: Washington Avenue, San Antonio, Basco, Batanes
N5: : www.bscbatanes.edu.ph * bscpprocurement.unit@gmail.com '09507848658
E6: OFFICE OF THE BIDS AND AWARDS COMMITTEE | N6: OFFICE OF THE BIDS AND AWARDS COMMITTEE
E7: bac resolution No: | M7: =E7 -> bac resolution No:
D8: =PR!B12 -> 2510-1005-380 | M8: =D8 -> 2510-1005-380
E10: BAC RESOLUTION RECOMMENDING FOR AWARD | N10: APPROVAL OF THE BAC RECOMMENDATION FOR AWARD
A12: WHEREAS, Section 48 Rule XVI of the Revised Implementing Rules and Regulations of RA 9184 allows Alternative Mode of Procurement subject to prior approval of the HOPE thru Annual Procurement Plan (APP) and only to promote economy and efficiency; | J12: WHEREAS, Section 48 Rule XVI of the Revised Implementing Rules and Regulations of RA 9184 allows Alternative Mode of Procurement subject to prior approval of the HOPE thru Annual Procurement Plan (APP) and only to promote economy and efficiency;
A15: WHEREAS, Section 50© allows Direct Contracting in cases where procuring Entity intends to procure goods from an exclusive local manufacturer,supplier,distributor or dealer for which no suitable substitute can be obtain at more advantegeous terms to the GoP. | J15: WHEREAS, Section 50© allows Direct Contracting in cases where procuring Entity intends to procure goods from an exclusive local manufacturer,supplier,distributor or dealer for which no suitable substitute can be obtain at more advantegeous terms to the GoP.
A18: WHEREAS, the Price Quotation of the sole bidder was opened and its bid price was read as follows: | J18: WHEREAS, the Price Quotation of the sole bidder was opened and its bid price was read as follows:
A21: ITEM NO. | B21: BIDDER WITH CALCULATED BID | G21: ABC | I21: BID AMOUNT | J21: ITEM NO. | K21: BIDDER WITH CALCULATED BID | P21: ABC | R21: BID AMOUNT
A22: 1 | B22: =DATA!W393 -> 0 | G22: =PR!H110 -> 81000 | I22: 30000 | J22: 1 | K22: =B22 -> 0 | P22: =G22 -> 81000 | R22: =I22 -> 30000
A23: 2 | J23: 2 | K23: =B23 -> 0 | P23: =G23 -> 0 | R23: =I23 -> 0
A24: 3 | J24: 3 | K24: =B24 -> 0 | P24: =G24 -> 0 | R24: =I24 -> 0
A25: 4 | J25: 4 | K25: =B25 -> 0 | P25: =G25 -> 0 | R25: =I25 -> 0
A26: 5 | J26: 5 | K26: =B26 -> 0 | P26: =G26 -> 0 | R26: =I26 -> 0
A27: 6 | J27: 6 | K27: =B27 -> 0 | P27: =G27 -> 0 | R27: =I27 -> 0
A28: 7 | J28: 7 | K28: =B28 -> 0 | P28: =G28 -> 0 | R28: =I28 -> 0
A29: 8 | G29: 19350 | J29: 8 | K29: =B29 -> 0 | P29: =G29 -> 19350 | R29: =I29 -> 0
J30: NOW THEREFORE, I DJOVI R. DURANTE,DPA by virtue of the authority vested in me of this institution and after taking into consideration the merits and legal bases of the recommendation of the members of the Bids and Awards Committee (BAC) do hereby APPROVE the following;
B32: 1. To declare Bitstop Network Services, Inc. as the sole supplier for Additional 2GB RAM for the College Website PR # 2410-1002B-436 dated October 2, 2024.
B35: 2. To recommend for approval by the Head of Procuring Entity of the Batanes State College the foregoing findings.
A36: RESOLVED FINALLY, at the BAC Office, Batanes State College, this _______day of . | J36: 1. To declare Bitstop Network Services, Inc. as the sole supplier for Additional 2GB RAM for the College Website PR # 2310-1002B-436.
A37: Recommending Approval:
A40: RHOUPHELINE AYA A. CADIZ | D40: EMILYN D. ALUETA | G40: RANDALL G. CASTILLO | J40: Done this ______ day of _________ 2024.
A41: BAC Member | D41: BAC Member | G41: BAC Member
L44: DJOVI REGALA DURANTE,DPA
A45: =PR!B115 -> JANE S. CASTILLO | F45: FORTUNATO PHILIP A. CABUGAO | L45: SUC President I
A46: End-user/Provisional Member | F46: Vice BAC Chairperson
D48: DOREEN C. CASTILLO
D49: BAC Chairperson

Sheet AckReceipt (2)
A1: Acknowledgement for Request for Quotation
A2: RIS# | B2: 2311-1016-498
A3: No. | B3: Supplier | F3: Received by: | G3: Date & Time:
B4: JPM Gen. Mdse. & Hardware
B5: Thine-line Trading
B6: J-Tech Trading & Services
B7: MDAC Trading & Compuserve
B8: FVA Gen Mdse & Construction Supply
B10: GDP Trading
B11: EA Amboy Gen Mdse
B12: L & R's Hontomin Gen Mdse
B13: Davocol's Gen. Mdse.
B14: RCJ Hardware & Gen Mdse
B15: Fitero's Gen Mdse & Electronic Supply
B16: Lar & San's Store
... B18: Wilmerson Gen Mdse
B19: FMG Trading & Construction Supply | C19: q
B20: MG Hubalde Gen Mdse
B21: Basco Cable TV Services, Inc.
B22: Berlen's Store
B23: Melad's Gen. Mdse
B24: R. A. Electronics
B25: RJ General Merchandise
B26: Batanes Multi-Purpose Cooperative, Inc.
B27: Romy & Ava's Store
B28: J-nell's Gen Mdse
B29: Impression Digital Printing Solutions
B30: Golden Press
B31: Tawsen's Agri-Venture & Souvenirs
... B60: Sophia Marie Store
A61: 1 | B61: Susan's Mini Mart
A62: 2 | B62: Sophia Marie Store
A63: 3 | B63: Apostol's General Merchandise
A64: 4
A65: 5
A66: 6
A67: 7
A68: NOTE: | B68: 1. MODE OF PRICE EVALUATION SHALL BE ON A LOT BASIS, OTHERWISE PER ITEMS EVALUATION SHALL BE USED IF THERE WILL BE LACKING ITEMS IN ALL RFQ'S AND THE END-USER AGREED, . (Clause 15.2, Section II, Instructions to Bidders of the Philippine Bidding Documents for goods and infrastructure projects)
B69: 2. DELIVERY PERIOD: Thirty (30) calendar days.
B70: 3. WARRANTY SHALL BE FOR A PERIOD OF SIX (6) MONTHS FOR SUPPLIES AND MATERIALS, ONE (1) YEAR FOR EQUIPMENT, FROM THE DATE OF ACCEPTANCE BY THE PROCURING ENTITY.
B71: 4. THE APPROVED BUDGET CEILING FOR THIS PROCUREMENT IS PHP (GPPB Resolution no. 09-2009)
B72: 71445
B73: 5. PRICE VALIDITY SHALL BE OR THE PERIOD OF 30 CALENDAR DAYS.
B74: 6. BIDDERS SHALL SUBMIT ORIGINAL BROCHURES SHOWING SPECIFICATIONS OF THE PRODUCT BEING OFFERED IF APPLICABLE.
A75: In compliance with GPPB Resolution No. 09-2009
B77: Retrieval of Request for Quotation
A79: No. | B79: Supplier | F79: Released by: | G79: Date & Time: | N79: k
A80: 1 | B80: Susan's Mini Mart
A81: 2 | B81: Sophia Marie Store
A82: 3 | B82: Apostol's General Merchandise
A83: 4
A84: 5
A85: 6
A86: 7
