Workbook

Sheet PMR-Data
A2: MONTH | B2: (Multiple Items)
A3: YEAR | B3: (Multiple Items)
A5: PR# | B5: Purpose | C5: End-User | D5: Modality | E5: Delivery Date | F5: IAR Date | G5: Fund Code | H5: Class | I5: Status | J5: Sum of Estimated Total | K5: Sum of Total
A6: 202-013A | B6: supplies for the repair & maintenance of the building | C6: JERSHON RALPH F. CASTANO | D6: SVP | E6: August 23, 2021 | F6: August 23, 2021 | G6: 101 | H6: MOOE | I6: complete | J6: 85520 | K6: 65665
A7: 2021-001A | B7: snacks for the "Internal Quality Audit" on January 19-21, 2021 | J7: 17850 | K7: 17850
A8: 2021-002 | B8: Supply and installation of CCTV for Academic Building, Dormitory and Agriculture Building | C8: ALETH A. MEORA | D8: SVP | E8: April 27, 2021 | F8: May 26, 2021` | G8: 101 | H8: CO | I8: complete | J8: 435000 | K8: 397860
A9: 2021-002A | B9: to be used in the different activities and internet communication needs of BSC | C9: RANDALL G. CASTILLO | D9: SVP | E9: 5/19 & 7/19/2021 | F9: 5/26 & 7/21/2021 | G9: 101 | H9: (blank) | I9: complete | J9: 25500 | K9: 25480
A10: 2021-003 | B10: Purchase of Academic Equipment | C10: ALETH A. MEORA | D10: SVP | E10: 5/19 & 7/19/2021 | F10: 5/19 & 7/21/2021 | G10: 101 | H10: CO | I10: complete | J10: 947218.62 | K10: 928620
A11: 2021-003A | B11: for PBB compliance specifically transparency seal and BSC publication | C11: RANDALL G. CASTILLO | D11: SVP | E11: February 16, 2021 | F11: March 2, 2021 | G11: 165 | H11: MOOE | I11: complete | J11: 49000 | K11: 45560
A12: 2021-004 | B12: for the purchase of Academic Equipments | C12: ALETH A. MEORA | D12: SVP | E12: January 12, 2021 | F12: April 27, 2021 | G12: 101 | H12: CO | I12: complete | J12: 972105.5 | K12: 791000
A13: 2021-004A | B13: for the purchase of enrollment forms | C13: RHEA ANGELLICA B. ADDATU | D13: SVP | E13: August 23, 2021 | F13: August 23, 2021 | G13: 101 | H13: (blank) | I13: (blank) | J13: 22500 | K13: 22500
A14: 2021-005 | B14: Purchase of Academic Equipment | C14: ALETH A. MEORA | D14: SVP | E14: 44396 | F14: 44403 | G14: 101 | H14: CO | I14: reimbursement | J14: 378961.7 | K14: 359780
A15: 2021-005A | B15: to be used in the different activities and internet communication needs of BSC | C15: RANDALL G. CASTILLO | D15: SVP | E15: May 19, 2021 | F15: May 26, 2021 | G15: 101 | H15: MOOE | I15: complete | J15: 30250 | K15: 29960
A16: 2021-006 | B16: Supply and Delivery of Academic Equipment | C16: ALETH A. MEORA | D16: SVP | E16: January 12, 2021 | F16: January 25, 2021 | G16: 101 | H16: CO | I16: complete | J16: 315813.75 | K16: 195700
E17: January 25, 2021 | F17: January 25, 2021 | G17: 101 | H17: CO | I17: complete | J17: 45000 | K17: 42000
A18: 2021-006A | B18: for the ISO Activity Management Review on Feb. 3, 2021 | C18: ROMINA KATRINA C. BAYARAS | D18: SVP | E18: 44230 | F18: February 16, 2021 | G18: 164 | H18: MOOE | I18: complete | J18: 14000 | K18: 11800
A19: 2021-007A | B19: Internet data/Regular load Allocation of Administrative & Finance staff of the college to support online submission of reports & other related activities for the Fiscal Year 2021 | C19: DJOVI R. DURANTE | D19: SVP | E19: March 29, 2021 | F19: March 31, 2021 | G19: 101 | H19: MOOE | I19: complete | J19: 107880 | K19: 107880
A20: 2021-008A | B20: for the "ISO Documentation" | C20: ROMINA KATRINA C. BAYARAS | D20: SVP | E20: March 15, 2021 | F20: March 15, 2021 | G20: 164 | H20: MOOE | I20: complete | J20: 3960 | K20: 3885
A21: 2021-009 | B21: Purchase of Academic Furniture Fixtures | C21: ALETH A. MEORA | D21: SVP | E21: August 23, 2021 | F21: August 23, 2021 | G21: 101 | H21: MOOE | I21: complete | J21: 200000 | K21: 199680
A22: 2021-009A | B22: stamp use for the filing of ISO documents | C22: ROMINA KATRINA C. BAYARAS | D22: SVP | E22: - | F22: - | G22: 165 | H22: (blank) | I22: FAILED | J22: 28000 | K22: 0
A23: 2021-0100 | B23: for the Implementation of "ADOPT through Varied R & D of Ivatan Endemic Resources" research project | C23: JANE S. CASTILLO | D23: SVP | E23: August 23, 2021 | F23: August 23, 2021 | G23: 165 | H23: MOOE | I23: for delivery | J23: 30950 | K23: 29315
A24: 2021-0101 | B24: office supplies for the Administrative & Finance Services Units | C24: DJOVI R. DURANTE | D24: SVP | E24: August 23, 2021 | F24: August 23, 2021 | G24: 165 | H24: MOOE | I24: for delivery | J24: 30840 | K24: 28941.9
A25: 2021-0102 | B25: supplies for Budget office | C25: BRYAN DAVE P. REVILLA | D25: SVP | E25: August 23, 2021 | F25: August 23, 2021 | G25: 101 | H25: MOOE | I25: for delivery | J25: 3500 | K25: 2990
A26: 2021-0103 | B26: supplies for Budget office | C26: BRYAN DAVE P. REVILLA | D26: SVP | E26: July 1, 2021 | F26: July 1, 2021 | G26: 101 | H26: MOOE | I26: complete | J26: 790 | K26: 600
A27: 2021-0104 | B27: supplies for the Budget office | C27: BRYAN DAVE P. REVILLA | D27: SVP | E27: August 23, 2021 | F27: August 23, 2021 | G27: 101 | H27: MOOE | I27: for delivery | J27: 1000 | K27: 800
A28: 2021-0105 | B28: repair of 2 units floor type airconditioner at Faculty Room | C28: JERSHON RALPH F. CASTANO | D28: SVP | E28: August 23, 2021 | F28: August 23, 2021 | G28: (blank) | H28: (blank) | I28: FAILED | J28: 13000
A29: 2021-0106 | B29: GSO Supplies | C29: JERSHON RALPH F. CASTANO | D29: SVP | E29: July 19 & 26, 2021 | F29: July 21 & 26, 2021 | G29: 101 | H29: MOOE | I29: complete | J29: 10950 | K29: 8314
A30: 2021-0107 | B30: GSO Supplies | C30: JERSHON RALPH F. CASTANO | D30: SVP | E30: 44399 | F30: 44411 | G30: 101 | H30: MOOE | I30: reimbursement | J30: 18500 | K30: 15780
A31: 2021-0108 | B31: Snack for the Preparatory Board Meeting on June 25, 2021 at 10:00 a.m | C31: GERZON R. ABAD | D31: SVP | E31: August 23, 2021 | F31: August 23, 2021 | G31: (blank) | H31: (blank) | I31: FAILED | J31: 3000 | K31: 0
A32: 2021-0109 | B32: PM snack and dinner for the 52nd Board of Trustees Meeting on June 25, 2021 | C32: GERZON R. ABAD | D32: SVP | E32: June 25, 2021 | F32: 44377 | G32: 101 | H32: MOOE | I32: reimbursement | J32: 13000 | K32: 9000
A33: 2021-010A | B33: ink use for enrollment | C33: RHEA ANGELLICA B. ADDATU | D33: SVP | E33: August 23, 2021 | F33: August 23, 2021 | G33: 101 | H33: (blank) | I33: FAILED | J33: 1500
A34: 2021-0110 | B34: Lunch, PM Snack and Dinner of Commissioner Lilian A. De Las Llagas and Staff for the 52nd BOT Meeting on 25 June 2021 | C34: GERZON R. ABAD | D34: SVP | E34: August 23, 2021 | F34: August 23, 2021 | G34: (blank) | H34: (blank) | I34: reimbursement | J34: 12597.5 | K34: 12597.5
A35: 2021-0111 | B35: repair & maintenance of A/C units of Registrar's, Cashier's, Accountant's & President's office | C35: JERSHON RALPH F. CASATANO | D35: SVP | E35: August 23, 2021 | F35: August 23, 2021 | G35: 101 | H35: MOOE | I35: on-going | J35: 8000 | K35: 8000
A36: 2021-0112 | B36: supplies for the rewiring of faculty room electrical system | C36: JERSHON RALPH F. CASATANO | D36: SVP | E36: July 21, 2021 | F36: July 26, 2021 | G36: 101 | H36: MOOE | I36: complete | J36: 23700 | K36: 21624
A37: 2021-0113 | B37: for the purchase of Semi-expendable equipments purposes | C37: JERSHON RALPH F. CASATANO | D37: SVP | E37: August 23, 2021 | F37: August 23, 2021 | G37: 101 | H37: MOOE | I37: on-going | J37: 10000 | K37: 10000
A38: 2021-011A | B38: for the Pre Assessment Audit Plan on Feb. 10-11, 2021 | C38: ROMINA KATRINA C. BAYARAS | D38: SVP | E38: February 10-11, 2021 | F38: March 2, 2021 | G38: 164 | H38: MOOE | I38: complete | J38: 7500 | K38: 7125
A39: 2021-012A | B39: supplies for the repair & maintenance of transportation vehicle | C39: JERSHON RALPH F. CASTANO | D39: SVP | E39: March 31, 2021 | F39: April 5, 2021 | G39: 101 | H39: MOOE | I39: on-going | J39: 49399.99 | K39: 42550
A40: 2021-013 | B40: Puchase of drafting tables and chairs for the Academiic Furnitures and Fixtures | C40: ALETH A. MEORA | D40: SVP | E40: January 26, 2021 | F40: January 26, 2021 | G40: 101 | H40: CO | I40: complete | J40: 277500 | K40: 195000
A41: 2021-014A | B41: office machinery & equipment | C41: JERSHON RALPH F. CASTANO | D41: SVP | E41: March 29, 2021 | F41: March 30, 2021 | G41: 101 | H41: MOOE | I41: complete | J41: 47002 | K41: 42500
A42: 2021-015A | B42: supplies for janitorial services | C42: JERSHON RALPH F. CASTANO | D42: SVP | E42: April 15, 2021 | F42: April 15, 2021 | G42: 101 | H42: MOOE | I42: complete | J42: 5000 | K42: 3000
E43: March 30, 2021 | F43: April 15, 2021 | G43: 101 | H43: MOOE | I43: complete | J43: 15000 | K43: 15200
A44: 2021-016A | B44: AM snacks for the meeting on the Assessment of the Conduct of Flexible Learning in the 1st Semester of SY 2020-2021 | C44: ANGELITA H. VARGAS | D44: SVP | E44: February 16, 2021 | F44: March 24, 2021 | G44: 101 | H44: MOOE | I44: complete | J44: 7950 | K44: 7950
A45: 2021-017A | B45: snacks & meals for the Administrative & Finance Conference on the finalization of FY 2021 targets and deliverables | C45: DJOVI R. DURANTE | D45: SVP | E45: February 23, 2021 | F45: March 1, 2021 | G45: 101 | H45: MOOE | I45: complete | J45: 19250 | K45: 16275
A46: 2021-018A | B46: snacks & dinner for the 51st Board meeting on Feb. 24, 2021 | C46: GERZON R. ABAD | D46: SVP | E46: February 24, 2021 | F46: March 9, 2021 | G46: 101 | H46: MOOE | I46: complete | J46: 10200 | K46: 8330
A47: 2021-019A | B47: use for National Women's Month Celebration | C47: JENNY S. ALINA | D47: SVP | E47: March 29, 2021 | F47: March 29, 2021 | G47: 101 | H47: MOOE | I47: complete | J47: 5320 | K47: 5320
A48: 2021-020 | B48: seed propagation for the Production of High Value Crop (HVC) Seess & Seedling in Batanes under the Bayanihan II project | C48: ROMEL A. RATERTA | D48: (blank) | E48: August 23, 2021 | F48: August 23, 2021 | G48: (blank) | H48: (blank) | I48: FAILED | J48: 259100 | K48: 0
A49: 2021-021 | B49: supplies for the National Women's Month Celebration | C49: JENNY S. ALINA | D49: SVP | E49: March 29, 2021 | F49: March 30, 2021 | G49: 101 | H49: MOOE | I49: complete | J49: 1170 | K49: 735
A50: 2021-022 | B50: supplies & materials for the installation of 3 units television | C50: JERSHON RALPH F. CASTANO | D50: (blank) | E50: August 23, 2021 | F50: August 23, 2021 | G50: (blank) | H50: (blank) | I50: FAILED | J50: 4500 | K50: 0
A51: 2021-023 | B51: supplies & materials for the connection of 3 units television | C51: JERSHON RALPH F. CASTANO | D51: (blank) | E51: August 23, 2021 | F51: August 23, 2021 | G51: (blank) | H51: (blank) | I51: FAILED | J51: 5200 | K51: 0
A52: 2021-024 | B52: stamp use for the filing of ISO documents | C52: ROMINA KATRINA C. BAYARAS | D52: SVP | E52: May 7, 2021 | F52: May 19, 2021 | G52: 164 | H52: MOOE | I52: complete | J52: 40000 | K52: 40000
A53: 2021-025 | B53: stamp to be used in the office of the President & Office of the Board Sec | C53: GERZON R. ABAD | D53: SVP | E53: June 2, 2021 | F53: June 10, 2021 | G53: 101 | H53: (blank) | I53: complete | J53: 8000 | K53: 8000
A54: 2021-026 | B54: snacks & lunch for the "Records Management System Echo Seminar on March 23, 2021 | C54: ROMINA KATRINA C. BAYARAS | D54: SVP | E54: April 8, 2021 | F54: April 12, 2021 | G54: 101 | H54: MOOE | I54: complete | J54: 17500 | K54: 14750
A55: 2021-027 | B55: meals & snacks for the FY 2022 Budget Review & Consultation on March 16, 2021 | C55: BRYAN DAVE P. REVILLA | D55: SVP | E55: March 16, 2021 | F55: March 26, 2021 | G55: 101 | H55: MOOE | I55: complete | J55: 7700 | K55: 6930
A56: 2021-028 | B56: for preventive maintenance of BSC ICT Equipment | C56: RANDALL G. CASTILLO | D56: (blank) | E56: August 23, 2021 | F56: August 23, 2021 | G56: (blank) | H56: (blank) | I56: FAILED | J56: 42000 | K56: 0
A57: 2021-029 | B57: for preventive maintenance of BSC ICT Equipment | C57: RANDALL G. CASTILLO | D57: (blank) | E57: August 23, 2021 | F57: August 23, 2021 | G57: (blank) | H57: (blank) | I57: pending | J57: 48250 | K57: 0
A58: 2021-030 | B58: Snacks during the National Women's Month Celebration | C58: JENNY S. ALINA | D58: SVP | E58: March 25, 2021 | F58: May 4, 2021 | G58: 101 | H58: MOOE | I58: complete | J58: 11100 | K58: 10730
A59: 2021-031 | B59: for National Womens Month Celebration activity | C59: JENNY S. ALINA | D59: (blank) | E59: August 23, 2021 | F59: August 23, 2021 | G59: (blank) | H59: (blank) | I59: (blank) | J59: 12750 | K59: 12750
A60: 2021-032 | B60: Snacks and lunch during the Administrative Council meeting on March 31, 2021 | C60: GERZON R. ABAD | D60: SVP | E60: March 31, 2021 | F60: March 31, 2021 | G60: 101 | H60: MOOE | I60: complete | J60: 18200 | K60: 17500
A61: 2021-033 | B61: Snacks and Lunch during the Academic Council meeting on March 30, 2021 | C61: GERZON R. ABAD | D61: SVP | E61: March 30, 2021 | F61: March 30, 2021 | G61: 101 | H61: MOOE | I61: complete | J61: 24700 | K61: 23750
A62: 2021-034 | B62: seed propagation for the Production of High Value Crop (HVC) Seess & Seedling in Batanes under the Bayanihan II project | C62: ROMEL A. RATERTA | D62: SVP | E62: May 31, 2021 | F62: June 10, 2021 | G62: 165 | H62: MOOE | I62: complete | J62: 60000 | K62: 61200
E63: August 23, 2021 | F63: June 10, 2021 | G63: 165 | H63: MOOE | I63: complete | J63: 529100 | K63: 467600
A64: 2021-035 | B64: for the purchase of Semi-Expendable Office Supply purposes | C64: ALETH A. MEORA | D64: (blank) | E64: August 23, 2021 | F64: August 23, 2021 | G64: (blank) | H64: (blank) | I64: FAILED | J64: 55200 | K64: 0
A65: 2021-036 | B65: For the purchase of office equipment | C65: ALETH A. MEORA | D65: (blank) | E65: May 31, 2021 | F65: June 1, 2021 | G65: 101 | H65: (blank) | I65: complete | J65: 85000 | K65: 56025
G66: (blank) | H66: (blank) | I66: complete | J66: 70000 | K66: 43425
A67: 2021-037 | B67: For the purchase of office equipment | C67: ALETH A. MEORA | D67: SVP | E67: June 30, 2021 | F67: July 1, 2021 | G67: 101 | H67: CO | I67: complete | J67: 319140 | K67: 279976.5
A68: 2021-038 | B68: For the purchase of semi-expendable equipment | C68: ALETH A. MEORA | D68: SVP | E68: June 10, 2021 | F68: June 11, 2021 | G68: 101 | H68: MOOE | I68: complete | J68: 637300 | K68: 633015
A69: 2021-039 | B69: for the purchase of Academic furnitures & fixtures purposes | C69: ALETH A. MEORA | D69: Public Bidding | E69: August 23, 2021 | F69: August 23, 2021 | G69: (blank) | H69: (blank) | I69: (blank) | J69: 980000 | K69: 0
A70: 2021-040 | B70: Snacks during the Expanded Finance Committee Meeting on April 13, 2021 | C70: GERZON R. ABAD | D70: SVP | E70: April 13, 2021 | F70: April 22, 2021 | G70: 101 | H70: MOOE | I70: complete | J70: 2550 | K70: 1445
A71: 2021-041 | B71: for back-up and saving documents purposes | C71: ANGELITA H. VARGAS | D71: SVP | E71: 44384 | F71: 44384 | G71: 101 | H71: MOOE | I71: completed | J71: 168000 | K71: 139720
A72: 2021-042 | B72: communication expenses in the implementation of the Learning Continuity Plan | C72: ANGELITA H. VARGAS | D72: SVP | E72: June 9, 2021 | F72: June 29, 2021 | G72: 101 | H72: MOOE | I72: complete | J72: 171680 | K72: 171400
A73: 2021-043 | B73: Supplies and materials for Sports Development | C73: WILLIAM POL M. MAGGAY | D73: SVP | E73: August 23, 2021 | F73: August 23, 2021 | G73: 165 | H73: MOOE | I73: FAILED | J73: 3300 | K73: 0
A74: 2021-044 | B74: supplies/materials use for product development | C74: JANE S. CASTILLO | D74: SVP | E74: May 31 & July 1, 2021 | F74: June 10 & July 1, 2021 | G74: 165 | H74: MOOE | I74: complete | J74: 22625 | K74: 22170
A75: 2021-045 | B75: supplies/materials use for product development | C75: JANE S. CASTILLO | D75: SVP | E75: August 23, 2021 | F75: August 23, 2021 | G75: 165 | H75: MOOE | I75: for delivery | J75: 2000 | K75: 2000
A76: 2021-046 | B76: supplies/materials use for product development | C76: JANE S. CASTILLO | D76: SVP | E76: May 20, 2021 | F76: May 26, 2021 | G76: 165 | H76: MOOE | I76: complete | J76: 4500 | K76: 4500
A77: 2021-047 | B77: supplies/materials use for product development | C77: JANE S. CASTILLO | D77: SVP | E77: May 4, 2021 | F77: May 4, 2021 | G77: 165 | H77: MOOE | I77: complete | J77: 3000 | K77: 2650
A78: 2021-048 | B78: For President's Office use | C78: GERZON R. ABAD | D78: SVP | E78: May 20, 2021 | F78: May 26, 2021 | G78: 101 | H78: MOOE | I78: complete | J78: 3500 | K78: 2900
A79: 2021-049 | B79: Supplies for operational use of the Procurement Office | C79: ANNE MARIELLE V. TEVES | D79: SVP | E79: June 2 & July 7, 2021 | F79: June 10 & July 7, 2021 | G79: 101 | H79: MOOE | I79: partial delivery | J79: 14500 | K79: 14800
E80: August 23, 2021 | F80: August 23, 2021 | G80: 101 | H80: MOOE | I80: for delivery | J80: 22580 | K80: 21860
A81: 2021-050 | B81: replacement of defective HDD of ACER ASPIRE 3 | C81: JERSHON RALPH F. CASTANO | D81: SVP | E81: May 25, 2021 | F81: May 26, 2021 | G81: 101 | H81: MOOE | I81: complete | J81: 4500 | K81: 3800
A82: 2021-051 | B82: for office supplies | C82: WILLIAM JO SE M. BILLOTE | D82: SVP | E82: July 1, 2021 | F82: June 1 & July 1, 2021 | G82: 165 | H82: MOOE | I82: complete | J82: 39000 | K82: 36750
A83: 2021-052 | B83: for office supply | C83: WILLIAM JO SE M. BILLOTE | D83: (blank) | E83: August 23, 2021 | F83: August 23, 2021 | G83: (blank) | H83: (blank) | I83: FAILED | J83: 6000 | K83: 0
A84: 2021-053 | B84: use for office supplies | C84: WILLIAM JO SE M. BILLOTE | D84: SVP | E84: May 26, 2021 | F84: May 26, 2021 | G84: 165 | H84: MOOE | I84: complete | J84: 1450 | K84: 1400
A85: 2021-054 | B85: supplies & equuipment for the installation of split type | C85: JERSHON RALPH F. CASTANO | D85: SVP | E85: August 23, 2021 | F85: August 23, 2021 | G85: 101 | H85: MOOE | I85: on going | J85: 30000 | K85: 28020
A86: 2021-055 | B86: food for the BSC employees during the Tree Planting Activity at "Rakuh A Payaman" in Mahatao, Batanes 7:00am | C86: ANGELITA H. VARGAS | D86: SVP | E86: April 30, 2021 | F86: April 30, 2021 | G86: 101 | H86: MOOE | I86: complete | J86: 25000 | K86: 24900
A87: 2021-056 | B87: communication expenses | C87: XINA V. VINALAY | D87: (blank) | E87: August 23, 2021 | F87: August 23, 2021 | G87: (blank) | H87: (blank) | I87: (blank) | J87: 9880 | K87: 0
A88: 2021-057 | B88: for office supply | C88: ANDREI JOHN S. CORDOVA | D88: SVP | E88: June 2 & July 19, 2021 | F88: June 10 & July 26, 2021 | G88: 165 | H88: MOOE | I88: complete | J88: 13200 | K88: 12390
A89: 2021-058 | B89: snacks & lunch for the 2nd Quarter Performance Review & Regular meeting (May 18, 2021) | C89: DJOVI R. DURANTE | D89: SVP | E89: May 18, 2021 | F89: June 1, 2021 | G89: 101 | H89: MOOE | I89: complete | J89: 15700 | K89: 15400
A90: 2021-059 | B90: to keep update on the development of training/program for sports development | C90: WILLIAM POL M. MAGGAY | D90: SVP | E90: May 25, 2021 | F90: May 26, 2021 | G90: 165 | H90: MOOE | I90: complete | J90: 3300 | K90: 2800
A91: 2021-060 | B91: Use for mailing report of grades to parents, request credentials, Form 137 | C91: MAGDALENA V. BALLES | D91: SVP | E91: July 1, 2021 | F91: July 1, 2021 | G91: 165 | H91: MOOE | I91: for delivery | J91: 3000 | K91: 2950
A92: 2021-061 | B92: lunch & snacks for the Lab-Trip Training on May 6 and 7, 2021 at BSC | C92: FERDINAND BULUSAN | D92: SVP | E92: May 6 & 7, 2021 | F92: 44323 | G92: 165 | H92: MOOE | I92: complete | J92: 10500 | K92: 10425
A93: 2021-062 | B93: for office consumption (office supplies) | C93: WILLIAM JO SE M. BILLOTE | D93: SVP | E93: May 25 & July 5, 2021 | F93: May 26 & July 7, 2021 | G93: 101 | H93: MOOE | I93: complete | J93: 10000 | K93: 6270
A94: 2021-063 | B94: Installation of 2 units grrenhouse (4 x 12 sq. m) | C94: ROMEL A. RATERTA | D94: SVP | E94: August 23, 2021 | F94: August 23, 2021 | G94: (blank) | H94: (blank) | I94: on going | J94: 985000 | K94: 886500
A95: 2021-064 | B95: repair & maintenance of the cables of old 16 channel CCTV located at Supply Office | C95: JERSHON RALPH F. CASTANO | D95: SVP | E95: July 2, 2021 | F95: July 2, 2021 | G95: 101 | H95: MOOE | I95: complete | J95: 29000 | K95: 14860
A96: 2021-065 | B96: materials for the National Higher Education Week Competition (May 17-21, 2021) | C96: ELEIN T. ESPERANZA | D96: SVP | E96: May 17, 2021 | F96: June 1, 2021 | G96: 165 | H96: MOOE | I96: complete | J96: 900 | K96: 318
A97: 2021-066 | B97: materials for the National Higher Education Week Competition (May 17-21, 2021) | C97: ELEIN T. ESPERANZA | D97: SVP | E97: May 14, 2021 | F97: June 7, 2021 | G97: 165 | H97: MOOE | I97: complete | J97: 3420 | K97: 2537
A98: 2021-067 | B98: materials for the National Higher Education Week Competition (May 17-21, 2021) | C98: ELEIN T. ESPERANZA | D98: SVP | E98: August 23, 2021 | F98: August 23, 2021 | G98: (blank) | H98: (blank) | I98: FAILED | J98: 1500 | K98: 0
A99: 2021-068 | B99: materials for the National Higher Education Week Competition (May 17-21, 2021) | C99: ELEIN T. ESPERANZA | D99: SVP | E99: August 23, 2021 | F99: August 23, 2021 | G99: (blank) | H99: (blank) | I99: FAILED | J99: 1050 | K99: 0
A100: 2021-069 | B100: provision of WiFi Modems for internet connectivity (Admin. & Finance units) | C100: DJOVI R. DURANTE | D100: SVP | E100: August 23, 2021 | F100: August 23, 2021 | G100: 101 | H100: MOOE | I100: for delivery | J100: 30000 | K100: 27950
A101: 2021-070 | B101: Health Insurance of students | C101: WILLIAM JO SE M. BILLOTE | D101: SVP | E101: July 1, 2021 | F101: July 2, 2021 | G101: 165 | H101: (blank) | I101: complete | J101: 7500 | K101: 7500
A102: 2021-071 | B102: for the Implementation of "ADOPT through varied R & D of Ivatan Endemic Resources" research project | C102: FERDINAND BULUSAN | D102: SVP | E102: August 23, 2021 | F102: August 23, 2021 | G102: (blank) | H102: (blank) | I102: FAILED | J102: 45400 | K102: 0
...

Sheet Suppliers TIN
B1: Business Name | C1: Name/Owner | D1: TIN #
A2: 1 | B2: Apostol General Merchandise | C2: Leo A. Apostol | D2: 183-008-448
A3: 2 | B3: Bartilad's Feeds Trading | C3: Roldan Q. Bartilad | D3: 771-272-422
A4: 3 | B4: Bitstop Network Services Inc. | C4: JC James P. Jihay | D4: 005-931-291
A5: 4 | B5: Casa Del Basco | D5: 107-549-729
A6: 5 | B6: Crisel General Merchandise | C6: Cresencio M. Verana | D6: 135-792-662
A7: 6 | B7: Claire's Drugstore | C7: Claire H. Abad | D7: 264-438-671
A8: 7 | B8: Davocol's General Merchandise | C8: Lilibeth T. Davocol | D8: 116-311-342
A9: 8 | B9: Davocol's Inn | C9: Dan Ardie T. Davocol | D9: 739-884-154
A10: 9 | B10: D' Islands Gasoline Station | C10: Lito Doroteo A. Adarme | D10: 124-072-664
A11: 10 | B11: Doque's Congie Hauz | C11: Glenda L. Gordo | D11: 922-904-311
A12: 11 | B12: D. Michael Co Industrial Supply (DMC) Corp. | C12: Eunelyn O. Ramilla | D12: 007-776-953
A13: 12 | B13: E. A. Amboy General Merchandise | C13: Cesar Edgardo Amboy | D13: 928-655-269
A14: 13 | B14: Enrinar Trading | C14: Narcisa Co Melad | D14: 123-394-221
A15: 14 | B15: FMG Trading & Construction Supply | C15: Frederick Gari | D15: 219-884-940
A16: 15 | B16: GDP Trading | C16: George D. Peralta | D16: 150-214-534
A17: 16 | B17: Hubalde's Drugstore | C17: Marilyn G. Hubalde | D17: 914-979-941
A18: 17 | B18: Hudzan Café & Catering Services | C18: Susan Villegas | D18: 290-315-057 | E18: **
A19: 18 | B19: I.B.S Pharmacy & General Merchadise | C19: Dale Anthony C. Gutierrez | D19: 411-599-160
A20: 19 | B20: IAM'J Graphic Design & Printing | C20: Jaycy S. Alina | D20: 318-666-833
A21: 20 | B21: JPM General Merchandise & Hardware | C21: Emma P. Adarme | D21: 160-183-814
A22: 21 | B22: J-Tech Trading & Services | C22: Cecilia C. De Sagon | D22: 933-429-635
A23: 22 | B23: M.G. Hubalde's General Merchandise | C23: Marilyn G. Hubalde | D23: 914-979-941-001
A24: 23 | B24: MDAC Trading & Compuserve | C24: Florescita A. Cruz | D24: 100-194-776
A25: 24 | B25: NRA Hardware | C25: Neil Bernardo Ordas | D25: 196-062-499
A26: 25 | B26: One-Touch Technology Trading | C26: Janice A. Alasco | D26: 283-009-327
A27: 26 | B27: Pension Ivatan | C27: Teresita D. Valiente | D27: 106-115-883
A28: 27 | B28: Sophia Marie Store | C28: Regina B. Gabaldon | D28: 279-057-542
A29: 28 | B29: Twixbiz General Merchandise | C29: Charles B. Domingo | D29: 118-687-531
A30: 29 | B30: Northern Star General Merchandise | C30: Cesar A. Calma | D30: 151-407-774
... A37: 36 | B37: MKM Hardware | C37: Enrique Abuyo Melad Jr. | D37: 148-780-907
A38: 37 | B38: NSGB Books Trading | C38: Nica Sandra Go Banag
A39: 38 | B39: ONPREM2CLOUD IT SOLUTIONS CO. | C39: Emmanuel B. Mamayson | D39: 101-626-582
A40: 39 | B40: Petonio's Kitchen Food Services | C40: Ramona C. Tabuso | D40: 013-000-080-045-720-21
A41: 40 | B41: Tiger Consulting and Software Devt Inc. | D41: 007-073-548
A42: 41 | B42: MOJR Construction Trading & General Services, Ltd, Co. | C42: Manuel S. Obedoza Jr.
A43: 42 | B43: Batanes Electric Cooperative Inc. | C43: Victoria A. Mata | D43: 005-641-216-000
A44: 43 | B44: Maddies Fashion Design Services | C44: Madeline Palencia Palustre
A45: 44 | B45: CMVILL Trading | C45: Zariffe G. Villanueva | D45: 421-603-862-000
A46: 45 | B46: VL Mini Canteen | C46: Estela N. Lizardo | D46: 930-779-799
A47: 46 | B47: IDB Merida Photo Studio & Artworks | C47: Ignacio Danilo B. Merida | D47: 925-632-231
A48: 47 | B48: SKE Souvenir Trading | C48: Sophia Kate L. Esdicul | D48: 613-655-085-00001
A49: 48 | B49: I.B.S. Travel and Tours | C49: Zharmaine C. Gutierrez | D49: 258-905-353
A50: 49 | B50: FVA Trading | C50: NathaN a. Amboy | D50: 436-695-403
A51: 50 | B51: JC Delatado's Telecommunication Equipment Trading | C51: Jesse A. Delatado | D51: 713-001-589-00001
A52: 51 | B52: AZ Blue Box Café | C52: Zafra Hazel B. Baldovino | D52: 434-947-764-00001
A53: 52 | B53: Kian's Food Product | C53: William Pol M. Maggay | D53: 915-768-533-00000
A54: 53 | B54: ORCA General Merchandise | C54: Engr. La Verne Sarmiento | D54: 614-297-100-00000 | E54: Owner
A55: 54 | B55: Boulder Bay Residence | C55: Mario Rey Roa Pacana | D55: 943-433-381-002
A56: 55 | B56: Milagrosa Multi-Purpose Cooperative | C56: Katherine A. Balderas-Cashier/Authorized Representative | D56: 458-415-006-00000
A57: 56 | B57: F Digital Prints & Design Enterprises | C57: Geraldine Geneva D. Ferrer
A58: 57 | B58: Innovation Printshoppe, Inc. | C58: Yves Kenneth P. Mallari | D58: 004-591-735-000
A59: 58 | B59: Bunkers Bistro | C59: Jennifer Gabilo | D59: 297-134-097-00000 | E59: Owner
A60: 59 | B60: YCA Office Supplies and Equipment Trading | C60: Clark Michael A. Cruz | D60: 206-113-292-00000
A61: 60 | B61: YCA Printing Services | C61: Clark Michael A. Cruz | D61: 206-113-292-00000
A62: 62 | B62: Simsiman Arts & Crafts Manufacturing | C62: Catherine De Mata | D62: 187-250-096-000
A63: 63 | B63: Chanpan Photo & Video Services | C63: Katrina Caren B. Fitero | D63: 758-403-303-000
A64: 64 | B64: Ituxuh | E64: Videography
A65: 65 | B65: DRN Films | E65: Videography
A66: 66 | B66: Estylo Advertising | C66: Ellsworth C. Angeles Jr. | D66: 907-756-077-000 | E66: #9 Balzain Hi-Way,Centro 12,Tuguegarao City,Cagayan 3500
A67: 67 | B67: Wavetech Billboard and Outdoor Advertising Services | C67: Jerry M. Bitong | D67: 278-132-821 | E67: unit J,# 4 Batay St. Brgy. Kaunlaran, Cubao, Quezon City | G67: 92327624604

Sheet FundCodes
A1: CODE | B1: CATEGORY | C1: OFFICE/UNIT
A2: GAS1 | B2: General Administration Services | C2: Office of the President
A3: GAS2 | B3: General Administration Services | C3: Office of the Board Secretary
A4: GAS3 | B4: General Administration Services | C4: Office of the College Secretary | G4: Fund
A5: GAS4 | B5: General Administration Services | C5: Information & Communications Technology Unit | G5: 01-101
A6: GAS5 | B6: General Administration Services | C6: Information Unit | G6: 05-164
A7: GAS6 | B7: General Administration Services | C7: Internal Audit Unit | G7: 06-162
A8: GAS7 | B8: General Administration Services | C8: Legal Unit | G8: 07-165
A9: GAS8 | B9: General Administration Services | C9: Planning Unit
A10: GAS9 | B10: General Administration Services | C10: Project Management Unit
A11: GAS10 | B11: General Administration Services | C11: Quality Assurance Office
A12: GAS11 | B12: General Administration Services | C12: Administrative Office
A13: GAS12 | B13: General Administration Services | C13: Cash Unit
A14: GAS13 | B14: General Administration Services | C14: General Services Unit
A15: GAS14 | B15: General Administration Services | C15: Human Resource Management Unit
A16: GAS15 | B16: General Administration Services | C16: Procurement Unit
A17: GAS16 | B17: General Administration Services | C17: Records Unit
A18: GAS17 | B18: General Administration Services | C18: Supply & Property Management Unit
A19: GAS18 | B19: General Administration Services | C19: Accounting Unit
A20: GAS19 | B20: General Administration Services | C20: Budget Unit
... A42: Acad9 | B42: Director for Instruction | C42: DI
A43: 1005 | B43: Research & Extension Services | C43: Research & Extension Office
A44: 1006 | B44: Business Affairs Office | C44: Business Affairs Office
A45: 1006A | B45: College Assessment Center | C45: College Assessment Center
A46: 1006B | C46: CBAO-IGP
A47: 1006C | C47: CBAO-Dorm
A48: 1006D | C48: CBAO-Hostel

Sheet DATA
A1: YEAR | B1: MONTH | C1: End-User | D1: Position/Designation | E1: Fund Code | F1: Class | G1: PR# | H1: Modality | I1: Item | J1: Quantity | K1: Unit of Issue | L1: Unit Budget | M1: Estimated Total | N1: Unit LCRB | O1: Total | P1: Purpose | Q1: Office | R1: Date of LON | S1: Date of BAC Award | T1: PO/Contract Date Received | U1: Delivery Date | V1: Supplier | W1: IAR Date | X1: Section Code/Dept. | Y1: Released Date | Z1: Status | AA1: Remarks | AB1: ObR # | AC1: # of RFQ's printed | AD1: Sales/Charge Invoice/Billing
A2: 2025 | B2: May | C2: JANE S. CASTILLO | D2: Chair,Program Committee | E2: 101 | G2: 2025-173 | H2: SVP | I2: Wooden Plaque (A4), see attached content | J2: 9 | K2: pcs | L2: 1000 | M2: =SUM(J2*L2) -> 9000 | N2: 1000 | O2: =SUM(J2*N2) -> 9000 | P2: supplies & materials for the conduct of 2025 Commencement Excercises,Recognition Rites & Parents Night | Q2: DI | R2: May 22, 2025 | S2: June 3, 2025 | T2: June 4, 2025 | U2: June 16, 2025 | V2: SKE Souvenir Trading | W2: June 16, 2025 | X2: Acad9 | Y2: August 22, 2025 | Z2: complete | AA2: for payment-Acctg. | AB2: 02-101101-2025-06-00357 | AC2: 3 RFQ's | AD2: 0230/6/16/2025
A3: 2025 | B3: May | C3: JANE S. CASTILLO | D3: Chair,Program Committee | E3: 101 | G3: 2025-174 | H3: SVP | I3: Tarpaulin (6ft x 4ft) | J3: 1 | K3: pcs | L3: 1000 | M3: =SUM(J3*L3) -> 1000 | N3: 720 | O3: =SUM(J3*N3) -> 720 | P3: supplies & materials for the conduct of 2025 Commencement Excercises,Recognition Rites & Parents Night | Q3: DI | R3: May 16, 2025 | S3: May 20, 2025 | T3: May 21, 2025 | U3: May 21, 2025 | V3: YCA Printing Services | W3: May 21, 2025 | X3: Acad9 | Y3: August 26, 2025 | Z3: complete | AA3: for payment-Acctg. | AB3: 02-101101-2025-05-00309 | AC3: 3 RFQ's | AD3: 336/5/21/2025
A4: 2025 | B4: May | C4: JANE S. CASTILLO | D4: Chair,Program Committee | E4: 101 | G4: 2025-175 | H4: SVP | I4: Specialty Paper(10 pcs per pack),A4-size, Color: white,GSM-200 | J4: 150 | K4: packs | L4: 150 | M4: =SUM(J4*L4) -> 22500 | N4: 65 | O4: =SUM(J4*N4) -> 9750 | P4: supplies & materials for the conduct of 2025 Commencement Excercises,Recognition Rites & Parents Night | Q4: DI | R4: May 22, 2025 | S4: June 3, 2025 | T4: June 4, 2025 | U4: June 16, 2025 | V4: JPM General Merchandise & Hardware | W4: June 16, 2025 | X4: Acad9 | Y4: June 25, 2025 | Z4: complete | AA4: for payment-Acctg. | AB4: 02-101101-2025-06-00358 | AC4: 5 RFQ's + 1blank | AD4: 12921/
A5: 2025 | B5: May | C5: JANE S. CASTILLO | D5: Chair,Program Committee | E5: 101 | G5: 2025-175 | H5: SVP | I5: Ink (003,black,yellow,cyan,magenta) | J5: 3 | K5: set | L5: 4500 | M5: =SUM(J5*L5) -> 13500 | N5: 1800 | O5: =SUM(J5*N5) -> 5400 | P5: supplies & materials for the conduct of 2025 Commencement Excercises,Recognition Rites & Parents Night | Q5: DI | R5: May 22, 2025 | S5: June 3, 2025 | T5: June 4, 2025 | U5: June 16, 2025 | V5: JPM General Merchandise & Hardware | W5: June 16, 2025 | X5: Acad9 | Y5: June 25, 2025 | Z5: complete | AA5: for payment-Acctg. | AB5: 02-101101-2025-06-00358
A6: 2025 | B6: May | C6: JANE S. CASTILLO | D6: Chair,Program Committee | E6: 101 | G6: 2025-175 | H6: SVP | I6: Certificate Holder (A4) | J6: 300 | K6: pcs | L6: 100 | M6: =SUM(J6*L6) -> 30000 | N6: 80 | O6: =SUM(J6*N6) -> 24000 | P6: supplies & materials for the conduct of 2025 Commencement Excercises,Recognition Rites & Parents Night | Q6: DI | R6: May 22, 2025 | S6: June 3, 2025 | T6: June 4, 2025 | U6: June 16, 2025 | V6: JPM General Merchandise & Hardware | W6: June 16, 2025 | X6: Acad9 | Y6: June 25, 2025 | Z6: complete | AA6: for payment-Acctg. | AB6: 02-101101-2025-06-00358
A7: 2025 | B7: May | C7: JANE S. CASTILLO | D7: Chair,Program Committee | E7: 101 | G7: 2025-175 | H7: SVP | I7: Bondpaper (A4,70 gsm, 5 reams/box) | J7: 4 | K7: box | L7: 1450 | M7: =SUM(J7*L7) -> 5800 | N7: 1325 | O7: =SUM(J7*N7) -> 5300 | P7: supplies & materials for the conduct of 2025 Commencement Excercises,Recognition Rites & Parents Night | Q7: DI | R7: May 22, 2025 | S7: June 3, 2025 | T7: June 4, 2025 | U7: June 16, 2025 | V7: JPM General Merchandise & Hardware | W7: June 16, 2025 | X7: Acad9 | Y7: June 25, 2025 | Z7: complete | AA7: for payment-Acctg. | AB7: 02-101101-2025-06-00358
A8: 2025 | B8: May | C8: VILMA D. BACCAY | D8: Acting College Registrar | G8: 2025-176 | H8: SVP | I8: Graduation Medal (diameter; 9cm, maroon-black gradient border) Summa Cum Laude | J8: 2 | K8: pcs | L8: 400 | M8: =SUM(J8*L8) -> 800 | O8: =SUM(J8*N8) -> 0 | P8: medals for Academic Awardees for Graduation 2025 Ceremony | Q8: DI | X8: Acad9 | Z8: CANCELLED | AA8: by the end-user (use the remaining supplies for last year)
A9: 2025 | B9: May | C9: VILMA D. BACCAY | D9: Acting College Registrar | G9: 2025-176 | H9: SVP | I9: Graduation Medal (diameter; 8cm, maroon-black gradient border) Magna Cum Laude | J9: 5 | K9: pcs | L9: 390 | M9: =SUM(J9*L9) -> 1950 | O9: =SUM(J9*N9) -> 0 | P9: medals for Academic Awardees for Graduation 2025 Ceremony | Q9: DI | X9: Acad9
A10: 2025 | B10: May | C10: VILMA D. BACCAY | D10: Acting College Registrar | G10: 2025-176 | H10: SVP | I10: Graduation Medal (diameter; 7cm, maroon-black gradient border) Cum Laude | J10: 20 | K10: pcs | L10: 350 | M10: =SUM(J10*L10) -> 7000 | O10: =SUM(J10*N10) -> 0 | P10: medals for Academic Awardees for Graduation 2025 Ceremony | Q10: DI | X10: Acad9
A11: 2025 | B11: May | C11: VILMA D. BACCAY | D11: Acting College Registrar | G11: 2025-176 | H11: SVP | I11: Graduation Medal (diameter; 7cm, maroon-black gradient border) with Academic Distinction | J11: 5 | K11: pcs | L11: 350 | M11: =SUM(J11*L11) -> 1750 | O11: =SUM(J11*N11) -> 0 | P11: medals for Academic Awardees for Graduation 2025 Ceremony | Q11: DI | X11: Acad9
A12: 2025 | B12: May | C12: VILMA D. BACCAY | D12: Acting College Registrar | G12: 2025-177 | H12: SVP | I12: Emerald Green Satin Ribbon (1") | J12: 1 | K12: roll | L12: 250 | M12: =SUM(J12*L12) -> 250 | O12: =SUM(J12*N12) -> 0 | P12: for use in preparing academic medals for Graduation 2025 | Q12: DI | X12: Acad9 | Z12: CANCELLED
A13: 2025 | B13: May | C13: VILMA D. BACCAY | D13: Acting College Registrar | G13: 2025-177 | H13: SVP | I13: Metallic Gold Satin Ribbon (1/2") | J13: 1 | K13: roll | L13: 200 | M13: =SUM(J13*L13) -> 200 | O13: =SUM(J13*N13) -> 0 | P13: for use in preparing academic medals for Graduation 2025 | Q13: DI
A14: 2025 | B14: May | C14: VILMA D. BACCAY | D14: Acting College Registrar | G14: 2025-177 | H14: SVP | I14: Button Lock/Rematche Hand Press machine | J14: 1 | K14: pc | L14: 3000 | M14: =SUM(J14*L14) -> 3000 | O14: =SUM(J14*N14) -> 0 | P14: for use in preparing academic medals for Graduation 2025 | Q14: DI | X14: Acad9
A15: 2025 | B15: May | C15: JOHN MICHAEL A. VILLASPIR | D15: Administrative Officer I | G15: 2025-178 | H15: SVP | I15: 1/2 Copper Tube | J15: 6 | K15: rolls | L15: 4100 | M15: =SUM(J15*L15) -> 24600 | O15: =SUM(J15*N15) -> 0 | P15: use for installation of Airconditioning Unit | Q15: GSO | X15: GAS20 | Z15: FAILED | AA15: qoutation exceeded the budget | AC15: 4 RFQ's + 1blank
A16: 2025 | B16: May | C16: JOHN MICHAEL A. VILLASPIR | D16: Administrative Officer I | G16: 2025-178 | H16: SVP | I16: 1/4 Copper Tube | J16: 9 | K16: rolls | L16: 1990 | M16: =SUM(J16*L16) -> 17910 | O16: =SUM(J16*N16) -> 0 | P16: use for installation of Airconditioning Unit | Q16: GSO | X16: GAS20
A17: 2025 | B17: May | C17: JOHN MICHAEL A. VILLASPIR | D17: Administrative Officer I | G17: 2025-178 | H17: SVP | I17: 1 1/2 Stainless Dyna Bolt | J17: 50 | K17: pcs | L17: 20 | M17: =SUM(J17*L17) -> 1000 | O17: =SUM(J17*N17) -> 0 | P17: use for installation of Airconditioning Unit | Q17: GSO | X17: GAS20
A18: 2025 | B18: May | C18: JOHN MICHAEL A. VILLASPIR | D18: Administrative Officer I | G18: 2025-178 | H18: SVP | I18: Mapro Gas | J18: 5 | K18: pcs | L18: 580 | M18: =SUM(J18*L18) -> 2900 | O18: =SUM(J18*N18) -> 0 | P18: use for installation of Airconditioning Unit | Q18: GSO | X18: GAS20
A19: 2025 | B19: May | C19: JOHN MICHAEL A. VILLASPIR | D19: Administrative Officer I | G19: 2025-178 | H19: SVP | I19: #12 AWG THHN Wire | J19: 3 | K19: rolls | L19: 5500 | M19: =SUM(J19*L19) -> 16500 | O19: =SUM(J19*N19) -> 0 | P19: use for installation of Airconditioning Unit | Q19: GSO | X19: GAS20
A20: 2025 | B20: May | C20: MICHEL A. CABRERA | D20: Assistant Professor IV | E20: 165 | G20: 2025-179 | H20: SVP | I20: Black Ink Refill (774) 140ml | J20: 4 | K20: bottle | L20: 900 | M20: =SUM(J20*L20) -> 3600 | N20: 800 | O20: =SUM(J20*N20) -> 3200 | P20: to be used for instruction and office supplies | Q20: ICT | R20: May 30, 2025 | S20: June 3, 2025 | T20: June 4, 2025 | U20: July 3, 2025 | V20: One-Touch Technology Trading | W20: July 3, 2025 | X20: GAS4 | Y20: 45883 | Z20: complete | AA20: for payment-Acctg. | AB20: 07-02-2025-06-0201 | AC20: 5 RFQ's | AD20: 7799/7/3/2025
A21: 2025 | B21: May | C21: MICHEL A. CABRERA | D21: Assistant Professor IV | E21: 165 | G21: 2025-179 | H21: SVP | I21: Cyan Ink Refill (664) 70ml | J21: 2 | K21: bottle | L21: 450 | M21: =SUM(J21*L21) -> 900 | N21: 450 | O21: =SUM(J21*N21) -> 900 | P21: to be used for instruction and office supplies | Q21: ICT | R21: May 30, 2025 | S21: June 3, 2025 | T21: June 4, 2025 | U21: July 3, 2025 | V21: One-Touch Technology Trading | W21: July 3, 2025 | X21: GAS4 | Y21: 45883 | Z21: complete | AA21: for payment-Acctg. | AB21: 07-02-2025-06-0201
A22: 2025 | B22: May | C22: MICHEL A. CABRERA | D22: Assistant Professor IV | E22: 165 | G22: 2025-179 | H22: SVP | I22: Cyan Ink Refill (664) 70ml | J22: 2 | K22: bottle | L22: 450 | M22: =SUM(J22*L22) -> 900 | N22: 450 | O22: =SUM(J22*N22) -> 900 | P22: to be used for instruction and office supplies | Q22: ICT | R22: May 30, 2025 | S22: June 3, 2025 | T22: June 4, 2025 | U22: July 3, 2025 | V22: One-Touch Technology Trading | W22: July 3, 2025 | X22: GAS4 | Y22: 45883 | Z22: complete | AA22: for payment-Acctg. | AB22: 07-02-2025-06-0201
A23: 2025 | B23: May | C23: MICHEL A. CABRERA | D23: Assistant Professor IV | E23: 165 | G23: 2025-179 | H23: SVP | I23: Magenta Ink Refill (664) 70ml | J23: 2 | K23: bottle | L23: 450 | M23: =SUM(J23*L23) -> 900 | N23: 450 | O23: =SUM(J23*N23) -> 900 | P23: to be used for instruction and office supplies | Q23: ICT | R23: May 30, 2025 | S23: June 3, 2025 | T23: June 4, 2025 | U23: July 3, 2025 | V23: One-Touch Technology Trading | W23: July 3, 2025 | X23: GAS4 | Y23: 45883 | Z23: complete | AA23: for payment-Acctg. | AB23: 07-02-2025-06-0201
A24: 2025 | B24: May | C24: MICHEL A. CABRERA | D24: Assistant Professor IV | E24: 165 | G24: 2025-179 | H24: SVP | I24: L14150 Ink Refill 001 (CMYK) 65ml | J24: 3 | K24: set | L24: 2000 | M24: =SUM(J24*L24) -> 6000 | N24: 2220 | O24: =SUM(J24*N24) -> 6660 | P24: to be used for instruction and office supplies | Q24: ICT | R24: May 30, 2025 | S24: June 3, 2025 | T24: June 4, 2025 | U24: July 3, 2025 | V24: One-Touch Technology Trading | W24: July 3, 2025 | X24: GAS4 | Y24: 45883 | Z24: complete | AA24: for payment-Acctg. | AB24: 07-02-2025-06-0201
A25: 2025 | B25: May | C25: MICHEL A. CABRERA | D25: Assistant Professor IV | E25: 165 | G25: 2025-179 | H25: SVP | I25: Specialty Paper (white,A4) | J25: 15 | K25: packs | L25: 200 | M25: =SUM(J25*L25) -> 3000 | N25: 65 | O25: =SUM(J25*N25) -> 975 | P25: to be used for instruction and office supplies | Q25: ICT | R25: May 30, 2025 | S25: June 3, 2025 | T25: June 4, 2025 | U25: July 3, 2025 | V25: One-Touch Technology Trading | W25: July 3, 2025 | X25: GAS4 | Y25: 45883 | Z25: complete | AA25: for payment-Acctg. | AB25: 07-02-2025-06-0201
A26: 2025 | B26: May | C26: MICHEL A. CABRERA | D26: Assistant Professor IV | E26: 165 | G26: 2025-179 | H26: SVP | I26: L3110 Ink Refill 003 (CMYK) 65ml | J26: 2 | K26: set | L26: 2000 | M26: =SUM(J26*L26) -> 4000 | N26: 1880 | O26: =SUM(J26*N26) -> 3760 | P26: to be used for instruction and office supplies | Q26: ICT | R26: May 30, 2025 | S26: June 3, 2025 | T26: June 4, 2025 | U26: July 3, 2025 | V26: One-Touch Technology Trading | W26: July 3, 2025 | X26: GAS4 | Y26: 45883 | Z26: complete | AA26: for payment-Acctg. | AB26: 07-02-2025-06-0201
A27: 2025 | B27: May | C27: MICHEL A. CABRERA | D27: Assistant Professor IV | G27: 2025-180 | H27: SVP | I27: Routerboard RouterOS L5 1U 8-port gigabit router (RB5009UG+S+IN) | J27: 2 | K27: pcs | L27: 18525 | M27: =SUM(J27*L27) -> 37050 | O27: =SUM(J27*N27) -> 0 | P27: to be used for instruction and office supplies | Q27: ICT | X27: GAS4 | Z27: FAILED | AA27: quotation exceeded the budget | AC27: 4 RFQ's + 1blank
A28: 2025 | B28: May | C28: MICHEL A. CABRERA | D28: Assistant Professor IV | G28: 2025-180 | H28: SVP | I28: Router Board | J28: 5 | K28: pcs | L28: 2250 | M28: =SUM(J28*L28) -> 11250 | O28: =SUM(J28*N28) -> 0 | P28: to be used for instruction and office supplies | Q28: ICT | X28: GAS4
A29: 2025 | B29: May | C29: MICHEL A. CABRERA | D29: Assistant Professor IV | G29: 2025-180 | H29: SVP | I29: Canon Lens EF-S 55-250mm (f4-5.6 lS STM | J29: 1 | K29: pc | L29: 29250 | M29: =SUM(J29*L29) -> 29250 | O29: =SUM(J29*N29) -> 0 | P29: to be used for instruction and office supplies | Q29: ICT | X29: GAS4
A30: 2025 | B30: May | C30: MICHEL A. CABRERA | D30: Assistant Professor IV | G30: 2025-180 | H30: SVP | I30: Canon LP-E17 battery for camera EOS 200D | J30: 1 | K30: pc | L30: 3300 | M30: =SUM(J30*L30) -> 3300 | O30: =SUM(J30*N30) -> 0 | P30: to be used for instruction and office supplies | Q30: ICT | X30: GAS4
A31: 2025 | B31: May | C31: MICHEL A. CABRERA | D31: Assistant Professor IV | G31: 2025-180 | H31: SVP | I31: Expansion Portable Drive 2TB XHDD | J31: 1 | K31: pc | L31: 3450 | M31: =SUM(J31*L31) -> 3450 | O31: =SUM(J31*N31) -> 0 | P31: to be used for instruction and office supplies | Q31: ICT | X31: GAS4
A32: 2025 | B32: May | C32: PHILIP ULYSSES T. CASTILLO | D32: Attorney IV | E32: 101 | G32: 2025-181 | H32: SVP | I32: Heavy Duty Extension Cord Set with individual switch (4 gang) | J32: 1 | K32: pc | L32: 1000 | M32: =SUM(J32*L32) -> 1000 | N32: 1680 | O32: =SUM(J32*N32) -> 1680 | P32: for office use | Q32: Legal | R32: May 30, 2025 | S32: June 3, 2025 | T32: June 4, 2025 | U32: July 3, 2025 | V32: One-Touch Technology Trading | W32: July 3, 2025 | X32: GAS7 | Y32: 45883 | Z32: complete | AA32: for payment-Acctg. | AB32: 02-101101-2025-06-00359 | AC32: 4 RFQ's | AD32: 7800/7/3/2025
A33: 2025 | B33: May | C33: PHILIP ULYSSES T. CASTILLO | D33: Attorney IV | E33: 101 | G33: 2025-181 | H33: SVP | I33: Staple Wire (26/6) | J33: 2 | K33: box | L33: 300 | M33: =SUM(J33*L33) -> 600 | N33: 50 | O33: =SUM(J33*N33) -> 100 | P33: for office use | Q33: Legal | R33: May 30, 2025 | S33: June 3, 2025 | T33: June 4, 2025 | U33: July 3, 2025 | V33: One-Touch Technology Trading | W33: July 3, 2025 | X33: GAS7 | Y33: 45883 | Z33: complete | AA33: for payment-Acctg. | AB33: 02-101101-2025-06-00359
A34: 2025 | B34: May | C34: PHILIP ULYSSES T. CASTILLO | D34: Attorney IV | E34: 101 | G34: 2025-181 | H34: SVP | I34: Red Ballpen (0.5) | J34: 1 | K34: doz | L34: 250 | M34: =SUM(J34*L34) -> 250 | N34: 180 | O34: =SUM(J34*N34) -> 180 | P34: for office use | Q34: Legal | R34: May 30, 2025 | S34: June 3, 2025 | T34: June 4, 2025 | U34: July 3, 2025 | V34: One-Touch Technology Trading | W34: July 3, 2025 | X34: GAS7 | Y34: 45883 | Z34: complete | AA34: for payment-Acctg. | AB34: 02-101101-2025-06-00359
A35: 2025 | B35: May | C35: PHILIP ULYSSES T. CASTILLO | D35: Attorney IV | E35: 101 | G35: 2025-181 | H35: SVP | I35: USB 64GB | J35: 2 | K35: pcs | L35: 500 | M35: =SUM(J35*L35) -> 1000 | N35: 580 | O35: =SUM(J35*N35) -> 1160 | P35: for office use | Q35: Legal | R35: May 30, 2025 | S35: June 3, 2025 | T35: June 4, 2025 | U35: July 3, 2025 | V35: One-Touch Technology Trading | W35: July 3, 2025 | X35: GAS7 | Y35: 45883 | Z35: complete | AA35: for payment-Acctg. | AB35: 02-101101-2025-06-00359
A36: 2025 | B36: May | C36: PHILIP ULYSSES T. CASTILLO | D36: Attorney IV | E36: 101 | G36: 2025-181 | H36: SVP | I36: Self Ink Stamp (Receive with date) | J36: 1 | K36: pc | L36: 500 | M36: =SUM(J36*L36) -> 500 | N36: 980 | O36: =SUM(J36*N36) -> 980 | P36: for office use | Q36: Legal | R36: May 30, 2025 | S36: June 3, 2025 | T36: June 4, 2025 | U36: July 3, 2025 | V36: One-Touch Technology Trading | W36: July 3, 2025 | X36: GAS7 | Y36: 45883 | Z36: complete | AA36: for payment-Acctg. | AB36: 02-101101-2025-06-00359
A37: 2025 | B37: May | C37: PHILIP ULYSSES T. CASTILLO | D37: Attorney IV | E37: 101 | G37: 2025-181 | H37: SVP | I37: Whiteboard (40*60cm) | J37: 1 | K37: pc | L37: 800 | M37: =SUM(J37*L37) -> 800 | N37: 600 | O37: =SUM(J37*N37) -> 600 | P37: for office use | Q37: Legal | R37: May 30, 2025 | S37: June 3, 2025 | T37: June 4, 2025 | U37: July 3, 2025 | V37: One-Touch Technology Trading | W37: July 3, 2025 | X37: GAS7 | Y37: 45883 | Z37: complete | AA37: for payment-Acctg. | AB37: 02-101101-2025-06-00359
A38: 2025 | B38: May | C38: PHILIP ULYSSES T. CASTILLO | D38: Attorney IV | E38: 101 | G38: 2025-181 | H38: SVP | I38: Whiteboard Marker (2 red, 2 black, 2 blue) | J38: 6 | K38: pcs | L38: 85 | M38: =SUM(J38*L38) -> 510 | N38: 50 | O38: =SUM(J38*N38) -> 300 | P38: for office use | Q38: Legal | R38: May 30, 2025 | S38: June 3, 2025 | T38: June 4, 2025 | U38: July 3, 2025 | V38: One-Touch Technology Trading | W38: July 3, 2025 | X38: GAS7 | Y38: 45883 | Z38: complete | AA38: for payment-Acctg. | AB38: 02-101101-2025-06-00359
A39: 2025 | B39: May | C39: PHILIP ULYSSES T. CASTILLO | D39: Attorney IV | E39: 101 | G39: 2025-181 | H39: SVP | I39: Magnetic Whiteboard Eraser | J39: 1 | K39: pc | L39: 250 | M39: =SUM(J39*L39) -> 250 | N39: 80 | O39: =SUM(J39*N39) -> 80 | P39: for office use | Q39: Legal | R39: May 30, 2025 | S39: June 3, 2025 | T39: June 4, 2025 | U39: July 3, 2025 | V39: One-Touch Technology Trading | W39: July 3, 2025 | X39: GAS7 | Y39: 45883 | Z39: complete | AA39: for payment-Acctg. | AB39: 02-101101-2025-06-00359
A40: 2025 | B40: May | C40: PHILIP ULYSSES T. CASTILLO | D40: Attorney IV | E40: 101 | G40: 2025-181 | H40: SVP | I40: Assorted Highlighter | J40: 1 | K40: set | L40: 350 | M40: =SUM(J40*L40) -> 350 | N40: 180 | O40: =SUM(J40*N40) -> 180 | P40: for office use | Q40: Legal | R40: May 30, 2025 | S40: June 3, 2025 | T40: June 4, 2025 | U40: July 3, 2025 | V40: One-Touch Technology Trading | W40: July 3, 2025 | X40: GAS7 | Y40: 45883 | Z40: complete | AA40: for payment-Acctg. | AB40: 02-101101-2025-06-00359
A41: 2025 | B41: May | C41: WARLITO M. TOMAS JR. | D41: Project Leader | E41: 165 | G41: 2025-182 | H41: SVP | I41: Feeding Trough (15 kg capacity Plastic automatic feeder per pigs, dimension height of 45cm and width of 44cm | J41: 16 | K41: pcs | L41: 5500 | M41: =SUM(J41*L41) -> 88000 | N41: 5450 | O41: =SUM(J41*N41) -> 87200 | P41: for the project "Developing Feed Formulations for Bagu Ivatan Using Locally-Available Feeds and Forages" | Q41: Agri | R41: May 31, 2025 | S41: June 3, 2025 | T41: June 4, 2025 | U41: August 14 & Sept. 3, 2025 | V41: E.A.Amboy General Merchandise | W41: August 14 & Sept. 3, 2025 | X41: Acad7 | Y41: September 19, 2025 | Z41: complete | AA41: for payment-Acctg. | AB41: 07-02-2025-06-0202 | AC41: 4 RFQ's + 1blank | AD41: 015443/8/14/2025
A42: 2025 | B42: May | C42: EMILYN D. ALUETA | D42: Administrative Officer V | E42: 101 | G42: 2025-183 | H42: SVP | I42: Multi Function Printer- Functions: Print,scan,copy,Paper size: supported up to A3 (printing & scanning), Connectivity: USB, Wifi Direct; LAN and Airprint,Ink System: Ink Tank refillable,Printing Features: Auto Document Feeder (ADF & Auto-sided (Duplex, Back to back printing) | J42: 1 | K42: unit | L42: 47970 | M42: =SUM(J42*L42) -> 47970 | N42: 42000 | O42: =SUM(J42*N42) -> 42000 | P42: for office use | Q42: Cashier | R42: May 30, 2025 | S42: June 3, 2025 | T42: June 4, 2025 | U42: June 24, 2025 | V42: JPM General Merchandise & Hardware | W42: June 24, 2025 | X42: GAS12 | Y42: July 3, 2025 | Z42: complete | AA42: for payment-Acctg. | AB42: 02-101101-2025-06-00360 | AC42: 5 RFQ's | AD42: 12927/6/24/2025
A43: 2025 | B43: May | C43: DOREEN C. CASTILLO | D43: Study Leader (Study 5) | G43: 2025-184 | H43: SVP | I43: Pandanus Leaves Slitter/Pressing Machine-Technical Specifications;* single-point, metal to metal contact pressing,roller diameter: two 60mm and one 75mm,roller length; 128mm,synchronized roller rotation using spur gear mechanism,synchronized adjustment of roller gap up to five millimeter (5mm) distance,manual hand cranking method,roller speed; approximately 0.07 m/s | J43: 1 | K43: unit | L43: 100000 | M43: =SUM(J43*L43) -> 100000 | O43: =SUM(J43*N43) -> 0 | P43: for the implementation of the Project 2 Science & Technology based interventions for sustainable tourism in Batanes | Q43: BSC-RDET | X43: 1005 | Z43: FAILED | AA43: quotation exceeded the budget | AC43: 5 RFQ's + 1blank
A44: 2025 | B44: May | C44: DOREEN C. CASTILLO | D44: Study Leader (Study 5) | G44: 2025-184 | H44: SVP | I44: Inclusive: Operating & Trouble Shooting Manual, 1-2 weeks on the site training on: Machine Set up,Machine operation,machine maintenance,Basic Trouble shooting, Delivery & Site Installation In; Baco, Batanes,Warranty: One (1) year | M44: =SUM(J44*L44) -> 0 | O44: =SUM(J44*N44) -> 0 | P44: for the implementation of the Project 2 Science & Technology based interventions for sustainable tourism in Batanes | Q44: BSC-RDET | X44: 1005
A45: 2025 | B45: May | C45: WARLITO M. TOMAS JR. | D45: Project Leader | E45: 165 | G45: 2025-185 | H45: SVP | I45: Feeds (Lactation | J45: 20 | K45: sacks | L45: 1950 | M45: =SUM(J45*L45) -> 39000 | N45: 1950 | O45: =SUM(J45*N45) -> 39000 | P45: feeds for native pigs | Q45: DOST-PCAARRD | R45: May 30, 2025 | S45: June 3, 2025 | T45: June 4, 2025 | U45: June 27, 2025 | V45: Bartilad Feeds Trading | W45: June 27, 2025 | X45: 1005 | Y45: August 22, 2025 | Z45: complete | AA45: for payment-Acctg. | AB45: 07-02-2025-06-0203 | AC45: 3 RFQ's + 1blank | AD45: 042/6/27/2025
A46: 2025 | B46: May | C46: WARLITO M. TOMAS JR. | D46: Project Leader | E46: 165 | G46: 2025-185 | H46: SVP | I46: Gestation | J46: 20 | K46: sacks | L46: 1900 | M46: =SUM(J46*L46) -> 38000 | N46: 1900 | O46: =SUM(J46*N46) -> 38000 | P46: feeds for native pigs | Q46: DOST-PCAARRD | R46: May 30, 2025 | S46: June 3, 2025 | T46: June 4, 2025 | U46: June 27, 2025 | V46: Bartilad Feeds Trading | W46: June 27, 2025 | X46: 1005 | Y46: August 22, 2025 | Z46: complete | AA46: for payment-Acctg. | AB46: 07-02-2025-06-0203
A47: 2025 | B47: May | C47: WARLITO M. TOMAS JR. | D47: Project Leader | E47: 165 | G47: 2025-185 | H47: SVP | I47: Grower | J47: 10 | K47: sacks | L47: 2000 | M47: =SUM(J47*L47) -> 20000 | N47: 2000 | O47: =SUM(J47*N47) -> 20000 | P47: feeds for native pigs | Q47: DOST-PCAARRD | R47: May 30, 2025 | S47: June 3, 2025 | T47: June 4, 2025 | U47: June 27, 2025 | V47: Bartilad Feeds Trading | W47: June 27, 2025 | X47: 1005 | Y47: August 22, 2025 | Z47: complete | AA47: for payment-Acctg. | AB47: 07-02-2025-06-0203
A48: 2025 | B48: May | C48: KURT G. HOSTALLERO | D48: Quality Assurance Officer II | E48: 101 | G48: 2025-186 | H48: SVP | I48: Multi Function Printer- Functions: Print,scan,copy,Paper size: supported up to A3 (printing & scanning), Connectivity: USB, Wifi Direct; LAN and Airprint,Ink System: Ink Tank refillable,Printing Features: Auto Document Feeder (ADF & Auto-sided (Duplex, Back to back printing) | J48: 1 | K48: unit | L48: 48500 | M48: =SUM(J48*L48) -> 48500 | N48: 48000 | O48: =SUM(J48*N48) -> 48000 | P48: for printing & reproduce of documents in preparation for Quality Management System (QMS) Certification | Q48: QAO | R48: May 30, 2025 | S48: June 3, 2025 | T48: June 4, 2025 | V48: One-Touch Technology Trading | W48: July 14, 2025 | X48: GAS10 | Y48: September 1, 2025 | Z48: complete | AA48: for payment-Acctg. | AB48: 02-101101-2025-06-00363 | AC48: 5 RFQ's | AD48: 7820/7/14/2025
A49: 2025 | B49: May | C49: KURT G. HOSTALLERO | D49: Quality Assurance Officer II | E49: 101 | G49: 2025-187 | H49: SVP | I49: Printer Ink (BTD60) | J49: 3 | K49: bottles | L49: 600 | M49: =SUM(J49*L49) -> 1800 | N49: 680 | O49: =SUM(J49*N49) -> 2040 | P49: for printing & reproduction of documents | Q49: QAO | R49: May 30, 2025 | S49: June 3, 2025 | T49: June 4, 2025 | U49: June 27, 2025 | V49: Apostol General Merchandise | W49: June 27, 2025 | X49: GAS10 | Y49: July 3, 2025 | Z49: complete | AA49: for payment-Acctg. | AB49: 02-101101-2025-06-00361 | AC49: 5 RFQ's | AD49: 2851/6/27/2025
A50: 2025 | B50: May | C50: KURT G. HOSTALLERO | D50: Quality Assurance Officer II | E50: 101 | G50: 2025-187 | H50: SVP | I50: Printer Ink (BT5000-C) | J50: 2 | K50: bottles | L50: 600 | M50: =SUM(J50*L50) -> 1200 | N50: 400 | O50: =SUM(J50*N50) -> 800 | P50: for printing & reproduction of documents | Q50: QAO | R50: May 30, 2025 | S50: June 3, 2025 | T50: June 4, 2025 | U50: June 27, 2025 | V50: Apostol General Merchandise | W50: June 27, 2025 | X50: GAS10 | Y50: July 3, 2025 | Z50: complete | AA50: for payment-Acctg. | AB50: 02-101101-2025-06-00361
A51: 2025 | B51: May | C51: KURT G. HOSTALLERO | D51: Quality Assurance Officer II | E51: 101 | G51: 2025-187 | H51: SVP | I51: Printer Ink (BT5000-M) | J51: 2 | K51: bottles | L51: 600 | M51: =SUM(J51*L51) -> 1200 | N51: 400 | O51: =SUM(J51*N51) -> 800 | P51: for printing & reproduction of documents | Q51: QAO | R51: May 30, 2025 | S51: June 3, 2025 | T51: June 4, 2025 | U51: June 27, 2025 | V51: Apostol General Merchandise | W51: June 27, 2025 | X51: GAS10 | Y51: July 3, 2025 | Z51: complete | AA51: for payment-Acctg. | AB51: 02-101101-2025-06-00361
A52: 2025 | B52: May | C52: KURT G. HOSTALLERO | D52: Quality Assurance Officer II | E52: 101 | G52: 2025-187 | H52: SVP | I52: Printer Ink (BT5000-Y) | J52: 3 | K52: bottles | L52: 600 | M52: =SUM(J52*L52) -> 1800 | N52: 400 | O52: =SUM(J52*N52) -> 1200 | P52: for printing & reproduction of documents | Q52: QAO | R52: May 30, 2025 | S52: June 3, 2025 | T52: June 4, 2025 | U52: June 27, 2025 | V52: Apostol General Merchandise | W52: June 27, 2025 | X52: GAS10 | Y52: July 3, 2025 | Z52: complete | AA52: for payment-Acctg. | AB52: 02-101101-2025-06-00361
A53: 2025 | B53: May | C53: JANNEL B. BASIUANG | D53: Student Publication Adviser | G53: 2025-188 | H53: SVP | I53: EOS R 100 Canon Camera | J53: 1 | K53: pc | L53: 39998 | M53: =SUM(J53*L53) -> 39998 | O53: =SUM(J53*N53) -> 0 | P53: to be used by the Builder's Board of Editors for students activities and during competitions,photojournalism in particular (charge to the student publication fund) | Q53: Publication | X53: SS04 | Z53: FAILED | AA53: quotation exceeded the budget | AC53: 5 RFQ's
A54: 2025 | B54: May | C54: KURT G. HOSTALLERO | D54: Quality Assurance Officer II | E54: 162 | F54: MOOE | G54: 2025-189 | H54: SVP | I54: GI Plain Sheet (0.5mm) | J54: 4 | K54: pcs | L54: 650 | M54: =SUM(J54*L54) -> 2600 | N54: 700 | O54: =SUM(J54*N54) -> 2800 | P54: to be used in repairing the doors of BSC Dormitory | Q54: CBAO-Dorm | R54: May 30, 2025 | S54: June 3, 2025 | T54: June 4, 2025 | U54: June 19 & July 8, 2025 | V54: FVA Trading | W54: June 19 & July 8, 2025 | X54: 1006C | Y54: September 1, 2025 | Z54: complete | AA54: for payment-Acctg. | AB54: 05-02-2025-06-0050 | AC54: 4 RFQ's | AD54: 2951/
A55: 2025 | B55: May | C55: KURT G. HOSTALLERO | D55: Quality Assurance Officer II | E55: 162 | F55: MOOE | G55: 2025-189 | H55: SVP | I55: Palochina (2" x 4" x 12ft) | J55: 4 | K55: pcs | L55: 700 | M55: =SUM(J55*L55) -> 2800 | N55: 495 | O55: =SUM(J55*N55) -> 1980 | P55: to be used in repairing the doors of BSC Dormitory | Q55: CBAO-Dorm | R55: May 30, 2025 | S55: June 3, 2025 | T55: June 4, 2025 | U55: June 19 & July 8, 2025 | V55: FVA Trading | W55: June 19 & July 8, 2025 | X55: 1006C | Y55: September 1, 2025 | Z55: complete | AA55: for payment-Acctg. | AB55: 05-02-2025-06-0050
A56: 2025 | B56: May | C56: KURT G. HOSTALLERO | D56: Quality Assurance Officer II | E56: 162 | F56: MOOE | G56: 2025-189 | H56: SVP | I56: Rough Lumber (2" x 4" x 12ft) | J56: 4 | K56: pcs | L56: 850 | M56: =SUM(J56*L56) -> 3400 | N56: 510 | O56: =SUM(J56*N56) -> 2040 | P56: to be used in repairing the doors of BSC Dormitory | Q56: CBAO-Dorm | R56: May 30, 2025 | S56: June 3, 2025 | T56: June 4, 2025 | U56: June 19 & July 8, 2025 | V56: FVA Trading | W56: June 19 & July 8, 2025 | X56: 1006C | Y56: September 1, 2025 | Z56: complete | AA56: for payment-Acctg. | AB56: 05-02-2025-06-0050
A57: 2025 | B57: May | C57: KURT G. HOSTALLERO | D57: Quality Assurance Officer II | E57: 162 | F57: MOOE | G57: 2025-189 | H57: SVP | I57: Stainless Hinges (3") | J57: 4 | K57: sets | L57: 450 | M57: =SUM(J57*L57) -> 1800 | N57: 200 | O57: =SUM(J57*N57) -> 800 | P57: to be used in repairing the doors of BSC Dormitory | Q57: CBAO-Dorm | R57: May 30, 2025 | S57: June 3, 2025 | T57: June 4, 2025 | U57: June 19 & July 8, 2025 | V57: FVA Trading | W57: June 19 & July 8, 2025 | X57: 1006C | Y57: September 1, 2025 | Z57: complete | AA57: for payment-Acctg. | AB57: 05-02-2025-06-0050
A58: 2025 | B58: May | C58: KURT G. HOSTALLERO | D58: Quality Assurance Officer II | E58: 162 | F58: MOOE | G58: 2025-189 | H58: SVP | I58: Sand | J58: 4 | K58: bags | L58: 150 | M58: =SUM(J58*L58) -> 600 | N58: 240 | O58: =SUM(J58*N58) -> 960 | P58: to be used in repairing the doors of BSC Dormitory | Q58: CBAO-Dorm | R58: May 30, 2025 | S58: June 3, 2025 | T58: June 4, 2025 | U58: June 19 & July 8, 2025 | V58: FVA Trading | W58: June 19 & July 8, 2025 | X58: 1006C | Y58: September 1, 2025 | Z58: complete | AA58: for payment-Acctg. | AB58: 05-02-2025-06-0050
A59: 2025 | B59: May | C59: KURT G. HOSTALLERO | D59: Quality Assurance Officer II | E59: 162 | F59: MOOE | G59: 2025-189 | H59: SVP | I59: Cement | J59: 1 | K59: bags | L59: 375 | M59: =SUM(J59*L59) -> 375 | N59: 380 | O59: =SUM(J59*N59) -> 380 | P59: to be used in repairing the doors of BSC Dormitory | Q59: CBAO-Dorm | R59: May 30, 2025 | S59: June 3, 2025 | T59: June 4, 2025 | U59: June 19 & July 8, 2025 | V59: FVA Trading | W59: June 19 & July 8, 2025 | X59: 1006C | Y59: September 1, 2025 | Z59: complete | AA59: for payment-Acctg. | AB59: 05-02-2025-06-0050
A60: 2025 | B60: May | C60: JOHN MICHAEL A. VILLASPIR | D60: Administrative Officer I | E60: 101 | G60: 2025-190 | H60: SVP | I60: Single Face P4 HD Outdoor LED Screen (rear maintenance), Full Set Up including controller (Novastar) & receiving card (Novastar) warranty, after sales support & training controller (novastar) & receiving card (novastar)warranty , after sales support & training size: 2.88M x 2.88M (9 panels) screen resolution; 720 pixels (W) x 720 pixels (H) Type; movable frame Accessories: replacement module , replacemenr power supply,replacement receiving card,power cable,signal cable FREE: LED control software Training and Support | J60: 1 | K60: set | L60: 650000 | M60: =SUM(J60*L60) -> 650000 | N60: 640000 | O60: =SUM(J60*N60) -> 640000 | P60: for program/projects/activities of information Technology Unit charged to cost to operate of admin. Bldg. | Q60: ITU | R60: June 4, 2025 | S60: June 9, 2025 | T60: June 9, 2025 | V60: Wavetech Billboard and Outdoor Advertising Services | X60: GAS5 | Z60: CANCELLED | AA60: due to unforeseen issues encountered with suppliers supplier | AB60: 06-101101-2025-06-00376 | AC60: 3 RFQ's + 1blank
A61: 2025 | B61: May | C61: RENELYN D. KILLASE | D61: College Librarian | G61: 2025-191 | H61: SVP | I61: Biotechnology and Society (2nd Edition), Yoshinaka, 2024, 9781984688989, Wiseman's Book Trading, Inc. | J61: 1 | K61: copy | L61: 5998 | M61: =SUM(J61*L61) -> 5998 | O61: =SUM(J61*N61) -> 0 | P61: `the list of books titles have been carefully selected by the program chairpersons to enhance the learning resources | Q61: Library | X61: SS010 | Z61: CANCELLED | AA61: revised PR divided into 3 PR w/ diff. Fund charge
A62: 2025 | B62: May | C62: RENELYN D. KILLASE | D62: College Librarian | G62: 2025-191 | H62: SVP | I62: Plant Taxonomy (2nd Edition) (with Access code), Saxiano, 2024, 9781984688873, Wiseman's Book Trading, Inc. | J62: 1 | K62: copy | L62: 5998 | M62: =SUM(J62*L62) -> 5998 | O62: =SUM(J62*N62) -> 0 | P62: `the list of books titles have been carefully selected by the program chairpersons to enhance the learning resources | Q62: Library | X62: SS010
A63: 2025 | B63: May | C63: RENELYN D. KILLASE | D63: College Librarian | G63: 2025-191 | H63: SVP | I63: Sustainable Farming: Nurturing the Earth for Future Generations, Kushwaha, 2024, 9781774699515, Wiseman's Book Trading, Inc. | J63: 1 | K63: copy | L63: 6998 | M63: =SUM(J63*L63) -> 6998 | O63: =SUM(J63*N63) -> 0 | P63: `the list of books titles have been carefully selected by the program chairpersons to enhance the learning resources | Q63: Library | X63: SS010
A64: 2025 | B64: May | C64: RENELYN D. KILLASE | D64: College Librarian | G64: 2025-191 | H64: SVP | I64: Agroforestry and Climate Change, Kauffeld, 2023, 9781682508428, Wiseman's Book Trading, Inc. | J64: 1 | K64: copy | L64: 4998 | M64: =SUM(J64*L64) -> 4998 | O64: =SUM(J64*N64) -> 0 | P64: `the list of books titles have been carefully selected by the program chairpersons to enhance the learning resources | Q64: Library | X64: SS010
A65: 2025 | B65: May | C65: RENELYN D. KILLASE | D65: College Librarian | G65: 2025-191 | H65: SVP | I65: Current Trends in Agriculture, Chauhan, 2023, 9789388854825, Wiseman's Book Trading, Inc. | J65: 1 | K65: copy | L65: 4998 | M65: =SUM(J65*L65) -> 4998 | O65: =SUM(J65*N65) -> 0 | P65: `the list of books titles have been carefully selected by the program chairpersons to enhance the learning resources | Q65: Library | X65: SS010
A66: 2025 | B66: May | C66: RENELYN D. KILLASE | D66: College Librarian | G66: 2025-191 | H66: SVP | I66: Principles of Animal Nutrition, Srivastava, 2023, 9788119205196, Wiseman's Book Trading, Inc. | J66: 1 | K66: copy | L66: 4998 | M66: =SUM(J66*L66) -> 4998 | O66: =SUM(J66*N66) -> 0 | P66: `the list of books titles have been carefully selected by the program chairpersons to enhance the learning resources | Q66: Library | X66: SS010
A67: 2025 | B67: May | C67: RENELYN D. KILLASE | D67: College Librarian | G67: 2025-191 | H67: SVP | I67: The Genetic Manipulation in Plants, Singh, 2023, 9789394137646, Wiseman's Book Trading, Inc. | J67: 1 | K67: copy | L67: 4998 | M67: =SUM(J67*L67) -> 4998 | O67: =SUM(J67*N67) -> 0 | P67: `the list of books titles have been carefully selected by the program chairpersons to enhance the learning resources | Q67: Library | X67: SS010
A68: 2025 | B68: May | C68: RENELYN D. KILLASE | D68: College Librarian | G68: 2025-191 | H68: SVP | I68: Environment and Society (2nd Edition), Ohdan, 2024, 9781984688958, Wiseman's Book Trading, Inc. | J68: 1 | K68: copy | L68: 5998 | M68: =SUM(J68*L68) -> 5998 | O68: =SUM(J68*N68) -> 0 | P68: `the list of books titles have been carefully selected by the program chairpersons to enhance the learning resources | Q68: Library | X68: SS010
A69: 2025 | B69: May | C69: RENELYN D. KILLASE | D69: College Librarian | G69: 2025-191 | H69: SVP | I69: Biodiversity ,Environment & Ecosystem Services, Arya, 2023, 9788195916931, Wiseman's Book Trading, Inc. | J69: 1 | K69: copy | L69: 4998 | M69: =SUM(J69*L69) -> 4998 | O69: =SUM(J69*N69) -> 0 | P69: `the list of books titles have been carefully selected by the program chairpersons to enhance the learning resources | Q69: Library | X69: SS010
A70: 2025 | B70: May | C70: RENELYN D. KILLASE | D70: College Librarian | G70: 2025-191 | H70: SVP | I70: Climate Impacts on Sustainable Natural Resource Management, Trognon, 2023, 9781682508411, Wiseman's Book Trading, Inc. | J70: 1 | K70: copy | L70: 4998 | M70: =SUM(J70*L70) -> 4998 | O70: =SUM(J70*N70) -> 0 | P70: `the list of books titles have been carefully selected by the program chairpersons to enhance the learning resources | Q70: Library | X70: SS010
A71: 2025 | B71: May | C71: RENELYN D. KILLASE | D71: College Librarian | G71: 2025-191 | H71: SVP | I71: Agritourism, Sznajder, 2009, 978-1845934828, Big Faith Trading | J71: 1 | K71: copy | L71: 8653 | M71: =SUM(J71*L71) -> 8653 | O71: =SUM(J71*N71) -> 0 | P71: `the list of books titles have been carefully selected by the program chairpersons to enhance the learning resources | Q71: Library | X71: SS010
A72: 2025 | C72: RENELYN D. KILLASE | D72: College Librarian | G72: 2025-191 | H72: SVP | I72: Child growth and development, Matthews, 2024, 9798886263572, Wiseman's Book Trading, Inc. | J72: 1 | K72: copy | L72: 6998 | M72: =SUM(J72*L72) -> 6998 | O72: =SUM(J72*N72) -> 0 | P72: `the list of books titles have been carefully selected by the program chairpersons to enhance the learning resources | Q72: Library | X72: SS010
A73: 2025 | B73: May | C73: RENELYN D. KILLASE | D73: College Librarian | G73: 2025-191 | H73: SVP | I73: School and Peer Contexts of Bullying: An Introduction and Exploration, Ramirez, 2024, 9781774698792, Wiseman's Book Trading, Inc. | J73: 1 | K73: copy | L73: 6998 | M73: =SUM(J73*L73) -> 6998 | O73: =SUM(J73*N73) -> 0 | P73: `the list of books titles have been carefully selected by the program chairpersons to enhance the learning resources | Q73: Library | X73: SS010
A74: 2025 | B74: May | C74: RENELYN D. KILLASE | D74: College Librarian | G74: 2025-191 | H74: SVP | I74: Creative Writing, Paulose, 2023, 9788196050184, Wiseman's Book Trading, Inc. | J74: 1 | K74: copy | L74: 4998 | M74: =SUM(J74*L74) -> 4998 | O74: =SUM(J74*N74) -> 0 | P74: `the list of books titles have been carefully selected by the program chairpersons to enhance the learning resources | Q74: Library | X74: SS010
A75: 2025 | B75: May | C75: RENELYN D. KILLASE | D75: College Librarian | G75: 2025-191 | H75: SVP | I75: Design and Implement the Curriculum to Foster Children's Learning and Development, 3G E-Leraning, 2022, Wiseman's Book Trading, Inc. | J75: 1 | K75: copy | L75: 4998 | M75: =SUM(J75*L75) -> 4998 | O75: =SUM(J75*N75) -> 0 | P75: `the list of books titles have been carefully selected by the program chairpersons to enhance the learning resources | Q75: Library | X75: SS010
A76: 2025 | B76: May | C76: RENELYN D. KILLASE | D76: College Librarian | G76: 2025-191 | H76: SVP | I76: Designing of Applied Qualitative Research, Davies, 2024, 9781984658661, Wiseman's Book Trading, Inc. | J76: 1 | K76: copy | L76: 6998 | M76: =SUM(J76*L76) -> 6998 | O76: =SUM(J76*N76) -> 0 | P76: `the list of books titles have been carefully selected by the program chairpersons to enhance the learning resources | Q76: Library | X76: SS010
A77: 2025 | B77: May | C77: RENELYN D. KILLASE | D77: College Librarian | G77: 2025-191 | H77: SVP | I77: Encyclopedia of Earth Science, Malode, 2024, 9781774693902, Wiseman's Book Trading, Inc. | J77: 1 | K77: copy | L77: 6998 | M77: =SUM(J77*L77) -> 6998 | O77: =SUM(J77*N77) -> 0 | P77: `the list of books titles have been carefully selected by the program chairpersons to enhance the learning resources | Q77: Library | X77: SS010
A78: 2025 | B78: May | C78: RENELYN D. KILLASE | D78: College Librarian | G78: 2025-191 | H78: SVP | I78: Assessment in learning 1 (Traditional Assessment) OBE Approach, Abrogena, 2024, Big Faith Trading | J78: 1 | K78: copy | L78: 640 | M78: =SUM(J78*L78) -> 640 | O78: =SUM(J78*N78) -> 0 | P78: `the list of books titles have been carefully selected by the program chairpersons to enhance the learning resources | Q78: Library | X78: SS010
A79: 2025 | B79: May | C79: RENELYN D. KILLASE | D79: College Librarian | G79: 2025-191 | H79: SVP | I79: Assessment Learning 1 : A Modular Approach, 2ed, Boholano, 2023, Big Faith Trading | J79: 1 | K79: copy | L79: 880 | M79: =SUM(J79*L79) -> 880 | O79: =SUM(J79*N79) -> 0 | P79: `the list of books titles have been carefully selected by the program chairpersons to enhance the learning resources | Q79: Library | X79: SS010
A80: 2025 | B80: May | C80: RENELYN D. KILLASE | D80: College Librarian | G80: 2025-191 | H80: SVP | I80: Assessment Learning 2 : A Modular Approach, Sanchez, 2023, Big Faith Trading | J80: 1 | K80: copy | L80: 825 | M80: =SUM(J80*L80) -> 825 | O80: =SUM(J80*N80) -> 0 | P80: `the list of books titles have been carefully selected by the program chairpersons to enhance the learning resources | Q80: Library | X80: SS010
A81: 2025 | B81: May | C81: RENELYN D. KILLASE | D81: College Librarian | G81: 2025-191 | H81: SVP | I81: Assessment of Learning 1 Obe Approach, Manas, 2024, Big Faith Trading | J81: 1 | K81: copy | L81: 440 | M81: =SUM(J81*L81) -> 440 | O81: =SUM(J81*N81) -> 0 | P81: `the list of books titles have been carefully selected by the program chairpersons to enhance the learning resources | Q81: Library | X81: SS010
A82: 2025 | B82: May | C82: RENELYN D. KILLASE | D82: College Librarian | G82: 2025-191 | H82: SVP | I82: Building and enhancing New Literacies Across the Curriculum OBE-& PPST-based, De Leon, 2020, Big Faith Trading | J82: 1 | K82: copy | L82: 650 | M82: =SUM(J82*L82) -> 650 | O82: =SUM(J82*N82) -> 0 | P82: `the list of books titles have been carefully selected by the program chairpersons to enhance the learning resources | Q82: Library | X82: SS010
A83: 2025 | B83: May | C83: RENELYN D. KILLASE | D83: College Librarian | G83: 2025-191 | H83: SVP | I83: Facilitating Learner-Centered Teaching 5e OBE-&PPST-Based, Lucas & Corpuz, 2020, Big Faith Trading | J83: 1 | K83: copy | L83: 620 | M83: =SUM(J83*L83) -> 620 | O83: =SUM(J83*N83) -> 0 | P83: `the list of books titles have been carefully selected by the program chairpersons to enhance the learning resources | Q83: Library | X83: SS010
A84: 2025 | B84: May | C84: RENELYN D. KILLASE | D84: College Librarian | G84: 2025-191 | H84: SVP | I84: Facilitating Student-Centered Teaching & Learning, Larioque, et al., 2024, Big Faith Trading | J84: 1 | K84: copy | L84: 760 | M84: =SUM(J84*L84) -> 760 | O84: =SUM(J84*N84) -> 0 | P84: `the list of books titles have been carefully selected by the program chairpersons to enhance the learning resources | Q84: Library | X84: SS010
... A130: 2025 | B130: May | C130: RENELYN D. KILLASE | D130: College Librarian | G130: 2025-191 | H130: SVP | I130: Competitive advantages of service quality in hospitality, tourism, and leisure services, Kalacas, 2024, 9781774698884, Wiseman's Books Trading | J130: 1 | K130: copy | L130: 6998 | M130: =SUM(J130*L130) -> 6998 | O130: =SUM(J130*N130) -> 0 | P130: `the list of books titles have been carefully selected by the program chairpersons to enhance the learning resources | Q130: Library | X130: SS010
A131: 2025 | B131: May | C131: RENELYN D. KILLASE | D131: College Librarian | G131: 2025-191 | H131: SVP | I131: Strategic management for tourism, hospitality & events (4th ed.), Evans, 2024, 9781032331836, Forefront Book | J131: 1 | K131: copy | L131: 7312 | M131: =SUM(J131*L131) -> 7312 | P131: `the list of books titles have been carefully selected by the program chairpersons to enhance the learning resources | Q131: Library | X131: SS010
A132: 2025 | B132: May | C132: RENELYN D. KILLASE | D132: College Librarian | G132: 2025-191 | H132: SVP | I132: Transforming leisure in the pandemic: re-imagining interaction and activity during crisis, Sharp, 2024, 9781032201580, Forefront Book | J132: 1 | K132: copy | L132: 3736 | M132: =SUM(J132*L132) -> 3736 | P132: `the list of books titles have been carefully selected by the program chairpersons to enhance the learning resources | Q132: Library | X132: SS010
A133: 2025 | B133: May | C133: RENELYN D. KILLASE | D133: College Librarian | G133: 2025-191 | H133: SVP | I133: Food and wine tourism (2nd ed.) with DVD, 3G, 2023, 978198469536, Forefront Book | J133: 1 | K133: copy | L133: 4992 | M133: =SUM(J133*L133) -> 4992 | O133: =SUM(J133*N133) -> 0 | P133: `the list of books titles have been carefully selected by the program chairpersons to enhance the learning resources | Q133: Library | X133: SS010
A134: 2025 | B134: May | C134: RENELYN D. KILLASE | D134: College Librarian | G134: 2025-191 | H134: SVP | I134: Cases for event management and event tourism, Getz, 2023, 9781915097347, Forefront Book | J134: 1 | K134: copy | L134: 11415 | M134: =SUM(J134*L134) -> 11415 | O134: =SUM(J134*N134) -> 0 | P134: `the list of books titles have been carefully selected by the program chairpersons to enhance the learning resources | Q134: Library | X134: SS010
A135: 2025 | B135: May | C135: RENELYN D. KILLASE | D135: College Librarian | G135: 2025-191 | H135: SVP | I135: Community based tourism, Juyal, 2024, 9781774697153, Forefront Book | J135: 1 | K135: copy | L135: 4680 | M135: =SUM(J135*L135) -> 4680 | O135: =SUM(J135*N135) -> 0 | P135: `the list of books titles have been carefully selected by the program chairpersons to enhance the learning resources | Q135: Library | X135: SS010
A136: 2025 | B136: May | C136: RENELYN D. KILLASE | D136: College Librarian | G136: 2025-191 | H136: SVP | I136: Electronics All-in-One For Dummies, 3rd edition, Lowe, 2022, 978-1119822110, https://www.amazon.com | J136: 1 | K136: copy | L136: 1420 | M136: =SUM(J136*L136) -> 1420 | O136: =SUM(J136*N136) -> 0 | P136: `the list of books titles have been carefully selected by the program chairpersons to enhance the learning resources | Q136: Library | X136: SS010
A137: 2025 | B137: May | C137: RENELYN D. KILLASE | D137: College Librarian | G137: 2025-191 | H137: SVP | I137: Practical Electronics for Inventors, 4th Edition, Scherz & Monk, 2016, 9.78126E+12, https://www.amazon.com | J137: 1 | K137: copy | L137: 1370 | M137: =SUM(J137*L137) -> 1370 | O137: =SUM(J137*N137) -> 0 | P137: `the list of books titles have been carefully selected by the program chairpersons to enhance the learning resources | Q137: Library | X137: SS010
A138: 2025 | B138: May | C138: RENELYN D. KILLASE | D138: College Librarian | G138: 2025-191 | H138: SVP | I138: Make: Electronics: Learning by Discovery: A hands-on primer for the new electronics enthusiast 3rd Edition, Platt, 2021, 978-1680456875, https://www.amazon.com | J138: 1 | K138: copy | L138: 1050 | M138: =SUM(J138*L138) -> 1050 | O138: =SUM(J138*N138) -> 0 | P138: `the list of books titles have been carefully selected by the program chairpersons to enhance the learning resources | Q138: Library | X138: SS010
A139: 2025 | B139: May | C139: RENELYN D. KILLASE | D139: College Librarian | G139: 2025-191 | H139: SVP | I139: Electronic Devices and Curcuits Theory, Boylestad & Nashelsky, latest ed., https://www.amazon.com | J139: 1 | K139: copy | L139: 5640 | M139: =SUM(J139*L139) -> 5640 | O139: =SUM(J139*N139) -> 0 | P139: `the list of books titles have been carefully selected by the program chairpersons to enhance the learning resources | Q139: Library | X139: SS010
A140: 2025 | B140: May | C140: RENELYN D. KILLASE | D140: College Librarian | G140: 2025-191 | H140: SVP | I140: Digital Fundamentals, Floyd, latest ed., https://www.amazon.com/Digital-Fundamentals-11th-Thomas-Floyd/dp/0132737965 | J140: 1 | K140: copy | L140: 1779 | M140: =SUM(J140*L140) -> 1779 | O140: =SUM(J140*N140) -> 0 | P140: `the list of books titles have been carefully selected by the program chairpersons to enhance the learning resources | Q140: Library | X140: SS010
A141: 2025 | B141: May | C141: RENELYN D. KILLASE | D141: College Librarian | G141: 2025-191 | H141: SVP | I141: Microelectronics circuits, Sedra & Smith, latest ed., https://www.amazon.com/Microelectronic-Circuits-Electrical-Computer-Engineering/dp/0195323033 | J141: 1 | K141: copy | L141: 2328 | M141: =SUM(J141*L141) -> 2328 | O141: =SUM(J141*N141) -> 0 | P141: `the list of books titles have been carefully selected by the program chairpersons to enhance the learning resources | Q141: Library | X141: SS010
A142: 2025 | B142: May | C142: RENELYN D. KILLASE | D142: College Librarian | G142: 2025-191 | H142: SVP | I142: The art of electronics, Horowitz & Hill, latest ed., https://www.amazon.com/Art-Electronics-Paul-Horowitz/dp/0521809266 | J142: 1 | K142: copy | L142: 4229 | M142: =SUM(J142*L142) -> 4229 | O142: =SUM(J142*N142) -> 0 | P142: `the list of books titles have been carefully selected by the program chairpersons to enhance the learning resources | Q142: Library | X142: SS010
A143: 2025 | B143: May | C143: RENELYN D. KILLASE | D143: College Librarian | G143: 2025-191 | H143: SVP | I143: Insustrial electronics, Rehg & Sartori, latest ed., https://www.amazon.com/Industrial-Electronics-James-Rehg/dp/0132064189 | J143: 1 | K143: copy | L143: 10436 | M143: =SUM(J143*L143) -> 10436 | O143: =SUM(J143*N143) -> 0 | P143: `the list of books titles have been carefully selected by the program chairpersons to enhance the learning resources | Q143: Library | X143: SS010
A144: 2025 | B144: May | C144: RENELYN D. KILLASE | D144: College Librarian | G144: 2025-191 | H144: SVP | I144: Basic Electronics: Theory and Practice by Sean Westcott and Jean Riescher Westcott, 2023, 978-1683929581, amazon.com | J144: 1 | K144: copy | L144: 2895.71 | M144: =SUM(J144*L144) -> 2895.71 | O144: =SUM(J144*N144) -> 0 | P144: the list of book titles have been carefully selected by the program chairpersons to entrance the learning resources | Q144: Library | X144: SS010
A145: 2025 | B145: May | C145: DOREEN C. CASTILLO | D145: BAC Chairperson | E145: 101 | G145: 2025-192 | H145: SVP | I145: BT5000 (Yellow,Cyan,Magenta),BTD60 Black | J145: 3 | K145: set | L145: 2800 | M145: =SUM(J145*L145) -> 8400 | N145: 2050 | O145: =SUM(J145*N145) -> 6150 | P145: for office use | Q145: BAC | R145: May 22, 2025 | S145: June 3, 2025 | T145: June 4, 2025 | U145: June 17, 2025 | V145: YCA Office Supplies & Equipment | W145: June 17, 2025 | X145: GAS22 | Y145: July 2, 2025 | Z145: complete | AA145: for payment-Acctg. | AB145: 02-101101-2025-06-00362 | AC145: 5 RFQ's | AD145: 222/06/17/2025
...

Sheet PR
A7: PURCHASE REQUEST
D9: PR No. | E9: =DATA!G60 -> 2025-190 | F9: Date
A10: Department: | D10: SAI No.: | E10: .
A11: Section: | B11: =DATA!X60 -> GAS5 | D11: OBR#
A12: Ref. No.: | B12: 2505-GAS5-190
A14: Qty | B14: Unit of Issue | D14: Item Description | F14: Stock No. | G14: Estimated
G15: Unit Cost | H15: Total Cost
A16: =DATA!J60 -> 1 | B16: =DATA!K60 -> set | D16: =DATA!I60 -> Single Face P4 HD Outdoor LED Screen (rear maintenance), Full Set Up including controller (Novastar) & receiving card (Novastar) warranty, after sales support & training controller (novastar) & receiving card (novastar)warranty , after sales support & training size: 2.88M x 2.88M (9 panels) screen resolution; 720 pixels (W) x 720 pixels (H) Type; movable frame Accessories: replacement module , replacemenr power supply,replacement receiving card,power cable,signal cable FREE: LED control software Training and Support | G16: =DATA!L60 -> 650000 | H16: =SUM(A16*G16) -> 650000
H17: =SUM(A17*G17) -> 0
H18: =SUM(A18*G18) -> 0
H19: =SUM(A19*G19) -> 0
H20: =SUM(A20*G20) -> 0
H21: =SUM(A21*G21) -> 0
H22: =SUM(A22*G22) -> 0
H23: =SUM(A23*G23) -> 0
H24: =SUM(A24*G24) -> 0
H25: =SUM(A25*G25) -> 0
H26: =SUM(A26*G26) -> 0
H27: =SUM(A27*G27) -> 0
H28: =SUM(A28*G28) -> 0
H29: =SUM(A29*G29) -> 0
A30: =DATA!J252 -> 1 | B30: =DATA!K252 -> copy | D30: =DATA!I252 -> Design and Implement the Curriculum to Foster Children's Learning and Development, 3G E-Leraning, 2022, Wiseman's Book Trading, Inc. | G30: =DATA!L252 -> 4998 | H30: =SUM(A30*G30) -> 4998
A31: =DATA!J253 -> 1 | B31: =DATA!K253 -> copy | D31: =DATA!I253 -> Designing of Applied Qualitative Research, Davies, 2024, 9781984658661, Wiseman's Book Trading, Inc. | G31: =DATA!L253 -> 6998 | H31: =SUM(A31*G31) -> 6998
A32: =DATA!J254 -> 1 | B32: =DATA!K254 -> copy | D32: =DATA!I254 -> Encyclopedia of Earth Science, Malode, 2024, 9781774693902, Wiseman's Book Trading, Inc. | G32: =DATA!L254 -> 6998 | H32: =SUM(A32*G32) -> 6998
A33: =DATA!J255 -> 1 | B33: =DATA!K255 -> copy | D33: =DATA!I255 -> Assessment in learning 1 (Traditional Assessment) OBE Approach, Abrogena, 2024, Big Faith Trading | G33: =DATA!L255 -> 640 | H33: =SUM(A33*G33) -> 640
A34: =DATA!J256 -> 1 | B34: =DATA!K256 -> copy | D34: =DATA!I256 -> Assessment Learning 1 : A Modular Approach, 2ed, Boholano, 2023, Big Faith Trading | G34: =DATA!L256 -> 880 | H34: =SUM(A34*G34) -> 880
A35: =DATA!J257 -> 1 | B35: =DATA!K257 -> copy | D35: =DATA!I257 -> Assessment Learning 2 : A Modular Approach, Sanchez, 2023, Big Faith Trading | G35: =DATA!L257 -> 825 | H35: =SUM(A35*G35) -> 825
A36: =DATA!J258 -> 1 | B36: =DATA!K258 -> copy | D36: =DATA!I258 -> Assessment of Learning 1 Obe Approach, Manas, 2024, Big Faith Trading | G36: =DATA!L258 -> 440 | H36: =SUM(A36*G36) -> 440
A37: =DATA!J259 -> 1 | B37: =DATA!K259 -> copy | D37: =DATA!I259 -> Building and enhancing New Literacies Across the Curriculum OBE-& PPST-based, De Leon, 2020, Big Faith Trading | G37: =DATA!L259 -> 650 | H37: =SUM(A37*G37) -> 650
A38: =DATA!J260 -> 1 | B38: =DATA!K260 -> copy | D38: =DATA!I260 -> Facilitating Learner-Centered Teaching 5e OBE-&PPST-Based, Lucas & Corpuz, 2020, Big Faith Trading | G38: =DATA!L260 -> 620 | H38: =SUM(A38*G38) -> 620
A39: =DATA!J261 -> 1 | B39: =DATA!K261 -> copy | D39: =DATA!I261 -> Facilitating Student-Centered Teaching & Learning, Larioque, et al., 2024, Big Faith Trading | G39: =DATA!L261 -> 760 | H39: =SUM(A39*G39) -> 760
A40: =DATA!J262 -> 1 | B40: =DATA!K262 -> copy | D40: =DATA!I262 -> Field Study 2, Boholano, et al, 2022, Big Faith Trading | G40: =DATA!L262 -> 825 | H40: =SUM(A40*G40) -> 825
A41: =DATA!J263 -> 1 | B41: =DATA!K263 -> copy | D41: =DATA!I263 -> Field Study 2 Participation and Teaching Assistanship OBE- & PPST, Lucas, et al., 2021, Big Faith Trading | G41: =DATA!L263 -> 670 | H41: =SUM(A41*G41) -> 670
... A67: =DATA!J289 -> 1 | B67: =DATA!K289 -> copy | D67: =DATA!I289 -> Environmental Geology \5ed., Reichard, Jim, 2024, 9781266132261, Forefront Book | G67: =DATA!L289 -> 5393 | H67: =SUM(A67*G67) -> 5393
H68: =SUM(H16:H21) -> 650000
A69: Purpose: | B69: =DATA!P60 -> for program/projects/activities of information Technology Unit charged to cost to operate of admin. Bldg.
F70: Approved By:
A72: Signature:
A73: Printed Name: | B73: =DATA!C60 -> JOHN MICHAEL A. VILLASPIR | F73: DJOVI REGALA DURANTE,DPA
A74: Designation: | B74: =DATA!D60 -> Administrative Officer I | F74: SUC President I
A75: Date:

Sheet ResoSVP
A5: BAC Resolution Recommending Alternative Mode of Procurement under Small Value Procurement
B7: BAC Resolution No. | D7: =AResoSVP!D6 -> 2505-GAS5-190
A9: WHEREAS, Section 48 Rule XVI of the Revised Implementing Rules and Regulations of RA 9184 allows Alternative Mode of Procurement subject to prior approval of the HOPE thru Annual Procurement Plan (APP) and only to promote economy and efficiency;
A10: WHEREAS, Section 53.9 allows Small Value Procurement provided that the procurement does not fall under shopping in Section 52 of this IRR and the amount involved does not exceed the thresholds prescribed in Annex "H" of this IRR;
A11: WHEREAS, Appendix 18, Section 3.e on the Guidelines for Shopping and Small Value Procurement provides an Abstract of Quotations shall be prepared setting forth the names of those who responded to the RFQ's right after the deadline for submission except for shopping under Section 52.1(b), where at least three (3) price quotations (RFQ) must be obtained;
A12: WHEREAS, Annex "H" of the Consolidated Guidelines for the Alternative Methods of Procurement prescribed under Section V, Paragraph D.8.b.ii that the BAC shall prepare and send the RFQs/RFPs to at least three (3) suppliers, contractors or consultants of known qualifications where receipt of at least one (1) quotations is sufficient to proceed with the evaluation thererof;
A13: WHEREAS, Purchase Request No. | D13: =AResoSVP!D12 -> 2025-190 | E13: involves the procurement of
A14: 4 Layered Steel Filling Cabinet with central lock--to ensure proper organization and secure storage of CBAO documents
A15: with the approved budget of | D15: =AResoSVP!D14 -> 650000
A16: WHEREAS, the default mode of evaluation shall be on a lot basis which means that the determination of the single/lowest calculated and responsive bid (S/LCRB) is the total amount of offered unit price multiply by the required quantity;
A18: NOW THEREFORE, we, the members of the Bids and Awards Committee hereby RESOLVE as it is hereby RESOLVED to recommend to the College President to adopt Alternative Mode of Procurement under Small Value Procurement for the said transaction;
A20: RESOLVED FINALLY, at the Batanes State College, this
A21: Recommending Approval:
A24: RHOUPHELINE AYA A.. CADIZ | C24: FORTUNATO PHILIP A. CABUGAO | E24: EMILYN D. ALUETA
A25: BAC Member | C25: BAC Member | E25: BAC Member
A28: =PR!B73 -> JOHN MICHAEL A. VILLASPIR | C28: PHILIP ULYSSES T. CASTILLO | E28: DOREEN C. CASTILLO
A29: End-User/Provisional Member | C29: BAC Vice Chairperson | E29: BAC Chairperson

Sheet AResoSVP
A4: Approval of BAC Resolution Recommending Alternative Mode of Procurement under Small Value Procurement
B6: BAC Resolution No. | D6: =PR!B12 -> 2505-GAS5-190
A8: WHEREAS, Section 48 Rule XVI of the Revised Implementing Rules and Regulations of RA 9184 allows Alternative Mode of Procurement subject to prior approval of the HOPE thru Annual Procurement Plan (APP) and only to promote economy and efficiency;
A9: WHEREAS, Section 53.9 allows Small Value Procurement provided that the procurement does not fall under shopping in Section 52 of this IRR and the amount involved does not exceed the thresholds prescribed in Annex "H" of this IRR;
A10: WHEREAS, Appendix 18, Section 3.e on the Guidelines for Shopping and Small Value Procurement provides an Abstract of Quotations shall be prepared setting forth the names of those who responded to the RFQ's right after the deadline for submission except for shopping under Section 52.1(b), where at least three (3) price quotations (RFQ) must be obtained;
A11: WHEREAS, Annex "H" of the Consolidated Guidelines for the Alternative Methods of Procurement prescribed under Section V, Paragraph D.8.b.ii that the BAC shall prepare and send the RFQs/RFPs to at least three (3) suppliers, contractors or consultants of known qualifications where receipt of at least one (1) quotations is sufficient to proceed with the evaluation thererof;
A12: WHEREAS, Purchase Request No. | D12: =PR!E9 -> 2025-190 | E12: involves the procurement of
A13: 4 Layered Steel Filling Cabinet with central lock--to ensure proper organization and secure storage of CBAO documents | H13: Items:
A14: with the approved budget of | D14: =PR!H68 -> 650000
A15: WHEREAS, the default mode of evaluation shall be on a lot basis which means that the determination of the single/lowest calculated and responsive bid (S/LCRB) is the total amount of offered unit price multiply by the required quantity;
A16: NOW THEREFORE, I,DR.DJOVI R. DURANTE, Head of the Procuring Entity (HOPE) by virtue of the authority vested in me by the Board of Trustees of this Institution and after taking into consideration the merits and legal bases of the recommendation of the members of the Bids and Awards Committee (BAC) do hereby APPROVE the foregoing recommendation and adoption of Alternative Mode of Procurement under Small Value Procurement;
A18: APPROVED FINALLY, at the Batanes State College, this | F18: ___________________
A22: DJOVI REGALA DURANTE,DPA
A23: SUC President I
A30: BRYAN H. CIELO
A85: EMILYN D. ALUETA
A86: EMILYN D. ALUETA

Sheet RFQ_
E1: Date: | F1: =NOW() -> 46148.737
A2: REQUEST FOR PRICE QUOTATION
A3: FVA Trading
A4: Please give us your best and final price offer for the item/s listed below, have this signed and submit this by you or by your duly authorized representative WITHIN SEVEN (7) CALENDAR DAYS upon receipt to Procurement Section, Batanes State College.
A6: NOTE: | B6: 1. THE DEFAULT MODE OF PRICE EVALUATION SHALL BE ON A LOT BASIS, OTHERWISE PER ITEMS EVALUATION SHALL BE USED IF THERE WILL BE LACKING ITEMS IN ALL RFQ's AND SUBJECT TO END-USER APPROVAL., (Clause 15.2, Section I, Instruction to Bidders of the Philippine Bidding Documents for goods and infrastructure projects)
B7: 2. DELIVERY PERIOD: Thirty (30) calendar days
B8: 3. Submission of price quotation shall be in sealed envelope.
B9: 4. THE APPROVED BUDGET FOR THIS PROCUREMENT IS
B10: =PR!H68 -> 650000 | D10: (GPPB Resolution No. 09-2009)
B11: 5. PURSUANT TO ANNEX "H", APPENDIX A, SECTION II, SUBMISSION OF APPLICABLE DOCUMENTS (e.g.MAYORS/BUSINESS PERMIT, PROFESSIONAL LICENSE/CURRICULUM VITAE (CONSULTING SEERVICES),PHILGEPS CERT. NO., PCAB LICENSE (INFRA), INCOME/BUSINESS TAX RETURN,OMNIBUS SWORN STATEMENT SHALL BE REQUIRED BEFORE THE ISSUANCE OF NOA OR PRIOR TO PAYMENT.
B12: 6. In case the item is not availble, please write "None".
A13: Item # | B13: Qty. | C13: Unit | D13: PARTICULAR | E13: Unit Price | F13: Total
A14: 001 | B14: =PR!A16 -> 1 | C14: =PR!B16 -> set | D14: =PR!D16 -> Single Face P4 HD Outdoor LED Screen (rear maintenance), Full Set Up including controller (Novastar) & receiving card (Novastar) warranty, after sales support & training controller (novastar) & receiving card (novastar)warranty , after sales support & training size: 2.88M x 2.88M (9 panels) screen resolution; 720 pixels (W) x 720 pixels (H) Type; movable frame Accessories: replacement module , replacemenr power supply,replacement receiving card,power cable,signal cable FREE: LED control software Training and Support
A15: 002 | B15: =PR!A17 -> 0 | C15: =PR!B17 -> 0 | D15: =PR!D17 -> 0
A16: 003 | B16: =PR!A18 -> 0 | C16: =PR!B18 -> 0 | D16: =PR!D18 -> 0
A17: 004 | B17: =PR!A19 -> 0 | C17: =PR!B19 -> 0 | D17: =PR!D19 -> 0
A18: 005 | B18: =PR!A20 -> 0 | C18: =PR!B20 -> 0 | D18: =PR!D20 -> 0
A19: 006 | B19: =PR!A21 -> 0 | C19: =PR!B21 -> 0 | D19: =PR!D21 -> 0
A20: 007 | B20: =PR!A22 -> 0 | C20: =PR!B22 -> 0 | D20: =PR!D22 -> 0
A21: 008 | B21: =PR!A23 -> 0 | C21: =PR!B23 -> 0 | D21: =PR!D23 -> 0
A22: 009 | B22: =PR!A24 -> 0 | C22: =PR!B24 -> 0 | D22: =PR!D24 -> 0
A23: 010 | B23: =PR!A25 -> 0 | C23: =PR!B25 -> 0 | D23: =PR!D25 -> 0
A24: 011 | B24: =PR!A26 -> 0 | C24: =PR!B26 -> 0 | D24: =PR!D26 -> 0
A25: 012 | B25: =PR!A27 -> 0 | C25: =PR!B27 -> 0 | D25: =PR!D27 -> 0
... A28: 015 | B28: =PR!A30 -> 1 | C28: =PR!B30 -> copy | D28: =PR!D30 -> Design and Implement the Curriculum to Foster Children's Learning and Development, 3G E-Leraning, 2022, Wiseman's Book Trading, Inc.
A29: 016 | B29: =PR!A52 -> 1 | C29: =PR!B52 -> copy | D29: =PR!D52 -> The Teacher and the School Curriculum Obe Approach, Otinero-Gallardo, 2024, Big Faith Trading
A30: 017 | B30: =PR!A53 -> 1 | C30: =PR!B53 -> copy | D30: =PR!D53 -> The Teaching Profession, Fernando, et al., 2024, Big Faith Trading
A31: 018 | B31: =PR!A54 -> 1 | C31: =PR!B54 -> copy | D31: =PR!D54 -> English/Purposive Communication (A Modular Approach), Gutierrez-Ang, 2023, Big Faith Trading
A32: 019 | B32: =PR!A55 -> 1 | C32: =PR!B55 -> copy | D32: =PR!D55 -> Artificial Intelligence and Quantum Computing, Schweinfurth, 2025, 9789362241931, Wiseman's Book Trading, Inc.
A33: 020 | B33: =PR!A56 -> 1 | C33: =PR!B56 -> copy | D33: =PR!D56 -> Basic Computer Coding: Java Script 3rd/ed, Gbadegesin, 2024, 9781984689337, Wiseman's Book Trading, Inc.
A34: 021 | B34: =PR!A57 -> 1 | C34: =PR!B57 -> copy | D34: =PR!D57 -> Electronics All-in-One For Dummies, 3rd edition, Lowe, 2022, 978-1119822110, https://www.amazon.com
A35: 022 | B35: =PR!A58 -> 1 | C35: =PR!B58 -> copy | D35: =PR!D58 -> Practical Electronics for Inventors, 4th Edition, Scherz & Monk, 2016, 9.78126E+12, https://www.amazon.com
A36: 023 | B36: =PR!A59 -> 1 | C36: =PR!B59 -> copy | D36: =PR!D59 -> Make: Electronics: Learning by Discovery: A hands-on primer for the new electronics enthusiast 3rd Edition, Platt, 2021, 978-1680456875, https://www.amazon.com
A37: 024 | B37: =PR!A60 -> 1 | C37: =PR!B60 -> copy | D37: =PR!D60 -> Electronic Devices and Curcuits Theory, Boylestad & Nashelsky, latest ed., https://www.amazon.com
A38: 046 | B38: =PR!A61 -> 1 | C38: =PR!B61 -> copy | D38: =PR!D61 -> Digital Fundamentals, Floyd, latest ed., https://www.amazon.com/Digital-Fundamentals-11th-Thomas-Floyd/dp/0132737965
A39: 047 | B39: =PR!A62 -> 1 | C39: =PR!B62 -> copy | D39: =PR!D62 -> Microelectronics circuits, Sedra & Smith, latest ed., https://www.amazon.com/Microelectronic-Circuits-Electrical-Computer-Engineering/dp/0195323033
A40: 048 | B40: =PR!A63 -> 1 | C40: =PR!B63 -> copy | D40: =PR!D63 -> The art of electronics, Horowitz & Hill, latest ed., https://www.amazon.com/Art-Electronics-Paul-Horowitz/dp/0521809266
... A44: 052 | B44: =PR!A67 -> 1 | C44: =PR!B67 -> copy | D44: =PR!D67 -> Environmental Geology \5ed., Reichard, Jim, 2024, 9781266132261, Forefront Book
A45: 053 | B45: =PR!#REF! -> #REF! | C45: =PR!#REF! -> #REF! | D45: =PR!#REF! -> #REF!
A46: 054 | B46: =PR!#REF! -> #REF! | C46: =PR!#REF! -> #REF! | D46: =PR!#REF! -> #REF!
A47: 055 | B47: =PR!#REF! -> #REF! | C47: =PR!#REF! -> #REF! | D47: =PR!#REF! -> #REF!
A48: 056 | B48: =PR!#REF! -> #REF! | C48: =PR!#REF! -> #REF! | D48: =PR!#REF! -> #REF!
A49: 057 | B49: =PR!#REF! -> #REF! | C49: =PR!#REF! -> #REF! | D49: =PR!#REF! -> #REF!
A50: 058 | B50: =PR!#REF! -> #REF! | C50: =PR!#REF! -> #REF! | D50: =PR!#REF! -> #REF!
A51: 059 | B51: =PR!#REF! -> #REF! | C51: =PR!#REF! -> #REF! | D51: =PR!#REF! -> #REF!
A52: 060 | B52: =PR!#REF! -> #REF! | C52: =PR!#REF! -> #REF! | D52: =PR!#REF! -> #REF!
A53: 061 | B53: =PR!#REF! -> #REF! | C53: =PR!#REF! -> #REF! | D53: =PR!#REF! -> #REF!
A54: 062 | B54: =PR!#REF! -> #REF! | C54: =PR!#REF! -> #REF! | D54: =PR!#REF! -> #REF!
A55: 063 | B55: =PR!#REF! -> #REF! | C55: =PR!#REF! -> #REF! | D55: =PR!#REF! -> #REF!
A56: 064 | B56: =PR!#REF! -> #REF! | C56: =PR!#REF! -> #REF! | D56: =PR!#REF! -> #REF!
... A89: 097 | B89: =PR!#REF! -> #REF! | C89: =PR!#REF! -> #REF! | D89: =PR!#REF! -> #REF!
E91: Total
A92: After having carefully read and accepted your conditions, I/We have place my /our best and final price offer on the item/s listed above.
A94: Printed Name/Signature | E94: Very truly yours,
E97: DOREEN C. CASTILLO
A98: Ref.# | B98: =PR!B12 -> 2505-GAS5-190 | E98: BAC Chairperson

Sheet RFQ_ (2)
A1: Republic of the Philippines
A2: BATANES STATE COLLEGE
A3: Basco, Batanes
E4: Date:
A5: REQUEST FOR PRICE QUOTATION
B6: MOJR Construction Trading & General Services, Ltd, Co. | C6: MOJR Construction Trading & General Services, Ltd, Co. | D6: MOJR Construction Trading & General Services, Ltd, Co.
A7: Please give us your best and final price offer for the item/s listed below, have this signed and submit this by you or by your duly authorized representative WITHIN SEVEN (7) CALENDAR DAYS upon receipt to Procurement Section, Batanes State College.
A9: NOTE: | B9: 1. THE DEFAULT MODE OF PRICE EVALUATION SHALL BE ON A LOT BASIS, OTHERWISE PER ITEMS EVALUATION SHALL BE USED IF THERE WILL BE LACKING ITEMS IN ALL RFQ's AND SUBJECT TO END-USER APPROVAL., (Clause 15.2, Section I, Instruction to Bidders of the Philippine Bidding Documents for goods and infrastructure projects)
B10: 2. DELIVERY PERIOD: Thirty (30) calendar days.
B11: 3. Submission of price quotation shall be in sealed envelope.
B12: 4. THE APPROVED BUDGET FOR THIS PROCUREMENT IS
B13: =PR!H68 -> 650000 | D13: (GPPB Resolution No. 09-2009)
B14: 5. PURSUANT TO ANNEX "H", APPENDIX A, SECTION II, SUBMISSION OF APPLICABLE DOCUMENTS (e.g.MAYORS/BUSINESS PERMIT, PROFESSIONAL LICENSE/CURRICULUM VITAE (CONSULTING SEERVICES),PHILGEPS CERT. NO., PCAB LICENSE (INFRA), INCOME/BUSINESS TAX RETURN,OMNIBUS SWORN STATEMENT SHALL BE REQUIRED BEFORE THE ISSUANCE OF NOA OR PRIOR TO PAYMENT.
B15: 6. In case the item is not availble, please write "None".
A16: Item # | B16: Qty. | C16: Unit | D16: PARTICULAR | E16: Unit Price | F16: Total
A17: 001
A18: 002
A19: 003
A20: 004
A21: 005
A22: 006
A23: 007
A24: 008
A25: 009
A26: 010
A27: 011
A28: 012
... A33: 017
A34: 018 | B34: =PR!A33 -> 1 | C34: =PR!B33 -> copy | D34: graphite pencil 12b | J34: graphite pencil 12b
A35: 019 | B35: =PR!A34 -> 1 | C35: =PR!B34 -> copy | D35: graphite pencil 8b | J35: graphite pencil 8b
A36: 020 | B36: =PR!A41 -> 1 | C36: =PR!B41 -> copy | D36: graphite pencil 6b | J36: graphite pencil 6b
A37: 021 | B37: =PR!A42 -> 1 | C37: =PR!B42 -> copy | D37: graphite pencil 4b | J37: graphite pencil 4b
A38: 022 | B38: =PR!A43 -> 1 | C38: =PR!B43 -> copy | D38: graphite pencil 2b | J38: graphite pencil 2b
A39: 023 | B39: =PR!A44 -> 1 | C39: =PR!B44 -> copy | D39: graphite pencil HB | J39: graphite pencil HB
A40: 024 | B40: =PR!A45 -> 1 | C40: =PR!B45 -> copy | D40: =PR!D45 -> Physical Activity Towards Health and Fitness PATHFIT( Dance, Fitness, Tradition), Aquino, 2024, Big Faith Trading
A41: 025 | B41: =PR!A46 -> 1 | C41: =PR!B46 -> copy | D41: =PR!D46 -> Physical Activity Towards Health and Fitness PATHFIT(Arnis), Dela Cruz, 2024, Big Faith Trading
A42: 026 | B42: =PR!A47 -> 1 | C42: =PR!B47 -> copy | D42: =PR!D47 -> Qualitative Research, Macapagal/Sombilo, 2024, Big Faith Trading
A43: 027 | B43: =PR!A48 -> 1 | C43: =PR!B48 -> copy | D43: =PR!D48 -> Teaching Science in the Elementary Grades Vol. 2: Physics, Earth and Space OBE- & PPST based, Bilbao, 2024, Big Faith Trading
A44: 028 | B44: =PR!A49 -> 1 | C44: =PR!B49 -> copy | D44: =PR!D49 -> The Teacher and the Community, School Culture and Organizational Leadership, Serrano, 2020, Big Faith Trading
A45: 029 | B45: =PR!A50 -> 1 | C45: =PR!B50 -> copy | D45: illustration board 20”x30” | J45: illustration board 20”x30”
A46: 030 | B46: =PR!A51 -> 1 | C46: =PR!B51 -> copy | D46: illustration board 10”x15” | G46: 11/29/22 | H46: 3:54PM | I46: Gael | J46: illustration board 10”x15”
A47: 031 | B47: =PR!A52 -> 1 | C47: =PR!B52 -> copy | D47: illustration board 15”x20” | J47: illustration board 15”x20”
A48: 032 | B48: =PR!A53 -> 1 | C48: =PR!B53 -> copy | D48: =PR!D53 -> The Teaching Profession, Fernando, et al., 2024, Big Faith Trading
A49: 033 | B49: =PR!A54 -> 1 | C49: =PR!B54 -> copy | D49: 90 ml sap green | J49: 90 ml sap green
A50: 034 | B50: =PR!A55 -> 1 | C50: =PR!B55 -> copy | D50: 90 ml raw sienna | J50: 90 ml raw sienna
A51: 035 | B51: =PR!A56 -> 1 | C51: =PR!B56 -> copy | D51: 90 ml burnt umber | J51: 90 ml burnt umber
A52: 036 | B52: =PR!A57 -> 1 | C52: =PR!B57 -> copy | D52: 90 ml payne’s gray | J52: 90 ml payne’s gray
A53: 037 | B53: =PR!A58 -> 1 | C53: =PR!B58 -> copy | D53: 90 ml titanium white | J53: 90 ml titanium white
A54: 038 | B54: =PR!A59 -> 1 | C54: =PR!B59 -> copy | D54: 90 ml cadmium orange hue | J54: 90 ml cadmium orange hue
A55: 039 | B55: =PR!A60 -> 1 | C55: =PR!B60 -> copy | D55: 90 ml yellow light hue | J55: 90 ml yellow light hue
A56: 040 | B56: =PR!A61 -> 1 | C56: =PR!B61 -> copy | D56: 90 ml ultramarine blue | J56: 90 ml ultramarine blue
A57: 041 | B57: =PR!A62 -> 1 | C57: =PR!B62 -> copy | D57: 90 ml cadmium red light hue | J57: 90 ml cadmium red light hue
A58: 042 | B58: =PR!A63 -> 1 | C58: =PR!B63 -> copy | D58: 90 ml hooker’s green hue | J58: 90 ml hooker’s green hue
A59: 043 | D59: =PR!D64 -> Industrial electronics, Rehg & Sartori, latest ed., https://www.amazon.com/Industrial-Electronics-James-Rehg/dp/0132064189
A60: 044 | D60: =PR!D65 -> Environmental and Atmospheric Chemistry, Devi, 2023 9789395431309, Wiseman's Book Trading
A61: 045 | D61: =PR!D66 -> Ecology in Action \2ed., Singer, Fred D., 2025, 9781108927222, Forefront Books
A62: 046 | D62: =PR!D67 -> Environmental Geology \5ed., Reichard, Jim, 2024, 9781266132261, Forefront Book
A63: 047 | D63: =PR!#REF! -> #REF!
A64: 048 | D64: =PR!#REF! -> #REF!
A65: 049 | D65: =PR!#REF! -> #REF!
A66: 050 | D66: =PR!#REF! -> #REF!
A67: 051 | D67: =PR!#REF! -> #REF!
A68: 052 | D68: =PR!#REF! -> #REF!
A69: 053 | D69: =PR!#REF! -> #REF!
A70: 054 | D70: =PR!#REF! -> #REF!
A71: 055 | D71: =PR!#REF! -> #REF!
A72: 056 | D72: =PR!#REF! -> #REF!
A73: 057 | D73: =PR!#REF! -> #REF!
A74: 058 | D74: =PR!#REF! -> #REF!
... A100: 084 | D100: =PR!#REF! -> #REF!
F101: Total:
A102: After having carefully read and accepted your conditions, I/We have place my /our best and final price offer on the item/s listed above.
A104: Printed Name/Signature | E104: Very truly yours,
E107: DOREEN C. CASTILLO
A108: Ref.# | B108: =PR!B12 -> 2505-GAS5-190 | E108: BAC Chairperson

Sheet AckReceipt (2)
A1: Acknowledgement for Request for Quotation
A2: RIS# | B2: =PR!B12 -> 2505-GAS5-190
A3: No. | B3: Supplier | F3: Received by: | G3: Date & Time:
B4: JPM Gen. Mdse. & Hardware
B5: Thine-line Trading
B6: J-Tech Trading & Services
B7: MDAC Trading & Compuserve
B8: FVA Gen Mdse & Construction Supply
B10: GDP Trading
B11: EA Amboy Gen Mdse
B12: L & R's Hontomin Gen Mdse
B13: Davocol's Gen. Mdse.
B14: RCJ Hardware & Gen Mdse
B15: Fitero's Gen Mdse & Electronic Supply
B16: Lar & San's Store
... B18: Wilmerson Gen Mdse
B19: FMG Trading & Construction Supply | C19: q
B20: MG Hubalde Gen Mdse
B21: Basco Cable TV Services, Inc.
B22: Berlen's Store
B23: Melad's Gen. Mdse
B24: R. A. Electronics
B25: RJ General Merchandise
B26: Batanes Multi-Purpose Cooperative, Inc.
B27: Romy & Ava's Store
B28: J-nell's Gen Mdse
B29: Impression Digital Printing Solutions
B30: Golden Press
B31: Tawsen's Agri-Venture & Souvenirs
... B60: Sophia Marie Store
A61: 1 | B61: GDP Trading
A62: 2 | B62: JPM Gen. Mdse. & Hardware
A63: 3 | B63: FVA Trading
A64: 4
A65: 5 | J65: zz
A66: 6
A67: 7
A68: NOTE: | B68: 1. MODE OF PRICE EVALUATION SHALL BE ON A LOT BASIS, OTHERWISE PER ITEMS EVALUATION SHALL BE USED IF THERE WILL BE LACKING ITEMS IN ALL RFQ'S AND THE END-USER AGREED, . (Clause 15.2, Section II, Instructions to Bidders of the Philippine Bidding Documents for goods and infrastructure projects)
B69: 2. DELIVERY PERIOD: Thirty (30) calendar days.
B70: 3. WARRANTY SHALL BE FOR A PERIOD OF SIX (6) MONTHS FOR SUPPLIES AND MATERIALS, ONE (1) YEAR FOR EQUIPMENT, FROM THE DATE OF ACCEPTANCE BY THE PROCURING ENTITY.
B71: 4. THE APPROVED BUDGET CEILING FOR THIS PROCUREMENT IS PHP (GPPB Resolution no. 09-2009)
B72: =PR!H68 -> 650000
B73: 5. PRICE VALIDITY SHALL BE OR THE PERIOD OF 30 CALENDAR DAYS.
B74: 6. BIDDERS SHALL SUBMIT ORIGINAL BROCHURES SHOWING SPECIFICATIONS OF THE PRODUCT BEING OFFERED IF APPLICABLE.
A75: In compliance with GPPB Resolution No. 09-2009
B77: Retrieval of Request for Quotation
A79: No. | B79: Supplier | E79: Released by: | F79: Date & Time: | G79: Remarks | N79: k
A80: 1 | B80: GDP Trading
A81: 2 | B81: JPM Gen. Mdse. & Hardware
A82: 3 | B82: FVA Trading
A83: 4
A84: 5
A85: 6
A86: 7

Sheet Abstract 
B3: ABSTRACT OF QUOTATIONS
I4: 6750
B5: (x) Furnishing/delivery of supplies, and materials or equipment | H5: Bids opened at Basco, Batanes
B6: ( x ) Furnishing Labor, services, etc. | I6: =NOW() -> 46148.737
B7: ( ) Rental or use of transportation facilities equipment, quarters, rooms, lot or space, etc.
B9: To be furnished at the | D9: BATANES STATE COLLEGE
D10: (State place or site of Office or project where articles or services be furnished or returned)
A12: NAME OF ARTICLES OR SERVICES TO BE FURNISHED, RENDERED OR FACILITIES TO BE RENTED
F15: JPM Gen. Mdse. & Hardware
F16: Thine-line Trading
F17: J-Tech Trading & Services
F18: Mulong Ydel
F19: MDAC Trading & Compuserve
F20: FVA Gen Mdse & Construction Supply
F21: MKM Hardware
F22: GDP Trading
F23: EA Amboy Gen Mdse
F24: L & R's Hontomin Gen Mdse
F25: Davocol's Gen. Mdse.
F26: RCJ Hardware & Gen Mdse
... F87: Valiente Food Producer
F88: =DATA!V298 -> Apostol General Merchandise | G88: M.G. Hubalde's General Merchandise | H88: JPM General Merchandise & Hardware | I88: E.A. General Merchandise
A90: =PR!D16 -> Single Face P4 HD Outdoor LED Screen (rear maintenance), Full Set Up including controller (Novastar) & receiving card (Novastar) warranty, after sales support & training controller (novastar) & receiving card (novastar)warranty , after sales support & training size: 2.88M x 2.88M (9 panels) screen resolution; 720 pixels (W) x 720 pixels (H) Type; movable frame Accessories: replacement module , replacemenr power supply,replacement receiving card,power cable,signal cable FREE: LED control software Training and Support | F90: =DATA!O298 -> 12000 | G90: 14800 | H90: 22000 | I90: none
M92: =DATA!W479 -> 0
M93: =DATA!W480 -> 0
M94: =DATA!W481 -> 0
A99: =PR!D25 -> 0 | F99: =DATA!O157 -> 770
A100: =PR!D26 -> 0 | F100: =DATA!O158 -> 880
A101: =DATA!I483 -> 0 | B101: Bond paper, A4 size | C101: Bond paper, A4 size | D101: Bond paper, A4 size | E101: Bond paper, A4 size | F101: =DATA!O159 -> 1325
A102: =DATA!I484 -> 0 | B102: Bond paper, A4 size | C102: Bond paper, A4 size | D102: Bond paper, A4 size | E102: Bond paper, A4 size | F102: =DATA!O160 -> 0
A103: =DATA!I485 -> 0 | B103: Bond paper, A4 size | C103: Bond paper, A4 size | D103: Bond paper, A4 size | E103: Bond paper, A4 size | F103: =DATA!O161 -> 0
A104: =DATA!I486 -> 0 | B104: Bond paper, A4 size | C104: Bond paper, A4 size | D104: Bond paper, A4 size | E104: Bond paper, A4 size | F104: =DATA!O162 -> 0
A105: =DATA!I487 -> 0 | B105: Bond paper, A4 size | C105: Bond paper, A4 size | D105: Bond paper, A4 size | E105: Bond paper, A4 size | F105: =DATA!O163 -> 0
A106: =DATA!I488 -> 0 | B106: Bond paper, A4 size | C106: Bond paper, A4 size | D106: Bond paper, A4 size | E106: Bond paper, A4 size | F106: =DATA!O164 -> 0
A107: =DATA!I489 -> 0 | B107: Bond paper, A4 size | C107: Bond paper, A4 size | D107: Bond paper, A4 size | E107: Bond paper, A4 size | F107: =DATA!O165 -> 0
A108: =DATA!I490 -> 0 | B108: Bond paper, A4 size | C108: Bond paper, A4 size | D108: Bond paper, A4 size | E108: Bond paper, A4 size | F108: =DATA!O166 -> 0
A109: =DATA!I491 -> 0 | B109: Bond paper, A4 size | C109: Bond paper, A4 size | D109: Bond paper, A4 size | E109: Bond paper, A4 size | F109: =DATA!O167 -> 0
A110: =DATA!I492 -> 0 | B110: Bond paper, A4 size | C110: Bond paper, A4 size | D110: Bond paper, A4 size | E110: Bond paper, A4 size | F110: =DATA!O168 -> 0
A111: =DATA!I493 -> 0 | B111: Bond paper, A4 size | C111: Bond paper, A4 size | D111: Bond paper, A4 size | E111: Bond paper, A4 size | F111: =DATA!O169 -> 0
A112: =DATA!I494 -> 0 | B112: Bond paper, A4 size | C112: Bond paper, A4 size | D112: Bond paper, A4 size | E112: Bond paper, A4 size | F112: =DATA!O170 -> 0
... A121: =DATA!I503 -> 0 | B121: Bond paper, A4 size | C121: Bond paper, A4 size | D121: Bond paper, A4 size | E121: Bond paper, A4 size | F121: =DATA!O179 -> 350
F122: =DATA!O180 -> 4400
F123: =DATA!O181 -> 1400
F124: =DATA!O182 -> 3000
F125: =DATA!O183 -> 0
F126: =DATA!O184 -> 0
F127: =DATA!O185 -> 0
F128: =DATA!O186 -> 0
F129: =DATA!O187 -> 0
F130: =DATA!O188 -> 0
F131: =DATA!O189 -> 0
F132: =DATA!O190 -> 975
F133: =DATA!O191 -> 3520
... F148: =DATA!O206 -> 0
H149: =SUM(H90:H97) -> 22000
F150: =SUM(F90:F95) -> 12000 | G150: =SUM(G90:G94) -> 14800 | H150: =SUM(H90:H96) -> 22000 | I150: none | J150: =SUM(J90:J96) -> 0 | M150: none
E152: all Items are Failed due to No Supplier Quoted the RFQ
A153: =A154 -> Lowest Calculated Bidder | E153: =F150 -> 12000 | F153: are Failed due to the qoutation Exceeded the Budget
A154: Lowest Calculated Bidder | F154: in the amount of | G154: =F150 -> 12000 | H154: is awarded to | I154: =F88 -> Apostol General Merchandise
A155: RHOUPHELINE AYA A. CADIZ | E155: FORTUNATO PHILIP A. CABUGAO | I155: EMILYN D. ALUETA
A156: BAC Member | F156: BAC Member | I156: BAC Member
A158: =PR!B73 -> JOHN MICHAEL A. VILLASPIR | F158: PHILIP ULYSSES T. CASTILLO | I158: DOREEN C. CASTILLO
A159: End-User/Provisional Member | F159: BAC Vice Chair | I159: BAC Chairperson
G160: BAC Sec. Cert. No: | I160: =PR!B12 -> 2505-GAS5-190

Sheet  LON-
A6: BIDS AND AWARDS COMMITTEE
A8: LETTER OF NOTICE
A11: LEO A. APOSTOL
A12: Owner
A13: Apostol General Merchandise
A14: Brgy. Kayhuvokan,Batanes
A17: Madam/Sir:
A18: We are happy to notify you that your quotation dated June 4 2025 for the 4 Layered Steel Filling Cabinet with central lock with PR # 2505-1006-211 with contract price equivalent to TWELVE THOUSAND PESOS ONLY (Php 12,000.00) is hereby accepted.
A19: You are hereby required to provide within Ten (10) days a certified photocopy of the following requirements:
A20: .
B21: 1. Updated Mayor's Permit/Business Permit
B22: 2. PhilGEPS Registration no.
B23: 3. Latest Income/Business Tax Return
B24: 4. Duly Notarized Omnibus Sworn Statement
B25: 5. BIR 2302 Certificate of Registration
B26: 6. Updated DTI Registration
B27: 7. Landbank Account details of the business (for payment purposes)
A30: However, If you already have a maintaining and updated file of the above-mentioned requirements in the BAC Office you may no longer require its re-submission (Annex "H", Appendix "A" Section III)
A32: *For individuals engaged under Sec. 53.6, 53.7, and 53.9 of the IRR of RA 9184, only the BIR Certificate of Registration shall be submitted in lieu of DTI Registration and Mayor’s Permit.
A33: Thank you
A35: Very truly yours,
A38: DOREEN C. CASTILLO
A39: BAC Chairperson
A41: Received by:
A44: (Signature over printed name)
A45: Date: ___________________
A46: Ref. No.: | B46: =PR!B12 -> 2505-GAS5-190

Sheet BAC RESO 2022
E3: OFFICE OF THE BIDS AND AWARDS COMMITTEE | N3: OFFICE OF THE BIDS AND AWARDS COMMITTEE
E4: bac resolution No: | M4: =E4 -> bac resolution No:
D5: =PR!B12 -> 2505-GAS5-190 | M5: =D5 -> 2505-GAS5-190
E7: BAC RESOLUTION RECOMMENDING FOR AWARD | N7: APPROVAL OF THE BAC RECOMMENDATION FOR AWARD
A9: WHEREAS, the BATANES STATE COLLEGE advertised the Request for Price Quotation (RFQ) for the 4 Layered Steel Filling Cabinet with central lock with PR # 2505-1006-211 dated June 4, 2025. | J9: WHEREAS, the BATANES STATE COLLEGE advertised the Request for Price Quotation (RFQ) for the BT5000-yellow,cyan,magenta with PR # 2505-GAS1-209 dated May 30, 2025.
A11: WHEREAS, from the period the Request for Price Quotation (RFQ) has started up to the time of bid submission and opening, Four(4) prospective bidder were able to submit the RFQ; | J11: WHEREAS, from the period the Request for Price Quotation (RFQ) has started up to the time of bid submission and opening, Five (5) prospective bidder were able to submit the RFQ;
A13: WHEREAS, the Price Quotation based on the Lowest Calculated & Responsive Bid (LCRB) format of the bidders were opened and its bid price was read as follows: | J13: WHEREAS, the Price Quotation based on the Lowest Calculated & Responsive Bid (LCRB) format of the bidders were opened and its bid price was read as follows:
A16: ITEM NO. | B16: BIDDER WITH CALCULATED BID | G16: ABC | I16: BID AMOUNT | J16: ITEM NO. | K16: BIDDER WITH CALCULATED BID | P16: ABC | R16: BID AMOUNT
A17: 1 | B17: =DATA!V298 -> Apostol General Merchandise | G17: =PR!H68 -> 650000 | I17: 12000 | J17: 1 | K17: =B17 -> Apostol General Merchandise | P17: =G17 -> 650000 | R17: =I17 -> 12000
A18: 2 | B18: M.G. Hubalde's General Merchandise | G18: 20000 | I18: 14800 | J18: 2 | K18: =B18 -> M.G. Hubalde's General Merchandise | P18: =G18 -> 20000 | R18: =I18 -> 14800
A19: 3 | B19: JPM General Mdse. & Hardware | G19: 20000 | I19: 22000 | J19: 3 | K19: =B19 -> JPM General Mdse. & Hardware | P19: =G19 -> 20000 | R19: =I19 -> 22000
A20: 4 | B20: E.A.Amboy General Merchandise | G20: 20000 | I20: none | J20: 4 | K20: =B20 -> E.A.Amboy General Merchandise | P20: =G20 -> 20000 | R20: =I20 -> none
A21: 5 | J21: 5 | K21: =B21 -> 0 | P21: =G21 -> 0 | R21: =I21 -> 0
A22: 6 | G22: 13000 | I22: none | J22: 6 | K22: =B22 -> 0 | P22: =G22 -> 13000 | R22: =I22 -> none
A23: 7 | G23: 13000 | I23: none | J23: 7 | K23: =B23 -> 0 | P23: =G23 -> 13000 | R23: =I23 -> none
A24: 8 | J24: 8 | K24: =B24 -> 0 | P24: =G24 -> 0 | R24: =I24 -> 0
J25: NOW THEREFORE, I DJOVI R. DURANTE,DPA by virtue of the authority vested in me of this institution and after taking into consideration the merits and legal bases of the recommendation of the members of the Bids and Awards Committee (BAC) do hereby APPROVE the following;
B26: 1. To declare Apostol General Merchandise as supplier with the Lowest Calculated & Responsive Bid for the 4 Layered Steel Filling Cabinet with central lock with PR # 2505-1006-211 dated June 4, 2025.
B27: 2. To recommend for approval by the Head of Procuring Entity of the Batanes State College the foregoing findings.
A28: RESOLVED FINALLY, at the BAC Office, Batanes State College, this _______day of . | J28: To declare Apostol General Merchandise as supplier with the Lowest Calculated & Responsive Bid for the 4 Layered Steel Filling Cabinet with central lock with PR # 2505-1006-211.
A29: Recommending Approval:
A32: RHOUPHELINE AYA A. CADIZ | D32: EMILYN D. ALUETA | G32: FORTUNATO PHILIP A. CABUGAO | J32: Done this ______ day of _________ 2025.
A33: BAC Member | D33: BAC Member | G33: BAC Member
L36: DJOVI REGALA DURANTE,DPA
A37: =PR!B73 -> JOHN MICHAEL A. VILLASPIR | F37: PHILIP ULYSSES T. CASTILLO | L37: SUC President I
A38: End-user/Provisional Member | F38: Vice BAC Chairperson
D40: DOREEN C. CASTILLO
D41: BAC Chairperson

Sheet BAC RESO 2022 (Toss Coin)
E6: OFFICE OF THE BIDS AND AWARDS COMMITTEE | N6: OFFICE OF THE BIDS AND AWARDS COMMITTEE
E7: bac resolution No: | M7: =E7 -> bac resolution No:
D8: =PR!B12 -> 2505-GAS5-190 | M8: =D8 -> 2505-GAS5-190
E10: BAC RESOLUTION RECOMMENDING FOR AWARD | N10: APPROVAL OF THE BAC RECOMMENDATION FOR AWARD
A12: WHEREAS, the BATANES STATE COLLEGE advertised the Request for Price Quotation (RFQ)of the AM Snack: Special Cheese Burger w/ camote fries and canned soda with PR # 2405-GAS17-204dated May 23, 2024. | J12: WHEREAS, the BATANES STATE COLLEGE advertised the Request for Price Quotation (RFQ)of the AM Snack: Special Cheese Burger w/ camote fries and canned soda with PR # 2405-GAS17-204dated May 23, 2024.
A15: WHEREAS, from the period the Request for Price Quotation (RFQ) has started up to the time of bid submission and opening, Five (5) prospective bidders were able to submit the RFQ; | J15: WHEREAS, from the period the Request for Price Quotation (RFQ) has started up to the time of bid submission and opening, Five (5) prospective bidders were able to submit the RFQ;
A18: WHEREAS, the Price Quotation based on the Lowest Calculated & Responsive Bid (LCRB) format of the bidders were opened and its bid price was read as follows: | J18: WHEREAS, the Price Quotation based on the Lowest Calculated & Responsive Bid (LCRB) format of the bidders were opened and its bid price was read as follows:
A21: ITEM NO. | B21: BIDDER WITH CALCULATED BID | G21: ABC | I21: BID AMOUNT | J21: ITEM NO. | K21: BIDDER WITH CALCULATED BID | P21: ABC | R21: BID AMOUNT
A22: 1 | B22: =DATA!V234 -> 0 | G22: =PR!H68 -> 650000 | I22: 1750 | J22: 1 | K22: =B22 -> 0 | P22: =G22 -> 650000 | R22: =I22 -> 1750
A23: 2 | B23: Korner Hauz Café | G23: =PR!H68 -> 650000 | I23: 1750 | J23: 2 | K23: =B23 -> Korner Hauz Café | P23: =G23 -> 650000 | R23: =I23 -> 1750
A24: 3 | B24: Bunkers Bistro | G24: =PR!H68 -> 650000 | I24: 1,750 (withdraw) | J24: 3 | K24: =B24 -> Bunkers Bistro | P24: =G24 -> 650000 | R24: =I24 -> 1,750 (withdraw)
A25: 4 | B25: AZ Blue Box Café | G25: 1750 | I25: 1800 | J25: 4 | K25: =B25 -> AZ Blue Box Café | P25: =G25 -> 1750 | R25: =I25 -> 1800
A26: 5 | B26: Doque's Congie Hauz | G26: 1750 | I26: 2000 | J26: 5 | K26: =B26 -> Doque's Congie Hauz | P26: =G26 -> 1750 | R26: =I26 -> 2000
A27: 6 | J27: 6 | K27: =B27 -> 0 | P27: =G27 -> 0 | R27: =I27 -> 0
A28: 7 | J28: 7 | K28: =B28 -> 0 | P28: =G28 -> 0 | R28: =I28 -> 0
A29: 8 | J29: 8 | K29: =B29 -> 0 | P29: =G29 -> 0 | R29: =I29 -> 0
A30: WHEREAS,two (2) of the suppliers have the same total price quotation; | J30: WHEREAS,two (2) of the suppliers have the same total price quotation;
A32: WHEREAS, to resolve cases involving a tie, the procuring entity may determine a measure to be used by which it shall be non-discretionary and non-discriminatory such that the same shall be based on sheer luck or chance. The method used was "toss coin"; | J32: WHEREAS, to resolve cases involving a tie, the procuring entity may determine a measure to be used by which it shall be non-discretionary and non-discriminatory such that the same shall be based on sheer luck or chance. The method used was "toss coin";
A34: WHEREAS, as per result of the toss coin conducted, Pension Ivatan was announced as the winner: | J34: WHEREAS, as per result of the toss coin conducted, Pension Ivatan was announced as the winner:
B36: 1. To declare Pension Ivatan as supplier of AM Snack: Special Cheese Burger w/ camote fries and canned soda with PR # 2505-GAS17-204 dated May 23, 2025. | J36: NOW THEREFORE, I DJOVI R. DURANTE,DPA by virtue of the authority vested in me of this institution and after taking into consideration the merits and legal bases of the recommendation of the members of the Bids and Awards Committee (BAC) do hereby APPROVE the following;
B39: 2. To recommend for approval by the Head of Procuring Entity of the Batanes State College the foregoing findings.
A40: RESOLVED FINALLY, at the BAC Office, Batanes State College, this _______day of . | J40: To declare Pension Ivatan as supplier of AM Snack: Special Cheese Burger w/ camote fries and canned soda with PR # 2405-GAS17-204.
A41: Recommending Approval:
A44: RHOUPHELINE AYA A. CADIZ | D44: EMILYN D. ALUETA | G44: FORTUNATO PHILIP A. CABUGAO | J44: Done this _______ day of ___________ 2022 | N44: 2025
A45: BAC Member | D45: BAC Member | G45: BAC Member
L47: DJOVI REGALA DURANTE,DPA
A48: =PR!B73 -> JOHN MICHAEL A. VILLASPIR | D48: PHILIP ULYSSES T. CASTILLO | H48: DOREEN C. CASTILLO | L48: SUC President I
A49: End-user/Provisional Member | D49: BAC Vice Chairperson | H49: BAC Chairperson

Sheet PO
A3: PURCHASE ORDER | I3: INSTRUCTIONS
A4: Supplier | B4: =DATA!V298 -> Apostol General Merchandise | D4: PO No. | F4: 2025-05-211 | I4: specific quantities of supplies/goods/property subject to the terms and conditions contained in the PO.
A5: Address | B5: Basco, Batanes | D5: Date | F5: =NOW() -> 46148.737 | I5: B. This form shall be accomplished as follows:
A6: TIN | B6: 183-008-448 | C6: 183-008-448 | E6: Small Value Procurement | J6: 1. Entity Name - name of the agency/entity
B7: 150-214-534 | J7: 2. Supplier/Address/TIN - name, address and TIN of the supplier
A8: Please furnish this office the following articles subject to the term and conditions contained herein: | J8: 3. P.O. No. - the number assigned to the PO which shall be as follows:
A9: Place of Delivery: | C9: Batanes State College | D9: Delivery Term: | F9: FOB Destination | K9: 0000-00-0000 | M9: Serial number (one series for each year)
A10: Date of Delivery: | C10: 30 days upon receipt of PO | D10: Payment Term: | F10: 15 days upon complete delivery | M10: Month
A11: No. | B11: Unit | C11: Description | D11: Qty | E11: Unit Cost | F11: Amount | M11: Year
A12: 001 | B12: =PR!B16 -> set | C12: =PR!D16 -> Single Face P4 HD Outdoor LED Screen (rear maintenance), Full Set Up including controller (Novastar) & receiving card (Novastar) warranty, after sales support & training controller (novastar) & receiving card (novastar)warranty , after sales support & training size: 2.88M x 2.88M (9 panels) screen resolution; 720 pixels (W) x 720 pixels (H) Type; movable frame Accessories: replacement module , replacemenr power supply,replacement receiving card,power cable,signal cable FREE: LED control software Training and Support | D12: =PR!A16 -> 1 | E12: =DATA!N298 -> 12000 | F12: =SUM(D12*E12) -> 12000 | J12: 4. Date - date of the preparation of the PO
A13: =RFQ_!A15 -> 002 | B13: =PR!B17 -> 0 | F13: =SUM(D13*E13) -> 0 | J13: 5. Mode of Procurement - mode of procurement such as public bidding, through Procurement Service, limited source bidding, direct contracting, repeat order, shopping and negotiated procurement in accordance with RA 9184
A14: =RFQ_!A16 -> 003 | B14: =PR!B18 -> 0 | F14: =SUM(D14*E14) -> 0 | J14: 6. Place/Date of Delivery - place of delivery and definite date/s of delivery; if not stated, the date of delivery shall mean seven (7) calendar days after the receipt of PO by the supplier
A15: =RFQ_!A17 -> 004 | B15: =PR!B19 -> 0 | F15: =SUM(D15*E15) -> 0 | J15: 7. Delivery Term - delivery term i.e., FOB destination, FOB shipping point
A16: =RFQ_!A18 -> 005 | B16: =PR!B20 -> 0 | F16: =SUM(D16*E16) -> 0 | J16: 8. Payment Term - specified period required when the delivered goods shall be paid and discounts, if any, such as 2/10, n/30
A17: =RFQ_!A19 -> 006 | B17: =PR!B21 -> 0 | F17: =SUM(D17*E17) -> 0 | J17: 9. Stock/Property No. - stock/property number of the goods to be purchased as provided by the Supply and/or Property Division Unit
A18: =RFQ_!A20 -> 007 | B18: =PR!B22 -> 0 | F18: =SUM(D18*E18) -> 0 | J18: 10. Unit - unit of measurement of the supplies/goods/property being procured (i.e. piece, roll, box, reams, etc.)
A19: =RFQ_!A21 -> 008 | B19: =PR!B23 -> 0 | F19: =SUM(D19*E19) -> 0 | J19: 11. Description - brief description of the supplies/goods/property being procured
A20: =RFQ_!A22 -> 009 | B20: =PR!B24 -> 0 | F20: =SUM(D20*E20) -> 0 | J20: 12. Quantity - quantity of supplies/goods/property being procured
A21: =RFQ_!A23 -> 010 | F21: =SUM(D21*E21) -> 0 | J21: 13. Unit Cost - cost per unit of the supplies/goods/property being procured
A22: =RFQ_!#REF! -> #REF! | F22: =SUM(D22*E22) -> 0 | J22: 14. Amount - total amount of the supplies/goods/property being procured (Quantity x Unit Cost)
A23: =RFQ_!#REF! -> #REF! | F23: =SUM(D23*E23) -> 0 | J23: 15. Penalty Clause - penalty to be imposed by the agency/entity in case of non-compliance with the term, that is, one-tenth (1/10) of one percent (1%) for every day of delay on the undelivered item/s
A24: =RFQ_!#REF! -> #REF! | B24: =DATA!K370 -> 0 | F24: =SUM(D24*E24) -> 0 | J24: 16. Approval - signature over printed name and designation of the Approving Official
A25: =RFQ_!#REF! -> #REF! | B25: =DATA!K371 -> 0 | F25: =SUM(D25*E25) -> 0 | J25: 17. Conforme - signature over printed name of the supplier or his/her representative signifying his/her approval to the term set by the agency/entity and the date of signing
A26: =RFQ_!#REF! -> #REF! | B26: =DATA!K372 -> 0 | F26: =SUM(D26*E26) -> 0 | J26: 18. Fund Cluster - fund cluster name/code in accordance with the UACS
A27: =RFQ_!#REF! -> #REF! | B27: =DATA!K373 -> 0 | C27: =PR!D31 -> Designing of Applied Qualitative Research, Davies, 2024, 9781984658661, Wiseman's Book Trading, Inc. | D27: =DATA!J373 -> 0 | E27: =DATA!N205 -> 0 | F27: =SUM(D27*E27) -> 0 | J27: 19. Funds Available - amount of funds available which shall be certified by the Chief Accountant/Head of Accounting Division/Unit
A28: =RFQ_!#REF! -> #REF! | B28: =DATA!K374 -> 0 | C28: =PR!D32 -> Encyclopedia of Earth Science, Malode, 2024, 9781774693902, Wiseman's Book Trading, Inc. | D28: =DATA!J374 -> 0 | E28: =DATA!N206 -> 0 | F28: =SUM(D28*E28) -> 0 | J28: 20. ORS/BURSNo., Date and Amount - ORS/BURS number assigned by the Budget Division/Unit, date of the ORS/BURS and the amount of obligation supporting the purchase
A29: =RFQ_!#REF! -> #REF! | B29: =DATA!K375 -> 0 | C29: =PR!D33 -> Assessment in learning 1 (Traditional Assessment) OBE Approach, Abrogena, 2024, Big Faith Trading | D29: =DATA!J375 -> 0 | E29: =DATA!N207 -> 0 | F29: =SUM(D29*E29) -> 0 | I29: C. It shall be prepared in four (4) copies distributed as follows:
A30: =RFQ_!#REF! -> #REF! | B30: =DATA!K376 -> 0 | C30: =PR!D34 -> Assessment Learning 1 : A Modular Approach, 2ed, Boholano, 2023, Big Faith Trading | D30: =DATA!J376 -> 0 | E30: =DATA!N208 -> 0 | F30: =SUM(D30*E30) -> 0 | J30: Original - to the supplier for conforme to the terms of the PO and as attachment to the DV upon request for payment
A31: =RFQ_!#REF! -> #REF! | B31: =DATA!K377 -> 0 | C31: =PR!D35 -> Assessment Learning 2 : A Modular Approach, Sanchez, 2023, Big Faith Trading | D31: =DATA!J377 -> 0 | E31: =DATA!N209 -> 0 | F31: =SUM(D31*E31) -> 0 | J31: Copy 2 - retained by the Supply and/or Property Division Unit for file
A32: =RFQ_!#REF! -> #REF! | B32: =DATA!K378 -> 0 | C32: =PR!D36 -> Assessment of Learning 1 Obe Approach, Manas, 2024, Big Faith Trading | D32: =DATA!J378 -> 0 | E32: =DATA!N210 -> 0 | F32: =SUM(D32*E32) -> 0 | J32: Copy 3 - to be submitted to COA within five (5) days after conformity by the supplier
A33: =RFQ_!#REF! -> #REF! | B33: =DATA!K379 -> 0 | C33: =PR!D37 -> Building and enhancing New Literacies Across the Curriculum OBE-& PPST-based, De Leon, 2020, Big Faith Trading | D33: =DATA!J379 -> 0 | E33: =DATA!N211 -> 0 | F33: =SUM(D33*E33) -> 0 | J33: Copy 4 - Supplier's copy
A34: =RFQ_!#REF! -> #REF! | B34: =DATA!K380 -> 0 | C34: =PR!D38 -> Facilitating Learner-Centered Teaching 5e OBE-&PPST-Based, Lucas & Corpuz, 2020, Big Faith Trading | D34: =DATA!J380 -> 0 | E34: =DATA!N212 -> 0 | F34: =SUM(D34*E34) -> 0
A35: =RFQ_!#REF! -> #REF! | B35: =DATA!K381 -> 0 | C35: =PR!D39 -> Facilitating Student-Centered Teaching & Learning, Larioque, et al., 2024, Big Faith Trading | D35: =DATA!J381 -> 0 | E35: =DATA!N213 -> 0 | F35: =SUM(D35*E35) -> 0
A36: =RFQ_!#REF! -> #REF! | B36: =DATA!K382 -> 0 | C36: =PR!D40 -> Field Study 2, Boholano, et al, 2022, Big Faith Trading | D36: =DATA!J382 -> 0 | E36: =DATA!N214 -> 0 | F36: =SUM(D36*E36) -> 0
A37: =RFQ_!#REF! -> #REF! | B37: =DATA!K383 -> 0 | C37: =PR!D41 -> Field Study 2 Participation and Teaching Assistanship OBE- & PPST, Lucas, et al., 2021, Big Faith Trading | D37: =DATA!J383 -> 0 | E37: =DATA!N215 -> 0 | F37: =SUM(D37*E37) -> 0
A38: =RFQ_!#REF! -> #REF! | B38: =DATA!K384 -> 0 | C38: =PR!D42 -> Field Study 2 Participation and Teaching Assistanship OBE 2e, Brawner, 2023, Big Faith Trading | D38: =DATA!J384 -> 0 | E38: =DATA!N216 -> 0 | F38: =SUM(D38*E38) -> 0
A39: =RFQ_!#REF! -> #REF! | B39: =DATA!K385 -> 0 | C39: =PR!D43 -> Foundations of Special and Inclusive Education, Gil, 2025, Big Faith Trading | D39: =DATA!J385 -> 0 | E39: =DATA!N217 -> 0 | F39: =SUM(D39*E39) -> 0
A40: =RFQ_!#REF! -> #REF! | B40: =DATA!K386 -> 0 | C40: =PR!D44 -> Foundations of Special and Inclusive Education, Aligada-Halal, et al., 2020, Big Faith Trading | D40: =DATA!J386 -> 0 | E40: =DATA!N218 -> 0 | F40: =SUM(D40*E40) -> 0
A41: =RFQ_!#REF! -> #REF! | B41: =DATA!K387 -> 0 | C41: =PR!D45 -> Physical Activity Towards Health and Fitness PATHFIT( Dance, Fitness, Tradition), Aquino, 2024, Big Faith Trading | D41: =DATA!J387 -> 0 | E41: =DATA!N219 -> 0 | F41: =SUM(D41*E41) -> 0
A42: =RFQ_!#REF! -> #REF! | B42: =DATA!K388 -> 0 | C42: =PR!D46 -> Physical Activity Towards Health and Fitness PATHFIT(Arnis), Dela Cruz, 2024, Big Faith Trading | D42: =DATA!J388 -> 0 | E42: =DATA!N220 -> 0 | F42: =SUM(D42*E42) -> 0
A43: =RFQ_!A24 -> 011 | B43: =DATA!K389 -> 0 | C43: =PR!D47 -> Qualitative Research, Macapagal/Sombilo, 2024, Big Faith Trading | D43: =DATA!J389 -> 0 | E43: =DATA!N221 -> 0 | F43: =SUM(D43*E43) -> 0
A44: =RFQ_!A25 -> 012 | B44: =DATA!K390 -> 0 | C44: =PR!D48 -> Teaching Science in the Elementary Grades Vol. 2: Physics, Earth and Space OBE- & PPST based, Bilbao, 2024, Big Faith Trading | D44: =DATA!J390 -> 0 | E44: =DATA!N222 -> 0 | F44: =SUM(D44*E44) -> 0
A45: =RFQ_!A26 -> 013 | B45: =DATA!K391 -> 0 | C45: =PR!D49 -> The Teacher and the Community, School Culture and Organizational Leadership, Serrano, 2020, Big Faith Trading | D45: =DATA!J391 -> 0 | E45: =DATA!N223 -> 0 | F45: =SUM(D45*E45) -> 0
A46: =RFQ_!A27 -> 014 | B46: =DATA!K392 -> 0 | C46: =PR!D50 -> The Teacher and the Community, School Culture, and Organizational Leadership, Boholano, 2024, Big Faith Trading | D46: =DATA!J392 -> 0 | E46: =DATA!N224 -> 0 | F46: =SUM(D46*E46) -> 0
A47: =RFQ_!A28 -> 015 | B47: =DATA!K393 -> 0 | C47: =PR!D51 -> The Teacher and the School Curriculum, Fernando & Oamil, 2022, Big Faith Trading | D47: =DATA!J393 -> 0 | E47: =DATA!N225 -> 0 | F47: =SUM(D47*E47) -> 0
A48: =RFQ_!A29 -> 016 | B48: =DATA!K394 -> 0 | C48: =PR!D52 -> The Teacher and the School Curriculum Obe Approach, Otinero-Gallardo, 2024, Big Faith Trading | D48: =DATA!J394 -> 0 | E48: =DATA!N226 -> 0 | F48: =SUM(D48*E48) -> 0
A49: =RFQ_!A30 -> 017 | B49: =DATA!K395 -> 0 | C49: =PR!D53 -> The Teaching Profession, Fernando, et al., 2024, Big Faith Trading | D49: =DATA!J395 -> 0 | E49: =DATA!N227 -> 0 | F49: =SUM(D49*E49) -> 0
A50: =RFQ_!A31 -> 018 | B50: =DATA!K396 -> 0 | C50: =PR!D54 -> English/Purposive Communication (A Modular Approach), Gutierrez-Ang, 2023, Big Faith Trading | D50: =DATA!J396 -> 0 | E50: =DATA!N228 -> 0 | F50: =SUM(D50*E50) -> 0
A51: =RFQ_!A54 -> 062 | B51: =DATA!K419 -> 0 | C51: =PR!D55 -> Artificial Intelligence and Quantum Computing, Schweinfurth, 2025, 9789362241931, Wiseman's Book Trading, Inc. | D51: =DATA!J419 -> 0 | E51: =DATA!N229 -> 0 | F51: =SUM(D51*E51) -> 0
A52: =RFQ_!A55 -> 063 | B52: =DATA!K420 -> 0 | C52: =PR!D56 -> Basic Computer Coding: Java Script 3rd/ed, Gbadegesin, 2024, 9781984689337, Wiseman's Book Trading, Inc. | D52: =DATA!J420 -> 0 | E52: =DATA!N230 -> 0 | F52: =SUM(D52*E52) -> 0
A53: =RFQ_!A56 -> 064 | B53: =DATA!K421 -> 0 | C53: =PR!D57 -> Electronics All-in-One For Dummies, 3rd edition, Lowe, 2022, 978-1119822110, https://www.amazon.com | D53: =DATA!J421 -> 0 | E53: =DATA!N231 -> 0 | F53: =SUM(D53*E53) -> 0
A54: =RFQ_!A57 -> 065 | B54: =DATA!K422 -> 0 | C54: =PR!D58 -> Practical Electronics for Inventors, 4th Edition, Scherz & Monk, 2016, 9.78126E+12, https://www.amazon.com | D54: =DATA!J422 -> 0 | E54: =DATA!N232 -> 0 | F54: =SUM(D54*E54) -> 0
A55: =RFQ_!A58 -> 066 | B55: =DATA!K423 -> 0 | C55: =PR!D59 -> Make: Electronics: Learning by Discovery: A hands-on primer for the new electronics enthusiast 3rd Edition, Platt, 2021, 978-1680456875, https://www.amazon.com | D55: =DATA!J423 -> 0 | E55: =DATA!N233 -> 0 | F55: =SUM(D55*E55) -> 0
A56: =RFQ_!A59 -> 067 | B56: =DATA!K424 -> 0 | C56: =PR!D60 -> Electronic Devices and Curcuits Theory, Boylestad & Nashelsky, latest ed., https://www.amazon.com | D56: =DATA!J424 -> 0 | E56: =DATA!N234 -> 0 | F56: =SUM(D56*E56) -> 0
A57: =RFQ_!A60 -> 068 | B57: =DATA!K425 -> 0 | C57: =PR!D61 -> Digital Fundamentals, Floyd, latest ed., https://www.amazon.com/Digital-Fundamentals-11th-Thomas-Floyd/dp/0132737965 | D57: =DATA!J425 -> 0 | E57: =DATA!N235 -> 0 | F57: =SUM(D57*E57) -> 0
A58: =RFQ_!A61 -> 069 | B58: =DATA!K426 -> 0 | C58: =PR!D62 -> Microelectronics circuits, Sedra & Smith, latest ed., https://www.amazon.com/Microelectronic-Circuits-Electrical-Computer-Engineering/dp/0195323033 | D58: =DATA!J426 -> 0 | E58: =DATA!N236 -> 0 | F58: =SUM(D58*E58) -> 0
A59: =RFQ_!A62 -> 070 | B59: =DATA!K427 -> 0 | C59: =PR!D63 -> The art of electronics, Horowitz & Hill, latest ed., https://www.amazon.com/Art-Electronics-Paul-Horowitz/dp/0521809266 | D59: =DATA!J427 -> 0 | E59: =DATA!N237 -> 0 | F59: =SUM(D59*E59) -> 0
A60: =RFQ_!A63 -> 071 | B60: =DATA!K428 -> 0 | C60: =PR!D64 -> Industrial electronics, Rehg & Sartori, latest ed., https://www.amazon.com/Industrial-Electronics-James-Rehg/dp/0132064189 | D60: =DATA!J428 -> 0 | E60: =DATA!N238 -> 0 | F60: =SUM(D60*E60) -> 0
A61: =RFQ_!A64 -> 072 | B61: =DATA!K429 -> 0 | C61: =PR!D65 -> Environmental and Atmospheric Chemistry, Devi, 2023 9789395431309, Wiseman's Book Trading | D61: =DATA!J429 -> 0 | E61: =DATA!N239 -> 0 | F61: =SUM(D61*E61) -> 0
A62: =RFQ_!A65 -> 073 | B62: =DATA!K430 -> 0 | C62: =PR!D66 -> Ecology in Action \2ed., Singer, Fred D., 2025, 9781108927222, Forefront Books | D62: =DATA!J430 -> 0 | E62: =DATA!N240 -> 0 | F62: =SUM(D62*E62) -> 0
... A86: =RFQ_!A89 -> 097 | B86: =DATA!K454 -> 0 | C86: =PR!D90 -> 0 | D86: =DATA!J454 -> 0 | E86: =DATA!N264 -> 0 | F86: =SUM(D86*E86) -> 0
A87: TOTAL | C87: **TWELVE THOUSAND PESOS ONLY ** | F87: =SUM(F12:F20) -> 12000
A88: Purpose | C88: for the program/activities/project of (CBAO) use to ensure proper organization & secure storage of CBAO documents to be charged to Fund 164
A89: In case of failure to make the full delivery within the time specified above, a penalty of one-tenth
A90: (1/10) of one percent for everyday of delay shall be imposed.
E95: Very truly yours,
A98: Conforme: | D98: DJOVI REGALA DURANTE,DPA
D100: SUC President I
A101: (Signature over printed name)
A102: Date: ____________________
A104: Funds Cluster: | E104: ORS/BURS No.
A105: Funds Available: | E105: Date of the ORS/BURS:
E107: Amount: | F107: =F87 -> 12000
C108: RHEA ANGELLICA B. ADDATU,CPA
C109: Accountant I
A110: Note: See PO instructions at the back | D110: Ref. No.: | E110: =PR!B12 -> 2505-GAS5-190

Sheet POback (2)
A1: INSTRUCTIONS
A3: A. The PO is a form/document used by the agency/entity, addressed to supplier, to deliver specific quantities of supplies/goods/property subject to the terms and conditions contained in the PO.
A4: B. This form shall be accomplished as follows:
B5: 1. Entity Name - name of the agency/entity
B6: 2. Supplier/Address/TIN - name, address and TIN of the supplier
B7: 3. P.O. No. - the number assigned to the PO which shall be as follows:
C8: 0000-00-0000 | E8: Serial number (one series for each year)
E9: Month
E10: Year
B11: 4. Date - date of the preparation of the PO
B12: 5. Mode of Procurement - mode of procurement such as public bidding, through Procurement Service, limited source bidding, direct contracting, repeat order, shopping and negotiated procurement in accordance with RA 9184
B13: 6. Place/Date of Delivery - place of delivery and definite date/s of delivery; if not stated, the date of delivery shall mean seven (7) calendar days after the receipt of PO by the supplier
B14: 7. Delivery Term - delivery term i.e., FOB destination, FOB shipping point
B15: 8. Payment Term - specified period required when the delivered goods shall be paid and discounts, if any, such as 2/10, n/30
B16: 9. Stock/Property No. - stock/property number of the goods to be purchased as provided by the Supply and/or Property Division Unit
B17: 10. Unit - unit of measurement of the supplies/goods/property being procured (i.e. piece, roll, box, reams, etc.)
B18: 11. Description - brief description of the supplies/goods/property being procured
B19: 12. Quantity - quantity of supplies/goods/property being procured
B20: 13. Unit Cost - cost per unit of the supplies/goods/property being procured
B21: 14. Amount - total amount of the supplies/goods/property being procured (Quantity x Unit Cost)
B22: 15. Penalty Clause - penalty to be imposed by the agency/entity in case of non-compliance with the term, that is, one-tenth (1/10) of one percent (1%) for every day of delay on the undelivered item/s
... B27: 20. ORS/BURSNo., Date and Amount - ORS/BURS number assigned by the Budget Division/Unit, date of the ORS/BURS and the amount of obligation supporting the purchase
A28: C. It shall be prepared in four (4) copies distributed as follows:
B29: Original - to the supplier for conforme to the terms of the PO and as attachment to the DV upon request for payment
B30: Copy 2 - retained by the Supply and/or Property Division Unit for file
B31: Copy 3 - to be submitted to COA within five (5) days after conformity by the supplier
B32: Copy 4 - Supplier's copy

Sheet ChkDocs
B1: PR No.: | C1: 23-181 | D1: -------------------cut here-------------------cut here-------------------cut here-------------------cut here-------------------cut here------------------- | E1: PR No.: | F1: =C1 -> 23-181 | G1: -------------------cut here-------------------cut here-------------------cut here-------------------cut here-------------------cut here------------------- | H1: PR No.: | I1: =C1 -> 23-181
B2: Checklist of Documents Submitted: | E2: Checklist of Documents Submitted: | H2: Checklist of Documents Submitted:
C3: Management Monitoring Slip | F3: Management Monitoring Slip | I3: Management Monitoring Slip
B4: X | C4: Purchase Request | E4: X | F4: Purchase Request | H4: X | I4: Purchase Request
C5: Pre and Post Inspection Report | F5: Pre and Post Inspection Report | I5: Pre and Post Inspection Report
B6: X | C6: OBR | E6: X | F6: OBR | H6: X | I6: OBR
B7: X | C7: BAC Resolution | E7: =B7 -> X | F7: BAC Resolution | H7: =B7 -> X | I7: BAC Resolution
B8: X | C8: Approval of BAC Resolution on SVP | E8: =B8 -> X | F8: Approval of BAC Resolution on SVP | H8: =B8 -> X | I8: Approval of BAC Resolution on SVP
B9: X | C9: RFQ1 | E9: =B9 -> X | F9: RFQ1 | H9: =B9 -> X | I9: RFQ1
B10: X | C10: RFQ2 | E10: =B10 -> X | F10: RFQ2 | H10: =B10 -> X | I10: RFQ2
B11: X | C11: RFQ3 | E11: =B11 -> X | F11: RFQ3 | H11: =B11 -> X | I11: RFQ3
B12: X | C12: Acknowledgment for Request for Quotation | E12: =B12 -> X | F12: Acknowledgment for Request for Quotation | H12: =B12 -> X | I12: Acknowledgment for Request for Quotation
C13: Abstract of Bids | E13: =B13 -> 0 | F13: Abstract of Bids | H13: =B13 -> 0 | I13: Abstract of Bids
B14: X | C14: BAC Resolution for Award | E14: =B14 -> X | F14: BAC Resolution for Award | H14: =E14 -> X | I14: BAC Resolution for Award
B15: X | C15: Approval of Reso. for Award | E15: =B15 -> X | F15: Approval of Reso. for Award | H15: =E15 -> X | I15: Approval of Reso. for Award
B16: X | C16: Letter of Notice | E16: =B16 -> X | F16: Letter of Notice | H16: =B16 -> X | I16: Letter of Notice
B17: X | C17: Notice to Proceed | E17: =B17 -> X | F17: Notice to Proceed | I17: Notice to Proceed
B18: X | C18: Certification of BAC | E18: =B18 -> X | F18: Certification of BAC | H18: =B18 -> X | I18: Certification of BAC
C19: Waste Materials Report/Pre & Post Repair Inspection | E19: =B19 -> 0 | F19: Waste Materials Report/Pre & Post Repair Inspection | H19: =B19 -> 0 | I19: Waste Materials Report/Pre & Post Repair Inspection
B20: X | C20: Purchase Order (PO) | E20: =B20 -> X | F20: Purchase Order (PO) | H20: =B20 -> X | I20: Purchase Order (PO)
B21: X | C21: Charge/Sales Invoice | E21: =B21 -> X | F21: Charge/Sales Invoice | H21: =B21 -> X | I21: Charge/Sales Invoice
B22: X | C22: IAR | E22: X | F22: IAR | H22: X | I22: IAR
C23: Inventory Custodian Slip (ICS) | E23: =B23 -> 0 | F23: Inventory Custodian Slip (ICS) | H23: =B23 -> 0 | I23: Inventory Custodian Slip (ICS)
B24: X | C24: RIS | E24: X | F24: RIS | H24: X | I24: RIS
C25: (3)ARE # 221111LLB,DRD,AAM-ARE | F25: =C25 -> (3)ARE # 221111LLB,DRD,AAM-ARE | H25: =B25 -> 0 | I25: =C25 -> (3)ARE # 221111LLB,DRD,AAM-ARE
C26: PhilGEPS Bid Notice Abstract ref #9477623 | E26: =B26 -> 0 | F26: =C26 -> PhilGEPS Bid Notice Abstract ref #9477623 | H26: =B26 -> 0 | I26: =C26 -> PhilGEPS Bid Notice Abstract ref #9477623
C27: MOA | F27: MOA | I27: MOA
B28: X | C28: PPMP for CY2021 | E28: =B28 -> X | F28: =C28 -> PPMP for CY2021 | H28: =B28 -> X | I28: =C28 -> PPMP for CY2021
C29: Attendance Sheet | E29: =B29 -> 0 | F29: Attendance Sheet | H29: =B29 -> 0 | I29: Attendance Sheet
C30: Recipient of load | E30: =B30 -> 0 | F30: Recipient of load | H30: =B30 -> 0 | I30: Recipient of load
B31: Received by: | E31: Received by: | H31: Received by:
C33: (Signature over Printed Name/Date) | F33: (Signature over Printed Name/Date) | I33: (Signature over Printed Name/Date)
B34: Note: Please return one (1) copy to Supply section for filing purposes. Thank you. | E34: Note: Please return one (1) copy to Supply section for filing purposes. Thank you. | H34: Note: Please return one (1) copy to Supply section for filing purposes. Thank you.
B35: SS Form 14/001 (A) | E35: SS Form 14/001 (B) | H35: SS Form 14/001©
D36: "
B40: +

Sheet AResoSVP -Emergency
A1: BATANES STATE COLLEGE
A2: Basco, Batanes
A4: Approval of BAC Resolution Recommending Emergency Procurement of the Project: Supply and Installation of 50KVA Transformer
B6: BAC Resolution No. | D6: =PR!B12 -> 2505-GAS5-190
A8: WHEREAS, Section 53 Rule XVI of the Revised Implementing Rules and Regulations of RA 9184
A9: allows Negotiated Mode of Procurement subject to prior approval of the HOPE thru Annual
A10: Procurement Plan (APP) and only to promote economy and efficiency;
A12: WHEREAS, Section 53.2 allows Emergency Cases in case of imminent danger to life or property
A13: during state of calamity, or when time is of the essence arising from natural or man-made calamities or other
A14: causes where immediate action is necessary to prevent damage to or loss of life or property, or to
A15: restore vital public services, infrastructure facilities and other public utilities;
A17: WHEREAS, "Annex H" of the Consolidated Guidelines for Emergency Cases prescribed under
A18: Section V, Paragraph D.2.b.,upon submission of request and other supporting documents identifying
A19: the emergency sought to be addressed, the BAC shall prepare the appropriate procurement
A20: documents and directly negotiate with a supplier, contractor, or consultant with technical, legal and
A21: financial capability to deliver the goods, execute the works and perform the services to address the emergency;
... A24: the HOPE, upon the recommendation of the BAC, shall immediately award the contract to the Supplier, Contractor or Consultant;
A25: WHEREAS, Purchase Request No. | D25: =PR!E9 -> 2025-190 | E25: involves the procurement of
A26: =PR!B69 -> for program/projects/activities of information Technology Unit charged to cost to operate of admin. Bldg.
A27: with the Approved Budget of | D27: =PR!H68 -> 650000
A28: WHEREAS, the default mode of evaluation shall be on a lot basis which means that the
A29: determination of the single/lowest calculated and responsive bid (S/LCRB) is the total amount of offered
A30: unit price multiply by the required quantity;
A32: NOW THEREFORE, I, DR.DJOVI R. DURANTE, Director for Admin & Finance Services by virtue of
A33: the authority vested in me by the Board of Trustees of this Institution and after taking into consideration
A34: the merits and legal bases of the recommendation of the members of the Bids and Awards Committee (BAC)
A35: do hereby APPROVE the foregoing recommendation and adoption of Negotiated Mode of Procurement
A36: under Emergency Case;
A38: APPROVED FINALLY, at the Batanes State College, this | F38: ___________________
B41: DJOVI REGALA DURANTE,DPA
B42: SUC President I
A47: BRYAN H. CIELO
A48: DELMA G. MALUPA-ABAD
A49: EDWIN F.MACABALLUG, Ph.D.
A50: LIEZL P. DELA CRUZ
A51: RODERICK Y. ABAD
A52: VILMA D. BACCAY
A53: ESTEBAN C. BADAJOS
A54: LEOBERT L. BANZALI
A55: MIAH DAPHNIE B. BUENAFE
A56: GLORIA N. CABIZON
A57: FORTUNATO PHILIP A. CABUGAO
A58: RICARDO Q. CABUGAO, JR.
... A103: EMILYN D. ALUETA

Sheet ResoSVP -Emergency
A1: BATANES STATE COLLEGE
A2: Basco, Batanes
A4: BAC Resolution Recommending Emergency Procurement of the Project: Supply and Installation of 50KVA Transformer
B6: BAC Resolution No. | D6: =PR!B12 -> 2505-GAS5-190
A8: WHEREAS, Section 53 Rule XVI of the Revised Implementing Rules and Regulations of RA 9184
A9: allows Negotiated Mode of Procurement subject to prior approval of the HOPE thru Annual
A10: Procurement Plan (APP) and only to promote economy and efficiency;
A12: WHEREAS, Section 53.2 allows Emergency Cases in case of imminent danger to life or property
A13: during state of calamity, or when time is of the essence arising from natural or man-made calamities or other
A14: causes where immediate action is necessary to prevent damage to or loss of life or property, or to
A15: restore vital public services, infrastructure facilities and other public utilities;
A17: WHEREAS, "Annex H" of the Consolidated Guidelines for Emergency Cases prescribed under
A18: Section V, Paragraph D.2.b.,upon submission of request and other supporting documents identifying
A19: the emergency sought to be addressed, the BAC shall prepare the appropriate procurement
A20: documents and directly negotiate with a supplier, contractor, or consultant with technical, legal and
A21: financial capability to deliver the goods, execute the works and perform the services to address the emergency;
... A24: the HOPE, upon the recommendation of the BAC, shall immediately award the contract to the Supplier, Contractor or Consultant;
A25: WHEREAS, Purchase Request No. | D25: =PR!E9 -> 2025-190 | E25: involves the procurement of
A26: =PR!B69 -> for program/projects/activities of information Technology Unit charged to cost to operate of admin. Bldg.
A27: with the Approved Budget of | D27: =PR!H68 -> 650000
A28: WHEREAS, the default mode of evaluation shall be on a lot basis which means that the
A29: determination of the single/lowest calculated and responsive bid (S/LCRB) is the total amount of offered
A30: unit price multiply by the required quantity;
A32: NOW THEREFORE, we, the members of the Bids and Awards Committee hereby RESOLVE to recommend to the HOPE to adopt Negotiated Mode of Procurement under Emergency Cases for the said transaction;
A33: RESOLVED FINALLY, at the Batanes State College, this
A34: Recommending Approval:
A37: RHOUPHELINE AYA A. CADIZ | C37: RANDALL G. CASTILLO | E37: EMILYN D. ALUETA
A38: BAC Member | C38: BAC Member | E38: BAC Member
A41: =PR!B73 -> JOHN MICHAEL A. VILLASPIR | E41: FORTUNATO PHILIP A. CABUGAO
A42: End-User/Provisional Member | E42: BAC Chairperson
A47: BRYAN H. CIELO
A48: DELMA G. MALUPA-ABAD
A49: EDWIN F.MACABALLUG, Ph.D.
A50: LIEZL P. DELA CRUZ
A51: RODERICK Y. ABAD
A52: VILMA D. BACCAY
A53: ESTEBAN C. BADAJOS
A54: LEOBERT L. BANZALI
A55: MIAH DAPHNIE B. BUENAFE
A56: GLORIA N. CABIZON
A57: FORTUNATO PHILIP A. CABUGAO
A58: RICARDO Q. CABUGAO, JR.
... A103: EMILYN D. ALUETA

Sheet ResoSoSVP(Direct Contracting)
A5: BAC Resolution Recommending Alternative Mode of Procurement under Direct Contracting for the Renewal of the materials,garland and labor for the Investiture Program
B7: BAC Resolution No. | D7: =PR!B12 -> 2505-GAS5-190
A9: WHEREAS, Rule XVI of the Revised Implementing Rules and Regulations of RA 9184
A10: allows Alternative Mode of Procurement subject to prior approval of the HOPE thru Annual
A11: Procurement Plan (APP) and only to promote economy and efficiency;
A13: WHEREAS, Section 50(c) allows Direct Contracting in cases where Procuring Entity intends to procure
A14: goods form an exclusive local manufacturer, supplier, distributor, or dealer for which no suitable
A15: substitute can be obtained at more advantageous terms to the GoP.
A17: WHEREAS, "Annex H" of the Consolidated Guidelines for Direct Contracting prescribed under
A18: Section V, Paragraph A.2.,upon submission of request and other supporting documents
A19: the BAC shall prepare the RFQ or pro-forma invoice together with the term and conditions of sale,
A20: and shall send the same to the identified direct supplier.
A21: WHEREAS, the BAC shall ensure that the supplier is technically, legally and financially capable
A22: to deliver the goods at the most advantageous price and contract for the Government
... A25: contract to the Supplier, Contractor or dealer.
A26: WHEREAS, Purchase Request No. | D26: =PR!E9 -> 2025-190 | E26: involves the procurement of
A27: =PR!B69 -> for program/projects/activities of information Technology Unit charged to cost to operate of admin. Bldg.
A28: with the Approved Budget of | D28: =PR!H68 -> 650000
A29: WHEREAS, the default mode of evaluation shall be on a lot basis which means that the
A30: determination of the single/lowest calculated and responsive bid (S/LCRB) is the total amount of offered
A31: unit price multiply by the required quantity;
A33: NOW THEREFORE, we, the members of the Bids and Awards Committee hereby RESOLVE to recommend to the HOPE to adopt Negotiated Mode of Procurement under Direct Contracting for the said transaction;
A34: RESOLVED FINALLY, at the Batanes State College, this
A35: Recommending Approval:
A38: RHOUPHELINE AYA A. CADIZ | C38: RANDALL G. CASTILLO | E38: EMILYN D. ALUETA
A39: BAC Member | C39: BAC Member | E39: BAC Member
A42: =PR!B73 -> JOHN MICHAEL A. VILLASPIR | C42: FORTUNATO PHILIP A. CABUGAO | E42: DOREEN C. CASTILLO
A43: End-User/Provisional Member | C43: BAC Vice Chairperson | E43: BAC Chairperson
A48: BRYAN H. CIELO
A49: DELMA G. MALUPA-ABAD
A50: EDWIN F.MACABALLUG, Ph.D.
A51: LIEZL P. DELA CRUZ
A52: RODERICK Y. ABAD
A53: VILMA D. BACCAY
A54: ESTEBAN C. BADAJOS
A55: LEOBERT L. BANZALI
A56: MIAH DAPHNIE B. BUENAFE
A57: GLORIA N. CABIZON
A58: FORTUNATO PHILIP A. CABUGAO
A59: RICARDO Q. CABUGAO, JR.
... A104: EMILYN D. ALUETA

Sheet AResoSoSVP(Direct Contractin (2
A5: Approval of BAC Resolution Recommending Alternative Mode of Procurement under Direct Contracting for the materials,garland and labor for the Investiture Program
B7: BAC Resolution No. | D7: =PR!B12 -> 2505-GAS5-190
A9: WHEREAS, Rule XVI of the Revised Implementing Rules and Regulations of RA 9184
A10: allows Alternative Mode of Procurement subject to prior approval of the HOPE thru Annual
A11: Procurement Plan (APP) and only to promote economy and efficiency;
A13: WHEREAS, Section 50(c) allows Direct Contracting in cases where Procuring Entity intends to procure
A14: goods form an exclusive local manufacturer, supplier, distributor, or dealer for which no suitable
A15: substitute can be obtained at more advantageous terms to the GoP.
A17: WHEREAS, "Annex H" of the Consolidated Guidelines for Direct Contracting prescribed under
A18: Section V, Paragraph A.2.,upon submission of request and other supporting documents
A19: the BAC shall prepare the RFQ or pro-forma invoice together with the term and conditions of sale,
A20: and shall send the same to the identified direct supplier.
A21: WHEREAS, the BAC shall ensure that the supplier is technically, legally and financially capable
A22: to deliver the goods at the most advantageous price and contract for the Government
... A25: contract to the Supplier, Contractor or dealer.
A26: WHEREAS, Purchase Request No. | D26: =PR!E9 -> 2025-190 | E26: involves the procurement of
A27: =PR!B69 -> for program/projects/activities of information Technology Unit charged to cost to operate of admin. Bldg.
A28: with the Approved Budget of | D28: =PR!H68 -> 650000
A29: WHEREAS, the default mode of evaluation shall be on a lot basis which means that the
A30: determination of the single/lowest calculated and responsive bid (S/LCRB) is the total amount of offered
A31: unit price multiply by the required quantity;
A33: NOW THEREFORE, I, DR.DJOVI R. DURANTE, Director for Admin & Finance Services by virtue of
A34: the authority vested in me by the Board of Trustees of this Institution and after taking into consideration
A35: the merits and legal bases of the recommendation of the members of the Bids and Awards Committee (BAC)
A36: do hereby APPROVE the foregoing recommendation and adoption of Alternative Mode of Procurement
A37: under Direct Contracting;
A39: APPROVED FINALLY, at the Batanes State College, this | F39: ___________________
B42: DJOVI REGALA DURANTE,DPA
B43: SUC President I
A48: BRYAN H. CIELO
A49: DELMA G. MALUPA-ABAD
A50: EDWIN F.MACABALLUG, Ph.D.
A51: LIEZL P. DELA CRUZ
A52: RODERICK Y. ABAD
A53: VILMA D. BACCAY
A54: ESTEBAN C. BADAJOS
A55: LEOBERT L. BANZALI
A56: MIAH DAPHNIE B. BUENAFE
A57: GLORIA N. CABIZON
A58: FORTUNATO PHILIP A. CABUGAO
A59: RICARDO Q. CABUGAO, JR.
... A104: EMILYN D. ALUETA

Sheet Abstract (Failed)
B3: ABSTRACT OF QUOTATIONS
B5: (x) Furnishing/delivery of supplies, and materials or equipment | H5: Bids opened at Basco, Batanes
B6: ( x ) Furnishing Labor, services, etc. | H6: Date | I6: =NOW() -> 46148.737
B7: ( ) Rental or use of transportation facilities equipment, quarters, rooms, lot or space, etc.
B8: To be furnished at the | D8: BATANES STATE COLLEGE
D9: (State place or site of Office or project where articles or services be furnished or returned)
A10: NAME OF ARTICLES OR SERVICES TO BE FURNISHED, RENDERED OR FACILITIES TO BE RENTED | K10: Valiente Food Producer | M10: Valiente Food Producer
F11: JPM Gen. Mdse. & Hardware | G11: GDP Trading | H11: FVA Trading
A13: =PR!D16 -> Single Face P4 HD Outdoor LED Screen (rear maintenance), Full Set Up including controller (Novastar) & receiving card (Novastar) warranty, after sales support & training controller (novastar) & receiving card (novastar)warranty , after sales support & training size: 2.88M x 2.88M (9 panels) screen resolution; 720 pixels (W) x 720 pixels (H) Type; movable frame Accessories: replacement module , replacemenr power supply,replacement receiving card,power cable,signal cable FREE: LED control software Training and Support | F13: none | G13: none | H13: no bid
A14: =PR!D17 -> 0 | F14: none | G14: none | H14: no bid
A15: =PR!D18 -> 0 | F15: none | G15: none | H15: no bid
A16: =PR!D19 -> 0 | F16: none | G16: none | H16: no bid
A17: =PR!D20 -> 0 | F17: none | G17: none | H17: no bid
A18: =PR!D21 -> 0 | F18: none | G18: none | H18: no bid
A19: =PR!D22 -> 0 | F19: none | G19: none | H19: no bid
A20: =PR!D23 -> 0 | F20: none | G20: none | H20: no bid
A21: =PR!D24 -> 0 | F21: none | G21: none | H21: no bid
A22: =PR!D25 -> 0 | F22: none | G22: none | H22: no bid
A23: =PR!D26 -> 0 | F23: none | G23: none | H23: no bid
A24: =PR!D27 -> 0 | F24: none | G24: none | H24: no bid
... A54: =PR!D57 -> Electronics All-in-One For Dummies, 3rd edition, Lowe, 2022, 978-1119822110, https://www.amazon.com | F54: none | G54: none | H54: no bid
A55: =PR!D58 -> Practical Electronics for Inventors, 4th Edition, Scherz & Monk, 2016, 9.78126E+12, https://www.amazon.com | F55: none | G55: none | H55: no bid | K55: none
A56: =PR!D59 -> Make: Electronics: Learning by Discovery: A hands-on primer for the new electronics enthusiast 3rd Edition, Platt, 2021, 978-1680456875, https://www.amazon.com | F56: none | G56: none | H56: no bid | K56: none
A57: =PR!D60 -> Electronic Devices and Curcuits Theory, Boylestad & Nashelsky, latest ed., https://www.amazon.com | F57: none | G57: none | H57: no bid | K57: none
A58: =PR!D61 -> Digital Fundamentals, Floyd, latest ed., https://www.amazon.com/Digital-Fundamentals-11th-Thomas-Floyd/dp/0132737965 | F58: none | G58: none | H58: no bid | K58: none
A59: =PR!D62 -> Microelectronics circuits, Sedra & Smith, latest ed., https://www.amazon.com/Microelectronic-Circuits-Electrical-Computer-Engineering/dp/0195323033 | F59: none | G59: none | H59: no bid | K59: none
A60: =PR!D63 -> The art of electronics, Horowitz & Hill, latest ed., https://www.amazon.com/Art-Electronics-Paul-Horowitz/dp/0521809266 | F60: none | G60: none | H60: no bid | K60: none
A61: =PR!D64 -> Industrial electronics, Rehg & Sartori, latest ed., https://www.amazon.com/Industrial-Electronics-James-Rehg/dp/0132064189 | F61: none | G61: none | H61: no bid | K61: none
A62: =PR!D65 -> Environmental and Atmospheric Chemistry, Devi, 2023 9789395431309, Wiseman's Book Trading | F62: none | G62: none | H62: no bid | K62: none
A63: =PR!D66 -> Ecology in Action \2ed., Singer, Fred D., 2025, 9781108927222, Forefront Books | F63: none | G63: none | H63: no bid | K63: none
A64: =PR!D67 -> Environmental Geology \5ed., Reichard, Jim, 2024, 9781266132261, Forefront Book | F64: none | G64: none | H64: no bid | K64: none
A65: =PR!D68 -> 0 | F65: =DATA!O1205 -> 0 | G65: none | H65: none | I65: none | J65: none | K65: none
A66: =PR!D69 -> 0 | F66: =DATA!O1206 -> 0 | G66: none | H66: none | I66: none | J66: none | K66: none
A67: =PR!D70 -> 0 | F67: =DATA!O1207 -> 0 | G67: none | H67: none | I67: none | J67: none | K67: none
A68: =PR!D71 -> 0 | F68: =DATA!O1208 -> 0 | G68: none | H68: none | I68: none | J68: none | K68: none
A69: =PR!D72 -> 0 | F69: =DATA!O1209 -> 0 | G69: none | H69: none | I69: none | J69: none | K69: none
A70: =PR!D73 -> 0 | F70: =DATA!O1210 -> 0 | G70: none | H70: none | I70: none | J70: none | K70: none
A71: =PR!D74 -> 0 | F71: =DATA!O1211 -> 0 | G71: none | H71: none | I71: none | J71: none | K71: none
A72: =PR!D75 -> 0 | F72: =DATA!O1212 -> 0 | G72: none | H72: none | I72: none | J72: none | K72: none
A73: =PR!D76 -> 0 | F73: =DATA!O1213 -> 0 | G73: none | H73: none | I73: none | J73: none | K73: none
A74: =PR!D77 -> 0 | F74: =DATA!O1214 -> 0
A75: =PR!D78 -> 0 | F75: =DATA!O1215 -> 0
A76: =PR!D79 -> 0 | F76: =DATA!O1216 -> 0
A77: =PR!D80 -> 0 | F77: =DATA!O1217 -> 0
A78: =PR!D81 -> 0 | F78: =DATA!O1218 -> 0 | G78: 17000 | H78: 17000 | I78: 17000
A79: =PR!D82 -> 0 | F79: =DATA!O1219 -> 0 | G79: 1500 | H79: 1500 | I79: 1500
A80: =PR!D83 -> 0 | F80: =DATA!O1220 -> 0 | G80: 880 | H80: 880 | I80: 880
A81: =PR!D84 -> 0 | F81: =DATA!O1221 -> 0 | G81: 180 | H81: 180 | I81: 180
A82: =PR!D85 -> 0 | F82: =DATA!O1222 -> 0 | G82: 360 | H82: 360 | I82: 360
A83: =PR!D86 -> 0 | F83: =DATA!O1223 -> 0 | G83: 900 | H83: 900 | I83: 900
A84: =PR!D87 -> 0 | F84: =DATA!O1224 -> 0 | G84: 900 | H84: 900 | I84: 900
A85: =PR!D88 -> 0 | F85: =DATA!O1225 -> 0 | G85: 925 | H85: 925 | I85: 925
A86: =PR!D89 -> 0 | F86: =DATA!O1226 -> 0 | G86: 9300 | H86: 9300 | I86: 9300
A87: =PR!D90 -> 0 | F87: =DATA!O1227 -> 0 | G87: 32000 | H87: 32000 | I87: 32000
A88: =PR!D91 -> 0 | F88: =DATA!O1228 -> 0 | G88: 9900 | H88: 9900 | I88: 9900
A89: =PR!D92 -> 0 | F89: =DATA!O1229 -> 0 | G89: 400 | H89: 400 | I89: 400
... A92: =PR!D95 -> 0 | F92: =DATA!O1232 -> 0 | G92: 1440 | H92: 1440 | I92: 1440
A93: =PR!D96 -> 0 | F93: =DATA!O1233 -> 0
A94: =PR!D97 -> 0 | F94: =DATA!O1234 -> 0
A95: =PR!D98 -> 0 | F95: =DATA!O1235 -> 0
A96: =PR!D99 -> 0 | F96: =DATA!O1236 -> 0
A97: =PR!D100 -> 0 | F97: =DATA!O1237 -> 0
A98: =PR!D101 -> 0 | F98: =DATA!O1238 -> 0
A99: =PR!D102 -> 0 | F99: =DATA!O1239 -> 0
A100: =PR!D103 -> 0 | F100: =DATA!O1240 -> 0
A101: =PR!D104 -> 0 | F101: =DATA!O1241 -> 0
A102: =PR!D105 -> 0 | F102: =DATA!O1242 -> 0
A103: =PR!D106 -> 0 | F103: =DATA!O1243 -> 0
A104: =PR!D107 -> 0 | F104: =DATA!O1244 -> 0
... A132: =PR!D135 -> 0 | F132: =DATA!O1272 -> 0
A133: =PR!D136 -> 0 | F133: =DATA!#REF! -> #REF!
A134: =PR!D137 -> 0 | F134: =DATA!O1274 -> 0
A135: =PR!D138 -> 0 | F135: =DATA!O1275 -> 0
A136: =PR!D139 -> 0 | F136: =DATA!O1276 -> 0
A137: =PR!D140 -> 0 | F137: =DATA!O1277 -> 0
A138: =PR!D141 -> 0 | F138: =DATA!O1278 -> 0
A139: =PR!D142 -> 0 | F139: =DATA!O1279 -> 0
A140: =PR!D143 -> 0 | F140: =DATA!O1280 -> 0
A141: =PR!D144 -> 0 | F141: =DATA!O1281 -> 0
A142: =PR!D145 -> 0 | F142: =DATA!O1282 -> 0
A143: =PR!D146 -> 0 | F143: =DATA!O1283 -> 0
A144: =PR!D147 -> 0 | F144: =DATA!O1284 -> 0
A145: =PR!D148 -> 0 | F145: =DATA!O1285 -> 0
... A147: =PR!D150 -> 0 | F147: =DATA!O1287 -> 0
A148: =PR!D151 -> 0 | F148: =DATA!O1273 -> 0
A149: =PR!D152 -> 0 | F149: =DATA!O1289 -> 0
A150: =PR!D153 -> 0 | F150: =DATA!O1290 -> 0
A151: =PR!D154 -> 0 | F151: =DATA!O1291 -> 0
A152: =PR!D155 -> 0 | F152: =DATA!O1292 -> 0
A153: =PR!D156 -> 0 | F153: =DATA!O1293 -> 0
A154: =PR!D157 -> 0 | F154: =DATA!O1294 -> 0
A155: =PR!D158 -> 0 | F155: =DATA!O1295 -> 0
A156: =PR!D159 -> 0 | F156: =DATA!O1296 -> 0
A157: =PR!D160 -> 0 | F157: =DATA!O1297 -> 0
A158: =PR!D161 -> 0 | F158: =DATA!O1298 -> 0
A159: =PR!D162 -> 0 | F159: =DATA!O1299 -> 0
A160: =PR!D163 -> 0 | F160: =DATA!O1300 -> 0
... A182: =PR!D185 -> 0 | F182: =DATA!O1322 -> 0
A183: =PR!D186 -> 0
A184: =PR!D187 -> 0
...

Sheet Reso-Repeat Order
A6: BAC Resolution Recommending Alternative Mode of Procurement under Small Value Procurement
B8: BAC Resolution No. | D8: =AResoSVP!D6 -> 2505-GAS5-190
A10: WHEREAS, Section 48 Rule XVI of the Revised Implementing Rules and Regulations of RA 9184 allows Alternative Mode of Procurement subject to prior approval of the HOPE thru Annual Procurement Plan (APP) and only to promote economy and efficiency;
A11: WHEREAS, Section 53.9 allows Small Value Procurement provided that the procurement does not fall under shopping in Section 52 of this IRR and the amount involved does not exceed the thresholds prescribed in Annex "H" of this IRR;
A12: WHEREAS, Rule XVI, Section 51., on Repeat Order states this when provided for in the APP, is a method of procurement of goods from the previous winning bidder, whenever there is a need to replenish goods procured under a contract previously awarded through competitive bidding. | H12: c
A13: WHEREAS, Rule XVI, Section 51.,a) A repeat order provides that unit prices of the repeat order must be the same as or lower than those in the original contract: provided, that such prices are still the most advantegous to the GoP after price verification: b) thet the repeat order will not result in splitting of contracts, requisitions, or purchase orders, as provided for in Section 54.1 of this IRR;
A14: WHEREAS, Purchase Request No. | D14: =AResoSVP!D12 -> 2025-190 | E14: involves the procurement of
A15: =AResoSVP!A13 -> 4 Layered Steel Filling Cabinet with central lock--to ensure proper organization and secure storage of CBAO documents
A16: =AResoSVP!A14 -> with the approved budget of | D16: =AResoSVP!D14 -> 650000
A17: WHEREAS, the default mode of evaluation shall be on a lot basis which means that the determination of the single/lowest calculated and responsive bid (S/LCRB) is the total amount of offered unit price multiply by the required quantity;
A19: NOW THEREFORE, we, the members of the Bids and Awards Committee hereby RESOLVE as it is hereby RESOLVED to recommend to the College President to adopt Alternative Mode of Procurement under Small Value Procurement for the said transaction;
A21: RESOLVED FINALLY, at the Batanes State College, this
A22: Recommending Approval:
A25: RHOUPHELINE AYA A. CADIZ | C25: RANDALL G. CASTILLO | E25: EMILYN D. ALUETA
A26: BAC Member | C26: BAC Member | E26: BAC Member
A29: =PR!B73 -> JOHN MICHAEL A. VILLASPIR | C29: FORTUNATO PHILIP A. CABUGAO | E29: DOREEN C. CASTILLO
A30: End-User/Provisional Member | C30: BAC Vice Chairperson | E30: BAC Chairperson

Sheet AReso-Repeat Order
A1: BATANES STATE COLLEGE
A2: Basco, Batanes
A4: Approval of BAC Resolution Recommending Alternative Mode of Procurement under Small Value Procurement
B6: BAC Resolution No. | D6: =PR!B12 -> 2505-GAS5-190
A8: WHEREAS, Section 48 Rule XVI of the Revised Implementing Rules and Regulations of RA 9184 allows Alternative Mode of Procurement subject to prior approval of the HOPE thru Annual Procurement Plan (APP) and only to promote economy and efficiency;
A9: WHEREAS, Section 53.9 allows Small Value Procurement provided that the procurement does not fall under shopping in Section 52 of this IRR and the amount involved does not exceed the thresholds prescribed in Annex "H" of this IRR;
A10: WHEREAS, Appendix 18, Section 3.e on the Guidelines for Shopping and Small Value Procurement provides an Abstract of Quotations shall be prepared setting forth the names of those who responded to the RFQ's right after the deadline for submission except for shopping under Section 52.1(b), where at least three (3) price quotations (RFQ) must be obtained;
A11: WHEREAS, Annex "H" of the Consolidated Guidelines for the Alternative Methods of Procurement prescribed under Section V, Paragraph D.8.b.ii that the BAC shall prepare and send the RFQs/RFPs to at least three (3) suppliers, contractors or consultants of known qualifications where receipt of at least one (1) quotations is sufficient to proceed with the evaluation thererof;
A12: WHEREAS, Purchase Request No. | D12: =PR!E9 -> 2025-190 | E12: involves the procurement of
A13: Presidential Medallion | H13: Items:
A14: with the Approved Budget of | D14: =PR!H68 -> 650000
A15: WHEREAS, the default mode of evaluation shall be on a lot basis which means that the determination of the single/lowest calculated and responsive bid (S/LCRB) is the total amount of offered unit price multiply by the required quantity;
A16: NOW THEREFORE, I,DR.DJOVI R. DURANTE, Head of the Procuring Entity (HOPE) by virtue of the authority vested in me by the Board of Trustees of this Institution and after taking into consideration the merits and legal bases of the recommendation of the members of the Bids and Awards Committee (BAC) do hereby APPROVE the foregoing recommendation and adoption of Alternative Mode of Procurement under Small Value Procurement;
A18: APPROVED FINALLY, at the Batanes State College, this | F18: ___________________
B24: DJOVI REGALA DURANTE,DPA
B25: SUC President I
A30: BRYAN H. CIELO
A31: DELMA G. MALUPA-ABAD
A32: EDWIN F.MACABALLUG, Ph.D.
A33: LIEZL P. DELA CRUZ
A34: RODERICK Y. ABAD
A35: VILMA D. BACCAY
A36: ESTEBAN C. BADAJOS
A37: LEOBERT L. BANZALI
A38: MIAH DAPHNIE B. BUENAFE
A39: GLORIA N. CABIZON
A40: FORTUNATO PHILIP A. CABUGAO
A41: RICARDO Q. CABUGAO, JR.
... A86: EMILYN D. ALUETA

Sheet Sheet1

Sheet Sheet2

Sheet Sheet3

Sheet Sheet4

Sheet Sheet5

Sheet Sheet6
