Workbook

Sheet PMR-Data
A2: MONTH | B2: (Multiple Items)
A3: YEAR | B3: (Multiple Items)
A5: PR# | B5: Purpose | C5: End-User | D5: Modality | E5: Delivery Date | F5: IAR Date | G5: Fund Code | H5: Class | I5: Status | J5: Sum of Estimated Total | K5: Sum of Total
A6: 202-013A | B6: supplies for the repair & maintenance of the building | C6: JERSHON RALPH F. CASTANO | D6: SVP | E6: August 23, 2021 | F6: August 23, 2021 | G6: 101 | H6: MOOE | I6: complete | J6: 85520 | K6: 65665
A7: 2021-001A | B7: snacks for the "Internal Quality Audit" on January 19-21, 2021 | J7: 17850 | K7: 17850
A8: 2021-002 | B8: Supply and installation of CCTV for Academic Building, Dormitory and Agriculture Building | C8: ALETH A. MEORA | D8: SVP | E8: April 27, 2021 | F8: May 26, 2021` | G8: 101 | H8: CO | I8: complete | J8: 435000 | K8: 397860
A9: 2021-002A | B9: to be used in the different activities and internet communication needs of BSC | C9: RANDALL G. CASTILLO | D9: SVP | E9: 5/19 & 7/19/2021 | F9: 5/26 & 7/21/2021 | G9: 101 | H9: (blank) | I9: complete | J9: 25500 | K9: 25480
A10: 2021-003 | B10: Purchase of Academic Equipment | C10: ALETH A. MEORA | D10: SVP | E10: 5/19 & 7/19/2021 | F10: 5/19 & 7/21/2021 | G10: 101 | H10: CO | I10: complete | J10: 947218.62 | K10: 928620
A11: 2021-003A | B11: for PBB compliance specifically transparency seal and BSC publication | C11: RANDALL G. CASTILLO | D11: SVP | E11: February 16, 2021 | F11: March 2, 2021 | G11: 165 | H11: MOOE | I11: complete | J11: 49000 | K11: 45560
A12: 2021-004 | B12: for the purchase of Academic Equipments | C12: ALETH A. MEORA | D12: SVP | E12: January 12, 2021 | F12: April 27, 2021 | G12: 101 | H12: CO | I12: complete | J12: 972105.5 | K12: 791000
A13: 2021-004A | B13: for the purchase of enrollment forms | C13: RHEA ANGELLICA B. ADDATU | D13: SVP | E13: August 23, 2021 | F13: August 23, 2021 | G13: 101 | H13: (blank) | I13: (blank) | J13: 22500 | K13: 22500
A14: 2021-005 | B14: Purchase of Academic Equipment | C14: ALETH A. MEORA | D14: SVP | E14: 44396 | F14: 44403 | G14: 101 | H14: CO | I14: reimbursement | J14: 378961.7 | K14: 359780
A15: 2021-005A | B15: to be used in the different activities and internet communication needs of BSC | C15: RANDALL G. CASTILLO | D15: SVP | E15: May 19, 2021 | F15: May 26, 2021 | G15: 101 | H15: MOOE | I15: complete | J15: 30250 | K15: 29960
A16: 2021-006 | B16: Supply and Delivery of Academic Equipment | C16: ALETH A. MEORA | D16: SVP | E16: January 12, 2021 | F16: January 25, 2021 | G16: 101 | H16: CO | I16: complete | J16: 315813.75 | K16: 195700
E17: January 25, 2021 | F17: January 25, 2021 | G17: 101 | H17: CO | I17: complete | J17: 45000 | K17: 42000
A18: 2021-006A | B18: for the ISO Activity Management Review on Feb. 3, 2021 | C18: ROMINA KATRINA C. BAYARAS | D18: SVP | E18: 44230 | F18: February 16, 2021 | G18: 164 | H18: MOOE | I18: complete | J18: 14000 | K18: 11800
A19: 2021-007A | B19: Internet data/Regular load Allocation of Administrative & Finance staff of the college to support online submission of reports & other related activities for the Fiscal Year 2021 | C19: DJOVI R. DURANTE | D19: SVP | E19: March 29, 2021 | F19: March 31, 2021 | G19: 101 | H19: MOOE | I19: complete | J19: 107880 | K19: 107880
A20: 2021-008A | B20: for the "ISO Documentation" | C20: ROMINA KATRINA C. BAYARAS | D20: SVP | E20: March 15, 2021 | F20: March 15, 2021 | G20: 164 | H20: MOOE | I20: complete | J20: 3960 | K20: 3885
A21: 2021-009 | B21: Purchase of Academic Furniture Fixtures | C21: ALETH A. MEORA | D21: SVP | E21: August 23, 2021 | F21: August 23, 2021 | G21: 101 | H21: MOOE | I21: complete | J21: 200000 | K21: 199680
A22: 2021-009A | B22: stamp use for the filing of ISO documents | C22: ROMINA KATRINA C. BAYARAS | D22: SVP | E22: - | F22: - | G22: 165 | H22: (blank) | I22: FAILED | J22: 28000 | K22: 0
A23: 2021-0100 | B23: for the Implementation of "ADOPT through Varied R & D of Ivatan Endemic Resources" research project | C23: JANE S. CASTILLO | D23: SVP | E23: August 23, 2021 | F23: August 23, 2021 | G23: 165 | H23: MOOE | I23: for delivery | J23: 30950 | K23: 29315
A24: 2021-0101 | B24: office supplies for the Administrative & Finance Services Units | C24: DJOVI R. DURANTE | D24: SVP | E24: August 23, 2021 | F24: August 23, 2021 | G24: 165 | H24: MOOE | I24: for delivery | J24: 30840 | K24: 28941.9
A25: 2021-0102 | B25: supplies for Budget office | C25: BRYAN DAVE P. REVILLA | D25: SVP | E25: August 23, 2021 | F25: August 23, 2021 | G25: 101 | H25: MOOE | I25: for delivery | J25: 3500 | K25: 2990
A26: 2021-0103 | B26: supplies for Budget office | C26: BRYAN DAVE P. REVILLA | D26: SVP | E26: July 1, 2021 | F26: July 1, 2021 | G26: 101 | H26: MOOE | I26: complete | J26: 790 | K26: 600
A27: 2021-0104 | B27: supplies for the Budget office | C27: BRYAN DAVE P. REVILLA | D27: SVP | E27: August 23, 2021 | F27: August 23, 2021 | G27: 101 | H27: MOOE | I27: for delivery | J27: 1000 | K27: 800
A28: 2021-0105 | B28: repair of 2 units floor type airconditioner at Faculty Room | C28: JERSHON RALPH F. CASTANO | D28: SVP | E28: August 23, 2021 | F28: August 23, 2021 | G28: (blank) | H28: (blank) | I28: FAILED | J28: 13000
A29: 2021-0106 | B29: GSO Supplies | C29: JERSHON RALPH F. CASTANO | D29: SVP | E29: July 19 & 26, 2021 | F29: July 21 & 26, 2021 | G29: 101 | H29: MOOE | I29: complete | J29: 10950 | K29: 8314
A30: 2021-0107 | B30: GSO Supplies | C30: JERSHON RALPH F. CASTANO | D30: SVP | E30: 44399 | F30: 44411 | G30: 101 | H30: MOOE | I30: reimbursement | J30: 18500 | K30: 15780
A31: 2021-0108 | B31: Snack for the Preparatory Board Meeting on June 25, 2021 at 10:00 a.m | C31: GERZON R. ABAD | D31: SVP | E31: August 23, 2021 | F31: August 23, 2021 | G31: (blank) | H31: (blank) | I31: FAILED | J31: 3000 | K31: 0
A32: 2021-0109 | B32: PM snack and dinner for the 52nd Board of Trustees Meeting on June 25, 2021 | C32: GERZON R. ABAD | D32: SVP | E32: June 25, 2021 | F32: 44377 | G32: 101 | H32: MOOE | I32: reimbursement | J32: 13000 | K32: 9000
A33: 2021-010A | B33: ink use for enrollment | C33: RHEA ANGELLICA B. ADDATU | D33: SVP | E33: August 23, 2021 | F33: August 23, 2021 | G33: 101 | H33: (blank) | I33: FAILED | J33: 1500
A34: 2021-0110 | B34: Lunch, PM Snack and Dinner of Commissioner Lilian A. De Las Llagas and Staff for the 52nd BOT Meeting on 25 June 2021 | C34: GERZON R. ABAD | D34: SVP | E34: August 23, 2021 | F34: August 23, 2021 | G34: (blank) | H34: (blank) | I34: reimbursement | J34: 12597.5 | K34: 12597.5
A35: 2021-0111 | B35: repair & maintenance of A/C units of Registrar's, Cashier's, Accountant's & President's office | C35: JERSHON RALPH F. CASATANO | D35: SVP | E35: August 23, 2021 | F35: August 23, 2021 | G35: 101 | H35: MOOE | I35: on-going | J35: 8000 | K35: 8000
A36: 2021-0112 | B36: supplies for the rewiring of faculty room electrical system | C36: JERSHON RALPH F. CASATANO | D36: SVP | E36: July 21, 2021 | F36: July 26, 2021 | G36: 101 | H36: MOOE | I36: complete | J36: 23700 | K36: 21624
A37: 2021-0113 | B37: for the purchase of Semi-expendable equipments purposes | C37: JERSHON RALPH F. CASATANO | D37: SVP | E37: August 23, 2021 | F37: August 23, 2021 | G37: 101 | H37: MOOE | I37: on-going | J37: 10000 | K37: 10000
A38: 2021-011A | B38: for the Pre Assessment Audit Plan on Feb. 10-11, 2021 | C38: ROMINA KATRINA C. BAYARAS | D38: SVP | E38: February 10-11, 2021 | F38: March 2, 2021 | G38: 164 | H38: MOOE | I38: complete | J38: 7500 | K38: 7125
A39: 2021-012A | B39: supplies for the repair & maintenance of transportation vehicle | C39: JERSHON RALPH F. CASTANO | D39: SVP | E39: March 31, 2021 | F39: April 5, 2021 | G39: 101 | H39: MOOE | I39: on-going | J39: 49399.99 | K39: 42550
A40: 2021-013 | B40: Puchase of drafting tables and chairs for the Academiic Furnitures and Fixtures | C40: ALETH A. MEORA | D40: SVP | E40: January 26, 2021 | F40: January 26, 2021 | G40: 101 | H40: CO | I40: complete | J40: 277500 | K40: 195000
A41: 2021-014A | B41: office machinery & equipment | C41: JERSHON RALPH F. CASTANO | D41: SVP | E41: March 29, 2021 | F41: March 30, 2021 | G41: 101 | H41: MOOE | I41: complete | J41: 47002 | K41: 42500
A42: 2021-015A | B42: supplies for janitorial services | C42: JERSHON RALPH F. CASTANO | D42: SVP | E42: April 15, 2021 | F42: April 15, 2021 | G42: 101 | H42: MOOE | I42: complete | J42: 5000 | K42: 3000
E43: March 30, 2021 | F43: April 15, 2021 | G43: 101 | H43: MOOE | I43: complete | J43: 15000 | K43: 15200
A44: 2021-016A | B44: AM snacks for the meeting on the Assessment of the Conduct of Flexible Learning in the 1st Semester of SY 2020-2021 | C44: ANGELITA H. VARGAS | D44: SVP | E44: February 16, 2021 | F44: March 24, 2021 | G44: 101 | H44: MOOE | I44: complete | J44: 7950 | K44: 7950
A45: 2021-017A | B45: snacks & meals for the Administrative & Finance Conference on the finalization of FY 2021 targets and deliverables | C45: DJOVI R. DURANTE | D45: SVP | E45: February 23, 2021 | F45: March 1, 2021 | G45: 101 | H45: MOOE | I45: complete | J45: 19250 | K45: 16275
A46: 2021-018A | B46: snacks & dinner for the 51st Board meeting on Feb. 24, 2021 | C46: GERZON R. ABAD | D46: SVP | E46: February 24, 2021 | F46: March 9, 2021 | G46: 101 | H46: MOOE | I46: complete | J46: 10200 | K46: 8330
A47: 2021-019A | B47: use for National Women's Month Celebration | C47: JENNY S. ALINA | D47: SVP | E47: March 29, 2021 | F47: March 29, 2021 | G47: 101 | H47: MOOE | I47: complete | J47: 5320 | K47: 5320
A48: 2021-020 | B48: seed propagation for the Production of High Value Crop (HVC) Seess & Seedling in Batanes under the Bayanihan II project | C48: ROMEL A. RATERTA | D48: (blank) | E48: August 23, 2021 | F48: August 23, 2021 | G48: (blank) | H48: (blank) | I48: FAILED | J48: 259100 | K48: 0
A49: 2021-021 | B49: supplies for the National Women's Month Celebration | C49: JENNY S. ALINA | D49: SVP | E49: March 29, 2021 | F49: March 30, 2021 | G49: 101 | H49: MOOE | I49: complete | J49: 1170 | K49: 735
A50: 2021-022 | B50: supplies & materials for the installation of 3 units television | C50: JERSHON RALPH F. CASTANO | D50: (blank) | E50: August 23, 2021 | F50: August 23, 2021 | G50: (blank) | H50: (blank) | I50: FAILED | J50: 4500 | K50: 0
A51: 2021-023 | B51: supplies & materials for the connection of 3 units television | C51: JERSHON RALPH F. CASTANO | D51: (blank) | E51: August 23, 2021 | F51: August 23, 2021 | G51: (blank) | H51: (blank) | I51: FAILED | J51: 5200 | K51: 0
A52: 2021-024 | B52: stamp use for the filing of ISO documents | C52: ROMINA KATRINA C. BAYARAS | D52: SVP | E52: May 7, 2021 | F52: May 19, 2021 | G52: 164 | H52: MOOE | I52: complete | J52: 40000 | K52: 40000
A53: 2021-025 | B53: stamp to be used in the office of the President & Office of the Board Sec | C53: GERZON R. ABAD | D53: SVP | E53: June 2, 2021 | F53: June 10, 2021 | G53: 101 | H53: (blank) | I53: complete | J53: 8000 | K53: 8000
A54: 2021-026 | B54: snacks & lunch for the "Records Management System Echo Seminar on March 23, 2021 | C54: ROMINA KATRINA C. BAYARAS | D54: SVP | E54: April 8, 2021 | F54: April 12, 2021 | G54: 101 | H54: MOOE | I54: complete | J54: 17500 | K54: 14750
A55: 2021-027 | B55: meals & snacks for the FY 2022 Budget Review & Consultation on March 16, 2021 | C55: BRYAN DAVE P. REVILLA | D55: SVP | E55: March 16, 2021 | F55: March 26, 2021 | G55: 101 | H55: MOOE | I55: complete | J55: 7700 | K55: 6930
A56: 2021-028 | B56: for preventive maintenance of BSC ICT Equipment | C56: RANDALL G. CASTILLO | D56: (blank) | E56: August 23, 2021 | F56: August 23, 2021 | G56: (blank) | H56: (blank) | I56: FAILED | J56: 42000 | K56: 0
A57: 2021-029 | B57: for preventive maintenance of BSC ICT Equipment | C57: RANDALL G. CASTILLO | D57: (blank) | E57: August 23, 2021 | F57: August 23, 2021 | G57: (blank) | H57: (blank) | I57: pending | J57: 48250 | K57: 0
A58: 2021-030 | B58: Snacks during the National Women's Month Celebration | C58: JENNY S. ALINA | D58: SVP | E58: March 25, 2021 | F58: May 4, 2021 | G58: 101 | H58: MOOE | I58: complete | J58: 11100 | K58: 10730
A59: 2021-031 | B59: for National Womens Month Celebration activity | C59: JENNY S. ALINA | D59: (blank) | E59: August 23, 2021 | F59: August 23, 2021 | G59: (blank) | H59: (blank) | I59: (blank) | J59: 12750 | K59: 12750
A60: 2021-032 | B60: Snacks and lunch during the Administrative Council meeting on March 31, 2021 | C60: GERZON R. ABAD | D60: SVP | E60: March 31, 2021 | F60: March 31, 2021 | G60: 101 | H60: MOOE | I60: complete | J60: 18200 | K60: 17500
A61: 2021-033 | B61: Snacks and Lunch during the Academic Council meeting on March 30, 2021 | C61: GERZON R. ABAD | D61: SVP | E61: March 30, 2021 | F61: March 30, 2021 | G61: 101 | H61: MOOE | I61: complete | J61: 24700 | K61: 23750
A62: 2021-034 | B62: seed propagation for the Production of High Value Crop (HVC) Seess & Seedling in Batanes under the Bayanihan II project | C62: ROMEL A. RATERTA | D62: SVP | E62: May 31, 2021 | F62: June 10, 2021 | G62: 165 | H62: MOOE | I62: complete | J62: 60000 | K62: 61200
E63: August 23, 2021 | F63: June 10, 2021 | G63: 165 | H63: MOOE | I63: complete | J63: 529100 | K63: 467600
A64: 2021-035 | B64: for the purchase of Semi-Expendable Office Supply purposes | C64: ALETH A. MEORA | D64: (blank) | E64: August 23, 2021 | F64: August 23, 2021 | G64: (blank) | H64: (blank) | I64: FAILED | J64: 55200 | K64: 0
A65: 2021-036 | B65: For the purchase of office equipment | C65: ALETH A. MEORA | D65: (blank) | E65: May 31, 2021 | F65: June 1, 2021 | G65: 101 | H65: (blank) | I65: complete | J65: 85000 | K65: 56025
G66: (blank) | H66: (blank) | I66: complete | J66: 70000 | K66: 43425
A67: 2021-037 | B67: For the purchase of office equipment | C67: ALETH A. MEORA | D67: SVP | E67: June 30, 2021 | F67: July 1, 2021 | G67: 101 | H67: CO | I67: complete | J67: 319140 | K67: 279976.5
A68: 2021-038 | B68: For the purchase of semi-expendable equipment | C68: ALETH A. MEORA | D68: SVP | E68: June 10, 2021 | F68: June 11, 2021 | G68: 101 | H68: MOOE | I68: complete | J68: 637300 | K68: 633015
A69: 2021-039 | B69: for the purchase of Academic furnitures & fixtures purposes | C69: ALETH A. MEORA | D69: Public Bidding | E69: August 23, 2021 | F69: August 23, 2021 | G69: (blank) | H69: (blank) | I69: (blank) | J69: 980000 | K69: 0
A70: 2021-040 | B70: Snacks during the Expanded Finance Committee Meeting on April 13, 2021 | C70: GERZON R. ABAD | D70: SVP | E70: April 13, 2021 | F70: April 22, 2021 | G70: 101 | H70: MOOE | I70: complete | J70: 2550 | K70: 1445
A71: 2021-041 | B71: for back-up and saving documents purposes | C71: ANGELITA H. VARGAS | D71: SVP | E71: 44384 | F71: 44384 | G71: 101 | H71: MOOE | I71: completed | J71: 168000 | K71: 139720
A72: 2021-042 | B72: communication expenses in the implementation of the Learning Continuity Plan | C72: ANGELITA H. VARGAS | D72: SVP | E72: June 9, 2021 | F72: June 29, 2021 | G72: 101 | H72: MOOE | I72: complete | J72: 171680 | K72: 171400
A73: 2021-043 | B73: Supplies and materials for Sports Development | C73: WILLIAM POL M. MAGGAY | D73: SVP | E73: August 23, 2021 | F73: August 23, 2021 | G73: 165 | H73: MOOE | I73: FAILED | J73: 3300 | K73: 0
A74: 2021-044 | B74: supplies/materials use for product development | C74: JANE S. CASTILLO | D74: SVP | E74: May 31 & July 1, 2021 | F74: June 10 & July 1, 2021 | G74: 165 | H74: MOOE | I74: complete | J74: 22625 | K74: 22170
A75: 2021-045 | B75: supplies/materials use for product development | C75: JANE S. CASTILLO | D75: SVP | E75: August 23, 2021 | F75: August 23, 2021 | G75: 165 | H75: MOOE | I75: for delivery | J75: 2000 | K75: 2000
A76: 2021-046 | B76: supplies/materials use for product development | C76: JANE S. CASTILLO | D76: SVP | E76: May 20, 2021 | F76: May 26, 2021 | G76: 165 | H76: MOOE | I76: complete | J76: 4500 | K76: 4500
A77: 2021-047 | B77: supplies/materials use for product development | C77: JANE S. CASTILLO | D77: SVP | E77: May 4, 2021 | F77: May 4, 2021 | G77: 165 | H77: MOOE | I77: complete | J77: 3000 | K77: 2650
A78: 2021-048 | B78: For President's Office use | C78: GERZON R. ABAD | D78: SVP | E78: May 20, 2021 | F78: May 26, 2021 | G78: 101 | H78: MOOE | I78: complete | J78: 3500 | K78: 2900
A79: 2021-049 | B79: Supplies for operational use of the Procurement Office | C79: ANNE MARIELLE V. TEVES | D79: SVP | E79: June 2 & July 7, 2021 | F79: June 10 & July 7, 2021 | G79: 101 | H79: MOOE | I79: partial delivery | J79: 14500 | K79: 14800
E80: August 23, 2021 | F80: August 23, 2021 | G80: 101 | H80: MOOE | I80: for delivery | J80: 22580 | K80: 21860
A81: 2021-050 | B81: replacement of defective HDD of ACER ASPIRE 3 | C81: JERSHON RALPH F. CASTANO | D81: SVP | E81: May 25, 2021 | F81: May 26, 2021 | G81: 101 | H81: MOOE | I81: complete | J81: 4500 | K81: 3800
A82: 2021-051 | B82: for office supplies | C82: WILLIAM JO SE M. BILLOTE | D82: SVP | E82: July 1, 2021 | F82: June 1 & July 1, 2021 | G82: 165 | H82: MOOE | I82: complete | J82: 39000 | K82: 36750
A83: 2021-052 | B83: for office supply | C83: WILLIAM JO SE M. BILLOTE | D83: (blank) | E83: August 23, 2021 | F83: August 23, 2021 | G83: (blank) | H83: (blank) | I83: FAILED | J83: 6000 | K83: 0
A84: 2021-053 | B84: use for office supplies | C84: WILLIAM JO SE M. BILLOTE | D84: SVP | E84: May 26, 2021 | F84: May 26, 2021 | G84: 165 | H84: MOOE | I84: complete | J84: 1450 | K84: 1400
A85: 2021-054 | B85: supplies & equuipment for the installation of split type | C85: JERSHON RALPH F. CASTANO | D85: SVP | E85: August 23, 2021 | F85: August 23, 2021 | G85: 101 | H85: MOOE | I85: on going | J85: 30000 | K85: 28020
A86: 2021-055 | B86: food for the BSC employees during the Tree Planting Activity at "Rakuh A Payaman" in Mahatao, Batanes 7:00am | C86: ANGELITA H. VARGAS | D86: SVP | E86: April 30, 2021 | F86: April 30, 2021 | G86: 101 | H86: MOOE | I86: complete | J86: 25000 | K86: 24900
A87: 2021-056 | B87: communication expenses | C87: XINA V. VINALAY | D87: (blank) | E87: August 23, 2021 | F87: August 23, 2021 | G87: (blank) | H87: (blank) | I87: (blank) | J87: 9880 | K87: 0
A88: 2021-057 | B88: for office supply | C88: ANDREI JOHN S. CORDOVA | D88: SVP | E88: June 2 & July 19, 2021 | F88: June 10 & July 26, 2021 | G88: 165 | H88: MOOE | I88: complete | J88: 13200 | K88: 12390
A89: 2021-058 | B89: snacks & lunch for the 2nd Quarter Performance Review & Regular meeting (May 18, 2021) | C89: DJOVI R. DURANTE | D89: SVP | E89: May 18, 2021 | F89: June 1, 2021 | G89: 101 | H89: MOOE | I89: complete | J89: 15700 | K89: 15400
A90: 2021-059 | B90: to keep update on the development of training/program for sports development | C90: WILLIAM POL M. MAGGAY | D90: SVP | E90: May 25, 2021 | F90: May 26, 2021 | G90: 165 | H90: MOOE | I90: complete | J90: 3300 | K90: 2800
A91: 2021-060 | B91: Use for mailing report of grades to parents, request credentials, Form 137 | C91: MAGDALENA V. BALLES | D91: SVP | E91: July 1, 2021 | F91: July 1, 2021 | G91: 165 | H91: MOOE | I91: for delivery | J91: 3000 | K91: 2950
A92: 2021-061 | B92: lunch & snacks for the Lab-Trip Training on May 6 and 7, 2021 at BSC | C92: FERDINAND BULUSAN | D92: SVP | E92: May 6 & 7, 2021 | F92: 44323 | G92: 165 | H92: MOOE | I92: complete | J92: 10500 | K92: 10425
A93: 2021-062 | B93: for office consumption (office supplies) | C93: WILLIAM JO SE M. BILLOTE | D93: SVP | E93: May 25 & July 5, 2021 | F93: May 26 & July 7, 2021 | G93: 101 | H93: MOOE | I93: complete | J93: 10000 | K93: 6270
A94: 2021-063 | B94: Installation of 2 units grrenhouse (4 x 12 sq. m) | C94: ROMEL A. RATERTA | D94: SVP | E94: August 23, 2021 | F94: August 23, 2021 | G94: (blank) | H94: (blank) | I94: on going | J94: 985000 | K94: 886500
A95: 2021-064 | B95: repair & maintenance of the cables of old 16 channel CCTV located at Supply Office | C95: JERSHON RALPH F. CASTANO | D95: SVP | E95: July 2, 2021 | F95: July 2, 2021 | G95: 101 | H95: MOOE | I95: complete | J95: 29000 | K95: 14860
A96: 2021-065 | B96: materials for the National Higher Education Week Competition (May 17-21, 2021) | C96: ELEIN T. ESPERANZA | D96: SVP | E96: May 17, 2021 | F96: June 1, 2021 | G96: 165 | H96: MOOE | I96: complete | J96: 900 | K96: 318
A97: 2021-066 | B97: materials for the National Higher Education Week Competition (May 17-21, 2021) | C97: ELEIN T. ESPERANZA | D97: SVP | E97: May 14, 2021 | F97: June 7, 2021 | G97: 165 | H97: MOOE | I97: complete | J97: 3420 | K97: 2537
A98: 2021-067 | B98: materials for the National Higher Education Week Competition (May 17-21, 2021) | C98: ELEIN T. ESPERANZA | D98: SVP | E98: August 23, 2021 | F98: August 23, 2021 | G98: (blank) | H98: (blank) | I98: FAILED | J98: 1500 | K98: 0
A99: 2021-068 | B99: materials for the National Higher Education Week Competition (May 17-21, 2021) | C99: ELEIN T. ESPERANZA | D99: SVP | E99: August 23, 2021 | F99: August 23, 2021 | G99: (blank) | H99: (blank) | I99: FAILED | J99: 1050 | K99: 0
A100: 2021-069 | B100: provision of WiFi Modems for internet connectivity (Admin. & Finance units) | C100: DJOVI R. DURANTE | D100: SVP | E100: August 23, 2021 | F100: August 23, 2021 | G100: 101 | H100: MOOE | I100: for delivery | J100: 30000 | K100: 27950
A101: 2021-070 | B101: Health Insurance of students | C101: WILLIAM JO SE M. BILLOTE | D101: SVP | E101: July 1, 2021 | F101: July 2, 2021 | G101: 165 | H101: (blank) | I101: complete | J101: 7500 | K101: 7500
A102: 2021-071 | B102: for the Implementation of "ADOPT through varied R & D of Ivatan Endemic Resources" research project | C102: FERDINAND BULUSAN | D102: SVP | E102: August 23, 2021 | F102: August 23, 2021 | G102: (blank) | H102: (blank) | I102: FAILED | J102: 45400 | K102: 0
...

Sheet Suppliers TIN
B1: Business Name | C1: Name/Owner | D1: TIN # | E1: Scope of Business
A2: 1 | B2: Apostol General Merchandise | C2: Leo A. Apostol | D2: 183-008-448 | E2: Food,beverages,computers,gas fuel products,agri.farm
A3: 2 | B3: Bartilad's Feeds Trading | C3: Roldan Q. Bartilad | D3: 771-272-422 | E3: agricultural farm supplies, & equipment
A4: 3 | B4: Bitstop Network Services Inc. | C4: JC James P. Jihay | D4: 005-931-291
A5: 4 | B5: Casa Del Basco | D5: 107-549-729
A6: 5 | B6: Crisel General Merchandise | C6: Cresencio M. Verana | D6: 135-792-662
A7: 6 | B7: Claire's Drugstore | C7: Claire H. Abad | D7: 264-438-671
A8: 7 | B8: Davocol's General Merchandise | C8: Lilibeth T. Davocol | D8: 116-311-342
A9: 8 | B9: Davocol's Inn | C9: Dan Ardie T. Davocol | D9: 739-884-154
A10: 9 | B10: D' Islands Gasoline Station | C10: Lito Doroteo A. Adarme | D10: 124-072-664
A11: 10 | B11: Doque's Congie Hauz | C11: Glenda L. Gordo | D11: 922-904-311
A12: 11 | B12: D. Michael Co Industrial Supply (DMC) Corp. | C12: Eunelyn O. Ramilla | D12: 007-776-953
A13: 12 | B13: E. A. Amboy General Merchandise | C13: Cesar Edgardo Amboy | D13: 928-655-269 | E13: repair of personal & household goods,tailoring,dressmaking printing,beverages
A14: 13 | B14: Enrinar Trading | C14: Narcisa Co Melad | D14: 123-394-221
A15: 14 | B15: FMG Trading & Construction Supply | C15: Frederick Gari | D15: 219-884-940
A16: 15 | B16: GDP Trading | C16: George D. Peralta | D16: 150-214-534 | E16: beverages,pharmaceutical,medical,computers,agri.farm
A17: 16 | B17: Hubalde's Drugstore | C17: Marilyn G. Hubalde | D17: 914-979-941
A18: 17 | B18: Hudzan Café & Catering Services | C18: Susan Villegas | D18: 290-315-057 | E18: **
A19: 18 | B19: I.B.S Pharmacy & General Merchadise | C19: Dale Anthony C. Gutierrez | D19: 411-599-160 | E19: pharmaceutical,medical,and other sale in specialized stores
A20: 19 | B20: IAM'J Graphic Design & Printing | C20: Jaycy S. Alina | D20: 318-666-833
A21: 20 | B21: JPM General Merchandise & Hardware | C21: Emma P. Adarme | D21: 160-183-814
A22: 21 | B22: J-Tech Trading & Services | C22: Cecilia C. De Sagon | D22: 933-429-635 | E22: office supplies,computers,office machines,other service activities
A23: 22 | B23: M.G. Hubalde's General Merchandise | C23: Marilyn G. Hubalde | D23: 914-979-941-001 | E23: clothing,appliances,hardware,computers,fuel products,agri.farm
A24: 23 | B24: MDAC Trading & Compuserve | C24: Florescita A. Cruz | D24: 100-194-776 | E24: printing,office & school supplies,medical supplies & equipments
A25: 24 | B25: NRA Hardware | C25: Neil Bernardo Ordas | D25: 196-062-499
A26: 25 | B26: One-Touch Technology Trading | C26: Janice A. Alasco | D26: 283-009-327 | E26: office machines,equipments,pharmaceutical & medical,construction supplies,sports & athletic
A27: 26 | B27: Pension Ivatan | C27: Teresita D. Valiente | D27: 106-115-883
A28: 27 | B28: Sophia Marie Store | C28: Regina B. Gabaldon | D28: 279-057-542
A29: 28 | B29: Twixbiz General Merchandise | C29: Charles B. Domingo | D29: 118-687-531
A30: 29 | B30: Northern Star General Merchandise | C30: Cesar A. Calma | D30: 151-407-774 | E30: retail of Agri farm supplies & equipment,other retail sale in specialized stores
A31: 30 | B31: SKR Furiture & Fixture Trading | C31: Delma M. Abad | D31: 443-694-557 | E31: sale of computer,various merchandise,hardware,construction supplies,household appliances,office supplies,machines & equipment
A32: 31 | B32: Philippine Red Cross | C32: Waldimar C. Ballada | D32: 000-804-271-096
A33: 32 | B33: Marconine's Food Catering Services | C33: Winefredo C. Maduro | D33: 917-830-052
A34: 33 | B34: Korner Hauz Café | C34: Zharmaine C. Guttierez | D34: 431-974-729
A35: 34 | B35: J. F. Gabotero, Inc. | C35: Quirino Crisanto F. Gabotero | D35: 770-322-881
A36: 35 | B36: KCM hardware & Construction Supplies | C36: Kathleen Enica Co Melad | D36: 466-514-463
A37: 36 | B37: MKM Hardware | C37: Enrique Abuyo Melad Jr. | D37: 148-780-907
A38: 37 | B38: NSGB Books Trading | C38: Nica Sandra Go Banag
A39: 38 | B39: ONPREM2CLOUD IT SOLUTIONS CO. | C39: Emmanuel B. Mamayson | D39: 101-626-582
A40: 39 | B40: Petonio's Kitchen Food Services | C40: Ramona C. Tabuso | D40: 013-000-080-045-720-21
A41: 40 | B41: Tiger Consulting and Software Devt Inc. | D41: 007-073-548
A42: 41 | B42: MOJR Construction Trading & General Services, Ltd, Co. | C42: Manuel S. Obedoza Jr.
A43: 42 | B43: Batanes Electric Cooperative Inc. | C43: Victoria A. Mata | D43: 005-641-216-000
A44: 43 | B44: Maddies Fashion Design Services | C44: Madeline Palencia Palustre
A45: 44 | B45: CMVILL Trading | C45: Zariffe G. Villanueva | D45: 421-603-862-000 | E45: pharmaceutical,medical,officesupplies, machines,computers
A46: 45 | B46: VL Mini Canteen | C46: Estela N. Lizardo | D46: 930-779-799
A47: 46 | B47: IDB Merida Photo Studio & Artworks | C47: Ignacio Danilo B. Merida | D47: 925-632-231
A48: 47 | B48: SKE Souvenir Trading | C48: Sophia Kate L. Esdicul | D48: 613-655-085-00001 | E48: souvenir store,sale of new goods in specialized stores
A49: 48 | B49: I.B.S. Travel and Tours | C49: Zharmaine C. Gutierrez | D49: 258-905-353
A50: 49 | B50: FVA Trading | C50: Nathan A. Amboy | D50: 436-695-403 | E50: sale of construction,office supplies,drugs,pharmaceutical,office machines & equipments
A51: 50 | B51: JC Delatado's Telecommunication Equipment Trading | C51: Jesse A. Delatado | D51: 713-001-589-00001
A52: 51 | B52: AZ Blue Box Café | C52: Zafra Hazel B. Baldovino | D52: 434-947-764-00001
A53: 52 | B53: Kian's Food Product | C53: William Pol M. Maggay | D53: 915-768-533-00000
A54: 53 | B54: ORCA General Merchandise | C54: Engr. La Verne Sarmiento | D54: 614-297-100-00000
A55: 54 | B55: Boulder Bay Residence | C55: Mario Rey Roa Pacana | D55: 943-433-381-002
A56: 55 | B56: Simsiman Arts & Crafts Manufacturing | C56: Catherine De Mata | D56: 187-250-096
A57: 56 | B57: Chanpan Photo & Video Services | C57: Katrina Caren Fitero | D57: 758-403-303-0000 | E57: photographic activities
A58: 57 | B58: Amboy Hometel | C58: Ceasar Edgardo Amboy | D58: 928-655-269-002
A59: 58 | B59: Golden Press | C59: Ma. Belen B. Lim | D59: 102-204-257
A60: 59 | B60: Brownstone Asia-Tech,Inc. | C60: Maricris T. Mercado-Batalla | D60: 004-845-348-000
A61: 60 | B61: Sierralinks Corporation | C61: George b. Lorenzana | D61: 623-582-256-00000
A62: 61 | B62: Elaralouis Builders Supply and Services | C62: Raul Leo G. Elacion | D62: 204-840-997-000
A63: 62 | B63: YCA Office Supplies and Equipment Trading | C63: Clark Michael A. Cruz | D63: 206-113-292-00001
A64: 63 | B64: RGIE's Canteen | C64: Raquel G. Manzo | D64: 323-863-259-000
A65: 64 | B65: Bunkers Bistro | C65: Jennifer Gabilo | D65: 297-134-097-00000
A66: 65 | B66: YCA Printing Services | C66: Clark Michael A. Cruz | D66: 206-113-292-00000
A67: 66 | B67: Wiseman's Book Trading, Inc. | C67: ? | D67: 258-328-341-000
A68: 67 | B68: Artech Printing Services | C68: John Patrick D. Pasion | D68: 477-299-309-00000
A69: 68 | B69: Big Mark Advertising | C69: Evelyn Pagunuran | D69: 938-113-364-000 | E69: Door 1 Sapphire Square Bldg. Bagay Road, Tuguegarao City -- 09176263086 | F69: sales.bigmarkadvertising@gmail.com
A70: 69 | B70: Lasercraft Arts & Crafts Manufacturing | C70: Garth Gavilan
A71: 70 | B71: Bethel General Insurance & Surety Corporation | C71: Nicasio B. Subteniente Jr. | D71: 000-745-041-000
A72: 71 | B72: A.C.S. W3-Solutionz Management Consultancy | C72: Suyan Edna Magpantay | D72: 606-458-849-00001
C73: John Vincent B. Ramos | D73: Account Manager | E73: Calarin Road. Malued 2400 Dagupan City, Panagasinan
A74: 72 | B74: Bethel General Insurance & Surety Corporation | C74: Nicasio B. Subteniente Jr. | D74: 000-745-041-000 | E74: Unit 200 Valero Plaza 124 Valero St. Salcedo Village, Makati City
A75: 73

Sheet FundCodes
A1: CODE | B1: CATEGORY | C1: OFFICE/UNIT | D1: Fund
A2: GAS1 | B2: General Administration Services | C2: Office of the President | D2: 01-101
A3: GAS2 | B3: General Administration Services | C3: Office of the Board Secretary | D3: 05-164
A4: GAS3 | B4: General Administration Services | C4: Office of the College Secretary | D4: 06-162
A5: GAS4 | B5: General Administration Services | C5: Information & Communications Technology Unit | D5: 07-165
A6: GAS5 | B6: General Administration Services | C6: Information Unit
A7: GAS6 | B7: General Administration Services | C7: Internal Audit Unit
A8: GAS7 | B8: General Administration Services | C8: Legal Unit
A9: GAS8 | B9: General Administration Services | C9: Planning Unit
A10: GAS9 | B10: General Administration Services | C10: Project Management Unit
A11: GAS10 | B11: General Administration Services | C11: Quality Assurance Office
A12: GAS11 | B12: General Administration Services | C12: Administrative Office
A13: GAS12 | B13: General Administration Services | C13: Cash Unit
A14: GAS13 | B14: General Administration Services | C14: General Services Unit
A15: GAS14 | B15: General Administration Services | C15: Human Resource Management Unit
A16: GAS15 | B16: General Administration Services | C16: Procurement Unit
A17: GAS16 | B17: General Administration Services | C17: Records Unit
... A45: Acad9 | B45: Director for Instruction | C45: DI
A46: 1005 | B46: Research & Extension Office | C46: RDET
A47: 1006 | B47: College Business Affairs Office | C47: CBAO
A48: 1006A | B48: College Assessment Center | C48: College Assessment Center
A49: 1006B | B49: College Business Affairs Office | C49: CBAO-IGP
A50: 1006C | B50: College Business Affairs Office | C50: CBAO-Dorm
A51: 1006D | B51: College Business Affairs Office | C51: CBAO-Hostel

Sheet DATA
A1: YEAR | B1: MONTH | C1: End-User | D1: Position/Designation | E1: Fund Code | F1: Class | G1: PR# | H1: Modality | I1: Item | J1: Qty | K1: Unit of Issue | L1: Unit Budget | M1: Estimated Total | N1: Unit LCRB | O1: Total | P1: Purpose | Q1: Office | R1: Date of LON | S1: Date of BAC Award | T1: PO/Contract Date | U1: PO/Contract Date Received | V1: Delivery Date | W1: Supplier | X1: IAR Date | Y1: Section Code/Dept. | Z1: Released Date | AA1: Status | AB1: Remarks | AC1: ObR # | AD1: # of RFQ's printed | AE1: Sales/Charge Invoice/Billing
A2: 2025 | B2: July | C2: WARLITO M. TOMAS JR. | D2: Project Leader | E2: 165 | G2: 2025-234 | I2: Feeds (lactation) | J2: 20 | K2: sacks | L2: 1950 | M2: =SUM(J2*L2) -> 39000 | N2: 1970 | O2: =SUM(J2*N2) -> 39400 | P2: feeds for native pigs (Feeds Formulation) | Q2: Agri-DOST-PCAARRD | R2: July 23, 2025 | S2: July 30, 2025 | T2: July 31, 2025 | U2: August 12, 2025 | V2: August 18, 2025 | W2: Bartilad Feeds Trading | X2: August 18, 2025 | Y2: 1005 | Z2: September 3, 2025 | AA2: complete | AB2: for payment-Acctg. | AC2: 07-02-2025-07-0255 | AD2: 3 RFQ's + 1Blank | AE2: 043/8/18/2025
A3: 2025 | B3: July | C3: WARLITO M. TOMAS JR. | D3: Project Leader | E3: 165 | G3: 2025-234 | I3: Gestation | J3: 20 | K3: sacks | L3: 1900 | M3: =SUM(J3*L3) -> 38000 | N3: 1900 | O3: =SUM(J3*N3) -> 38000 | P3: feeds for native pigs (Feeds Formulation) | Q3: Agri-DOST-PCAARRD | R3: July 23, 2025 | S3: July 30, 2025 | T3: July 31, 2025 | U3: August 12, 2025 | V3: August 18, 2025 | W3: Bartilad Feeds Trading | X3: August 18, 2025 | Y3: 1005 | Z3: September 3, 2025 | AA3: complete | AB3: for payment-Acctg. | AC3: 07-02-2025-07-0255
A4: 2025 | B4: July | C4: WARLITO M. TOMAS JR. | D4: Project Leader | E4: 165 | G4: 2025-234 | I4: Grower | J4: 10 | K4: sacks | L4: 2000 | M4: =SUM(J4*L4) -> 20000 | N4: 2000 | O4: =SUM(J4*N4) -> 20000 | P4: feeds for native pigs (Feeds Formulation) | Q4: Agri-DOST-PCAARRD | R4: July 23, 2025 | S4: July 30, 2025 | T4: July 31, 2025 | U4: August 12, 2025 | V4: August 18, 2025 | W4: Bartilad Feeds Trading | X4: August 18, 2025 | Y4: 1005 | Z4: September 3, 2025 | AA4: complete | AB4: for payment-Acctg. | AC4: 07-02-2025-07-0255
A5: 2025 | B5: July | C5: WARLITO M. TOMAS JR. | D5: Project Leader | E5: 165 | G5: 2025-234 | I5: Starter | J5: 5 | K5: sacks | L5: 2200 | M5: =SUM(J5*L5) -> 11000 | N5: 2070 | O5: =SUM(J5*N5) -> 10350 | P5: feeds for native pigs (Feeds Formulation) | Q5: Agri-DOST-PCAARRD | R5: July 23, 2025 | S5: July 30, 2025 | T5: July 31, 2025 | U5: August 12, 2025 | V5: August 18, 2025 | W5: Bartilad Feeds Trading | X5: August 18, 2025 | Y5: 1005 | Z5: September 3, 2025 | AA5: complete | AB5: for payment-Acctg. | AC5: 07-02-2025-07-0255
A6: 2025 | B6: July | C6: KLARISSE KEITH M. COBICO | D6: Administrative Assistant III | G6: 2025-235 | I6: Self-inking Dater Stamp -- Date Format: month/day/year, Year starts at 2025 | J6: 2 | K6: pcs | L6: 350 | M6: =SUM(J6*L6) -> 700 | O6: =SUM(J6*N6) -> 0 | P6: for office use | Q6: OOP | Y6: GAS1 | AA6: FAILED | AB6: quotation exceeded the budget | AD6: 4 RFQ's
A7: 2025 | B7: July | C7: KLARISSE KEITH M. COBICO | D7: Administrative Assistant III | G7: 2025-235 | I7: Stamp Pad (purple)- medium (125mm x 85mm) | J7: 1 | K7: pc | L7: 110 | M7: =SUM(J7*L7) -> 110 | O7: =SUM(J7*N7) -> 0 | P7: for office use | Q7: OOP | Y7: GAS1
A8: 2025 | B8: July | C8: KLARISSE KEITH M. COBICO | D8: Administrative Assistant III | G8: 2025-235 | I8: Transparent Tape (3/4 inch) | J8: 5 | K8: pcs | L8: 20 | M8: =SUM(J8*L8) -> 100 | O8: =SUM(J8*N8) -> 0 | P8: for office use | Q8: OOP | Y8: GAS1
A9: 2025 | B9: July | C9: KLARISSE KEITH M. COBICO | D9: Administrative Assistant III | G9: 2025-235 | I9: Certificate Holder, A4-size (green) | J9: 20 | K9: pcs | L9: 75 | M9: =SUM(J9*L9) -> 1500 | O9: =SUM(J9*N9) -> 0 | P9: for office use | Q9: OOP | Y9: GAS1
A10: 2025 | B10: July | C10: KLARISSE KEITH M. COBICO | D10: Administrative Assistant III | G10: 2025-235 | I10: Ruler (12 inches) | J10: 1 | K10: pc | L10: 15 | M10: =SUM(J10*L10) -> 15 | O10: =SUM(J10*N10) -> 0 | P10: for office use | Q10: OOP | Y10: GAS1
A11: 2025 | B11: July | C11: KLARISSE KEITH M. COBICO | D11: Administrative Assistant III | G11: 2025-235 | I11: Ruler (18 inches) | J11: 1 | K11: pc | L11: 55 | M11: =SUM(J11*L11) -> 55 | O11: =SUM(J11*N11) -> 0 | P11: for office use | Q11: OOP | Y11: GAS1
A12: 2025 | B12: July | C12: KLARISSE KEITH M. COBICO | D12: Administrative Assistant III | G12: 2025-235 | I12: Tower Extension Cord 12 outlets with switch WTE-512 Heavy Duty | J12: 2 | K12: unit | L12: 1700 | M12: =SUM(J12*L12) -> 3400 | O12: =SUM(J12*N12) -> 0 | P12: for office use | Q12: OOP | Y12: GAS1
A13: 2025 | B13: July | C13: KLARISSE KEITH M. COBICO | D13: Administrative Assistant III | G13: 2025-235 | I13: White Glue (130gms) | J13: 2 | K13: bottle | L13: 80 | M13: =SUM(J13*L13) -> 160 | O13: =SUM(J13*N13) -> 0 | P13: for office use | Q13: OOP | Y13: GAS1
A14: 2025 | B14: July | C14: KLARISSE KEITH M. COBICO | D14: Administrative Assistant III | G14: 2025-235 | I14: BT D100 (black,magenta,cyan,yellow) | J14: 2 | K14: set | L14: 2200 | M14: =SUM(J14*L14) -> 4400 | O14: =SUM(J14*N14) -> 0 | P14: for office use | Q14: OOP | Y14: GAS1
A15: 2025 | B15: July | C15: KLARISSE KEITH M. COBICO | D15: Administrative Assistant III | G15: 2025-235 | I15: Mailing Envelop (long) | J15: 1 | K15: box | L15: 530 | M15: =SUM(J15*L15) -> 530 | O15: =SUM(J15*N15) -> 0 | P15: for office use | Q15: OOP | Y15: GAS1
A16: 2025 | B16: July | C16: KLARISSE KEITH M. COBICO | D16: Administrative Assistant III | G16: 2025-235 | I16: Humidifier Scent (lavender) | J16: 1 | K16: bottle | L16: 820 | M16: =SUM(J16*L16) -> 820 | O16: =SUM(J16*N16) -> 0 | P16: for office use | Q16: OOP | Y16: GAS1
A17: 2025 | B17: July | C17: KLARISSE KEITH M. COBICO | D17: Administrative Assistant III | G17: 2025-235 | I17: Humidifier Scent (black ice) | J17: 1 | K17: bottle | L17: 820 | M17: =SUM(J17*L17) -> 820 | O17: =SUM(J17*N17) -> 0 | P17: for office use | Q17: OOP | Y17: GAS1
A18: 2025 | B18: July | C18: RICHARD B. VINALAY | D18: PM IGP Printing Services | G18: 2025-236 | I18: Desktop Computer - Specs: *Processor;Intel® Core™ i5 12th Gen.* RAM Memory; 16GB DDR4-2666MHz * Internal Storage; 1TB SSD * Graphics Card (integrate); Intel® UHD Graphics 770 *24 inches Full HD display monitor * Pre-Install; Windows 11 & MS Office * Includes; Mouse, Keyboard, Speaker *WiFi ready | J18: 1 | K18: unit | L18: 50000 | M18: =SUM(J18*L18) -> 50000 | O18: =SUM(J18*N18) -> 0 | P18: use for IGP Printing Services & Book Binding | Q18: CBAO-IGP | Y18: 1006B | AA18: FAILED | AB18: quotation exceeded the budget | AD18: 5 RFQ's + 1blank
A19: 2025 | B19: July | C19: RICHARD B. VINALAY | D19: PM IGP Printing Services | G19: 2025-236 | I19: Desktop Glue Binding Machine - Maximum size; 210*297mm, Copy Thickness; 20-500 pages (A4 paper), Format; A4 Digital, Temperature Control; Yes, Machine size; 560*360*510mm, Preheating Time; about 10 minutes, Display Mode; LCD display, Machine Power; 220V (500W),Includes; 2 packs of 5kg Hot Melt Glue Pellet for Book Binding | J19: 1 | K19: unit | L19: 34000 | M19: =SUM(J19*L19) -> 34000 | O19: =SUM(J19*N19) -> 0 | P19: use for IGP Printing Services & Book Binding | Q19: CBAO-IGP | Y19: 1006B
A20: 2025 | B20: July | C20: RICHARD B. VINALAY | D20: PM IGP Printing Services | G20: 2025-236 | I20: A3 Paper Creasing Machine - manual paper creaser multi-function indentation dashing machine | J20: 1 | K20: unit | L20: 9000 | M20: =SUM(J20*L20) -> 9000 | O20: =SUM(J20*N20) -> 0 | P20: use for IGP Printing Services & Book Binding | Q20: CBAO-IGP | Y20: 1006B
A21: 2025 | B21: July | C21: JERSHON RALPH F. CASTANO | D21: Admin. Aide III | E21: 101 | G21: 2025-237 | I21: Premium Gasoline | J21: 420 | K21: L | L21: 104 | M21: =SUM(J21*L21) -> 43680 | N21: 92 | O21: =SUM(J21*N21) -> 38640 | P21: fuel for collge motorcycle and other laboratory machines | Q21: GSO | R21: July 23, 2025 | S21: July 24, 2025 | T21: July 25, 2025 | U21: August 5, 2025 | V21: August 13, 2025 | W21: D'Island Gasoline Station | X21: August 15, 2025 | Y21: GAS20 | Z21: August 22, 2025 | AA21: complete | AB21: for payment-Acctg. | AC21: 02-101101-2025-07-00530 | AD21: 3 RFQ's | AE21: 11855/8/5/2025
A22: 2025 | B22: July | C22: JERSHON RALPH F. CASTANO | D22: Admin. Aide III | E22: 101 | G22: 2025-238 | I22: Diesel, Company Sealed | J22: 420 | K22: L | L22: 100 | M22: =SUM(J22*L22) -> 42000 | N22: 94 | O22: =SUM(J22*N22) -> 39480 | P22: fuel for collge motorcycle and other laboratory machines | Q22: GSO | R22: July 23, 2025 | S22: July 28, 2025 | T22: July 30, 2025 | U22: August 11, 2025 | V22: August 14, 2025 | W22: D'Island Gasoline Station | X22: August 14, 2025 | Y22: GAS20 | Z22: August 22, 2025 | AA22: complete | AB22: for payment-Acctg. | AC22: 02-101101-2025-07-00534 | AD22: 3 RFQ's | AE22: 11856/8/14/2025
A23: 2025 | B23: July | C23: JERSHON RALPH F. CASTANO | D23: Admin. Aide III | E23: 101 | G23: 2025-239 | I23: Multi-purpose bleach for home and laundry, (1000ml / bottle) | J23: 96 | K23: bottle | L23: 50 | M23: =SUM(J23*L23) -> 4800 | N23: 70 | O23: =SUM(J23*N23) -> 6720 | P23: supplies & materials for the upkeeping of comfort rooms | Q23: GSO | R23: July 23, 2025 | S23: July 24, 2025 | T23: July 25, 2025 | U23: August 5, 2025 | V23: Aug. 11 & Sept. 5, 2025 | W23: GDP Trading | X23: Aug. 11 & Sept. 5, 2025 | Y23: GAS20 | Z23: September 19, 2025 | AA23: complete | AB23: for payment-Acctg. | AC23: 02-101101-2025-07-00531 | AD23: 4 RFQ's | AE23: 23602/9/8/2025
A24: 2025 | B24: July | C24: JERSHON RALPH F. CASTANO | D24: Admin. Aide III | E24: 101 | G24: 2025-239 | I24: 100mm x 70mm Scrub Sponge | J24: 10 | K24: pc | L24: 55 | M24: =SUM(J24*L24) -> 550 | N24: 65 | O24: =SUM(J24*N24) -> 650 | P24: supplies & materials for the upkeeping of comfort rooms | Q24: GSO | R24: July 23, 2025 | S24: July 24, 2025 | T24: July 25, 2025 | U24: August 5, 2025 | V24: Aug. 11 & Sept. 5, 2025 | W24: GDP Trading | X24: Aug. 11 & Sept. 5, 2025 | Y24: GAS20 | Z24: September 19, 2025 | AA24: complete | AB24: for payment-Acctg. | AC24: 02-101101-2025-07-00531 | AD24: 4 RFQ's
A25: 2025 | B25: July | C25: JERSHON RALPH F. CASTANO | D25: Admin. Aide III | E25: 101 | G25: 2025-239 | I25: Toilet Hand-held bidet sprayer w/ hose | J25: 10 | K25: set | L25: 700 | M25: =SUM(J25*L25) -> 7000 | N25: 310 | O25: =SUM(J25*N25) -> 3100 | P25: supplies & materials for the upkeeping of comfort rooms | Q25: GSO | R25: July 23, 2025 | S25: July 24, 2025 | T25: July 25, 2025 | U25: August 5, 2025 | V25: Aug. 11 & Sept. 5, 2025 | W25: GDP Trading | X25: Aug. 11 & Sept. 5, 2025 | Y25: GAS20 | Z25: September 19, 2025 | AA25: complete | AB25: for payment-Acctg. | AC25: 02-101101-2025-07-00531
A26: 2025 | B26: July | C26: JERSHON RALPH F. CASTANO | D26: Admin. Aide III | E26: 101 | G26: 2025-239 | I26: Male Urinal push button flush valve | J26: 10 | K26: pc | L26: 650 | M26: =SUM(J26*L26) -> 6500 | N26: 385 | O26: =SUM(J26*N26) -> 3850 | P26: supplies & materials for the upkeeping of comfort rooms | Q26: GSO | R26: July 23, 2025 | S26: July 24, 2025 | T26: July 25, 2025 | U26: August 5, 2025 | V26: Aug. 11 & Sept. 5, 2025 | W26: GDP Trading | X26: Aug. 11 & Sept. 5, 2025 | Y26: GAS20 | Z26: September 19, 2025 | AA26: complete | AB26: for payment-Acctg. | AC26: 02-101101-2025-07-00531
A27: 2025 | B27: July | C27: ARNEL D. PABLEO | D27: Information Systems Analyst 1 | E27: 101 | G27: 2025-240 | I27: Stamp Pad Ink | J27: 2 | K27: pc | L27: 150 | M27: =SUM(J27*L27) -> 300 | N27: 30 | O27: =SUM(J27*N27) -> 60 | P27: for use on enrollment | Q27: Registrar | R27: July 24, 2025 | S27: July 31, 2025 | T27: July 31, 2025 | U27: August 12, 2025 | W27: GDP Trading | Y27: SS05 | AA27: inc. delivery | AB27: 0.82 | AC27: 02-101101-2025-07-00535 | AD27: 5 RFQ's
A28: 2025 | B28: July | C28: ARNEL D. PABLEO | D28: Information Systems Analyst 1 | E28: 101 | G28: 2025-240 | I28: Self-inking Personalized Stamp (30mm x 60mm) | J28: 1 | K28: pc | L28: 2000 | M28: =SUM(J28*L28) -> 2000 | N28: 575 | O28: =SUM(J28*N28) -> 575 | P28: for use on enrollment | Q28: Registrar | R28: July 24, 2025 | S28: July 31, 2025 | T28: July 31, 2025 | U28: August 12, 2025 | W28: GDP Trading | Y28: SS05 | AC28: 02-101101-2025-07-00535
A29: 2025 | B29: July | C29: ARNEL D. PABLEO | D29: Information Systems Analyst 1 | E29: 101 | G29: 2025-240 | I29: Pastel Stamp Ink | J29: 1 | K29: pc | L29: 350 | M29: =SUM(J29*L29) -> 350 | N29: 105 | O29: =SUM(J29*N29) -> 105 | P29: for use on enrollment | Q29: Registrar | R29: July 24, 2025 | S29: July 31, 2025 | T29: July 31, 2025 | U29: August 12, 2025 | W29: GDP Trading | Y29: SS05 | AC29: 02-101101-2025-07-00535
A30: 2025 | B30: July | C30: ARNEL D. PABLEO | D30: Information Systems Analyst 1 | E30: 101 | G30: 2025-240 | I30: Correction Tape (5mm x 10mm) | J30: 10 | K30: pc | L30: 50 | M30: =SUM(J30*L30) -> 500 | N30: 45 | O30: =SUM(J30*N30) -> 450 | P30: for use on enrollment | Q30: Registrar | R30: July 24, 2025 | S30: July 31, 2025 | T30: July 31, 2025 | U30: August 12, 2025 | W30: GDP Trading | Y30: SS05 | AC30: 02-101101-2025-07-00535
A31: 2025 | B31: July | C31: ARNEL D. PABLEO | D31: Information Systems Analyst 1 | E31: 101 | G31: 2025-240 | I31: Sign Pen (blue) | J31: 10 | K31: pc | L31: 50 | M31: =SUM(J31*L31) -> 500 | N31: 40 | O31: =SUM(J31*N31) -> 400 | P31: for use on enrollment | Q31: Registrar | R31: July 24, 2025 | S31: July 31, 2025 | T31: July 31, 2025 | U31: August 12, 2025 | W31: GDP Trading | Y31: SS05 | AC31: 02-101101-2025-07-00535
A32: 2025 | B32: July | C32: ARNEL D. PABLEO | D32: Information Systems Analyst 1 | E32: 101 | G32: 2025-240 | I32: Double-sided Foam Tape ( 1 inch) | J32: 2 | K32: roll | L32: 150 | M32: =SUM(J32*L32) -> 300 | N32: 110 | O32: =SUM(J32*N32) -> 220 | P32: for use on enrollment | Q32: Registrar | R32: July 24, 2025 | S32: July 31, 2025 | T32: July 31, 2025 | U32: August 12, 2025 | W32: GDP Trading | Y32: SS05 | AC32: 02-101101-2025-07-00535
A33: 2025 | B33: July | C33: ARNEL D. PABLEO | D33: Information Systems Analyst 1 | E33: 101 | G33: 2025-240 | I33: Double-sided Tape ( 1 inch) | J33: 5 | K33: roll | L33: 60 | M33: =SUM(J33*L33) -> 300 | N33: 40 | O33: =SUM(J33*N33) -> 200 | P33: for use on enrollment | Q33: Registrar | R33: July 24, 2025 | S33: July 31, 2025 | T33: July 31, 2025 | U33: August 12, 2025 | W33: GDP Trading | Y33: SS05 | AC33: 02-101101-2025-07-00535
A34: 2025 | B34: July | C34: ARNEL D. PABLEO | D34: Information Systems Analyst 1 | E34: 101 | G34: 2025-240 | I34: Paper Clips (vinyl coated, 33mm) | J34: 3 | K34: box | L34: 25 | M34: =SUM(J34*L34) -> 75 | N34: 25 | O34: =SUM(J34*N34) -> 75 | P34: for use on enrollment | Q34: Registrar | R34: July 24, 2025 | S34: July 31, 2025 | T34: July 31, 2025 | U34: August 12, 2025 | W34: GDP Trading | Y34: SS05 | AC34: 02-101101-2025-07-00535
A35: 2025 | B35: July | C35: ARNEL D. PABLEO | D35: Information Systems Analyst 1 | E35: 101 | G35: 2025-240 | I35: Paper Clips (vinyl coated, 50mm) | J35: 2 | K35: box | L35: 30 | M35: =SUM(J35*L35) -> 60 | N35: 35 | O35: =SUM(J35*N35) -> 70 | P35: for use on enrollment | Q35: Registrar | R35: July 24, 2025 | S35: July 31, 2025 | T35: July 31, 2025 | U35: August 12, 2025 | W35: GDP Trading | Y35: SS05 | AC35: 02-101101-2025-07-00535
A36: 2025 | B36: July | C36: ARNEL D. PABLEO | D36: Information Systems Analyst 1 | E36: 101 | G36: 2025-240 | I36: Binder Clip (2") | J36: 2 | K36: dozen | L36: 300 | M36: =SUM(J36*L36) -> 600 | N36: 105 | O36: =SUM(J36*N36) -> 210 | P36: for use on enrollment | Q36: Registrar | R36: July 24, 2025 | S36: July 31, 2025 | T36: July 31, 2025 | U36: August 12, 2025 | W36: GDP Trading | Y36: SS05 | AC36: 02-101101-2025-07-00535
A37: 2025 | B37: July | C37: ARNEL D. PABLEO | D37: Information Systems Analyst 1 | E37: 101 | G37: 2025-240 | I37: Binder Clip (1") | J37: 2 | K37: dozen | L37: 120 | M37: =SUM(J37*L37) -> 240 | N37: 30 | O37: =SUM(J37*N37) -> 60 | P37: for use on enrollment | Q37: Registrar | R37: July 24, 2025 | S37: July 31, 2025 | T37: July 31, 2025 | U37: August 12, 2025 | W37: GDP Trading | Y37: SS05 | AC37: 02-101101-2025-07-00535
A38: 2025 | B38: July | C38: ARNEL D. PABLEO | D38: Information Systems Analyst 1 | E38: 101 | G38: 2025-240 | I38: Binder Clip (3/4") | J38: 3 | K38: dozen | L38: 72 | M38: =SUM(J38*L38) -> 216 | N38: 25 | O38: =SUM(J38*N38) -> 75 | P38: for use on enrollment | Q38: Registrar | R38: July 24, 2025 | S38: July 31, 2025 | T38: July 31, 2025 | U38: August 12, 2025 | W38: GDP Trading | Y38: SS05 | AC38: 02-101101-2025-07-00535
A39: 2025 | B39: July | C39: ARNEL D. PABLEO | D39: Information Systems Analyst 1 | E39: 101 | G39: 2025-240 | I39: Binder Clip (5/8") | J39: 3 | K39: dozen | L39: 60 | M39: =SUM(J39*L39) -> 180 | N39: 60 | O39: =SUM(J39*N39) -> 180 | P39: for use on enrollment | Q39: Registrar | R39: July 24, 2025 | S39: July 31, 2025 | T39: July 31, 2025 | U39: August 12, 2025 | W39: GDP Trading | Y39: SS05 | AC39: 02-101101-2025-07-00535
... A53: 2025 | B53: July | C53: ARNEL D. PABLEO | D53: Information Systems Analyst 1 | E53: 101 | G53: 2025-240 | I53: Scotch Tape (1") | J53: 3 | K53: roll | L53: 100 | M53: =SUM(J53*L53) -> 300 | N53: 30 | O53: =SUM(J53*N53) -> 90 | P53: for use on enrollment | Q53: Registrar | R53: July 24, 2025 | S53: July 31, 2025 | T53: July 31, 2025 | U53: August 12, 2025 | W53: GDP Trading | Y53: SS05 | AC53: 02-101101-2025-07-00535
A54: 2025 | B54: July | C54: RHOUPHELINE AYA A. CADIZ | D54: Planning Officer III | G54: 2025-241 | I54: Printed Polo Shirt | J54: 140 | K54: pc | L54: 550 | M54: =SUM(J54*L54) -> 77000 | O54: =SUM(J54*N54) -> 0 | P54: to be used as a uniform for the 21st Founding Anniversary Celebration | Q54: Planning | Y54: GAS8 | AA54: CANCELLED | AB54: the 1st PR proceeded there is a supplier….
A55: 2025 | B55: July | C55: DOREEN C. CASTILLO | D55: Director for CBAO | E55: 101 | G55: 2025-242 | I55: Pork | J55: 10.5 | K55: kg | L55: 460 | M55: =SUM(J55*L55) -> 4830 | N55: 440 | O55: =SUM(J55*N55) -> 4620 | P55: for catering services | Q55: CBAO | R55: July 23, 2025 | S55: July 28, 2025 | T55: July 30, 2025 | U55: August 12, 2025 | V55: August 16, 2025 | W55: Sophia Marie Store | X55: August 22, 2025 | Y55: 1006 | Z55: September 2, 2025 | AA55: complete | AB55: for payment-Acctg. | AC55: 02-101101-2025-08-00538 | AD55: 3 RFQ's | AE55: 1301/
A56: 2025 | B56: July | C56: DOREEN C. CASTILLO | D56: Director for CBAO | E56: 101 | G56: 2025-242 | I56: Whole Chicken | J56: 9.5 | K56: kg | L56: 270 | M56: =SUM(J56*L56) -> 2565 | N56: 280 | O56: =SUM(J56*N56) -> 2660 | P56: for catering services | Q56: CBAO | R56: July 23, 2025 | S56: July 28, 2025 | T56: July 30, 2025 | U56: August 12, 2025 | V56: August 16, 2025 | W56: Sophia Marie Store | X56: August 22, 2025 | Y56: 1006 | Z56: September 2, 2025 | AA56: complete | AB56: for payment-Acctg. | AC56: 02-101101-2025-08-00538
A57: 2025 | B57: July | C57: ANGELITA H. VARGAS | D57: Director for Instruction | E57: 101 | G57: 2025-243 | I57: Printer Functions: Print,scan,copy, Printer Type: Inkjet Printer, Product Dimensions (width x depth x height): 435mm x 418mm x 180mm, Weight: 9.6 kg, Print Speed: Up to 17.0 (mono)/Up to 16.5 (colour) ipm, Paper Type: Plain Paper, Inkjet Paper (coated paper), Glossy Paper,Recycled Paper, Paper size: A4, Letter,Legal, Mexico Legal,India Legal, Folio, Executive, B5 (JIS),A5,B6(JIS),A6,Photo (10x15cm/4x6"), Photo-L(9x13cm/3.5x5"),Photo-2L(13x18cm/5x7"),index card(13x20cm/5x8"),Com-10,DL Envelop,Monarch,C5 | J57: 1 | K57: unit | L57: 26000 | M57: =SUM(J57*L57) -> 26000 | N57: 20800 | O57: =SUM(J57*N57) -> 20800 | P57: for DI's office use | Q57: DI | R57: July 24, 2025 | S57: July 31, 2025 | T57: July 31, 2025 | U57: August 12, 2025 | V57: October 2, 2025 | W57: One-Touch Technology Trading | X57: October 2, 2025 | Y57: Acad9 | Z57: October 8, 2025 | AA57: complete | AB57: for payment-Acctg. | AC57: 05-02-2025-07-0067 | AD57: 5 RFQ's | AE57: 7954/10/2/2025
A58: 2025 | B58: July | C58: RENELYN D. KILLASE | D58: College Librarian | E58: 165 | F58: Dir. Acquisition | G58: 2025-244 | H58: Dir. Acquisition | I58: Sustainable Farming: Nurturing the Earth for Future Generations,Kushwaha, 2024, 9781774699515,Wiseman's Book Trading, Inc. | J58: 1 | K58: copy | L58: 6998 | M58: =SUM(J58*L58) -> 6998 | N58: 6998 | O58: =SUM(J58*N58) -> 6998 | P58: the list of book titles have been carefully selected by the program chairpersons to enhance the learning resources | Q58: Library | T58: September 24, 2025 | U58: October 1, 2025 | W58: Wiseman's Book Trading, Inc. | X58: October 13, 2025 | Y58: SSO10 | Z58: October 28, 2025 | AA58: complete | AB58: for payment-Acctg. | AC58: 07-02-2025-09-0328 | AD58: 11996/
A59: 2025 | B59: July | C59: RENELYN D. KILLASE | D59: College Librarian | E59: 165 | G59: 2025-244 | I59: The Genetic Manipulation in Plants, Singh, 2023, 9789394137646, Wiseman's Book Trading, Inc. | J59: 1 | K59: copy | L59: 4998 | M59: =SUM(J59*L59) -> 4998 | N59: 4998 | O59: =SUM(J59*N59) -> 4998 | P59: the list of book titles have been carefully selected by the program chairpersons to enhance the learning resources | Q59: Library | T59: September 24, 2025 | U59: October 1, 2025 | W59: Wiseman's Book Trading, Inc. | X59: October 13, 2025 | Y59: SSO10 | Z59: October 28, 2025 | AA59: complete | AB59: for payment-Acctg. | AC59: 07-02-2025-09-0328
A60: 2025 | B60: July | C60: RENELYN D. KILLASE | D60: College Librarian | E60: 165 | G60: 2025-244 | I60: Thermodynamics of the Atmosphere: Basic Physics and applications to Earth's Science, Spezia, 2024, 97817746998730, Wiseman's Book Trading, Inc. | J60: 1 | K60: copy | L60: 6998 | M60: =SUM(J60*L60) -> 6998 | N60: 6998 | O60: =SUM(J60*N60) -> 6998 | P60: the list of book titles have been carefully selected by the program chairpersons to enhance the learning resources | Q60: Library | T60: September 24, 2025 | U60: October 1, 2025 | W60: Wiseman's Book Trading, Inc. | X60: October 13, 2025 | Y60: SSO10 | Z60: October 28, 2025 | AA60: complete | AB60: for payment-Acctg. | AC60: 07-02-2025-09-0328
A61: 2025 | B61: July | C61: RENELYN D. KILLASE | D61: College Librarian | E61: 165 | G61: 2025-245 | I61: Biodegradable Garbage Bag (black,large) | J61: 10 | K61: roll | L61: 70 | M61: =SUM(J61*L61) -> 700 | N61: 100 | O61: =SUM(J61*N61) -> 1000 | P61: the following items will support the overall maintenance, functionality & comfort of the library | Q61: Library | R61: July 25, 2025 | S61: July 31, 2025 | T61: August 1, 2025 | U61: August 12, 2025 | V61: Aug.12,Sept. 12,17,Nov.13 & 25, 2025 | W61: M.G. Hubalde's General Merchandise | X61: Aug.15,Sept.15,17,Nov.13 &25, 2025 | Y61: SSO10 | Z61: December 5, 2025 | AA61: complete | AB61: for payment-Acctg. | AC61: 07-02-2025-08-0259 | AD61: 5 RFQ's | AE61: 13299-13302/11/25/2025
A62: 2025 | B62: July | C62: RENELYN D. KILLASE | D62: College Librarian | E62: 165 | G62: 2025-245 | I62: Soft Broom (soft bristles) | J62: 2 | K62: pcs | L62: 200 | M62: =SUM(J62*L62) -> 400 | N62: 250 | O62: =SUM(J62*N62) -> 500 | P62: the following items will support the overall maintenance, functionality & comfort of the library | Q62: Library | R62: July 25, 2025 | S62: July 31, 2025 | T62: August 1, 2025 | U62: August 12, 2025 | V62: Aug.12,Sept. 12,17,Nov.13 & 25, 2025 | W62: M.G. Hubalde's General Merchandise | X62: Aug.15,Sept.15,17,Nov.13 &25, 2025 | Y62: SSO10 | Z62: December 5, 2025 | AA62: complete | AB62: for payment-Acctg. | AC62: 07-02-2025-08-0259
A63: 2025 | B63: July | C63: RENELYN D. KILLASE | D63: College Librarian | E63: 165 | G63: 2025-245 | I63: Stain & Limescale Cleaner White Fresh 880ml | J63: 2 | K63: pcs | L63: 450 | M63: =SUM(J63*L63) -> 900 | N63: 310 | O63: =SUM(J63*N63) -> 620 | P63: the following items will support the overall maintenance, functionality & comfort of the library | Q63: Library | R63: July 25, 2025 | S63: July 31, 2025 | T63: August 1, 2025 | U63: August 12, 2025 | V63: Aug.12,Sept. 12,17,Nov.13 & 25, 2025 | W63: M.G. Hubalde's General Merchandise | X63: Aug.15,Sept.15,17,Nov.13 &25, 2025 | Y63: SSO10 | Z63: December 5, 2025 | AA63: complete | AB63: for payment-Acctg. | AC63: 07-02-2025-08-0259
A64: 2025 | B64: July | C64: RENELYN D. KILLASE | D64: College Librarian | E64: 165 | G64: 2025-245 | I64: Bathroom Deodorizer Sampaguita Scent 100g | J64: 3 | K64: pcs | L64: 97 | M64: =SUM(J64*L64) -> 291 | N64: 75 | O64: =SUM(J64*N64) -> 225 | P64: the following items will support the overall maintenance, functionality & comfort of the library | Q64: Library | R64: July 25, 2025 | S64: July 31, 2025 | T64: August 1, 2025 | U64: August 12, 2025 | V64: Aug.12,Sept. 12,17,Nov.13 & 25, 2025 | W64: M.G. Hubalde's General Merchandise | X64: Aug.15,Sept.15,17,Nov.13 &25, 2025 | Y64: SSO10 | Z64: December 5, 2025 | AA64: complete | AB64: for payment-Acctg. | AC64: 07-02-2025-08-0259
A65: 2025 | B65: July | C65: RENELYN D. KILLASE | D65: College Librarian | E65: 165 | G65: 2025-245 | I65: Bathroom Deodorizer Lemon Scent 100g | J65: 3 | K65: pcs | L65: 97 | M65: =SUM(J65*L65) -> 291 | N65: 75 | O65: =SUM(J65*N65) -> 225 | P65: the following items will support the overall maintenance, functionality & comfort of the library | Q65: Library | R65: July 25, 2025 | S65: July 31, 2025 | T65: August 1, 2025 | U65: August 12, 2025 | V65: Aug.12,Sept. 12,17,Nov.13 & 25, 2025 | W65: M.G. Hubalde's General Merchandise | X65: Aug.15,Sept.15,17,Nov.13 &25, 2025 | Y65: SSO10 | Z65: December 5, 2025 | AA65: complete | AB65: for payment-Acctg. | AC65: 07-02-2025-08-0259
A66: 2025 | B66: July | C66: RENELYN D. KILLASE | D66: College Librarian | E66: 165 | G66: 2025-245 | I66: 24hr Cockroach Killer (6pcs/pack) | J66: 2 | K66: pack | L66: 549 | M66: =SUM(J66*L66) -> 1098 | N66: 450 | O66: =SUM(J66*N66) -> 900 | P66: the following items will support the overall maintenance, functionality & comfort of the library | Q66: Library | R66: July 25, 2025 | S66: July 31, 2025 | T66: August 1, 2025 | U66: August 12, 2025 | V66: Aug.12,Sept. 12,17,Nov.13 & 25, 2025 | W66: M.G. Hubalde's General Merchandise | X66: Aug.15,Sept.15,17,Nov.13 &25, 2025 | Y66: SSO10 | Z66: December 5, 2025 | AA66: complete | AB66: for payment-Acctg. | AC66: 07-02-2025-08-0259
A67: 2025 | B67: July | C67: RENELYN D. KILLASE | D67: College Librarian | E67: 165 | G67: 2025-245 | I67: Disinfectant Spray Fresh Blossom 510g | J67: 1 | K67: pc | L67: 945 | M67: =SUM(J67*L67) -> 945 | N67: 750 | O67: =SUM(J67*N67) -> 750 | P67: the following items will support the overall maintenance, functionality & comfort of the library | Q67: Library | R67: July 25, 2025 | S67: July 31, 2025 | T67: August 1, 2025 | U67: August 12, 2025 | V67: Aug.12,Sept. 12,17,Nov.13 & 25, 2025 | W67: M.G. Hubalde's General Merchandise | X67: Aug.15,Sept.15,17,Nov.13 &25, 2025 | Y67: SSO10 | Z67: December 5, 2025 | AA67: complete | AB67: for payment-Acctg. | AC67: 07-02-2025-08-0259
A68: 2025 | B68: July | C68: RENELYN D. KILLASE | D68: College Librarian | E68: 165 | G68: 2025-245 | I68: Outdoor Doormat Rubber Rug (40x60cm, grey) | J68: 2 | K68: pcs | L68: 165 | M68: =SUM(J68*L68) -> 330 | N68: 480 | O68: =SUM(J68*N68) -> 960 | P68: the following items will support the overall maintenance, functionality & comfort of the library | Q68: Library | R68: July 25, 2025 | S68: July 31, 2025 | T68: August 1, 2025 | U68: August 12, 2025 | V68: Aug.12,Sept. 12,17,Nov.13 & 25, 2025 | W68: M.G. Hubalde's General Merchandise | X68: Aug.15,Sept.15,17,Nov.13 &25, 2025 | Y68: SSO10 | Z68: December 5, 2025 | AA68: complete | AB68: for payment-Acctg. | AC68: 07-02-2025-08-0259
A69: 2025 | B69: July | C69: RENELYN D. KILLASE | D69: College Librarian | E69: 165 | G69: 2025-245 | I69: Feather Duster Washable Anti Static Duster with soft micrifiber for cleaning (green) | J69: 2 | K69: pcs | L69: 105 | M69: =SUM(J69*L69) -> 210 | N69: 270 | O69: =SUM(J69*N69) -> 540 | P69: the following items will support the overall maintenance, functionality & comfort of the library | Q69: Library | R69: July 25, 2025 | S69: July 31, 2025 | T69: August 1, 2025 | U69: August 12, 2025 | V69: Aug.12,Sept. 12,17,Nov.13 & 25, 2025 | W69: M.G. Hubalde's General Merchandise | X69: Aug.15,Sept.15,17,Nov.13 &25, 2025 | Y69: SSO10 | Z69: December 5, 2025 | AA69: complete | AB69: for payment-Acctg. | AC69: 07-02-2025-08-0259
A70: 2025 | B70: July | C70: RENELYN D. KILLASE | D70: College Librarian | E70: 165 | G70: 2025-245 | I70: Metal Bookends/Book stand/book stopper,heavy duty (green/black) | J70: 50 | K70: pcs | L70: 60 | M70: =SUM(J70*L70) -> 3000 | N70: 100 | O70: =SUM(J70*N70) -> 5000 | P70: the following items will support the overall maintenance, functionality & comfort of the library | Q70: Library | R70: July 25, 2025 | S70: July 31, 2025 | T70: August 1, 2025 | U70: August 12, 2025 | V70: Aug.12,Sept. 12,17,Nov.13 & 25, 2025 | W70: M.G. Hubalde's General Merchandise | X70: Aug.15,Sept.15,17,Nov.13 &25, 2025 | Y70: SSO10 | Z70: December 5, 2025 | AA70: complete | AB70: for payment-Acctg. | AC70: 07-02-2025-08-0259
A71: 2025 | B71: July | C71: RENELYN D. KILLASE | D71: College Librarian | E71: 165 | G71: 2025-245 | I71: Sanitizer/Alcohol with moisturizer Alcohol Spray - 500ml with sprayer | J71: 4 | K71: pcs | L71: 185 | M71: =SUM(J71*L71) -> 740 | N71: 230 | O71: =SUM(J71*N71) -> 920 | P71: the following items will support the overall maintenance, functionality & comfort of the library | Q71: Library | R71: July 25, 2025 | S71: July 31, 2025 | T71: August 1, 2025 | U71: August 12, 2025 | V71: Aug.12,Sept. 12,17,Nov.13 & 25, 2025 | W71: M.G. Hubalde's General Merchandise | X71: Aug.15,Sept.15,17,Nov.13 &25, 2025 | Y71: SSO10 | Z71: December 5, 2025 | AA71: complete | AB71: for payment-Acctg. | AC71: 07-02-2025-08-0259
A72: 2025 | B72: July | C72: RENELYN D. KILLASE | D72: College Librarian | E72: 165 | G72: 2025-245 | I72: Matte Sticker Paper (A4, 80gsm, inkjet friendly) | J72: 10 | K72: pack | L72: 450 | M72: =SUM(J72*L72) -> 4500 | N72: 70 | O72: =SUM(J72*N72) -> 700 | P72: the following items will support the overall maintenance, functionality & comfort of the library | Q72: Library | R72: July 25, 2025 | S72: July 31, 2025 | T72: August 1, 2025 | U72: August 12, 2025 | V72: Aug.12,Sept. 12,17,Nov.13 & 25, 2025 | W72: M.G.Hubalde's General Merchandise | X72: Aug.15,Sept.15,17,Nov.13 &25, 2025 | Y72: SSO10 | Z72: December 5, 2025 | AA72: complete | AB72: for payment-Acctg. | AC72: 07-02-2025-08-0259
A73: 2025 | B73: July | C73: RENELYN D. KILLASE | D73: College Librarian | E73: 165 | F73: Dir. Acquisition | G73: 2025-246 | H73: Dir. Acquisition | I73: Artificial Intelligence and Quantum Computing, Schweinfurth, 2025, 9789362241931, Wiseman's Book Trading, Inc. | J73: 1 | K73: copy | L73: 4998 | M73: =SUM(J73*L73) -> 4998 | N73: 4998 | O73: =SUM(J73*N73) -> 4998 | P73: the list of book titles have been carefully selected by the program chairpersons to enhance the learning resources | Q73: Library | T73: September 24, 2025 | U73: October 1, 2025 | W73: Wiseman's Book Trading, Inc. | X73: October 13, 2025 | Y73: SSO10 | Z73: October 28, 2025 | AA73: complete | AB73: for payment-Acctg. | AC73: 07-02-2025-09-0329 | AE73: 11732-11733/11995
A74: 2025 | B74: July | C74: RENELYN D. KILLASE | D74: College Librarian | E74: 165 | G74: 2025-246 | I74: Bar management and control (2nd ed.) (with access code), Bezerra, 2024, 9781984688576, Wiseman's Book Trading | J74: 1 | K74: copy | L74: 5998 | M74: =SUM(J74*L74) -> 5998 | N74: 5998 | O74: =SUM(J74*N74) -> 5998 | P74: the list of book titles have been carefully selected by the program chairpersons to enhance the learning resources | Q74: Library | T74: September 24, 2025 | U74: October 1, 2025 | W74: Wiseman's Book Trading, Inc. | X74: October 13, 2025 | Y74: SSO10 | Z74: October 28, 2025 | AA74: complete | AB74: for payment-Acctg. | AC74: 07-02-2025-09-0329
A75: 2025 | B75: July | C75: RENELYN D. KILLASE | D75: College Librarian | E75: 165 | G75: 2025-246 | I75: Basic Computer Coding: Java Script 3rd/ed, Gbadegesin, 2024, 9781984689337, Wiseman's Book Trading, Inc. | J75: 1 | K75: copy | L75: 5998 | M75: =SUM(J75*L75) -> 5998 | N75: 5998 | O75: =SUM(J75*N75) -> 5998 | P75: the list of book titles have been carefully selected by the program chairpersons to enhance the learning resources | Q75: Library | T75: September 24, 2025 | U75: October 1, 2025 | W75: Wiseman's Book Trading, Inc. | X75: October 13, 2025 | Y75: SSO10 | Z75: October 28, 2025 | AA75: complete | AB75: for payment-Acctg. | AC75: 07-02-2025-09-0329
A76: 2025 | B76: July | C76: RENELYN D. KILLASE | D76: College Librarian | E76: 165 | G76: 2025-246 | I76: Basic of Cloud Computing, 3G E-Learning, 2024, 9781984685773, Wiseman's Book Trading, Inc. | J76: 1 | K76: copy | L76: 4998 | M76: =SUM(J76*L76) -> 4998 | N76: 4998 | O76: =SUM(J76*N76) -> 4998 | P76: the list of book titles have been carefully selected by the program chairpersons to enhance the learning resources | Q76: Library | T76: September 24, 2025 | U76: October 1, 2025 | W76: Wiseman's Book Trading, Inc. | X76: October 13, 2025 | Y76: SSO10 | Z76: October 28, 2025 | AA76: complete | AB76: for payment-Acctg. | AC76: 07-02-2025-09-0329
A77: 2025 | B77: July | C77: RENELYN D. KILLASE | D77: College Librarian | E77: 165 | G77: 2025-246 | I77: Basics of Computer Graphics, 3G E-Learning, 2024, 9781984685797, Wiseman's Book Trading, Inc. | J77: 1 | K77: copy | L77: 4998 | M77: =SUM(J77*L77) -> 4998 | N77: 4998 | O77: =SUM(J77*N77) -> 4998 | P77: the list of book titles have been carefully selected by the program chairpersons to enhance the learning resources | Q77: Library | T77: September 24, 2025 | U77: October 1, 2025 | W77: Wiseman's Book Trading, Inc. | X77: October 13, 2025 | Y77: SSO10 | Z77: October 28, 2025 | AA77: complete | AB77: for payment-Acctg. | AC77: 07-02-2025-09-0329
A78: 2025 | B78: July | C78: RENELYN D. KILLASE | D78: College Librarian | E78: 165 | G78: 2025-246 | I78: Basics of Networking, 3G E-Learning 2024, 9781984685780, Wiseman's Book Trading, Inc. | J78: 1 | K78: copy | L78: 4998 | M78: =SUM(J78*L78) -> 4998 | N78: 4998 | O78: =SUM(J78*N78) -> 4998 | P78: the list of book titles have been carefully selected by the program chairpersons to enhance the learning resources | Q78: Library | T78: September 24, 2025 | U78: October 1, 2025 | W78: Wiseman's Book Trading, Inc. | X78: October 13, 2025 | Y78: SSO10 | Z78: October 28, 2025 | AA78: complete | AB78: for payment-Acctg. | AC78: 07-02-2025-09-0329
A79: 2025 | B79: July | C79: RENELYN D. KILLASE | D79: College Librarian | E79: 165 | G79: 2025-246 | I79: Biodiversity ,Environment & Ecosystem Services, Arya, 2023, 9788195916931, Wiseman's Book Trading, Inc. | J79: 1 | K79: copy | L79: 4998 | M79: =SUM(J79*L79) -> 4998 | N79: 4998 | O79: =SUM(J79*N79) -> 4998 | P79: the list of book titles have been carefully selected by the program chairpersons to enhance the learning resources | Q79: Library | T79: September 24, 2025 | U79: October 1, 2025 | W79: Wiseman's Book Trading, Inc. | X79: October 13, 2025 | Y79: SSO10 | Z79: October 28, 2025 | AA79: complete | AB79: for payment-Acctg. | AC79: 07-02-2025-09-0329
A80: 2025 | B80: July | C80: RENELYN D. KILLASE | D80: College Librarian | E80: 165 | G80: 2025-246 | I80: Biotechnology and Society (2nd Edition), Yoshinaka, 2024, 9781984688989, Wiseman's Book Trading, Inc. | J80: 1 | K80: copy | L80: 5998 | M80: =SUM(J80*L80) -> 5998 | N80: 5998 | O80: =SUM(J80*N80) -> 5998 | P80: the list of book titles have been carefully selected by the program chairpersons to enhance the learning resources | Q80: Library | T80: September 24, 2025 | U80: October 1, 2025 | W80: Wiseman's Book Trading, Inc. | X80: October 13, 2025 | Y80: SSO10 | Z80: October 28, 2025 | AA80: complete | AB80: for payment-Acctg. | AC80: 07-02-2025-09-0329
A81: 2025 | B81: July | C81: RENELYN D. KILLASE | D81: College Librarian | E81: 165 | G81: 2025-246 | I81: C Programming, Singh, 2024, 9781774699607, Wiseman's Book Trading, Inc. | J81: 1 | K81: copy | L81: 6998 | M81: =SUM(J81*L81) -> 6998 | N81: 6998 | O81: =SUM(J81*N81) -> 6998 | P81: the list of book titles have been carefully selected by the program chairpersons to enhance the learning resources | Q81: Library | T81: September 24, 2025 | U81: October 1, 2025 | W81: Wiseman's Book Trading, Inc. | X81: October 13, 2025 | Y81: SSO10 | Z81: October 28, 2025 | AA81: complete | AB81: for payment-Acctg. | AC81: 07-02-2025-09-0329
A82: 2025 | B82: July | C82: RENELYN D. KILLASE | D82: College Librarian | E82: 165 | G82: 2025-246 | I82: Child growth and development, Matthews, 2024, 9798886263572, Wiseman's Book Trading, Inc. | J82: 1 | K82: copy | L82: 6998 | M82: =SUM(J82*L82) -> 6998 | N82: 6998 | O82: =SUM(J82*N82) -> 6998 | P82: the list of book titles have been carefully selected by the program chairpersons to enhance the learning resources | Q82: Library | T82: September 24, 2025 | U82: October 1, 2025 | W82: Wiseman's Book Trading, Inc. | X82: October 13, 2025 | Y82: SSO10 | Z82: October 28, 2025 | AA82: complete | AB82: for payment-Acctg. | AC82: 07-02-2025-09-0329
A83: 2025 | B83: July | C83: RENELYN D. KILLASE | D83: College Librarian | E83: 165 | G83: 2025-246 | I83: Community based tourism, Juyal, 2024, 9781774697153, Forefront Book | J83: 1 | K83: copy | L83: 4680 | M83: =SUM(J83*L83) -> 4680 | N83: 4680 | O83: =SUM(J83*N83) -> 4680 | P83: the list of book titles have been carefully selected by the program chairpersons to enhance the learning resources | Q83: Library | T83: September 24, 2025 | U83: October 1, 2025 | W83: Wiseman's Book Trading, Inc. | X83: October 13, 2025 | Y83: SSO10 | Z83: October 28, 2025 | AA83: complete | AB83: for payment-Acctg. | AC83: 07-02-2025-09-0329
A84: 2025 | B84: July | C84: RENELYN D. KILLASE | D84: College Librarian | E84: 165 | G84: 2025-246 | I84: Competitive advantages of service quality in hospitality, tourism, and leisure services, Kalacas, 2024, 9781774698884, Wiseman's Books Trading | J84: 1 | K84: copy | L84: 6998 | M84: =SUM(J84*L84) -> 6998 | N84: 6998 | O84: =SUM(J84*N84) -> 6998 | P84: the list of book titles have been carefully selected by the program chairpersons to enhance the learning resources | Q84: Library | T84: September 24, 2025 | U84: October 1, 2025 | W84: Wiseman's Book Trading, Inc. | X84: October 13, 2025 | Y84: SSO10 | Z84: October 28, 2025 | AA84: complete | AB84: for payment-Acctg. | AC84: 07-02-2025-09-0329
A85: 2025 | B85: July | C85: RENELYN D. KILLASE | D85: College Librarian | E85: 165 | G85: 2025-246 | I85: Computer Basics With Office Automation , Singh, 2024, 9789357511087, Wiseman's Book Trading, Inc. | J85: 1 | K85: copy | L85: 5998 | M85: =SUM(J85*L85) -> 5998 | N85: 5998 | O85: =SUM(J85*N85) -> 5998 | P85: the list of book titles have been carefully selected by the program chairpersons to enhance the learning resources | Q85: Library | T85: September 24, 2025 | U85: October 1, 2025 | W85: Wiseman's Book Trading, Inc. | X85: October 13, 2025 | Y85: SSO10 | Z85: October 28, 2025 | AA85: complete | AB85: for payment-Acctg. | AC85: 07-02-2025-09-0329
... A102: 2025 | B102: July | C102: RENELYN D. KILLASE | D102: College Librarian | E102: 165 | G102: 2025-246 | I102: Software design, Lal, 2024, 9781774697795, Wiseman's Book Trading, Inc. | J102: 1 | K102: copy | L102: 5998 | M102: =SUM(J102*L102) -> 5998 | N102: 5998 | O102: =SUM(J102*N102) -> 5998 | P102: the list of book titles have been carefully selected by the program chairpersons to enhance the learning resources | Q102: Library | T102: September 24, 2025 | U102: October 1, 2025 | W102: Wiseman's Book Trading, Inc. | X102: October 13, 2025 | Y102: SSO10 | Z102: October 28, 2025 | AA102: complete | AB102: for payment-Acctg. | AC102: 07-02-2025-09-0329
A103: 2025 | B103: July | C103: WARLITO M. TOMAS JR. | D103: Project Leader | E103: 165 | G103: 2025-247 | I103: Rosemary Powder (500grams) | J103: 1 | K103: gram | L103: 500 | M103: =SUM(J103*L103) -> 500 | O103: =SUM(J103*N103) -> 0 | P103: for research project " Developing Feed Formulations for Bagu Ivatan Using Locally-Available Feeds and Forages" | Q103: Agri-Feed Formulation | Y103: Acad7 | AA103: FAILED | AB103: quotation exceeded the budget | AD103: 3 RFQ's
A104: 2025 | B104: July | C104: WARLITO M. TOMAS JR. | D104: Project Leader | E104: 165 | G104: 2025-248 | I104: Basemix (Atovi) | J104: 2 | K104: kg | L104: 1425 | M104: =SUM(J104*L104) -> 2850 | N104: 890 | O104: =SUM(J104*N104) -> 1780 | P104: for research project " Developing Feed Formulations for Bagu Ivatan Using Locally-Available Feeds and Forages" | Q104: Agri-Feed Formulation | R104: July 24, 2025 | S104: July 31, 2025 | T104: July 31, 2025 | U104: August 12, 2025 | W104: FVA Trading | X104: September 1, 2025 | Y104: Acad7 | Z104: September 12, 2025 | AA104: complete | AB104: for payment-Acctg. | AC104: 07-02-2025-07-0254 | AD104: 5 RFQ's | AE104: 3002/9/2/2025
A105: 2025 | B105: July | C105: WARLITO M. TOMAS JR. | D105: Project Leader | E105: 165 | G105: 2025-248 | I105: Potassium Sorbate | J105: 1 | K105: kg | L105: 750 | M105: =SUM(J105*L105) -> 750 | N105: 1150 | O105: =SUM(J105*N105) -> 1150 | P105: for research project " Developing Feed Formulations for Bagu Ivatan Using Locally-Available Feeds and Forages" | Q105: Agri-Feed Formulation | R105: July 24, 2025 | S105: July 31, 2025 | T105: July 31, 2025 | U105: August 12, 2025 | W105: FVA Trading | X105: September 1, 2025 | Y105: Acad7 | Z105: September 12, 2025 | AA105: complete | AB105: for payment-Acctg. | AC105: 07-02-2025-07-0254
A106: 2025 | B106: July | C106: WARLITO M. TOMAS JR. | D106: Project Leader | E106: 165 | G106: 2025-248 | I106: Molasses | J106: 1 | K106: gallon | L106: 500 | M106: =SUM(J106*L106) -> 500 | N106: 385 | O106: =SUM(J106*N106) -> 385 | P106: for research project " Developing Feed Formulations for Bagu Ivatan Using Locally-Available Feeds and Forages" | Q106: Agri-Feed Formulation | R106: July 24, 2025 | S106: July 31, 2025 | T106: July 31, 2025 | U106: August 12, 2025 | V106: September 1, 2025 | W106: FVA Trading | X106: September 1, 2025 | Y106: Acad7 | Z106: September 12, 2025 | AA106: complete | AB106: for payment-Acctg. | AC106: 07-02-2025-07-0254 | AD106: 5 RFQ's | AE106: 3002/9/2/2025
A107: 2025 | B107: July | C107: EMMA B. ABAD | D107: Audit Team Leader | E107: 101 | F107: Toss Coin | G107: 2025-249 | I107: 4 Drawer Lateral Filing Cabinet | J107: 1 | K107: pc | L107: 20000 | M107: =SUM(J107*L107) -> 20000 | N107: 18000 | O107: =SUM(J107*N107) -> 18000 | P107: for office use | Q107: COA | R107: July 25, 2025 | S107: July 31, 2025 | T107: August 1, 2025 | U107: August 12, 2025 | V107: September 2, 2025 | W107: FVA Trading | X107: September 3, 2025 | Y107: GAS25 | Z107: September 12, 2025 | AA107: complete | AB107: for payment-Acctg. | AC107: 02-101101-2025-08-00542 | AD107: 5 RFQ's | AE107: 3001/9/2/2025
A108: 2025 | B108: July | C108: ZOE DYMPNA H. CARTANO | D108: Budget Officer II | E108: 101 | G108: 2025-250 | I108: Metal File Document Tray (4 layers) | J108: 2 | K108: pcs | L108: 1500 | M108: =SUM(J108*L108) -> 3000 | N108: 600 | O108: =SUM(J108*N108) -> 1200 | P108: for office use | Q108: Budget | R108: July 25, 2025 | S108: July 31, 2025 | T108: August 1, 2025 | U108: August 12, 2025 | V108: August 29 & Oct. 24, 2025 | W108: FVA Trading | X108: Sept. 1 & Oct. 24, 2025 | Y108: GAS19 | Z108: November 13, 2025 | AA108: complete | AB108: for payment-Acctg. | AC108: 02-101101-2025-08-00541 | AD108: 5 RFQ's | AE108: 3122/11/13/2025
A109: 2025 | B109: July | C109: ZOE DYMPNA H. CARTANO | D109: Budget Officer II | E109: 101 | G109: 2025-250 | I109: Side Table with 2 drawers | J109: 1 | K109: unit | L109: 1500 | M109: =SUM(J109*L109) -> 1500 | N109: 975 | O109: =SUM(J109*N109) -> 975 | P109: for office use | Q109: Budget | R109: July 25, 2025 | S109: July 31, 2025 | T109: August 1, 2025 | U109: August 12, 2025 | V109: August 29 & Oct. 24, 2025 | W109: FVA Trading | X109: Sept. 1 & Oct. 24, 2025 | Y109: GAS19 | Z109: November 13, 2025 | AA109: complete | AB109: for payment-Acctg. | AC109: 02-101101-2025-08-00541
A110: 2025 | B110: July | C110: ZOE DYMPNA H. CARTANO | D110: Budget Officer II | E110: 101 | G110: 2025-250 | I110: Multifunctional File Holder | J110: 2 | K110: pcs | L110: 450 | M110: =SUM(J110*L110) -> 900 | N110: 525 | O110: =SUM(J110*N110) -> 1050 | P110: for office use | Q110: Budget | R110: July 25, 2025 | S110: July 31, 2025 | T110: August 1, 2025 | U110: August 12, 2025 | V110: August 29 & Oct. 24, 2025 | W110: FVA Trading | X110: Sept. 1 & Oct. 24, 2025 | Y110: GAS19 | Z110: November 13, 2025 | AA110: complete | AB110: for payment-Acctg. | AC110: 02-101101-2025-08-00541
A111: 2025 | B111: July | C111: ZOE DYMPNA H. CARTANO | D111: Budget Officer II | E111: 101 | G111: 2025-250 | I111: Acrylic Bookshelf Storage Box | J111: 2 | K111: pcs | L111: 300 | M111: =SUM(J111*L111) -> 600 | N111: 375 | O111: =SUM(J111*N111) -> 750 | P111: for office use | Q111: Budget | R111: July 25, 2025 | S111: July 31, 2025 | T111: August 1, 2025 | U111: August 12, 2025 | V111: August 29 & Oct. 24, 2025 | W111: FVA Trading | X111: Sept. 1 & Oct. 24, 2025 | Y111: GAS19 | Z111: November 13, 2025 | AA111: complete | AB111: for payment-Acctg. | AC111: 02-101101-2025-08-00541
A112: 2025 | B112: July | C112: ZOE DYMPNA H. CARTANO | D112: Budget Officer II | E112: 101 | G112: 2025-250 | I112: Magazine Box (preferably black or gray) made of chipboard | J112: 10 | K112: pcs | L112: 350 | M112: =SUM(J112*L112) -> 3500 | N112: 270 | O112: =SUM(J112*N112) -> 2700 | P112: for office use | Q112: Budget | R112: July 25, 2025 | S112: July 31, 2025 | T112: August 1, 2025 | U112: August 12, 2025 | V112: August 29 & Oct. 24, 2025 | W112: FVA Trading | X112: Sept. 1 & Oct. 24, 2025 | Y112: GAS19 | Z112: November 13, 2025 | AA112: complete | AB112: for payment-Acctg. | AC112: 02-101101-2025-08-00541
A113: 2025 | B113: July | C113: ZOE DYMPNA H. CARTANO | D113: Budget Officer II | E113: 101 | G113: 2025-250 | I113: Office Table (80x50x75) | J113: 1 | K113: unit | L113: 9000 | M113: =SUM(J113*L113) -> 9000 | N113: 9000 | O113: =SUM(J113*N113) -> 9000 | P113: for office use | Q113: Budget | R113: July 25, 2025 | S113: July 31, 2025 | T113: August 1, 2025 | U113: August 12, 2025 | V113: August 29 & Oct. 24, 2025 | W113: FVA Trading | X113: Sept. 1 & Oct. 24, 2025 | Y113: GAS19 | Z113: November 13, 2025 | AA113: complete | AB113: for payment-Acctg. | AC113: 02-101101-2025-08-00541
A114: 2025 | B114: July | C114: JENNY S. ALINA | D114: College Nurse | E114: 165 | G114: 2025-251 | I114: Health Insurance Coverage: Accidental Death & Disablement,Unprovoked Murder & Assault Medical Expense or Reimbursement,Burial Benefits due to Accident/Natural Death,Daily Hospital Benefits due to Accident or illness,Dengue Cash Assistance,Ambulance Cash Assistance,Fire Cash Assistance,COVID-19 Cash Assistance for "Death Only",Combined Single Limit for Bodily Injury & Property Damage within premises of the school campus | J114: 900 | K114: pcs | L114: 200 | M114: =SUM(J114*L114) -> 180000 | N114: 130 | O114: =SUM(J114*N114) -> 117000 | P114: health insurance | Q114: Medical | R114: September 1, 2025 | S114: September 9, 2025 | T114: September 9, 2025 | U114: September 9, 2025 | W114: Bethel General Insurance & Surety Corporation | X114: Sept. 11, 2025 & Jan. 26, 2026 | Y114: SS02 | Z114: February 25, 2026 | AA114: Orig. PO sent to supplier | AB114: PO not return by supplier | AC114: 07-02-2025-09-0305 | AD114: 3 RFQ's + 2blanks | AE114: SOA#D01-25-001/9/11/2025SOA-D01-26-010
A115: 2025 | B115: July | C115: KLARISSE KEITH M. COBICO | D115: Administrative Assistant III | G115: 2025-252 | I115: BSC medal (diameter: 9cm, Gold Plated) | J115: 10 | K115: pcs | L115: 700 | M115: =SUM(J115*L115) -> 7000 | O115: =SUM(J115*N115) -> 0 | P115: for Presidential Medal of Merit Awards | Q115: OOP | Y115: GAS1 | AA115: CANCELLED | AB115: insufficient budget
A116: 2025 | B116: July | C116: WARLITO M. TOMAS JR. | D116: Project Leader | E116: 165 | G116: 2025-253 | I116: Plastic Pallet (120cmx100cm*15cm) | J116: 17 | K116: pcs | L116: 4900 | M116: =SUM(J116*L116) -> 83300 | N116: 4500 | O116: =SUM(J116*N116) -> 76500 | P116: for research project " Developing Feed Formulations for Bagu Ivatan Using Locally-Available Feeds and Forages" | Q116: Agri | R116: July 25,2025 | S116: July 31, 2025 | T116: August 1, 2025 | U116: August 12, 2025 | V116: September 3, 2025 | W116: FVA Trading | X116: September 3, 2025 | Y116: Acad7 | Z116: September 19, 2025 | AA116: complete | AB116: for payment-Acctg. | AC116: 07-02-2025-08-0258 | AD116: 5 RFQ's + 1 blank | AE116: 3000/9/5/2025 | AF116: no posting accrdng to maam Yen 200,000 above 7/23/25
A117: 2025 | B117: July | C117: WARLITO M. TOMAS JR. | D117: Project Leader | E117: 165 | G117: 2025-254 | I117: Cement | J117: 2 | K117: pcs | L117: 595 | M117: =SUM(J117*L117) -> 1190 | N117: 370 | O117: =SUM(J117*N117) -> 740 | P117: for research project " Developing Feed Formulations for Bagu Ivatan Using Locally-Available Feeds and Forages" | Q117: Agri | R117: July 25,2025 | S117: July 31, 2025 | T117: August 1, 2025 | U117: August 12, 2025 | V117: Sept. 10 &, 25,Dec. 3,& 5, 2025 | W117: GDP Trading | X117: Sept. 10,25,Oct.7,Dec. 3 & 5, 2025 | Y117: Acad7 | Z117: January 7, 2026 | AA117: complete | AB117: for payment-Acctg. | AC117: 07-02-2025-08-0257 | AD117: 5 RFQ's + 1 blank | AE117: 23896/12/05/2025 | AF117: no posting accrdng to maam Yen 200,000 above 7/23/25
A118: 2025 | B118: July | C118: WARLITO M. TOMAS JR. | D118: Project Leader | E118: 165 | G118: 2025-254 | I118: 2x4x14ft - lumber | J118: 20 | K118: pcs | L118: 1011.5 | M118: =SUM(J118*L118) -> 20230 | N118: 613 | O118: =SUM(J118*N118) -> 12260 | P118: for research project " Developing Feed Formulations for Bagu Ivatan Using Locally-Available Feeds and Forages" | Q118: Agri | R118: July 25,2025 | S118: July 31, 2025 | T118: August 1, 2025 | U118: August 12, 2025 | V118: Sept. 10 &, 25,Dec. 3,& 5, 2025 | W118: GDP Trading | X118: Sept. 10,25,Oct.7,Dec. 3 & 5, 2025 | Y118: Acad7 | Z118: January 7, 2026 | AA118: complete | AB118: for payment-Acctg. | AC118: 07-02-2025-08-0257
A119: 2025 | B119: July | C119: WARLITO M. TOMAS JR. | D119: Project Leader | E119: 165 | G119: 2025-254 | I119: 2x4x12ft - lumber | J119: 40 | K119: pcs | L119: 868 | M119: =SUM(J119*L119) -> 34720 | N119: 525 | O119: =SUM(J119*N119) -> 21000 | P119: for research project " Developing Feed Formulations for Bagu Ivatan Using Locally-Available Feeds and Forages" | Q119: Agri | R119: July 25,2025 | S119: July 31, 2025 | T119: August 1, 2025 | U119: August 12, 2025 | V119: Sept. 10 &, 25,Dec. 3,& 5, 2025 | W119: GDP Trading | X119: Sept. 10,25,Oct.7,Dec. 3 & 5, 2025 | Y119: Acad7 | Z119: January 7, 2026 | AA119: complete | AB119: for payment-Acctg. | AC119: 07-02-2025-08-0257
A120: 2025 | B120: July | C120: WARLITO M. TOMAS JR. | D120: Project Leader | E120: 165 | G120: 2025-254 | I120: 2x2x12ft - lumber | J120: 10 | K120: pcs | L120: 434 | M120: =SUM(J120*L120) -> 4340 | N120: 262 | O120: =SUM(J120*N120) -> 2620 | P120: for research project " Developing Feed Formulations for Bagu Ivatan Using Locally-Available Feeds and Forages" | Q120: Agri | R120: July 25,2025 | S120: July 31, 2025 | T120: August 1, 2025 | U120: August 12, 2025 | V120: Sept. 10 &, 25,Dec. 3,& 5, 2025 | W120: GDP Trading | X120: Sept. 10,25,Oct.7,Dec. 3 & 5, 2025 | Y120: Acad7 | Z120: January 7, 2026 | AA120: complete | AB120: for payment-Acctg. | AC120: 07-02-2025-08-0257
A121: 2025 | B121: July | C121: WARLITO M. TOMAS JR. | D121: Project Leader | E121: 165 | G121: 2025-254 | I121: 3" common nail | J121: 20 | K121: kg | L121: 148.75 | M121: =SUM(J121*L121) -> 2975 | N121: 85 | O121: =SUM(J121*N121) -> 1700 | P121: for research project " Developing Feed Formulations for Bagu Ivatan Using Locally-Available Feeds and Forages" | Q121: Agri | R121: July 25,2025 | S121: July 31, 2025 | T121: August 1, 2025 | U121: August 12, 2025 | V121: Sept. 10 &, 25,Dec. 3,& 5, 2025 | W121: GDP Trading | X121: Sept. 10,25,Oct.7,Dec. 3 & 5, 2025 | Y121: Acad7 | Z121: January 7, 2026 | AA121: complete | AB121: for payment-Acctg. | AC121: 07-02-2025-08-0257
A122: 2025 | B122: July | C122: WARLITO M. TOMAS JR. | D122: Project Leader | E122: 165 | G122: 2025-254 | I122: 4" common nail | J122: 15 | K122: kg | L122: 148.75 | M122: =SUM(J122*L122) -> 2231.25 | N122: 85 | O122: =SUM(J122*N122) -> 1275 | P122: for research project " Developing Feed Formulations for Bagu Ivatan Using Locally-Available Feeds and Forages" | Q122: Agri | R122: July 25,2025 | S122: July 31, 2025 | T122: August 1, 2025 | U122: August 12, 2025 | V122: Sept. 10 &, 25,Dec. 3,& 5, 2025 | W122: GDP Trading | X122: Sept. 10,25,Oct.7,Dec. 3 & 5, 2025 | Y122: Acad7 | Z122: January 7, 2026 | AA122: complete | AB122: for payment-Acctg. | AC122: 07-02-2025-08-0257
A123: 2025 | B123: July | C123: WARLITO M. TOMAS JR. | D123: Project Leader | E123: 165 | G123: 2025-254 | I123: 5" common nail | J123: 5 | K123: kg | L123: 148.75 | M123: =SUM(J123*L123) -> 743.75 | N123: 112 | O123: =SUM(J123*N123) -> 560 | P123: for research project " Developing Feed Formulations for Bagu Ivatan Using Locally-Available Feeds and Forages" | Q123: Agri | R123: July 25,2025 | S123: July 31, 2025 | T123: August 1, 2025 | U123: August 12, 2025 | V123: Sept. 10 &, 25,Dec. 3,& 5, 2025 | W123: GDP Trading | X123: Sept. 10,25,Oct.7,Dec. 3 & 5, 2025 | Y123: Acad7 | Z123: January 7, 2026 | AA123: complete | AB123: for payment-Acctg. | AC123: 07-02-2025-08-0257
A124: 2025 | B124: July | C124: WARLITO M. TOMAS JR. | D124: Project Leader | E124: 165 | G124: 2025-254 | I124: 12ft yero (5mm) | J124: 40 | K124: pcs | L124: 3307.5 | M124: =SUM(J124*L124) -> 132300 | N124: 1160 | O124: =SUM(J124*N124) -> 46400 | P124: for research project " Developing Feed Formulations for Bagu Ivatan Using Locally-Available Feeds and Forages" | Q124: Agri | R124: July 25,2025 | S124: July 31, 2025 | T124: August 1, 2025 | U124: August 12, 2025 | V124: Sept. 10 &, 25,Dec. 3,& 5, 2025 | W124: GDP Trading | X124: Sept. 10,25,Oct.7,Dec. 3 & 5, 2025 | Y124: Acad7 | Z124: January 7, 2026 | AA124: complete | AB124: for payment-Acctg. | AC124: 07-02-2025-08-0257
A125: 2025 | B125: July | C125: DOREEN C. CASTILLO | D125: Chairperson-PRAISE Committee | E125: 101 | G125: 2025-255 | I125: Plaque of Recognition: Made of premium quality clear acrylic material with beveled edges & polish finish; size: approximately 8.5 inches(H) x 5.5 inches(W); Design includes full color UV-printed or laser-engraved text & logo of Batanes State College; customized with recipient's name, award title & event details; mounted on a sturdy acrylic or wooden base; individually packed in a box or bubble wrap | J125: 17 | K125: pcs | L125: 1200 | M125: =SUM(J125*L125) -> 20400 | N125: 1170 | O125: =SUM(J125*N125) -> 19890 | P125: for BSC Gabi ng Parangal 2025 | Q125: DAFS | S125: August 6, 2025 | T125: August 7, 2025 | V125: August 7, 2025 | W125: Big Mark Advertising | X125: August 7, 2025 | Y125: GAS23 | Z125: October 6, 2025 | AA125: complete | AB125: for payment-Acctg. | AC125: 02-101101-2025-08-00572 | AD125: 3 RFQ's + 1 | AE125: 0258/8/7/2025
A126: 2025 | B126: July | C126: DOREEN C. CASTILLO | D126: Chairperson-PRAISE Committee | E126: 101 | G126: 2025-255 | I126: Plaque of Commendation: made of premium-quality clear acrylic material with beveled edges & polish finish; size; approximately 10 inches(H) x 5.5 (W);Design includes full-color UV-printed or laser-engraved text or logo of Batanes State College; customized with recipient's name,award title & event details; mounted on a sturdy acrylic or wooden base; packed in a box or bubble wrap | J126: 1 | K126: pc | L126: 1200 | M126: =SUM(J126*L126) -> 1200 | N126: 1687.5 | O126: =SUM(J126*N126) -> 1687.5 | P126: for BSC Gabi ng Parangal 2025 | Q126: DAFS | S126: August 6, 2025 | T126: August 7, 2025 | W126: Big Mark Advertising | Y126: GAS23
A127: 2025 | B127: July | C127: DOREEN C. CASTILLO | D127: Chairperson-PRAISE Committee | E127: 101 | G127: 2025-256 | I127: Corporate Jacket with embroidery (BSC Logo) in the front (left side), color; black, adult standard size with polo collar design, high quality | J127: 6 | K127: pcs | L127: 2500 | M127: =SUM(J127*L127) -> 15000 | N127: 2000 | O127: =SUM(J127*N127) -> 12000 | P127: merchandise for awardees during the BSC Gabi ng Parangal 2025 | Q127: DAFS | R127: July 29, 2025 | S127: August 5, 2025 | T127: August 5, 2025 | U127: August 6, 2025 | V127: August 27, 2025 | W127: Artech Printing Services | X127: August 27, 2025 | Y127: GAS23 | Z127: December 4, 2025 | AA127: complete | AB127: for payment-Acctg. | AC127: 02-101101-2025-08-00547 | AD127: 5 RFQ's | AE127: 0454/8/27/2025
A128: 2025 | B128: July | C128: DOREEN C. CASTILLO | D128: Chairperson-PRAISE Committee | E128: 101 | G128: 2025-256 | I128: Customized Ballpen with engraved name (personalized-name will be provided), premium ball paint, black ink, with packaging | J128: 1 | K128: pc | L128: 3000 | M128: =SUM(J128*L128) -> 3000 | N128: 650 | O128: =SUM(J128*N128) -> 650 | P128: merchandise for awardees during the BSC Gabi ng Parangal 2025 | Q128: DAFS | R128: July 29, 2025 | S128: August 5, 2025 | T128: August 5, 2025 | U128: August 6, 2025 | V128: August 27, 2025 | W128: Artech Printing Services | X128: August 27, 2025 | Y128: GAS23 | Z128: December 4, 2025 | AA128: complete | AB128: for payment-Acctg. | AC128: 02-101101-2025-08-00547
A129: 2025 | B129: July | C129: DOREEN C. CASTILLO | D129: Director for CBAO | G129: 2025-257 | I129: Food Tong 24.0cm | J129: 15 | K129: pcs | L129: 200 | M129: =SUM(J129*L129) -> 3000 | O129: =SUM(J129*N129) -> 0 | P129: for catering services | Q129: CBAO | Y129: 1006 | AA129: FAILED | AB129: quotation exceeded the budget | AD129: 4 RFQ's
...

Sheet PR
A7: PURCHASE REQUEST
D9: PR No. | E9: =DATA!G114 -> 2025-251 | F9: Date
A10: Department: | D10: SAI No.:
A11: Section: | B11: =DATA!Y114 -> SS02 | D11: OBR#
A12: Ref. No.: | B12: 2507-SS02-251
A14: Qty | B14: Unit of Issue | D14: Item Description | F14: Stock No. | G14: Estimated
G15: Unit Cost | H15: Total Cost
A16: =DATA!J114 -> 900 | B16: =DATA!K114 -> pcs | D16: =DATA!I114 -> Health Insurance Coverage: Accidental Death & Disablement,Unprovoked Murder & Assault Medical Expense or Reimbursement,Burial Benefits due to Accident/Natural Death,Daily Hospital Benefits due to Accident or illness,Dengue Cash Assistance,Ambulance Cash Assistance,Fire Cash Assistance,COVID-19 Cash Assistance for "Death Only",Combined Single Limit for Bodily Injury & Property Damage within premises of the school campus | G16: =DATA!L114 -> 200 | H16: =SUM(A16*G16) -> 180000
H17: =SUM(A17*G17) -> 0
H18: =SUM(A18*G18) -> 0
H19: =SUM(A19*G19) -> 0
H20: =SUM(A20*G20) -> 0
H21: =SUM(A21*G21) -> 0
H22: =SUM(A22*G22) -> 0
H23: =SUM(A23*G23) -> 0
H24: =SUM(A24*G24) -> 0
H25: =SUM(A25*G25) -> 0
H26: =SUM(A26*G26) -> 0
H27: =SUM(A27*G27) -> 0
H28: =SUM(A28*G28) -> 0
... H38: =SUM(A38*G38) -> 0
A39: =DATA!J50 -> 4 | B39: =DATA!K50 -> bottle | D39: =DATA!I179 -> Rotary Hammer 850 W 3-Mode Function, with Drill Bit & Chisel included, 220V-240V | G39: =DATA!L50 -> 650 | H39: =SUM(A39*G39) -> 2600
A40: =DATA!J51 -> 4 | B40: =DATA!K51 -> bottle | D40: =DATA!I180 -> Rotary Hammer 28mm, 1300W with Drill Bit & Chisel included, 220V-240V | G40: =DATA!L51 -> 650 | H40: =SUM(A40*G40) -> 2600
A41: =DATA!J52 -> 2 | B41: =DATA!K52 -> roll | D41: =DATA!I181 -> 45-135˚ Multi Angel Miter Shear Cutter, Adjustable angle cutter for cutting plastic, PVC & Molding Trim | G41: =DATA!L52 -> 150 | H41: =SUM(A41*G41) -> 300
A42: =DATA!J53 -> 3 | B42: =DATA!K53 -> roll | D42: =DATA!I182 -> U Type Edge trimming scissor 45 degrees 90 degrees Trunking Pliers (Large Edge Clamp) | G42: =DATA!L53 -> 100 | H42: =SUM(A42*G42) -> 300
A43: =DATA!J54 -> 140 | B43: =DATA!K100 -> copy | D43: =DATA!I183 -> U Type Edge trimming scissor 45 degrees 90 degrees Trunking Pliers (Small size Edge Clamp) | G43: =DATA!L183 -> 700 | H43: =SUM(A43*G43) -> 98000
A44: =DATA!J55 -> 10.5 | B44: =DATA!K101 -> copy | D44: =DATA!I184 -> 9000KPA Portable Pressure Washer set: with Pressure Gauge & Adjustable Pressure, PW Gun, High Pressure Hose, Water Inlet connector & filter, Foam spray bottle | G44: =DATA!L184 -> 4000 | H44: =SUM(A44*G44) -> 42000
A45: =DATA!J56 -> 9.5 | B45: =DATA!K102 -> copy | D45: =DATA!I185 -> Electric Air Blower 650W Hand Dust Cleaner Blow Machine, 650W - AB6038, Dust Bag Included, Max Blowing Rate 0-4.0m/min., input power 650W | G45: =DATA!L185 -> 3000 | H45: =SUM(A45*G45) -> 28500
A46: =DATA!J57 -> 1 | D46: =DATA!I186 -> Aircon Coli Cleaner | G46: =DATA!L186 -> 1500 | H46: =SUM(A46*G46) -> 1500
A47: =DATA!J58 -> 1 | D47: =DATA!I187 -> Aircon Fin Straightener/Fin Comb, Condenser Evaporator Fin | G47: =DATA!L187 -> 500 | H47: =SUM(A47*G47) -> 500
A48: =DATA!J59 -> 1 | D48: =DATA!I188 -> 2 Liter Hand Pressure Pump Sprayer (LTGT2000HSX) | G48: =DATA!L188 -> 1000 | H48: =SUM(A48*G48) -> 1000
A49: =DATA!J60 -> 1 | D49: =DATA!I189 -> 5L Shoulder Hand-Operated Sprayer (LTGT5000PSX) | G49: =DATA!L189 -> 2000 | H49: =SUM(A49*G49) -> 2000
A50: =DATA!J61 -> 10 | D50: =DATA!I190 -> Wet & Dry Vaccuum Cleaner, 3 in 1 Carpet Extractor Cleaner, Power: 1034 W, Voltage: 230 v, 40 Liter | G50: =DATA!L190 -> 23000 | H50: =SUM(A50*G50) -> 230000
A51: =DATA!J62 -> 2 | D51: =DATA!I191 -> BSC medal (diameter: 9cm, Gold Plated) | G51: =DATA!L191 -> 1200 | H51: =SUM(A51*G51) -> 2400
A52: =DATA!J63 -> 2 | D52: =DATA!I192 -> Molder | G52: =DATA!L192 -> 9850 | H52: =SUM(A52*G52) -> 19700
A53: =DATA!J64 -> 3 | D53: =DATA!I193 -> Plaque for Loyalty Award - made of premium quality MDF wood, size: 30cm-35cm; inclusive of design and lay-out logo of Batanes State College,customized with recipient's name, award title and events details; mounted on a sturdy wooden base; | G53: =DATA!L193 -> 950 | H53: =SUM(A53*G53) -> 2850
A54: =DATA!J65 -> 3 | D54: =DATA!I194 -> Shovel | G54: =DATA!L194 -> 500 | H54: =SUM(A54*G54) -> 1500
A55: =DATA!J66 -> 2 | D55: =DATA!I195 -> Construction Reflectorized Vest (yellow green) | G55: =DATA!L195 -> 180 | H55: =SUM(A55*G55) -> 360
A56: =DATA!J67 -> 1 | D56: =DATA!I196 -> Gold Spray Paint | G56: =DATA!L196 -> 160 | H56: =SUM(A56*G56) -> 160
A57: =DATA!J68 -> 2 | D57: =DATA!I197 -> 2 x 3 Palochina | G57: =DATA!L197 -> 400 | H57: =SUM(A57*G57) -> 800
... A107: =DATA!J118 -> 20 | D107: =DATA!I247 -> Mangoes | G107: =DATA!L247 -> 300 | H107: =SUM(A107*G107) -> 6000
A108: =DATA!J119 -> 40 | D108: =DATA!I248 -> Apples | G108: =DATA!L248 -> 50
A109: =DATA!J120 -> 10 | D109: =DATA!I249 -> Oranges | G109: =DATA!L249 -> 50
H110: =SUM(H16:H38) -> 180000
A111: Purpose: | B111: =DATA!P114 -> health insurance
F112: Approved By:
A114: Signature:
A115: Printed Name: | B115: =DATA!C114 -> JENNY S. ALINA | F115: DJOVI REGALA DURANTE,DPA
A116: Designation: | B116: =DATA!D114 -> College Nurse | F116: SUC President I
A117: Date:

Sheet Direct Acq.-Res
A7: BAC Resolution Recommending use of New Mode of Procurement under Direct Acquisition
B8: BAC Resolution No. | D8: =PR!B12 -> 2507-SS02-251
A10: WHEREAS, Section 26 Rule IV of the Implementing Rules and Regulations of RA 12009 allows the use of New Modes of Procurement consistent with the Fit-for-Purpose approach;
A11: WHEREAS, Section 32 allows Direct Acquisition as a mode of procurement of CSE not available in the PS-DBM, Non-CSE, and services with ABC not exceeding Two Hundred Thousand Pesos (₱200,000.00);
A12: WHEREAS, the Procuring Entity, without need to conduct a canvass or request for quotations, may procure directly from any known and reputable sources;
A13: WHEREAS, Goods covered under this mode may be procured from stores, such as but not limited to, department store,depot, fast food chain, grocery and supermarket, wholesale and retail store, convenience store, clothing and apparel store,bookstore, drugstore and pharmacy, automotive parts and accessories store, construction and hardware store, and online stores.
A14: WHEREAS, The HoPE may authorize the End-User or Implementing Unit to directly purchase from any known and reputable source with legal, technical, and financial capacity, based on any of the following: a)The Suppliers are registered with the PhilGEPS as verified from the PhilGEPS website; b) The goods are available in electronic commerce platforms for delivery or pick up at such date and time identified by the Procuring Entity; and c) The goods are readily available off-the-shelf and can be picked up or delivered immediately;
A15: WHEREAS, Purchase Request No. | D15: =PR!E9 -> 2025-251 | E15: involves the procurement of
A16: Sustainable Farming: Nurturing the Earth for Future Generations,Kushwaha, 2024, 9781774699515, The Genetic Manipulation in Plants, Singh, 2023, 9789394137646,,etc,.-- the list of book titles have been carefully selected by the program chairpersons to enhance the learning resources
A17: with the approved budget of | D17: =PR!H110 -> 180000
A18: WHEREAS, Procuring Entities shall procure only from sources that issue invoices compliant with the rules of the BIR or other documents evidencing delivery and payment acceptable to the COA;
A20: NOW THEREFORE, we, the members of the Bids and Awards Committee hereby RESOLVE as it is hereby RESOLVED to recommend to the College President to adopt Direct Acquisition as Mode of Procurement for the said transaction;
A22: RESOLVED FINALLY, at the Batanes State College, this
A23: Recommending Approval:
A26: RHOUPHELINE AYA A. CADIZ | C26: FORTUNATO PHILIP A. CABUGAO | F26: EMILYN D. ALUETA
A27: BAC Member | C27: BAC Member | F27: BAC Member
A30: =PR!B115 -> JENNY S. ALINA | C30: PHILIP ULYSSES T. CASTILLO | F30: DOREEN C. CASTILLO
A31: End-User/Provisional Member | C31: BAC Vice Chairperson | E31: BAC Chairperson
A32: BRYAN H. CIELO
A33: DELMA G. MALUPA-ABAD
A34: EDWIN F.MACABALLUG, Ph.D.
A35: LIEZL P. DELA CRUZ
A36: RODERICK Y. ABAD
A37: VILMA D. BACCAY
A38: ESTEBAN C. BADAJOS
A39: LEOBERT L. BANZALI
A40: MIAH DAPHNIE B. BUENAFE
A41: GLORIA N. CABIZON
A42: FORTUNATO PHILIP A. CABUGAO
A43: RICARDO Q. CABUGAO, JR.
... A83: DARYL ALVA C. BATIN

Sheet ResoSVP (3)
A7: BAC Resolution Recommending Alternative Mode of Procurement under Small Value Procurement
B8: BAC Resolution No. | D8: =PR!B12 -> 2507-SS02-251
A10: WHEREAS, Section 48 Rule XVI of the Revised Implementing Rules and Regulations of RA 9184 allows Alternative Mode of Procurement subject to prior approval of the HOPE thru Annual Procurement Plan (APP) and only to promote economy and efficiency;
A11: WHEREAS, Section 53.9 allows Small Value Procurement provided that the procurement does not fall under shopping in Section 52 of this IRR and the amount involved does not exceed the thresholds prescribed in Annex "H" of this IRR;
A12: WHEREAS, Appendix 18, Section 3.e on the Guidelines for Shopping and Small Value Procurement provides an Abstract of Quotations shall be prepared setting forth the names of those who responded to the RFQ's right after the deadline for submission except for shopping under Section 52.1(b), where at least three (3) price quotations (RFQ) must be obtained;
A13: WHEREAS, Annex "H" of the Consolidated Guidelines for the Alternative Methods of Procurement prescribed under Section V, Paragraph D.8.b.ii that the BAC shall prepare and send the RFQs/RFPs to at least three (3) suppliers, contractors or consultants of known qualifications where receipt of at least one (1) quotations is sufficient to proceed with the evaluation thererof;
A14: WHEREAS, Purchase Request No. | D14: =PR!E9 -> 2025-251 | E14: involves the procurement of
A15: Refill Ink (BT5000-C,M,Y),BTD60BK-black,Air Freshener,Trash Bag (small),Dishwashing Paste --to be use for printing of Certification of Registration during enrollment for 1st Sem AY 2025-2026,printing of documents & other office purposes
A16: with the approved budget of | D16: =PR!H110 -> 180000
A17: WHEREAS, the default mode of evaluation shall be on a lot basis which means that the determination of the single/lowest calculated and responsive bid (S/LCRB) is the total amount of offered unit price multiply by the required quantity;
A19: NOW THEREFORE, we, the members of the Bids and Awards Committee hereby RESOLVE as it is hereby RESOLVED to recommend to the College President to adopt Alternative Mode of Procurement under Small Value Procurement for the said transaction;
A21: RESOLVED FINALLY, at the Batanes State College, this
A22: Recommending Approval:
A25: RHOUPHELINE AYA A. CADIZ | C25: FORTUNATO PHILIP A. CABUGAO | E25: EMILYN D. ALUETA
A26: BAC Member | C26: BAC Member | E26: BAC Member
A29: =PR!B115 -> JENNY S. ALINA | C29: PHILIP ULYSSES T. CASTILLO | E29: DOREEN C. CASTILLO
A30: End-User/Provisional Member | C30: BAC Vice Chairperson | E30: BAC Chairperson
A31: BRYAN H. CIELO
A32: DELMA G. MALUPA-ABAD
A33: EDWIN F.MACABALLUG, Ph.D.
A34: LIEZL P. DELA CRUZ
A35: RODERICK Y. ABAD
A36: VILMA D. BACCAY
A37: ESTEBAN C. BADAJOS
A38: LEOBERT L. BANZALI
A39: MIAH DAPHNIE B. BUENAFE
A40: GLORIA N. CABIZON
A41: FORTUNATO PHILIP A. CABUGAO
A42: RICARDO Q. CABUGAO, JR.
... A82: DARYL ALVA C. BATIN

Sheet Direct Acq.-App
A4: Approval of BAC Resolution Recommending Mode of Procurement under Direct Acquisition
B6: BAC Resolution No. | D6: =PR!B12 -> 2507-SS02-251
A8: WHEREAS, Section 48 Rule XVI of the Revised Implementing Rules and Regulations of RA 9184 allows Alternative Mode of Procurement subject to prior approval of the HOPE thru Annual Procurement Plan (APP) and only to promote economy and efficiency;
A9: WHEREAS, Section 53.9 allows Small Value Procurement provided that the procurement does not fall under shopping in Section 52 of this IRR and the amount involved does not exceed the thresholds prescribed in Annex "H" of this IRR;
A10: WHEREAS, Appendix 18, Section 3.e on the Guidelines for Shopping and Small Value Procurement provides an Abstract of Quotations shall be prepared setting forth the names of those who responded to the RFQ's right after the deadline for submission except for shopping under Section 52.1(b), where at least three (3) price quotations (RFQ) must be obtained;
A11: WHEREAS, Annex "H" of the Consolidated Guidelines for the Alternative Methods of Procurement prescribed under Section V, Paragraph D.8.b.ii that the BAC shall prepare and send the RFQs/RFPs to at least three (3) suppliers, contractors or consultants of known qualifications where receipt of at least one (1) quotations is sufficient to proceed with the evaluation thererof;
A12: WHEREAS, Purchase Request No. | D12: =PR!E9 -> 2025-251 | E12: involves the procurement of
A13: Sustainable Farming: Nurturing the Earth for Future Generations,Kushwaha, 2024, 9781774699515, The Genetic Manipulation in Plants, Singh, 2023, 9789394137646,,etc,.-- the list of book titles have been carefully selected by the program chairpersons to enhance the learning resources | H13: Items:
A14: with the approved budget of | D14: =PR!H110 -> 180000
A15: WHEREAS, the default mode of evaluation shall be on a lot basis which means that the determination of the single/lowest calculated and responsive bid (S/LCRB) is the total amount of offered unit price multiply by the required quantity;
A16: NOW THEREFORE, I,DR.DJOVI R. DURANTE, Head of the Procuring Entity (HOPE) by virtue of the authority vested in me by the Board of Trustees of this Institution and after taking into consideration the merits and legal bases of the recommendation of the members of the Bids and Awards Committee (BAC) do hereby APPROVE the foregoing recommendation and adoption of Alternative Mode of Procurement under Small Value Procurement;
A18: APPROVED FINALLY, at the Batanes State College, this | F18: ___________________
D22: DJOVI REGALA DURANTE,DPA
D23: SUC President I
A30: BRYAN H. CIELO
A85: EMILYN D. ALUETA
A86: EMILYN D. ALUETA

Sheet AResoSVP
A5: Approval of BAC Resolution Recommending Alternative Mode of Procurement under Small Value Procurement
B7: BAC Resolution No. | D7: =PR!B12 -> 2507-SS02-251
A9: WHEREAS, Section 48 Rule XVI of the Revised Implementing Rules and Regulations of RA 9184 allows Alternative Mode of Procurement subject to prior approval of the HOPE thru Annual Procurement Plan (APP) and only to promote economy and efficiency;
A10: WHEREAS, Section 53.9 allows Small Value Procurement provided that the procurement does not fall under shopping in Section 52 of this IRR and the amount involved does not exceed the thresholds prescribed in Annex "H" of this IRR;
A11: WHEREAS, Appendix 18, Section 3.e on the Guidelines for Shopping and Small Value Procurement provides an Abstract of Quotations shall be prepared setting f+A1:S11orth the names of those who responded to the RFQ's right after the deadline for submission except for shopping under Section 52.1(b), where at least three (3) price quotations (RFQ) must be obtained;
A12: WHEREAS, Annex "H" of the Consolidated Guidelines for the Alternative Methods of Procurement prescribed under Section V, Paragraph D.8.b.ii that the BAC shall prepare and send the RFQs/RFPs to at least three (3) suppliers, contractors or consultants of known qualifications where receipt of at least one (1) quotations is sufficient to proceed with the evaluation thererof;
A13: WHEREAS, Purchase Request No. | D13: =PR!E9 -> 2025-251 | E13: involves the procurement of
A14: Refill Ink (BT5000-C,M,Y),BTD60BK-black,Air Freshener,Trash Bag (small),Dishwashing Paste --to be use for printing of Certification of Registration during enrollment for 1st Sem AY 2025-2026,printing of documents & other office purposes | H14: Items:
A15: with the approved budget of | D15: =PR!H110 -> 180000
A16: WHEREAS, the default mode of evaluation shall be on a lot basis which means that the determination of the single/lowest calculated and responsive bid (S/LCRB) is the total amount of offered unit price multiply by the required quantity;
A17: NOW THEREFORE, I,DR.DJOVI R. DURANTE, Head of the Procuring Entity (HOPE) by virtue of the authority vested in me by the Board of Trustees of this Institution and after taking into consideration the merits and legal bases of the recommendation of the members of the Bids and Awards Committee (BAC) do hereby APPROVE the foregoing recommendation and adoption of Alternative Mode of Procurement under Small Value Procurement;
A19: APPROVED FINALLY, at the Batanes State College, this | F19: ___________________
C23: DJOVI REGALA DURANTE,DPA
C24: SUC President I
A31: BRYAN H. CIELO
A86: EMILYN D. ALUETA
A87: EMILYN D. ALUETA

Sheet RFQ_ (2)
E6: Date: | F6: =NOW() -> 46148.741
A7: REQUEST FOR PRICE QUOTATION
A8: CMVILL Trading
A9: Please give us your best and final price offer for the item/s listed below, have this signed and submit this by you or by your duly authorized representative WITHIN SEVEN (7) CALENDAR DAYS upon receipt to Procurement Section, Batanes State College.
A11: NOTE: | B11: 1. THE DEFAULT MODE OF PRICE EVALUATION SHALL BE ON A LOT BASIS, OTHERWISE PER ITEMS EVALUATION SHALL BE USED IF THERE WILL BE LACKING ITEMS IN ALL RFQ's AND SUBJECT TO END-USER APPROVAL., (Clause 15.2, Section I, Instruction to Bidders of the Philippine Bidding Documents for goods and infrastructure projects)
B12: 2. DELIVERY PERIOD: Thirty (30) calendar days.
B13: 3. Submission of price quotation shall be in sealed envelope.
B14: 4. THE APPROVED BUDGET FOR THIS PROCUREMENT IS
B15: =PR!H110 -> 180000 | D15: (GPPB Resolution No. 09-2009)
B16: 5. PURSUANT TO ANNEX "H", APPENDIX A, SECTION II, SUBMISSION OF APPLICABLE DOCUMENTS (e.g.MAYORS/BUSINESS PERMIT, PROFESSIONAL LICENSE/CURRICULUM VITAE (CONSULTING SEERVICES),PHILGEPS CERT. NO., PCAB LICENSE (INFRA), INCOME/BUSINESS TAX RETURN,OMNIBUS SWORN STATEMENT SHALL BE REQUIRED BEFORE THE ISSUANCE OF NOA OR PRIOR TO PAYMENT.
B17: 6. In case the item is not availble, please write "None".
A18: Item # | B18: Qty. | C18: Unit | D18: PARTICULAR | E18: Unit Price | F18: Total
A19: 001 | B19: =PR!A16 -> 900 | C19: =PR!B16 -> pcs | D19: =PR!D16 -> Health Insurance Coverage: Accidental Death & Disablement,Unprovoked Murder & Assault Medical Expense or Reimbursement,Burial Benefits due to Accident/Natural Death,Daily Hospital Benefits due to Accident or illness,Dengue Cash Assistance,Ambulance Cash Assistance,Fire Cash Assistance,COVID-19 Cash Assistance for "Death Only",Combined Single Limit for Bodily Injury & Property Damage within premises of the school campus
A20: 002 | B20: =PR!A17 -> 0 | C20: =PR!B17 -> 0 | D20: =PR!D17 -> 0
A21: 003 | B21: =PR!A18 -> 0 | C21: =PR!B18 -> 0 | D21: =PR!D18 -> 0
A22: 004 | B22: =PR!A19 -> 0 | C22: =PR!B19 -> 0 | D22: =PR!D19 -> 0
A23: 005 | B23: =PR!A20 -> 0 | C23: =PR!B20 -> 0 | D23: =PR!D20 -> 0
A24: 006 | B24: =PR!A21 -> 0 | C24: =PR!B21 -> 0 | D24: =PR!D21 -> 0
A25: 007 | B25: =PR!A22 -> 0 | C25: =PR!B22 -> 0 | D25: =PR!D22 -> 0
A26: 008
A27: 009
A28: 010 | B28: =PR!A25 -> 0
A29: 011 | B29: =PR!A26 -> 0
A30: 012 | B30: =PR!A27 -> 0
A31: 013 | B31: =PR!A28 -> 0
A32: 014 | B32: =PR!A29 -> 0
A33: 015 | B33: =PR!A30 -> 0
A34: 016 | B34: =PR!A31 -> 0
A35: 017 | B35: =PR!A32 -> 0
A36: 018 | B36: =PR!A33 -> 0
A37: 019 | B37: =PR!A34 -> 0
A38: 020 | B38: =PR!A35 -> 0
A39: 021 | B39: =PR!A36 -> 0
... A41: 023 | B41: =PR!A38 -> 0
A42: 024 | B42: =PR!A39 -> 4 | C42: =[1]PR!B39 -> copy | D42: =PR!D39 -> Rotary Hammer 850 W 3-Mode Function, with Drill Bit & Chisel included, 220V-240V
A43: 025 | B43: =PR!A40 -> 4 | C43: =[1]PR!B40 -> copy | D43: =PR!D40 -> Rotary Hammer 28mm, 1300W with Drill Bit & Chisel included, 220V-240V
A44: 026 | B44: =PR!A41 -> 2 | C44: =[1]PR!B41 -> copy | D44: =PR!D41 -> 45-135˚ Multi Angel Miter Shear Cutter, Adjustable angle cutter for cutting plastic, PVC & Molding Trim
A45: 027 | B45: =PR!A42 -> 3 | C45: =[1]PR!B43 -> sets | D45: =PR!D42 -> U Type Edge trimming scissor 45 degrees 90 degrees Trunking Pliers (Large Edge Clamp)
A46: 028 | B46: =PR!A43 -> 140 | C46: =[1]PR!B44 -> pcs | D46: =PR!D43 -> U Type Edge trimming scissor 45 degrees 90 degrees Trunking Pliers (Small size Edge Clamp)
A47: 029 | B47: =PR!A44 -> 10.5 | C47: =[1]PR!B45 -> pcs | D47: =PR!D44 -> 9000KPA Portable Pressure Washer set: with Pressure Gauge & Adjustable Pressure, PW Gun, High Pressure Hose, Water Inlet connector & filter, Foam spray bottle
A48: 030 | B48: =PR!A45 -> 9.5 | C48: =[1]PR!B46 -> pcs | D48: =PR!D45 -> Electric Air Blower 650W Hand Dust Cleaner Blow Machine, 650W - AB6038, Dust Bag Included, Max Blowing Rate 0-4.0m/min., input power 650W
A49: 031 | B49: =PR!A46 -> 1 | C49: =[1]PR!B47 -> pc | D49: =PR!D46 -> Aircon Coli Cleaner
A50: 033 | B50: =PR!A47 -> 1 | C50: =[1]PR!B48 -> box | D50: =PR!D47 -> Aircon Fin Straightener/Fin Comb, Condenser Evaporator Fin
A51: 034 | B51: =PR!A48 -> 1 | C51: =[1]PR!B49 -> kg | D51: =PR!D48 -> 2 Liter Hand Pressure Pump Sprayer (LTGT2000HSX)
A52: 035 | B52: =PR!A49 -> 1 | C52: =[1]PR!B50 -> kg | D52: =PR!D49 -> 5L Shoulder Hand-Operated Sprayer (LTGT5000PSX)
A53: 036 | B53: =PR!A50 -> 10 | C53: =[1]PR!B51 -> kg | D53: =PR!D50 -> Wet & Dry Vaccuum Cleaner, 3 in 1 Carpet Extractor Cleaner, Power: 1034 W, Voltage: 230 v, 40 Liter
A54: 037 | B54: =PR!A51 -> 2 | C54: =[1]PR!B52 -> pcs | D54: =PR!D51 -> BSC medal (diameter: 9cm, Gold Plated)
A55: 038 | B55: =PR!A52 -> 2 | C55: =[1]PR!B53 -> pcs | D55: =PR!D52 -> Molder
A56: 039 | B56: =PR!A53 -> 3 | C56: =[1]PR!B54 -> pcs | D56: =PR!D53 -> Plaque for Loyalty Award - made of premium quality MDF wood, size: 30cm-35cm; inclusive of design and lay-out logo of Batanes State College,customized with recipient's name, award title and events details; mounted on a sturdy wooden base;
... A101: 084 | B101: =PR!A98 -> 1 | C101: =[1]PR!B99 -> pcs | D101: =PR!D98 -> Coffee Spoon 17cm x 3.7cm 12's/10's
E102: Total
A104: After having carefully read and accepted your conditions, I/We have place my /our best and final price offer on the item/s listed above.
E105: Very truly yours,
A107: Printed Name/Signature
E108: DOREEN C. CASTILLO
A109: Ref.# | B109: =PR!B12 -> 2507-SS02-251 | E109: BAC Chairperson

Sheet RFQ_
E5: Date: | F5: =NOW() -> 46148.741
A6: REQUEST FOR PRICE QUOTATION
A7: One-Touch Technology Trading | B7: MOJR Construction Trading & General Services, Ltd, Co. | C7: MOJR Construction Trading & General Services, Ltd, Co. | D7: MOJR Construction Trading & General Services, Ltd, Co.
A8: Please give us your best and final price offer for the item/s listed below, have this signed and submit this by you or by your duly authorized representative WITHIN SEVEN (7) CALENDAR DAYS upon receipt to Procurement Section, Batanes State College.
A10: NOTE: | B10: 1. THE DEFAULT MODE OF PRICE EVALUATION SHALL BE ON A LOT BASIS, OTHERWISE PER ITEMS EVALUATION SHALL BE USED IF THERE WILL BE LACKING ITEMS IN ALL RFQ's AND SUBJECT TO END-USER APPROVAL., (Clause 15.2, Section I, Instruction to Bidders of the Philippine Bidding Documents for goods and infrastructure projects)
B11: 2. DELIVERY PERIOD: Thirty (30) calendar days.
B12: 3. Submission of price quotation shall be in sealed envelope.
B13: 4. THE APPROVED BUDGET FOR THIS PROCUREMENT IS
B14: =PR!H110 -> 180000 | D14: (GPPB Resolution No. 09-2009)
B15: 5. PURSUANT TO ANNEX "H", APPENDIX A, SECTION II, SUBMISSION OF APPLICABLE DOCUMENTS (e.g.MAYORS/BUSINESS PERMIT, PROFESSIONAL LICENSE/CURRICULUM VITAE (CONSULTING SEERVICES),PHILGEPS CERT. NO., PCAB LICENSE (INFRA), INCOME/BUSINESS TAX RETURN,OMNIBUS SWORN STATEMENT SHALL BE REQUIRED BEFORE THE ISSUANCE OF NOA OR PRIOR TO PAYMENT.
B16: 6. In case the item is not availble, please write "None".
A17: Item # | B17: Qty. | C17: Unit | D17: PARTICULAR | E17: Unit Price | F17: Total
A18: 001 | B18: =PR!A16 -> 900 | C18: =PR!B16 -> pcs | D18: =PR!D16 -> Health Insurance Coverage: Accidental Death & Disablement,Unprovoked Murder & Assault Medical Expense or Reimbursement,Burial Benefits due to Accident/Natural Death,Daily Hospital Benefits due to Accident or illness,Dengue Cash Assistance,Ambulance Cash Assistance,Fire Cash Assistance,COVID-19 Cash Assistance for "Death Only",Combined Single Limit for Bodily Injury & Property Damage within premises of the school campus
A19: 002
A20: 003
A21: 004
A22: 005
A23: 006
A24: 007
A25: 008
A26: 009
A27: 010
A28: 011
A29: 012
A30: 013
... A32: 015
A33: 019 | B33: =PR!A33 -> 0 | C33: =PR!B33 -> 0 | D33: =PR!D34 -> 0
A34: 019 | B34: =PR!A34 -> 0 | C34: =PR!B34 -> 0 | D34: =PR!D34 -> 0
A35: 020 | B35: =PR!A35 -> 0 | C35: =PR!B35 -> 0 | D35: =PR!D35 -> 0
A36: 021 | B36: =PR!A36 -> 0 | C36: =PR!B36 -> 0 | D36: =PR!D36 -> 0
A37: 022 | B37: =PR!A37 -> 0 | C37: =PR!B37 -> 0 | D37: =PR!D37 -> 0
A38: 023 | B38: =PR!A38 -> 0 | C38: =PR!B38 -> 0 | D38: =PR!D38 -> 0
A39: 024 | B39: =PR!A39 -> 4 | C39: =PR!B39 -> bottle | D39: =PR!D39 -> Rotary Hammer 850 W 3-Mode Function, with Drill Bit & Chisel included, 220V-240V
A40: 025 | B40: =PR!A40 -> 4 | C40: =PR!B40 -> bottle | D40: =PR!D40 -> Rotary Hammer 28mm, 1300W with Drill Bit & Chisel included, 220V-240V
A41: 026 | B41: =PR!A41 -> 2 | C41: =PR!B41 -> roll | D41: =PR!D41 -> 45-135˚ Multi Angel Miter Shear Cutter, Adjustable angle cutter for cutting plastic, PVC & Molding Trim
A42: 027 | B42: =PR!A42 -> 3 | C42: =PR!B42 -> roll | D42: =PR!D42 -> U Type Edge trimming scissor 45 degrees 90 degrees Trunking Pliers (Large Edge Clamp)
A43: 028 | B43: =PR!A43 -> 140 | C43: =PR!B43 -> copy | D43: =PR!D43 -> U Type Edge trimming scissor 45 degrees 90 degrees Trunking Pliers (Small size Edge Clamp)
A44: 029 | B44: =PR!A44 -> 10.5 | C44: =PR!B44 -> copy | D44: =PR!D44 -> 9000KPA Portable Pressure Washer set: with Pressure Gauge & Adjustable Pressure, PW Gun, High Pressure Hose, Water Inlet connector & filter, Foam spray bottle
A45: 030 | B45: =PR!A45 -> 9.5 | C45: =PR!B45 -> copy | D45: =PR!D45 -> Electric Air Blower 650W Hand Dust Cleaner Blow Machine, 650W - AB6038, Dust Bag Included, Max Blowing Rate 0-4.0m/min., input power 650W
... A85: 070 | B85: =PR!A85 -> 1 | C85: =PR!B85 -> 0 | D85: =PR!D85 -> 9 Watts LED Bulb, Warm White, E27
B86: =PR!A86 -> 1 | C86: =PR!B86 -> 0 | D86: =PR!D86 -> Vinyl Electrical Tape 0.16mmx19mmx16m (black)
B87: =PR!A87 -> 1 | C87: =PR!B87 -> 0 | D87: =PR!D87 -> A4, Certificate Frame with stand
B88: =PR!A88 -> 1 | C88: =PR!B88 -> 0 | D88: =PR!D88 -> Paper Vellum Board (220 gsm)
B89: =PR!A89 -> 1 | C89: =PR!B89 -> 0 | D89: =PR!D89 -> Photo Paper A4
B90: =PR!A90 -> 1 | C90: =PR!B90 -> 0 | D90: =PR!D90 -> Ink 774 (Black 108ml)
B91: =PR!A91 -> 1 | C91: =PR!B91 -> 0 | D91: =PR!D91 -> Ink 664 (Yellow,Cyan,Magenta-48.8ml)
B92: =PR!A92 -> 1 | C92: =PR!B92 -> 0 | D92: =PR!D92 -> Food Tong 24.0cm
B93: =PR!A93 -> 2 | C93: =PR!B93 -> 0 | D93: =PR!D93 -> Serving Spoon 9" stainless steel
B94: =PR!A94 -> 1 | C94: =PR!B94 -> 0 | D94: =PR!D94 -> Serving Fork
B95: =PR!A95 -> 1 | C95: =PR!B95 -> 0 | D95: =PR!D95 -> Rice Cooker 45cups 7.8L capacity
B96: =PR!A96 -> 1 | C96: =PR!B96 -> 0 | D96: =PR!D96 -> Heavy Duty Coffee Perculator 100cups 15Liters
B97: =PR!A97 -> 2 | C97: =PR!B97 -> 0 | D97: =PR!D97 -> Tissue Holder
... B99: =PR!A99 -> 2 | C99: =PR!B99 -> 0 | D99: =PR!D99 -> M-GAS Refill (Large)
E100: Total
A102: After having carefully read and accepted your conditions, I/We have place my /our best and final price offer on the item/s listed above.
A103: Printed Name/Signature | E103: Very truly yours,
E106: DOREEN C. CASTILLO
A107: Ref.# | B107: =PR!B12 -> 2507-SS02-251 | E107: BAC Chairperson

Sheet AckReceipt
A1: Acknowledgement for Request for Quotation
A2: RIS# | B2: =PR!B12 -> 2507-SS02-251
A3: No. | B3: Supplier | F3: Received by: | G3: Date & Time:
B4: JPM Gen. Mdse. & Hardware
B5: Thine-line Trading
B6: J-Tech Trading & Services
B7: MDAC Trading & Compuserve
B8: FVA Gen Mdse & Construction Supply
B10: GDP Trading
B11: EA Amboy Gen Mdse
B12: L & R's Hontomin Gen Mdse
B13: Davocol's Gen. Mdse.
B14: RCJ Hardware & Gen Mdse
B15: Fitero's Gen Mdse & Electronic Supply
B16: Lar & San's Store
... B18: Wilmerson Gen Mdse
B19: FMG Trading & Construction Supply | C19: q
B20: MG Hubalde Gen Mdse
B21: Basco Cable TV Services, Inc.
B22: Berlen's Store
B23: Melad's Gen. Mdse
B24: R. A. Electronics
B25: RJ General Merchandise
B26: Batanes Multi-Purpose Cooperative, Inc.
B27: Romy & Ava's Store
B28: J-nell's Gen Mdse
B29: Impression Digital Printing Solutions
B30: Golden Press
B31: Tawsen's Agri-Venture & Souvenirs
... B60: Sophia Marie Store
A61: 1 | B61: Apostol's General Merchandise
A62: 2 | B62: CMVILL Trading
A63: 3 | B63: JPM General Merchandise & Hardware
A64: 4 | B64: One-Touch Technology Trading
A65: 5 | B65: YCA Office Supplies & Equipment | J65: zz
A66: 6
A67: 7
A68: NOTE: | B68: 1. MODE OF PRICE EVALUATION SHALL BE ON A LOT BASIS, OTHERWISE PER ITEMS EVALUATION SHALL BE USED IF THERE WILL BE LACKING ITEMS IN ALL RFQ'S AND THE END-USER AGREED, . (Clause 15.2, Section II, Instructions to Bidders of the Philippine Bidding Documents for goods and infrastructure projects)
B69: 2. DELIVERY PERIOD: Thirty (30) calendar days.
B70: 3. WARRANTY SHALL BE FOR A PERIOD OF SIX (6) MONTHS FOR SUPPLIES AND MATERIALS, ONE (1) YEAR FOR EQUIPMENT, FROM THE DATE OF ACCEPTANCE BY THE PROCURING ENTITY.
B71: 4. THE APPROVED BUDGET CEILING FOR THIS PROCUREMENT IS PHP (GPPB Resolution no. 09-2009)
B72: =PR!H110 -> 180000
B73: 5. PRICE VALIDITY SHALL BE OR THE PERIOD OF 30 CALENDAR DAYS.
B74: 6. BIDDERS SHALL SUBMIT ORIGINAL BROCHURES SHOWING SPECIFICATIONS OF THE PRODUCT BEING OFFERED IF APPLICABLE.
A75: In compliance with GPPB Resolution No. 09-2009
B77: Retrieval of Request for Quotation
A79: No. | B79: Supplier | E79: Released by: | F79: Date & Time: | G79: Remarks | N79: k
A80: 1 | B80: Apostol's General Merchandise
A81: 2 | B81: CMVILL Trading
A82: 3 | B82: JPM General Merchandise & Hardware
A83: 4 | B83: One-Touch Technology Trading
A84: 5 | B84: YCA Office Supplies & Equipment
A85: 6
A86: 7

Sheet Abstract 
B4: ABSTRACT OF QUOTATIONS
B6: (x) Furnishing/delivery of supplies, and materials or equipment | G6: Bids opened at Basco, Batanes
B7: ( x ) Furnishing Labor, services, etc. | I7: =NOW() -> 46148.741
B8: ( ) Rental or use of transportation facilities equipment, quarters, rooms, lot or space, etc.
B10: To be furnished at the | D10: BATANES STATE COLLEGE
C11: (State place or site of Office or project where articles or services be furnished or returned)
A13: NAME OF ARTICLES OR SERVICES TO BE FURNISHED, RENDERED OR FACILITIES TO BE RENTED
F16: JPM Gen. Mdse. & Hardware
F17: Thine-line Trading
F18: J-Tech Trading & Services
F19: Mulong Ydel
F20: MDAC Trading & Compuserve
F21: FVA Gen Mdse & Construction Supply
F22: MKM Hardware
F23: GDP Trading
F24: EA Amboy Gen Mdse
F25: L & R's Hontomin Gen Mdse
F26: Davocol's Gen. Mdse.
F27: RCJ Hardware & Gen Mdse
... F88: Valiente Food Producer
F89: =DATA!W114 -> Bethel General Insurance & Surety Corporation | G89: AlliedBankers Insurance Corporation | H89: Philippine Redcross
N90: JPM General Merchandise & Hardware
A91: =PR!D16 -> Health Insurance Coverage: Accidental Death & Disablement,Unprovoked Murder & Assault Medical Expense or Reimbursement,Burial Benefits due to Accident/Natural Death,Daily Hospital Benefits due to Accident or illness,Dengue Cash Assistance,Ambulance Cash Assistance,Fire Cash Assistance,COVID-19 Cash Assistance for "Death Only",Combined Single Limit for Bodily Injury & Property Damage within premises of the school campus | B91: Bond paper, A4 size | C91: Bond paper, A4 size | D91: Bond paper, A4 size | E91: Bond paper, A4 size | F91: =DATA!O114 -> 117000 | G91: No Philgeps Registration | H91: No Philgeps Registration | L91: none
L92: none
L93: none
B100: Bond paper, A4 size | C100: Bond paper, A4 size | D100: Bond paper, A4 size | E100: Bond paper, A4 size
A114: =DATA!I179 -> Rotary Hammer 850 W 3-Mode Function, with Drill Bit & Chisel included, 220V-240V | B114: Bond paper, A4 size | C114: Bond paper, A4 size | D114: Bond paper, A4 size | E114: Bond paper, A4 size | F114: =DATA!O50 -> 2620 | G114: 2200 | H114: 2320 | I114: 2320
A115: =DATA!I180 -> Rotary Hammer 28mm, 1300W with Drill Bit & Chisel included, 220V-240V | B115: Bond paper, A4 size | C115: Bond paper, A4 size | D115: Bond paper, A4 size | E115: Bond paper, A4 size | F115: =DATA!O51 -> 2620 | G115: 2200 | H115: 2320 | I115: 2320
A116: =DATA!I181 -> 45-135˚ Multi Angel Miter Shear Cutter, Adjustable angle cutter for cutting plastic, PVC & Molding Trim | B116: Bond paper, A4 size | C116: Bond paper, A4 size | D116: Bond paper, A4 size | E116: Bond paper, A4 size | F116: =DATA!O52 -> 70 | G116: 110 | H116: 190 | I116: 190
A117: =DATA!I182 -> U Type Edge trimming scissor 45 degrees 90 degrees Trunking Pliers (Large Edge Clamp) | B117: Bond paper, A4 size | C117: Bond paper, A4 size | D117: Bond paper, A4 size | E117: Bond paper, A4 size | F117: =DATA!O53 -> 90 | G117: 60 | H117: 75 | I117: 75
A118: =DATA!I183 -> U Type Edge trimming scissor 45 degrees 90 degrees Trunking Pliers (Small size Edge Clamp) | B118: Bond paper, A4 size | C118: Bond paper, A4 size | D118: Bond paper, A4 size | E118: Bond paper, A4 size | F118: =DATA!O54 -> 0 | H118: none | I118: none
A119: =DATA!I184 -> 9000KPA Portable Pressure Washer set: with Pressure Gauge & Adjustable Pressure, PW Gun, High Pressure Hose, Water Inlet connector & filter, Foam spray bottle | B119: Bond paper, A4 size | C119: Bond paper, A4 size | D119: Bond paper, A4 size | E119: Bond paper, A4 size | F119: =DATA!O55 -> 4620 | H119: none | I119: none
A120: =DATA!I185 -> Electric Air Blower 650W Hand Dust Cleaner Blow Machine, 650W - AB6038, Dust Bag Included, Max Blowing Rate 0-4.0m/min., input power 650W | B120: Bond paper, A4 size | C120: Bond paper, A4 size | D120: Bond paper, A4 size | E120: Bond paper, A4 size | F120: =DATA!O56 -> 2660 | H120: none | I120: none
A121: =DATA!I186 -> Aircon Coli Cleaner | B121: Bond paper, A4 size | C121: Bond paper, A4 size | D121: Bond paper, A4 size | E121: Bond paper, A4 size | F121: =DATA!O57 -> 20800 | H121: none | I121: none
A122: =DATA!I187 -> Aircon Fin Straightener/Fin Comb, Condenser Evaporator Fin | B122: Bond paper, A4 size | C122: Bond paper, A4 size | D122: Bond paper, A4 size | E122: Bond paper, A4 size | F122: =DATA!O58 -> 6998 | H122: none | I122: none
A123: =DATA!I188 -> 2 Liter Hand Pressure Pump Sprayer (LTGT2000HSX) | B123: Bond paper, A4 size | C123: Bond paper, A4 size | D123: Bond paper, A4 size | E123: Bond paper, A4 size | F123: =DATA!O59 -> 4998 | H123: none | I123: none
A124: =DATA!I189 -> 5L Shoulder Hand-Operated Sprayer (LTGT5000PSX) | B124: Bond paper, A4 size | C124: Bond paper, A4 size | D124: Bond paper, A4 size | E124: Bond paper, A4 size | F124: =DATA!O60 -> 6998 | H124: none | I124: none
A125: =DATA!I190 -> Wet & Dry Vaccuum Cleaner, 3 in 1 Carpet Extractor Cleaner, Power: 1034 W, Voltage: 230 v, 40 Liter | B125: Bond paper, A4 size | C125: Bond paper, A4 size | D125: Bond paper, A4 size | E125: Bond paper, A4 size | F125: =DATA!O61 -> 1000 | H125: none | I125: none
A126: =DATA!I191 -> BSC medal (diameter: 9cm, Gold Plated) | B126: Bond paper, A4 size | C126: Bond paper, A4 size | D126: Bond paper, A4 size | E126: Bond paper, A4 size | F126: =DATA!O62 -> 500 | H126: none | I126: none
A127: =DATA!I192 -> Molder | B127: Bond paper, A4 size | C127: Bond paper, A4 size | D127: Bond paper, A4 size | E127: Bond paper, A4 size | F127: =DATA!O63 -> 620 | H127: none | I127: none
A128: =DATA!I193 -> Plaque for Loyalty Award - made of premium quality MDF wood, size: 30cm-35cm; inclusive of design and lay-out logo of Batanes State College,customized with recipient's name, award title and events details; mounted on a sturdy wooden base; | B128: Bond paper, A4 size | C128: Bond paper, A4 size | D128: Bond paper, A4 size | E128: Bond paper, A4 size | F128: =DATA!O64 -> 225 | H128: none | I128: none
A129: =DATA!I194 -> Shovel | B129: Bond paper, A4 size | C129: Bond paper, A4 size | D129: Bond paper, A4 size | E129: Bond paper, A4 size | F129: =DATA!O65 -> 225 | H129: none | I129: none
... A160: =DATA!I225 -> 9 Watts LED Bulb, Warm White, E27 | B160: Bond paper, A4 size | C160: Bond paper, A4 size | D160: Bond paper, A4 size | E160: Bond paper, A4 size | F160: =DATA!O96 -> 5998 | H160: none | I160: none
A161: =DATA!I226 -> Vinyl Electrical Tape 0.16mmx19mmx16m (black) | B161: Bond paper, A4 size | C161: Bond paper, A4 size | D161: Bond paper, A4 size | E161: Bond paper, A4 size | F161: =DATA!O97 -> 5998 | G161: 900 | H161: none | I161: none
A162: =DATA!I227 -> A4, Certificate Frame with stand | B162: Bond paper, A4 size | C162: Bond paper, A4 size | D162: Bond paper, A4 size | E162: Bond paper, A4 size | F162: =DATA!O98 -> 5998 | G162: 900 | H162: none | I162: none
A163: =DATA!I228 -> Paper Vellum Board (220 gsm) | B163: Bond paper, A4 size | C163: Bond paper, A4 size | D163: Bond paper, A4 size | E163: Bond paper, A4 size | F163: =DATA!O99 -> 4998 | G163: 925 | H163: none | I163: none
A164: =DATA!I229 -> Photo Paper A4 | B164: Bond paper, A4 size | C164: Bond paper, A4 size | D164: Bond paper, A4 size | E164: Bond paper, A4 size | F164: =DATA!O100 -> 2498 | G164: 9300 | H164: none | I164: none
A165: =DATA!I230 -> Ink 774 (Black 108ml) | B165: Bond paper, A4 size | C165: Bond paper, A4 size | D165: Bond paper, A4 size | E165: Bond paper, A4 size | F165: =DATA!O101 -> 6998 | G165: 32000 | H165: none | I165: none
A166: =DATA!I231 -> Ink 664 (Yellow,Cyan,Magenta-48.8ml) | B166: Bond paper, A4 size | C166: Bond paper, A4 size | D166: Bond paper, A4 size | E166: Bond paper, A4 size | F166: =DATA!O102 -> 5998 | G166: 9900 | H166: none | I166: none
A167: =DATA!I232 -> Food Tong 24.0cm | B167: Bond paper, A4 size | C167: Bond paper, A4 size | D167: Bond paper, A4 size | E167: Bond paper, A4 size | F167: =DATA!O103 -> 0 | G167: 400 | H167: none | I167: none
A168: =DATA!I233 -> Serving Spoon 9" stainless steel | B168: Bond paper, A4 size | C168: Bond paper, A4 size | D168: Bond paper, A4 size | E168: Bond paper, A4 size | F168: =DATA!O104 -> 1780 | G168: 1500 | H168: none | I168: none
A169: =DATA!I234 -> Serving Fork | B169: Bond paper, A4 size | C169: Bond paper, A4 size | D169: Bond paper, A4 size | E169: Bond paper, A4 size | F169: =DATA!O105 -> 1150 | G169: 9950 | H169: none | I169: none
A170: =DATA!I235 -> Rice Cooker 45cups 7.8L capacity | B170: Bond paper, A4 size | C170: Bond paper, A4 size | D170: Bond paper, A4 size | E170: Bond paper, A4 size | F170: =DATA!O106 -> 385 | G170: 1440 | H170: none | I170: none
A171: =DATA!I236 -> Heavy Duty Coffee Perculator 100cups 15Liters | B171: Bond paper, A4 size | C171: Bond paper, A4 size | D171: Bond paper, A4 size | E171: Bond paper, A4 size | F171: =DATA!O107 -> 18000 | H171: none | I171: none
A172: =DATA!I237 -> Tissue Holder | B172: Bond paper, A4 size | C172: Bond paper, A4 size | D172: Bond paper, A4 size | E172: Bond paper, A4 size | F172: =DATA!O108 -> 1200 | H172: none | I172: none
A173: =DATA!I238 -> Coffee Spoon 17cm x 3.7cm 12's/10's | B173: Bond paper, A4 size | C173: Bond paper, A4 size | D173: Bond paper, A4 size | E173: Bond paper, A4 size | F173: =DATA!O109 -> 975 | H173: none | I173: none
A174: =DATA!I239 -> M-GAS Refill (Large) | B174: Bond paper, A4 size | C174: Bond paper, A4 size | D174: Bond paper, A4 size | E174: Bond paper, A4 size | F174: =DATA!O110 -> 1050 | H174: none | I174: none
A175: =DATA!I240 -> Picture Frame, A4 size | B175: Bond paper, A4 size | C175: Bond paper, A4 size | D175: Bond paper, A4 size | E175: Bond paper, A4 size | F175: =DATA!O111 -> 750 | H175: none | I175: none
A176: =DATA!I241 -> Wine Paper Bag | B176: Bond paper, A4 size | C176: Bond paper, A4 size | D176: Bond paper, A4 size | E176: Bond paper, A4 size | F176: =DATA!O112 -> 2700 | H176: none | I176: none
A177: =DATA!I242 -> Plain Paper Bag (medium) | B177: Bond paper, A4 size | C177: Bond paper, A4 size | D177: Bond paper, A4 size | E177: Bond paper, A4 size | F177: =DATA!O113 -> 9000 | H177: none | I177: none
A178: =DATA!I243 -> Chinese Paper (Gold & red) | B178: Bond paper, A4 size | C178: Bond paper, A4 size | D178: Bond paper, A4 size | E178: Bond paper, A4 size | F178: =DATA!O114 -> 117000 | H178: none | I178: none
A179: =DATA!I244 -> Sacramental Bread | B179: Bond paper, A4 size | C179: Bond paper, A4 size | D179: Bond paper, A4 size | E179: Bond paper, A4 size | F179: =DATA!O115 -> 0 | H179: none | I179: none
A180: =DATA!I245 -> Fruit Basket (Large) | B180: Bond paper, A4 size | C180: Bond paper, A4 size | D180: Bond paper, A4 size | E180: Bond paper, A4 size | F180: =DATA!O116 -> 76500 | H180: none | I180: none
A181: =DATA!I246 -> Grapes | B181: Bond paper, A4 size | C181: Bond paper, A4 size | D181: Bond paper, A4 size | E181: Bond paper, A4 size | F181: =DATA!O117 -> 740 | H181: none | I181: none
A182: =DATA!I247 -> Mangoes | B182: Bond paper, A4 size | C182: Bond paper, A4 size | D182: Bond paper, A4 size | E182: Bond paper, A4 size | F182: =DATA!O118 -> 12260 | H182: none | I182: none
... A263: =DATA!I328 -> 0 | B263: Bond paper, A4 size | C263: Bond paper, A4 size | D263: Bond paper, A4 size | E263: Bond paper, A4 size | F263: =DATA!O199 -> 5200 | H263: none | I263: none
A264: =DATA!I329 -> 0 | B264: Bond paper, A4 size | C264: Bond paper, A4 size | D264: Bond paper, A4 size | E264: Bond paper, A4 size | F264: =DATA!O200 -> 1600 | G264: =SUM(G91:G108) -> 0 | H264: 1100 | I264: 1100 | K264: .
A265: TOTAL | F265: =SUM(F91:F97) -> 117000 | G265: non-compliant | H265: non-compliant | I265: =SUM(I91:I97) -> 0 | J265: =SUM(J91:J98) -> 0
E267: all Items are Failed due to No Supplier Quoted the RFQ
A268: =A269 -> Lowest Calculated Bidder | E268: =F265 -> 117000 | F268: are Failed due to the qoutation Exceeded the Budget
A269: Lowest Calculated Bidder | F269: in the amount of | G269: =F265 -> 117000 | H269: is awarded to | I269: =F89 -> Bethel General Insurance & Surety Corporation
A270: RHOUPHELINE AYA A. CADIZ | F270: FORTUNATO PHILIP A. CABUGAO | I270: EMILYN D. ALUETA
A271: BAC Member | F271: BAC Member | I271: BAC Member
A273: =PR!B115 -> JENNY S. ALINA | E273: PHILIP ULYSSES T. CASTILLO | I273: DOREEN C. CASTILLO
A274: End-User/Provisional Member | F274: BAC Vice Chair | I274: BAC Chairperson
G275: BAC Sec. Cert. No: | I275: =PR!B12 -> 2507-SS02-251

Sheet LON
A6: BIDS AND AWARDS COMMITTEE
A8: LETTER OF NOTICE
A10: NICASIO B. SUBTENIENTE JR.
A11: Owner
A12: Bethel General Insurance and Surety Corporation
A13: Unit 200 Valero Plaza 124 Valero St. Salcedo Village, Makati City
A15: Madam/Sir:
A16: We are happy to notify you that your quotation date July 14, 2025 for the Health Insurance Coverage: Accidental Death & Disablement,Unprovoked Murder & Assault Medical Expense or Reimbursement,Burial Benefits due to Accident/Natural Death,Daily Hospital Benefits due to Accident or illness,Dengue Cash Assistance,Ambulance Cash Assistance,Fire Cash Assistance,COVID-19 Cash Assistance for "Death Only",Combined Single Limit for Bodily Injury & Property Damage within premises of the school campus with PR # 2507-SS02-251 contract price equivalent to ONE HUNDRED SEVENTEEN THOUSAND PESOS ONLY (Php 117,000.00) is hereby accepted.
A17: You are hereby required to provide within Ten (10) days a certified photocopy of the following requirements:
A18: .
B19: 1. Updated Mayor's Permit/Business Permit
B20: 2. PhilGEPS Registration no.
B21: 3. Latest Income/Business Tax Return
B22: 4. Duly Notarized Omnibus Sworn Statement
B23: 5. BIR 2302 Certificate of Registration
B24: 6. Updated DTI Registration
B25: 7. Landbank Account details of the business (for payment purposes)
A27: However, If you already have a maintaining and updated file of the above-mentioned requirements in the BAC Office you may no longer require its re-submission (Annex "H", Appendix "A" Section III)
A29: *For individuals engaged under Sec. 53.6, 53.7, and 53.9 of the IRR of RA 9184, only the BIR Certificate of Registration shall be submitted in lieu of DTI Registration and Mayor’s Permit.
A30: Thank you
A32: Very truly yours,
A35: DOREEN C. CASTILLO
A36: BAC Chairperson
A38: Received by:
A41: (Signature over printed name)
A42: Date: ___________________
A43: Ref. No.: | B43: =PR!B12 -> 2507-SS02-251

Sheet BAC RESO 2022
E6: OFFICE OF THE BIDS AND AWARDS COMMITTEE | N6: OFFICE OF THE BIDS AND AWARDS COMMITTEE
E7: bac resolution No: | M7: =E7 -> bac resolution No:
D8: =PR!B12 -> 2507-SS02-251 | M8: =D8 -> 2507-SS02-251
E10: BAC RESOLUTION RECOMMENDING FOR AWARD | N10: APPROVAL OF THE BAC RECOMMENDATION FOR AWARD
A12: WHEREAS, the BATANES STATE COLLEGE advertised the Request for Price Quotation (RFQ) of the Metal File Document Tray (4 layers),Side Table with 2 drawers,Multifunctional File Holder,etc,. with PR # 2507-GAS19-250 dated July 14, 2025. | J12: WHEREAS, the BATANES STATE COLLEGE advertised the Request for Price Quotation (RFQ) of the Metal File Document Tray (4 layers),Side Table with 2 drawers,Multifunctional File Holder,etc,. with PR # 2507-GAS19-250 dated July 14, 2025.
A15: WHEREAS, from the period the Request for Price Quotation (RFQ) has started up to the time of bid submission and opening, Five (5) prospective bidder were able to submit the RFQ; | J15: WHEREAS, from the period the Request for Price Quotation (RFQ) has started up to the time of bid submission and opening, Five (5) prospective bidder were able to submit the RFQ;
S16: P
A18: WHEREAS, the Price Quotation based on the Lowest Calculated & Responsive Bid (LCRB) format of the bidders were opened and its bid price was read as follows: | J18: WHEREAS, the Price Quotation based on the Lowest Calculated & Responsive Bid (LCRB) format of the bidders were opened and its bid price was read as follows:
A21: ITEM NO. | B21: BIDDER WITH CALCULATED BID | G21: ABC | I21: BID AMOUNT | J21: ITEM NO. | K21: BIDDER WITH CALCULATED BID | P21: ABC | R21: BID AMOUNT
A22: 1 | B22: =DATA!W108 -> FVA Trading | G22: =PR!H110 -> 180000 | I22: 15675 | J22: 1 | K22: =B22 -> FVA Trading | P22: =G22 -> 180000 | R22: =I22 -> 15675
A23: 2 | B23: YCA Office Supplies & Equipment Trading | G23: =PR!H110 -> 180000 | I23: 19900 | J23: 2 | K23: =B23 -> YCA Office Supplies & Equipment Trading | P23: =G23 -> 180000 | R23: =I23 -> 19900
A24: 3 | B24: Apostol General Merchandise | G24: =PR!H110 -> 180000 | I24: non-compliant | J24: 3 | K24: =B24 -> Apostol General Merchandise | P24: =G24 -> 180000 | R24: =I24 -> non-compliant
A25: 4 | B25: JPM General Merchandise & Hardware | G25: =PR!H110 -> 180000 | I25: non-compliant | J25: 4 | K25: =B25 -> JPM General Merchandise & Hardware | P25: =G25 -> 180000 | R25: =I25 -> non-compliant
A26: 5 | B26: One-Touch Technology Trading | G26: =PR!H110 -> 180000 | I26: non-compliant | J26: 5 | K26: =B26 -> One-Touch Technology Trading | P26: =G26 -> 180000 | R26: =I26 -> non-compliant
A27: 6 | G27: =PR!H110 -> 180000 | J27: 6 | K27: =B27 -> 0 | P27: =G27 -> 180000 | R27: =I27 -> 0
A28: 7 | J28: 7 | K28: =B28 -> 0 | P28: =G28 -> 0 | R28: =I28 -> 0
A29: 8 | G29: 19350 | I29: 9000 | J29: 8 | K29: =B29 -> 0 | P29: =G29 -> 19350 | R29: =I29 -> 9000
J30: NOW THEREFORE, I DJOVI R. DURANTE,DPA by virtue of the authority vested in me of this institution and after taking into consideration the merits and legal bases of the recommendation of the members of the Bids and Awards Committee (BAC) do hereby APPROVE the following;
B32: 1. To declare FVA Trading as supplier with the Lowest Calculated & Responsive Bid of the with Metal File Document Tray (4 layers),Side Table with 2 drawers,Multifunctional File Holder,etc,. with PR # 2507-GAS19-250 dated July 14, 2025.
B35: 2. To recommend for approval by the Head of Procuring Entity of the Batanes State College the foregoing findings.
A36: RESOLVED FINALLY, at the BAC Office, Batanes State College, this _______day of . | J36: To declare FVA Trading as supplier with the Lowest Calculated & Responsive Bid of the with Metal File Document Tray (4 layers),Side Table with 2 drawers,Multifunctional File Holder,etc,. with PR # 2507-GAS19-250.
A37: Recommending Approval:
A39: RHOUPHELINE AYA A. CADIZ | D39: EMILYN D. ALUETA | G39: FORTUNATO PHILIP A. CABUGAO | J39: Done this ______ day of _________ 2025.
A40: BAC Member | D40: BAC Member | G40: BAC Member
L43: DJOVI REGALA DURANTE,DPA
A44: =PR!B115 -> JENNY S. ALINA | F44: PHILIP ULYSSES T. CASTILLO | L44: SUC President I
A45: End-user/Provisional Member | F45: Vice BAC Chairperson
D47: DOREEN C. CASTILLO
D48: BAC Chairperson

Sheet BAC RESO 2022 (Toss Coin)
E6: OFFICE OF THE BIDS AND AWARDS COMMITTEE | N6: OFFICE OF THE BIDS AND AWARDS COMMITTEE
E7: bac resolution No: | M7: =E7 -> bac resolution No:
D8: =PR!B12 -> 2507-SS02-251 | M8: =D8 -> 2507-SS02-251
E10: BAC RESOLUTION RECOMMENDING FOR AWARD | N10: APPROVAL OF THE BAC RECOMMENDATION FOR AWARD
A12: WHEREAS, the BATANES STATE COLLEGE advertised the Request for Price Quotation (RFQ)of the 4 Drawer Lateral Filing Cabinet with PR # 2507-GAS25-249 dated July 14, 2025. | J12: WHEREAS, the BATANES STATE COLLEGE advertised the Request for Price Quotation (RFQ)of the 4 Drawer Lateral Filing Cabinet with PR # 2507-GAS25-249 dated July 14, 2025.
A15: WHEREAS, from the period the Request for Price Quotation (RFQ) has started up to the time of bid submission and opening, Five (5) prospective bidders were able to submit the RFQ; | J15: WHEREAS, from the period the Request for Price Quotation (RFQ) has started up to the time of bid submission and opening, Five (5) prospective bidders were able to submit the RFQ;
A18: WHEREAS, the Price Quotation based on the Lowest Calculated & Responsive Bid (LCRB) format of the bidders were opened and its bid price was read as follows: | J18: WHEREAS, the Price Quotation based on the Lowest Calculated & Responsive Bid (LCRB) format of the bidders were opened and its bid price was read as follows:
A21: ITEM NO. | B21: BIDDER WITH CALCULATED BID | G21: ABC | I21: BID AMOUNT | J21: ITEM NO. | K21: BIDDER WITH CALCULATED BID | P21: ABC | R21: BID AMOUNT
A22: 1 | B22: =DATA!W107 -> FVA Trading | G22: =PR!H110 -> 180000 | I22: 18000 | J22: 1 | K22: =B22 -> FVA Trading | P22: =G22 -> 180000 | R22: =I22 -> 18000
A23: 2 | B23: One-Touch Technology Trading | G23: =PR!H110 -> 180000 | I23: 18000 | J23: 2 | K23: =B23 -> One-Touch Technology Trading | P23: =G23 -> 180000 | R23: =I23 -> 18000
A24: 3 | B24: YCA Office Supplies & Equipment | G24: =PR!H110 -> 180000 | I24: 19500 | J24: 3 | K24: =B24 -> YCA Office Supplies & Equipment | P24: =G24 -> 180000 | R24: =I24 -> 19500
A25: 4 | B25: JPM General Merchandise & Hardware | G25: =PR!H110 -> 180000 | I25: 20000 | J25: 4 | K25: =B25 -> JPM General Merchandise & Hardware | P25: =G25 -> 180000 | R25: =I25 -> 20000
A26: 5 | B26: E.A.Amboy General Merchandise | G26: =PR!H110 -> 180000 | I26: none | J26: 5 | K26: =B26 -> E.A.Amboy General Merchandise | P26: =G26 -> 180000 | R26: =I26 -> none
A27: 6 | J27: 6 | K27: =B27 -> 0 | P27: =G27 -> 0 | R27: =I27 -> 0
A28: 7 | J28: 7 | K28: =B28 -> 0 | P28: =G28 -> 0 | R28: =I28 -> 0
A29: 8 | J29: 8 | K29: =B29 -> 0 | P29: =G29 -> 0 | R29: =I29 -> 0
A30: WHEREAS,two (2) of the suppliers have the same total price quotation; | J30: WHEREAS,two (2) of the suppliers have the same total price quotation;
A32: WHEREAS, to resolve cases involving a tie, the procuring entity may determine a measure to be used by which it shall be non-discretionary and non-discriminatory such that the same shall be based on sheer luck or chance. The method used was "toss coin"; | J32: WHEREAS, to resolve cases involving a tie, the procuring entity may determine a measure to be used by which it shall be non-discretionary and non-discriminatory such that the same shall be based on sheer luck or chance. The method used was "toss coin";
A34: WHEREAS, as per result of the toss coin conducted, FVA Trading was announced as the winner: | J34: WHEREAS, as per result of the toss coin conducted, FVA Trading was announced as the winner:
B36: 1. To declare FVA Trading as supplier of 4 Drawer Lateral Filing Cabinet with PR # 2507-GAS25-249 dated July 14, 2025. | J36: NOW THEREFORE, I DJOVI R. DURANTE,DPA by virtue of the authority vested in me of this institution and after taking into consideration the merits and legal bases of the recommendation of the members of the Bids and Awards Committee (BAC) do hereby APPROVE the following;
B39: 2. To recommend for approval by the Head of Procuring Entity of the Batanes State College the foregoing findings.
A40: RESOLVED FINALLY, at the BAC Office, Batanes State College, this _______day of . | J40: To declare FVA Trading as supplier of 4 Drawer Lateral Filing Cabinet with PR # 2507-GAS25-249 dated July 14, 2025.
A41: Recommending Approval:
A44: RHOUPHELINE AYA A. CADIZ | D44: EMILYN D. ALUETA | G44: FORTUNATO PHILIP A. CABUGAO | J44: Done this _______ day of ___________ 2022 | N44: 2025
A45: BAC Member | D45: BAC Member | G45: BAC Member
L47: DJOVI REGALA DURANTE,DPA
A48: =PR!B115 -> JENNY S. ALINA | D48: PHILIP ULYSSES T. CASTILLO | H48: DOREEN C. CASTILLO | L48: SUC President I
A49: End-user/Provisional Member | D49: BAC Vice Chairperson | H49: BAC Chairperson

Sheet PO
A2: PURCHASE ORDER | I2: INSTRUCTIONS
A3: Supplier: | B3: =DATA!W114 -> Bethel General Insurance & Surety Corporation | D3: PO No. | F3: 2025-07-251 | I3: specific quantities of supplies/goods/property subject to the terms and conditions contained in the PO.
A4: Address: | B4: Unit 200 Valero Plaza 124 Valero St. Salcedo Village,Makati City | D4: Date | F4: September 9, 2025 | I4: B. This form shall be accomplished as follows:
A5: TIN: | B5: 000-745-041-000 | C5: 000-745-041-000 | E5: Small Value Procurement | J5: 1. Entity Name - name of the agency/entity
B6: 150-214-534 | J6: 2. Supplier/Address/TIN - name, address and TIN of the supplier
A7: Please furnish this office the following articles subject to the term and conditions contained herein: | J7: 3. P.O. No. - the number assigned to the PO which shall be as follows:
A8: Place of Delivery: | C8: Batanes State College | D8: Delivery Term: | F8: FOB Destination | K8: 0000-00-0000 | M8: Serial number (one series for each year)
A9: Date of Delivery: | C9: 30 days upon receipt od PO | D9: Payment Term: | F9: 15 days upon complete delivery | M9: Month
A10: No. | B10: Unit | C10: Description | D10: Qty | E10: Unit Cost | F10: Amount | M10: Year
A11: =RFQ_!A18 -> 001 | B11: =PR!B16 -> pcs | C11: =PR!D16 -> Health Insurance Coverage: Accidental Death & Disablement,Unprovoked Murder & Assault Medical Expense or Reimbursement,Burial Benefits due to Accident/Natural Death,Daily Hospital Benefits due to Accident or illness,Dengue Cash Assistance,Ambulance Cash Assistance,Fire Cash Assistance,COVID-19 Cash Assistance for "Death Only",Combined Single Limit for Bodily Injury & Property Damage within premises of the school campus | D11: =PR!A16 -> 900 | E11: =DATA!N114 -> 130 | F11: =SUM(D11*E11) -> 117000 | J11: 4. Date - date of the preparation of the PO
A12: =RFQ_!A19 -> 002 | B12: =PR!B17 -> 0 | F12: =SUM(D12*E12) -> 0 | J12: 5. Mode of Procurement - mode of procurement such as public bidding, through Procurement Service, limited source bidding, direct contracting, repeat order, shopping and negotiated procurement in accordance with RA 9184
A13: =RFQ_!A20 -> 003 | B13: =PR!B18 -> 0 | F13: =SUM(D13*E13) -> 0 | H13: P | J13: 6. Place/Date of Delivery - place of delivery and definite date/s of delivery; if not stated, the date of delivery shall mean seven (7) calendar days after the receipt of PO by the supplier
A14: =RFQ_!A21 -> 004 | B14: =PR!B19 -> 0 | F14: =SUM(D14*E14) -> 0 | J14: 7. Delivery Term - delivery term i.e., FOB destination, FOB shipping point
A15: =RFQ_!A22 -> 005 | B15: =PR!B20 -> 0 | F15: =SUM(D15*E15) -> 0 | J15: 8. Payment Term - specified period required when the delivered goods shall be paid and discounts, if any, such as 2/10, n/30
A16: =RFQ_!A23 -> 006 | B16: =PR!B21 -> 0 | F16: =SUM(D16*E16) -> 0 | J16: 9. Stock/Property No. - stock/property number of the goods to be purchased as provided by the Supply and/or Property Division Unit
A17: =RFQ_!A24 -> 007 | B17: =PR!B22 -> 0 | F17: =SUM(D17*E17) -> 0 | J17: 10. Unit - unit of measurement of the supplies/goods/property being procured (i.e. piece, roll, box, reams, etc.)
A18: =RFQ_!A25 -> 008 | B18: =PR!B23 -> 0 | F18: =SUM(D18*E18) -> 0 | J18: 11. Description - brief description of the supplies/goods/property being procured
A19: =RFQ_!A26 -> 009 | B19: =PR!B24 -> 0 | F19: =SUM(D19*E19) -> 0 | J19: 12. Quantity - quantity of supplies/goods/property being procured
A20: =RFQ_!A27 -> 010 | B20: =PR!B25 -> 0 | F20: =SUM(D20*E20) -> 0 | J20: 13. Unit Cost - cost per unit of the supplies/goods/property being procured
A21: =RFQ_!A28 -> 011 | B21: =PR!B26 -> 0 | F21: =SUM(D21*E21) -> 0 | J21: 14. Amount - total amount of the supplies/goods/property being procured (Quantity x Unit Cost)
A22: =RFQ_!A29 -> 012 | B22: =PR!B27 -> 0 | F22: =SUM(D22*E22) -> 0 | J22: 15. Penalty Clause - penalty to be imposed by the agency/entity in case of non-compliance with the term, that is, one-tenth (1/10) of one percent (1%) for every day of delay on the undelivered item/s
A23: =RFQ_!A30 -> 013 | B23: =PR!B28 -> 0 | F23: =SUM(D23*E23) -> 0 | J23: 16. Approval - signature over printed name and designation of the Approving Official
A24: =RFQ_!A31 -> 014 | B24: =PR!B29 -> 0 | C24: =PR!D29 -> 0 | D24: =PR!A29 -> 0 | E24: =DATA!N230 -> 850 | F24: =SUM(D24*E24) -> 0 | J24: 17. Conforme - signature over printed name of the supplier or his/her representative signifying his/her approval to the term set by the agency/entity and the date of signing
A25: =RFQ_!A32 -> 015 | B25: =PR!B30 -> 0 | C25: =PR!D30 -> 0 | D25: =PR!A30 -> 0 | E25: =DATA!N231 -> 850 | F25: =SUM(D25*E25) -> 0 | J25: 18. Fund Cluster - fund cluster name/code in accordance with the UACS
A26: =RFQ_!#REF! -> #REF! | B26: =PR!B31 -> 0 | C26: =PR!D31 -> 0 | D26: =PR!A31 -> 0 | E26: =DATA!N232 -> 290 | F26: =SUM(D26*E26) -> 0 | J26: 19. Funds Available - amount of funds available which shall be certified by the Chief Accountant/Head of Accounting Division/Unit
A27: =RFQ_!#REF! -> #REF! | B27: =PR!B32 -> 0 | C27: =PR!D32 -> 0 | D27: =PR!A32 -> 0 | E27: =DATA!N233 -> 100 | F27: =SUM(D27*E27) -> 0 | J27: 20. ORS/BURSNo., Date and Amount - ORS/BURS number assigned by the Budget Division/Unit, date of the ORS/BURS and the amount of obligation supporting the purchase
A28: =RFQ_!#REF! -> #REF! | B28: =PR!B33 -> 0 | C28: =PR!D33 -> 0 | D28: =PR!A33 -> 0 | E28: =DATA!N234 -> 110 | F28: =SUM(D28*E28) -> 0 | I28: C. It shall be prepared in four (4) copies distributed as follows:
A29: =RFQ_!A33 -> 019 | B29: =PR!B34 -> 0 | C29: =PR!D34 -> 0 | D29: =PR!A34 -> 0 | E29: =DATA!N235 -> 5900 | F29: =SUM(D29*E29) -> 0 | J29: Original - to the supplier for conforme to the terms of the PO and as attachment to the DV upon request for payment
A30: 020 | B30: =PR!B35 -> 0 | C30: =PR!D35 -> 0 | D30: =PR!A35 -> 0 | E30: =DATA!N236 -> 13500 | F30: =SUM(D30*E30) -> 0 | J30: Copy 2 - retained by the Supply and/or Property Division Unit for file
A31: 021 | B31: =PR!B36 -> 0 | C31: =PR!D36 -> 0 | D31: =PR!A36 -> 0 | E31: =DATA!N237 -> 150 | F31: =SUM(D31*E31) -> 0 | J31: Copy 3 - to be submitted to COA within five (5) days after conformity by the supplier
A32: 022 | B32: =PR!B37 -> 0 | C32: =PR!D37 -> 0 | D32: =PR!A37 -> 0 | E32: =DATA!N238 -> 1080 | F32: =SUM(D32*E32) -> 0 | J32: Copy 4 - Supplier's copy
A33: 023 | B33: =PR!B38 -> 0 | C33: =PR!D38 -> 0 | D33: =PR!A38 -> 0 | E33: =DATA!N239 -> 5890 | F33: =SUM(D33*E33) -> 0
A34: 024 | B34: =PR!B39 -> bottle | C34: =PR!D39 -> Rotary Hammer 850 W 3-Mode Function, with Drill Bit & Chisel included, 220V-240V | D34: =PR!A39 -> 4 | E34: =DATA!N240 -> 180 | F34: =SUM(D34*E34) -> 720
A35: 025 | B35: =PR!B40 -> bottle | C35: =PR!D40 -> Rotary Hammer 28mm, 1300W with Drill Bit & Chisel included, 220V-240V | D35: =PR!A40 -> 4 | E35: =DATA!N241 -> 40 | F35: =SUM(D35*E35) -> 160
A36: 026 | B36: =PR!B41 -> roll | C36: =PR!D41 -> 45-135˚ Multi Angel Miter Shear Cutter, Adjustable angle cutter for cutting plastic, PVC & Molding Trim | D36: =PR!A41 -> 2 | E36: =DATA!N242 -> 50 | F36: =SUM(D36*E36) -> 100
A37: =RFQ_!A41 -> 026 | B37: =PR!B42 -> roll | C37: =PR!D42 -> U Type Edge trimming scissor 45 degrees 90 degrees Trunking Pliers (Large Edge Clamp) | D37: =PR!A42 -> 3 | E37: =DATA!N243 -> 20 | F37: =SUM(D37*E37) -> 60
A38: =RFQ_!A43 -> 028 | B38: =PR!B43 -> copy | C38: =DATA!I100 -> Principles of Hotel Front Office Operations, Baneji, 2023, 9789351541707, Wiseman's Books Trading | D38: =DATA!J100 -> 1 | E38: =DATA!N244 -> 280 | F38: =SUM(D38*E38) -> 280
A39: =RFQ_!A44 -> 029 | B39: =PR!B44 -> copy | C39: =DATA!I101 -> School and Peer Contexts of Bullying: An Introduction and Exploration, Ramirez, 2024, 9781774698792, Wiseman's Book Trading, Inc. | D39: =DATA!J101 -> 1 | E39: =DATA!N245 -> 480 | F39: =SUM(D39*E39) -> 480
A40: =RFQ_!A45 -> 030 | B40: =PR!B45 -> copy | C40: =DATA!I102 -> Software design, Lal, 2024, 9781774697795, Wiseman's Book Trading, Inc. | D40: =DATA!J102 -> 1 | E40: =DATA!N246 -> 450 | F40: =SUM(D40*E40) -> 450
A41: =RFQ_!A46 -> 031 | B41: =PR!B46 -> 0 | D41: =DATA!J103 -> 1 | E41: =DATA!N247 -> 350 | F41: =SUM(D41*E41) -> 350
A42: =RFQ_!A47 -> 032 | B42: =PR!B47 -> 0 | D42: =DATA!J104 -> 2 | E42: =DATA!N248 -> 45 | F42: =SUM(D42*E42) -> 90
A43: =RFQ_!A48 -> 033 | B43: =PR!B48 -> 0 | D43: =DATA!J105 -> 1 | E43: =DATA!N249 -> 45 | F43: =SUM(D43*E43) -> 45
A44: =RFQ_!A49 -> 034 | B44: =PR!B49 -> 0 | D44: =DATA!J106 -> 1 | E44: =DATA!N250 -> 240 | F44: =SUM(D44*E44) -> 240
A45: =RFQ_!A50 -> 035 | B45: =PR!B50 -> 0 | D45: =DATA!J107 -> 1 | E45: =DATA!N251 -> 20000 | F45: =SUM(D45*E45) -> 20000
A46: =RFQ_!A51 -> 036 | B46: =PR!B51 -> 0 | C46: =DATA!I95 -> Fundamentals of Internet Programming, Ahmad, 2024, 9781774697627, Wiseman's Book Trading, Inc. | D46: =DATA!J108 -> 2 | E46: =DATA!N252 -> 5000 | F46: =SUM(D46*E46) -> 10000
A47: =RFQ_!A52 -> 037 | B47: =PR!B52 -> 0 | C47: =DATA!I96 -> Housekeeping management, Juyal, 2024, 9781774697207, Forefront Book | D47: =DATA!J109 -> 1 | E47: =DATA!N253 -> 28000 | F47: =SUM(D47*E47) -> 28000
A48: =RFQ_!A53 -> 038 | B48: =PR!B53 -> 0 | C48: =DATA!I97 -> Information Systems, Qaiser, 2024, 9781774697894, Wiseman's Book Trading, Inc. | D48: =DATA!J110 -> 2 | E48: =DATA!N254 -> 4500 | F48: =SUM(D48*E48) -> 9000
A49: =RFQ_!A54 -> 039 | B49: =PR!B54 -> 0 | C49: =DATA!I98 -> Plant Taxonomy (2nd Edition) (with Access code), Saxiano, 2024, 9781984688873, Wiseman's Book Trading, Inc. | D49: =DATA!J111 -> 2 | E49: =DATA!N255 -> 7000 | F49: =SUM(D49*E49) -> 14000
A50: =RFQ_!A55 -> 040 | B50: =PR!B55 -> 0 | D50: =DATA!J112 -> 10 | E50: =DATA!N256 -> 300 | F50: =SUM(D50*E50) -> 3000
A51: =RFQ_!A56 -> 041 | B51: =PR!B56 -> 0 | D51: =DATA!J113 -> 1 | E51: =DATA!N257 -> 300 | F51: =SUM(D51*E51) -> 300
A52: =RFQ_!A57 -> 042 | B52: =PR!B57 -> 0 | D52: =DATA!J114 -> 900 | E52: =DATA!N258 -> 300 | F52: =SUM(D52*E52) -> 270000
A53: =RFQ_!A58 -> 043 | B53: =PR!B58 -> 0 | D53: =DATA!J115 -> 10 | E53: =DATA!N259 -> 350 | F53: =SUM(D53*E53) -> 3500
A54: =RFQ_!A59 -> 044 | B54: =PR!B59 -> 0 | D54: =DATA!J116 -> 17 | E54: =DATA!N260 -> 250 | F54: =SUM(D54*E54) -> 4250
A55: =RFQ_!A60 -> 045 | B55: =PR!B60 -> 0 | D55: =DATA!J117 -> 2 | E55: =DATA!N261 -> 90 | F55: =SUM(D55*E55) -> 180
A56: =RFQ_!A61 -> 046 | B56: =PR!B61 -> 0 | D56: =DATA!J118 -> 20 | E56: =DATA!N262 -> 95 | F56: =SUM(D56*E56) -> 1900
A57: =RFQ_!A62 -> 047 | B57: =PR!B62 -> 0 | D57: =DATA!J119 -> 40 | E57: =DATA!N263 -> 0 | F57: =SUM(D57*E57) -> 0
A58: =RFQ_!A63 -> 048 | B58: =PR!B63 -> 0 | D58: =DATA!J120 -> 10 | E58: =DATA!N264 -> 0 | F58: =SUM(D58*E58) -> 0
A59: =RFQ_!A64 -> 049 | B59: =PR!B64 -> 0 | D59: =DATA!J121 -> 20 | E59: =DATA!N265 -> 0 | F59: =SUM(D59*E59) -> 0
A60: =RFQ_!A65 -> 050 | B60: =PR!B65 -> 0 | D60: =DATA!J122 -> 15 | E60: =DATA!N266 -> 0 | F60: =SUM(D60*E60) -> 0
A61: =RFQ_!A66 -> 051 | B61: =PR!B66 -> 0 | D61: =DATA!J123 -> 5 | E61: =DATA!N267 -> 0 | F61: =SUM(D61*E61) -> 0
... A94: =RFQ_!A99 -> 0 | B94: =PR!B99 -> 0 | D94: =DATA!J156 -> 1 | E94: =DATA!N300 -> 0 | F94: =SUM(D94*E94) -> 0
A95: =RFQ_!A106 -> 0 | B95: =PR!B100 -> 0 | D95: =DATA!J157 -> 12 | E95: =DATA!N301 -> 0 | F95: =SUM(D95*E95) -> 0
A96: =RFQ_!A107 -> Ref.# | B96: =PR!B101 -> 0 | D96: =DATA!J158 -> 20 | E96: =DATA!N302 -> 0 | F96: =SUM(D96*E96) -> 0
A97: =RFQ_!A108 -> 0 | B97: =PR!B102 -> 0 | D97: =DATA!J160 -> 6 | E97: =DATA!N303 -> 0 | F97: =SUM(D97*E97) -> 0
A98: =RFQ_!A109 -> 0 | B98: =PR!B103 -> 0 | D98: =DATA!J161 -> 6 | E98: =DATA!N304 -> 0 | F98: =SUM(D98*E98) -> 0
A99: =RFQ_!A110 -> 0 | B99: =PR!B104 -> 0 | D99: =DATA!J162 -> 6 | E99: =DATA!N305 -> 0 | F99: =SUM(D99*E99) -> 0
A100: =RFQ_!A111 -> 0 | B100: =PR!B105 -> 0 | D100: =DATA!J163 -> 6 | E100: =DATA!N306 -> 0 | F100: =SUM(D100*E100) -> 0
A101: =RFQ_!A112 -> 0 | B101: =PR!B106 -> 0 | D101: =DATA!J164 -> 5 | E101: =DATA!N307 -> 0 | F101: =SUM(D101*E101) -> 0
A102: =RFQ_!A113 -> 0 | B102: =PR!B107 -> 0 | D102: =DATA!J165 -> 5 | E102: =DATA!N308 -> 0 | F102: =SUM(D102*E102) -> 0
A103: =RFQ_!A114 -> 0 | B103: =PR!B108 -> 0 | D103: =DATA!J166 -> 3 | E103: =DATA!N309 -> 0 | F103: =SUM(D103*E103) -> 0
A104: =RFQ_!A115 -> 0 | B104: =PR!B109 -> 0 | D104: =DATA!J167 -> 1 | E104: =DATA!N310 -> 0 | F104: =SUM(D104*E104) -> 0
A105: =RFQ_!A116 -> 0 | B105: =PR!B110 -> 0 | D105: =DATA!J168 -> 10 | E105: =DATA!N311 -> 0 | F105: =SUM(D105*E105) -> 0
A106: =RFQ_!A117 -> 0 | B106: =PR!B111 -> health insurance | D106: =DATA!J169 -> 15 | E106: =DATA!N312 -> 0 | F106: =SUM(D106*E106) -> 0
A107: =RFQ_!A118 -> 0 | B107: =PR!B112 -> 0 | D107: =DATA!J170 -> 4 | E107: =DATA!N313 -> 0 | F107: =SUM(D107*E107) -> 0
A108: TOTAL | C108: ** ONE HUNDRED SEVENTEEN THOUSAND PESOS ONLY ** | F108: =SUM(F11:F23) -> 117000
A109: Purpose | C109: for the program/activIty/ of (SSO-Medical) for Health Insurance to be charged to Fund 07 | H109: for the program/project/activity of _________ to be charge to _______ budget as per PRE 2023 and approved APP 2023.
A110: In case of failure to make the full delivery within the time specified above, a penalty of one-tenth
A111: (1/10) of one percent for everyday of delay shall be imposed.
E112: Very truly yours,
A113: Conforme: | D113: DJOVI REGALA DURANTE, DPA
D114: SUC President I
A115: (Signature over printed name)
A116: Date: ____________________
A117: Funds Cluster: | E117: ORS/BURS No.
A118: Funds Available: | E118: Date of the ORS/BURS:
E120: Amount: | F120: =F108 -> 117000
C121: RHEA ANGELLICA B. ADDATU,CPA
C122: Accountant I
A123: Note: See PO instructions at the back | D123: Ref. No.: | E123: =PR!B12 -> 2507-SS02-251

Sheet POback (2)
A1: INSTRUCTIONS
A3: A. The PO is a form/document used by the agency/entity, addressed to supplier, to deliver specific quantities of supplies/goods/property subject to the terms and conditions contained in the PO.
A4: B. This form shall be accomplished as follows:
B5: 1. Entity Name - name of the agency/entity
B6: 2. Supplier/Address/TIN - name, address and TIN of the supplier
B7: 3. P.O. No. - the number assigned to the PO which shall be as follows:
C8: 0000-00-0000 | E8: Serial number (one series for each year)
E9: Month
E10: Year
B11: 4. Date - date of the preparation of the PO
B12: 5. Mode of Procurement - mode of procurement such as public bidding, through Procurement Service, limited source bidding, direct contracting, repeat order, shopping and negotiated procurement in accordance with RA 9184
B13: 6. Place/Date of Delivery - place of delivery and definite date/s of delivery; if not stated, the date of delivery shall mean seven (7) calendar days after the receipt of PO by the supplier
B14: 7. Delivery Term - delivery term i.e., FOB destination, FOB shipping point
B15: 8. Payment Term - specified period required when the delivered goods shall be paid and discounts, if any, such as 2/10, n/30
B16: 9. Stock/Property No. - stock/property number of the goods to be purchased as provided by the Supply and/or Property Division Unit
B17: 10. Unit - unit of measurement of the supplies/goods/property being procured (i.e. piece, roll, box, reams, etc.)
B18: 11. Description - brief description of the supplies/goods/property being procured
B19: 12. Quantity - quantity of supplies/goods/property being procured
B20: 13. Unit Cost - cost per unit of the supplies/goods/property being procured
B21: 14. Amount - total amount of the supplies/goods/property being procured (Quantity x Unit Cost)
B22: 15. Penalty Clause - penalty to be imposed by the agency/entity in case of non-compliance with the term, that is, one-tenth (1/10) of one percent (1%) for every day of delay on the undelivered item/s
... B27: 20. ORS/BURSNo., Date and Amount - ORS/BURS number assigned by the Budget Division/Unit, date of the ORS/BURS and the amount of obligation supporting the purchase
A28: C. It shall be prepared in four (4) copies distributed as follows:
B29: Original - to the supplier for conforme to the terms of the PO and as attachment to the DV upon request for payment
B30: Copy 2 - retained by the Supply and/or Property Division Unit for file
B31: Copy 3 - to be submitted to COA within five (5) days after conformity by the supplier
B32: Copy 4 - Supplier's copy

Sheet ChkDocs
B1: PR No.: | C1: 22-040 | D1: -------------------cut here-------------------cut here-------------------cut here-------------------cut here-------------------cut here------------------- | E1: PR No.: | F1: =C1 -> 22-040 | G1: -------------------cut here-------------------cut here-------------------cut here-------------------cut here-------------------cut here------------------- | H1: PR No.: | I1: =C1 -> 22-040
B2: Checklist of Documents Submitted: | E2: Checklist of Documents Submitted: | H2: Checklist of Documents Submitted:
C3: Management Monitoring Slip | F3: Management Monitoring Slip | I3: Management Monitoring Slip
B4: X | C4: Purchase Request | E4: X | F4: Purchase Request | H4: X | I4: Purchase Request
C5: Pre and Post Inspection Report | F5: Pre and Post Inspection Report | I5: Pre and Post Inspection Report
B6: X | C6: OBR | E6: X | F6: OBR | H6: X | I6: OBR
B7: X | C7: BAC Resolution | E7: =B7 -> X | F7: BAC Resolution | H7: =B7 -> X | I7: BAC Resolution
B8: X | C8: Approval of BAC Resolution on SVP | E8: =B8 -> X | F8: Approval of BAC Resolution on SVP | H8: =B8 -> X | I8: Approval of BAC Resolution on SVP
B9: X | C9: RFQ1 | E9: =B9 -> X | F9: RFQ1 | H9: =B9 -> X | I9: RFQ1
B10: X | C10: RFQ2 | E10: =B10 -> X | F10: RFQ2 | H10: =B10 -> X | I10: RFQ2
B11: X | C11: RFQ3 | E11: =B11 -> X | F11: RFQ3 | H11: =B11 -> X | I11: RFQ3
B12: X | C12: Acknowledgment for Request for Quotation | E12: =B12 -> X | F12: Acknowledgment for Request for Quotation | H12: =B12 -> X | I12: Acknowledgment for Request for Quotation
C13: Abstract of Bids | E13: =B13 -> 0 | F13: Abstract of Bids | H13: =B13 -> 0 | I13: Abstract of Bids
B14: X | C14: BAC Resolution for Award | E14: =B14 -> X | F14: BAC Resolution for Award | H14: =E14 -> X | I14: BAC Resolution for Award
B15: X | C15: Approval of Reso. for Award | E15: =B15 -> X | F15: Approval of Reso. for Award | H15: =E15 -> X | I15: Approval of Reso. for Award
B16: X | C16: Letter of Notice | E16: =B16 -> X | F16: Letter of Notice | H16: =B16 -> X | I16: Letter of Notice
B17: X | C17: Notice to Proceed | E17: =B17 -> X | F17: Notice to Proceed | I17: Notice to Proceed
B18: X | C18: Certification of BAC | E18: =B18 -> X | F18: Certification of BAC | H18: =B18 -> X | I18: Certification of BAC
C19: Waste Materials Report/Pre & Post Repair Inspection | E19: =B19 -> 0 | F19: Waste Materials Report/Pre & Post Repair Inspection | H19: =B19 -> 0 | I19: Waste Materials Report/Pre & Post Repair Inspection
B20: X | C20: Purchase Order (PO) | E20: =B20 -> X | F20: Purchase Order (PO) | H20: =B20 -> X | I20: Purchase Order (PO)
B21: X | C21: Charge/Sales Invoice | E21: =B21 -> X | F21: Charge/Sales Invoice | H21: =B21 -> X | I21: Charge/Sales Invoice
B22: X | C22: IAR | E22: X | F22: IAR | H22: X | I22: IAR
C23: Inventory Custodian Slip (ICS) | E23: =B23 -> 0 | F23: Inventory Custodian Slip (ICS) | H23: =B23 -> 0 | I23: Inventory Custodian Slip (ICS)
B24: X | C24: RIS | E24: X | F24: RIS | H24: X | I24: RIS
C25: (3)ARE # 221111LLB,DRD,AAM-ARE | F25: =C25 -> (3)ARE # 221111LLB,DRD,AAM-ARE | H25: =B25 -> 0 | I25: =C25 -> (3)ARE # 221111LLB,DRD,AAM-ARE
B26: X | C26: PhilGEPS Bid Notice Abstract ref #8607137 | E26: =B26 -> X | F26: =C26 -> PhilGEPS Bid Notice Abstract ref #8607137 | H26: =B26 -> X | I26: =C26 -> PhilGEPS Bid Notice Abstract ref #8607137
C27: MOA | F27: MOA | I27: MOA
B28: X | C28: PPMP for CY2021 | E28: =B28 -> X | F28: =C28 -> PPMP for CY2021 | H28: =B28 -> X | I28: =C28 -> PPMP for CY2021
C29: Attendance Sheet | E29: =B29 -> 0 | F29: Attendance Sheet | H29: =B29 -> 0 | I29: Attendance Sheet
C30: Recipient of load | E30: =B30 -> 0 | F30: Recipient of load | H30: =B30 -> 0 | I30: Recipient of load
B31: Received by: | E31: Received by: | H31: Received by:
C33: (Signature over Printed Name/Date) | F33: (Signature over Printed Name/Date) | I33: (Signature over Printed Name/Date)
B34: Note: Please return one (1) copy to Supply section for filing purposes. Thank you. | E34: Note: Please return one (1) copy to Supply section for filing purposes. Thank you. | H34: Note: Please return one (1) copy to Supply section for filing purposes. Thank you.
B35: SS Form 14/001 (A) | E35: SS Form 14/001 (B) | H35: SS Form 14/001©
D36: "
B40: +

Sheet Abstract (Failed)
B2: ABSTRACT OF QUOTATIONS
B4: (x) Furnishing/delivery of supplies, and materials or equipment | G4: Bids opened at Basco, Batanes
B5: ( x ) Furnishing Labor, services, etc. | I5: =NOW() -> 46148.741
B6: ( ) Rental or use of transportation facilities equipment, quarters, rooms, lot or space, etc.
B8: To be furnished at the | D8: BATANES STATE COLLEGE
D9: (State place or site of Office or project where articles or services be furnished or returned)
A11: NAME OF ARTICLES OR SERVICES TO BE FURNISHED, RENDERED OR FACILITIES TO BE RENTED
F14: JPM Gen. Mdse. & Hardware | K14: JPM Gen. Mdse. & Hardware | M14: JPM Gen. Mdse. & Hardware
F15: Thine-line Trading | K15: Thine-line Trading | M15: Thine-line Trading
F16: J-Tech Trading & Services | K16: J-Tech Trading & Services | M16: J-Tech Trading & Services
F17: Mulong Ydel | K17: Mulong Ydel | M17: Mulong Ydel
F18: MDAC Trading & Compuserve | K18: MDAC Trading & Compuserve | M18: MDAC Trading & Compuserve
F19: FVA Gen Mdse & Construction Supply | K19: FVA Gen Mdse & Construction Supply | M19: FVA Gen Mdse & Construction Supply
F20: MKM Hardware | K20: MKM Hardware | M20: MKM Hardware
F21: GDP Trading | K21: GDP Trading | M21: GDP Trading
F22: EA Amboy Gen Mdse | K22: EA Amboy Gen Mdse | M22: EA Amboy Gen Mdse
F23: L & R's Hontomin Gen Mdse | K23: L & R's Hontomin Gen Mdse | M23: L & R's Hontomin Gen Mdse
F24: Davocol's Gen. Mdse. | K24: Davocol's Gen. Mdse. | M24: Davocol's Gen. Mdse.
F25: RCJ Hardware & Gen Mdse | K25: RCJ Hardware & Gen Mdse | M25: RCJ Hardware & Gen Mdse
... F86: Valiente Food Producer | K86: Valiente Food Producer | M86: Valiente Food Producer
F87: YCA Office Supplies & Equipment | G87: Apostol General Merchandise | H87: CMVILL Trading | I87: JPM General Merchandise & Hardware | J87: One-Touch Technology Trading | L87: MDAC Trading & Compuserve | M87: J-Tech Trading & Services
A89: =PR!D16 -> Health Insurance Coverage: Accidental Death & Disablement,Unprovoked Murder & Assault Medical Expense or Reimbursement,Burial Benefits due to Accident/Natural Death,Daily Hospital Benefits due to Accident or illness,Dengue Cash Assistance,Ambulance Cash Assistance,Fire Cash Assistance,COVID-19 Cash Assistance for "Death Only",Combined Single Limit for Bodily Injury & Property Damage within premises of the school campus | F89: 5600 | G89: none | H89: 5000 | I89: 4000 | J89: none | L89: 200000 | M89: none
A90: =PR!D17 -> 0 | F90: 1800 | G90: 1600 | H90: 2000 | I90: 1400 | J90: none
A91: =PR!D18 -> 0 | F91: 1800 | G91: 2500 | H91: 2850 | I91: 3000 | J91: none
A92: =PR!D19 -> 0 | F92: 1700 | G92: 1360 | H92: none | I92: none | J92: none
A93: =PR!D20 -> 0 | F93: 3600 | G93: 3360 | H93: 3960 | I93: 3860 | J93: none
A102: =PR!D29 -> 0 | F102: 460 | G102: 800 | H102: none
A103: =PR!D30 -> 0 | F103: 12950 | G103: 13300 | H103: none
A104: =PR!D31 -> 0 | F104: 490 | G104: 600 | H104: none
A105: =PR!D32 -> 0 | F105: none | G105: 150 | H105: none
A106: =PR!D33 -> 0 | F106: 3500 | G106: 3750 | H106: none
A107: =PR!D34 -> 0 | F107: 3180 | G107: 2800 | H107: none
A108: =PR!D35 -> 0 | F108: 360 | G108: 200 | H108: none
A109: =PR!D36 -> 0 | F109: 1440 | G109: 800 | H109: none
A110: =PR!D37 -> 0 | F110: 3350 | G110: none | H110: none
A111: =PR!D38 -> 0 | F111: 530 | G111: 780 | H111: none
A112: =PR!D39 -> Rotary Hammer 850 W 3-Mode Function, with Drill Bit & Chisel included, 220V-240V | F112: 260 | G112: 300 | H112: none
A113: =PR!D40 -> Rotary Hammer 28mm, 1300W with Drill Bit & Chisel included, 220V-240V | F113: 300 | G113: 200 | H113: none
A114: =PR!D41 -> 45-135˚ Multi Angel Miter Shear Cutter, Adjustable angle cutter for cutting plastic, PVC & Molding Trim | F114: 360 | G114: 400 | H114: none
A115: =PR!D42 -> U Type Edge trimming scissor 45 degrees 90 degrees Trunking Pliers (Large Edge Clamp) | F115: 980 | G115: 700 | H115: none
A116: =PR!D43 -> U Type Edge trimming scissor 45 degrees 90 degrees Trunking Pliers (Small size Edge Clamp) | F116: 70 | G116: 100 | H116: none
A117: =PR!D44 -> 9000KPA Portable Pressure Washer set: with Pressure Gauge & Adjustable Pressure, PW Gun, High Pressure Hose, Water Inlet connector & filter, Foam spray bottle | F117: 100 | G117: 200 | H117: none
A118: =PR!D45 -> Electric Air Blower 650W Hand Dust Cleaner Blow Machine, 650W - AB6038, Dust Bag Included, Max Blowing Rate 0-4.0m/min., input power 650W | F118: 1260 | G118: 1400 | H118: none
A119: =PR!D46 -> Aircon Coli Cleaner | F119: 5850 | G119: 5850 | H119: none
A120: =PR!D47 -> Aircon Fin Straightener/Fin Comb, Condenser Evaporator Fin | F120: 380 | G120: 400 | H120: none
A121: =PR!D48 -> 2 Liter Hand Pressure Pump Sprayer (LTGT2000HSX) | F121: 70 | G121: 100 | H121: none
A122: =PR!D49 -> 5L Shoulder Hand-Operated Sprayer (LTGT5000PSX) | F122: 485 | G122: none | H122: none
A123: =PR!D50 -> Wet & Dry Vaccuum Cleaner, 3 in 1 Carpet Extractor Cleaner, Power: 1034 W, Voltage: 230 v, 40 Liter | F123: 350 | G123: 600 | H123: none
A131: =DATA!I1232 -> 0 | B131: Bond paper, A4 size | C131: Bond paper, A4 size | D131: Bond paper, A4 size | E131: Bond paper, A4 size | F131: =DATA!O1232 -> 0 | G131: none | H131: 881.1 | I131: none | K131: none
A132: =DATA!I1233 -> 0 | B132: Bond paper, A4 size | C132: Bond paper, A4 size | D132: Bond paper, A4 size | E132: Bond paper, A4 size | F132: =DATA!O1233 -> 0 | G132: none | H132: 4699.2 | I132: none | K132: none
A133: =DATA!I1234 -> 0 | B133: Bond paper, A4 size | C133: Bond paper, A4 size | D133: Bond paper, A4 size | E133: Bond paper, A4 size | F133: =DATA!O1234 -> 0 | G133: none | H133: 4307.6 | I133: none | K133: none
A134: =DATA!I1235 -> 0 | B134: Bond paper, A4 size | C134: Bond paper, A4 size | D134: Bond paper, A4 size | E134: Bond paper, A4 size | F134: =DATA!O1235 -> 0 | G134: none | H134: 3328.6 | I134: none | K134: none
A135: =DATA!I1236 -> 0 | B135: Bond paper, A4 size | C135: Bond paper, A4 size | D135: Bond paper, A4 size | E135: Bond paper, A4 size | F135: =DATA!O1236 -> 0 | G135: none | H135: 7440.4 | I135: none | K135: none
A136: =DATA!I1237 -> 0 | B136: Bond paper, A4 size | C136: Bond paper, A4 size | D136: Bond paper, A4 size | E136: Bond paper, A4 size | F136: =DATA!O1237 -> 0 | G136: none | H136: 14293.4 | I136: none | K136: none
A137: =DATA!I1238 -> 0 | B137: Bond paper, A4 size | C137: Bond paper, A4 size | D137: Bond paper, A4 size | E137: Bond paper, A4 size | F137: =DATA!O1238 -> 0 | G137: none | H137: 7048.8 | I137: none | K137: none
A138: =DATA!I1239 -> 0 | B138: Bond paper, A4 size | C138: Bond paper, A4 size | D138: Bond paper, A4 size | E138: Bond paper, A4 size | F138: =DATA!O1239 -> 0 | G138: none | H138: 13706 | I138: none | K138: none
A139: =DATA!I1240 -> 0 | B139: Bond paper, A4 size | C139: Bond paper, A4 size | D139: Bond paper, A4 size | E139: Bond paper, A4 size | F139: =DATA!O1240 -> 0 | G139: none | H139: 7832 | I139: none | K139: none
A140: =DATA!I1241 -> 0 | B140: Bond paper, A4 size | C140: Bond paper, A4 size | D140: Bond paper, A4 size | E140: Bond paper, A4 size | F140: =DATA!O1241 -> 0 | G140: none | H140: 7538.3 | I140: none | K140: none
A141: =DATA!I1242 -> 0 | B141: Bond paper, A4 size | C141: Bond paper, A4 size | D141: Bond paper, A4 size | E141: Bond paper, A4 size | F141: =DATA!O1242 -> 0 | G141: none | H141: 2349.6 | I141: none | K141: none
A142: =DATA!I1243 -> 0 | B142: Bond paper, A4 size | C142: Bond paper, A4 size | D142: Bond paper, A4 size | E142: Bond paper, A4 size | F142: =DATA!O1243 -> 0 | G142: none | H142: 1958 | I142: none | K142: none
... A149: =DATA!I1250 -> 0 | B149: Bond paper, A4 size | C149: Bond paper, A4 size | D149: Bond paper, A4 size | E149: Bond paper, A4 size | F149: =DATA!O1250 -> 0 | G149: none | H149: 15566.1 | I149: none | K149: none
A150: =DATA!I1251 -> 0 | B150: Bond paper, A4 size | C150: Bond paper, A4 size | D150: Bond paper, A4 size | E150: Bond paper, A4 size | F150: =DATA!O1251 -> 0
A151: =DATA!I1252 -> 0 | B151: Bond paper, A4 size | C151: Bond paper, A4 size | D151: Bond paper, A4 size | E151: Bond paper, A4 size | F151: =DATA!O1252 -> 0
A152: =DATA!I1253 -> 0 | B152: Bond paper, A4 size | C152: Bond paper, A4 size | D152: Bond paper, A4 size | E152: Bond paper, A4 size | F152: =DATA!O1253 -> 0
A153: =DATA!I1254 -> 0 | B153: Bond paper, A4 size | C153: Bond paper, A4 size | D153: Bond paper, A4 size | E153: Bond paper, A4 size | F153: =DATA!O1254 -> 0
A154: =DATA!I1255 -> 0 | B154: Bond paper, A4 size | C154: Bond paper, A4 size | D154: Bond paper, A4 size | E154: Bond paper, A4 size | F154: =DATA!O1255 -> 0 | G154: 17000 | I154: 17000
A155: =DATA!I1256 -> 0 | B155: Bond paper, A4 size | C155: Bond paper, A4 size | D155: Bond paper, A4 size | E155: Bond paper, A4 size | F155: =DATA!O1256 -> 0 | G155: 1500 | I155: 1500
A156: =DATA!I1257 -> 0 | B156: Bond paper, A4 size | C156: Bond paper, A4 size | D156: Bond paper, A4 size | E156: Bond paper, A4 size | F156: =DATA!O1257 -> 0 | G156: 880 | I156: 880
A157: =DATA!I1258 -> 0 | B157: Bond paper, A4 size | C157: Bond paper, A4 size | D157: Bond paper, A4 size | E157: Bond paper, A4 size | F157: =DATA!O1258 -> 0 | G157: 180 | I157: 180
A158: =DATA!I1259 -> 0 | B158: Bond paper, A4 size | C158: Bond paper, A4 size | D158: Bond paper, A4 size | E158: Bond paper, A4 size | F158: =DATA!O1259 -> 0 | G158: 360 | I158: 360
F159: =DATA!O1260 -> 0 | G159: 900 | I159: 900
F160: =DATA!O1261 -> 0 | G160: 900 | I160: 900
F161: =DATA!O1262 -> 0 | G161: 925 | I161: 925
F162: =DATA!O1263 -> 0 | G162: 9300 | I162: 9300
F163: =DATA!O1264 -> 0 | G163: 32000 | I163: 32000
F164: =DATA!O1265 -> 0 | G164: 9900 | I164: 9900
F165: =DATA!O1266 -> 0 | G165: 400 | I165: 400
F166: =DATA!O1267 -> 0 | G166: 1500 | I166: 1500
F167: =DATA!O1268 -> 0 | G167: 9950 | I167: 9950
F168: =DATA!O1269 -> 0 | G168: 1440 | I168: 1440
F169: =DATA!O1270 -> 0
F170: =DATA!O1271 -> 0
F171: =DATA!O1272 -> 0
F172: =DATA!O1273 -> 0
F173: =DATA!O1274 -> 0
F174: =DATA!O1275 -> 0
F175: =DATA!O1276 -> 0
F176: =DATA!O1277 -> 0
F177: =DATA!O1278 -> 0
F178: =DATA!O1279 -> 0
F179: =DATA!O1280 -> 0
F180: =DATA!O1281 -> 0
... F190: =DATA!O1291 -> 0
A191: ='[2]SourceData 2022'!H423 -> ipatropium bromide+salbutamol sulfate 200mcg/1mg/ml | F191: =DATA!O1292 -> 0
A192: ='[2]SourceData 2022'!H424 -> Salbutamol 2mg/tablet | F192: =DATA!O1293 -> 0
A193: ='[2]SourceData 2022'!H425 -> salbutamol inhaler 100mcg/dose | F193: =DATA!O1294 -> 0
A194: ='[2]SourceData 2022'!H426 -> salbutamol+fluticasone inhaler 25mcg/125mcg meter dose inhaler | F194: =DATA!O1295 -> 0
A195: ='[2]SourceData 2022'!H427 -> zinc oxide +calamine ointment 3.5g | F195: =DATA!O1296 -> 0
A196: ='[2]SourceData 2022'!H428 -> cinnarizine 25mg/tablet | F196: =DATA!O1297 -> 0
A197: ='[2]SourceData 2022'!H429 -> povidone iodine 60ml | F197: =DATA!O1298 -> 0
...

Sheet AResoSVP -Emergency
A1: BATANES STATE COLLEGE
A2: Basco, Batanes
A4: Approval of BAC Resolution Recommending Emergency Procurement of the Project: Supply and Installation of 50KVA Transformer
B6: BAC Resolution No. | D6: =PR!B12 -> 2507-SS02-251
A8: WHEREAS, Section 53 Rule XVI of the Revised Implementing Rules and Regulations of RA 9184
A9: allows Negotiated Mode of Procurement subject to prior approval of the HOPE thru Annual
A10: Procurement Plan (APP) and only to promote economy and efficiency;
A12: WHEREAS, Section 53.2 allows Emergency Cases in case of imminent danger to life or property
A13: during state of calamity, or when time is of the essence arising from natural or man-made calamities or other
A14: causes where immediate action is necessary to prevent damage to or loss of life or property, or to
A15: restore vital public services, infrastructure facilities and other public utilities;
A17: WHEREAS, "Annex H" of the Consolidated Guidelines for Emergency Cases prescribed under
A18: Section V, Paragraph D.2.b.,upon submission of request and other supporting documents identifying
A19: the emergency sought to be addressed, the BAC shall prepare the appropriate procurement
A20: documents and directly negotiate with a supplier, contractor, or consultant with technical, legal and
A21: financial capability to deliver the goods, execute the works and perform the services to address the emergency;
... A24: the HOPE, upon the recommendation of the BAC, shall immediately award the contract to the Supplier, Contractor or Consultant;
A25: WHEREAS, Purchase Request No. | D25: =PR!E9 -> 2025-251 | E25: involves the procurement of
A26: =PR!B111 -> health insurance
A27: with the Approved Budget of | D27: =PR!H110 -> 180000
A28: WHEREAS, the default mode of evaluation shall be on a lot basis which means that the
A29: determination of the single/lowest calculated and responsive bid (S/LCRB) is the total amount of offered
A30: unit price multiply by the required quantity;
A32: NOW THEREFORE, I, DR.DJOVI R. DURANTE, Director for Admin & Finance Services by virtue of
A33: the authority vested in me by the Board of Trustees of this Institution and after taking into consideration
A34: the merits and legal bases of the recommendation of the members of the Bids and Awards Committee (BAC)
A35: do hereby APPROVE the foregoing recommendation and adoption of Negotiated Mode of Procurement
A36: under Emergency Case;
A38: APPROVED FINALLY, at the Batanes State College, this | F38: ___________________
B41: DJOVI REGALA DURANTE,DPA
B42: SUC President I
A47: BRYAN H. CIELO
A48: DELMA G. MALUPA-ABAD
A49: EDWIN F.MACABALLUG, Ph.D.
A50: LIEZL P. DELA CRUZ
A51: RODERICK Y. ABAD
A52: VILMA D. BACCAY
A53: ESTEBAN C. BADAJOS
A54: LEOBERT L. BANZALI
A55: MIAH DAPHNIE B. BUENAFE
A56: GLORIA N. CABIZON
A57: FORTUNATO PHILIP A. CABUGAO
A58: RICARDO Q. CABUGAO, JR.
... A103: EMILYN D. ALUETA

Sheet ResoSVP -Emergency
A1: BATANES STATE COLLEGE
A2: Basco, Batanes
A4: BAC Resolution Recommending Emergency Procurement of the Project: Supply and Installation of 50KVA Transformer
B6: BAC Resolution No. | D6: =PR!B12 -> 2507-SS02-251
A8: WHEREAS, Section 53 Rule XVI of the Revised Implementing Rules and Regulations of RA 9184
A9: allows Negotiated Mode of Procurement subject to prior approval of the HOPE thru Annual
A10: Procurement Plan (APP) and only to promote economy and efficiency;
A12: WHEREAS, Section 53.2 allows Emergency Cases in case of imminent danger to life or property
A13: during state of calamity, or when time is of the essence arising from natural or man-made calamities or other
A14: causes where immediate action is necessary to prevent damage to or loss of life or property, or to
A15: restore vital public services, infrastructure facilities and other public utilities;
A17: WHEREAS, "Annex H" of the Consolidated Guidelines for Emergency Cases prescribed under
A18: Section V, Paragraph D.2.b.,upon submission of request and other supporting documents identifying
A19: the emergency sought to be addressed, the BAC shall prepare the appropriate procurement
A20: documents and directly negotiate with a supplier, contractor, or consultant with technical, legal and
A21: financial capability to deliver the goods, execute the works and perform the services to address the emergency;
... A24: the HOPE, upon the recommendation of the BAC, shall immediately award the contract to the Supplier, Contractor or Consultant;
A25: WHEREAS, Purchase Request No. | D25: =PR!E9 -> 2025-251 | E25: involves the procurement of
A26: =PR!B111 -> health insurance
A27: with the Approved Budget of | D27: =PR!H110 -> 180000
A28: WHEREAS, the default mode of evaluation shall be on a lot basis which means that the
A29: determination of the single/lowest calculated and responsive bid (S/LCRB) is the total amount of offered
A30: unit price multiply by the required quantity;
A32: NOW THEREFORE, we, the members of the Bids and Awards Committee hereby RESOLVE to recommend to the HOPE to adopt Negotiated Mode of Procurement under Emergency Cases for the said transaction;
A33: RESOLVED FINALLY, at the Batanes State College, this
A34: Recommending Approval:
A37: RHOUPHELINE AYA A. CADIZ | C37: RANDALL G. CASTILLO | E37: EMILYN D. ALUETA
A38: BAC Member | C38: BAC Member | E38: BAC Member
A41: =PR!B115 -> JENNY S. ALINA | C41: FORTUNATO PHILIP A. CABUGAO | E41: DOREEN C. CASTILLO
A42: End-User/Provisional Member | C42: BAC Vice Chairperson | E42: BAC Chairperson
A47: BRYAN H. CIELO
A48: DELMA G. MALUPA-ABAD
A49: EDWIN F.MACABALLUG, Ph.D.
A50: LIEZL P. DELA CRUZ
A51: RODERICK Y. ABAD
A52: VILMA D. BACCAY
A53: ESTEBAN C. BADAJOS
A54: LEOBERT L. BANZALI
A55: MIAH DAPHNIE B. BUENAFE
A56: GLORIA N. CABIZON
A57: FORTUNATO PHILIP A. CABUGAO
A58: RICARDO Q. CABUGAO, JR.
... A103: EMILYN D. ALUETA

Sheet ResoSoSVP(Direct Contracting)
A1: BATANES STATE COLLEGE
A2: Basco, Batanes
A4: BAC Resolution Recommending Alternative Mode of Procurement under Direct Contracting for the Blank TOR Paper
B6: BAC Resolution No. | D6: =PR!B12 -> 2507-SS02-251
A8: WHEREAS, Rule XVI of the Revised Implementing Rules and Regulations of RA 9184
A9: allows Alternative Mode of Procurement subject to prior approval of the HOPE thru Annual
A10: Procurement Plan (APP) and only to promote economy and efficiency;
A12: WHEREAS, Section 50(c) allows Direct Contracting in cases where Procuring Entity intends to procure
A13: goods form an exclusive local manufacturer, supplier, distributor, or dealer for which no suitable
A14: substitute can be obtained at more advantageous terms to the GoP.
A16: WHEREAS, "Annex H" of the Consolidated Guidelines for Direct Contracting prescribed under
A17: Section V, Paragraph A.2.,upon submission of request and other supporting documents
A18: the BAC shall prepare the RFQ or pro-forma invoice together with the term and conditions of sale,
A19: and shall send the same to the identified direct supplier.
A20: WHEREAS, the BAC shall ensure that the supplier is technically, legally and financially capable
A21: to deliver the goods at the most advantageous price and contract for the Government
... A24: contract to the Supplier, Contractor or dealer.
A25: WHEREAS, Purchase Request No. | D25: =PR!E9 -> 2025-251 | E25: involves the procurement of
A26: =PR!B111 -> health insurance
A27: with the Approved Budget of | D27: =PR!H110 -> 180000
A28: WHEREAS, the default mode of evaluation shall be on a lot basis which means that the
A29: determination of the single/lowest calculated and responsive bid (S/LCRB) is the total amount of offered
A30: unit price multiply by the required quantity;
A32: NOW THEREFORE, we, the members of the Bids and Awards Committee hereby RESOLVE to recommend to the HOPE to adopt Negotiated Mode of Procurement under Direct Contracting for the said transaction;
A33: RESOLVED FINALLY, at the Batanes State College, this
A34: Recommending Approval:
A37: RHOUPHELINE AYA A. CADIZ | C37: RANDALL G. CASTILLO | E37: EMILYN D. ALUETA
A38: BAC Member | C38: BAC Member | E38: BAC Member
A41: =PR!B115 -> JENNY S. ALINA | C41: FORTUNATO PHILIP A. CABUGAO | E41: DOREEN C. CASTILLO
A42: End-User/Provisional Member | C42: BAC Vice Chairperson | E42: BAC Chairperson
A47: BRYAN H. CIELO
A48: DELMA G. MALUPA-ABAD
A49: EDWIN F.MACABALLUG, Ph.D.
A50: LIEZL P. DELA CRUZ
A51: RODERICK Y. ABAD
A52: VILMA D. BACCAY
A53: ESTEBAN C. BADAJOS
A54: LEOBERT L. BANZALI
A55: MIAH DAPHNIE B. BUENAFE
A56: GLORIA N. CABIZON
A57: FORTUNATO PHILIP A. CABUGAO
A58: RICARDO Q. CABUGAO, JR.
... A103: EMILYN D. ALUETA

Sheet AResoSoSVP(Direct Contractin (2
A1: BATANES STATE COLLEGE
A2: Basco, Batanes
A4: Approval of BAC Resolution Recommending Alternative Mode of Procurement under Direct Contracting for Blank TOR Paper
B6: BAC Resolution No. | D6: =PR!B12 -> 2507-SS02-251
A8: WHEREAS, Rule XVI of the Revised Implementing Rules and Regulations of RA 9184
A9: allows Alternative Mode of Procurement subject to prior approval of the HOPE thru Annual
A10: Procurement Plan (APP) and only to promote economy and efficiency;
A12: WHEREAS, Section 50(c) allows Direct Contracting in cases where Procuring Entity intends to procure
A13: goods form an exclusive local manufacturer, supplier, distributor, or dealer for which no suitable
A14: substitute can be obtained at more advantageous terms to the GoP.
A16: WHEREAS, "Annex H" of the Consolidated Guidelines for Direct Contracting prescribed under
A17: Section V, Paragraph A.2.,upon submission of request and other supporting documents
A18: the BAC shall prepare the RFQ or pro-forma invoice together with the term and conditions of sale,
A19: and shall send the same to the identified direct supplier.
A20: WHEREAS, the BAC shall ensure that the supplier is technically, legally and financially capable
A21: to deliver the goods at the most advantageous price and contract for the Government
... A24: contract to the Supplier, Contractor or dealer.
A25: WHEREAS, Purchase Request No. | D25: =PR!E9 -> 2025-251 | E25: involves the procurement of
A26: =PR!B111 -> health insurance
A27: with the Approved Budget of | D27: =PR!H110 -> 180000
A28: WHEREAS, the default mode of evaluation shall be on a lot basis which means that the
A29: determination of the single/lowest calculated and responsive bid (S/LCRB) is the total amount of offered
A30: unit price multiply by the required quantity;
A32: NOW THEREFORE, I, DR.DJOVI R. DURANTE, Director for Admin & Finance Services by virtue of
A33: the authority vested in me by the Board of Trustees of this Institution and after taking into consideration
A34: the merits and legal bases of the recommendation of the members of the Bids and Awards Committee (BAC)
A35: do hereby APPROVE the foregoing recommendation and adoption of Alternative Mode of Procurement
A36: under Direct Contracting;
A38: APPROVED FINALLY, at the Batanes State College, this | F38: ___________________
B41: DJOVI REGALA DURANTE,DPA
B42: SUC President I
A47: BRYAN H. CIELO
A48: DELMA G. MALUPA-ABAD
A49: EDWIN F.MACABALLUG, Ph.D.
A50: LIEZL P. DELA CRUZ
A51: RODERICK Y. ABAD
A52: VILMA D. BACCAY
A53: ESTEBAN C. BADAJOS
A54: LEOBERT L. BANZALI
A55: MIAH DAPHNIE B. BUENAFE
A56: GLORIA N. CABIZON
A57: FORTUNATO PHILIP A. CABUGAO
A58: RICARDO Q. CABUGAO, JR.
... A103: EMILYN D. ALUETA

Sheet Reso-Repeat Order
A2: BATANES STATE COLLEGE
A3: Basco, Batanes
A5: BAC Resolution Recommending Alternative Mode of Procurement under Small Value Procurement
B7: BAC Resolution No. | D7: =#REF! -> #REF!
A9: WHEREAS, Section 48 Rule XVI of the Revised Implementing Rules and Regulations of RA 9184 allows Alternative Mode of Procurement subject to prior approval of the HOPE thru Annual Procurement Plan (APP) and only to promote economy and efficiency;
A10: WHEREAS, Section 53.9 allows Small Value Procurement provided that the procurement does not fall under shopping in Section 52 of this IRR and the amount involved does not exceed the thresholds prescribed in Annex "H" of this IRR;
A11: WHEREAS, Rule XVI, Section 51., on Repeat Order states this when provided for in the APP, is a method of procurement of goods from the previous winning bidder, whenever there is a need to replenish goods procured under a contract previously awarded through competitive bidding. | H11: c
A12: WHEREAS, Rule XVI, Section 51.,a) A repeat order provides that unit prices of the repeat order must be the same as or lower than those in the original contract: provided, that such prices are still the most advantegous to the GoP after price verification: b) thet the repeat order will not result in splitting of contracts, requisitions, or purchase orders, as provided for in Section 54.1 of this IRR;
A13: WHEREAS, Purchase Request No. | D13: =#REF! -> #REF! | E13: involves the procurement of
A14: =#REF! -> #REF!
A15: =#REF! -> #REF! | D15: =#REF! -> #REF!
A16: WHEREAS, the default mode of evaluation shall be on a lot basis which means that the determination of the single/lowest calculated and responsive bid (S/LCRB) is the total amount of offered unit price multiply by the required quantity;
A18: NOW THEREFORE, we, the members of the Bids and Awards Committee hereby RESOLVE as it is hereby RESOLVED to recommend to the College President to adopt Alternative Mode of Procurement under Small Value Procurement for the said transaction;
A20: RESOLVED FINALLY, at the Batanes State College, this
A21: Recommending Approval:
A24: RHOUPHELINE AYA A. CADIZ | C24: RANDALL G. CASTILLO | E24: EMILYN D. ALUETA
A25: BAC Member | C25: BAC Member | E25: BAC Member
A28: =PR!B115 -> JENNY S. ALINA | C28: FORTUNATO PHILIP A. CABUGAO | E28: DOREEN C. CASTILLO
A29: End-User/Provisional Member | C29: BAC Vice Chairperson | E29: BAC Chairperson
A30: BRYAN H. CIELO
A31: DELMA G. MALUPA-ABAD
A32: EDWIN F.MACABALLUG, Ph.D.
A33: LIEZL P. DELA CRUZ
A34: RODERICK Y. ABAD
A35: VILMA D. BACCAY
A36: ESTEBAN C. BADAJOS
A37: LEOBERT L. BANZALI
A38: MIAH DAPHNIE B. BUENAFE
A39: GLORIA N. CABIZON
A40: FORTUNATO PHILIP A. CABUGAO
A41: RICARDO Q. CABUGAO, JR.
... A83: LEONARDO CABRERA

Sheet AReso-Repeat Order
A1: BATANES STATE COLLEGE
A2: Basco, Batanes
A4: Approval of BAC Resolution Recommending Alternative Mode of Procurement under Small Value Procurement
B6: BAC Resolution No. | D6: =PR!B12 -> 2507-SS02-251
A8: WHEREAS, Section 48 Rule XVI of the Revised Implementing Rules and Regulations of RA 9184 allows Alternative Mode of Procurement subject to prior approval of the HOPE thru Annual Procurement Plan (APP) and only to promote economy and efficiency;
A9: WHEREAS, Section 53.9 allows Small Value Procurement provided that the procurement does not fall under shopping in Section 52 of this IRR and the amount involved does not exceed the thresholds prescribed in Annex "H" of this IRR;
A10: WHEREAS, Appendix 18, Section 3.e on the Guidelines for Shopping and Small Value Procurement provides an Abstract of Quotations shall be prepared setting forth the names of those who responded to the RFQ's right after the deadline for submission except for shopping under Section 52.1(b), where at least three (3) price quotations (RFQ) must be obtained;
A11: WHEREAS, Annex "H" of the Consolidated Guidelines for the Alternative Methods of Procurement prescribed under Section V, Paragraph D.8.b.ii that the BAC shall prepare and send the RFQs/RFPs to at least three (3) suppliers, contractors or consultants of known qualifications where receipt of at least one (1) quotations is sufficient to proceed with the evaluation thererof;
A12: WHEREAS, Purchase Request No. | D12: =PR!E9 -> 2025-251 | E12: involves the procurement of
A13: Presidential Medallion | H13: Items:
A14: with the Approved Budget of | D14: =PR!H110 -> 180000
A15: WHEREAS, the default mode of evaluation shall be on a lot basis which means that the determination of the single/lowest calculated and responsive bid (S/LCRB) is the total amount of offered unit price multiply by the required quantity;
A16: NOW THEREFORE, I,DR.DJOVI R. DURANTE, Head of the Procuring Entity (HOPE) by virtue of the authority vested in me by the Board of Trustees of this Institution and after taking into consideration the merits and legal bases of the recommendation of the members of the Bids and Awards Committee (BAC) do hereby APPROVE the foregoing recommendation and adoption of Alternative Mode of Procurement under Small Value Procurement;
A18: APPROVED FINALLY, at the Batanes State College, this | F18: ___________________
B24: DJOVI REGALA DURANTE,DPA
B25: SUC President I
A30: BRYAN H. CIELO
A31: DELMA G. MALUPA-ABAD
A32: EDWIN F.MACABALLUG, Ph.D.
A33: LIEZL P. DELA CRUZ
A34: RODERICK Y. ABAD
A35: VILMA D. BACCAY
A36: ESTEBAN C. BADAJOS
A37: LEOBERT L. BANZALI
A38: MIAH DAPHNIE B. BUENAFE
A39: GLORIA N. CABIZON
A40: FORTUNATO PHILIP A. CABUGAO
A41: RICARDO Q. CABUGAO, JR.
... A86: EMILYN D. ALUETA

Sheet PO (2)
A2: PURCHASE ORDER | I2: INSTRUCTIONS
A3: Supplier: | B3: =DATA!W114 -> Bethel General Insurance & Surety Corporation | D3: PO No. | F3: 2025-07-251 | I3: specific quantities of supplies/goods/property subject to the terms and conditions contained in the PO.
A4: Address: | B4: Unit 200 Valero Plaza 124 Valero St. Salcedo Village,Makati City | D4: Date | F4: September 9, 2025 | I4: B. This form shall be accomplished as follows:
A5: TIN: | B5: 000-745-041-000 | C5: 000-745-041-000 | E5: Small Value Procurement | J5: 1. Entity Name - name of the agency/entity
B6: 150-214-534 | J6: 2. Supplier/Address/TIN - name, address and TIN of the supplier
A7: Please furnish this office the following articles subject to the term and conditions contained herein: | J7: 3. P.O. No. - the number assigned to the PO which shall be as follows:
A8: Place of Delivery: | C8: Batanes State College | D8: Delivery Term: | F8: FOB Destination | K8: 0000-00-0000 | M8: Serial number (one series for each year)
A9: Date of Delivery: | C9: 30 days upon receipt od PO | D9: Payment Term: | F9: 15 days upon complete delivery | M9: Month
A10: No. | B10: Unit | C10: Description | D10: Qty | E10: Unit Cost | F10: Amount | M10: Year
A11: =RFQ_!A18 -> 001 | B11: =PR!B16 -> pcs | C11: =PR!D16 -> Health Insurance Coverage: Accidental Death & Disablement,Unprovoked Murder & Assault Medical Expense or Reimbursement,Burial Benefits due to Accident/Natural Death,Daily Hospital Benefits due to Accident or illness,Dengue Cash Assistance,Ambulance Cash Assistance,Fire Cash Assistance,COVID-19 Cash Assistance for "Death Only",Combined Single Limit for Bodily Injury & Property Damage within premises of the school campus | D11: =PR!A16 -> 900 | E11: =DATA!N114 -> 130 | F11: =SUM(D11*E11) -> 117000 | J11: 4. Date - date of the preparation of the PO
A12: =RFQ_!A19 -> 002 | B12: =PR!B17 -> 0 | F12: =SUM(D12*E12) -> 0 | J12: 5. Mode of Procurement - mode of procurement such as public bidding, through Procurement Service, limited source bidding, direct contracting, repeat order, shopping and negotiated procurement in accordance with RA 9184
A13: =RFQ_!A20 -> 003 | B13: =PR!B18 -> 0 | F13: =SUM(D13*E13) -> 0 | H13: P | J13: 6. Place/Date of Delivery - place of delivery and definite date/s of delivery; if not stated, the date of delivery shall mean seven (7) calendar days after the receipt of PO by the supplier
A14: =RFQ_!A21 -> 004 | B14: =PR!B19 -> 0 | F14: =SUM(D14*E14) -> 0 | J14: 7. Delivery Term - delivery term i.e., FOB destination, FOB shipping point
A15: =RFQ_!A22 -> 005 | B15: =PR!B20 -> 0 | F15: =SUM(D15*E15) -> 0 | J15: 8. Payment Term - specified period required when the delivered goods shall be paid and discounts, if any, such as 2/10, n/30
A16: =RFQ_!A23 -> 006 | B16: =PR!B21 -> 0 | F16: =SUM(D16*E16) -> 0 | J16: 9. Stock/Property No. - stock/property number of the goods to be purchased as provided by the Supply and/or Property Division Unit
A17: =RFQ_!A24 -> 007 | B17: =PR!B22 -> 0 | F17: =SUM(D17*E17) -> 0 | J17: 10. Unit - unit of measurement of the supplies/goods/property being procured (i.e. piece, roll, box, reams, etc.)
A18: =RFQ_!A25 -> 008 | B18: =PR!B23 -> 0 | F18: =SUM(D18*E18) -> 0 | J18: 11. Description - brief description of the supplies/goods/property being procured
A19: =RFQ_!A26 -> 009 | B19: =PR!B24 -> 0 | F19: =SUM(D19*E19) -> 0 | J19: 12. Quantity - quantity of supplies/goods/property being procured
A20: =RFQ_!A27 -> 010 | B20: =PR!B25 -> 0 | F20: =SUM(D20*E20) -> 0 | J20: 13. Unit Cost - cost per unit of the supplies/goods/property being procured
A21: =RFQ_!A28 -> 011 | B21: =PR!B26 -> 0 | F21: =SUM(D21*E21) -> 0 | J21: 14. Amount - total amount of the supplies/goods/property being procured (Quantity x Unit Cost)
A22: =RFQ_!A29 -> 012 | B22: =PR!B27 -> 0 | F22: =SUM(D22*E22) -> 0 | J22: 15. Penalty Clause - penalty to be imposed by the agency/entity in case of non-compliance with the term, that is, one-tenth (1/10) of one percent (1%) for every day of delay on the undelivered item/s
A23: =RFQ_!A30 -> 013 | B23: =PR!B28 -> 0 | F23: =SUM(D23*E23) -> 0 | J23: 16. Approval - signature over printed name and designation of the Approving Official
A24: =RFQ_!A31 -> 014 | B24: =PR!B29 -> 0 | C24: =PR!D29 -> 0 | D24: =PR!A29 -> 0 | E24: =DATA!N230 -> 850 | F24: =SUM(D24*E24) -> 0 | J24: 17. Conforme - signature over printed name of the supplier or his/her representative signifying his/her approval to the term set by the agency/entity and the date of signing
A25: =RFQ_!A32 -> 015 | B25: =PR!B30 -> 0 | C25: =PR!D30 -> 0 | D25: =PR!A30 -> 0 | E25: =DATA!N231 -> 850 | F25: =SUM(D25*E25) -> 0 | J25: 18. Fund Cluster - fund cluster name/code in accordance with the UACS
A26: =RFQ_!#REF! -> #REF! | B26: =PR!B31 -> 0 | C26: =PR!D31 -> 0 | D26: =PR!A31 -> 0 | E26: =DATA!N232 -> 290 | F26: =SUM(D26*E26) -> 0 | J26: 19. Funds Available - amount of funds available which shall be certified by the Chief Accountant/Head of Accounting Division/Unit
A27: =RFQ_!#REF! -> #REF! | B27: =PR!B32 -> 0 | C27: =PR!D32 -> 0 | D27: =PR!A32 -> 0 | E27: =DATA!N233 -> 100 | F27: =SUM(D27*E27) -> 0 | J27: 20. ORS/BURSNo., Date and Amount - ORS/BURS number assigned by the Budget Division/Unit, date of the ORS/BURS and the amount of obligation supporting the purchase
A28: =RFQ_!#REF! -> #REF! | B28: =PR!B33 -> 0 | C28: =PR!D33 -> 0 | D28: =PR!A33 -> 0 | E28: =DATA!N234 -> 110 | F28: =SUM(D28*E28) -> 0 | I28: C. It shall be prepared in four (4) copies distributed as follows:
A29: =RFQ_!A33 -> 019 | B29: =PR!B34 -> 0 | C29: =PR!D34 -> 0 | D29: =PR!A34 -> 0 | E29: =DATA!N235 -> 5900 | F29: =SUM(D29*E29) -> 0 | J29: Original - to the supplier for conforme to the terms of the PO and as attachment to the DV upon request for payment
A30: 020 | B30: =PR!B35 -> 0 | C30: =PR!D35 -> 0 | D30: =PR!A35 -> 0 | E30: =DATA!N236 -> 13500 | F30: =SUM(D30*E30) -> 0 | J30: Copy 2 - retained by the Supply and/or Property Division Unit for file
A31: 021 | B31: =PR!B36 -> 0 | C31: =PR!D36 -> 0 | D31: =PR!A36 -> 0 | E31: =DATA!N237 -> 150 | F31: =SUM(D31*E31) -> 0 | J31: Copy 3 - to be submitted to COA within five (5) days after conformity by the supplier
A32: 022 | B32: =PR!B37 -> 0 | C32: =PR!D37 -> 0 | D32: =PR!A37 -> 0 | E32: =DATA!N238 -> 1080 | F32: =SUM(D32*E32) -> 0 | J32: Copy 4 - Supplier's copy
A33: 023 | B33: =PR!B38 -> 0 | C33: =PR!D38 -> 0 | D33: =PR!A38 -> 0 | E33: =DATA!N239 -> 5890 | F33: =SUM(D33*E33) -> 0
A34: 024 | B34: =PR!B39 -> bottle | C34: =PR!D39 -> Rotary Hammer 850 W 3-Mode Function, with Drill Bit & Chisel included, 220V-240V | D34: =PR!A39 -> 4 | E34: =DATA!N240 -> 180 | F34: =SUM(D34*E34) -> 720
A35: 025 | B35: =PR!B40 -> bottle | C35: =PR!D40 -> Rotary Hammer 28mm, 1300W with Drill Bit & Chisel included, 220V-240V | D35: =PR!A40 -> 4 | E35: =DATA!N241 -> 40 | F35: =SUM(D35*E35) -> 160
A36: 026 | B36: =PR!B41 -> roll | C36: =PR!D41 -> 45-135˚ Multi Angel Miter Shear Cutter, Adjustable angle cutter for cutting plastic, PVC & Molding Trim | D36: =PR!A41 -> 2 | E36: =DATA!N242 -> 50 | F36: =SUM(D36*E36) -> 100
A37: =RFQ_!A41 -> 026 | B37: =PR!B42 -> roll | C37: =PR!D42 -> U Type Edge trimming scissor 45 degrees 90 degrees Trunking Pliers (Large Edge Clamp) | D37: =PR!A42 -> 3 | E37: =DATA!N243 -> 20 | F37: =SUM(D37*E37) -> 60
A38: =RFQ_!A43 -> 028 | B38: =PR!B43 -> copy | C38: =DATA!I100 -> Principles of Hotel Front Office Operations, Baneji, 2023, 9789351541707, Wiseman's Books Trading | D38: =DATA!J100 -> 1 | E38: =DATA!N244 -> 280 | F38: =SUM(D38*E38) -> 280
A39: =RFQ_!A44 -> 029 | B39: =PR!B44 -> copy | C39: =DATA!I101 -> School and Peer Contexts of Bullying: An Introduction and Exploration, Ramirez, 2024, 9781774698792, Wiseman's Book Trading, Inc. | D39: =DATA!J101 -> 1 | E39: =DATA!N245 -> 480 | F39: =SUM(D39*E39) -> 480
A40: =RFQ_!A45 -> 030 | B40: =PR!B45 -> copy | C40: =DATA!I102 -> Software design, Lal, 2024, 9781774697795, Wiseman's Book Trading, Inc. | D40: =DATA!J102 -> 1 | E40: =DATA!N246 -> 450 | F40: =SUM(D40*E40) -> 450
A41: =RFQ_!A46 -> 031 | B41: =PR!B46 -> 0 | D41: =DATA!J103 -> 1 | E41: =DATA!N247 -> 350 | F41: =SUM(D41*E41) -> 350
A42: =RFQ_!A47 -> 032 | B42: =PR!B47 -> 0 | D42: =DATA!J104 -> 2 | E42: =DATA!N248 -> 45 | F42: =SUM(D42*E42) -> 90
A43: =RFQ_!A48 -> 033 | B43: =PR!B48 -> 0 | D43: =DATA!J105 -> 1 | E43: =DATA!N249 -> 45 | F43: =SUM(D43*E43) -> 45
A44: =RFQ_!A49 -> 034 | B44: =PR!B49 -> 0 | D44: =DATA!J106 -> 1 | E44: =DATA!N250 -> 240 | F44: =SUM(D44*E44) -> 240
A45: =RFQ_!A50 -> 035 | B45: =PR!B50 -> 0 | D45: =DATA!J107 -> 1 | E45: =DATA!N251 -> 20000 | F45: =SUM(D45*E45) -> 20000
A46: =RFQ_!A51 -> 036 | B46: =PR!B51 -> 0 | C46: =DATA!I95 -> Fundamentals of Internet Programming, Ahmad, 2024, 9781774697627, Wiseman's Book Trading, Inc. | D46: =DATA!J108 -> 2 | E46: =DATA!N252 -> 5000 | F46: =SUM(D46*E46) -> 10000
A47: =RFQ_!A52 -> 037 | B47: =PR!B52 -> 0 | C47: =DATA!I96 -> Housekeeping management, Juyal, 2024, 9781774697207, Forefront Book | D47: =DATA!J109 -> 1 | E47: =DATA!N253 -> 28000 | F47: =SUM(D47*E47) -> 28000
