Workbook

Sheet PMR-Data
A2: MONTH | B2: (Multiple Items)
A3: YEAR | B3: (Multiple Items)
A5: PR# | B5: Purpose | C5: End-User | D5: Modality | E5: Delivery Date | F5: IAR Date | G5: Fund Code | H5: Class | I5: Status | J5: Sum of Estimated Total | K5: Sum of Total
A6: 202-013A | B6: supplies for the repair & maintenance of the building | C6: JERSHON RALPH F. CASTANO | D6: SVP | E6: August 23, 2021 | F6: August 23, 2021 | G6: 101 | H6: MOOE | I6: complete | J6: 85520 | K6: 65665
A7: 2021-001A | B7: snacks for the "Internal Quality Audit" on January 19-21, 2021 | J7: 17850 | K7: 17850
A8: 2021-002 | B8: Supply and installation of CCTV for Academic Building, Dormitory and Agriculture Building | C8: ALETH A. MEORA | D8: SVP | E8: April 27, 2021 | F8: May 26, 2021` | G8: 101 | H8: CO | I8: complete | J8: 435000 | K8: 397860
A9: 2021-002A | B9: to be used in the different activities and internet communication needs of BSC | C9: RANDALL G. CASTILLO | D9: SVP | E9: 5/19 & 7/19/2021 | F9: 5/26 & 7/21/2021 | G9: 101 | H9: (blank) | I9: complete | J9: 25500 | K9: 25480
A10: 2021-003 | B10: Purchase of Academic Equipment | C10: ALETH A. MEORA | D10: SVP | E10: 5/19 & 7/19/2021 | F10: 5/19 & 7/21/2021 | G10: 101 | H10: CO | I10: complete | J10: 947218.62 | K10: 928620
A11: 2021-003A | B11: for PBB compliance specifically transparency seal and BSC publication | C11: RANDALL G. CASTILLO | D11: SVP | E11: February 16, 2021 | F11: March 2, 2021 | G11: 165 | H11: MOOE | I11: complete | J11: 49000 | K11: 45560
A12: 2021-004 | B12: for the purchase of Academic Equipments | C12: ALETH A. MEORA | D12: SVP | E12: January 12, 2021 | F12: April 27, 2021 | G12: 101 | H12: CO | I12: complete | J12: 972105.5 | K12: 791000
A13: 2021-004A | B13: for the purchase of enrollment forms | C13: RHEA ANGELLICA B. ADDATU | D13: SVP | E13: August 23, 2021 | F13: August 23, 2021 | G13: 101 | H13: (blank) | I13: (blank) | J13: 22500 | K13: 22500
A14: 2021-005 | B14: Purchase of Academic Equipment | C14: ALETH A. MEORA | D14: SVP | E14: 44396 | F14: 44403 | G14: 101 | H14: CO | I14: reimbursement | J14: 378961.7 | K14: 359780
A15: 2021-005A | B15: to be used in the different activities and internet communication needs of BSC | C15: RANDALL G. CASTILLO | D15: SVP | E15: May 19, 2021 | F15: May 26, 2021 | G15: 101 | H15: MOOE | I15: complete | J15: 30250 | K15: 29960
A16: 2021-006 | B16: Supply and Delivery of Academic Equipment | C16: ALETH A. MEORA | D16: SVP | E16: January 12, 2021 | F16: January 25, 2021 | G16: 101 | H16: CO | I16: complete | J16: 315813.75 | K16: 195700
E17: January 25, 2021 | F17: January 25, 2021 | G17: 101 | H17: CO | I17: complete | J17: 45000 | K17: 42000
A18: 2021-006A | B18: for the ISO Activity Management Review on Feb. 3, 2021 | C18: ROMINA KATRINA C. BAYARAS | D18: SVP | E18: 44230 | F18: February 16, 2021 | G18: 164 | H18: MOOE | I18: complete | J18: 14000 | K18: 11800
A19: 2021-007A | B19: Internet data/Regular load Allocation of Administrative & Finance staff of the college to support online submission of reports & other related activities for the Fiscal Year 2021 | C19: DJOVI R. DURANTE | D19: SVP | E19: March 29, 2021 | F19: March 31, 2021 | G19: 101 | H19: MOOE | I19: complete | J19: 107880 | K19: 107880
A20: 2021-008A | B20: for the "ISO Documentation" | C20: ROMINA KATRINA C. BAYARAS | D20: SVP | E20: March 15, 2021 | F20: March 15, 2021 | G20: 164 | H20: MOOE | I20: complete | J20: 3960 | K20: 3885
A21: 2021-009 | B21: Purchase of Academic Furniture Fixtures | C21: ALETH A. MEORA | D21: SVP | E21: August 23, 2021 | F21: August 23, 2021 | G21: 101 | H21: MOOE | I21: complete | J21: 200000 | K21: 199680
A22: 2021-009A | B22: stamp use for the filing of ISO documents | C22: ROMINA KATRINA C. BAYARAS | D22: SVP | E22: - | F22: - | G22: 165 | H22: (blank) | I22: FAILED | J22: 28000 | K22: 0
A23: 2021-0100 | B23: for the Implementation of "ADOPT through Varied R & D of Ivatan Endemic Resources" research project | C23: JANE S. CASTILLO | D23: SVP | E23: August 23, 2021 | F23: August 23, 2021 | G23: 165 | H23: MOOE | I23: for delivery | J23: 30950 | K23: 29315
A24: 2021-0101 | B24: office supplies for the Administrative & Finance Services Units | C24: DJOVI R. DURANTE | D24: SVP | E24: August 23, 2021 | F24: August 23, 2021 | G24: 165 | H24: MOOE | I24: for delivery | J24: 30840 | K24: 28941.9
A25: 2021-0102 | B25: supplies for Budget office | C25: BRYAN DAVE P. REVILLA | D25: SVP | E25: August 23, 2021 | F25: August 23, 2021 | G25: 101 | H25: MOOE | I25: for delivery | J25: 3500 | K25: 2990
A26: 2021-0103 | B26: supplies for Budget office | C26: BRYAN DAVE P. REVILLA | D26: SVP | E26: July 1, 2021 | F26: July 1, 2021 | G26: 101 | H26: MOOE | I26: complete | J26: 790 | K26: 600
A27: 2021-0104 | B27: supplies for the Budget office | C27: BRYAN DAVE P. REVILLA | D27: SVP | E27: August 23, 2021 | F27: August 23, 2021 | G27: 101 | H27: MOOE | I27: for delivery | J27: 1000 | K27: 800
A28: 2021-0105 | B28: repair of 2 units floor type airconditioner at Faculty Room | C28: JERSHON RALPH F. CASTANO | D28: SVP | E28: August 23, 2021 | F28: August 23, 2021 | G28: (blank) | H28: (blank) | I28: FAILED | J28: 13000
A29: 2021-0106 | B29: GSO Supplies | C29: JERSHON RALPH F. CASTANO | D29: SVP | E29: July 19 & 26, 2021 | F29: July 21 & 26, 2021 | G29: 101 | H29: MOOE | I29: complete | J29: 10950 | K29: 8314
A30: 2021-0107 | B30: GSO Supplies | C30: JERSHON RALPH F. CASTANO | D30: SVP | E30: 44399 | F30: 44411 | G30: 101 | H30: MOOE | I30: reimbursement | J30: 18500 | K30: 15780
A31: 2021-0108 | B31: Snack for the Preparatory Board Meeting on June 25, 2021 at 10:00 a.m | C31: GERZON R. ABAD | D31: SVP | E31: August 23, 2021 | F31: August 23, 2021 | G31: (blank) | H31: (blank) | I31: FAILED | J31: 3000 | K31: 0
A32: 2021-0109 | B32: PM snack and dinner for the 52nd Board of Trustees Meeting on June 25, 2021 | C32: GERZON R. ABAD | D32: SVP | E32: June 25, 2021 | F32: 44377 | G32: 101 | H32: MOOE | I32: reimbursement | J32: 13000 | K32: 9000
A33: 2021-010A | B33: ink use for enrollment | C33: RHEA ANGELLICA B. ADDATU | D33: SVP | E33: August 23, 2021 | F33: August 23, 2021 | G33: 101 | H33: (blank) | I33: FAILED | J33: 1500
A34: 2021-0110 | B34: Lunch, PM Snack and Dinner of Commissioner Lilian A. De Las Llagas and Staff for the 52nd BOT Meeting on 25 June 2021 | C34: GERZON R. ABAD | D34: SVP | E34: August 23, 2021 | F34: August 23, 2021 | G34: (blank) | H34: (blank) | I34: reimbursement | J34: 12597.5 | K34: 12597.5
A35: 2021-0111 | B35: repair & maintenance of A/C units of Registrar's, Cashier's, Accountant's & President's office | C35: JERSHON RALPH F. CASATANO | D35: SVP | E35: August 23, 2021 | F35: August 23, 2021 | G35: 101 | H35: MOOE | I35: on-going | J35: 8000 | K35: 8000
A36: 2021-0112 | B36: supplies for the rewiring of faculty room electrical system | C36: JERSHON RALPH F. CASATANO | D36: SVP | E36: July 21, 2021 | F36: July 26, 2021 | G36: 101 | H36: MOOE | I36: complete | J36: 23700 | K36: 21624
A37: 2021-0113 | B37: for the purchase of Semi-expendable equipments purposes | C37: JERSHON RALPH F. CASATANO | D37: SVP | E37: August 23, 2021 | F37: August 23, 2021 | G37: 101 | H37: MOOE | I37: on-going | J37: 10000 | K37: 10000
A38: 2021-011A | B38: for the Pre Assessment Audit Plan on Feb. 10-11, 2021 | C38: ROMINA KATRINA C. BAYARAS | D38: SVP | E38: February 10-11, 2021 | F38: March 2, 2021 | G38: 164 | H38: MOOE | I38: complete | J38: 7500 | K38: 7125
A39: 2021-012A | B39: supplies for the repair & maintenance of transportation vehicle | C39: JERSHON RALPH F. CASTANO | D39: SVP | E39: March 31, 2021 | F39: April 5, 2021 | G39: 101 | H39: MOOE | I39: on-going | J39: 49399.99 | K39: 42550
A40: 2021-013 | B40: Puchase of drafting tables and chairs for the Academiic Furnitures and Fixtures | C40: ALETH A. MEORA | D40: SVP | E40: January 26, 2021 | F40: January 26, 2021 | G40: 101 | H40: CO | I40: complete | J40: 277500 | K40: 195000
A41: 2021-014A | B41: office machinery & equipment | C41: JERSHON RALPH F. CASTANO | D41: SVP | E41: March 29, 2021 | F41: March 30, 2021 | G41: 101 | H41: MOOE | I41: complete | J41: 47002 | K41: 42500
A42: 2021-015A | B42: supplies for janitorial services | C42: JERSHON RALPH F. CASTANO | D42: SVP | E42: April 15, 2021 | F42: April 15, 2021 | G42: 101 | H42: MOOE | I42: complete | J42: 5000 | K42: 3000
E43: March 30, 2021 | F43: April 15, 2021 | G43: 101 | H43: MOOE | I43: complete | J43: 15000 | K43: 15200
A44: 2021-016A | B44: AM snacks for the meeting on the Assessment of the Conduct of Flexible Learning in the 1st Semester of SY 2020-2021 | C44: ANGELITA H. VARGAS | D44: SVP | E44: February 16, 2021 | F44: March 24, 2021 | G44: 101 | H44: MOOE | I44: complete | J44: 7950 | K44: 7950
A45: 2021-017A | B45: snacks & meals for the Administrative & Finance Conference on the finalization of FY 2021 targets and deliverables | C45: DJOVI R. DURANTE | D45: SVP | E45: February 23, 2021 | F45: March 1, 2021 | G45: 101 | H45: MOOE | I45: complete | J45: 19250 | K45: 16275
A46: 2021-018A | B46: snacks & dinner for the 51st Board meeting on Feb. 24, 2021 | C46: GERZON R. ABAD | D46: SVP | E46: February 24, 2021 | F46: March 9, 2021 | G46: 101 | H46: MOOE | I46: complete | J46: 10200 | K46: 8330
A47: 2021-019A | B47: use for National Women's Month Celebration | C47: JENNY S. ALINA | D47: SVP | E47: March 29, 2021 | F47: March 29, 2021 | G47: 101 | H47: MOOE | I47: complete | J47: 5320 | K47: 5320
A48: 2021-020 | B48: seed propagation for the Production of High Value Crop (HVC) Seess & Seedling in Batanes under the Bayanihan II project | C48: ROMEL A. RATERTA | D48: (blank) | E48: August 23, 2021 | F48: August 23, 2021 | G48: (blank) | H48: (blank) | I48: FAILED | J48: 259100 | K48: 0
A49: 2021-021 | B49: supplies for the National Women's Month Celebration | C49: JENNY S. ALINA | D49: SVP | E49: March 29, 2021 | F49: March 30, 2021 | G49: 101 | H49: MOOE | I49: complete | J49: 1170 | K49: 735
A50: 2021-022 | B50: supplies & materials for the installation of 3 units television | C50: JERSHON RALPH F. CASTANO | D50: (blank) | E50: August 23, 2021 | F50: August 23, 2021 | G50: (blank) | H50: (blank) | I50: FAILED | J50: 4500 | K50: 0
A51: 2021-023 | B51: supplies & materials for the connection of 3 units television | C51: JERSHON RALPH F. CASTANO | D51: (blank) | E51: August 23, 2021 | F51: August 23, 2021 | G51: (blank) | H51: (blank) | I51: FAILED | J51: 5200 | K51: 0
A52: 2021-024 | B52: stamp use for the filing of ISO documents | C52: ROMINA KATRINA C. BAYARAS | D52: SVP | E52: May 7, 2021 | F52: May 19, 2021 | G52: 164 | H52: MOOE | I52: complete | J52: 40000 | K52: 40000
A53: 2021-025 | B53: stamp to be used in the office of the President & Office of the Board Sec | C53: GERZON R. ABAD | D53: SVP | E53: June 2, 2021 | F53: June 10, 2021 | G53: 101 | H53: (blank) | I53: complete | J53: 8000 | K53: 8000
A54: 2021-026 | B54: snacks & lunch for the "Records Management System Echo Seminar on March 23, 2021 | C54: ROMINA KATRINA C. BAYARAS | D54: SVP | E54: April 8, 2021 | F54: April 12, 2021 | G54: 101 | H54: MOOE | I54: complete | J54: 17500 | K54: 14750
A55: 2021-027 | B55: meals & snacks for the FY 2022 Budget Review & Consultation on March 16, 2021 | C55: BRYAN DAVE P. REVILLA | D55: SVP | E55: March 16, 2021 | F55: March 26, 2021 | G55: 101 | H55: MOOE | I55: complete | J55: 7700 | K55: 6930
A56: 2021-028 | B56: for preventive maintenance of BSC ICT Equipment | C56: RANDALL G. CASTILLO | D56: (blank) | E56: August 23, 2021 | F56: August 23, 2021 | G56: (blank) | H56: (blank) | I56: FAILED | J56: 42000 | K56: 0
A57: 2021-029 | B57: for preventive maintenance of BSC ICT Equipment | C57: RANDALL G. CASTILLO | D57: (blank) | E57: August 23, 2021 | F57: August 23, 2021 | G57: (blank) | H57: (blank) | I57: pending | J57: 48250 | K57: 0
A58: 2021-030 | B58: Snacks during the National Women's Month Celebration | C58: JENNY S. ALINA | D58: SVP | E58: March 25, 2021 | F58: May 4, 2021 | G58: 101 | H58: MOOE | I58: complete | J58: 11100 | K58: 10730
A59: 2021-031 | B59: for National Womens Month Celebration activity | C59: JENNY S. ALINA | D59: (blank) | E59: August 23, 2021 | F59: August 23, 2021 | G59: (blank) | H59: (blank) | I59: (blank) | J59: 12750 | K59: 12750
A60: 2021-032 | B60: Snacks and lunch during the Administrative Council meeting on March 31, 2021 | C60: GERZON R. ABAD | D60: SVP | E60: March 31, 2021 | F60: March 31, 2021 | G60: 101 | H60: MOOE | I60: complete | J60: 18200 | K60: 17500
A61: 2021-033 | B61: Snacks and Lunch during the Academic Council meeting on March 30, 2021 | C61: GERZON R. ABAD | D61: SVP | E61: March 30, 2021 | F61: March 30, 2021 | G61: 101 | H61: MOOE | I61: complete | J61: 24700 | K61: 23750
A62: 2021-034 | B62: seed propagation for the Production of High Value Crop (HVC) Seess & Seedling in Batanes under the Bayanihan II project | C62: ROMEL A. RATERTA | D62: SVP | E62: May 31, 2021 | F62: June 10, 2021 | G62: 165 | H62: MOOE | I62: complete | J62: 60000 | K62: 61200
E63: August 23, 2021 | F63: June 10, 2021 | G63: 165 | H63: MOOE | I63: complete | J63: 529100 | K63: 467600
A64: 2021-035 | B64: for the purchase of Semi-Expendable Office Supply purposes | C64: ALETH A. MEORA | D64: (blank) | E64: August 23, 2021 | F64: August 23, 2021 | G64: (blank) | H64: (blank) | I64: FAILED | J64: 55200 | K64: 0
A65: 2021-036 | B65: For the purchase of office equipment | C65: ALETH A. MEORA | D65: (blank) | E65: May 31, 2021 | F65: June 1, 2021 | G65: 101 | H65: (blank) | I65: complete | J65: 85000 | K65: 56025
G66: (blank) | H66: (blank) | I66: complete | J66: 70000 | K66: 43425
A67: 2021-037 | B67: For the purchase of office equipment | C67: ALETH A. MEORA | D67: SVP | E67: June 30, 2021 | F67: July 1, 2021 | G67: 101 | H67: CO | I67: complete | J67: 319140 | K67: 279976.5
A68: 2021-038 | B68: For the purchase of semi-expendable equipment | C68: ALETH A. MEORA | D68: SVP | E68: June 10, 2021 | F68: June 11, 2021 | G68: 101 | H68: MOOE | I68: complete | J68: 637300 | K68: 633015
A69: 2021-039 | B69: for the purchase of Academic furnitures & fixtures purposes | C69: ALETH A. MEORA | D69: Public Bidding | E69: August 23, 2021 | F69: August 23, 2021 | G69: (blank) | H69: (blank) | I69: (blank) | J69: 980000 | K69: 0
A70: 2021-040 | B70: Snacks during the Expanded Finance Committee Meeting on April 13, 2021 | C70: GERZON R. ABAD | D70: SVP | E70: April 13, 2021 | F70: April 22, 2021 | G70: 101 | H70: MOOE | I70: complete | J70: 2550 | K70: 1445
A71: 2021-041 | B71: for back-up and saving documents purposes | C71: ANGELITA H. VARGAS | D71: SVP | E71: 44384 | F71: 44384 | G71: 101 | H71: MOOE | I71: completed | J71: 168000 | K71: 139720
A72: 2021-042 | B72: communication expenses in the implementation of the Learning Continuity Plan | C72: ANGELITA H. VARGAS | D72: SVP | E72: June 9, 2021 | F72: June 29, 2021 | G72: 101 | H72: MOOE | I72: complete | J72: 171680 | K72: 171400
A73: 2021-043 | B73: Supplies and materials for Sports Development | C73: WILLIAM POL M. MAGGAY | D73: SVP | E73: August 23, 2021 | F73: August 23, 2021 | G73: 165 | H73: MOOE | I73: FAILED | J73: 3300 | K73: 0
A74: 2021-044 | B74: supplies/materials use for product development | C74: JANE S. CASTILLO | D74: SVP | E74: May 31 & July 1, 2021 | F74: June 10 & July 1, 2021 | G74: 165 | H74: MOOE | I74: complete | J74: 22625 | K74: 22170
A75: 2021-045 | B75: supplies/materials use for product development | C75: JANE S. CASTILLO | D75: SVP | E75: August 23, 2021 | F75: August 23, 2021 | G75: 165 | H75: MOOE | I75: for delivery | J75: 2000 | K75: 2000
A76: 2021-046 | B76: supplies/materials use for product development | C76: JANE S. CASTILLO | D76: SVP | E76: May 20, 2021 | F76: May 26, 2021 | G76: 165 | H76: MOOE | I76: complete | J76: 4500 | K76: 4500
A77: 2021-047 | B77: supplies/materials use for product development | C77: JANE S. CASTILLO | D77: SVP | E77: May 4, 2021 | F77: May 4, 2021 | G77: 165 | H77: MOOE | I77: complete | J77: 3000 | K77: 2650
A78: 2021-048 | B78: For President's Office use | C78: GERZON R. ABAD | D78: SVP | E78: May 20, 2021 | F78: May 26, 2021 | G78: 101 | H78: MOOE | I78: complete | J78: 3500 | K78: 2900
A79: 2021-049 | B79: Supplies for operational use of the Procurement Office | C79: ANNE MARIELLE V. TEVES | D79: SVP | E79: June 2 & July 7, 2021 | F79: June 10 & July 7, 2021 | G79: 101 | H79: MOOE | I79: partial delivery | J79: 14500 | K79: 14800
E80: August 23, 2021 | F80: August 23, 2021 | G80: 101 | H80: MOOE | I80: for delivery | J80: 22580 | K80: 21860
A81: 2021-050 | B81: replacement of defective HDD of ACER ASPIRE 3 | C81: JERSHON RALPH F. CASTANO | D81: SVP | E81: May 25, 2021 | F81: May 26, 2021 | G81: 101 | H81: MOOE | I81: complete | J81: 4500 | K81: 3800
A82: 2021-051 | B82: for office supplies | C82: WILLIAM JO SE M. BILLOTE | D82: SVP | E82: July 1, 2021 | F82: June 1 & July 1, 2021 | G82: 165 | H82: MOOE | I82: complete | J82: 39000 | K82: 36750
A83: 2021-052 | B83: for office supply | C83: WILLIAM JO SE M. BILLOTE | D83: (blank) | E83: August 23, 2021 | F83: August 23, 2021 | G83: (blank) | H83: (blank) | I83: FAILED | J83: 6000 | K83: 0
A84: 2021-053 | B84: use for office supplies | C84: WILLIAM JO SE M. BILLOTE | D84: SVP | E84: May 26, 2021 | F84: May 26, 2021 | G84: 165 | H84: MOOE | I84: complete | J84: 1450 | K84: 1400
A85: 2021-054 | B85: supplies & equuipment for the installation of split type | C85: JERSHON RALPH F. CASTANO | D85: SVP | E85: August 23, 2021 | F85: August 23, 2021 | G85: 101 | H85: MOOE | I85: on going | J85: 30000 | K85: 28020
A86: 2021-055 | B86: food for the BSC employees during the Tree Planting Activity at "Rakuh A Payaman" in Mahatao, Batanes 7:00am | C86: ANGELITA H. VARGAS | D86: SVP | E86: April 30, 2021 | F86: April 30, 2021 | G86: 101 | H86: MOOE | I86: complete | J86: 25000 | K86: 24900
A87: 2021-056 | B87: communication expenses | C87: XINA V. VINALAY | D87: (blank) | E87: August 23, 2021 | F87: August 23, 2021 | G87: (blank) | H87: (blank) | I87: (blank) | J87: 9880 | K87: 0
A88: 2021-057 | B88: for office supply | C88: ANDREI JOHN S. CORDOVA | D88: SVP | E88: June 2 & July 19, 2021 | F88: June 10 & July 26, 2021 | G88: 165 | H88: MOOE | I88: complete | J88: 13200 | K88: 12390
A89: 2021-058 | B89: snacks & lunch for the 2nd Quarter Performance Review & Regular meeting (May 18, 2021) | C89: DJOVI R. DURANTE | D89: SVP | E89: May 18, 2021 | F89: June 1, 2021 | G89: 101 | H89: MOOE | I89: complete | J89: 15700 | K89: 15400
A90: 2021-059 | B90: to keep update on the development of training/program for sports development | C90: WILLIAM POL M. MAGGAY | D90: SVP | E90: May 25, 2021 | F90: May 26, 2021 | G90: 165 | H90: MOOE | I90: complete | J90: 3300 | K90: 2800
A91: 2021-060 | B91: Use for mailing report of grades to parents, request credentials, Form 137 | C91: MAGDALENA V. BALLES | D91: SVP | E91: July 1, 2021 | F91: July 1, 2021 | G91: 165 | H91: MOOE | I91: for delivery | J91: 3000 | K91: 2950
A92: 2021-061 | B92: lunch & snacks for the Lab-Trip Training on May 6 and 7, 2021 at BSC | C92: FERDINAND BULUSAN | D92: SVP | E92: May 6 & 7, 2021 | F92: 44323 | G92: 165 | H92: MOOE | I92: complete | J92: 10500 | K92: 10425
A93: 2021-062 | B93: for office consumption (office supplies) | C93: WILLIAM JO SE M. BILLOTE | D93: SVP | E93: May 25 & July 5, 2021 | F93: May 26 & July 7, 2021 | G93: 101 | H93: MOOE | I93: complete | J93: 10000 | K93: 6270
A94: 2021-063 | B94: Installation of 2 units grrenhouse (4 x 12 sq. m) | C94: ROMEL A. RATERTA | D94: SVP | E94: August 23, 2021 | F94: August 23, 2021 | G94: (blank) | H94: (blank) | I94: on going | J94: 985000 | K94: 886500
A95: 2021-064 | B95: repair & maintenance of the cables of old 16 channel CCTV located at Supply Office | C95: JERSHON RALPH F. CASTANO | D95: SVP | E95: July 2, 2021 | F95: July 2, 2021 | G95: 101 | H95: MOOE | I95: complete | J95: 29000 | K95: 14860
A96: 2021-065 | B96: materials for the National Higher Education Week Competition (May 17-21, 2021) | C96: ELEIN T. ESPERANZA | D96: SVP | E96: May 17, 2021 | F96: June 1, 2021 | G96: 165 | H96: MOOE | I96: complete | J96: 900 | K96: 318
A97: 2021-066 | B97: materials for the National Higher Education Week Competition (May 17-21, 2021) | C97: ELEIN T. ESPERANZA | D97: SVP | E97: May 14, 2021 | F97: June 7, 2021 | G97: 165 | H97: MOOE | I97: complete | J97: 3420 | K97: 2537
A98: 2021-067 | B98: materials for the National Higher Education Week Competition (May 17-21, 2021) | C98: ELEIN T. ESPERANZA | D98: SVP | E98: August 23, 2021 | F98: August 23, 2021 | G98: (blank) | H98: (blank) | I98: FAILED | J98: 1500 | K98: 0
A99: 2021-068 | B99: materials for the National Higher Education Week Competition (May 17-21, 2021) | C99: ELEIN T. ESPERANZA | D99: SVP | E99: August 23, 2021 | F99: August 23, 2021 | G99: (blank) | H99: (blank) | I99: FAILED | J99: 1050 | K99: 0
A100: 2021-069 | B100: provision of WiFi Modems for internet connectivity (Admin. & Finance units) | C100: DJOVI R. DURANTE | D100: SVP | E100: August 23, 2021 | F100: August 23, 2021 | G100: 101 | H100: MOOE | I100: for delivery | J100: 30000 | K100: 27950
A101: 2021-070 | B101: Health Insurance of students | C101: WILLIAM JO SE M. BILLOTE | D101: SVP | E101: July 1, 2021 | F101: July 2, 2021 | G101: 165 | H101: (blank) | I101: complete | J101: 7500 | K101: 7500
A102: 2021-071 | B102: for the Implementation of "ADOPT through varied R & D of Ivatan Endemic Resources" research project | C102: FERDINAND BULUSAN | D102: SVP | E102: August 23, 2021 | F102: August 23, 2021 | G102: (blank) | H102: (blank) | I102: FAILED | J102: 45400 | K102: 0
...

Sheet FundCodes (2)
A1: CODE | B1: CATEGORY | C1: OFFICE/UNIT | D1: Fund
A2: GAS1 | B2: General Administration Services | C2: Office of the President | D2: 01-101
A3: GAS2 | B3: General Administration Services | C3: Office of the Board Secretary | D3: 05-164
A4: GAS3 | B4: General Administration Services | C4: Office of the College Secretary | D4: 06-162
A5: GAS4 | B5: General Administration Services | C5: Information & Communications Technology Unit | D5: 07-165
A6: GAS5 | B6: General Administration Services | C6: Information Unit
A7: GAS6 | B7: General Administration Services | C7: Internal Audit Unit
A8: GAS7 | B8: General Administration Services | C8: Legal Unit
A9: GAS8 | B9: General Administration Services | C9: Planning Unit
A10: GAS9 | B10: General Administration Services | C10: Project Management Unit
A11: GAS10 | B11: General Administration Services | C11: Quality Assurance Office
A12: GAS11 | B12: General Administration Services | C12: Administrative Office
A13: GAS12 | B13: General Administration Services | C13: Cash Unit
A14: GAS13 | B14: General Administration Services | C14: General Services Unit
A15: GAS14 | B15: General Administration Services | C15: Human Resource Management Unit
A16: GAS15 | B16: General Administration Services | C16: Procurement Unit
A17: GAS16 | B17: General Administration Services | C17: Records Unit
... A46: Acad9 | B46: Director for Instruction | C46: DI
A47: 1005 | B47: Research & Extension Services | C47: Research & Extension Office
A48: 1006 | B48: College Business Affairs Office | C48: CBAO
A49: 1006A | B49: College Assessment Center | C49: College Assessment Center
A50: 1006B | B50: College Business Affairs Office | C50: CBAO-IGP
A51: 1006C | B51: College Business Affairs Office | C51: CBAO-Dorm
A52: 1006D | B52: College Business Affairs Office | C52: CBAO-Hostel

Sheet Suppliers TIN
B1: Business Name | C1: Name/Owner | D1: TIN #
A2: 1 | B2: Apostol General Merchandise | C2: Leo A. Apostol | D2: 183-008-448
A3: 2 | B3: Bartilad's Feeds Trading | C3: Roldan Q. Bartilad | D3: 771-272-422
A4: 3 | B4: Bitstop Network Services Inc. | C4: JC James P. Jihay | D4: 005-931-291
A5: 4 | B5: Casa Del Basco | D5: 107-549-729
A6: 5 | B6: Crisel General Merchandise | C6: Cresencio M. Verana | D6: 135-792-662
A7: 6 | B7: Claire's Drugstore | C7: Claire H. Abad | D7: 264-438-671
A8: 7 | B8: Davocol's General Merchandise | C8: Lilibeth T. Davocol | D8: 116-311-342
A9: 8 | B9: Davocol's Inn | C9: Dan Ardie T. Davocol | D9: 739-884-154
A10: 9 | B10: D' Islands gasoline Station | C10: Lito Doroteo A. Adarme | D10: 124-072-664
A11: 10 | B11: Doque's Congie Hauz | C11: Glenda L. Gordo | D11: 922-904-311
A12: 11 | B12: D. Michael Co Industrial Supply (DMC) Corp. | C12: Eunelyn O. Ramilla | D12: 007-776-953
A13: 12 | B13: E. A. Amboy General Merchandise | C13: Cesar Edgardo Amboy | D13: 928-655-269
A14: 13 | B14: Enrinar Trading | C14: Narcisa Co Melad | D14: 123-394-221
A15: 14 | B15: FMG Trading & Construction Supply | C15: Frederick Gari | D15: 219-884-940
A16: 15 | B16: GDP Trading | C16: George D. Peralta | D16: 150-214-534
A17: 16 | B17: Hubalde's Drugstore | C17: Marilyn G. Hubalde | D17: 914-979-941
A18: 17 | B18: Hudzan Café & Catering Services | C18: Susan Villegas | D18: 290-315-057 | E18: **
A19: 18 | B19: I.B.S Pharmacy & General Merchadise | C19: Dale Anthony C. Gutierrez | D19: 411-599-160
A20: 19 | B20: IAM'J Graphic Design & Printing | C20: Jaycy S. Alina | D20: 318-666-833
A21: 20 | B21: JPM General Merchandise & Hardware | C21: Emma P. Adarme | D21: 160-183-814
A22: 21 | B22: J-Tech Trading & Services | C22: Cecilia C. De Sagon | D22: 933-429-635
A23: 22 | B23: M.G. Hubalde's General Merchandise | C23: Marilyn G. Hubalde | D23: 914-979-941-001
A24: 23 | B24: MDAC Trading & Compuserve | C24: Florescita A. Cruz | D24: 100-194-776
A25: 24 | B25: NRA Hardware | C25: Neil Bernardo Ordas | D25: 196-062-499
A26: 25 | B26: One-Touch Technology Trading | C26: Janice A. Alasco | D26: 283-009-327
A27: 26 | B27: Pension Ivatan | C27: Teresita D. Valiente | D27: 106-115-883
A28: 27 | B28: Sophia Marie Store | C28: Regina B. Gabaldon | D28: 279-057-542
A29: 28 | B29: Twixbiz General Merchandise | C29: Charles B. Domingo | D29: 118-687-531
A30: 29 | B30: Northern Star General Merchandise | C30: Cesar A. Calma | D30: 151-407-774
... A37: 36 | B37: MKM Hardware | C37: Enrique Abuyo Melad Jr. | D37: 148-780-907
A38: 37 | B38: NSGB Books Trading | C38: Nica Sandra Go Banag
A39: 38 | B39: ONPREM2CLOUD IT SOLUTIONS CO. | C39: Emmanuel B. Mamayson | D39: 101-626-582
A40: 39 | B40: Petonio's Kitchen Food Services | C40: Ramona C. Tabuso | D40: 013-000-080-045-720-21
A41: 40 | B41: Tiger Consulting and Software Devt Inc. | D41: 007-073-548
A42: 41 | B42: MOJR Construction Trading & General Services, Ltd, Co. | C42: Manuel S. Obedoza Jr.
A43: 42 | B43: Batanes Electric Cooperative Inc. | C43: Victoria A. Mata | D43: 005-641-216-000
A44: 43 | B44: Maddies Fashion Design Services | C44: Madeline Palencia Palustre
A45: 44 | B45: CMVILL Trading | C45: Zariffe G. Villanueva | D45: 421-603-862-000
A46: 45 | B46: VL Mini Canteen | C46: Estela N. Lizardo | D46: 930-779-799
A47: 46 | B47: IDB Merida Photo Studio & Artworks | C47: Ignacio Danilo B. Merida | D47: 925-632-231
A48: 47 | B48: SKE Souvenir Trading | C48: Sophia Kate L. Esdicul | D48: 613-655-085-00001
A49: 48 | B49: I.B.S. Travel and Tours | C49: Zharmaine C. Gutierrez | D49: 258-905-353
A50: 49 | B50: FVA Trading | C50: Nathan A. Amboy | D50: 436-695-403
A51: 50 | B51: JC Delatado's Telecommunication Equipment Trading | C51: Jesse A. Delatado | D51: 713-001-589-00001
A52: 51 | B52: AZ Blue Box Café | C52: Zafra Hazel B. Baldovino | D52: 434-947-764-00001
A53: 52 | B53: Kian's Food Product | C53: William Pol M. Maggay | D53: 915-768-533-00000
A54: 53 | B54: ORCA General Merchandise | C54: Engr. La Verne Sarmiento | D54: 614-297-100-00000
A55: 54 | B55: Boulder Bay Residence | C55: Mario Rey Roa Pacana | D55: 943-433-381-002
A56: 55 | B56: Simsiman Arts & Crafts Manufacturing | C56: Catherine De Mata | D56: 187-250-096
... A66: 65 | B66: Katuvang B and B | C66: Miguel Mariano B. Acebes | D66: 155-777-594-000
A67: 66 | B67: Bethel General Insurance and Surety Corporation | C67: Nicasio B. Subteniente Jr.
A68: 67 | B68: LaserCraft Arts & Crafts Manufacturing | C68: Garth G. Gavilan | D68: 489-033-719-00000
A69: 68 | B69: REMAR Construction | C69: Remy G. Cadiente | D69: 122-590-100-000
A70: 69 | B70: Artech Printing Services | C70: John Patrick D. Pasio | D70: 477-299-309-00000
A71: 70 | B71: Cielo General Merchandise | C71: Cyprian Crisostomo B. Cielo | D71: 275-653-568-00001
A72: 71 | B72: GMPI Construction OPC | C72: Gilbert N. Imperial | D72: 617-880-746-00000
A73: 72

Sheet DATA
A1: YEAR | B1: MONTH | C1: End-User | D1: Position/Designation | E1: Fund Code | F1: Class | G1: PR# | H1: Modality | I1: Item | J1: Qty | K1: Unit of Issue | L1: Unit Budget | M1: Estimated Total | N1: Unit LCRB | O1: Total | P1: Purpose | Q1: Office | R1: Date of LON | S1: Date of BAC Award | T1: PO/Contract Date | U1: PO/Contract Date Received | V1: Delivery Date | W1: Supplier | X1: IAR Date | Y1: Section Code/Dept. | Z1: Released Date | AA1: Status | AB1: Remarks | AC1: ObR # | AD1: # of RFQ's printed | AE1: Sales/Charge Invoice/Billing
A2: 2025 | B2: September | C2: ANNE MARIELLE V. TEVES | D2: BAC Secretariat | E2: 101 | G2: 2025-298 | I2: Ink-LC462XL | J2: 1 | K2: cartridge | L2: 2700 | M2: =SUM(J2*L2) -> 2700 | N2: 2680 | O2: =SUM(J2*N2) -> 2680 | P2: for office use | Q2: BAC | R2: September 16, 2025 | S2: September 17, 2025 | T2: September 18, 2025 | U2: October 1, 2025 | V2: October 2, 2025 | W2: One-Touch Technology Trading | X2: October 2, 2025 | Y2: GAS22 | Z2: 45938 | AA2: complete | AB2: for payment-Acctg. | AC2: 02-101101-2025-09-00754 | AD2: 5 RFQ's | AE2: 7955/10/2/2025
A3: 2025 | B3: September | C3: ANNE MARIELLE V. TEVES | D3: BAC Secretariat | E3: 101 | G3: 2025-298 | I3: Ink-LC462-yellow | J3: 1 | K3: cartridge | L3: 2000 | M3: =SUM(J3*L3) -> 2000 | N3: 880 | O3: =SUM(J3*N3) -> 880 | P3: for office use | Q3: BAC | R3: September 16, 2025 | S3: September 17, 2025 | T3: September 18, 2025 | U3: October 1, 2025 | V3: October 2, 2025 | W3: One-Touch Technology Trading | X3: October 2, 2025 | Y3: GAS22 | Z3: 45938 | AA3: complete | AB3: for payment-Acctg. | AC3: 02-101101-2025-09-00754
A4: 2025 | B4: September | C4: ANNE MARIELLE V. TEVES | D4: BAC Secretariat | E4: 101 | G4: 2025-298 | I4: Ink-LC462-magenta | J4: 1 | K4: cartridge | L4: 2000 | M4: =SUM(J4*L4) -> 2000 | N4: 880 | O4: =SUM(J4*N4) -> 880 | P4: for office use | Q4: BAC | R4: September 16, 2025 | S4: September 17, 2025 | T4: September 18, 2025 | U4: October 1, 2025 | V4: October 2, 2025 | W4: One-Touch Technology Trading | X4: October 2, 2025 | Y4: GAS22 | Z4: 45938 | AA4: complete | AB4: for payment-Acctg. | AC4: 02-101101-2025-09-00754
A5: 2025 | B5: September | C5: ANNE MARIELLE V. TEVES | D5: BAC Secretariat | E5: 101 | G5: 2025-298 | I5: Ink-LC462-cyan | J5: 1 | K5: cartridge | L5: 2000 | M5: =SUM(J5*L5) -> 2000 | N5: 880 | O5: =SUM(J5*N5) -> 880 | P5: for office use | Q5: BAC | R5: September 16, 2025 | S5: September 17, 2025 | T5: September 18, 2025 | U5: October 1, 2025 | V5: October 2, 2025 | W5: One-Touch Technology Trading | X5: October 2, 2025 | Y5: GAS22 | Z5: 45938 | AA5: complete | AB5: for payment-Acctg. | AC5: 02-101101-2025-09-00754
A6: 2025 | B6: September | C6: SYRA KARLA C. GORDO | D6: Project Technical Specialist 1 | E6: 165 | G6: 2025-298-A | I6: Heavy Snack (spaghetti,chicken fingers canned juice) | J6: 60 | K6: pax | L6: 350 | M6: =SUM(J6*L6) -> 21000 | N6: 350 | O6: =SUM(J6*N6) -> 21000 | P6: for the implementation of the project 2 - charge to S & T based interventions for sustainable tourism in Batanes-MOOE-Direct-Represenattion Expenses | Q6: RDET-S & T | R6: September 11, 2025 | S6: September 16, 2025 | T6: September 17, 2025 | U6: September 18, 2025 | V6: September 19, 2025 | W6: Doque's Congie Hauz | X6: September 19, 2025 | Y6: 1005 | Z6: February 6, 2026 | AA6: complete | AB6: for payment-Acctg. | AC6: 07-02-2025-09-0320A | AD6: 3 RFQ's | AE6: 25-09-001/10/23/2025 0802/9/17/2025
A7: 2025 | B7: September | C7: SYRA KARLA C. GORDO | D7: Project Technical Specialist 1 | E7: 165 | G7: 2025-299 | I7: Medium Roast Coffee 200g | J7: 5 | K7: jar | L7: 950 | M7: =SUM(J7*L7) -> 4750 | N7: 850 | O7: =SUM(J7*N7) -> 4250 | P7: supplies for the project/RDET office-charged to Sustainable Tourism Project (Representation Expenses) | Q7: RDET-S & T | R7: September 11, 2025 | S7: September 16, 2025 | T7: September 17, 2025 | U7: October 1, 2025 | V7: October 2, 2025 | W7: Sophia Marie Store | X7: October 2, 2025 | Y7: 1005 | Z7: October 28, 2025 | AA7: complete | AB7: for payment-Acctg. | AC7: 07-02-2025-09-0320 | AD7: 3 RFQ's | AE7: 1323/10/6/2025
A8: 2025 | B8: September | C8: SYRA KARLA C. GORDO | D8: Project Technical Specialist 1 | E8: 165 | G8: 2025-299 | I8: Washed Sugar | J8: 4 | K8: kg | L8: 100 | M8: =SUM(J8*L8) -> 400 | N8: 130 | O8: =SUM(J8*N8) -> 520 | P8: supplies for the project/RDET office-charged to Sustainable Tourism Project (Representation Expenses) | Q8: RDET-S & T | R8: September 11, 2025 | S8: September 16, 2025 | T8: September 17, 2025 | U8: October 1, 2025 | V8: October 2, 2025 | W8: Sophia Marie Store | X8: October 2, 2025 | Y8: 1005 | Z8: October 28, 2025 | AA8: complete | AB8: for payment-Acctg. | AC8: 07-02-2025-09-0320
A9: 2025 | B9: September | C9: SYRA KARLA C. GORDO | D9: Project Technical Specialist 1 | E9: 165 | G9: 2025-299 | I9: Creamer 400g | J9: 5 | K9: pouch | L9: 185 | M9: =SUM(J9*L9) -> 925 | N9: 178 | O9: =SUM(J9*N9) -> 890 | P9: supplies for the project/RDET office-charged to Sustainable Tourism Project (Representation Expenses) | Q9: RDET-S & T | R9: September 11, 2025 | S9: September 16, 2025 | T9: September 17, 2025 | U9: October 1, 2025 | V9: October 2, 2025 | W9: Sophia Marie Store | X9: October 2, 2025 | Y9: 1005 | Z9: October 28, 2025 | AA9: complete | AB9: for payment-Acctg. | AC9: 07-02-2025-09-0320
A10: 2025 | B10: September | C10: SYRA KARLA C. GORDO | D10: Project Technical Specialist 1 | E10: 165 | G10: 2025-299 | I10: Concentrated Powdered Tea drink mix | J10: 2 | K10: doz | L10: 150 | M10: =SUM(J10*L10) -> 300 | N10: 288 | O10: =SUM(J10*N10) -> 576 | P10: supplies for the project/RDET office-charged to Sustainable Tourism Project (Representation Expenses) | Q10: RDET-S & T | R10: September 11, 2025 | S10: September 16, 2025 | T10: September 17, 2025 | U10: October 1, 2025 | V10: October 2, 2025 | W10: Sophia Marie Store | X10: October 2, 2025 | Y10: 1005 | Z10: October 28, 2025 | AA10: complete | AB10: for payment-Acctg. | AC10: 07-02-2025-09-0320
A11: 2025 | B11: September | C11: SHEILA H. YDEL | D11: Admin. Officer IV | E11: 101 | G11: 2025-300 | I11: Office Laptop, CPU: AMD Ryzen 7 7000 series, RAM; 16GB DORS, Graphics: AMD Radeon Graphics (Integrated), Storage 1TB SSD, Wireless; Wi-Fi 6E(802.11ax) (Dual Band) 1*1 + bluetooth 5.3 wireless card, Pheripherals; Keyboard and mouse combo, Operating System: Windows 11 | J11: 1 | K11: unit | L11: 72000 | M11: =SUM(J11*L11) -> 72000 | N11: 68500 | O11: =SUM(J11*N11) -> 68500 | P11: for General Services Office use | Q11: GSO | R11: September 18, 2025 | S11: September 25, 2025 | T11: September 26, 2025 | U11: October 3, 2025 | V11: March 31, 2026 | W11: M.G. Hubalde's General Merchandise | X11: April 6, 2026 | Y11: GAS20 | Z11: April 14, 2026 | AA11: complete | AB11: for payment-Acctg. | AC11: 06-101101-2025-09-00787 | AD11: 5 RFQ's + 1 blank | AE11: 13387-13388/11/18/2025
A12: 2025 | B12: September | C12: SHEILA H. YDEL | D12: Admin. Officer IV | G12: 2025-301 | I12: Supply,Delivery and Installation of Wooden Door with Wooden Jamb and Doorknob with Key, Overall Dimension: Height - 98.5 inches, Width - 42 inches, Upper Clear Tempered Glass; Height - 8 inches, Width - 38 inches, Middle Clear Glass Acrylic; Height - 15 inches, Width - 10 inches | J12: 6 | K12: pcs | L12: 20000 | M12: =SUM(J12*L12) -> 120000 | O12: =SUM(J12*N12) -> 0 | P12: replacement of doors in 2nd floor classrooms (Rm. 210,211, & 213) | Q12: GSO | Y12: GAS20 | AA12: FAILED | AB12: winning supplier cancel the project due to financial challenges | AD12: 3 RFQ's + 1 blank
A13: 2025 | B13: September | C13: MICHEL A. CABRERA | D13: Assistant Professor IV | G13: 2025-302 | I13: A3 Wi-Fi Duplex All-In-One Ink Tank Printer | J13: 1 | K13: pc | L13: 55000 | M13: =SUM(J13*L13) -> 55000 | O13: =SUM(J13*N13) -> 0 | P13: to be used for instruction and office supplies | Q13: ICT | Y13: GAS4 | AA13: FAILED | AB13: quotation exceeded the budget | AD13: 4 RFQ's + 1 blank
A14: 2025 | B14: September | C14: MICHEL A. CABRERA | D14: Assistant Professor IV | G14: 2025-302 | I14: 70-180mm f/2.8 Di III VC G2 Camera Lens (Sony E) - for A7RIII | J14: 1 | K14: pc | L14: 70000 | M14: =SUM(J14*L14) -> 70000 | O14: =SUM(J14*N14) -> 0 | P14: to be used for instruction and office supplies | Q14: ICT | Y14: GAS4
A15: 2025 | B15: September | C15: MICHEL A. CABRERA | D15: Assistant Professor IV | G15: 2025-302 | I15: Z-series Rechargeable Battery Pack NP-FZ100 - for A7RIII | J15: 1 | K15: pc | L15: 6000 | M15: =SUM(J15*L15) -> 6000 | O15: =SUM(J15*N15) -> 0 | P15: to be used for instruction and office supplies | Q15: ICT | Y15: GAS4
A16: 2025 | B16: September | C16: MICHEL A. CABRERA | D16: Assistant Professor IV | G16: 2025-302 | I16: Mini Gimbal Stabilizer | J16: 1 | K16: pc | L16: 15000 | M16: =SUM(J16*L16) -> 15000 | O16: =SUM(J16*N16) -> 0 | P16: to be used for instruction and office supplies | Q16: ICT | Y16: GAS4
A17: 2025 | B17: September | C17: MICHEL A. CABRERA | D17: Assistant Professor IV | G17: 2025-302 | I17: Cat6 UTP LAN Ethernet Cable 305 meters | J17: 1 | K17: box | L17: 10000 | M17: =SUM(J17*L17) -> 10000 | O17: =SUM(J17*N17) -> 0 | P17: to be used for instruction and office supplies | Q17: ICT | Y17: GAS4
A18: 2025 | B18: September | C18: MICHEL A. CABRERA | D18: Assistant Professor IV | G18: 2025-302 | I18: 100pcs set RJ45 Connector Network Cat5e/Cat6 | J18: 5 | K18: box | L18: 200 | M18: =SUM(J18*L18) -> 1000 | O18: =SUM(J18*N18) -> 0 | P18: to be used for instruction and office supplies | Q18: ICT | Y18: GAS4
A19: 2025 | B19: September | C19: MARVIN KEITH C. ALAVADO | D19: Information Systems Analyst II/ ITO Officer | E19: 165 | G19: 2025-303 | I19: Camera cleaning kit 47pcs set | J19: 1 | K19: set | L19: 939 | M19: =SUM(J19*L19) -> 939 | N19: 320 | O19: =SUM(J19*N19) -> 320 | P19: for Programs, Activities and Projects of IT Unit charged under PRE 2025 | Q19: ITU | R19: October 7, 2025 | S19: October 13, 2025 | T19: October 14, 2025 | U19: October 21, 2025 | V19: 74% | W19: YCA Office Supplies & Equipment Trading | Y19: GAS5 | AA19: inc. delivery | AB19: 0.74 | AC19: 07-02-2025-10-0368 | AD19: 5 RFQ's + 1 blank
A20: 2025 | B20: September | C20: MARVIN KEITH C. ALAVADO | D20: Information Systems Analyst II/ ITO Officer | E20: 165 | G20: 2025-303 | I20: Magnifying glass with 30x magnification repair lamp | J20: 1 | K20: unit | L20: 750 | M20: =SUM(J20*L20) -> 750 | N20: 495 | O20: =SUM(J20*N20) -> 495 | P20: for Programs, Activities and Projects of IT Unit charged under PRE 2025 | Q20: ITU | R20: October 7, 2025 | S20: October 13, 2025 | T20: October 14, 2025 | U20: October 21, 2025 | W20: YCA Office Supplies & Equipment Trading | Y20: GAS5 | AC20: 07-02-2025-10-0368
A21: 2025 | B21: September | C21: MARVIN KEITH C. ALAVADO | D21: Information Systems Analyst II/ ITO Officer | E21: 165 | G21: 2025-303 | I21: 4pcs/set Syringe with hose | J21: 3 | K21: set | L21: 172.5 | M21: =SUM(J21*L21) -> 517.5 | N21: 120 | O21: =SUM(J21*N21) -> 360 | P21: for Programs, Activities and Projects of IT Unit charged under PRE 2025 | Q21: ITU | R21: October 7, 2025 | S21: October 13, 2025 | T21: October 14, 2025 | U21: October 21, 2025 | W21: YCA Office Supplies & Equipment Trading | Y21: GAS5 | AC21: 07-02-2025-10-0368
A22: 2025 | B22: September | C22: MARVIN KEITH C. ALAVADO | D22: Information Systems Analyst II/ ITO Officer | E22: 165 | G22: 2025-303 | I22: 2.5"/3.5" SATA docking station | J22: 1 | K22: pc | L22: 6000 | M22: =SUM(J22*L22) -> 6000 | N22: 2000 | O22: =SUM(J22*N22) -> 2000 | P22: for Programs, Activities and Projects of IT Unit charged under PRE 2025 | Q22: ITU | R22: October 7, 2025 | S22: October 13, 2025 | T22: October 14, 2025 | U22: October 21, 2025 | W22: YCA Office Supplies & Equipment Trading | Y22: GAS5 | AC22: 07-02-2025-10-0368
A23: 2025 | B23: September | C23: MARVIN KEITH C. ALAVADO | D23: Information Systems Analyst II/ ITO Officer | E23: 165 | G23: 2025-303 | I23: M.2 enclosure (Dual Protocol) | J23: 1 | K23: pc | L23: 4050 | M23: =SUM(J23*L23) -> 4050 | N23: 1700 | O23: =SUM(J23*N23) -> 1700 | P23: for Programs, Activities and Projects of IT Unit charged under PRE 2025 | Q23: ITU | R23: October 7, 2025 | S23: October 13, 2025 | T23: October 14, 2025 | U23: October 21, 2025 | W23: YCA Office Supplies & Equipment Trading | Y23: GAS5 | AC23: 07-02-2025-10-0368
A24: 2025 | B24: September | C24: MARVIN KEITH C. ALAVADO | D24: Information Systems Analyst II/ ITO Officer | E24: 165 | G24: 2025-303 | I24: 100's/box Black nitril disposable gloves powder free (Medium) | J24: 1 | K24: box | L24: 396 | M24: =SUM(J24*L24) -> 396 | N24: 210 | O24: =SUM(J24*N24) -> 210 | P24: for Programs, Activities and Projects of IT Unit charged under PRE 2025 | Q24: ITU | R24: October 7, 2025 | S24: October 13, 2025 | T24: October 14, 2025 | U24: October 21, 2025 | W24: YCA Office Supplies & Equipment Trading | Y24: GAS5 | AC24: 07-02-2025-10-0368
A25: 2025 | B25: September | C25: MARVIN KEITH C. ALAVADO | D25: Information Systems Analyst II/ ITO Officer | E25: 165 | G25: 2025-303 | I25: Ultrasonic Cleaning Machine 0.8L | J25: 1 | K25: unit | L25: 5548.5 | M25: =SUM(J25*L25) -> 5548.5 | N25: 4500 | O25: =SUM(J25*N25) -> 4500 | P25: for Programs, Activities and Projects of IT Unit charged under PRE 2025 | Q25: ITU | R25: October 7, 2025 | S25: October 13, 2025 | T25: October 14, 2025 | U25: October 21, 2025 | W25: YCA Office Supplies & Equipment Trading | Y25: GAS5 | AC25: 07-02-2025-10-0368
A26: 2025 | B26: September | C26: MARVIN KEITH C. ALAVADO | D26: Information Systems Analyst II/ ITO Officer | E26: 165 | G26: 2025-303 | I26: Cleaning solution 1000ml | J26: 1 | K26: bottle | L26: 735 | M26: =SUM(J26*L26) -> 735 | N26: 650 | O26: =SUM(J26*N26) -> 650 | P26: for Programs, Activities and Projects of IT Unit charged under PRE 2025 | Q26: ITU | R26: October 7, 2025 | S26: October 13, 2025 | T26: October 14, 2025 | U26: October 21, 2025 | W26: YCA Office Supplies & Equipment Trading | Y26: GAS5 | AC26: 07-02-2025-10-0368
A27: 2025 | B27: September | C27: MARVIN KEITH C. ALAVADO | D27: Information Systems Analyst II/ ITO Officer | E27: 165 | G27: 2025-303 | I27: Tool belt (6 slots, 1 pocket) | J27: 3 | K27: pcs | L27: 591 | M27: =SUM(J27*L27) -> 1773 | N27: 200 | O27: =SUM(J27*N27) -> 600 | P27: for Programs, Activities and Projects of IT Unit charged under PRE 2025 | Q27: ITU | R27: October 7, 2025 | S27: October 13, 2025 | T27: October 14, 2025 | U27: October 21, 2025 | W27: YCA Office Supplies & Equipment Trading | Y27: GAS5 | AC27: 07-02-2025-10-0368
A28: 2025 | B28: September | C28: MARVIN KEITH C. ALAVADO | D28: Information Systems Analyst II/ ITO Officer | E28: 165 | G28: 2025-303 | I28: 2000w Electric heat gun with Nozzle (w/ rotating back for precise temperature control) | J28: 1 | K28: unit | L28: 4185 | M28: =SUM(J28*L28) -> 4185 | N28: 3500 | O28: =SUM(J28*N28) -> 3500 | P28: for Programs, Activities and Projects of IT Unit charged under PRE 2025 | Q28: ITU | R28: October 7, 2025 | S28: October 13, 2025 | T28: October 14, 2025 | U28: October 21, 2025 | W28: YCA Office Supplies & Equipment Trading | Y28: GAS5 | AC28: 07-02-2025-10-0368
A29: 2025 | B29: September | C29: MARVIN KEITH C. ALAVADO | D29: Information Systems Analyst II/ ITO Officer | E29: 165 | G29: 2025-303 | I29: Silicone repair work mat (60x35 cm) | J29: 2 | K29: pcs | L29: 2340 | M29: =SUM(J29*L29) -> 4680 | N29: 1300 | O29: =SUM(J29*N29) -> 2600 | P29: for Programs, Activities and Projects of IT Unit charged under PRE 2025 | Q29: ITU | R29: October 7, 2025 | S29: October 13, 2025 | T29: October 14, 2025 | U29: October 21, 2025 | W29: YCA Office Supplies & Equipment Trading | Y29: GAS5 | AC29: 07-02-2025-10-0368
A30: 2025 | B30: September | C30: MARVIN KEITH C. ALAVADO | D30: Information Systems Analyst II/ ITO Officer | E30: 165 | G30: 2025-303 | I30: High performance thermal paste for CPU and GPU with spreader (20g) | J30: 1 | K30: tube | L30: 900 | M30: =SUM(J30*L30) -> 900 | N30: 1800 | O30: =SUM(J30*N30) -> 1800 | P30: for Programs, Activities and Projects of IT Unit charged under PRE 2025 | Q30: ITU | R30: October 7, 2025 | S30: October 13, 2025 | T30: October 14, 2025 | U30: October 21, 2025 | W30: YCA Office Supplies & Equipment Trading | Y30: GAS5 | AC30: 07-02-2025-10-0368
A31: 2025 | B31: September | C31: MARVIN KEITH C. ALAVADO | D31: Information Systems Analyst II/ ITO Officer | E31: 165 | G31: 2025-303 | I31: RJ45 Crimping tool | J31: 1 | K31: pc | L31: 553.5 | M31: =SUM(J31*L31) -> 553.5 | N31: 300 | O31: =SUM(J31*N31) -> 300 | P31: for Programs, Activities and Projects of IT Unit charged under PRE 2025 | Q31: ITU | R31: October 7, 2025 | S31: October 13, 2025 | T31: October 14, 2025 | U31: October 21, 2025 | W31: YCA Office Supplies & Equipment Trading | Y31: GAS5 | AC31: 07-02-2025-10-0368
... A52: 2025 | B52: September | C52: MARVIN KEITH C. ALAVADO | D52: Information Systems Analyst II/ ITO Officer | E52: 165 | G52: 2025-303 | I52: Foldable garden saw (18m blade) | J52: 1 | K52: pc | L52: 585 | M52: =SUM(J52*L52) -> 585 | N52: 380 | O52: =SUM(J52*N52) -> 380 | P52: for Programs, Activities and Projects of IT Unit charged under PRE 2025 | Q52: ITU | R52: October 7, 2025 | S52: October 13, 2025 | T52: October 14, 2025 | U52: October 21, 2025 | W52: YCA Office Supplies & Equipment Trading | Y52: GAS5 | AC52: 07-02-2025-10-0368
A53: 2025 | B53: September | C53: MARVIN KEITH C. ALAVADO | D53: Information Systems Analyst II/ ITO Officer | E53: 165 | G53: 2025-303 | H53: 35 | I53: Standard wall mount for Starlink Gen 3 | J53: 1 | K53: pc | L53: 8490 | M53: =SUM(J53*L53) -> 8490 | N53: 16000 | O53: =SUM(J53*N53) -> 16000 | P53: for Programs, Activities and Projects of IT Unit charged under PRE 2025 | Q53: ITU | R53: October 7, 2025 | S53: October 13, 2025 | T53: October 14, 2025 | U53: October 21, 2025 | W53: YCA Office Supplies & Equipment Trading | Y53: GAS5 | AC53: 07-02-2025-10-0368
A54: 2025 | B54: September | C54: GLORIA N. CABIZON | D54: ITD Chairperson | G54: 2025-304 | I54: Acrylic Based Paint - Red | J54: 1 | K54: liter | L54: 400 | M54: =SUM(J54*L54) -> 400 | O54: =SUM(J54*N54) -> 0 | P54: materials for ASEAN program (ASEAN mural wall painting) | Q54: ITD | Y54: Acad5 | AA54: CANCELLED | AB54: Re-PR
A55: 2025 | B55: September | C55: GLORIA N. CABIZON | D55: ITD Chairperson | G55: 2025-304 | I55: Acrylic Based Paint - Blue | J55: 1 | K55: liter | L55: 400 | M55: =SUM(J55*L55) -> 400 | O55: =SUM(J55*N55) -> 0 | P55: materials for ASEAN program (ASEAN mural wall painting) | Q55: ITD | Y55: Acad5
A56: 2025 | B56: September | C56: GLORIA N. CABIZON | D56: ITD Chairperson | G56: 2025-304 | I56: Acrylic Based Paint - Yellow | J56: 1 | K56: liter | L56: 400 | M56: =SUM(J56*L56) -> 400 | O56: =SUM(J56*N56) -> 0 | P56: materials for ASEAN program (ASEAN mural wall painting) | Q56: ITD | Y56: Acad5
A57: 2025 | B57: September | C57: GLORIA N. CABIZON | D57: ITD Chairperson | G57: 2025-304 | I57: Acrylic Based Paint - Black | J57: 1 | K57: liter | L57: 400 | M57: =SUM(J57*L57) -> 400 | O57: =SUM(J57*N57) -> 0 | P57: materials for ASEAN program (ASEAN mural wall painting) | Q57: ITD | Y57: Acad5
A58: 2025 | B58: September | C58: GLORIA N. CABIZON | D58: ITD Chairperson | G58: 2025-304 | I58: Acrylic Based Paint - White | J58: 1 | K58: pail | L58: 3200 | M58: =SUM(J58*L58) -> 3200 | O58: =SUM(J58*N58) -> 0 | P58: materials for ASEAN program (ASEAN mural wall painting) | Q58: ITD | Y58: Acad5
A59: 2025 | B59: September | C59: GLORIA N. CABIZON | D59: ITD Chairperson | G59: 2025-304 | I59: Artist Paint Brush | J59: 1 | K59: set | L59: 1200 | M59: =SUM(J59*L59) -> 1200 | O59: =SUM(J59*N59) -> 0 | P59: materials for ASEAN program (ASEAN mural wall painting) | Q59: ITD | Y59: Acad5
A60: 2025 | B60: September | C60: GLORIA N. CABIZON | D60: ITD Chairperson | G60: 2025-304 | I60: Paint Roller (4 inches) | J60: 4 | K60: pcs | L60: 200 | M60: =SUM(J60*L60) -> 800 | O60: =SUM(J60*N60) -> 0 | P60: materials for ASEAN program (ASEAN mural wall painting) | Q60: ITD | Y60: Acad5
A61: 2025 | B61: September | C61: SHEILA H. YDEL | D61: Admin. Officer IV | E61: 101 | G61: 2025-305 | I61: 4ft x 8ft Galvanized Plain Sheet, 25 Gauge | J61: 44 | K61: pcs | L61: 900 | M61: =SUM(J61*L61) -> 39600 | N61: 626 | O61: =SUM(J61*N61) -> 27544 | P61: materials use for fabrication of Tapangko | Q61: GSO | R61: September 26, 2025 | S61: September 30, 2025 | T61: October 1, 2025 | U61: October 8, 2025 | V61: October 8, 2025 | W61: FVA Trading | X61: October 8, 2025 | Y61: GAS20 | Z61: October 28, 2025 | AA61: complete | AB61: for payment-Actg. | AC61: 06-101101-2025-10-00793 | AD61: 6 RFQ's + 1 blank | AE61: 3094/
A62: 2025 | B62: September | C62: SHEILA H. YDEL | D62: Admin. Officer IV | E62: 101 | G62: 2025-305 | I62: 2inch x 3inch x 12ft Palochina Wood | J62: 120 | K62: pcs | L62: 480 | M62: =SUM(J62*L62) -> 57600 | N62: 365 | O62: =SUM(J62*N62) -> 43800 | P62: materials use for fabrication of Tapangko | Q62: GSO | R62: September 26, 2025 | S62: September 30, 2025 | T62: October 1, 2025 | U62: October 8, 2025 | V62: October 8, 2025 | W62: FVA Trading | X62: October 8, 2025 | Y62: GAS20 | Z62: October 28, 2025 | AA62: complete | AB62: for payment-Actg. | AC62: 06-101101-2025-10-00793
A63: 2025 | B63: September | C63: SHEILA H. YDEL | D63: Admin. Officer IV | E63: 101 | G63: 2025-305 | I63: 3inch Log Screw with Anchor | J63: 50 | K63: pcs | L63: 70 | M63: =SUM(J63*L63) -> 3500 | N63: 80 | O63: =SUM(J63*N63) -> 4000 | P63: materials use for fabrication of Tapangko | Q63: GSO | R63: September 26, 2025 | S63: September 30, 2025 | T63: October 1, 2025 | U63: October 8, 2025 | V63: October 8, 2025 | W63: FVA Trading | X63: October 8, 2025 | Y63: GAS20 | Z63: October 28, 2025 | AA63: complete | AB63: for payment-Actg. | AC63: 06-101101-2025-10-00793
A64: 2025 | B64: September | C64: SHEILA H. YDEL | D64: Admin. Officer IV | E64: 101 | G64: 2025-305 | I64: 1.5inch Common Nail | J64: 5 | K64: kgs | L64: 110 | M64: =SUM(J64*L64) -> 550 | N64: 80 | O64: =SUM(J64*N64) -> 400 | P64: materials use for fabrication of Tapangko | Q64: GSO | R64: September 26, 2025 | S64: September 30, 2025 | T64: October 1, 2025 | U64: October 8, 2025 | V64: October 8, 2025 | W64: FVA Trading | X64: October 8, 2025 | Y64: GAS20 | Z64: October 28, 2025 | AA64: complete | AB64: for payment-Actg. | AC64: 06-101101-2025-10-00793
A65: 2025 | B65: September | C65: SHEILA H. YDEL | D65: Admin. Officer IV | E65: 101 | G65: 2025-305 | I65: 3inch Common Nail | J65: 5 | K65: kgs | L65: 110 | M65: =SUM(J65*L65) -> 550 | N65: 80 | O65: =SUM(J65*N65) -> 400 | P65: materials use for fabrication of Tapangko | Q65: GSO | R65: September 26, 2025 | S65: September 30, 2025 | T65: October 1, 2025 | U65: October 8, 2025 | V65: October 8, 2025 | W65: FVA Trading | X65: October 8, 2025 | Y65: GAS20 | Z65: October 28, 2025 | AA65: complete | AB65: for payment-Actg. | AC65: 06-101101-2025-10-00793
A66: 2025 | B66: September | C66: SHEILA H. YDEL | D66: Admin. Officer IV | E66: 101 | G66: 2025-305 | I66: 4inch Common Nail' | J66: 5 | K66: kgs | L66: 110 | M66: =SUM(J66*L66) -> 550 | N66: 80 | O66: =SUM(J66*N66) -> 400 | P66: materials use for fabrication of Tapangko | Q66: GSO | R66: September 26, 2025 | S66: September 30, 2025 | T66: October 1, 2025 | U66: October 8, 2025 | V66: October 8, 2025 | W66: FVA Trading | X66: October 8, 2025 | Y66: GAS20 | Z66: October 28, 2025 | AA66: complete | AB66: for payment-Actg. | AC66: 06-101101-2025-10-00793
A67: 2025 | B67: September | C67: MARVIN KEITH C. ALAVADO | D67: Study Member | E67: 165 | G67: 2025-306 | I67: Internet Service Provider Subscription | J67: 9 | K67: months | L67: 5000 | M67: =SUM(J67*L67) -> 45000 | N67: 4500 | O67: =SUM(J67*N67) -> 40500 | P67: S & T internet service providers monthly service charge fee for Mutchong Tourism village at Uyugan, Batanes | Q67: RDET-S & T | R67: October 1, 2025 | S67: October 6, 2025 | T67: October 7, 2025 | U67: October 10, 2025 | V67: October 12, 2025 | W67: IBS Pharmacy & General Merchandise | X67: November 3, 2025 | Y67: 1005 | Z67: November 13, 2025 | AA67: complete | AB67: for payment-Actg. | AC67: 07-02-2025-10-0349 | AD67: 5 RFQ's + blank | AE67: 2893/11/03/2025
A68: 2025 | B68: September | C68: MA. NIAM KARLA D. GONZALES | D68: Chairperson-HTM Dept. | E68: 165 | G68: 2025-307 | I68: Refill MGAS (Large) | J68: 1 | K68: tank | L68: 8000 | M68: =SUM(J68*L68) -> 8000 | N68: 5700 | O68: =SUM(J68*N68) -> 5700 | P68: for baking laboratory | Q68: HTM | R68: October 7, 2025 | S68: October 13, 2025 | T68: October 14, 2025 | U68: October 17, 2025 | V68: October 21, 2025 | W68: GDP Trading | X68: October 21, 2025 | Y68: Acad3 | Z68: October 28, 2025 | AA68: complete | AB68: for payment-Actg. | AC68: 07-02-2025-10-0366 | AD68: 5 RFQ's | AE68: 23800/10/28/2025
A69: 2025 | B69: September | C69: XINA V. VINALAY | D69: Project Staff Leader Level II | E69: 165 | G69: 2025-308 | I69: Garbage Bag black (small) | J69: 5 | K69: pcs | L69: 90 | M69: =SUM(J69*L69) -> 450 | N69: 60 | O69: =SUM(J69*N69) -> 300 | P69: for IPTBM | Q69: RDET-IPTBM | R69: September 26, 2025 | S69: September 30, 2025 | T69: September 30, 2025 | U69: October 8, 2025 | V69: Oct.8,Nov. 13,24 & Dec. 5, 2025 | W69: M.G. Hubalde's General Merchandise | X69: Oct.8,Nov. 13,24 & Dec. 5, 2025 | Y69: 1005 | Z69: December 16, 2025 | AA69: complete | AB69: for payment-Actg. | AC69: 07-02-2025-09-0340 | AD69: 4 RFQ's | AE69: 13368-13371/12/4/2025
A70: 2025 | B70: September | C70: XINA V. VINALAY | D70: Project Staff Leader Level II | E70: 165 | G70: 2025-308 | I70: Garbage Bag black (medium) | J70: 5 | K70: pcs | L70: 150 | M70: =SUM(J70*L70) -> 750 | N70: 80 | O70: =SUM(J70*N70) -> 400 | P70: for IPTBM | Q70: RDET-IPTBM | R70: September 26, 2025 | S70: September 30, 2025 | T70: September 30, 2025 | U70: October 8, 2025 | V70: Oct.8,Nov. 13,24 & Dec. 5, 2025 | W70: M.G. Hubalde's General Merchandise | X70: Oct.8,Nov. 13,24 & Dec. 5, 2025 | Y70: 1005 | Z70: December 16, 2025 | AA70: complete | AB70: for payment-Actg. | AC70: 07-02-2025-09-0340
A71: 2025 | B71: September | C71: XINA V. VINALAY | D71: Project Staff Leader Level II | E71: 165 | G71: 2025-308 | I71: Garbage Bag black (large) | J71: 5 | K71: pcs | L71: 200 | M71: =SUM(J71*L71) -> 1000 | N71: 100 | O71: =SUM(J71*N71) -> 500 | P71: for IPTBM | Q71: RDET-IPTBM | R71: September 26, 2025 | S71: September 30, 2025 | T71: September 30, 2025 | U71: October 8, 2025 | V71: Oct.8,Nov. 13,24 & Dec. 5, 2025 | W71: M.G. Hubalde's General Merchandise | X71: Oct.8,Nov. 13,24 & Dec. 5, 2025 | Y71: 1005 | Z71: December 16, 2025 | AA71: complete | AB71: for payment-Actg. | AC71: 07-02-2025-09-0340
A72: 2025 | B72: September | C72: XINA V. VINALAY | D72: Project Staff Leader Level II | E72: 165 | G72: 2025-308 | I72: Rubbing Alcohol Pump (500ml) | J72: 2 | K72: bottles | L72: 800 | M72: =SUM(J72*L72) -> 1600 | N72: 250 | O72: =SUM(J72*N72) -> 500 | P72: for IPTBM | Q72: RDET-IPTBM | R72: September 26, 2025 | S72: September 30, 2025 | T72: September 30, 2025 | U72: October 8, 2025 | V72: Oct.8,Nov. 13,24 & Dec. 5, 2025 | W72: M.G. Hubalde's General Merchandise | X72: Oct.8,Nov. 13,24 & Dec. 5, 2025 | Y72: 1005 | Z72: December 16, 2025 | AA72: complete | AB72: for payment-Actg. | AC72: 07-02-2025-09-0340
A73: 2025 | B73: September | C73: XINA V. VINALAY | D73: Project Staff Leader Level II | E73: 165 | G73: 2025-308 | I73: Bathroom Tissue | J73: 25 | K73: pcs | L73: 50 | M73: =SUM(J73*L73) -> 1250 | N73: 15 | O73: =SUM(J73*N73) -> 375 | P73: for IPTBM | Q73: RDET-IPTBM | R73: September 26, 2025 | S73: September 30, 2025 | T73: September 30, 2025 | U73: October 8, 2025 | V73: Oct.8,Nov. 13,24 & Dec. 5, 2025 | W73: M.G. Hubalde's General Merchandise | X73: Oct.8,Nov. 13,24 & Dec. 5, 2025 | Y73: 1005 | Z73: December 16, 2025 | AA73: complete | AB73: for payment-Actg. | AC73: 07-02-2025-09-0340
A74: 2025 | B74: September | C74: XINA V. VINALAY | D74: Project Staff Leader Level II | E74: 165 | G74: 2025-308 | I74: Bathroom Deodorizer 50g (sampaguita) | J74: 25 | K74: pcs | L74: 50 | M74: =SUM(J74*L74) -> 1250 | N74: 45 | O74: =SUM(J74*N74) -> 1125 | P74: for IPTBM | Q74: RDET-IPTBM | R74: September 26, 2025 | S74: September 30, 2025 | T74: September 30, 2025 | U74: October 8, 2025 | V74: Oct.8,Nov. 13,24 & Dec. 5, 2025 | W74: M.G. Hubalde's General Merchandise | X74: Oct.8,Nov. 13,24 & Dec. 5, 2025 | Y74: 1005 | Z74: December 16, 2025 | AA74: complete | AB74: for payment-Actg. | AC74: 07-02-2025-09-0340
A75: 2025 | B75: September | C75: XINA V. VINALAY | D75: Project Staff Leader Level II | E75: 165 | G75: 2025-308 | I75: Colorsafe Bleach 900ml | J75: 5 | K75: bottles | L75: 90 | M75: =SUM(J75*L75) -> 450 | N75: 100 | O75: =SUM(J75*N75) -> 500 | P75: for IPTBM | Q75: RDET-IPTBM | R75: September 26, 2025 | S75: September 30, 2025 | T75: September 30, 2025 | U75: October 8, 2025 | V75: Oct.8,Nov. 13,24 & Dec. 5, 2025 | W75: M.G. Hubalde's General Merchandise | X75: Oct.8,Nov. 13,24 & Dec. 5, 2025 | Y75: 1005 | Z75: December 16, 2025 | AA75: complete | AB75: for payment-Actg. | AC75: 07-02-2025-09-0340
A76: 2025 | B76: September | C76: XINA V. VINALAY | D76: Project Staff Leader Level II | E76: 165 | G76: 2025-308 | I76: Liquid Bleach 1000g | J76: 5 | K76: bottles | L76: 90 | M76: =SUM(J76*L76) -> 450 | N76: 70 | O76: =SUM(J76*N76) -> 350 | P76: for IPTBM | Q76: RDET-IPTBM | R76: September 26, 2025 | S76: September 30, 2025 | T76: September 30, 2025 | U76: October 8, 2025 | V76: Oct.8,Nov. 13,24 & Dec. 5, 2025 | W76: M.G. Hubalde's General Merchandise | X76: Oct.8,Nov. 13,24 & Dec. 5, 2025 | Y76: 1005 | Z76: December 16, 2025 | AA76: complete | AB76: for payment-Actg. | AC76: 07-02-2025-09-0340
A77: 2025 | B77: September | C77: XINA V. VINALAY | D77: Project Staff Leader Level II | E77: 165 | G77: 2025-308 | I77: Disinfectant Spray 510g (lavender scent) | J77: 5 | K77: pcs | L77: 750 | M77: =SUM(J77*L77) -> 3750 | N77: 750 | O77: =SUM(J77*N77) -> 3750 | P77: for IPTBM | Q77: RDET-IPTBM | R77: September 26, 2025 | S77: September 30, 2025 | T77: September 30, 2025 | U77: October 8, 2025 | V77: Oct.8,Nov. 13,24 & Dec. 5, 2025 | W77: M.G. Hubalde's General Merchandise | X77: Oct.8,Nov. 13,24 & Dec. 5, 2025 | Y77: 1005 | Z77: December 16, 2025 | AA77: complete | AB77: for payment-Actg. | AC77: 07-02-2025-09-0340
A78: 2025 | B78: September | C78: XINA V. VINALAY | D78: Project Staff Leader Level II | E78: 165 | G78: 2025-308 | I78: Multipurpose Cleaner Liquid 500ml | J78: 5 | K78: bottles | L78: 200 | M78: =SUM(J78*L78) -> 1000 | N78: 290 | O78: =SUM(J78*N78) -> 1450 | P78: for IPTBM | Q78: RDET-IPTBM | R78: September 26, 2025 | S78: September 30, 2025 | T78: September 30, 2025 | U78: October 8, 2025 | V78: Oct.8,Nov. 13,24 & Dec. 5, 2025 | W78: M.G. Hubalde's General Merchandise | X78: Oct.8,Nov. 13,24 & Dec. 5, 2025 | Y78: 1005 | Z78: December 16, 2025 | AA78: complete | AB78: for payment-Actg. | AC78: 07-02-2025-09-0340
A79: 2025 | B79: September | C79: XINA V. VINALAY | D79: Project Staff Leader Level II | E79: 165 | G79: 2025-308 | I79: Dishwashing Sponge (small) | J79: 4 | K79: pcs | L79: 50 | M79: =SUM(J79*L79) -> 200 | N79: 35 | O79: =SUM(J79*N79) -> 140 | P79: for IPTBM | Q79: RDET-IPTBM | R79: September 26, 2025 | S79: September 30, 2025 | T79: September 30, 2025 | U79: October 8, 2025 | V79: Oct.8,Nov. 13,24 & Dec. 5, 2025 | W79: M.G. Hubalde's General Merchandise | X79: Oct.8,Nov. 13,24 & Dec. 5, 2025 | Y79: 1005 | Z79: December 16, 2025 | AA79: complete | AB79: for payment-Actg. | AC79: 07-02-2025-09-0340
A80: 2025 | B80: September | C80: XINA V. VINALAY | D80: Project Staff Leader Level II | E80: 165 | G80: 2025-308 | I80: Double AA Battery | J80: 5 | K80: pcs | L80: 70 | M80: =SUM(J80*L80) -> 350 | N80: 75 | O80: =SUM(J80*N80) -> 375 | P80: for IPTBM | Q80: RDET-IPTBM | R80: September 26, 2025 | S80: September 30, 2025 | T80: September 30, 2025 | U80: October 8, 2025 | W80: M.G. Hubalde's General Merchandise | Y80: 1005 | Z80: December 16, 2025 | AA80: complete | AB80: for payment-Actg. | AC80: 07-02-2025-09-0340
A81: 2025 | B81: September | C81: SHEILA H. YDEL | D81: Admin. Officer IV | G81: 2025-309 | I81: DC Arc Inverter Welding Machine PIW-250VRD Input Voltage: 230V/60hz, Output Current: 20-250A | J81: 1 | K81: pc | L81: 18000 | M81: =SUM(J81*L81) -> 18000 | O81: =SUM(J81*N81) -> 0 | P81: equipment use for fabrication of General Services Office | Q81: GSO | Y81: GAS20 | AA81: FAILED | AB81: quotation exceeded the budget | AD81: 5 RFQ's
A82: 2025 | B82: September | C82: SHEILA H. YDEL | D82: Admin. Officer IV | G82: 2025-309 | I82: Protection Head Mounted Welding Mask Open Type | J82: 1 | K82: pc | L82: 500 | M82: =SUM(J82*L82) -> 500 | O82: =SUM(J82*N82) -> 0 | P82: equipment use for fabrication of General Services Office | Q82: GSO | Y82: GAS20
A83: 2025 | B83: September | C83: JANE S. CASTILLO | D83: Futures Thinking & Strategic Foresight Coordinator | E83: 101 | G83: 2025-310 | I83: Water Container (with water refilled) | J83: 2 | K83: gallon | L83: 650 | M83: =SUM(J83*L83) -> 1300 | N83: 490 | O83: =SUM(J83*N83) -> 980 | P83: office supplies for Futures Thinking office | Q83: RDET-Futures Thinking | R83: October 6, 2025 | S83: October 8, 2025 | T83: October 9, 2025 | U83: October 17, 2025 | V83: October 17, 2025 | W83: Apostol General Merchandise | X83: October 20, 2025 | Y83: 1005 | Z83: November 6, 2025 | AA83: complete | AB83: for payment-Acctg. | AC83: 02-101101-2025-10-00833 | AD83: 5 RFQ's | AE83: 3069/10/17/2025
A84: 2025 | B84: September | C84: JANE S. CASTILLO | D84: Futures Thinking & Strategic Foresight Coordinator | E84: 101 | G84: 2025-310 | I84: Water Dispenser Top Load (with hot,normal,cold) | J84: 1 | K84: unit | L84: 30000 | M84: =SUM(J84*L84) -> 30000 | N84: 13000 | O84: =SUM(J84*N84) -> 13000 | P84: office supplies for Futures Thinking office | Q84: RDET-Futures Thinking | R84: October 6, 2025 | S84: October 8, 2025 | T84: October 9, 2025 | U84: October 17, 2025 | V84: October 17, 2025 | W84: Apostol General Merchandise | X84: October 20, 2025 | Y84: 1005 | Z84: November 6, 2025 | AA84: complete | AB84: for payment-Acctg. | AC84: 02-101101-2025-10-00833
A85: 2025 | B85: September | C85: JANE S. CASTILLO | D85: Futures Thinking & Strategic Foresight Coordinator | E85: 101 | G85: 2025-311 | I85: Office Laptop: AMD Ryzen 5-5500H/8GB DDR4/512GB M.2 PCIE NVME SSD/NVIDIA GeForce RTX™ 2050 4GB GDDR6/15.6" FHD/Windows 11 HOME SL 64BIT/WEBCAM/RGB BACKLIT KB/WIFI/BT/LAN/AUDIO PORT/USB 3.0/USB TYPE-C/HDMI/LAPTOP) | J85: 1 | K85: unit | L85: 49000 | M85: =SUM(J85*L85) -> 49000 | N85: 49800 | O85: =SUM(J85*N85) -> 49800 | P85: for printing, scanning,photocopy,encoding and editing files and documents of Futures Thinking Office | Q85: RDET-Futures Thinking | R85: October 6, 2025 | S85: October 8, 2025 | T85: October 9, 2025 | U85: October 16, 2025 | V85: November 13 & 20, 2025 | W85: M.G. Hubalde's General Merchandise | X85: November 19 & 21, 2025 | Y85: 1005 | Z85: December 4, 2025 | AA85: complete | AB85: for payment-Acctg. | AC85: 02-101101-2025-10-00832 | AD85: 5 RFQ's + 1 blank | AE85: 13377-13379/11/21/2025
A86: 2025 | B86: September | C86: JANE S. CASTILLO | D86: Futures Thinking & Strategic Foresight Coordinator | E86: 101 | G86: 2025-311 | I86: All-In-One Ink Tank Printer: (Print speed of up to 17.0 ipm) (Prints up to A3+ (for simplex) (Automatic duplex printing) (Ultra-high page yield of 7,500 pages (black) and 6,000 pages (colour) (Wi-Fi, Wi-Fi Direct) | J86: 1 | K86: unit | L86: 49000 | M86: =SUM(J86*L86) -> 49000 | N86: 38850 | O86: =SUM(J86*N86) -> 38850 | P86: for printing, scanning,photocopy,encoding and editing files and documents of Futures Thinking Office | Q86: RDET-Futures Thinking | R86: October 6, 2025 | S86: October 8, 2025 | T86: October 9, 2025 | U86: October 16, 2025 | V86: November 13 & 20, 2025 | W86: M.G. Hubalde's General Merchandise | X86: November 19 & 21, 2025 | Y86: 1005 | Z86: December 4, 2025 | AA86: complete | AB86: for payment-Acctg. | AC86: 02-101101-2025-10-00832
A87: 2025 | B87: September | C87: JANE S. CASTILLO | D87: Futures Thinking & Strategic Foresight Coordinator | G87: 2025-312 | I87: Medium Roast Soluble Coffee Intensity 5 Instatnt Coffee (bottled 200g) | J87: 2 | K87: pcs | L87: 1050 | M87: =SUM(J87*L87) -> 2100 | O87: =SUM(J87*N87) -> 0 | P87: office supplies for Futures Thinking office | Q87: RDET-Futures Thinking | Y87: 1005 | AA87: FAILED | AB87: incomplete quotation | AD87: 5 RFQ's
A88: 2025 | B88: September | C88: JANE S. CASTILLO | D88: Futures Thinking & Strategic Foresight Coordinator | G88: 2025-312 | I88: Refined Washed Sugar | J88: 2 | K88: kg | L88: 105 | M88: =SUM(J88*L88) -> 210 | O88: =SUM(J88*N88) -> 0 | P88: office supplies for Futures Thinking office | Q88: RDET-Futures Thinking | Y88: 1005
A89: 2025 | B89: September | C89: JANE S. CASTILLO | D89: Futures Thinking & Strategic Foresight Coordinator | G89: 2025-312 | I89: Powder Coffee Creamer (453.5g) | J89: 2 | K89: pcs | L89: 360 | M89: =SUM(J89*L89) -> 720 | O89: =SUM(J89*N89) -> 0 | P89: office supplies for Futures Thinking office | Q89: RDET-Futures Thinking | Y89: 1005
A90: 2025 | B90: September | C90: JANE S. CASTILLO | D90: Futures Thinking & Strategic Foresight Coordinator | G90: 2025-312 | I90: Choco Malt Powdered Milk Drink (24g) | J90: 2 | K90: dozen | L90: 150 | M90: =SUM(J90*L90) -> 300 | O90: =SUM(J90*N90) -> 0 | P90: office supplies for Futures Thinking office | Q90: RDET-Futures Thinking | Y90: 1005
A91: 2025 | B91: September | C91: JANE S. CASTILLO | D91: Futures Thinking & Strategic Foresight Coordinator | G91: 2025-312 | I91: Assorted Biscuit in plastic pail (1.5kg) | J91: 1 | K91: pail | L91: 550 | M91: =SUM(J91*L91) -> 550 | O91: =SUM(J91*N91) -> 0 | P91: office supplies for Futures Thinking office | Q91: RDET-Futures Thinking | Y91: 1005
A92: 2025 | B92: September | C92: JANE S. CASTILLO | D92: Futures Thinking & Strategic Foresight Coordinator | G92: 2025-312 | I92: Biscuit (with fillings assorted) | J92: 2 | K92: ballot | L92: 100 | M92: =SUM(J92*L92) -> 200 | O92: =SUM(J92*N92) -> 0 | P92: office supplies for Futures Thinking office | Q92: RDET-Futures Thinking | Y92: 1005
A93: 2025 | B93: September | C93: JANE S. CASTILLO | D93: Futures Thinking & Strategic Foresight Coordinator | G93: 2025-312 | I93: Wooden Coffee Stirrer (disposable individual paper wrapped) | J93: 2 | K93: pack | L93: 255 | M93: =SUM(J93*L93) -> 510 | O93: =SUM(J93*N93) -> 0 | P93: office supplies for Futures Thinking office | Q93: RDET-Futures Thinking | Y93: 1005
A94: 2025 | B94: September | C94: JANE S. CASTILLO | D94: Futures Thinking & Strategic Foresight Coordinator | E94: 101 | G94: 2025-313 | I94: Gloss White Paint | J94: 2 | K94: gallon | L94: 3975 | M94: =SUM(J94*L94) -> 7950 | N94: 1800 | O94: =SUM(J94*N94) -> 3600 | P94: supplies & materials for renovation of the Futures Thinking office | Q94: RDET-Futures Thinking | R94: October 10, 2025 | S94: October 15, 2025 | T94: October 15, 2025 | U94: October 21, 2025 | V94: October 22, 2025 | W94: E.A.Amboy General Merchandise | X94: October 22, 2025 | Y94: 1005 | Z94: November 6, 2025 | AA94: complete | AB94: for payment-Acctg. | AC94: 02-102101-2025-10-00855 | AD94: 6 RFQ's | AE94: 015481-15482/10/22/2025
A95: 2025 | B95: September | C95: JANE S. CASTILLO | D95: Futures Thinking & Strategic Foresight Coordinator | E95: 101 | G95: 2025-313 | I95: Roller Paint Brush (#07) | J95: 2 | K95: pcs | L95: 80 | M95: =SUM(J95*L95) -> 160 | N95: 150 | O95: =SUM(J95*N95) -> 300 | P95: supplies & materials for renovation of the Futures Thinking office | Q95: RDET-Futures Thinking | R95: October 10, 2025 | S95: October 15, 2025 | T95: October 15, 2025 | U95: October 21, 2025 | V95: October 22, 2025 | W95: E.A.Amboy General Merchandise | X95: October 22, 2025 | Y95: 1005 | Z95: November 6, 2025 | AA95: complete | AB95: for payment-Acctg. | AC95: 02-102101-2025-10-00855
A96: 2025 | B96: September | C96: JANE S. CASTILLO | D96: Futures Thinking & Strategic Foresight Coordinator | E96: 101 | G96: 2025-313 | I96: Paint Pan | J96: 2 | K96: pcs | L96: 53 | M96: =SUM(J96*L96) -> 106 | N96: 75 | O96: =SUM(J96*N96) -> 150 | P96: supplies & materials for renovation of the Futures Thinking office | Q96: RDET-Futures Thinking | R96: October 10, 2025 | S96: October 15, 2025 | T96: October 15, 2025 | U96: October 21, 2025 | V96: October 22, 2025 | W96: E.A.Amboy General Merchandise | X96: October 22, 2025 | Y96: 1005 | Z96: November 6, 2025 | AA96: complete | AB96: for payment-Acctg. | AC96: 02-102101-2025-10-00855
A97: 2025 | B97: September | C97: JANE S. CASTILLO | D97: Futures Thinking & Strategic Foresight Coordinator | E97: 101 | G97: 2025-313 | I97: PVC Race Way (3/4 inch) | J97: 2 | K97: pcs | L97: 95 | M97: =SUM(J97*L97) -> 190 | N97: 170 | O97: =SUM(J97*N97) -> 340 | P97: supplies & materials for renovation of the Futures Thinking office | Q97: RDET-Futures Thinking | R97: October 10, 2025 | S97: October 15, 2025 | T97: October 15, 2025 | U97: October 21, 2025 | V97: October 22, 2025 | W97: E.A.Amboy General Merchandise | X97: October 22, 2025 | Y97: 1005 | Z97: November 6, 2025 | AA97: complete | AB97: for payment-Acctg. | AC97: 02-102101-2025-10-00855
A98: 2025 | B98: September | C98: JANE S. CASTILLO | D98: Futures Thinking & Strategic Foresight Coordinator | E98: 101 | G98: 2025-313 | I98: Stranded Wire (3.5mm) | J98: 10 | K98: meters | L98: 40 | M98: =SUM(J98*L98) -> 400 | N98: 65 | O98: =SUM(J98*N98) -> 650 | P98: supplies & materials for renovation of the Futures Thinking office | Q98: RDET-Futures Thinking | R98: October 10, 2025 | S98: October 15, 2025 | T98: October 15, 2025 | U98: October 21, 2025 | V98: October 22, 2025 | W98: E.A.Amboy General Merchandise | X98: October 22, 2025 | Y98: 1005 | Z98: November 6, 2025 | AA98: complete | AB98: for payment-Acctg. | AC98: 02-102101-2025-10-00855
A99: 2025 | B99: September | C99: JANE S. CASTILLO | D99: Futures Thinking & Strategic Foresight Coordinator | E99: 101 | G99: 2025-313 | I99: Surface Type U Box | J99: 2 | K99: pcs | L99: 53 | M99: =SUM(J99*L99) -> 106 | N99: 90 | O99: =SUM(J99*N99) -> 180 | P99: supplies & materials for renovation of the Futures Thinking office | Q99: RDET-Futures Thinking | R99: October 10, 2025 | S99: October 15, 2025 | T99: October 15, 2025 | U99: October 21, 2025 | V99: October 22, 2025 | W99: E.A.Amboy General Merchandise | X99: October 22, 2025 | Y99: 1005 | Z99: November 6, 2025 | AA99: complete | AB99: for payment-Acctg. | AC99: 02-102101-2025-10-00855
A100: 2025 | B100: September | C100: JANE S. CASTILLO | D100: Futures Thinking & Strategic Foresight Coordinator | E100: 101 | G100: 2025-313 | I100: 3-gang Plate | J100: 2 | K100: pcs | L100: 74 | M100: =SUM(J100*L100) -> 148 | N100: 95 | O100: =SUM(J100*N100) -> 190 | P100: supplies & materials for renovation of the Futures Thinking office | Q100: RDET-Futures Thinking | R100: October 10, 2025 | S100: October 15, 2025 | T100: October 15, 2025 | U100: October 21, 2025 | V100: October 22, 2025 | W100: E.A.Amboy General Merchandise | X100: October 22, 2025 | Y100: 1005 | Z100: November 6, 2025 | AA100: complete | AB100: for payment-Acctg. | AC100: 02-102101-2025-10-00855
A101: 2025 | B101: September | C101: JANE S. CASTILLO | D101: Futures Thinking & Strategic Foresight Coordinator | E101: 101 | G101: 2025-313 | I101: 20 Watts LED Bulb | J101: 2 | K101: sets | L101: 286 | M101: =SUM(J101*L101) -> 572 | N101: 490 | O101: =SUM(J101*N101) -> 980 | P101: supplies & materials for renovation of the Futures Thinking office | Q101: RDET-Futures Thinking | R101: October 10, 2025 | S101: October 15, 2025 | T101: October 15, 2025 | U101: October 21, 2025 | V101: October 22, 2025 | W101: E.A.Amboy General Merchandise | X101: October 22, 2025 | Y101: 1005 | Z101: November 6, 2025 | AA101: complete | AB101: for payment-Acctg. | AC101: 02-102101-2025-10-00855
A102: 2025 | B102: September | C102: JANE S. CASTILLO | D102: Futures Thinking & Strategic Foresight Coordinator | E102: 101 | G102: 2025-313 | I102: Marine Plywood (3/4 inch) | J102: 1 | K102: pc | L102: 1791 | M102: =SUM(J102*L102) -> 1791 | N102: 2100 | O102: =SUM(J102*N102) -> 2100 | P102: supplies & materials for renovation of the Futures Thinking office | Q102: RDET-Futures Thinking | R102: October 10, 2025 | S102: October 15, 2025 | T102: October 15, 2025 | U102: October 21, 2025 | V102: October 22, 2025 | W102: E.A.Amboy General Merchandise | X102: October 22, 2025 | Y102: 1005 | Z102: November 6, 2025 | AA102: complete | AB102: for payment-Acctg. | AC102: 02-102101-2025-10-00855
A103: 2025 | B103: September | C103: SYRA KARLA C. GORDO | D103: Project Technical Specialist 1 | E103: 165 | G103: 2025-314 | I103: Gasoline (unleaded) | J103: 1 | K103: drum | L103: 20000 | M103: =SUM(J103*L103) -> 20000 | N103: 18150 | O103: =SUM(J103*N103) -> 18150 | P103: for operational needs of the project-charged to S & T Interventions for Sustainable Tourism in Batanes (MOOE-Fuel,Oil and Lubricants) | Q103: RDET-S & T | R103: October 6, 2025 | S103: October 8, 2025 | T103: October 9, 2025 | U103: October 16, 2025 | V103: October 20, 2025 | W103: GDP Trading | X103: October 21, 2025 | Y103: 1005 | Z103: October 28, 2025 | AA103: complete | AB103: for payment-Acctg. | AC103: 07-02-2025-10-0359 | AD103: 6 RFQ's | AE103: 23799/10/22/2025
A104: 2025 | B104: September | C104: SYRA KARLA C. GORDO | D104: Project Technical Specialist 1 | E104: 165 | G104: 2025-314 | I104: Diesel | J104: 1 | K104: drum | L104: 20000 | M104: =SUM(J104*L104) -> 20000 | N104: 17750 | O104: =SUM(J104*N104) -> 17750 | P104: for operational needs of the project-charged to S & T Interventions for Sustainable Tourism in Batanes (MOOE-Fuel,Oil and Lubricants) | Q104: RDET-S & T | R104: October 6, 2025 | S104: October 8, 2025 | T104: October 9, 2025 | U104: October 16, 2025 | V104: October 20, 2025 | W104: GDP Trading | X104: October 21, 2025 | Y104: 1005 | Z104: October 28, 2025 | AA104: complete | AB104: for payment-Acctg. | AC104: 07-02-2025-10-0359
A105: 2025 | B105: September | C105: SHEILA H. YDEL | D105: Admin. Officer IV | G105: 2025-315 | I105: Supply,Delivery and Installation of UPVC Window, Swing Type, 4 Panels Dimension: Width: 150cm, Height: 126cm | J105: 2 | K105: pcs | L105: 21500 | M105: =SUM(J105*L105) -> 43000 | O105: =SUM(J105*N105) -> 0 | P105: replacement of windows in BSC Canteen | Q105: GSO | Y105: GAS20 | AA105: FAILED | AB105: quotation exceeded the budget | AD105: 6 RFQ's
A106: 2025 | B106: September | C106: JANNEL B. BASIUANG | D106: Student Publication Adviser | E106: 165 | F106: Sept. 18-19 | G106: 2025-316 | I106: A4 size Specialty Board | J106: 20 | K106: ballots | L106: 100 | M106: =SUM(J106*L106) -> 2000 | N106: 65 | O106: =SUM(J106*N106) -> 1300 | P106: use for the 2nd day Journalism Seminar & Workshop by the student publication office | Q106: Publication | R106: September 18, 2025 | S106: September 25, 2025 | T106: September 26, 2025 | U106: October 1, 2025 | V106: October 1, 2025 | W106: JPM General Merchandise & Hardware | X106: October 1, 2025 | Y106: SS04 | Z106: October 28, 2025 | AA106: complete | AB106: for payment-Acctg. | AC106: 07-02-2025-09-0333 | AD106: 5 RFQ's | AE106: 13157/10/1/2025
A107: 2025 | B107: September | C107: JANNEL B. BASIUANG | D107: Student Publication Adviser | E107: 165 | G107: 2025-316 | I107: Tote Bag (medium size) | J107: 8 | K107: pcs | L107: 200 | M107: =SUM(J107*L107) -> 1600 | N107: 300 | O107: =SUM(J107*N107) -> 2400 | P107: use for the 2nd day Journalism Seminar & Workshop by the student publication office | Q107: Publication | R107: September 18, 2025 | S107: September 25, 2025 | T107: September 26, 2025 | U107: October 1, 2025 | V107: October 1, 2025 | W107: JPM General Merchandise & Hardware | X107: October 1, 2025 | Y107: SS04 | Z107: October 28, 2025 | AA107: complete | AB107: for payment-Acctg. | AC107: 07-02-2025-09-0333
A108: 2025 | B108: September | C108: JANNEL B. BASIUANG | D108: Student Publication Adviser | E108: 165 | G108: 2025-316 | I108: A4 size Certificate Holder | J108: 11 | K108: pcs | L108: 100 | M108: =SUM(J108*L108) -> 1100 | N108: 80 | O108: =SUM(J108*N108) -> 880 | P108: use for the 2nd day Journalism Seminar & Workshop by the student publication office | Q108: Publication | R108: September 18, 2025 | S108: September 25, 2025 | T108: September 26, 2025 | U108: October 1, 2025 | V108: October 1, 2025 | W108: JPM General Merchandise & Hardware | X108: October 1, 2025 | Y108: SS04 | Z108: October 28, 2025 | AA108: complete | AB108: for payment-Acctg. | AC108: 07-02-2025-09-0333
A109: 2025 | B109: September | C109: SYRA KARLA C. GORDO | D109: Project Technical Specialist 1 | E109: 165 | G109: 2025-317 | I109: Tarpaulin 4H x 8L ft | J109: 1 | K109: pc | L109: 1000 | M109: =SUM(J109*L109) -> 1000 | N109: 864 | O109: =SUM(J109*N109) -> 864 | P109: for promotion of project activities charged to S & T Interventions for Sustainable Tourism in Batanes-MOOE-Other supplies and materials | Q109: RDET-S & T | R109: September 26, 2025 | S109: September 30, 2025 | T109: October 1, 2025 | U109: October 8, 2025 | V109: October 8, 2025 | W109: YCA Printing Services | X109: October 8, 2025 | Y109: 1005 | Z109: October 28, 2025 | AA109: complete | AB109: for payment-Acctg. | AC109: 07-02-2025-10-0345 | AD109: 3 RFQ's | AE109: 363/
A110: 2025 | B110: September | C110: SYRA KARLA C. GORDO | D110: Project Technical Specialist 1 | E110: 165 | G110: 2025-317 | I110: Tarpaulin 4H x 4L ft | J110: 2 | K110: pc | L110: 600 | M110: =SUM(J110*L110) -> 1200 | N110: 432 | O110: =SUM(J110*N110) -> 864 | P110: for promotion of project activities charged to S & T Interventions for Sustainable Tourism in Batanes-MOOE-Other supplies and materials | Q110: RDET-S & T | R110: September 26, 2025 | S110: September 30, 2025 | T110: October 1, 2025 | U110: October 8, 2025 | V110: October 8, 2025 | W110: YCA Printing Services | X110: October 8, 2025 | Y110: 1005 | Z110: October 28, 2025 | AA110: complete | AB110: for payment-Acctg. | AC110: 07-02-2025-10-0345
A111: 2025 | B111: September | C111: DOREEN C. CASTILLO | D111: Study 5 Leader | E111: 165 | G111: 2025-318 | I111: LPG Tank medium with Refill | J111: 2 | K111: tank | L111: 7000 | M111: =SUM(J111*L111) -> 14000 | N111: 6490 | O111: =SUM(J111*N111) -> 12980 | P111: for operational needs of the project-charged to S & T Interventions for Sustainable Tourism in Batanes (MOOE-Utility-Cooking Fuel) | Q111: RDET-S & T | R111: October 6, 2025 | S111: October 13, 2025 | T111: October 14, 2025 | U111: October 16, 2025 | V111: October 16, 2025 | W111: Enrinar Trading | X111: October 16, 2025 | Y111: 1005 | Z111: October 28, 2025 | AA111: complete | AB111: for payment-Acctg. | AC111: 07-02-2025-10-0367 | AD111: 5 RFQ's | AE111: 7201/10/16/2025
A112: 2025 | B112: September | C112: DOREEN C. CASTILLO | D112: Study 5 Leader | E112: 165 | G112: 2025-318 | I112: LPG Regulator with gauge | J112: 2 | K112: pc | L112: 650 | M112: =SUM(J112*L112) -> 1300 | N112: 560 | O112: =SUM(J112*N112) -> 1120 | P112: for operational needs of the project-charged to S & T Interventions for Sustainable Tourism in Batanes (MOOE-Utility-Cooking Fuel) | Q112: RDET-S & T | R112: October 6, 2025 | S112: October 13, 2025 | T112: October 14, 2025 | U112: October 16, 2025 | V112: October 16, 2025 | W112: Enrinar Trading | X112: October 16, 2025 | Y112: 1005 | Z112: October 28, 2025 | AA112: complete | AB112: for payment-Acctg. | AC112: 07-02-2025-10-0367
A113: 2025 | B113: September | C113: DOREEN C. CASTILLO | D113: Study 5 Leader | E113: 165 | G113: 2025-318 | I113: LPG Hose with clamp | J113: 6 | K113: meters | L113: 100 | M113: =SUM(J113*L113) -> 600 | N113: 85 | O113: =SUM(J113*N113) -> 510 | P113: for operational needs of the project-charged to S & T Interventions for Sustainable Tourism in Batanes (MOOE-Utility-Cooking Fuel) | Q113: RDET-S & T | R113: October 6, 2025 | S113: October 13, 2025 | T113: October 14, 2025 | U113: October 16, 2025 | V113: October 16, 2025 | W113: Enrinar Trading | X113: October 16, 2025 | Y113: 1005 | Z113: October 28, 2025 | AA113: complete | AB113: for payment-Acctg. | AC113: 07-02-2025-10-0367
A114: 2025 | B114: September | C114: ALETH MEORA | D114: Study Leader (Study 3) | G114: 2025-319 | I114: Supply and Delivery and Installation of: | J114: 1 | K114: lot | L114: 400000 | M114: =SUM(J114*L114) -> 400000 | O114: =SUM(J114*N114) -> 0 | P114: For the Implementation of the S &T Research project study 3 - Charge to 1. Supplies and materials - MOOE-other supplies and materials 2. Delivery -MOOE-Transportation services 3. Labor -MOOE- Contract of Labor | Q114: RDET-S & T | Y114: 1005 | AA114: FAILED | AB114: no supplier quoted | AD114: 4 RFQ's + 1blank
A115: 2025 | B115: September | C115: ALETH MEORA | D115: Study Leader (Study 3) | G115: 2025-319 | I115: 1.Bore well drilling - manual drilling to be required depth of 10-20 meters or until reach the aquifer. | M115: =SUM(J115*L115) -> 0 | O115: =SUM(J115*N115) -> 0 | P115: For the Implementation of the S &T Research project study 3 - Charge to 1. Supplies and materials - MOOE-other supplies and materials 2. Delivery -MOOE-Transportation services 3. Labor -MOOE- Contract of Labor | Q115: RDET-S & T | Y115: 1005
A116: 2025 | B116: September | I116: 2.Monitoring well - must also drill a separate monitoring well at a location and depth specified in the design.monitoring well 10meters away from main bore well(refer to attached design drawing) and the dimension is .70cm and depth required is 10-20meters or until reach the aquifer. | M116: =SUM(J116*L116) -> 0 | O116: =SUM(J116*N116) -> 0 | Q116: RDET-S & T | Y116: 1005
A117: 2025 | B117: September | I117: 3.Supply and Installation of filter Materials - shall supply and install boulder, gravel, and sand filter materials.Placed at the bottom of the bore well. (As per standard) | M117: =SUM(J117*L117) -> 0 | O117: =SUM(J117*N117) -> 0 | Q117: RDET-S & T | Y117: 1005
A118: 2025 | B118: September | I118: 4.Supply and Installation of concrete Pipes - shall install concrete pipes of the specified diameter (1.0 meter) and length (1.0 meter). supplier/contractor also provide reinforce concrete cover with man hole. (NOTE: the concrete is already available at site). | M118: =SUM(J118*L118) -> 0 | O118: =SUM(J118*N118) -> 0 | Q118: RDET-S & T | Y118: 1005
A119: 2025 | B119: September | I119: Site: Sitio Mutchung,Kayvaluganan,Uyugan | M119: =SUM(J119*L119) -> 0 | O119: =SUM(J119*N119) -> 0 | Q119: RDET-S & T | Y119: 1005
A120: 2025 | B120: September | I120: *all works shall refer to attached Design Drawing TOR and Coordinate to BSC project tittled:Science and Technology-Based Intervensions for Sustainable Tourism in Batanes. | M120: =SUM(J120*L120) -> 0 | O120: =SUM(J120*N120) -> 0 | Q120: RDET-S & T | Y120: 1005
...

Sheet PR
A3: Republic of the Philippines
A4: BATANES STATE COLLEGE
A5: Basco, Batanes
A7: PURCHASE REQUEST
D9: PR No. | E9: =DATA!G204 -> 2025-343 | F9: Date
A10: Department: | D10: SAI No.: | E10: .
A11: Section: | B11: =DATA!Y204 -> SS09 | D11: OBR#
A12: Ref. No.: | B12: 2509-SS09-343
A14: Qty | B14: Unit of Issue | D14: Item Description | F14: Stock No. | G14: Estimated
G15: Unit Cost | H15: Total Cost
A16: =DATA!J204 -> 0 | B16: =DATA!K204 -> 0 | D16: =DATA!I204 -> DAY 1-Opening Day | G16: =DATA!L204 -> 0 | H16: =SUM(A16*G16) -> 0
A17: =DATA!J205 -> 12 | B17: =DATA!K205 -> kls | D17: =DATA!I205 -> Chicken (whole) | G17: =DATA!L205 -> 280 | H17: =SUM(A17*G17) -> 3360
A18: =DATA!J206 -> 2 | B18: =DATA!K206 -> bottle | D18: =DATA!I206 -> Vinegar (1 Ltr.) | G18: =DATA!L206 -> 90 | H18: =SUM(A18*G18) -> 180
A19: =DATA!J207 -> 1 | B19: =DATA!K207 -> bottle | D19: =DATA!I207 -> Soy Sauce (1Ltr) | G19: =DATA!L207 -> 90 | H19: =SUM(A19*G19) -> 90
A20: =DATA!J208 -> 1 | B20: =DATA!K208 -> pack | D20: =DATA!I208 -> Juice (Blue Lemonade) | G20: =DATA!L208 -> 200 | H20: =SUM(A20*G20) -> 200
A21: =DATA!J209 -> 0 | B21: =DATA!K209 -> 0 | D21: =DATA!I209 -> DAY 2- Activity Day | G21: =DATA!L209 -> 0 | H21: =SUM(A21*G21) -> 0
A22: =DATA!J210 -> 10 | B22: =DATA!K210 -> kls | D22: =DATA!I210 -> Pork & Pork Liver | G22: =DATA!L210 -> 380 | H22: =SUM(A22*G22) -> 3800
A23: =DATA!J211 -> 1 | B23: =DATA!K211 -> kls | D23: =DATA!I211 -> Carrots | G23: =DATA!L211 -> 320 | H23: =SUM(A23*G23) -> 320
A24: =DATA!J212 -> 1 | B24: =DATA!K212 -> pack | D24: =DATA!I212 -> Juice (Blue Lemonade) | G24: =DATA!L212 -> 200 | H24: =SUM(A24*G24) -> 200
A25: =DATA!J213 -> 2 | B25: =DATA!K213 -> pcs | D25: =DATA!I213 -> Yellow Ginger (Hama-100g) | G25: =DATA!L213 -> 150 | H25: =SUM(A25*G25) -> 300
A26: =DATA!J214 -> 50 | B26: =DATA!K214 -> pcs | D26: =DATA!I214 -> Coffee (Twin Pack) | G26: =DATA!L214 -> 20 | H26: =SUM(A26*G26) -> 1000
A27: =DATA!J215 -> 10 | B27: =DATA!K215 -> ballots | D27: =DATA!I215 -> Assorted Biscuits | G27: =DATA!L215 -> 100 | H27: =SUM(A27*G27) -> 1000
H28: =SUM(A28*G28) -> 0
H29: =SUM(A29*G29) -> 0
H30: =SUM(A30*G30) -> 0
H31: =SUM(A31*G31) -> 0
H32: =SUM(A32*G32) -> 0
H33: =SUM(A33*G33) -> 0
H34: =SUM(A34*G34) -> 0
H35: =SUM(A35*G35) -> 0
H36: =SUM(A36*G36) -> 0
H37: =SUM(A37*G37) -> 0
H38: =SUM(A38*G38) -> 0
H39: =SUM(A39*G39) -> 0
... H50: =SUM(A50*G50) -> 0
A51: =DATA!J260 -> 0 | B51: =DATA!K54 -> liter | D51: =DATA!I54 -> Acrylic Based Paint - Red | G51: =DATA!L260 -> 0 | H51: =SUM(A51*G51) -> 0
A52: =DATA!J261 -> 0 | B52: =DATA!K55 -> liter | D52: =DATA!I55 -> Acrylic Based Paint - Blue | G52: =DATA!L261 -> 0 | H52: =SUM(A52*G52) -> 0
A53: =DATA!J262 -> 0 | B53: =DATA!K56 -> liter | D53: =DATA!I56 -> Acrylic Based Paint - Yellow | G53: =DATA!L262 -> 0 | H53: =SUM(A53*G53) -> 0
A54: =DATA!J263 -> 0 | B54: =DATA!K57 -> liter | D54: =DATA!I57 -> Acrylic Based Paint - Black | G54: =DATA!L263 -> 0 | H54: =SUM(A54*G54) -> 0
A55: =DATA!J264 -> 0 | B55: =DATA!K58 -> pail | D55: =DATA!I58 -> Acrylic Based Paint - White | G55: =DATA!L264 -> 0 | H55: =SUM(A55*G55) -> 0
A56: =DATA!J265 -> 0 | B56: =DATA!K59 -> set | D56: =DATA!I59 -> Artist Paint Brush | G56: =DATA!L265 -> 0 | H56: =SUM(A56*G56) -> 0
A57: =DATA!J266 -> 0 | B57: =DATA!K60 -> pcs | D57: =DATA!I60 -> Paint Roller (4 inches) | G57: =DATA!L266 -> 0 | H57: =SUM(A57*G57) -> 0
A58: =DATA!J267 -> 0 | B58: =DATA!K61 -> pcs | D58: =DATA!I61 -> 4ft x 8ft Galvanized Plain Sheet, 25 Gauge | G58: =DATA!L267 -> 0 | H58: =SUM(A58*G58) -> 0
A59: =DATA!J268 -> 0 | B59: =DATA!K62 -> pcs | D59: =DATA!I62 -> 2inch x 3inch x 12ft Palochina Wood | G59: =DATA!L268 -> 0 | H59: =SUM(A59*G59) -> 0
B60: =DATA!K63 -> pcs | D60: =DATA!I63 -> 3inch Log Screw with Anchor | G60: =DATA!L304 -> 0 | H60: =SUM(A60*G60) -> 0
B61: =DATA!K64 -> kgs | D61: =DATA!I64 -> 1.5inch Common Nail | G61: =DATA!L305 -> 0 | H61: =SUM(A61*G61) -> 0
B62: =DATA!K65 -> kgs | D62: =DATA!I65 -> 3inch Common Nail | G62: =DATA!L306 -> 0 | H62: =SUM(A62*G62) -> 0
B63: =DATA!K66 -> kgs | D63: =DATA!I66 -> 4inch Common Nail' | G63: =DATA!L307 -> 0 | H63: =SUM(A63*G63) -> 0
B64: =DATA!K67 -> months | D64: =DATA!I67 -> Internet Service Provider Subscription | G64: =DATA!L308 -> 0 | H64: =SUM(A64*G64) -> 0
B65: =DATA!K68 -> tank | D65: =DATA!I274 -> 0 | G65: =DATA!L309 -> 0 | H65: =SUM(A65*G65) -> 0
B66: =DATA!K69 -> pcs | D66: =DATA!I275 -> 0 | G66: =DATA!L310 -> 0 | H66: =SUM(A66*G66) -> 0
B67: =DATA!K70 -> pcs | D67: =DATA!I276 -> 0 | G67: =DATA!L311 -> 0 | H67: =SUM(A67*G67) -> 0
B68: =DATA!K71 -> pcs | D68: =DATA!I277 -> 0 | G68: =DATA!L312 -> 0 | H68: =SUM(A68*G68) -> 0
B69: =DATA!K72 -> bottles | D69: =DATA!I278 -> 0 | G69: =DATA!L313 -> 0 | H69: =SUM(A69*G69) -> 0
B70: =DATA!K73 -> pcs | D70: =DATA!I279 -> 0 | G70: =DATA!L314 -> 0 | H70: =SUM(A70*G70) -> 0
B71: =DATA!K74 -> pcs | D71: =DATA!I280 -> 0 | G71: =DATA!L315 -> 0 | H71: =SUM(A71*G71) -> 0
B72: =DATA!K75 -> bottles | D72: =DATA!I281 -> 0 | G72: =DATA!L316 -> 0 | H72: =SUM(A72*G72) -> 0
B73: =DATA!K76 -> bottles | D73: =DATA!I453 -> 0 | G73: =DATA!L317 -> 0
B74: =DATA!K77 -> pcs | D74: =DATA!I454 -> 0 | G74: =DATA!L318 -> 0
H75: =SUM(H16:H50) -> 10450
A76: Purpose: | B76: =DATA!P205 -> for BEACON 2025 "Building Empowered and Accountable Councils of Noble BSCians"
F77: Approved By:
A79: Signature:
A80: Printed Name: | B80: =DATA!C204 -> ELEIN T. ESPERANZA | F80: DJOVI REGALA DURANTE,DPA
A81: Designation: | B81: =DATA!D6 -> Project Technical Specialist 1 | F81: SUC President I
A82: Date:

Sheet ResoSVP (2)
A6: BAC Resolution Recommending Alternative Mode of Procurement under Small Value Procurement
B7: BAC Resolution No. | D7: =PR!B12 -> 2509-SS09-343
A9: WHEREAS, Section 48 Rule XVI of the Revised Implementing Rules and Regulations of RA 9184 allows Alternative Mode of Procurement subject to prior approval of the HOPE thru Annual Procurement Plan (APP) and only to promote economy and efficiency;
A10: WHEREAS, Section 53.9 allows Small Value Procurement provided that the procurement does not fall under shopping in Section 52 of this IRR and the amount involved does not exceed the thresholds prescribed in Annex "H" of this IRR;
A11: WHEREAS, Appendix 18, Section 3.e on the Guidelines for Shopping and Small Value Procurement provides an Abstract of Quotations shall be prepared setting forth the names of those who responded to the RFQ's right after the deadline for submission except for shopping under Section 52.1(b), where at least three (3) price quotations (RFQ) must be obtained;
A12: WHEREAS, Annex "H" of the Consolidated Guidelines for the Alternative Methods of Procurement prescribed under Section V, Paragraph D.8.b.ii that the BAC shall prepare and send the RFQs/RFPs to at least three (3) suppliers, contractors or consultants of known qualifications where receipt of at least one (1) quotations is sufficient to proceed with the evaluation thererof;
A13: WHEREAS, Purchase Request No. | D13: =PR!E9 -> 2025-343 | E13: involves the procurement of
A14: Health Insurance (Age Range: 20-65 years old) Covers the following: Accidental Medical Reimbursement,Daily Hos[ital Allowance (Max 60 days),Accidental Death,Disablement and Disemberment,Unprovoked Murder & Assault, Accidental Burial Assistance--for medical insurance of the Bread & Pastry Production participants for (Batch 1, TWSP)
A15: with the approved budget of | D15: =PR!H75 -> 10450
A16: WHEREAS, the default mode of evaluation shall be on a lot basis which means that the determination of the single/lowest calculated and responsive bid (S/LCRB) is the total amount of offered unit price multiply by the required quantity;
A18: NOW THEREFORE, we, the members of the Bids and Awards Committee hereby RESOLVE as it is hereby RESOLVED to recommend to the College President to adopt Alternative Mode of Procurement under Small Value Procurement for the said transaction;
A20: RESOLVED FINALLY, at the Batanes State College, this
A21: Recommending Approval:
A24: RHOUPHELINE AYA A. CADIZ | C24: FORTUNATO PHILIP A. CABUGAO | E24: EMILYN D. ALUETA
A25: BAC Member | C25: BAC Member | E25: BAC Member
A28: =PR!B80 -> ELEIN T. ESPERANZA | C28: PHILIP ULYSSES T. CASTILLO | E28: DOREEN C. CASTILLO
A29: End-User/Provisional Member | C29: BAC Vice Chairperson | E29: BAC Chairperson
A30: BRYAN H. CIELO
A31: DELMA G. MALUPA-ABAD
A32: EDWIN F.MACABALLUG, Ph.D.
A33: LIEZL P. DELA CRUZ
A34: RODERICK Y. ABAD
A35: VILMA D. BACCAY
A36: ESTEBAN C. BADAJOS
A37: LEOBERT L. BANZALI
A38: MIAH DAPHNIE B. BUENAFE
A39: GLORIA N. CABIZON
A40: FORTUNATO PHILIP A. CABUGAO
A41: RICARDO Q. CABUGAO, JR.
... A83: LEONARDO CABRERA

Sheet AResoSVP (2)
A6: Approval of BAC Resolution Recommending Alternative Mode of Procurement under Small Value Procurement
B7: BAC Resolution No. | D7: =PR!B12 -> 2509-SS09-343
A9: WHEREAS, Section 48 Rule XVI of the Revised Implementing Rules and Regulations of RA 9184 allows Alternative Mode of Procurement subject to prior approval of the HOPE thru Annual Procurement Plan (APP) and only to promote economy and efficiency;
A10: WHEREAS, Section 53.9 allows Small Value Procurement provided that the procurement does not fall under shopping in Section 52 of this IRR and the amount involved does not exceed the thresholds prescribed in Annex "H" of this IRR;
A11: WHEREAS, Appendix 18, Section 3.e on the Guidelines for Shopping and Small Value Procurement provides an Abstract of Quotations shall be prepared setting forth the names of those who responded to the RFQ's right after the deadline for submission except for shopping under Section 52.1(b), where at least three (3) price quotations (RFQ) must be obtained;
A12: WHEREAS, Annex "H" of the Consolidated Guidelines for the Alternative Methods of Procurement prescribed under Section V, Paragraph D.8.b.ii that the BAC shall prepare and send the RFQs/RFPs to at least three (3) suppliers, contractors or consultants of known qualifications where receipt of at least one (1) quotations is sufficient to proceed with the evaluation thererof;
A13: WHEREAS, Purchase Request No. | D13: =PR!E9 -> 2025-343 | E13: involves the procurement of
A14: Health Insurance (Age Range: 20-65 years old) Covers the following: Accidental Medical Reimbursement,Daily Hos[ital Allowance (Max 60 days),Accidental Death,Disablement and Disemberment,Unprovoked Murder & Assault, Accidental Burial Assistance--for medical insurance of the Bread & Pastry Production participants for (Batch 1, TWSP) | H14: Items:
A15: with the approved budget of | D15: =PR!H75 -> 10450
A16: WHEREAS, the default mode of evaluation shall be on a lot basis which means that the determination of the single/lowest calculated and responsive bid (S/LCRB) is the total amount of offered unit price multiply by the required quantity;
A17: NOW THEREFORE, I,DR.DJOVI R. DURANTE, Head of the Procuring Entity (HOPE) by virtue of the authority vested in me by the Board of Trustees of this Institution and after taking into consideration the merits and legal bases of the recommendation of the members of the Bids and Awards Committee (BAC) do hereby APPROVE the foregoing recommendation and adoption of Alternative Mode of Procurement under Small Value Procurement;
A19: APPROVED FINALLY, at the Batanes State College, this | F19: ___________________
B25: DJOVI REGALA DURANTE,DPA
B26: SUC President I

Sheet RFQ_ (2)
E6: Date:
A7: REQUEST FOR PRICE QUOTATION
A8: Biang's Catering Services
A9: Please give us your best and final price offer for the item/s listed below, have this signed and submit this by you or by your duly authorized representative WITHIN SEVEN (7) CALENDAR DAYS upon receipt to Procurement Section, Batanes State College.
A11: NOTE: | B11: 1. THE DEFAULT MODE OF PRICE EVALUATION SHALL BE ON A LOT BASIS, OTHERWISE PER ITEMS EVALUATION SHALL BE USED IF THERE WILL BE LACKING ITEMS IN ALL RFQ's AND SUBJECT TO END-USER APPROVAL., (Clause 15.2, Section I, Instruction to Bidders of the Philippine Bidding Documents for goods and infrastructure projects)
B12: 2. DELIVERY PERIOD: Thirty (30) calendar days.
B13: 3. Submission of price quotation shall be in sealed envelope.
B14: 4. THE APPROVED BUDGET FOR THIS PROCUREMENT IS
B15: =PR!H75 -> 10450 | D15: (GPPB Resolution No. 09-2009)
B16: 5. PURSUANT TO ANNEX "H", APPENDIX A, SECTION II, SUBMISSION OF APPLICABLE DOCUMENTS (e.g.MAYORS/BUSINESS PERMIT, PROFESSIONAL LICENSE/CURRICULUM VITAE (CONSULTING SEERVICES),PHILGEPS CERT. NO., PCAB LICENSE (INFRA), INCOME/BUSINESS TAX RETURN,OMNIBUS SWORN STATEMENT SHALL BE REQUIRED BEFORE THE ISSUANCE OF NOA OR PRIOR TO PAYMENT.
B17: 6. In case the item is not availble, please write "None".
A18: Item # | B18: Qty. | C18: Unit | D18: PARTICULAR | E18: Unit Price | F18: Total
A19: 001 | B19: =PR!A16 -> 0 | C19: =PR!B16 -> 0 | D19: =PR!D16 -> DAY 1-Opening Day
A20: 002
A21: 003
A22: 004
A23: 005
A24: 006
A25: 007
A26: 008
A27: 009
A28: 010
A29: 011
A30: 012
A31: 013
... A33: 015
A34: 016 | B34: =[1]PR!A31 -> 0 | C34: =[1]PR!B31 -> 0 | D34: =[1]PR!D31 -> 0
A35: 017 | B35: =[1]PR!A32 -> 0 | C35: =[1]PR!B32 -> 0 | D35: =[1]PR!D32 -> 0
A36: 018 | B36: =[1]PR!A33 -> 0 | C36: =[1]PR!B33 -> 0 | D36: =[1]PR!D33 -> 0
A37: 019 | B37: =[1]PR!A34 -> 0 | C37: =[1]PR!B34 -> 0 | D37: =[1]PR!D34 -> 0
A38: 020 | B38: =[1]PR!A35 -> 0 | C38: =[1]PR!B35 -> 0 | D38: =[1]PR!D35 -> 0
A39: 021 | B39: =[1]PR!A36 -> 0 | C39: =[1]PR!B36 -> 0 | D39: =[1]PR!D36 -> 0
A40: 022 | B40: =[1]PR!A37 -> 0 | C40: =[1]PR!B37 -> 0 | D40: =[1]PR!D37 -> 0
A41: 023 | B41: =[1]PR!A38 -> 0 | C41: =[1]PR!B38 -> 0 | D41: =[1]PR!D38 -> 0
A42: 024 | B42: =[1]PR!A39 -> 0 | C42: =[1]PR!B39 -> 0 | D42: =[1]PR!D39 -> 0
A43: 025 | B43: =[1]PR!A40 -> 0 | C43: =[1]PR!B40 -> 0 | D43: =[1]PR!D40 -> 0
A44: 026 | B44: =[1]PR!A41 -> 0 | C44: =[1]PR!B41 -> 0 | D44: =[1]PR!D41 -> 0
A45: 027 | B45: =[1]PR!A42 -> 0 | C45: =[1]PR!B42 -> 0 | D45: =[1]PR!D42 -> 0
... A57: 039 | B57: =[1]PR!A54 -> 0 | C57: =[1]PR!B54 -> 0 | D57: =[1]PR!D54 -> 0
A58: 041 | B58: =[2]PR!A55 -> 2 | C58: =[3]PR!B56 -> meter | D58: =[1]PR!D55 -> Single Face P4 HD Outdoor LED Screen (rear maintenance, Full Set Up including controller (Novastar) & receiving card (Novastar) warranty, after sales support & training controller (Novastar) & receiving card (Novastar) warranty, after sales support & training size: 2.88M x 2.88M (9 panels) screen resolution: 720 pixels (W) x 720 pixels (H) Type, movable frame Accessories,replacement module, replacement power supply, replacement receiving card power cable, signal cable
A59: 042 | B59: =[2]PR!A56 -> 1 | C59: =[3]PR!B57 -> pcs | D59: =[1]PR!D56 -> Motorcycle Fuel Injection type, min. 125cc, Specs; a) 4 stroke, SOHC, air cooled b) with electric/ kick start c) 0.9 L engine oil capacity d) N-1-2-3 rotary gear shift pattern e) with disc break for front, drum brake for rear f) wire spoke wheel type g) with 3.8L min. tank fuel capacity h) with digital meter panel i) with manual, constant mesh transmission Inclusion: 1) LTO Registration for 3 years,lisence plate and Insurance 2) Full Face Helmets with clear visor (2 pcs.)
A60: 043 | B60: =[2]PR!A57 -> 2 | C60: =[3]PR!B58 -> can | D60: =[1]PR!D57 -> Paint (white gloss latex) 16L
A61: 044 | B61: =[2]PR!A58 -> 2 | C61: =[3]PR!B59 -> pc | D61: =[1]PR!D58 -> Paint Roller #7
A62: 045 | B62: =[2]PR!A59 -> 50 | C62: =[3]PR!B60 -> pc | D62: =[1]PR!D59 -> Paint Pan
A63: 046 | B63: =[2]PR!A60 -> 4 | C63: =[3]PR!B61 -> pc | D63: =[1]PR!D60 -> Contact Cement Adhesive
A64: 047 | B64: =[2]PR!A61 -> 10 | C64: =[3]PR!B62 -> pc | D64: =[1]PR!D61 -> FDA Approved 5 in 1 PH meter water quality tester TDS/EC/PH/salinity/thermometer digital water quality teste with manual.
A65: 048 | B65: =[2]PR!A62 -> 1 | C65: =[3]PR!B63 -> pc | D65: =[1]PR!D62 -> Cube ice maker machine 220V 60Hz produce 40kg to 1000kg/24 hours with manual
A66: 049 | B66: =[2]PR!A63 -> 1 | C66: =[3]PR!B64 -> pc | D66: =[1]PR!D63 -> Supply ,Delivery and Installation of UPVC Window,swing type,2 Panels Dimension: Width:0.9m, Height:1.7m
A67: 050 | B67: =[2]PR!A64 -> 1 | C67: =[3]PR!B65 -> pc | D67: =[1]PR!D64 -> Supply ,Delivery and Installation of UPVC Window,swing type,6 Panels Dimension: Width:1.97m, Height:1.58m
A68: 051 | B68: =[2]PR!A65 -> 1 | C68: =[3]PR!B66 -> pc | D68: =[1]PR!D65 -> Chicken Maintenance for dual type chicken
A69: 052 | B69: =[2]PR!A66 -> 1 | C69: =[3]PR!B67 -> pc | D69: =[1]PR!D66 -> Motorized grass cutter(2 stroke)
... A94: 077 | B94: =[2]PR!A91 -> 1 | C94: =[3]PR!B92 -> pcs | D94: =[1]PR!D91 -> 0
A95: 078 | B95: =[2]PR!A92 -> 1 | C95: =[3]PR!B93 -> pcs | D95: =[2]PR!D92 -> Food Tong 24.0cm
A96: 079 | B96: =[2]PR!A93 -> 2 | C96: =[3]PR!B94 -> pcs | D96: =[2]PR!D93 -> Serving Spoon 9" stainless steel
A97: 080 | B97: =[2]PR!A94 -> 1 | C97: =[3]PR!B95 -> pcs | D97: =[2]PR!D94 -> Serving Fork
A98: 081 | B98: =[2]PR!A95 -> 1 | C98: =[3]PR!B96 -> pcs | D98: =[2]PR!D95 -> Rice Cooker 45cups 7.8L capacity
A99: 082 | B99: =[2]PR!A96 -> 1 | C99: =[3]PR!B97 -> ream | D99: =[2]PR!D96 -> Heavy Duty Coffee Perculator 100cups 15Liters
A100: 083 | B100: =[2]PR!A97 -> 2 | C100: =[3]PR!B98 -> ream | D100: =[2]PR!D97 -> Tissue Holder
A101: 084 | B101: =[2]PR!A98 -> 1 | C101: =[3]PR!B99 -> pcs | D101: =[2]PR!D98 -> Coffee Spoon 17cm x 3.7cm 12's/10's
E102: Total
A104: After having carefully read and accepted your conditions, I/We have place my /our best and final price offer on the item/s listed above.
E105: Very truly yours,
A107: Printed Name/Signature
E108: DOREEN C. CASTILLO
A109: Ref.# | B109: =PR!B12 -> 2509-SS09-343 | E109: BAC Chairperson

Sheet RFQ-Travel)
A1: Republic of the Philippines
A2: BATANES STATE COLLEGE
A3: Basco, Batanes
E4: Date:
A5: REQUEST FOR PRICE QUOTATION
B6: MOJR Construction Trading & General Services, Ltd, Co. | C6: MOJR Construction Trading & General Services, Ltd, Co. | D6: MOJR Construction Trading & General Services, Ltd, Co.
A7: Please give us your best and final price offer for the item/s listed below, have this signed and submit this by you or by your duly authorized representative WITHIN SEVEN (7) CALENDAR DAYS upon receipt to Procurement Section, Batanes State College.
A9: NOTE: | B9: 1. THE DEFAULT MODE OF PRICE EVALUATION SHALL BE ON A LOT BASIS, OTHERWISE PER ITEMS EVALUATION SHALL BE USED IF THERE WILL BE LACKING ITEMS IN ALL RFQ's AND SUBJECT TO END-USER APPROVAL., (Clause 15.2, Section I, Instruction to Bidders of the Philippine Bidding Documents for goods and infrastructure projects)
B10: 2. DELIVERY PERIOD: Thirty (30) calendar days.
B11: 3. Submission of price quotation shall be in sealed envelope.
B12: 4. THE APPROVED BUDGET FOR THIS PROCUREMENT IS
D13: (GPPB Resolution No. 09-2009)
B14: 5. PURSUANT TO ANNEX "H", APPENDIX A, SECTION II, SUBMISSION OF APPLICABLE DOCUMENTS (e.g.MAYORS/BUSINESS PERMIT, PROFESSIONAL LICENSE/CURRICULUM VITAE (CONSULTING SEERVICES),PHILGEPS CERT. NO., PCAB LICENSE (INFRA), INCOME/BUSINESS TAX RETURN,OMNIBUS SWORN STATEMENT SHALL BE REQUIRED BEFORE THE ISSUANCE OF NOA OR PRIOR TO PAYMENT.
B15: 6. In case the item is not availble, please write "None".
A16: Item # | B16: Qty. | C16: Unit | D16: PARTICULAR | E16: Unit Price | F16: Total
A17: 001 | B17: 1 | C17: pax | D17: Plane Ticket-Basco to Manila (Sept. 6, 2023)
A18: 002 | B18: 1 | C18: pax | D18: Plane Ticket-Manila to Basco (Sept. 13, 2023)
A19: 003
A20: 004
A21: 005
A22: 006
A23: 007
A24: 008
A25: 009
A26: 010
A27: 011
A28: 012
A29: 013
A30: 014
... A33: 017
A34: 018 | J34: graphite pencil 12b
A35: 019 | J35: graphite pencil 8b
A36: 020 | J36: graphite pencil 6b
A37: 021 | J37: graphite pencil 4b
A38: 022 | J38: graphite pencil 2b
A39: 023 | J39: graphite pencil HB
A40: 024
A41: 025 | B41: =PR!#REF! -> #REF! | C41: =PR!#REF! -> #REF! | D41: =PR!#REF! -> #REF!
A42: 026 | B42: =PR!#REF! -> #REF! | C42: =PR!#REF! -> #REF! | D42: =PR!#REF! -> #REF!
A43: 027 | B43: =PR!#REF! -> #REF! | C43: =PR!#REF! -> #REF! | D43: =PR!#REF! -> #REF!
A44: 028 | B44: =PR!#REF! -> #REF! | C44: =PR!#REF! -> #REF! | D44: =PR!#REF! -> #REF!
A45: 029 | B45: =PR!#REF! -> #REF! | C45: =PR!#REF! -> #REF! | D45: illustration board 20”x30” | J45: illustration board 20”x30”
A46: 030 | B46: =PR!#REF! -> #REF! | C46: =PR!#REF! -> #REF! | D46: illustration board 10”x15” | G46: 11/29/22 | H46: 3:54PM | I46: Gael | J46: illustration board 10”x15”
A47: 031 | B47: =PR!#REF! -> #REF! | C47: =PR!#REF! -> #REF! | D47: illustration board 15”x20” | J47: illustration board 15”x20”
A48: 032 | B48: =PR!#REF! -> #REF! | C48: =PR!#REF! -> #REF! | D48: =PR!#REF! -> #REF!
A49: 033 | B49: =PR!#REF! -> #REF! | C49: =PR!#REF! -> #REF! | D49: 90 ml sap green | J49: 90 ml sap green
A50: 034 | B50: =PR!#REF! -> #REF! | C50: =PR!#REF! -> #REF! | D50: 90 ml raw sienna | J50: 90 ml raw sienna
A51: 035 | B51: =PR!#REF! -> #REF! | C51: =PR!#REF! -> #REF! | D51: 90 ml burnt umber | J51: 90 ml burnt umber
A52: 036 | B52: =PR!#REF! -> #REF! | C52: =PR!#REF! -> #REF! | D52: 90 ml payne’s gray | J52: 90 ml payne’s gray
A53: 037 | B53: =PR!#REF! -> #REF! | C53: =PR!#REF! -> #REF! | D53: 90 ml titanium white | J53: 90 ml titanium white
A54: 038 | B54: =PR!#REF! -> #REF! | C54: =PR!#REF! -> #REF! | D54: 90 ml cadmium orange hue | J54: 90 ml cadmium orange hue
A55: 039 | B55: =PR!A25 -> 2 | C55: =PR!B25 -> pcs | D55: 90 ml yellow light hue | J55: 90 ml yellow light hue
A56: 040 | B56: =PR!A26 -> 50 | C56: =PR!B26 -> pcs | D56: 90 ml ultramarine blue | J56: 90 ml ultramarine blue
A57: 041 | B57: =PR!A27 -> 10 | C57: =PR!B27 -> ballots | D57: 90 ml cadmium red light hue | J57: 90 ml cadmium red light hue
A58: 042 | B58: =PR!A28 -> 0 | C58: =PR!B28 -> 0 | D58: 90 ml hooker’s green hue | J58: 90 ml hooker’s green hue
A59: 043 | D59: =PR!D29 -> 0
A60: 044 | D60: =PR!D30 -> 0
A61: 045 | D61: =PR!D31 -> 0
A62: 046 | D62: =PR!D32 -> 0
A63: 047 | D63: =PR!D33 -> 0
A64: 048 | D64: =PR!D34 -> 0
A65: 049 | D65: =PR!D35 -> 0
A66: 050 | D66: =PR!D36 -> 0
A67: 051 | D67: =PR!D37 -> 0
A68: 052 | D68: =PR!D38 -> 0
A69: 053 | D69: =PR!D39 -> 0
A70: 054 | D70: =PR!D40 -> 0
... A100: 084 | D100: =PR!D70 -> 0
F101: Total:
A102: After having carefully read and accepted your conditions, I/We have place my /our best and final price offer on the item/s listed above.
A104: Printed Name/Signature | E104: Very truly yours,
E107: DOREEN C. CASTILLO
A108: Ref.# | E108: BAC Chairperson

Sheet AckReceipt
A1: Acknowledgement for Request for Quotation
A2: RIS# | B2: =PR!B12 -> 2509-SS09-343
A3: No. | B3: Supplier | F3: Received by: | G3: Date & Time:
B4: JPM Gen. Mdse. & Hardware
B5: Thine-line Trading
B6: J-Tech Trading & Services
B7: MDAC Trading & Compuserve
B8: FVA Gen Mdse & Construction Supply
B10: GDP Trading
B11: EA Amboy Gen Mdse
B12: L & R's Hontomin Gen Mdse
B13: Davocol's Gen. Mdse.
B14: RCJ Hardware & Gen Mdse
B15: Fitero's Gen Mdse & Electronic Supply
B16: Lar & San's Store
... B18: Wilmerson Gen Mdse
B19: FMG Trading & Construction Supply | C19: q
B20: MG Hubalde Gen Mdse
B21: Basco Cable TV Services, Inc.
B22: Berlen's Store
B23: Melad's Gen. Mdse
B24: R. A. Electronics
B25: RJ General Merchandise
B26: Batanes Multi-Purpose Cooperative, Inc.
B27: Romy & Ava's Store
B28: J-nell's Gen Mdse
B29: Impression Digital Printing Solutions
B30: Golden Press
B31: Tawsen's Agri-Venture & Souvenirs
... B60: Sophia Marie Store
A61: 1 | B61: Biang's Catering Services
A62: 2 | B62: AZ Blue Box Café
A63: 3 | B63: Doque's Congie Hauz café
A64: 4
A65: 5 | J65: zz
A66: 6
A67: 7
A68: NOTE: | B68: 1. MODE OF PRICE EVALUATION SHALL BE ON A LOT BASIS, OTHERWISE PER ITEMS EVALUATION SHALL BE USED IF THERE WILL BE LACKING ITEMS IN ALL RFQ'S AND THE END-USER AGREED, . (Clause 15.2, Section II, Instructions to Bidders of the Philippine Bidding Documents for goods and infrastructure projects)
B69: 2. DELIVERY PERIOD: Thirty (30) calendar days.
B70: 3. WARRANTY SHALL BE FOR A PERIOD OF SIX (6) MONTHS FOR SUPPLIES AND MATERIALS, ONE (1) YEAR FOR EQUIPMENT, FROM THE DATE OF ACCEPTANCE BY THE PROCURING ENTITY.
B71: 4. THE APPROVED BUDGET CEILING FOR THIS PROCUREMENT IS PHP (GPPB Resolution no. 09-2009)
B72: =PR!H75 -> 10450
B73: 5. PRICE VALIDITY SHALL BE OR THE PERIOD OF 30 CALENDAR DAYS.
B74: 6. BIDDERS SHALL SUBMIT ORIGINAL BROCHURES SHOWING SPECIFICATIONS OF THE PRODUCT BEING OFFERED IF APPLICABLE.
A75: In compliance with GPPB Resolution No. 09-2009
B77: Retrieval of Request for Quotation
A79: No. | B79: Supplier | E79: Released by: | F79: Date & Time: | G79: Remarks | N79: k
A80: 1 | B80: Biang's Catering Services
A81: 2 | B81: AZ Blue Box Café
A82: 3 | B82: Doque's Congie Hauz café
A83: 4
A84: 5
A85: 6
A86: 7
A87: 8

Sheet Abstract  (2)
A2: ABSTRACT OF QUOTATION
B4: (x) Furnishing/delivery of supplies, and materials or equipment | G4: Bids opened at Basco, Batanes
B5: ( x ) Furnishing Labor, services, etc. | I5: 45910
B6: ( ) Rental or use of transportation facilities equipment, quarters, rooms, lot or space, etc.
B8: To be furnished at the | D8: BATANES STATE COLLEGE
D9: (State place or site of Office or project where articles or services be furnished or returned)
A11: NAME OF ARTICLES OR SERVICES TO BE FURNISHED, RENDERED OR FACILITIES TO BE RENTED
F14: JPM Gen. Mdse. & Hardware
F15: Thine-line Trading
F16: J-Tech Trading & Services
F17: Mulong Ydel
F18: MDAC Trading & Compuserve
F19: FVA Gen Mdse & Construction Supply
F20: MKM Hardware
F21: GDP Trading
F22: EA Amboy Gen Mdse
F23: L & R's Hontomin Gen Mdse
F24: Davocol's Gen. Mdse.
F25: RCJ Hardware & Gen Mdse
... F86: Valiente Food Producer
F87: =DATA!W6 -> Doque's Congie Hauz | G87: Biang's Catering Services | H87: AZ Blue Box Café
A89: =PR!D16 -> DAY 1-Opening Day | F89: =DATA!O6 -> 21000 | G89: not available | H89: none
A103: =PR!D30 -> 0 | F103: =DATA!O219 -> 3500 | G103: 5200 | H103: 7600 | I103: none | J103: none
A104: =PR!D31 -> 0 | F104: =DATA!O220 -> 200 | G104: 600 | H104: 960 | I104: none | J104: none
A105: =PR!D32 -> 0 | B105: Bond paper, A4 size | C105: Bond paper, A4 size | D105: Bond paper, A4 size | E105: Bond paper, A4 size | F105: =DATA!O221 -> 900 | G105: 4800 | H105: 5960 | I105: none | J105: none
A106: =PR!D33 -> 0 | B106: Bond paper, A4 size | C106: Bond paper, A4 size | D106: Bond paper, A4 size | E106: Bond paper, A4 size | F106: =DATA!O222 -> 1500 | G106: 4400 | H106: 3960 | I106: none | J106: none
A107: =PR!D34 -> 0 | B107: Bond paper, A4 size | C107: Bond paper, A4 size | D107: Bond paper, A4 size | E107: Bond paper, A4 size | F107: =DATA!O223 -> 800 | G107: 11500 | H107: 6800 | I107: none | J107: none
A108: =PR!D35 -> 0 | B108: Bond paper, A4 size | C108: Bond paper, A4 size | D108: Bond paper, A4 size | E108: Bond paper, A4 size | F108: =DATA!O224 -> 1800 | G108: 8400 | H108: 13480 | I108: none | J108: none
A109: =PR!D36 -> 0 | B109: Bond paper, A4 size | C109: Bond paper, A4 size | D109: Bond paper, A4 size | E109: Bond paper, A4 size | F109: =DATA!O225 -> 500 | G109: 11000 | H109: 17600 | I109: none | J109: none
A110: =PR!D37 -> 0 | B110: Bond paper, A4 size | C110: Bond paper, A4 size | D110: Bond paper, A4 size | E110: Bond paper, A4 size | F110: =DATA!O226 -> 315 | G110: 100 | H110: 1360 | I110: none | J110: none
A111: =PR!D38 -> 0 | B111: Bond paper, A4 size | C111: Bond paper, A4 size | D111: Bond paper, A4 size | E111: Bond paper, A4 size | F111: =DATA!O227 -> 330 | G111: 5600 | H111: 5800 | I111: none | J111: none
A112: =PR!D39 -> 0 | B112: Bond paper, A4 size | C112: Bond paper, A4 size | D112: Bond paper, A4 size | E112: Bond paper, A4 size | F112: =DATA!O228 -> 6600 | G112: 45600 | H112: 35880 | I112: none | J112: none
A113: =PR!D40 -> 0 | B113: Bond paper, A4 size | C113: Bond paper, A4 size | D113: Bond paper, A4 size | E113: Bond paper, A4 size | F113: =DATA!O229 -> 1300 | G113: 18000 | H113: 14800 | I113: none | J113: none
A114: =PR!D41 -> 0 | B114: Bond paper, A4 size | C114: Bond paper, A4 size | D114: Bond paper, A4 size | E114: Bond paper, A4 size | F114: =DATA!O230 -> 150 | G114: 3200 | H114: 5600 | I114: none | J114: none
A115: =PR!D42 -> 0 | B115: Bond paper, A4 size | C115: Bond paper, A4 size | D115: Bond paper, A4 size | E115: Bond paper, A4 size | F115: =DATA!O231 -> 110 | G115: 7500 | H115: 3240 | I115: none | J115: none
A116: =PR!D43 -> 0 | B116: Bond paper, A4 size | C116: Bond paper, A4 size | D116: Bond paper, A4 size | E116: Bond paper, A4 size | F116: =DATA!O232 -> 275 | G116: 1200 | H116: 2970 | I116: none | J116: none
... A123: =PR!D50 -> 0 | B123: Bond paper, A4 size | C123: Bond paper, A4 size | D123: Bond paper, A4 size | E123: Bond paper, A4 size | F123: =DATA!O239 -> 225 | G123: 5200 | H123: 8800 | I123: none | J123: none
A124: =PR!D51 -> Acrylic Based Paint - Red | B124: Bond paper, A4 size | C124: Bond paper, A4 size | D124: Bond paper, A4 size | E124: Bond paper, A4 size | F124: =DATA!O240 -> 275 | G124: none | H124: none
A125: =PR!D52 -> Acrylic Based Paint - Blue | B125: Bond paper, A4 size | C125: Bond paper, A4 size | D125: Bond paper, A4 size | E125: Bond paper, A4 size | F125: =DATA!O241 -> 250 | G125: none | H125: none
A126: =PR!D53 -> Acrylic Based Paint - Yellow | B126: Bond paper, A4 size | C126: Bond paper, A4 size | D126: Bond paper, A4 size | E126: Bond paper, A4 size | F126: =DATA!O242 -> 180 | G126: none | H126: none
A127: =PR!D54 -> Acrylic Based Paint - Black | B127: Bond paper, A4 size | C127: Bond paper, A4 size | D127: Bond paper, A4 size | E127: Bond paper, A4 size | F127: =DATA!O243 -> 0 | G127: none | H127: none
A128: =PR!D55 -> Acrylic Based Paint - White | B128: Bond paper, A4 size | C128: Bond paper, A4 size | D128: Bond paper, A4 size | E128: Bond paper, A4 size | F128: =DATA!O244 -> 0
A129: =PR!D56 -> Artist Paint Brush | B129: Bond paper, A4 size | C129: Bond paper, A4 size | D129: Bond paper, A4 size | E129: Bond paper, A4 size | F129: =DATA!O245 -> 0
A130: =PR!D57 -> Paint Roller (4 inches) | B130: Bond paper, A4 size | C130: Bond paper, A4 size | D130: Bond paper, A4 size | E130: Bond paper, A4 size | F130: =DATA!O246 -> 0
A131: =PR!D58 -> 4ft x 8ft Galvanized Plain Sheet, 25 Gauge | B131: Bond paper, A4 size | C131: Bond paper, A4 size | D131: Bond paper, A4 size | E131: Bond paper, A4 size | F131: =DATA!O247 -> 0
A132: =PR!D59 -> 2inch x 3inch x 12ft Palochina Wood | B132: Bond paper, A4 size | C132: Bond paper, A4 size | D132: Bond paper, A4 size | E132: Bond paper, A4 size | F132: =DATA!O248 -> 0
A133: =PR!D60 -> 3inch Log Screw with Anchor | B133: Bond paper, A4 size | C133: Bond paper, A4 size | D133: Bond paper, A4 size | E133: Bond paper, A4 size | F133: =DATA!O249 -> 0
A134: =PR!D61 -> 1.5inch Common Nail | B134: Bond paper, A4 size | C134: Bond paper, A4 size | D134: Bond paper, A4 size | E134: Bond paper, A4 size | F134: =DATA!O250 -> 0
A135: =PR!D62 -> 3inch Common Nail | B135: Bond paper, A4 size | C135: Bond paper, A4 size | D135: Bond paper, A4 size | E135: Bond paper, A4 size | F135: =DATA!O251 -> 0
A136: =PR!D63 -> 4inch Common Nail' | B136: Bond paper, A4 size | C136: Bond paper, A4 size | D136: Bond paper, A4 size | E136: Bond paper, A4 size | F136: =DATA!O252 -> 0
A137: =PR!D64 -> Internet Service Provider Subscription | B137: Bond paper, A4 size | C137: Bond paper, A4 size | D137: Bond paper, A4 size | E137: Bond paper, A4 size | F137: =DATA!O253 -> 0
A138: =PR!D65 -> 0 | B138: Bond paper, A4 size | C138: Bond paper, A4 size | D138: Bond paper, A4 size | E138: Bond paper, A4 size | F138: =DATA!O254 -> 0
A139: =PR!D66 -> 0 | B139: Bond paper, A4 size | C139: Bond paper, A4 size | D139: Bond paper, A4 size | E139: Bond paper, A4 size | F139: =DATA!O255 -> 0
... A150: =PR!D77 -> 0 | B150: Bond paper, A4 size | C150: Bond paper, A4 size | D150: Bond paper, A4 size | E150: Bond paper, A4 size | F150: =DATA!O266 -> 0
F151: =DATA!O267 -> 0
F152: =DATA!O268 -> 0
F153: =DATA!O269 -> 0
F154: =DATA!O270 -> 0
F155: =DATA!O271 -> 0
F156: =DATA!O272 -> 0
F157: =DATA!O273 -> 0
F158: =DATA!O274 -> 0
A159: =[1]DATA!I105 -> 0 | B159: Bond paper, A4 size | C159: Bond paper, A4 size | D159: Bond paper, A4 size | E159: Bond paper, A4 size | F159: =DATA!O275 -> 0 | G159: 900 | I159: 900
F160: =DATA!O276 -> 0 | G160: 900 | I160: 900
F161: =DATA!O277 -> 0 | G161: 925 | I161: 925
F162: =DATA!O278 -> 0 | G162: 9300 | I162: 9300
F163: =DATA!O279 -> 0 | G163: 32000 | I163: 32000
F164: =DATA!O280 -> 0 | G164: 9900 | I164: 9900
F165: =DATA!O281 -> 0 | G165: 400 | I165: 400
F166: =DATA!O282 -> 0 | G166: 1500 | I166: 1500
F167: =DATA!O283 -> 0 | G167: 9950 | I167: 9950
F168: =DATA!O284 -> 0 | G168: 1440 | I168: 1440
F169: =DATA!O285 -> 0
F170: =DATA!O286 -> 0
F171: =DATA!O287 -> 0
F172: =DATA!O288 -> 0
F173: =DATA!O289 -> 0
F174: =DATA!O290 -> 0
F175: =DATA!O291 -> 0
F176: =DATA!O292 -> 0
F177: =DATA!O293 -> 0
F178: =DATA!O294 -> 0
F179: =DATA!O295 -> 0
F180: =DATA!O296 -> 0
... F190: =DATA!O306 -> 0
A191: ='[4]SourceData 2022'!H423 -> ipatropium bromide+salbutamol sulfate 200mcg/1mg/ml | F191: =DATA!O307 -> 0
A192: ='[4]SourceData 2022'!H424 -> Salbutamol 2mg/tablet | F192: =DATA!O308 -> 0
A193: ='[4]SourceData 2022'!H425 -> salbutamol inhaler 100mcg/dose | F193: =DATA!O309 -> 0
A194: ='[4]SourceData 2022'!H426 -> salbutamol+fluticasone inhaler 25mcg/125mcg meter dose inhaler | F194: =DATA!O310 -> 0
A195: ='[4]SourceData 2022'!H427 -> zinc oxide +calamine ointment 3.5g | F195: =DATA!O311 -> 0
A196: ='[4]SourceData 2022'!H428 -> cinnarizine 25mg/tablet | F196: =DATA!O312 -> 0
A197: ='[4]SourceData 2022'!H429 -> povidone iodine 60ml | F197: =DATA!O313 -> 0
A198: ='[4]SourceData 2022'!H430 -> gauze pad 4x4 | F198: =DATA!O314 -> 0
A199: ='[4]SourceData 2022'!H431 -> micropore 1 " 3m | F199: =DATA!O315 -> 0
A200: ='[4]SourceData 2022'!H432 -> micropore 1/2 " | F200: =DATA!O316 -> 0
A201: ='[4]SourceData 2022'!H433 -> baby oil 125ml | F201: =DATA!O317 -> 0
A202: ='[4]SourceData 2022'!H434 -> ethyl alochol 500ml 70% | F202: =DATA!O318 -> 0
... A260: ='[4]SourceData 2022'!H492 -> 0 | F260: =DATA!O376 -> 0
F261: =DATA!O377 -> 0
A262: ='[4]SourceData 2022'!H494 -> Printer ink (Y003) | F262: =DATA!O378 -> 0 | G262: =SUM(G89:G109) -> 45900 | H262: =SUM(H89:H127) -> 154360
...

Sheet AOQ Failed
A2: ABSTRACT OF QUOTATION
B4: (x) Furnishing/delivery of supplies, and materials or equipment | G4: Bids opened at Basco, Batanes
B5: ( x ) Furnishing Labor, services, etc. | I5: =NOW() -> 46128.641
B6: ( ) Rental or use of transportation facilities equipment, quarters, rooms, lot or space, etc.
B8: To be furnished at the | D8: BATANES STATE COLLEGE
D9: (State place or site of Office or project where articles or services be furnished or returned)
A11: NAME OF ARTICLES OR SERVICES TO BE FURNISHED, RENDERED OR FACILITIES TO BE RENTED
F14: JPM Gen. Mdse. & Hardware
F15: Thine-line Trading
F16: J-Tech Trading & Services
F17: Mulong Ydel
F18: MDAC Trading & Compuserve
F19: FVA Gen Mdse & Construction Supply
F20: MKM Hardware
F21: GDP Trading
F22: EA Amboy Gen Mdse
F23: L & R's Hontomin Gen Mdse
F24: Davocol's Gen. Mdse.
F25: RCJ Hardware & Gen Mdse
... F86: Valiente Food Producer
F87: GMPI Construction OPC | G87: REMAR Construction | H87: Swift Devt. & Supplies Corp. | I87: JF Gabotero Inc. | J87: MOJR Construction Trading & General Services, Ltd, Co.
A89: =PR!D16 -> DAY 1-Opening Day | F89: withdrawn their quotation | G89: none | H89: no bid | I89: none | J89: no bid
A99: =PR!D26 -> Coffee (Twin Pack)
A100: =PR!D27 -> Assorted Biscuits
A103: =[1]PR!D30 -> 0 | B103: Bond paper, A4 size | C103: Bond paper, A4 size | D103: Bond paper, A4 size | E103: Bond paper, A4 size | F103: =[1]DATA!O29 -> 1400 | G103: none | H103: none
A104: =[1]PR!D31 -> 0 | B104: Bond paper, A4 size | C104: Bond paper, A4 size | D104: Bond paper, A4 size | E104: Bond paper, A4 size | F104: =[1]DATA!O30 -> 1300 | G104: none | H104: none
A105: =[1]PR!D32 -> 0 | B105: Bond paper, A4 size | C105: Bond paper, A4 size | D105: Bond paper, A4 size | E105: Bond paper, A4 size | F105: =[1]DATA!O31 -> 3600 | G105: none | H105: none
A106: =[1]PR!D33 -> 0 | B106: Bond paper, A4 size | C106: Bond paper, A4 size | D106: Bond paper, A4 size | E106: Bond paper, A4 size | F106: 1100 | G106: none | H106: none
A107: =[1]PR!D34 -> 0 | B107: Bond paper, A4 size | C107: Bond paper, A4 size | D107: Bond paper, A4 size | E107: Bond paper, A4 size | F107: =[1]DATA!O33 -> 2400 | G107: none | H107: none
A108: =[1]PR!D35 -> 0 | B108: Bond paper, A4 size | C108: Bond paper, A4 size | D108: Bond paper, A4 size | E108: Bond paper, A4 size | F108: =[1]DATA!O34 -> 150 | G108: none | H108: none
A109: =[1]PR!D36 -> 0 | B109: Bond paper, A4 size | C109: Bond paper, A4 size | D109: Bond paper, A4 size | E109: Bond paper, A4 size | F109: =[1]DATA!O35 -> 165 | G109: none | H109: none
A110: =[1]PR!D37 -> 0 | B110: Bond paper, A4 size | C110: Bond paper, A4 size | D110: Bond paper, A4 size | E110: Bond paper, A4 size | F110: =[1]DATA!O36 -> 1225 | G110: none | H110: none
A111: =[1]PR!D38 -> 0 | B111: Bond paper, A4 size | C111: Bond paper, A4 size | D111: Bond paper, A4 size | E111: Bond paper, A4 size | F111: =[1]DATA!O37 -> 1350 | G111: none | H111: none
A112: =[1]PR!D39 -> 0 | B112: Bond paper, A4 size | C112: Bond paper, A4 size | D112: Bond paper, A4 size | E112: Bond paper, A4 size | F112: =[1]DATA!O38 -> 1225 | G112: none | H112: none
A113: =[1]PR!D40 -> 0 | B113: Bond paper, A4 size | C113: Bond paper, A4 size | D113: Bond paper, A4 size | E113: Bond paper, A4 size | F113: =[1]DATA!O39 -> 2200 | G113: none | H113: none
A114: =[1]PR!D41 -> 0 | B114: Bond paper, A4 size | C114: Bond paper, A4 size | D114: Bond paper, A4 size | E114: Bond paper, A4 size | F114: =[1]DATA!O40 -> 1050 | G114: none | H114: none
A115: =[1]PR!D42 -> 0 | B115: Bond paper, A4 size | C115: Bond paper, A4 size | D115: Bond paper, A4 size | E115: Bond paper, A4 size | F115: =[1]DATA!O41 -> 440 | G115: none | H115: none
A116: =[1]PR!D43 -> 0 | B116: Bond paper, A4 size | C116: Bond paper, A4 size | D116: Bond paper, A4 size | E116: Bond paper, A4 size | F116: =[1]DATA!O42 -> 1500 | G116: none | H116: none
A117: =[1]PR!D44 -> 0 | B117: Bond paper, A4 size | C117: Bond paper, A4 size | D117: Bond paper, A4 size | E117: Bond paper, A4 size | F117: =[1]DATA!O43 -> 2200 | G117: none | H117: none
A118: =[1]PR!D45 -> 0 | B118: Bond paper, A4 size | C118: Bond paper, A4 size | D118: Bond paper, A4 size | E118: Bond paper, A4 size | F118: =[1]DATA!O44 -> 2040 | G118: none | H118: none
... A127: =[1]PR!D54 -> 0 | B127: Bond paper, A4 size | C127: Bond paper, A4 size | D127: Bond paper, A4 size | E127: Bond paper, A4 size | F127: =[1]DATA!O53 -> 760 | G127: none | H127: none
A159: =[1]DATA!I105 -> 0 | B159: Bond paper, A4 size | C159: Bond paper, A4 size | D159: Bond paper, A4 size | E159: Bond paper, A4 size | F159: =[1]DATA!O1228 -> 0 | G159: 900 | I159: 900
F160: =[1]DATA!O1229 -> 0 | G160: 900 | I160: 900
F161: =[1]DATA!O1230 -> 0 | G161: 925 | I161: 925
F162: =[1]DATA!O1231 -> 0 | G162: 9300 | I162: 9300
F163: =[1]DATA!O1232 -> 0 | G163: 32000 | I163: 32000
F164: =[1]DATA!O1233 -> 0 | G164: 9900 | I164: 9900
F165: =[1]DATA!O1234 -> 0 | G165: 400 | I165: 400
F166: =[1]DATA!O1235 -> 0 | G166: 1500 | I166: 1500
F167: =[1]DATA!O1236 -> 0 | G167: 9950 | I167: 9950
F168: =[1]DATA!O1237 -> 0 | G168: 1440 | I168: 1440
F169: =[1]DATA!O1238 -> 0
F170: =[1]DATA!O1239 -> 0
F171: =[1]DATA!O1240 -> 0
F172: =[1]DATA!O1241 -> 0
F173: =[1]DATA!O1242 -> 0
F174: =[1]DATA!O1243 -> 0
F175: =[1]DATA!O1244 -> 0
F176: =[1]DATA!O1245 -> 0
F177: =[1]DATA!O1246 -> 0
F178: =[1]DATA!O1247 -> 0
F179: =[1]DATA!O1248 -> 0
F180: =[1]DATA!O1249 -> 0
... F190: =[1]DATA!O1259 -> 0
A191: ='[4]SourceData 2022'!H423 -> ipatropium bromide+salbutamol sulfate 200mcg/1mg/ml | F191: =[1]DATA!O1260 -> 0
A192: ='[4]SourceData 2022'!H424 -> Salbutamol 2mg/tablet | F192: =[1]DATA!O1261 -> 0
A193: ='[4]SourceData 2022'!H425 -> salbutamol inhaler 100mcg/dose | F193: =[1]DATA!O1262 -> 0
A194: ='[4]SourceData 2022'!H426 -> salbutamol+fluticasone inhaler 25mcg/125mcg meter dose inhaler | F194: =[1]DATA!O1263 -> 0
A195: ='[4]SourceData 2022'!H427 -> zinc oxide +calamine ointment 3.5g | F195: =[1]DATA!O1264 -> 0
A196: ='[4]SourceData 2022'!H428 -> cinnarizine 25mg/tablet | F196: =[1]DATA!O1265 -> 0
A197: ='[4]SourceData 2022'!H429 -> povidone iodine 60ml | F197: =[1]DATA!O1266 -> 0
A198: ='[4]SourceData 2022'!H430 -> gauze pad 4x4 | F198: =[1]DATA!O1267 -> 0
A199: ='[4]SourceData 2022'!H431 -> micropore 1 " 3m | F199: =[1]DATA!O1268 -> 0
A200: ='[4]SourceData 2022'!H432 -> micropore 1/2 " | F200: =[1]DATA!O1269 -> 0
A201: ='[4]SourceData 2022'!H433 -> baby oil 125ml | F201: =[1]DATA!O1270 -> 0
A202: ='[4]SourceData 2022'!H434 -> ethyl alochol 500ml 70% | F202: =[1]DATA!O1271 -> 0
... A208: ='[4]SourceData 2022'!H440 -> high quality "AAA" battery | F208: =[1]DATA!O1277 -> 0
A209: ='[4]SourceData 2022'!H441 -> high quality "AAA" battery | F209: =[1]DATA!#REF! -> #REF!
A210: ='[4]SourceData 2022'!H442 -> 0 | F210: =[1]DATA!O1279 -> 0
A211: ='[4]SourceData 2022'!H443 -> 50 KVA Transformer w/ accessories | F211: =[1]DATA!O1280 -> 0
A212: ='[4]SourceData 2022'!H444 -> installation of transformer | F212: =[1]DATA!O1281 -> 0
A213: ='[4]SourceData 2022'!H445 -> 0 | F213: =[1]DATA!O1282 -> 0
A214: ='[4]SourceData 2022'!H446 -> Repair of split type air conditioner (replace copper tubing and rechargefreon) | F214: =[1]DATA!O1283 -> 0
A215: ='[4]SourceData 2022'!H447 -> 0 | F215: =[1]DATA!O1284 -> 0
A216: ='[4]SourceData 2022'!H448 -> Isoprophyl alcohol | F216: =[1]DATA!O1285 -> 0
A217: ='[4]SourceData 2022'!H449 -> signing pen .4 (24 black, 24 blue) | F217: =[1]DATA!O1286 -> 0
A218: ='[4]SourceData 2022'!H450 -> garbage bag, XXL | F218: =[1]DATA!O1287 -> 0
A219: ='[4]SourceData 2022'!H451 -> 0 | F219: =[1]DATA!O1288 -> 0
A220: ='[4]SourceData 2022'!H452 -> PVC 20 mm water pipe | F220: =[1]DATA!O1289 -> 0
A221: ='[4]SourceData 2022'!H453 -> PVC 20 mm female adapter | F221: =[1]DATA!O1290 -> 0
... A223: ='[4]SourceData 2022'!H455 -> PVC 20 mm union patente | F223: =[1]DATA!O1292 -> 0
A224: ='[4]SourceData 2022'!H456 -> PVC 32 mm water pipe | F224: =[1]DATA!O1278 -> 0
A225: ='[4]SourceData 2022'!H457 -> PVC 32 mm male adapter | F225: =[1]DATA!O1294 -> 0
A226: ='[4]SourceData 2022'!H458 -> PVC 32 mm tee | F226: =[1]DATA!O1295 -> 0
A227: ='[4]SourceData 2022'!H459 -> PVC 32 mm ball valve | F227: =[1]DATA!O1296 -> 0
A228: ='[4]SourceData 2022'!H460 -> PVC 32 mm union patente | F228: =[1]DATA!O1297 -> 0
A229: ='[4]SourceData 2022'!H461 -> PVC 32 mm elbow | F229: =[1]DATA!O1298 -> 0
A230: ='[4]SourceData 2022'!H462 -> PVC reducer,1-3/4 | F230: =[1]DATA!O1299 -> 0
A231: ='[4]SourceData 2022'!H463 -> PVC reducer,3/4-1/2 | F231: =[1]DATA!O1300 -> 0
A232: ='[4]SourceData 2022'!H464 -> PVC 40 mm water pipe | F232: =[1]DATA!O1301 -> 0
...

Sheet LON
A6: BIDS AND AWARDS COMMITTEE
A8: LETTER OF NOTICE
A11: DALE ANTHONY C. GUITIERREZ
A12: Owner
A13: IBS Pharmacy & General Merchandise
A14: Brgy. Kayvaluganan, Batanes
A17: Madam/Sir:
A18: We are happy to notify you that your quotation dated September 8, 2025 for the Internet Service Provider Subscription with PR # 2509-1005-306 contract price equivalent to FORTY THOUSAND FIVE HUNDRED PESOS ONLY (Php 40,500.00) is hereby accepted.
A19: You are hereby required to provide within Ten (10) days a certified photocopy of the following requirements:
A20: .
B21: 1. Updated Mayor's Permit/Business Permit
B22: 2. PhilGEPS Registration no.
B23: 3. Latest Income/Business Tax Return (ITR)
B24: 4. Duly Notarized Omnibus Sworn Statement
B25: 5. BIR 2302 Certificate of Registration (COR)
B26: 6. Updated DTI Registration
B27: 7. Landbank Account details of the business (for payment purposes)
A29: However, If you already have a maintaining and updated file of the above-mentioned requirements in the BAC Office you may no longer require its re-submission (Annex "H", Appendix "A" Section III)
A31: *For individuals engaged under Sec. 53.6, 53.7, and 53.9 of the IRR of RA 9184, only the BIR Certificate of Registration shall be submitted in lieu of DTI Registration and Mayor’s Permit.
A32: Thank you
A34: Very truly yours,
A37: DOREEN C. CASTILLO
A38: BAC Chairperson
A40: Received by:
A43: (Signature over printed name)
A44: Date: ___________________
A45: Ref. No.: | B45: =PR!B12 -> 2509-SS09-343

Sheet BAC RESO 2022
E6: OFFICE OF THE BIDS AND AWARDS COMMITTEE | N6: OFFICE OF THE BIDS AND AWARDS COMMITTEE
E7: bac resolution No: | M7: =E7 -> bac resolution No:
D8: =PR!B12 -> 2509-SS09-343 | M8: =D8 -> 2509-SS09-343
E10: BAC RESOLUTION RECOMMENDING FOR AWARD | N10: APPROVAL OF THE BAC RECOMMENDATION FOR AWARD
A12: WHEREAS, the BATANES STATE COLLEGE advertised the Request for Price Quotation (RFQ) of the Heavy Snack (spaghetti,chicken fingers canned juice) with PR# 2509-1005-298-A September 10, 2025. | J12: WHEREAS, the BATANES STATE COLLEGE advertised the Request for Price Quotation (RFQ) of the Heavy Snack (spaghetti,chicken fingers canned juice) with PR# 2509-1005-298-A September 10, 2025.
A15: WHEREAS, from the period the Request for Price Quotation (RFQ) has started up to the time of bid submission and opening, Three (3) prospective bidder were able to submit the RFQ; | J15: WHEREAS, from the period the Request for Price Quotation (RFQ) has started up to the time of bid submission and opening, Three (3) prospective bidder were able to submit the RFQ;
A18: WHEREAS, the Price Quotation based on the Lowest Calculated & Responsive Bid (LCRB) format of the bidders were opened and its bid price was read as follows: | J18: WHEREAS, the Price Quotation based on the Lowest Calculated & Responsive Bid (LCRB) format of the bidders were opened and its bid price was read as follows:
A21: ITEM NO. | B21: BIDDER WITH CALCULATED BID | G21: ABC | I21: BID AMOUNT | J21: ITEM NO. | K21: BIDDER WITH CALCULATED BID | P21: ABC | R21: BID AMOUNT
A22: 1 | B22: =DATA!W6 -> Doque's Congie Hauz | G22: =PR!H75 -> 10450 | I22: 21000 | J22: 1 | K22: =B22 -> Doque's Congie Hauz | P22: =G22 -> 10450 | R22: =I22 -> 21000
A23: 2 | B23: Biang's Catering Services | G23: =PR!H75 -> 10450 | I23: not available | J23: 2 | K23: =B23 -> Biang's Catering Services | P23: =G23 -> 10450 | R23: =I23 -> not available
A24: 3 | B24: AZ Blue Box Café | G24: =PR!H75 -> 10450 | I24: none | J24: 3 | K24: =B24 -> AZ Blue Box Café | P24: =G24 -> 10450 | R24: =I24 -> none
A25: 4 | B25: One-Touch Technology Trading | G25: =PR!H75 -> 10450 | I25: 6315 | J25: 4 | K25: =B25 -> One-Touch Technology Trading | P25: =G25 -> 10450 | R25: =I25 -> 6315
A26: 5 | B26: Apostol General Merchandise | G26: =PR!H75 -> 10450 | I26: 8420 | J26: 5 | K26: =B26 -> Apostol General Merchandise | P26: =G26 -> 10450 | R26: =I26 -> 8420
A27: 6 | G27: =PR!H75 -> 10450 | I27: none | J27: 6 | P27: =G27 -> 10450 | R27: =I27 -> none
A28: 7 | J28: 7 | K28: =B28 -> 0 | P28: =G28 -> 0 | R28: =I28 -> 0
J29: 8 | K29: =B29 -> 0 | P29: =G29 -> 0 | R29: =I29 -> 0
J30: NOW THEREFORE, I DJOVI R. DURANTE,DPA by virtue of the authority vested in me of this institution and after taking into consideration the merits and legal bases of the recommendation of the members of the Bids and Awards Committee (BAC) do hereby APPROVE the following;
B32: 1. To declare Doque's Congie Hauz as supplier with the Lowest Calculated & Responsive Bid of Heavy Snack (spaghetti,chicken fingers canned juice) with PR# 2509-1005-298-A September 10, 2025.
B35: 2. To recommend for approval by the Head of Procuring Entity of the Batanes State College the foregoing findings.
A36: RESOLVED FINALLY, at the BAC Office, Batanes State College, this _______day of . | J36: To declare Doque's Congie Hauz as supplier with the Lowest Calculated & Responsive Bid of Heavy Snack (spaghetti,chicken fingers canned juice) with PR# 2509-1005-298-A.
A37: Recommending Approval:
A40: RHOUPHELINE AYA A. CADIZ | D40: EMILYN D. ALUETA | G40: FORTUNATO PHILIP A. CABUGAO | J40: Done this ______ day of _________ 2025.
A41: BAC Member | D41: BAC Member | G41: BAC Member
L44: DJOVI REGALA DURANTE,DPA
A45: =PR!B80 -> ELEIN T. ESPERANZA | F45: PHILIP ULYSSES T. CASTILLO | L45: SUC President I
A46: End-user/Provisional Member | F46: Vice BAC Chairperson
D48: DOREEN C. CASTILLO
D49: BAC Chairperson

Sheet BAC RESO 2022 (Toss Coin)
E6: OFFICE OF THE BIDS AND AWARDS COMMITTEE | N6: OFFICE OF THE BIDS AND AWARDS COMMITTEE
E7: bac resolution No: | M7: =E7 -> bac resolution No:
D8: =PR!B12 -> 2509-SS09-343 | M8: =D8 -> 2509-SS09-343
E10: BAC RESOLUTION RECOMMENDING FOR AWARD | N10: APPROVAL OF THE BAC RECOMMENDATION FOR AWARD
A12: WHEREAS, the BATANES STATE COLLEGE advertised the Request for Price Quotation (RFQ)of the Tote Bag with PR # 2409-Acad4-349 dated September 12, 2024. | J12: WHEREAS, the BATANES STATE COLLEGE advertised the Request for Price Quotation (RFQ)of the Tote Bag with PR # 2409-Acad4-349 dated September 12, 2024.
A15: WHEREAS, from the period the Request for Price Quotation (RFQ) has started up to the time of bid submission and opening, Six (6) prospective bidders were able to submit the RFQ; | J15: WHEREAS, from the period the Request for Price Quotation (RFQ) has started up to the time of bid submission and opening, Six (6) prospective bidders were able to submit the RFQ;
A18: WHEREAS, the Price Quotation based on the Lowest Calculated & Responsive Bid (LCRB) format of the bidders were opened and its bid price was read as follows: | J18: WHEREAS, the Price Quotation based on the Lowest Calculated & Responsive Bid (LCRB) format of the bidders were opened and its bid price was read as follows:
A21: ITEM NO. | B21: BIDDER WITH CALCULATED BID | G21: ABC | I21: BID AMOUNT | J21: ITEM NO. | K21: BIDDER WITH CALCULATED BID | P21: ABC | R21: BID AMOUNT
A22: 1 | B22: =DATA!W33 -> YCA Office Supplies & Equipment Trading | G22: =PR!H75 -> 10450 | I22: 4750 | J22: 1 | K22: =B22 -> YCA Office Supplies & Equipment Trading | P22: =G22 -> 10450 | R22: =I22 -> 4750
A23: 2 | B23: JPM General Merchandise & Hardware | G23: =PR!H75 -> 10450 | I23: 4750 | J23: 2 | K23: =B23 -> JPM General Merchandise & Hardware | P23: =G23 -> 10450 | R23: =I23 -> 4750
A24: 3 | B24: IAM'J Graphic Design & Printing | G24: =PR!H75 -> 10450 | I24: 5000 | J24: 3 | K24: =B24 -> IAM'J Graphic Design & Printing | P24: =G24 -> 10450 | R24: =I24 -> 5000
A25: 4 | B25: M.G.Hubalde's General Merchandise | G25: 5000 | I25: 6000 | J25: 4 | K25: =B25 -> M.G.Hubalde's General Merchandise | P25: =G25 -> 5000 | R25: =I25 -> 6000
A26: 5 | B26: Simsiman Arts & Crfats Manufacturing | G26: 5000 | I26: 32500 | J26: 5 | K26: =B26 -> Simsiman Arts & Crfats Manufacturing | P26: =G26 -> 5000 | R26: =I26 -> 32500
A27: 6 | B27: Apostol General Merchandise | G27: 5000 | J27: 6 | K27: =B27 -> Apostol General Merchandise | P27: =G27 -> 5000 | R27: =I27 -> 0
A28: 7 | J28: 7 | K28: =B28 -> 0 | P28: =G28 -> 0 | R28: =I28 -> 0
A29: 8 | J29: 8 | K29: =B29 -> 0 | P29: =G29 -> 0 | R29: =I29 -> 0
A30: WHEREAS,two (2) of the suppliers have the same total price quotation; | J30: WHEREAS,two (2) of the suppliers have the same total price quotation;
A32: WHEREAS, to resolve cases involving a tie, the procuring entity may determine a measure to be used by which it shall be non-discretionary and non-discriminatory such that the same shall be based on sheer luck or chance. The method used was "toss coin"; | J32: WHEREAS, to resolve cases involving a tie, the procuring entity may determine a measure to be used by which it shall be non-discretionary and non-discriminatory such that the same shall be based on sheer luck or chance. The method used was "toss coin";
A34: WHEREAS, as per result of the toss coin conducted, YCA Office Supplies & Equipment was announced as the winner: | J34: WHEREAS, as per result of the toss coin conducted, YCA Office Supplies & Equipment was announced as the winner:
B36: 1. To declare YCA Office Supplies & Equipment as supplier of Tote Bag with PR # 2409-Acad4-349 dated September 12, 2024. | J36: NOW THEREFORE, I DJOVI R. DURANTE,DPA by virtue of the authority vested in me of this institution and after taking into consideration the merits and legal bases of the recommendation of the members of the Bids and Awards Committee (BAC) do hereby APPROVE the following;
B39: 2. To recommend for approval by the Head of Procuring Entity of the Batanes State College the foregoing findings.
A40: RESOLVED FINALLY, at the BAC Office, Batanes State College, this _______day of . | J40: To declare YCA Office Supplies & Equipment as supplier of Tote Bag with PR # 2409-Acad4-349.
A41: Recommending Approval:
A44: RHOUPHELINE AYA A. CADIZ | D44: EMILYN D. ALUETA | G44: RANDALL G. CASTILLO | J44: Done this _______ day of ___________ 2022 | N44: 2024
A45: BAC Member | D45: BAC Member | G45: BAC Member
L47: DJOVI REGALA DURANTE,DPA
A48: =PR!B80 -> ELEIN T. ESPERANZA | D48: FORTUNATO PHILIP A. CABUGAO | H48: DOREEN C. CASTILLO | L48: SUC President I
A49: End-user/Provisional Member | D49: BAC Vice Chairperson | H49: BAC Chairperson

Sheet PO (2)
E3: Appendix 61
A4: PURCHASE ORDER
A5: BATANES STATE COLLEGE
A6: Entity Name
A8: Supplier : | B8: =DATA!W205 -> Sophia Marie Store | D8: P.O. No. : | E8: 2025-09-343
A9: Address : | B9: Basco, Batanes | D9: Date : | E9: October 14, 2025
A10: TIN : | B10: 279-057-542 | C10: 279-057-542 | D10: Mode of Procurement : Small Value Procurement
A11: Gentlemen:
A12: Please furnish this Office the following articles subject to the terms and conditions contained herein:
A14: Place of Delivery : ___________________________________ | B14: Batanes Stae College | D14: Delivery Term : FOB Destination
A15: Date of Delivery : ____________________________________ | B15: 30 days upon receipt of PO | D15: Payment Term : 15 days upon complete delivery
A16: Stock/ Property No. | B16: Unit | C16: Description | D16: Quantity | E16: Unit Cost | F16: Amount
A17: 1 | B17: =PR!B16 -> 0 | C17: =PR!D16 -> DAY 1-Opening Day | D17: =PR!A16 -> 0 | E17: =DATA!N204 -> 0 | F17: =SUM(D17*E17) -> 0
A18: 2 | B18: =PR!B17 -> kls | C18: =PR!D17 -> Chicken (whole) | D18: =PR!A17 -> 12 | E18: =DATA!N205 -> 250 | F18: =SUM(D18*E18) -> 3000
A19: 3 | B19: =PR!B18 -> bottle | C19: =PR!D18 -> Vinegar (1 Ltr.) | D19: =PR!A18 -> 2 | E19: =DATA!N206 -> 75 | F19: =SUM(D19*E19) -> 150
A20: 4 | B20: =PR!B19 -> bottle | C20: =PR!D19 -> Soy Sauce (1Ltr) | D20: =PR!A19 -> 1 | E20: =DATA!N207 -> 85 | F20: =SUM(D20*E20) -> 85
A21: 5 | B21: =PR!B20 -> pack | C21: =PR!D20 -> Juice (Blue Lemonade) | D21: =PR!A20 -> 1 | E21: =DATA!N208 -> 250 | F21: =SUM(D21*E21) -> 250
A22: 6 | B22: =PR!B21 -> 0 | C22: =PR!D21 -> DAY 2- Activity Day | D22: =PR!A21 -> 0 | E22: =DATA!N209 -> 0 | F22: =SUM(D22*E22) -> 0
A23: 7 | B23: =PR!B22 -> kls | C23: =PR!D22 -> Pork & Pork Liver | D23: =PR!A22 -> 10 | E23: =DATA!N210 -> 404 | F23: =SUM(D23*E23) -> 4040
A24: 8 | B24: =PR!B23 -> kls | C24: =PR!D23 -> Carrots | D24: =PR!A23 -> 1 | E24: =DATA!N211 -> 350 | F24: =SUM(D24*E24) -> 350
A25: 9 | B25: =PR!B24 -> pack | C25: =PR!D24 -> Juice (Blue Lemonade) | D25: =PR!A24 -> 1 | E25: =DATA!N212 -> 250 | F25: =SUM(D25*E25) -> 250
A26: 10 | B26: =PR!B25 -> pcs | C26: =PR!D25 -> Yellow Ginger (Hama-100g) | D26: =PR!A25 -> 2 | E26: =DATA!N213 -> 130 | F26: =SUM(D26*E26) -> 260
A27: 11 | B27: =PR!B26 -> pcs | C27: =PR!D26 -> Coffee (Twin Pack) | D27: =PR!A26 -> 50 | E27: =DATA!N214 -> 20 | F27: =SUM(D27*E27) -> 1000
A28: 12 | B28: =PR!B27 -> ballots | C28: =PR!D27 -> Assorted Biscuits | D28: =PR!A27 -> 10 | E28: =DATA!N215 -> 90 | F28: =SUM(D28*E28) -> 900
A29: 13 | B29: =PR!B28 -> 0 | C29: =PR!D28 -> 0 | D29: =PR!A28 -> 0 | E29: =DATA!N242 -> 180 | F29: =SUM(D29*E29) -> 0
A30: 14 | B30: =PR!B29 -> 0 | C30: =PR!D29 -> 0 | D30: =PR!A29 -> 0 | F30: =SUM(D30*E30) -> 0
A31: 15 | B31: =PR!B30 -> 0 | C31: =PR!D30 -> 0 | D31: =PR!A30 -> 0 | E31: =DATA!N33 -> 650 | F31: =SUM(D31*E31) -> 0
A32: 16 | B32: =PR!B31 -> 0 | C32: =PR!D31 -> 0 | D32: =PR!A31 -> 0 | E32: =DATA!N34 -> 350 | F32: =SUM(D32*E32) -> 0
A33: 17 | B33: =PR!B32 -> 0 | C33: =PR!D32 -> 0 | D33: =PR!A32 -> 0 | E33: =DATA!N35 -> 2000 | F33: =SUM(D33*E33) -> 0
A34: 18 | B34: =PR!B33 -> 0 | C34: =PR!D33 -> 0 | D34: =PR!A33 -> 0 | E34: =DATA!N36 -> 600 | F34: =SUM(D34*E34) -> 0
A35: 19 | B35: =PR!B34 -> 0 | C35: =PR!D34 -> 0 | D35: =PR!A34 -> 0 | E35: =DATA!N37 -> 10000 | F35: =SUM(D35*E35) -> 0
A36: 20 | B36: =PR!B35 -> 0 | C36: =PR!D35 -> 0 | D36: =PR!A35 -> 0 | E36: =DATA!N38 -> 8500 | F36: =SUM(D36*E36) -> 0
A37: 21 | B37: =PR!B36 -> 0 | C37: =PR!D36 -> 0 | D37: =PR!A36 -> 0 | E37: =DATA!N39 -> 5300 | F37: =SUM(D37*E37) -> 0
A38: 22 | B38: =PR!B37 -> 0 | C38: =PR!D37 -> 0 | D38: =PR!A37 -> 0 | E38: =DATA!N40 -> 550 | F38: =SUM(D38*E38) -> 0
A39: 23 | B39: =PR!B38 -> 0 | C39: =PR!D38 -> 0 | D39: =PR!A38 -> 0 | E39: =DATA!N41 -> 5000 | F39: =SUM(D39*E39) -> 0
A40: 24 | B40: =PR!B39 -> 0 | C40: =PR!D39 -> 0 | D40: =PR!A39 -> 0 | E40: =DATA!N42 -> 3950 | F40: =SUM(D40*E40) -> 0
A41: 25 | B41: =PR!B40 -> 0 | C41: =PR!D40 -> 0 | D41: =PR!A40 -> 0 | E41: =DATA!N43 -> 15000 | F41: =SUM(D41*E41) -> 0
A42: 26 | B42: =PR!B41 -> 0 | C42: =PR!D41 -> 0 | D42: =PR!A41 -> 0 | E42: =DATA!N44 -> 2400 | F42: =SUM(D42*E42) -> 0
... A51: 35 | B51: =PR!B50 -> 0 | C51: =PR!D50 -> 0 | D51: =PR!A50 -> 0 | E51: =DATA!N53 -> 16000 | F51: =SUM(D51*E51) -> 0
B52: =PR!B51 -> liter | C52: =PR!D51 -> Acrylic Based Paint - Red | D52: =PR!A51 -> 0
B53: =PR!B52 -> liter | C53: =PR!D52 -> Acrylic Based Paint - Blue | D53: =PR!A52 -> 0
B54: =PR!B53 -> liter | C54: =PR!D53 -> Acrylic Based Paint - Yellow | D54: =PR!A53 -> 0
B55: =PR!B54 -> liter | C55: =PR!D54 -> Acrylic Based Paint - Black | D55: =PR!A54 -> 0
B56: =PR!B55 -> pail | C56: =PR!D55 -> Acrylic Based Paint - White | D56: =PR!A55 -> 0
B57: =PR!B56 -> set | C57: =PR!D56 -> Artist Paint Brush | D57: =PR!A56 -> 0
B58: =PR!B57 -> pcs | C58: =PR!D57 -> Paint Roller (4 inches) | D58: =PR!A57 -> 0
A59: 14 | B59: =PR!B58 -> pcs | C59: =PR!D58 -> 4ft x 8ft Galvanized Plain Sheet, 25 Gauge | D59: =PR!A58 -> 0 | E59: =DATA!N139 -> 500 | F59: =SUM(D59*E59) -> 0
A60: Total | F60: =SUM(F17:F29) -> 10285
A61: (Total Amount in Words) | C61: TEN THOUSAND TWO HUNDRED EIGHTY FIVE PESOS ONLY
A63: In case of failure to make the full delivery within the time specified above, a penalty of one-tenth (1/10) of one percent for every day of delay shall be imposed on the undelivered item/s.
A66: Conforme: | D66: Very truly yours,
A68: __________________________ | D68: DJOVI REGALA DURANTE
A69: Signature over Printed Name of Supplier | D69: Signature over Printed Name of Authorized Official
A70: ___________________________ | D70: SUC President I
A71: Date | D71: Designation
A74: Fund Cluster : ___________________________________ | D74: ORS/BURS No. : ______________________
A75: Funds Available : _________________________________ | D75: Date of the ORS/BURS: _______________
B76: RHEA ANGELLICA B. ADDATU,CPA | D76: Amount : | E76: =F60 -> 10285
B77: Signature over Printed Name of Chief Accountant/Head of Accounting Division/Unit

Sheet POback (2)
A1: INSTRUCTIONS
A3: A. The PO is a form/document used by the agency/entity, addressed to supplier, to deliver specific quantities of supplies/goods/property subject to the terms and conditions contained in the PO.
A4: B. This form shall be accomplished as follows:
B5: 1. Entity Name - name of the agency/entity
B6: 2. Supplier/Address/TIN - name, address and TIN of the supplier
B7: 3. P.O. No. - the number assigned to the PO which shall be as follows:
C8: 0000-00-0000 | E8: Serial number (one series for each year)
E9: Month
E10: Year
B11: 4. Date - date of the preparation of the PO
B12: 5. Mode of Procurement - mode of procurement such as public bidding, through Procurement Service, limited source bidding, direct contracting, repeat order, shopping and negotiated procurement in accordance with RA 9184
B13: 6. Place/Date of Delivery - place of delivery and definite date/s of delivery; if not stated, the date of delivery shall mean seven (7) calendar days after the receipt of PO by the supplier
B14: 7. Delivery Term - delivery term i.e., FOB destination, FOB shipping point
B15: 8. Payment Term - specified period required when the delivered goods shall be paid and discounts, if any, such as 2/10, n/30
B16: 9. Stock/Property No. - stock/property number of the goods to be purchased as provided by the Supply and/or Property Division Unit
B17: 10. Unit - unit of measurement of the supplies/goods/property being procured (i.e. piece, roll, box, reams, etc.)
B18: 11. Description - brief description of the supplies/goods/property being procured
B19: 12. Quantity - quantity of supplies/goods/property being procured
B20: 13. Unit Cost - cost per unit of the supplies/goods/property being procured
B21: 14. Amount - total amount of the supplies/goods/property being procured (Quantity x Unit Cost)
B22: 15. Penalty Clause - penalty to be imposed by the agency/entity in case of non-compliance with the term, that is, one-tenth (1/10) of one percent (1%) for every day of delay on the undelivered item/s
... B27: 20. ORS/BURSNo., Date and Amount - ORS/BURS number assigned by the Budget Division/Unit, date of the ORS/BURS and the amount of obligation supporting the purchase
A28: C. It shall be prepared in four (4) copies distributed as follows:
B29: Original - to the supplier for conforme to the terms of the PO and as attachment to the DV upon request for payment
B30: Copy 2 - retained by the Supply and/or Property Division Unit for file
B31: Copy 3 - to be submitted to COA within five (5) days after conformity by the supplier
B32: Copy 4 - Supplier's copy

Sheet ChkDocs
B1: PR No.: | C1: 23-022 | D1: -------------------cut here-------------------cut here-------------------cut here-------------------cut here-------------------cut here------------------- | E1: PR No.: | F1: =C1 -> 23-022 | G1: -------------------cut here-------------------cut here-------------------cut here-------------------cut here-------------------cut here------------------- | H1: PR No.: | I1: =C1 -> 23-022
B2: Checklist of Documents Submitted: | E2: Checklist of Documents Submitted: | H2: Checklist of Documents Submitted:
C3: Management Monitoring Slip | F3: Management Monitoring Slip | I3: Management Monitoring Slip
B4: X | C4: Purchase Request | E4: X | F4: Purchase Request | H4: X | I4: Purchase Request
C5: Pre and Post Inspection Report | F5: Pre and Post Inspection Report | I5: Pre and Post Inspection Report
B6: X | C6: OBR | E6: X | F6: OBR | H6: X | I6: OBR
B7: X | C7: BAC Resolution | E7: =B7 -> X | F7: BAC Resolution | H7: =B7 -> X | I7: BAC Resolution
B8: X | C8: Approval of BAC Resolution on SVP | E8: =B8 -> X | F8: Approval of BAC Resolution on SVP | H8: =B8 -> X | I8: Approval of BAC Resolution on SVP
B9: X | C9: RFQ1 | E9: =B9 -> X | F9: RFQ1 | H9: =B9 -> X | I9: RFQ1
B10: X | C10: RFQ2 | E10: =B10 -> X | F10: RFQ2 | H10: =B10 -> X | I10: RFQ2
B11: X | C11: RFQ3 | E11: =B11 -> X | F11: RFQ3 | H11: =B11 -> X | I11: RFQ3
B12: X | C12: Acknowledgment for Request for Quotation | E12: =B12 -> X | F12: Acknowledgment for Request for Quotation | H12: =B12 -> X | I12: Acknowledgment for Request for Quotation
B13: X | C13: Abstract of Bids | E13: =B13 -> X | F13: Abstract of Bids | H13: =B13 -> X | I13: Abstract of Bids
B14: X | C14: BAC Resolution for Award | E14: =B14 -> X | F14: BAC Resolution for Award | H14: =E14 -> X | I14: BAC Resolution for Award
B15: X | C15: Approval of Reso. for Award | E15: =B15 -> X | F15: Approval of Reso. for Award | H15: =E15 -> X | I15: Approval of Reso. for Award
B16: X | C16: Letter of Notice | E16: =B16 -> X | F16: Letter of Notice | H16: =B16 -> X | I16: Letter of Notice
B17: X | C17: Notice to Proceed | E17: =B17 -> X | F17: Notice to Proceed | I17: Notice to Proceed
B18: X | C18: Certification of BAC | E18: =B18 -> X | F18: Certification of BAC | H18: =B18 -> X | I18: Certification of BAC
C19: Waste Materials Report/Pre & Post Repair Inspection | E19: =B19 -> 0 | F19: Waste Materials Report/Pre & Post Repair Inspection | H19: =B19 -> 0 | I19: Waste Materials Report/Pre & Post Repair Inspection
B20: X | C20: Purchase Order (PO) | E20: =B20 -> X | F20: Purchase Order (PO) | H20: =B20 -> X | I20: Purchase Order (PO)
B21: X | C21: Charge/Sales Invoice | E21: =B21 -> X | F21: Charge/Sales Invoice | H21: =B21 -> X | I21: Charge/Sales Invoice
B22: X | C22: IAR | E22: X | F22: IAR | H22: X | I22: IAR
C23: Inventory Custodian Slip (ICS) | E23: =B23 -> 0 | F23: Inventory Custodian Slip (ICS) | H23: =B23 -> 0 | I23: Inventory Custodian Slip (ICS)
B24: X | C24: RIS | E24: X | F24: RIS | H24: X | I24: RIS
C25: (3)ARE # 221111LLB,DRD,AAM-ARE | F25: =C25 -> (3)ARE # 221111LLB,DRD,AAM-ARE | H25: =B25 -> 0 | I25: =C25 -> (3)ARE # 221111LLB,DRD,AAM-ARE
B26: X | C26: PhilGEPS Bid Notice Abstract ref #8607137 | E26: =B26 -> X | F26: =C26 -> PhilGEPS Bid Notice Abstract ref #8607137 | H26: =B26 -> X | I26: =C26 -> PhilGEPS Bid Notice Abstract ref #8607137
C27: MOA | F27: MOA | I27: MOA
B28: X | C28: PPMP for CY2021 | E28: =B28 -> X | F28: =C28 -> PPMP for CY2021 | H28: =B28 -> X | I28: =C28 -> PPMP for CY2021
C29: Attendance Sheet | E29: =B29 -> 0 | F29: Attendance Sheet | H29: =B29 -> 0 | I29: Attendance Sheet
E30: =B30 -> 0 | F30: =C30 -> 0 | H30: =B30 -> 0 | I30: =C30 -> 0
B31: Received by: | E31: Received by: | H31: Received by:
C33: (Signature over Printed Name/Date) | F33: (Signature over Printed Name/Date) | I33: (Signature over Printed Name/Date)
B34: Note: Please return one (1) copy to Supply section for filing purposes. Thank you. | E34: Note: Please return one (1) copy to Supply section for filing purposes. Thank you. | H34: Note: Please return one (1) copy to Supply section for filing purposes. Thank you.
B35: SS Form 14/001 (A) | E35: SS Form 14/001 (B) | H35: SS Form 14/001©
D36: "
B40: +

Sheet AResoSVP -Emergency
A1: BATANES STATE COLLEGE
A2: Basco, Batanes
A4: Approval of BAC Resolution Recommending Emergency Procurement of the Project: Supply and Installation of 50KVA Transformer
B6: BAC Resolution No. | D6: =PR!B12 -> 2509-SS09-343
A8: WHEREAS, Section 53 Rule XVI of the Revised Implementing Rules and Regulations of RA 9184
A9: allows Negotiated Mode of Procurement subject to prior approval of the HOPE thru Annual
A10: Procurement Plan (APP) and only to promote economy and efficiency;
A12: WHEREAS, Section 53.2 allows Emergency Cases in case of imminent danger to life or property
A13: during state of calamity, or when time is of the essence arising from natural or man-made calamities or other
A14: causes where immediate action is necessary to prevent damage to or loss of life or property, or to
A15: restore vital public services, infrastructure facilities and other public utilities;
A17: WHEREAS, "Annex H" of the Consolidated Guidelines for Emergency Cases prescribed under
A18: Section V, Paragraph D.2.b.,upon submission of request and other supporting documents identifying
A19: the emergency sought to be addressed, the BAC shall prepare the appropriate procurement
A20: documents and directly negotiate with a supplier, contractor, or consultant with technical, legal and
A21: financial capability to deliver the goods, execute the works and perform the services to address the emergency;
... A24: the HOPE, upon the recommendation of the BAC, shall immediately award the contract to the Supplier, Contractor or Consultant;
A25: WHEREAS, Purchase Request No. | D25: =PR!E9 -> 2025-343 | E25: involves the procurement of
A26: =PR!B76 -> for BEACON 2025 "Building Empowered and Accountable Councils of Noble BSCians"
A27: with the Approved Budget of | D27: =PR!H75 -> 10450
A28: WHEREAS, the default mode of evaluation shall be on a lot basis which means that the
A29: determination of the single/lowest calculated and responsive bid (S/LCRB) is the total amount of offered
A30: unit price multiply by the required quantity;
A32: NOW THEREFORE, I, DR.DJOVI R. DURANTE, Director for Admin & Finance Services by virtue of
A33: the authority vested in me by the Board of Trustees of this Institution and after taking into consideration
A34: the merits and legal bases of the recommendation of the members of the Bids and Awards Committee (BAC)
A35: do hereby APPROVE the foregoing recommendation and adoption of Negotiated Mode of Procurement
A36: under Emergency Case;
A38: APPROVED FINALLY, at the Batanes State College, this | F38: ___________________
B41: DJOVI REGALA DURANTE,DPA
B42: SUC President I
A47: BRYAN H. CIELO
A48: DELMA G. MALUPA-ABAD
A49: EDWIN F.MACABALLUG, Ph.D.
A50: LIEZL P. DELA CRUZ
A51: RODERICK Y. ABAD
A52: VILMA D. BACCAY
A53: ESTEBAN C. BADAJOS
A54: LEOBERT L. BANZALI
A55: MIAH DAPHNIE B. BUENAFE
A56: GLORIA N. CABIZON
A57: FORTUNATO PHILIP A. CABUGAO
A58: RICARDO Q. CABUGAO, JR.
... A103: EMILYN D. ALUETA

Sheet ResoSVP -Emergency
A1: BATANES STATE COLLEGE
A2: Basco, Batanes
A4: BAC Resolution Recommending Emergency Procurement of the Project: Supply and Installation of 50KVA Transformer
B6: BAC Resolution No. | D6: =PR!B12 -> 2509-SS09-343
A8: WHEREAS, Section 53 Rule XVI of the Revised Implementing Rules and Regulations of RA 9184
A9: allows Negotiated Mode of Procurement subject to prior approval of the HOPE thru Annual
A10: Procurement Plan (APP) and only to promote economy and efficiency;
A12: WHEREAS, Section 53.2 allows Emergency Cases in case of imminent danger to life or property
A13: during state of calamity, or when time is of the essence arising from natural or man-made calamities or other
A14: causes where immediate action is necessary to prevent damage to or loss of life or property, or to
A15: restore vital public services, infrastructure facilities and other public utilities;
A17: WHEREAS, "Annex H" of the Consolidated Guidelines for Emergency Cases prescribed under
A18: Section V, Paragraph D.2.b.,upon submission of request and other supporting documents identifying
A19: the emergency sought to be addressed, the BAC shall prepare the appropriate procurement
A20: documents and directly negotiate with a supplier, contractor, or consultant with technical, legal and
A21: financial capability to deliver the goods, execute the works and perform the services to address the emergency;
... A24: the HOPE, upon the recommendation of the BAC, shall immediately award the contract to the Supplier, Contractor or Consultant;
A25: WHEREAS, Purchase Request No. | D25: =PR!E9 -> 2025-343 | E25: involves the procurement of
A26: =PR!B76 -> for BEACON 2025 "Building Empowered and Accountable Councils of Noble BSCians"
A27: with the Approved Budget of | D27: =PR!H75 -> 10450
A28: WHEREAS, the default mode of evaluation shall be on a lot basis which means that the
A29: determination of the single/lowest calculated and responsive bid (S/LCRB) is the total amount of offered
A30: unit price multiply by the required quantity;
A32: NOW THEREFORE, we, the members of the Bids and Awards Committee hereby RESOLVE to recommend to the HOPE to adopt Negotiated Mode of Procurement under Emergency Cases for the said transaction;
A33: RESOLVED FINALLY, at the Batanes State College, this
A34: Recommending Approval:
A37: RHOUPHELINE AYA A. CADIZ | C37: RANDALL G. CASTILLO | E37: EMILYN D. ALUETA
A38: BAC Member | C38: BAC Member | E38: BAC Member
A41: =PR!B80 -> ELEIN T. ESPERANZA | C41: FORTUNATO PHILIP A. CABUGAO | E41: DOREEN C. CASTILLO
A42: End-User/Provisional Member | C42: BAC Vice Chairperson | E42: BAC Chairperson
A47: BRYAN H. CIELO
A48: DELMA G. MALUPA-ABAD
A49: EDWIN F.MACABALLUG, Ph.D.
A50: LIEZL P. DELA CRUZ
A51: RODERICK Y. ABAD
A52: VILMA D. BACCAY
A53: ESTEBAN C. BADAJOS
A54: LEOBERT L. BANZALI
A55: MIAH DAPHNIE B. BUENAFE
A56: GLORIA N. CABIZON
A57: FORTUNATO PHILIP A. CABUGAO
A58: RICARDO Q. CABUGAO, JR.
... A103: EMILYN D. ALUETA

Sheet ResoSoSVP(Direct Contracting)
A1: BATANES STATE COLLEGE
A2: Basco, Batanes
A4: BAC Resolution Recommending Alternative Mode of Procurement under Direct Contracting for the Blank TOR Paper
B6: BAC Resolution No. | D6: =PR!B12 -> 2509-SS09-343
A8: WHEREAS, Rule XVI of the Revised Implementing Rules and Regulations of RA 9184
A9: allows Alternative Mode of Procurement subject to prior approval of the HOPE thru Annual
A10: Procurement Plan (APP) and only to promote economy and efficiency;
A12: WHEREAS, Section 50(c) allows Direct Contracting in cases where Procuring Entity intends to procure
A13: goods form an exclusive local manufacturer, supplier, distributor, or dealer for which no suitable
A14: substitute can be obtained at more advantageous terms to the GoP.
A16: WHEREAS, "Annex H" of the Consolidated Guidelines for Direct Contracting prescribed under
A17: Section V, Paragraph A.2.,upon submission of request and other supporting documents
A18: the BAC shall prepare the RFQ or pro-forma invoice together with the term and conditions of sale,
A19: and shall send the same to the identified direct supplier.
A20: WHEREAS, the BAC shall ensure that the supplier is technically, legally and financially capable
A21: to deliver the goods at the most advantageous price and contract for the Government
... A24: contract to the Supplier, Contractor or dealer.
A25: WHEREAS, Purchase Request No. | D25: =PR!E9 -> 2025-343 | E25: involves the procurement of
A26: =PR!B76 -> for BEACON 2025 "Building Empowered and Accountable Councils of Noble BSCians"
A27: with the Approved Budget of | D27: =PR!H75 -> 10450
A28: WHEREAS, the default mode of evaluation shall be on a lot basis which means that the
A29: determination of the single/lowest calculated and responsive bid (S/LCRB) is the total amount of offered
A30: unit price multiply by the required quantity;
A32: NOW THEREFORE, we, the members of the Bids and Awards Committee hereby RESOLVE to recommend to the HOPE to adopt Negotiated Mode of Procurement under Direct Contracting for the said transaction;
A33: RESOLVED FINALLY, at the Batanes State College, this
A34: Recommending Approval:
A37: RHOUPHELINE AYA A. CADIZ | C37: RANDALL G. CASTILLO | E37: EMILYN D. ALUETA
A38: BAC Member | C38: BAC Member | E38: BAC Member
A41: =PR!B80 -> ELEIN T. ESPERANZA | C41: FORTUNATO PHILIP A. CABUGAO | E41: DOREEN C. CASTILLO
A42: End-User/Provisional Member | C42: BAC Vice Chairperson | E42: BAC Chairperson
A47: BRYAN H. CIELO
A48: DELMA G. MALUPA-ABAD
A49: EDWIN F.MACABALLUG, Ph.D.
A50: LIEZL P. DELA CRUZ
A51: RODERICK Y. ABAD
A52: VILMA D. BACCAY
A53: ESTEBAN C. BADAJOS
A54: LEOBERT L. BANZALI
A55: MIAH DAPHNIE B. BUENAFE
A56: GLORIA N. CABIZON
A57: FORTUNATO PHILIP A. CABUGAO
A58: RICARDO Q. CABUGAO, JR.
... A103: EMILYN D. ALUETA

Sheet AResoSoSVP(Direct Contractin (2
A1: BATANES STATE COLLEGE
A2: Basco, Batanes
A4: Approval of BAC Resolution Recommending Alternative Mode of Procurement under Direct Contracting for Blank TOR Paper
B6: BAC Resolution No. | D6: =PR!B12 -> 2509-SS09-343
A8: WHEREAS, Rule XVI of the Revised Implementing Rules and Regulations of RA 9184
A9: allows Alternative Mode of Procurement subject to prior approval of the HOPE thru Annual
A10: Procurement Plan (APP) and only to promote economy and efficiency;
A12: WHEREAS, Section 50(c) allows Direct Contracting in cases where Procuring Entity intends to procure
A13: goods form an exclusive local manufacturer, supplier, distributor, or dealer for which no suitable
A14: substitute can be obtained at more advantageous terms to the GoP.
A16: WHEREAS, "Annex H" of the Consolidated Guidelines for Direct Contracting prescribed under
A17: Section V, Paragraph A.2.,upon submission of request and other supporting documents
A18: the BAC shall prepare the RFQ or pro-forma invoice together with the term and conditions of sale,
A19: and shall send the same to the identified direct supplier.
A20: WHEREAS, the BAC shall ensure that the supplier is technically, legally and financially capable
A21: to deliver the goods at the most advantageous price and contract for the Government
... A24: contract to the Supplier, Contractor or dealer.
A25: WHEREAS, Purchase Request No. | D25: =PR!E9 -> 2025-343 | E25: involves the procurement of
A26: =PR!B76 -> for BEACON 2025 "Building Empowered and Accountable Councils of Noble BSCians"
A27: with the Approved Budget of | D27: =PR!H75 -> 10450
A28: WHEREAS, the default mode of evaluation shall be on a lot basis which means that the
A29: determination of the single/lowest calculated and responsive bid (S/LCRB) is the total amount of offered
A30: unit price multiply by the required quantity;
A32: NOW THEREFORE, I, DR.DJOVI R. DURANTE, Director for Admin & Finance Services by virtue of
A33: the authority vested in me by the Board of Trustees of this Institution and after taking into consideration
A34: the merits and legal bases of the recommendation of the members of the Bids and Awards Committee (BAC)
A35: do hereby APPROVE the foregoing recommendation and adoption of Alternative Mode of Procurement
A36: under Direct Contracting;
A38: APPROVED FINALLY, at the Batanes State College, this | F38: ___________________
B41: DJOVI REGALA DURANTE,DPA
B42: SUC President I
A47: BRYAN H. CIELO
A48: DELMA G. MALUPA-ABAD
A49: EDWIN F.MACABALLUG, Ph.D.
A50: LIEZL P. DELA CRUZ
A51: RODERICK Y. ABAD
A52: VILMA D. BACCAY
A53: ESTEBAN C. BADAJOS
A54: LEOBERT L. BANZALI
A55: MIAH DAPHNIE B. BUENAFE
A56: GLORIA N. CABIZON
A57: FORTUNATO PHILIP A. CABUGAO
A58: RICARDO Q. CABUGAO, JR.
... A103: EMILYN D. ALUETA

Sheet Reso-Repeat Order
A2: BATANES STATE COLLEGE
A3: Basco, Batanes
A5: BAC Resolution Recommending Alternative Mode of Procurement under Small Value Procurement
B7: BAC Resolution No. | D7: =#REF! -> #REF!
A9: WHEREAS, Section 48 Rule XVI of the Revised Implementing Rules and Regulations of RA 9184 allows Alternative Mode of Procurement subject to prior approval of the HOPE thru Annual Procurement Plan (APP) and only to promote economy and efficiency;
A10: WHEREAS, Section 53.9 allows Small Value Procurement provided that the procurement does not fall under shopping in Section 52 of this IRR and the amount involved does not exceed the thresholds prescribed in Annex "H" of this IRR;
A11: WHEREAS, Rule XVI, Section 51., on Repeat Order states this when provided for in the APP, is a method of procurement of goods from the previous winning bidder, whenever there is a need to replenish goods procured under a contract previously awarded through competitive bidding. | H11: c
A12: WHEREAS, Rule XVI, Section 51.,a) A repeat order provides that unit prices of the repeat order must be the same as or lower than those in the original contract: provided, that such prices are still the most advantegous to the GoP after price verification: b) thet the repeat order will not result in splitting of contracts, requisitions, or purchase orders, as provided for in Section 54.1 of this IRR;
A13: WHEREAS, Purchase Request No. | D13: =#REF! -> #REF! | E13: involves the procurement of
A14: =#REF! -> #REF!
A15: =#REF! -> #REF! | D15: =#REF! -> #REF!
A16: WHEREAS, the default mode of evaluation shall be on a lot basis which means that the determination of the single/lowest calculated and responsive bid (S/LCRB) is the total amount of offered unit price multiply by the required quantity;
A18: NOW THEREFORE, we, the members of the Bids and Awards Committee hereby RESOLVE as it is hereby RESOLVED to recommend to the College President to adopt Alternative Mode of Procurement under Small Value Procurement for the said transaction;
A20: RESOLVED FINALLY, at the Batanes State College, this
A21: Recommending Approval:
A24: RHOUPHELINE AYA A. CADIZ | C24: RANDALL G. CASTILLO | E24: EMILYN D. ALUETA
A25: BAC Member | C25: BAC Member | E25: BAC Member
A28: =PR!B80 -> ELEIN T. ESPERANZA | C28: FORTUNATO PHILIP A. CABUGAO | E28: DOREEN C. CASTILLO
A29: End-User/Provisional Member | C29: BAC Vice Chairperson | E29: BAC Chairperson
A30: BRYAN H. CIELO
A31: DELMA G. MALUPA-ABAD
A32: EDWIN F.MACABALLUG, Ph.D.
A33: LIEZL P. DELA CRUZ
A34: RODERICK Y. ABAD
A35: VILMA D. BACCAY
A36: ESTEBAN C. BADAJOS
A37: LEOBERT L. BANZALI
A38: MIAH DAPHNIE B. BUENAFE
A39: GLORIA N. CABIZON
A40: FORTUNATO PHILIP A. CABUGAO
A41: RICARDO Q. CABUGAO, JR.
... A83: LEONARDO CABRERA

Sheet AReso-Repeat Order
A1: BATANES STATE COLLEGE
A2: Basco, Batanes
A4: Approval of BAC Resolution Recommending Alternative Mode of Procurement under Small Value Procurement
B6: BAC Resolution No. | D6: =PR!B12 -> 2509-SS09-343
A8: WHEREAS, Section 48 Rule XVI of the Revised Implementing Rules and Regulations of RA 9184 allows Alternative Mode of Procurement subject to prior approval of the HOPE thru Annual Procurement Plan (APP) and only to promote economy and efficiency;
A9: WHEREAS, Section 53.9 allows Small Value Procurement provided that the procurement does not fall under shopping in Section 52 of this IRR and the amount involved does not exceed the thresholds prescribed in Annex "H" of this IRR;
A10: WHEREAS, Appendix 18, Section 3.e on the Guidelines for Shopping and Small Value Procurement provides an Abstract of Quotations shall be prepared setting forth the names of those who responded to the RFQ's right after the deadline for submission except for shopping under Section 52.1(b), where at least three (3) price quotations (RFQ) must be obtained;
A11: WHEREAS, Annex "H" of the Consolidated Guidelines for the Alternative Methods of Procurement prescribed under Section V, Paragraph D.8.b.ii that the BAC shall prepare and send the RFQs/RFPs to at least three (3) suppliers, contractors or consultants of known qualifications where receipt of at least one (1) quotations is sufficient to proceed with the evaluation thererof;
A12: WHEREAS, Purchase Request No. | D12: =PR!E9 -> 2025-343 | E12: involves the procurement of
A13: Presidential Medallion | H13: Items:
A14: with the Approved Budget of | D14: =PR!H75 -> 10450
A15: WHEREAS, the default mode of evaluation shall be on a lot basis which means that the determination of the single/lowest calculated and responsive bid (S/LCRB) is the total amount of offered unit price multiply by the required quantity;
A16: NOW THEREFORE, I,DR.DJOVI R. DURANTE, Head of the Procuring Entity (HOPE) by virtue of the authority vested in me by the Board of Trustees of this Institution and after taking into consideration the merits and legal bases of the recommendation of the members of the Bids and Awards Committee (BAC) do hereby APPROVE the foregoing recommendation and adoption of Alternative Mode of Procurement under Small Value Procurement;
A18: APPROVED FINALLY, at the Batanes State College, this | F18: ___________________
B24: DJOVI REGALA DURANTE,DPA
B25: SUC President I
A30: BRYAN H. CIELO
A31: DELMA G. MALUPA-ABAD
A32: EDWIN F.MACABALLUG, Ph.D.
A33: LIEZL P. DELA CRUZ
A34: RODERICK Y. ABAD
A35: VILMA D. BACCAY
A36: ESTEBAN C. BADAJOS
A37: LEOBERT L. BANZALI
A38: MIAH DAPHNIE B. BUENAFE
A39: GLORIA N. CABIZON
A40: FORTUNATO PHILIP A. CABUGAO
A41: RICARDO Q. CABUGAO, JR.
... A86: EMILYN D. ALUETA

Sheet AckReceipt (2)
A1: Acknowledgement for Request for Quotation
A2: RIS# | B2: =PR!B12 -> 2509-SS09-343
A3: No. | B3: Supplier | F3: Received by: | G3: Date & Time:
B4: JPM Gen. Mdse. & Hardware
B5: Thine-line Trading
B6: J-Tech Trading & Services
B7: MDAC Trading & Compuserve
B8: FVA Gen Mdse & Construction Supply
B10: GDP Trading
B11: EA Amboy Gen Mdse
B12: L & R's Hontomin Gen Mdse
B13: Davocol's Gen. Mdse.
B14: RCJ Hardware & Gen Mdse
B15: Fitero's Gen Mdse & Electronic Supply
B16: Lar & San's Store
... B18: Wilmerson Gen Mdse
B19: FMG Trading & Construction Supply | C19: q
B20: MG Hubalde Gen Mdse
B21: Basco Cable TV Services, Inc.
B22: Berlen's Store
B23: Melad's Gen. Mdse
B24: R. A. Electronics
B25: RJ General Merchandise
B26: Batanes Multi-Purpose Cooperative, Inc.
B27: Romy & Ava's Store
B28: J-nell's Gen Mdse
B29: Impression Digital Printing Solutions
B30: Golden Press
B31: Tawsen's Agri-Venture & Souvenirs
... B60: Sophia Marie Store
A61: 1 | B61: FVA Trading
A62: 2 | B62: FMG Trading & Construction Supply
A63: 3 | B63: E.A. Amboy General Merchandise
A64: 4 | B64: GDP Trading
A65: 5 | B65: Prins Marie Hardware | J65: zz
A66: 6
A67: 7
A68: NOTE: | B68: 1. MODE OF PRICE EVALUATION SHALL BE ON A LOT BASIS, OTHERWISE PER ITEMS EVALUATION SHALL BE USED IF THERE WILL BE LACKING ITEMS IN ALL RFQ'S AND THE END-USER AGREED, . (Clause 15.2, Section II, Instructions to Bidders of the Philippine Bidding Documents for goods and infrastructure projects)
B69: 2. DELIVERY PERIOD: Thirty (30) calendar days.
B70: 3. WARRANTY SHALL BE FOR A PERIOD OF SIX (6) MONTHS FOR SUPPLIES AND MATERIALS, ONE (1) YEAR FOR EQUIPMENT, FROM THE DATE OF ACCEPTANCE BY THE PROCURING ENTITY.
B71: 4. THE APPROVED BUDGET CEILING FOR THIS PROCUREMENT IS PHP (GPPB Resolution no. 09-2009)
B72: =PR!H75 -> 10450
B73: 5. PRICE VALIDITY SHALL BE OR THE PERIOD OF 30 CALENDAR DAYS.
B74: 6. BIDDERS SHALL SUBMIT ORIGINAL BROCHURES SHOWING SPECIFICATIONS OF THE PRODUCT BEING OFFERED IF APPLICABLE.
A75: In compliance with GPPB Resolution No. 09-2009
B77: Retrieval of Request for Quotation
A79: No. | B79: Supplier | F79: Released by: | G79: Date & Time: | N79: k
A80: 1 | B80: FVA Trading
A81: 2 | B81: FMG Trading & Construction Supply
A82: 3 | B82: E.A. Amboy General Merchandise
A83: 4 | B83: GDP Trading
A84: 5 | B84: Prins Marie Hardware
A85: 6
A86: 7
